Workbook
Name IQ_CH: 110000
Name IQ_CQ: 5000
Name IQ_CY: 10000
Name IQ_DAILY: 500000
Name IQ_FH: 100000
Name IQ_FQ: 500
Name IQ_FY: 1000
Name IQ_LTM: 2000
Name IQ_MONTH: 15000
Name IQ_NTM: 6000
Name IQ_WEEK: 50000
Name IQ_YTD: 3000

Sheet Summary Annual Financials
A2: x | B2: Historical & Projected Annual Financial Summary | O2: x
B4: Annual Historical & Forecasted P&L
C6: Historical FYE | G6: Projected FYE
C7: 42735 | D7: =EOMONTH(C7,12) -> 43100 | E7: =EOMONTH(D7,12) -> 43465 | F7: =EOMONTH(E7,12) -> 43830 | G7: =EOMONTH(F7,12) -> 44196 | H7: =EOMONTH(G7,12) -> 44561 | I7: =EOMONTH(H7,12) -> 44926 | J7: =EOMONTH(I7,12) -> 45291 | K7: =EOMONTH(J7,12) -> 45657 | M7: ="'16A - '19A" -> '16A - '19A | N7: ="'20E - '24E" -> '20E - '24E
C8: =YEAR(C7) -> 2016 | D8: =YEAR(D7) -> 2017 | E8: =YEAR(E7) -> 2018 | F8: =YEAR(F7) -> 2019 | G8: =YEAR(G7) -> 2020 | H8: =YEAR(H7) -> 2021 | I8: =YEAR(I7) -> 2022 | J8: =YEAR(J7) -> 2023 | K8: =YEAR(K7) -> 2024 | M8: CAGR | N8: CAGR
B10: Subscription ACV | C10: ='Operating Model'!D150 -> 10583 | D10: ='Operating Model'!E150 -> 13462 | E10: ='Operating Model'!F150 -> 13698 | F10: ='Operating Model'!G150 -> 14334.923 | G10: ='Operating Model'!H150 -> 25086.356 | H10: ='Operating Model'!I150 -> 44780.935 | I10: ='Operating Model'!J150 -> 66322.846 | J10: ='Operating Model'!K150 -> 98798.763 | K10: ='Operating Model'!L150 -> 137301.22 | M10: =IFERROR(RATE($F$8-$C$8,0,-$C10,$F10),"N/A") -> 0.1064425 | N10: =IFERROR(RATE($K$8-$G$8,0,-$G10,$K10),"N/A") -> 0.52953425
B11: (+) Professional Services ACV | C11: ='Operating Model'!D151 -> 304 | D11: ='Operating Model'!E151 -> 1197 | E11: ='Operating Model'!F151 -> 2481 | F11: ='Operating Model'!G151 -> 10615.65 | G11: ='Operating Model'!H151 -> 16931.044 | H11: ='Operating Model'!I151 -> 26725 | I11: ='Operating Model'!J151 -> 35636.662 | J11: ='Operating Model'!K151 -> 46493.536 | K11: ='Operating Model'!L151 -> 58843.381 | M11: =IFERROR(RATE($F$8-$C$8,0,-$C11,$F11),"N/A") -> 2.2685691 | N11: =IFERROR(RATE($K$8-$G$8,0,-$G11,$K11),"N/A") -> 0.36537979
B12: (+) Other ACV | C12: ='Operating Model'!D152 -> 0 | D12: ='Operating Model'!E152 -> 147.865 | E12: ='Operating Model'!F152 -> 337.7 | F12: ='Operating Model'!G152 -> 0.5 | G12: ='Operating Model'!H152 -> 0 | H12: ='Operating Model'!I152 -> 0 | I12: ='Operating Model'!J152 -> 0 | J12: ='Operating Model'!K152 -> 0 | K12: ='Operating Model'!L152 -> 0 | M12: =IFERROR(RATE($F$8-$C$8,0,-$C12,$F12),"N/A") -> N/A | N12: =IFERROR(RATE($K$8-$G$8,0,-$G12,$K12),"N/A") -> N/A
B13: Total ACV (Bookings) | C13: =SUM(C10:C12) -> 10887 | D13: =SUM(D10:D12) -> 14806.865 | E13: =SUM(E10:E12) -> 16516.7 | F13: =SUM(F10:F12) -> 24951.073 | G13: =SUM(G10:G12) -> 42017.4 | H13: =SUM(H10:H12) -> 71505.935 | I13: =SUM(I10:I12) -> 101959.51 | J13: =SUM(J10:J12) -> 145292.3 | K13: =SUM(K10:K12) -> 196144.6 | M13: =IFERROR(RATE($F$8-$C$8,0,-$C13,$F13),"N/A") -> 0.31843988 | N13: =IFERROR(RATE($K$8-$G$8,0,-$G13,$K13),"N/A") -> 0.46989664
B14: Y-O-Y Growth % | D14: =D13/C13-1 -> 0.36005006 | E14: =E13/D13-1 -> 0.11547583 | F14: =F13/E13-1 -> 0.51065724 | G14: =G13/F13-1 -> 0.68399174 | H14: =H13/G13-1 -> 0.70181722 | I14: =I13/H13-1 -> 0.42588875 | J14: =J13/I13-1 -> 0.425 | K14: =K13/J13-1 -> 0.35
B16: Subscription Revenue | C16: ='Operating Model'!D160 -> 6452.948 | D16: ='Operating Model'!E160 -> 9384.025 | E16: ='Operating Model'!F160 -> 11241.66 | F16: ='Operating Model'!G160 -> 11937.494 | G16: ='Operating Model'!H160 -> 16914.655 | H16: ='Operating Model'!I160 -> 24733 | I16: ='Operating Model'!J160 -> 48670.188 | J16: ='Operating Model'!K160 -> 72718.102 | K16: ='Operating Model'!L160 -> 104964.84 | M16: =IFERROR(RATE($F$8-$C$8,0,-$C16,$F16),"N/A") -> 0.22758525 | N16: =IFERROR(RATE($K$8-$G$8,0,-$G16,$K16),"N/A") -> 0.57832043
B17: (+) Professional Services Revenue | C17: ='Operating Model'!D161 -> 3852.46 | D17: ='Operating Model'!E161 -> 1107.899 | E17: ='Operating Model'!F161 -> 1685.792 | F17: ='Operating Model'!G161 -> 4044.0992 | G17: ='Operating Model'!H161 -> 12492.517 | H17: ='Operating Model'!I161 -> 19325 | I17: ='Operating Model'!J161 -> 27638.311 | J17: ='Operating Model'!K161 -> 35993.517 | K17: ='Operating Model'!L161 -> 47694.205 | M17: =IFERROR(RATE($F$8-$C$8,0,-$C17,$F17),"N/A") -> 0.016313959 | N17: =IFERROR(RATE($K$8-$G$8,0,-$G17,$K17),"N/A") -> 0.39782859
B18: (+) Other Revenue | C18: ='Operating Model'!D162 -> 0 | D18: ='Operating Model'!E162 -> 0 | E18: ='Operating Model'!F162 -> 0 | F18: ='Operating Model'!G162 -> 0 | G18: ='Operating Model'!H162 -> 0 | H18: ='Operating Model'!I162 -> 0 | I18: ='Operating Model'!J162 -> 0 | J18: ='Operating Model'!K162 -> 0 | K18: ='Operating Model'!L162 -> 0 | M18: =IFERROR(RATE($F$8-$C$8,0,-$C18,$F18),"N/A") -> N/A | N18: =IFERROR(RATE($K$8-$G$8,0,-$G18,$K18),"N/A") -> N/A
B19: Total Revenue | C19: =SUM(C16:C18) -> 10305.408 | D19: =SUM(D16:D18) -> 10491.924 | E19: =SUM(E16:E18) -> 12927.452 | F19: =SUM(F16:F18) -> 15981.593 | G19: =SUM(G16:G18) -> 29407.172 | H19: =SUM(H16:H18) -> 44058 | I19: =SUM(I16:I18) -> 76308.499 | J19: =SUM(J16:J18) -> 108711.62 | K19: =SUM(K16:K18) -> 152659.05 | M19: =IFERROR(RATE($F$8-$C$8,0,-$C19,$F19),"N/A") -> 0.15749278 | N19: =IFERROR(RATE($K$8-$G$8,0,-$G19,$K19),"N/A") -> 0.5094451
B20: Y-O-Y Growth % | D20: =D19/C19-1 -> 0.018098847 | E20: =E19/D19-1 -> 0.23213359 | F20: =F19/E19-1 -> 0.23625235 | G20: =G19/F19-1 -> 0.84006515 | H20: =H19/G19-1 -> 0.49820595 | I20: =I19/H19-1 -> 0.73200098 | J20: =J19/I19-1 -> 0.42463317 | K20: =K19/J19-1 -> 0.40425698
B21: ARR * | C21: ='Operating Model'!D100 -> 5291.5 | D21: ='Operating Model'!E100 -> 9367 | E21: ='Operating Model'!F100 -> 11661 | F21: ='Operating Model'!G100 -> 14339 | G21: ='Operating Model'!H100 -> 19355 | H21: ='Operating Model'!I100 -> 34271 | I21: ='Operating Model'!J100 -> 55116 | J21: ='Operating Model'!K100 -> 82992 | K21: ='Operating Model'!L100 -> 116931
B24: (–) Cost of Goods Sold (Subscription) | C24: ='Operating Model'!D166 -> 0 | D24: ='Operating Model'!E166 -> -2926 | E24: ='Operating Model'!F166 -> -4706.26 | F24: ='Operating Model'!G166 -> -3838.9536 | G24: ='Operating Model'!H166 -> -7433.3234 | H24: ='Operating Model'!I166 -> -11135.954 | I24: ='Operating Model'!J166 -> -15936.922 | J24: ='Operating Model'!K166 -> -20501.264 | K24: ='Operating Model'!L166 -> -26953.975
B25: (–) Cost of Goods Sold (Professional Services) | C25: ='Operating Model'!D167 -> 0 | D25: ='Operating Model'!E167 -> -1323.9 | E25: ='Operating Model'!F167 -> -1822.74 | F25: ='Operating Model'!G167 -> -2480.7139 | G25: ='Operating Model'!H167 -> -3195.3975 | H25: ='Operating Model'!I167 -> -4144.6384 | I25: ='Operating Model'!J167 -> -8681.0692 | J25: ='Operating Model'!K167 -> -12034.097 | K25: ='Operating Model'!L167 -> -16539.377
B26: (+/–) Other Adjustments | C26: ='Operating Model'!D168 -> -3710.1656 | D26: ='Operating Model'!E168 -> 303.396 | E26: ='Operating Model'!F168 -> 348.978 | F26: ='Operating Model'!G168 -> 0.01386 | G26: ='Operating Model'!H168 -> -108 | H26: ='Operating Model'!I168 -> 0.01386 | I26: ='Operating Model'!J168 -> 0.01386 | J26: ='Operating Model'!K168 -> 0.01386 | K26: ='Operating Model'!L168 -> 0.01386
B27: Total Gross Profit | C27: =SUM(C19,C24:C26) -> 6595.2424 | D27: =SUM(D19,D24:D26) -> 6545.42 | E27: =SUM(E19,E24:E26) -> 6747.43 | F27: =SUM(F19,F24:F26) -> 9661.9392 | G27: =SUM(G19,G24:G26) -> 18670.451 | H27: =SUM(H19,H24:H26) -> 28777.421 | I27: =SUM(I19,I24:I26) -> 51690.522 | J27: =SUM(J19,J24:J26) -> 76176.271 | K27: =SUM(K19,K24:K26) -> 109165.71 | M27: =IFERROR(RATE($F$8-$C$8,0,-$C27,$F27),"N/A") -> 0.13573719 | N27: =IFERROR(RATE($K$8-$G$8,0,-$G27,$K27),"N/A") -> 0.55500883
B28: Gross Margin % | C28: =C27/C19 -> 0.63997878 | D28: =D27/D19 -> 0.62385317 | E28: =E27/E19 -> 0.52194586 | F28: =F27/F19 -> 0.60456672 | G28: =G27/G19 -> 0.63489448 | H28: =H27/H19 -> 0.6531713 | I28: =I27/I19 -> 0.67738879 | J28: =J27/J19 -> 0.70071876 | K28: =K27/K19 -> 0.71509492
B30: (–) OpEx: Personnel Expenses | C30: ='Operating Model'!D172 -> -6340.5862 | D30: ='Operating Model'!E172 -> -11467.276 | E30: ='Operating Model'!F172 -> -16185.352 | F30: ='Operating Model'!G172 -> -25229.878 | G30: ='Operating Model'!H172 -> -28327.955 | H30: ='Operating Model'!I172 -> -32011.486 | I30: ='Operating Model'!J172 -> -40312.83 | J30: ='Operating Model'!K172 -> -50972.619 | K30: ='Operating Model'!L172 -> -63256.732
B31: (–) OpEx: Non-Staff Expenses | C31: ='Operating Model'!D173 -> -10059.776 | D31: ='Operating Model'!E173 -> -5057.2005 | E31: ='Operating Model'!F173 -> -7954.0113 | F31: ='Operating Model'!G173 -> -9387.2908 | G31: ='Operating Model'!H173 -> -10414.902 | H31: ='Operating Model'!I173 -> -12670.973 | I31: ='Operating Model'!J173 -> -14650.681 | J31: ='Operating Model'!K173 -> -16892.155 | K31: ='Operating Model'!L173 -> -19324.917
B32: Adjusted EBITDA | C32: =SUM(C27,C30:C31) -> -9805.1193 | D32: =SUM(D27,D30:D31) -> -9979.0561 | E32: =SUM(E27,E30:E31) -> -17391.933 | F32: =SUM(F27,F30:F31) -> -24955.23 | G32: =SUM(G27,G30:G31) -> -20072.406 | H32: =SUM(H27,H30:H31) -> -15905.038 | I32: =SUM(I27,I30:I31) -> -3272.99 | J32: =SUM(J27,J30:J31) -> 8311.497 | K32: =SUM(K27,K30:K31) -> 26584.063
B33: EBITDA Margin % | C33: ='Operating Model'!D175 -> NM | D33: ='Operating Model'!E175 -> NM | E33: ='Operating Model'!F175 -> NM | F33: ='Operating Model'!G175 -> NM | G33: ='Operating Model'!H175 -> NM | H33: ='Operating Model'!I175 -> NM | I33: ='Operating Model'!J175 -> NM | J33: ='Operating Model'!K175 -> 0.076454542 | K33: ='Operating Model'!L175 -> 0.17414011
B35: Note: * ARR expressed as average quarterly MRR annualized
B37: Annual Cash Flow Schedule
C39: Historical FYE | G39: Projected FYE
C40: 42735 | D40: =EOMONTH(C40,12) -> 43100 | E40: =EOMONTH(D40,12) -> 43465 | F40: =EOMONTH(E40,12) -> 43830 | G40: =EOMONTH(F40,12) -> 44196 | H40: =EOMONTH(G40,12) -> 44561 | I40: =EOMONTH(H40,12) -> 44926 | J40: =EOMONTH(I40,12) -> 45291 | K40: =EOMONTH(J40,12) -> 45657
C41: =YEAR(C40) -> 2016 | D41: =YEAR(D40) -> 2017 | E41: =YEAR(E40) -> 2018 | F41: =YEAR(F40) -> 2019 | G41: =YEAR(G40) -> 2020 | H41: =YEAR(H40) -> 2021 | I41: =YEAR(I40) -> 2022 | J41: =YEAR(J40) -> 2023 | K41: =YEAR(K40) -> 2024
B43: Adjusted EBITDA | C43: ='Operating Model'!D183 -> -9805.1193 | D43: ='Operating Model'!E183 -> -9979.0561 | E43: ='Operating Model'!F183 -> -17391.933 | F43: ='Operating Model'!G183 -> -24955.23 | G43: ='Operating Model'!H183 -> -20072.406 | H43: ='Operating Model'!I183 -> -15905.038 | I43: ='Operating Model'!J183 -> -3272.99 | J43: ='Operating Model'!K183 -> 8311.497 | K43: ='Operating Model'!L183 -> 26584.063
B44: (–) Depreciation & Amortization | C44: ='Operating Model'!D184 -> -22.461 | D44: ='Operating Model'!E184 -> -141.629 | E44: ='Operating Model'!F184 -> -154.033 | F44: ='Operating Model'!G184 -> -217.28181 | G44: ='Operating Model'!H184 -> -279.55732 | H44: ='Operating Model'!I184 -> -279.54991 | I44: ='Operating Model'!J184 -> -279.5496 | J44: ='Operating Model'!K184 -> -279.5496 | K44: ='Operating Model'!L184 -> -279.5496
B45: (–) Employee Non-Cash Equity Expense | C45: ='Operating Model'!D185 -> -154.63 | D45: ='Operating Model'!E185 -> -251.855 | E45: ='Operating Model'!F185 -> -699.858 | F45: ='Operating Model'!G185 -> -1145 | G45: ='Operating Model'!H185 -> -3000 | H45: ='Operating Model'!I185 -> -3000 | I45: ='Operating Model'!J185 -> -6000 | J45: ='Operating Model'!K185 -> -6000 | K45: ='Operating Model'!L185 -> -9000
B46: (+/–) Other Non-Cash OpEx Adjustments, Net | C46: ='Operating Model'!D186 -> 6340.5853 | D46: ='Operating Model'!E186 -> 59.21806 | E46: ='Operating Model'!F186 -> -0.00256 | F46: ='Operating Model'!G186 -> -375.54141 | G46: ='Operating Model'!H186 -> -0.0032634868 | H46: ='Operating Model'!I186 -> 0 | I46: ='Operating Model'!J186 -> 0 | J46: ='Operating Model'!K186 -> 0 | K46: ='Operating Model'!L186 -> 0
B47: Operating Income (EBIT) | C47: =SUM(C43:C46) -> -3641.625 | D47: =SUM(D43:D46) -> -10313.322 | E47: =SUM(E43:E46) -> -18245.827 | F47: =SUM(F43:F46) -> -26693.053 | G47: =SUM(G43:G46) -> -23351.967 | H47: =SUM(H43:H46) -> -19184.588 | I47: =SUM(I43:I46) -> -9552.5396 | J47: =SUM(J43:J46) -> 2031.9474 | K47: =SUM(K43:K46) -> 17304.514
B48: (–) Other Expense, Net | C48: ='Operating Model'!D188 -> -511.933 | D48: ='Operating Model'!E188 -> -651.48598 | E48: ='Operating Model'!F188 -> -61.85321 | F48: ='Operating Model'!G188 -> -183.67753 | G48: ='Operating Model'!H188 -> -589 | H48: ='Operating Model'!I188 -> 0 | I48: ='Operating Model'!J188 -> 0 | J48: ='Operating Model'!K188 -> 0 | K48: ='Operating Model'!L188 -> 0
B49: (+/–) Interest Income (Expense), Net | C49: ='Operating Model'!D189 -> 0 | D49: ='Operating Model'!E189 -> 305.48198 | E49: ='Operating Model'!F189 -> 51.99022 | F49: ='Operating Model'!G189 -> 705.26704 | G49: ='Operating Model'!H189 -> 64.720266 | H49: ='Operating Model'!I189 -> 745.92894 | I49: ='Operating Model'!J189 -> 729.13576 | J49: ='Operating Model'!K189 -> 731.28733 | K49: ='Operating Model'!L189 -> 1006.0857
B50: (+/–) Income Taxes | C50: ='Operating Model'!D190 -> 0 | D50: ='Operating Model'!E190 -> 0 | E50: ='Operating Model'!F190 -> -19.8 | F50: ='Operating Model'!G190 -> 0.51824 | G50: ='Operating Model'!H190 -> 0 | H50: ='Operating Model'!I190 -> 0 | I50: ='Operating Model'!J190 -> 0 | J50: ='Operating Model'!K190 -> 0 | K50: ='Operating Model'!L190 -> 0
B51: Net Income | C51: =SUM(C47:C50) -> -4153.558 | D51: =SUM(D47:D50) -> -10659.326 | E51: =SUM(E47:E50) -> -18275.49 | F51: =SUM(F47:F50) -> -26170.945 | G51: =SUM(G47:G50) -> -23876.246 | H51: =SUM(H47:H50) -> -18438.659 | I51: =SUM(I47:I50) -> -8823.4039 | J51: =SUM(J47:J50) -> 2763.2347 | K51: =SUM(K47:K50) -> 18310.599
B52: (+) Depreciation & Amortization | C52: ='Operating Model'!D192 -> 22.461 | D52: ='Operating Model'!E192 -> 141.629 | E52: ='Operating Model'!F192 -> 154.033 | F52: ='Operating Model'!G192 -> 217.28181 | G52: ='Operating Model'!H192 -> 279.55732 | H52: ='Operating Model'!I192 -> 279.54991 | I52: ='Operating Model'!J192 -> 279.5496 | J52: ='Operating Model'!K192 -> 279.5496 | K52: ='Operating Model'!L192 -> 279.5496
B53: (+/–) Changes in Net Working Capital | C53: ='Operating Model'!D193 -> 1111.91 | D53: ='Operating Model'!E193 -> -396.7918 | E53: ='Operating Model'!F193 -> 1930.0771 | F53: ='Operating Model'!G193 -> 3826.4537 | G53: ='Operating Model'!H193 -> -697.88104 | H53: ='Operating Model'!I193 -> 7545.1666 | I53: ='Operating Model'!J193 -> 7311.5009 | J53: ='Operating Model'!K193 -> 6230.773 | K53: ='Operating Model'!L193 -> 9344.2352
B54: Cash Flow from Operating Activities | C54: =SUM(C51:C53) -> -3019.187 | D54: =SUM(D51:D53) -> -10914.489 | E54: =SUM(E51:E53) -> -16191.38 | F54: =SUM(F51:F53) -> -22127.21 | G54: =SUM(G51:G53) -> -24294.57 | H54: =SUM(H51:H53) -> -10613.942 | I54: =SUM(I51:I53) -> -1232.3534 | J54: =SUM(J51:J53) -> 9273.5573 | K54: =SUM(K51:K53) -> 27934.384
B55: (–) Capex | C55: ='Operating Model'!D195 -> -94.977 | D55: ='Operating Model'!E195 -> -156.6293 | E55: ='Operating Model'!F195 -> -208.536 | F55: ='Operating Model'!G195 -> -604.06569 | G55: ='Operating Model'!H195 -> -1637.2442 | H55: ='Operating Model'!I195 -> -595.2 | I55: ='Operating Model'!J195 -> -2000 | J55: ='Operating Model'!K195 -> -3000 | K55: ='Operating Model'!L195 -> -3000
B56: (+/–) FX effect on Cash | C56: ='Operating Model'!D196 -> 0 | D56: ='Operating Model'!E196 -> -307.42596 | E56: ='Operating Model'!F196 -> -40.77194 | F56: ='Operating Model'!G196 -> -168.56195 | G56: ='Operating Model'!H196 -> 0 | H56: ='Operating Model'!I196 -> 0 | I56: ='Operating Model'!J196 -> 0 | J56: ='Operating Model'!K196 -> 0 | K56: ='Operating Model'!L196 -> 0
B57: Net Cash Burn | C57: =SUM(C54:C56) -> -3114.164 | D57: =SUM(D54:D56) -> -11378.544 | E57: =SUM(E54:E56) -> -16440.688 | F57: =SUM(F54:F56) -> -22899.838 | G57: =SUM(G54:G56) -> -25931.814 | H57: =SUM(H54:H56) -> -11209.142 | I57: =SUM(I54:I56) -> -3232.3534 | J57: =SUM(J54:J56) -> 6273.5573 | K57: =SUM(K54:K56) -> 24934.384
B59: Beginning Cash Balance | E59: ='Operating Model'!F199 -> 4788.6979 | F59: =E62 -> 41131.647 | G59: =F62 -> 24379.336 | H59: =G62 -> 8947.5219 | I59: =H62 -> 40238.38 | J59: =I62 -> 37006.026 | K59: =J62 -> 43279.583
B60: (+/–) Net Cash Burn | E60: ='Operating Model'!F200 -> -16440.688 | F60: ='Operating Model'!G200 -> -22899.838 | G60: ='Operating Model'!H200 -> -25931.814 | H60: ='Operating Model'!I200 -> -11209.142 | I60: ='Operating Model'!J200 -> -3232.3534 | J60: ='Operating Model'!K200 -> 6273.5573 | K60: ='Operating Model'!L200 -> 24934.384
B61: (+) Cash Infusion from Financing Activities (Debt & Equity) | E61: ='Operating Model'!F201 -> 52783.637 | F61: ='Operating Model'!G201 -> 6147.5267 | G61: ='Operating Model'!H201 -> 10500 | H61: ='Operating Model'!I201 -> 42500 | I61: ='Operating Model'!J201 -> 0 | J61: ='Operating Model'!K201 -> 0 | K61: ='Operating Model'!L201 -> 0
B62: Ending Cash Balance | E62: =SUM(E59:E61) -> 41131.647 | F62: =SUM(F59:F61) -> 24379.336 | G62: =SUM(G59:G61) -> 8947.5219 | H62: =SUM(H59:H61) -> 40238.38 | I62: =SUM(I59:I61) -> 37006.026 | J62: =SUM(J59:J61) -> 43279.583 | K62: =SUM(K59:K61) -> 68213.968
B64: Key Financial & Operational Metrics
C66: Historical FYE | G66: Projected FYE
C67: 42735 | D67: =EOMONTH(C67,12) -> 43100 | E67: =EOMONTH(D67,12) -> 43465 | F67: =EOMONTH(E67,12) -> 43830 | G67: =EOMONTH(F67,12) -> 44196 | H67: =EOMONTH(G67,12) -> 44561 | I67: =EOMONTH(H67,12) -> 44926 | J67: =EOMONTH(I67,12) -> 45291 | K67: =EOMONTH(J67,12) -> 45657 | M67: ="'16A - '19A" -> '16A - '19A | N67: ="'20E - '24E" -> '20E - '24E
C68: =YEAR(C67) -> 2016 | D68: =YEAR(D67) -> 2017 | E68: =YEAR(E67) -> 2018 | F68: =YEAR(F67) -> 2019 | G68: =YEAR(G67) -> 2020 | H68: =YEAR(H67) -> 2021 | I68: =YEAR(I67) -> 2022 | J68: =YEAR(J67) -> 2023 | K68: =YEAR(K67) -> 2024 | M68: CAGR | N68: CAGR
B70: Total Clients | C70: ='Operating Model'!D68 -> 6 | D70: ='Operating Model'!E68 -> 8 | E70: ='Operating Model'!F68 -> 8 | F70: ='Operating Model'!G68 -> 13 | G70: ='Operating Model'!H68 -> 26 | H70: ='Operating Model'!I68 -> 49 | I70: ='Operating Model'!J68 -> 73 | J70: ='Operating Model'!K68 -> 96 | K70: ='Operating Model'!L68 -> 111 | M70: =IFERROR(RATE($F$68-$C$68,0,-$C70,$F70),"N/A") -> 0.29398935 | N70: =IFERROR(RATE($K$68-$G$68,0,-$G70,$K70),"N/A") -> 0.43743233
B71: Total ARR (Subscription ACV) Clients | C71: ='Operating Model'!D70 -> 4 | D71: ='Operating Model'!E70 -> 6 | E71: ='Operating Model'!F70 -> 7 | F71: ='Operating Model'!G70 -> 11 | G71: ='Operating Model'!H70 -> 21 | H71: ='Operating Model'!I70 -> 40 | I71: ='Operating Model'!J70 -> 59 | J71: ='Operating Model'!K70 -> 77 | K71: ='Operating Model'!L70 -> 89 | M71: =IFERROR(RATE($F$68-$C$68,0,-$C71,$F71),"N/A") -> 0.40101967 | N71: =IFERROR(RATE($K$68-$G$68,0,-$G71,$K71),"N/A") -> 0.43480433
B72: Recurring Clients as % of Total | C72: =C71/C70 -> 0.66666667 | D72: =D71/D70 -> 0.75 | E72: =E71/E70 -> 0.875 | F72: =F71/F70 -> 0.84615385 | G72: =G71/G70 -> 0.80769231 | H72: =H71/H70 -> 0.81632653 | I72: =I71/I70 -> 0.80821918 | J72: =J71/J70 -> 0.80208333 | K72: =K71/K70 -> 0.8018018
B74: FTEs | C74: ='Operating Model'!D136 -> 52 | D74: ='Operating Model'!E136 -> 78 | E74: ='Operating Model'!F136 -> 124 | F74: ='Operating Model'!G136 -> 146 | G74: ='Operating Model'!H136 -> 163 | H74: ='Operating Model'!I136 -> 207 | I74: ='Operating Model'!J136 -> 264 | J74: ='Operating Model'!K136 -> 328 | K74: ='Operating Model'!L136 -> 398 | M74: =IFERROR(RATE($F$68-$C$68,0,-$C74,$F74),"N/A") -> 0.41074928 | N74: =IFERROR(RATE($K$68-$G$68,0,-$G74,$K74),"N/A") -> 0.25003988
B76: ACV Per Client | C76: =C13/C70 -> 1814.5 | D76: =D13/D70 -> 1850.8581 | E76: =E13/E70 -> 2064.5875 | F76: =F13/F70 -> 1919.3133 | G76: =G13/G70 -> 1616.0538 | H76: =H13/H70 -> 1459.3048 | I76: =I13/I70 -> 1396.7056 | J76: =J13/J70 -> 1513.4615 | K76: =K13/K70 -> 1767.0685 | M76: =IFERROR(RATE($F$68-$C$68,0,-$C76,$F76),"N/A") -> 0.018895469 | N76: =IFERROR(RATE($K$68-$G$68,0,-$G76,$K76),"N/A") -> 0.022584934
B77: ACV (Bookings) Composition Mix
B78: Subscription | C78: =C10/C$13 -> 0.97207679 | D78: =D10/D$13 -> 0.90917287 | E78: =E10/E$13 -> 0.82934242 | F78: =F10/F$13 -> 0.5745213 | G78: =G10/G$13 -> 0.59704684 | H78: =H10/H$13 -> 0.6262548 | I78: =I10/I$13 -> 0.65048221 | J78: =J10/J$13 -> 0.68 | K78: =K10/K$13 -> 0.7
B79: Professional Services | C79: =C11/C$13 -> 0.027923211 | D79: =D11/D$13 -> 0.08084088 | E79: =E11/E$13 -> 0.1502116 | F79: =F11/F$13 -> 0.42545867 | G79: =G11/G$13 -> 0.40295316 | H79: =H11/H$13 -> 0.3737452 | I79: =I11/I$13 -> 0.34951779 | J79: =J11/J$13 -> 0.32 | K79: =K11/K$13 -> 0.3
B80: Other | C80: =C12/C$13 -> 0 | D80: =D12/D$13 -> 0.0099862462 | E80: =E12/E$13 -> 0.020445973 | F80: =F12/F$13 -> 2.0039219e-05 | G80: =G12/G$13 -> 0 | H80: =H12/H$13 -> 0 | I80: =I12/I$13 -> 0 | J80: =J12/J$13 -> 0 | K80: =K12/K$13 -> 0
B82: Revenue Per Client | C82: =C19/C70 -> 1717.568 | D82: =D19/D70 -> 1311.4905 | E82: =E19/E70 -> 1615.9315 | F82: =F19/F70 -> 1229.3533 | G82: =G19/G70 -> 1131.0451 | H82: =H19/H70 -> 899.14286 | I82: =I19/I70 -> 1045.3219 | J82: =J19/J70 -> 1132.4127 | K82: =K19/K70 -> 1375.3068 | M82: =IFERROR(RATE($F$68-$C$68,0,-$C82,$F82),"N/A") -> -0.10548508 | N82: =IFERROR(RATE($K$68-$G$68,0,-$G82,$K82),"N/A") -> 0.050098203
B83: Revenue Per FTE | C83: =C19/C74 -> 198.18092 | D83: =D19/D74 -> 134.51185 | E83: =E19/E74 -> 104.25365 | F83: =F19/F74 -> 109.46296 | G83: =G19/G74 -> 180.4121 | H83: =H19/H74 -> 212.84058 | I83: =I19/I74 -> 289.04734 | J83: =J19/J74 -> 331.43786 | K83: =K19/K74 -> 383.56545 | M83: =IFERROR(RATE($F$68-$C$68,0,-$C83,$F83),"N/A") -> -0.17951914 | N83: =IFERROR(RATE($K$68-$G$68,0,-$G83,$K83),"N/A") -> 0.20751756
B84: Revenue Composition Mix
B85: Subscription | C85: =C16/C$19 -> 0.62617104 | D85: =D16/D$19 -> 0.89440459 | E85: =E16/E$19 -> 0.86959596 | F85: =F16/F$19 -> 0.74695268 | G85: =G16/G$19 -> 0.5751881 | H85: =H16/H$19 -> 0.56137364 | I85: =I16/I$19 -> 0.63780822 | J85: =J16/J$19 -> 0.66890828 | K85: =K16/K$19 -> 0.68757696
B86: Professional Services | C86: =C17/C$19 -> 0.37382896 | D86: =D17/D$19 -> 0.10559541 | E86: =E17/E$19 -> 0.13040404 | F86: =F17/F$19 -> 0.25304732 | G86: =G17/G$19 -> 0.4248119 | H86: =H17/H$19 -> 0.43862636 | I86: =I17/I$19 -> 0.36219178 | J86: =J17/J$19 -> 0.33109172 | K86: =K17/K$19 -> 0.31242304
B87: Other | C87: =C18/C$19 -> 0 | D87: =D18/D$19 -> 0 | E87: =E18/E$19 -> 0 | F87: =F18/F$19 -> 0 | G87: =G18/G$19 -> 0 | H87: =H18/H$19 -> 0 | I87: =I18/I$19 -> 0 | J87: =J18/J$19 -> 0 | K87: =K18/K$19 -> 0
B89: ARR Per Client | C89: =C21/C71 -> 1322.875 | D89: =D21/D71 -> 1561.1667 | E89: =E21/E71 -> 1665.8571 | F89: =F21/F71 -> 1303.5455 | G89: =G21/G71 -> 921.66667 | H89: =H21/H71 -> 856.775 | I89: =I21/I71 -> 934.16949 | J89: =J21/J71 -> 1077.8182 | K89: =K21/K71 -> 1313.8315 | M89: =IFERROR(RATE($F$68-$C$68,0,-$C89,$F89),"N/A") -> -0.0048945072 | N89: =IFERROR(RATE($K$68-$G$68,0,-$G89,$K89),"N/A") -> 0.0926761
B90: ARR Per FTE | C90: =C21/C74 -> 101.75962 | D90: =D21/D74 -> 120.08974 | E90: =E21/E74 -> 94.040323 | F90: =F21/F74 -> 98.212329 | G90: =G21/G74 -> 118.74233 | H90: =H21/H74 -> 165.56039 | I90: =I21/I74 -> 208.77273 | J90: =J21/J74 -> 253.02439 | K90: =K21/K74 -> 293.79648 | M90: =IFERROR(RATE($F$68-$C$68,0,-$C90,$F90),"N/A") -> -0.011757522 | N90: =IFERROR(RATE($K$68-$G$68,0,-$G90,$K90),"N/A") -> 0.25418111
B92: Subscription Gross Margin | D92: ='Operating Model'!E123 -> 0.6881935 | E92: ='Operating Model'!F123 -> 0.58135542 | F92: ='Operating Model'!G123 -> 0.67841209 | G92: ='Operating Model'!H123 -> 0.56053947 | H92: ='Operating Model'!I123 -> 0.54975319 | I92: ='Operating Model'!J123 -> 0.67255269 | J92: ='Operating Model'!K123 -> 0.71807206 | K92: ='Operating Model'!L123 -> 0.7432095
B93: Professional Services Gross Margin | D93: ='Operating Model'!E126 -> NM | E93: ='Operating Model'!F126 -> NM | F93: ='Operating Model'!G126 -> 0.13096429 | G93: ='Operating Model'!H126 -> 0.54964875 | H93: ='Operating Model'!I126 -> 0.61376952 | I93: ='Operating Model'!J126 -> 0.38950418 | J93: ='Operating Model'!K126 -> 0.32948357 | K93: ='Operating Model'!L126 -> 0.29681203
B95: OpEx Per FTE | C95: ='Operating Model'!D134 -> -315.39157 | D95: ='Operating Model'!E134 -> -211.85226 | E95: ='Operating Model'!F134 -> -194.67229 | F95: ='Operating Model'!G134 -> -237.1039 | G95: ='Operating Model'!H134 -> -237.68624 | H95: ='Operating Model'!I134 -> -215.85729 | I95: ='Operating Model'!J134 -> -208.19512 | J95: ='Operating Model'!K134 -> -206.9048 | K95: ='Operating Model'!L134 -> -207.49158 | M95: =IFERROR(RATE($F$68-$C$68,0,-$C95,$F95),"N/A") -> -0.090723005 | N95: =IFERROR(RATE($K$68-$G$68,0,-$G95,$K95),"N/A") -> -0.033394842

Sheet Operating Model
A2: x | B2: Assumptions | P2: x
B4: ACV-Related Assumptions
C6: 2020 | D6: =C6+1 -> 2021 | E6: =D6+1 -> 2022 | F6: =E6+1 -> 2023 | G6: =F6+1 -> 2024
B8: ACV Annual Growth Escalator | C8: 0.68399174 | D8: 0.70181722 | E8: 0.42588875 | F8: 0.425 | G8: 0.35
B10: ACV Composition Mix Profile
B11: Subscription (% of Total) | C11: 0.59704684 | D11: 0.6262548 | E11: 0.65048221 | F11: 0.68 | G11: 0.7
B12: Professional Services (% of Total) | C12: 0.40295316 | D12: 0.3737452 | E12: 0.34951779 | F12: 0.32 | G12: 0.3
B13: Other (% of Total) | C13: 0 | D13: 0 | E13: 0 | F13: 0 | G13: 0
B14: Total | C14: =SUM(C11:C13) -> 1 | D14: =SUM(D11:D13) -> 1 | E14: =SUM(E11:E13) -> 1 | F14: =SUM(F11:F13) -> 1 | G14: =SUM(G11:G13) -> 1
B16: Number of Total Clients | C16: 26 | D16: 49 | E16: 73 | F16: 96 | G16: 111
B17: Number of Subscription ACV Clients | C17: 21 | D17: 40 | E17: 59 | F17: 77 | G17: 89
B19: Revenue-Related Assumptions
C21: 2020 | D21: =C21+1 -> 2021 | E21: =D21+1 -> 2022 | F21: =E21+1 -> 2023 | G21: =F21+1 -> 2024
B23: Revenue (ACV In-Year Realization Factor %) | C23: 0.3 | D23: 0.3 | E23: 0.3 | F23: 0.3 | G23: 0.3
B24: Revenue (ACV Prior-Year Realization Factor %) | C24: 0.67339598 | D24: 0.53802043 | E24: 0.63939653 | F24: 0.63872345 | G24: 0.64570296
B26: Revenue Composition Mix Profile
B27: Subscription (% of Total) | C27: 0.5751881 | D27: 0.56137364 | E27: 0.63780822 | F27: 0.66890828 | G27: 0.68757696
B28: Professional Services (% of Total) | C28: 0.4248119 | D28: 0.43862636 | E28: 0.36219178 | F28: 0.33109172 | G28: 0.31242304
B29: Other (% of Total) | C29: 0 | D29: 0 | E29: 0 | F29: 0 | G29: 0
B30: Total | C30: =SUM(C27:C29) -> 1 | D30: =SUM(D27:D29) -> 1 | E30: =SUM(E27:E29) -> 1 | F30: =SUM(F27:F29) -> 1 | G30: =SUM(G27:G29) -> 1
B32: Cost-Related Assumptions
D34: 2016 | E34: 2017 | F34: 2018 | G34: 2019 | H34: 2020 | I34: =H34+1 -> 2021 | J34: =I34+1 -> 2022 | K34: =J34+1 -> 2023 | L34: =K34+1 -> 2024
B36: Subscription Cost of Goods Sold (as % of Subscription Revenue) | E36: =-E116/E84 -> 0.3118065 | F36: =-F116/F84 -> 0.41864458 | G36: =-G116/G84 -> 0.32158791 | H36: 0.43946053 | I36: 0.45024681 | J36: 0.32744731 | K36: 0.28192794 | L36: 0.2567905
B37: Professional Services Cost of Goods Sold (as % of Professional Services Revenue) | E37: =-E117/E85 -> 1.1949645 | F37: =-F117/F85 -> 1.0812366 | G37: =-G117/G85 -> 0.61341568 | H37: 0.25578493 | I37: 0.21447029 | J37: 0.31409551 | K37: 0.33434069 | L37: 0.34677959
B38: OpEx: Personnel Expenses (as % of Total Revenue) | D38: =-D129/D$115 -> 0.61526784 | E38: =-E129/E$115 -> 1.0929621 | F38: =-F129/F$115 -> 1.2520141 | G38: =-G129/G$115 -> 1.5786836 | H38: 0.96330089 | I38: 0.72657601 | J38: 0.52828755 | K38: 0.46887921 | L38: 0.41436608
B39: OpEx: Non-Staff Expenses (as % of Total Revenue) | D39: =-D130/D$115 -> 0.97616471 | E39: =-E130/E$115 -> 0.48200888 | F39: =-F130/F$115 -> 0.61528067 | G39: =-G130/G$115 -> 0.58738143 | H39: 0.35416198 | I39: 0.28759755 | J39: 0.19199279 | K39: 0.155385 | L39: 0.12658874
B41: Cash Flow Schedule-Related Assumptions
D43: 2016 | E43: 2017 | F43: 2018 | G43: 2019 | H43: 2020 | I43: =H43+1 -> 2021 | J43: =I43+1 -> 2022 | K43: =J43+1 -> 2023 | L43: =K43+1 -> 2024
B45: D&A (as % of Total Revenue) | D45: =-D184/D$163 -> 0.0021795352 | E45: =-E184/E$163 -> 0.013498859 | F45: =-F184/F$163 -> 0.011915186 | G45: =-G184/G$163 -> 0.013595755 | H45: 0.0095064333 | I45: 0.0063450431 | J45: 0.0036634137 | K45: 0.0025714786 | L45: 0.0018312023
B46: Changes in Net Working Capital (as % of Total Revenue) | D46: =D193/D163 -> 0.10789578 | E46: =E193/E163 -> -0.037818783 | F46: =F193/F163 -> 0.14930066 | G46: =G193/G163 -> 0.23942881 | H46: -0.023731661 | I46: 0.17125531 | J46: 0.095815027 | K46: 0.057314692 | L46: 0.061209835
B47: Capex (as % of Total Revenue) | D47: =-D195/D$163 -> 0.009216229 | E47: =-E195/E$163 -> 0.014928558 | F47: =-F195/F$163 -> 0.016131253 | G47: =-G195/G$163 -> 0.03779759 | H47: 0.055674998 | I47: 0.013509465 | J47: 0.026209401 | K47: 0.027595946 | L47: 0.019651636
A49: x | B49: Operating Model Build-Up | P49: x
B51: Detailed Operating Model Build-Up
D53: Historical FYE | H53: Projected FYE
D54: 42735 | E54: =EOMONTH(D54,12) -> 43100 | F54: =EOMONTH(E54,12) -> 43465 | G54: =EOMONTH(F54,12) -> 43830 | H54: =EOMONTH(G54,12) -> 44196 | I54: =EOMONTH(H54,12) -> 44561 | J54: =EOMONTH(I54,12) -> 44926 | K54: =EOMONTH(J54,12) -> 45291 | L54: =EOMONTH(K54,12) -> 45657 | N54: ="'16A - '19A" -> '16A - '19A | O54: ="'20E - '24E" -> '20E - '24E
D55: =YEAR(D54) -> 2016 | E55: =YEAR(E54) -> 2017 | F55: =YEAR(F54) -> 2018 | G55: =YEAR(G54) -> 2019 | H55: =YEAR(H54) -> 2020 | I55: =YEAR(I54) -> 2021 | J55: =YEAR(J54) -> 2022 | K55: =YEAR(K54) -> 2023 | L55: =YEAR(L54) -> 2024 | N55: CAGR | O55: CAGR
B57: ACV (Bookings)
B59: Subscription (recurring fees for 'access') | D59: 10583 | E59: 13462 | F59: 13698 | G59: 14334.923 | H59: =PRODUCT(H$62,C11) -> 25086.356 | I59: =PRODUCT(I$62,D11) -> 44780.935 | J59: =PRODUCT(J$62,E11) -> 66322.846 | K59: =PRODUCT(K$62,F11) -> 98798.763 | L59: =PRODUCT(L$62,G11) -> 137301.22 | N59: =IFERROR(RATE($G$55-$D$55,0,-$D59,$G59),"N/A") -> 0.1064425 | O59: =IFERROR(RATE($L$55-$H$55,0,-$H59,$L59),"N/A") -> 0.52953425
B60: (+) Professional Services (contingent upon 'completion') | D60: 304 | E60: 1197 | F60: 2481 | G60: 10615.65 | H60: =PRODUCT(H$62,C12) -> 16931.044 | I60: =PRODUCT(I$62,D12) -> 26725 | J60: =PRODUCT(J$62,E12) -> 35636.662 | K60: =PRODUCT(K$62,F12) -> 46493.536 | L60: =PRODUCT(L$62,G12) -> 58843.381 | N60: =IFERROR(RATE($G$55-$D$55,0,-$D60,$G60),"N/A") -> 2.2685691 | O60: =IFERROR(RATE($L$55-$H$55,0,-$H60,$L60),"N/A") -> 0.36537979
B61: (+) Other (non-recurring engineering or setup fees) | D61: 0 | E61: 147.865 | F61: 337.7 | G61: 0.5 | H61: =PRODUCT(H$62,C13) -> 0 | I61: =PRODUCT(I$62,D13) -> 0 | J61: =PRODUCT(J$62,E13) -> 0 | K61: =PRODUCT(K$62,F13) -> 0 | L61: =PRODUCT(L$62,G13) -> 0 | N61: =IFERROR(RATE($G$55-$D$55,0,-$D61,$G61),"N/A") -> N/A | O61: =IFERROR(RATE($L$55-$H$55,0,-$H61,$L61),"N/A") -> N/A
B62: Total ACV (Bookings) | D62: =SUM(D59:D61) -> 10887 | E62: =SUM(E59:E61) -> 14806.865 | F62: =SUM(F59:F61) -> 16516.7 | G62: =SUM(G59:G61) -> 24951.073 | H62: =PRODUCT(G62,1+C$8) -> 42017.4 | I62: =PRODUCT(H62,1+D$8) -> 71505.935 | J62: =PRODUCT(I62,1+E$8) -> 101959.51 | K62: =PRODUCT(J62,1+F$8) -> 145292.3 | L62: =PRODUCT(K62,1+G$8) -> 196144.6 | N62: =IFERROR(RATE($G$55-$D$55,0,-$D62,$G62),"N/A") -> 0.31843988 | O62: =IFERROR(RATE($L$55-$H$55,0,-$H62,$L62),"N/A") -> 0.46989664
B64: Y-O-Y Growth % | E64: =E62/D62-1 -> 0.36005006 | F64: =F62/E62-1 -> 0.11547583 | G64: =G62/F62-1 -> 0.51065724 | H64: =H62/G62-1 -> 0.68399174 | I64: =I62/H62-1 -> 0.70181722 | J64: =J62/I62-1 -> 0.42588875 | K64: =K62/J62-1 -> 0.425 | L64: =L62/K62-1 -> 0.35
B65: ACV Per Client | D65: =D62/D68 -> 1814.5 | E65: =E62/E68 -> 1850.8581 | F65: =F62/F68 -> 2064.5875 | G65: =G62/G68 -> 1919.3133 | H65: =H62/H68 -> 1616.0538 | I65: =I62/I68 -> 1459.3048 | J65: =J62/J68 -> 1396.7056 | K65: =K62/K68 -> 1513.4615 | L65: =L62/L68 -> 1767.0685 | N65: =IFERROR(RATE($G$55-$D$55,0,-$D65,$G65),"N/A") -> 0.018895469 | O65: =IFERROR(RATE($L$55-$H$55,0,-$H65,$L65),"N/A") -> 0.022584934
B67: Client Count
B68: Total Clients | D68: 6 | E68: 8 | F68: 8 | G68: 13 | H68: =C16 -> 26 | I68: =D16 -> 49 | J68: =E16 -> 73 | K68: =F16 -> 96 | L68: =G16 -> 111 | N68: =IFERROR(RATE($G$55-$D$55,0,-$D68,$G68),"N/A") -> 0.29398935 | O68: =IFERROR(RATE($L$55-$H$55,0,-$H68,$L68),"N/A") -> 0.43743233
B69: Y-O-Y Growth % | E69: =E68/D68-1 -> 0.33333333 | F69: =F68/E68-1 -> 0 | G69: =G68/F68-1 -> 0.625 | H69: =H68/G68-1 -> 1 | I69: =I68/H68-1 -> 0.88461538 | J69: =J68/I68-1 -> 0.48979592 | K69: =K68/J68-1 -> 0.31506849 | L69: =L68/K68-1 -> 0.15625
B70: ARR (Subscription ACV) Clients | D70: 4 | E70: 6 | F70: 7 | G70: 11 | H70: =C17 -> 21 | I70: =D17 -> 40 | J70: =E17 -> 59 | K70: =F17 -> 77 | L70: =G17 -> 89 | N70: =IFERROR(RATE($G$55-$D$55,0,-$D70,$G70),"N/A") -> 0.40101967 | O70: =IFERROR(RATE($L$55-$H$55,0,-$H70,$L70),"N/A") -> 0.43480433
B71: Y-O-Y Growth % | E71: =E70/D70-1 -> 0.5 | F71: =F70/E70-1 -> 0.16666667 | G71: =G70/F70-1 -> 0.57142857 | H71: =H70/G70-1 -> 0.90909091 | I71: =I70/H70-1 -> 0.9047619 | J71: =J70/I70-1 -> 0.475 | K71: =K70/J70-1 -> 0.30508475 | L71: =L70/K70-1 -> 0.15584416
B73: ACV (Bookings) Composition Mix
B74: Subscription | D74: =D59/D$62 -> 0.97207679 | E74: =E59/E$62 -> 0.90917287 | F74: =F59/F$62 -> 0.82934242 | G74: =G59/G$62 -> 0.5745213 | H74: =H59/H$62 -> 0.59704684 | I74: =I59/I$62 -> 0.6262548 | J74: =J59/J$62 -> 0.65048221 | K74: =K59/K$62 -> 0.68 | L74: =L59/L$62 -> 0.7
B75: Professional Services | D75: =D60/D$62 -> 0.027923211 | E75: =E60/E$62 -> 0.08084088 | F75: =F60/F$62 -> 0.1502116 | G75: =G60/G$62 -> 0.42545867 | H75: =H60/H$62 -> 0.40295316 | I75: =I60/I$62 -> 0.3737452 | J75: =J60/J$62 -> 0.34951779 | K75: =K60/K$62 -> 0.32 | L75: =L60/L$62 -> 0.3
B76: Other | D76: =D61/D$62 -> 0 | E76: =E61/E$62 -> 0.0099862462 | F76: =F61/F$62 -> 0.020445973 | G76: =G61/G$62 -> 2.0039219e-05 | H76: =H61/H$62 -> 0 | I76: =I61/I$62 -> 0 | J76: =J61/J$62 -> 0 | K76: =K61/K$62 -> 0 | L76: =L61/L$62 -> 0
D78: Historical FYE | H78: Projected FYE
D79: 42735 | E79: =EOMONTH(D79,12) -> 43100 | F79: =EOMONTH(E79,12) -> 43465 | G79: =EOMONTH(F79,12) -> 43830 | H79: =EOMONTH(G79,12) -> 44196 | I79: =EOMONTH(H79,12) -> 44561 | J79: =EOMONTH(I79,12) -> 44926 | K79: =EOMONTH(J79,12) -> 45291 | L79: =EOMONTH(K79,12) -> 45657 | N79: ="'16A - '19A" -> '16A - '19A | O79: ="'20E - '24E" -> '20E - '24E
D80: =YEAR(D79) -> 2016 | E80: =YEAR(E79) -> 2017 | F80: =YEAR(F79) -> 2018 | G80: =YEAR(G79) -> 2019 | H80: =YEAR(H79) -> 2020 | I80: =YEAR(I79) -> 2021 | J80: =YEAR(J79) -> 2022 | K80: =YEAR(K79) -> 2023 | L80: =YEAR(L79) -> 2024 | N80: CAGR | O80: CAGR
B82: Revenue
B84: Subscription Revenue | D84: =AVERAGE($C27:$G27)*D$87 -> 6452.948 | E84: 9384.025 | F84: 11241.66 | G84: 11937.494 | H84: =PRODUCT(H$87,C27) -> 16914.655 | I84: =PRODUCT(I$87,D27) -> 24733 | J84: =PRODUCT(J$87,E27) -> 48670.188 | K84: =PRODUCT(K$87,F27) -> 72718.102 | L84: =PRODUCT(L$87,G27) -> 104964.84 | N84: =IFERROR(RATE($G$80-$D$80,0,-$D84,$G84),"N/A") -> 0.22758525 | O84: =IFERROR(RATE($L$80-$H$80,0,-$H84,$L84),"N/A") -> 0.57832043
B85: (+) Professional Services Revenue | D85: =AVERAGE($C28:$G28)*D$87 -> 3852.46 | E85: 1107.899 | F85: 1685.792 | G85: 4044.0992 | H85: =PRODUCT(H$87,C28) -> 12492.517 | I85: =PRODUCT(I$87,D28) -> 19325 | J85: =PRODUCT(J$87,E28) -> 27638.311 | K85: =PRODUCT(K$87,F28) -> 35993.517 | L85: =PRODUCT(L$87,G28) -> 47694.205 | N85: =IFERROR(RATE($G$80-$D$80,0,-$D85,$G85),"N/A") -> 0.016313959 | O85: =IFERROR(RATE($L$80-$H$80,0,-$H85,$L85),"N/A") -> 0.39782859
B86: (+) Other Revenue | D86: =AVERAGE($C29:$G29)*D$87 -> 0 | E86: 0 | F86: 0 | G86: 0 | H86: =PRODUCT(H$87,C29) -> 0 | I86: =PRODUCT(I$87,D29) -> 0 | J86: =PRODUCT(J$87,E29) -> 0 | K86: =PRODUCT(K$87,F29) -> 0 | L86: =PRODUCT(L$87,G29) -> 0 | N86: =IFERROR(RATE($G$80-$D$80,0,-$D86,$G86),"N/A") -> N/A | O86: =IFERROR(RATE($L$80-$H$80,0,-$H86,$L86),"N/A") -> N/A
B87: Total Revenue | D87: 10305.408 | E87: =SUM(E84:E86) -> 10491.924 | F87: =SUM(F84:F86) -> 12927.452 | G87: =SUM(G84:G86) -> 15981.593 | H87: =PRODUCT(C$23,H$62)+PRODUCT(C$24,G$62) -> 29407.172 | I87: =PRODUCT(D$23,I$62)+PRODUCT(D$24,H$62) -> 44058 | J87: =PRODUCT(E$23,J$62)+PRODUCT(E$24,I$62) -> 76308.499 | K87: =PRODUCT(F$23,K$62)+PRODUCT(F$24,J$62) -> 108711.62 | L87: =PRODUCT(G$23,L$62)+PRODUCT(G$24,K$62) -> 152659.05 | N87: =IFERROR(RATE($G$80-$D$80,0,-$D87,$G87),"N/A") -> 0.15749278 | O87: =IFERROR(RATE($L$80-$H$80,0,-$H87,$L87),"N/A") -> 0.5094451
B89: Y-O-Y Growth % | E89: =E87/D87-1 -> 0.018098847 | F89: =F87/E87-1 -> 0.23213359 | G89: =G87/F87-1 -> 0.23625235 | H89: =H87/G87-1 -> 0.84006515 | I89: =I87/H87-1 -> 0.49820595 | J89: =J87/I87-1 -> 0.73200098 | K89: =K87/J87-1 -> 0.42463317 | L89: =L87/K87-1 -> 0.40425698
B90: Revenue Per Client | D90: =D87/D$68 -> 1717.568 | E90: =E87/E$68 -> 1311.4905 | F90: =F87/F$68 -> 1615.9315 | G90: =G87/G$68 -> 1229.3533 | H90: =H87/H$68 -> 1131.0451 | I90: =I87/I$68 -> 899.14286 | J90: =J87/J$68 -> 1045.3219 | K90: =K87/K$68 -> 1132.4127 | L90: =L87/L$68 -> 1375.3068 | N90: =IFERROR(RATE($G$55-$D$55,0,-$D90,$G90),"N/A") -> -0.10548508 | O90: =IFERROR(RATE($L$80-$H$80,0,-$H90,$L90),"N/A") -> 0.050098203
B91: Revenue Per FTE | D91: =D87/D136 -> 198.18092 | E91: =E87/E136 -> 134.51185 | F91: =F87/F136 -> 104.25365 | G91: =G87/G136 -> 109.46296 | H91: =H87/H136 -> 180.4121 | I91: =I87/I136 -> 212.84058 | J91: =J87/J136 -> 289.04734 | K91: =K87/K136 -> 331.43786 | L91: =L87/L136 -> 383.56545 | N91: =IFERROR(RATE($G$55-$D$55,0,-$D91,$G91),"N/A") -> -0.17951914 | O91: =IFERROR(RATE($L$80-$H$80,0,-$H91,$L91),"N/A") -> 0.20751756
B93: Revenue Composition Mix
B94: Subscription | D94: =D84/D$87 -> 0.62617104 | E94: =E84/E$87 -> 0.89440459 | F94: =F84/F$87 -> 0.86959596 | G94: =G84/G$87 -> 0.74695268 | H94: =H84/H$87 -> 0.5751881 | I94: =I84/I$87 -> 0.56137364 | J94: =J84/J$87 -> 0.63780822 | K94: =K84/K$87 -> 0.66890828 | L94: =L84/L$87 -> 0.68757696
B95: Professional Services | D95: =D85/D$87 -> 0.37382896 | E95: =E85/E$87 -> 0.10559541 | F95: =F85/F$87 -> 0.13040404 | G95: =G85/G$87 -> 0.25304732 | H95: =H85/H$87 -> 0.4248119 | I95: =I85/I$87 -> 0.43862636 | J95: =J85/J$87 -> 0.36219178 | K95: =K85/K$87 -> 0.33109172 | L95: =L85/L$87 -> 0.31242304
B96: Other | D96: =D86/D$87 -> 0 | E96: =E86/E$87 -> 0 | F96: =F86/F$87 -> 0 | G96: =G86/G$87 -> 0 | H96: =H86/H$87 -> 0 | I96: =I86/I$87 -> 0 | J96: =J86/J$87 -> 0 | K96: =K86/K$87 -> 0 | L96: =L86/L$87 -> 0
B98: Average Rolling 3-Month MRR | D98: =D100/D99 -> 440.95833 | E98: 780.58333 | F98: 971.75 | G98: 1194.9167 | H98: 1612.9167 | I98: 2855.9167 | J98: 4593 | K98: 6916 | L98: 9744.25 | N98: =IFERROR(RATE($G$80-$D$80,0,-$D98,$G98),"N/A") -> 0.39416236 | O98: =IFERROR(RATE($L$80-$H$80,0,-$H98,$L98),"N/A") -> 0.5677764
B99: (x) Annualization Factor | D99: 12 | E99: =D99 -> 12 | F99: =E99 -> 12 | G99: =F99 -> 12 | H99: =G99 -> 12 | I99: =H99 -> 12 | J99: =I99 -> 12 | K99: =J99 -> 12 | L99: =K99 -> 12
B100: ARR | D100: 5291.5 | E100: =PRODUCT(E98:E99) -> 9367 | F100: =PRODUCT(F98:F99) -> 11661 | G100: =PRODUCT(G98:G99) -> 14339 | H100: =PRODUCT(H98:H99) -> 19355 | I100: =PRODUCT(I98:I99) -> 34271 | J100: =PRODUCT(J98:J99) -> 55116 | K100: =PRODUCT(K98:K99) -> 82992 | L100: =PRODUCT(L98:L99) -> 116931 | N100: =IFERROR(RATE($G$80-$D$80,0,-$D100,$G100),"N/A") -> 0.39416236 | O100: =IFERROR(RATE($L$80-$H$80,0,-$H100,$L100),"N/A") -> 0.5677764
B102: Y-O-Y Growth % | E102: =E100/D100-1 -> 0.77019749 | F102: =F100/E100-1 -> 0.24490232 | G102: =G100/F100-1 -> 0.2296544 | H102: =H100/G100-1 -> 0.34981519 | I102: =I100/H100-1 -> 0.77065358 | J102: =J100/I100-1 -> 0.6082402 | K102: =K100/J100-1 -> 0.50576965 | L102: =L100/K100-1 -> 0.40894303
B103: ARR Per Client (Subscription ACV Client) | D103: =D100/D$70 -> 1322.875 | E103: =E100/E$70 -> 1561.1667 | F103: =F100/F$70 -> 1665.8571 | G103: =G100/G$70 -> 1303.5455 | H103: =H100/H$70 -> 921.66667 | I103: =I100/I$70 -> 856.775 | J103: =J100/J$70 -> 934.16949 | K103: =K100/K$70 -> 1077.8182 | L103: =L100/L$70 -> 1313.8315 | N103: =IFERROR(RATE($G$80-$D$80,0,-$D103,$G103),"N/A") -> -0.0048945072 | O103: =IFERROR(RATE($L$80-$H$80,0,-$H103,$L103),"N/A") -> 0.0926761
B104: ARR Per FTE | D104: =D100/D136 -> 101.75962 | E104: =E100/E136 -> 120.08974 | F104: =F100/F136 -> 94.040323 | G104: =G100/G136 -> 98.212329 | H104: =H100/H136 -> 118.74233 | I104: =I100/I136 -> 165.56039 | J104: =J100/J136 -> 208.77273 | K104: =K100/K136 -> 253.02439 | L104: =L100/L136 -> 293.79648 | N104: =IFERROR(RATE($G$80-$D$80,0,-$D104,$G104),"N/A") -> -0.011757522 | O104: =IFERROR(RATE($L$80-$H$80,0,-$H104,$L104),"N/A") -> 0.25418111
D106: Historical FYE | H106: Projected FYE
D107: 42735 | E107: =EOMONTH(D107,12) -> 43100 | F107: =EOMONTH(E107,12) -> 43465 | G107: =EOMONTH(F107,12) -> 43830 | H107: =EOMONTH(G107,12) -> 44196 | I107: =EOMONTH(H107,12) -> 44561 | J107: =EOMONTH(I107,12) -> 44926 | K107: =EOMONTH(J107,12) -> 45291 | L107: =EOMONTH(K107,12) -> 45657 | N107: ="'16A - '19A" -> '16A - '19A | O107: ="'20E - '24E" -> '20E - '24E
D108: =YEAR(D107) -> 2016 | E108: =YEAR(E107) -> 2017 | F108: =YEAR(F107) -> 2018 | G108: =YEAR(G107) -> 2019 | H108: =YEAR(H107) -> 2020 | I108: =YEAR(I107) -> 2021 | J108: =YEAR(J107) -> 2022 | K108: =YEAR(K107) -> 2023 | L108: =YEAR(L107) -> 2024 | N108: CAGR | O108: CAGR
B110: Gross Profit, Operating Expenses, & EBITDA
B112: Subscription Revenue | D112: =D84 -> 6452.948 | E112: =E84 -> 9384.025 | F112: =F84 -> 11241.66 | G112: =G84 -> 11937.494 | H112: =H84 -> 16914.655 | I112: =I84 -> 24733 | J112: =J84 -> 48670.188 | K112: =K84 -> 72718.102 | L112: =L84 -> 104964.84 | N112: =IFERROR(RATE($G$108-$D$108,0,-$D112,$G112),"N/A") -> 0.22758525 | O112: =IFERROR(RATE($L$108-$H$108,0,-$H112,$L112),"N/A") -> 0.57832043
B113: (+) Professional Services Revenue | D113: =D85 -> 3852.46 | E113: =E85 -> 1107.899 | F113: =F85 -> 1685.792 | G113: =G85 -> 4044.0992 | H113: =H85 -> 12492.517 | I113: =I85 -> 19325 | J113: =J85 -> 27638.311 | K113: =K85 -> 35993.517 | L113: =L85 -> 47694.205 | N113: =IFERROR(RATE($G$108-$D$108,0,-$D113,$G113),"N/A") -> 0.016313959 | O113: =IFERROR(RATE($L$108-$H$108,0,-$H113,$L113),"N/A") -> 0.39782859
B114: (+) Other Revenue | D114: =D86 -> 0 | E114: =E86 -> 0 | F114: =F86 -> 0 | G114: =G86 -> 0 | H114: =H86 -> 0 | I114: =I86 -> 0 | J114: =J86 -> 0 | K114: =K86 -> 0 | L114: =L86 -> 0 | N114: =IFERROR(RATE($G$108-$D$108,0,-$D114,$G114),"N/A") -> N/A | O114: =IFERROR(RATE($L$108-$H$108,0,-$H114,$L114),"N/A") -> N/A
B115: Total Revenue | D115: =SUM(D112:D114) -> 10305.408 | E115: =SUM(E112:E114) -> 10491.924 | F115: =SUM(F112:F114) -> 12927.452 | G115: =SUM(G112:G114) -> 15981.593 | H115: =SUM(H112:H114) -> 29407.172 | I115: =SUM(I112:I114) -> 44058 | J115: =SUM(J112:J114) -> 76308.499 | K115: =SUM(K112:K114) -> 108711.62 | L115: =SUM(L112:L114) -> 152659.05 | N115: =IFERROR(RATE($G$108-$D$108,0,-$D115,$G115),"N/A") -> 0.15749278 | O115: =IFERROR(RATE($L$108-$H$108,0,-$H115,$L115),"N/A") -> 0.5094451
B116: (–) Cost of Goods Sold (Subscription) | E116: -2926 | F116: -4706.26 | G116: -3838.9536 | H116: =-PRODUCT(H$112,H$36) -> -7433.3234 | I116: =-PRODUCT(I$112,I$36) -> -11135.954 | J116: =-PRODUCT(J$112,J$36) -> -15936.922 | K116: =-PRODUCT(K$112,K$36) -> -20501.264 | L116: =-PRODUCT(L$112,L$36) -> -26953.975
B117: (–) Cost of Goods Sold (Professional Services) | E117: -1323.9 | F117: -1822.74 | G117: -2480.7139 | H117: =-PRODUCT(H$113,H$37) -> -3195.3975 | I117: =-PRODUCT(I$113,I$37) -> -4144.6384 | J117: =-PRODUCT(J$113,J$37) -> -8681.0692 | K117: =-PRODUCT(K$113,K$37) -> -12034.097 | L117: =-PRODUCT(L$113,L$37) -> -16539.377
B118: (+/–) Other Adjustments | D118: -3710.1656 | E118: 303.396 | F118: 348.978 | G118: 0.01386 | H118: -108 | I118: 0.01386 | J118: 0.01386 | K118: 0.01386 | L118: 0.01386
B119: Total Gross Profit | D119: =SUM(D115:D118) -> 6595.2424 | E119: =SUM(E115:E118) -> 6545.42 | F119: =SUM(F115:F118) -> 6747.43 | G119: =SUM(G115:G118) -> 9661.9392 | H119: =SUM(H115:H118) -> 18670.451 | I119: =SUM(I115:I118) -> 28777.421 | J119: =SUM(J115:J118) -> 51690.522 | K119: =SUM(K115:K118) -> 76176.271 | L119: =SUM(L115:L118) -> 109165.71 | N119: =IFERROR(RATE($G$108-$D$108,0,-$D119,$G119),"N/A") -> 0.13573719 | O119: =IFERROR(RATE($L$108-$H$108,0,-$H119,$L119),"N/A") -> 0.55500883
B120: Gross Margin % | D120: =D119/D115 -> 0.63997878 | E120: =E119/E115 -> 0.62385317 | F120: =F119/F115 -> 0.52194586 | G120: =G119/G115 -> 0.60456672 | H120: =H119/H115 -> 0.63489448 | I120: =I119/I115 -> 0.6531713 | J120: =J119/J115 -> 0.67738879 | K120: =K119/K115 -> 0.70071876 | L120: =L119/L115 -> 0.71509492
B122: Subscription Gross Profit | E122: =E112+E116 -> 6458.025 | F122: =F112+F116 -> 6535.4 | G122: =G112+G116 -> 8098.54 | H122: =H112+H116 -> 9481.3319 | I122: =I112+I116 -> 13597.046 | J122: =J112+J116 -> 32733.266 | K122: =K112+K116 -> 52216.837 | L122: =L112+L116 -> 78010.869 | N122: =IFERROR(RATE($G$108-$D$108,0,-$D122,$G122),"N/A") -> N/A | O122: =IFERROR(RATE($L$108-$H$108,0,-$H122,$L122),"N/A") -> 0.69364132
B123: Subscription Gross Margin % | E123: =IF(E122/E$112<0,"NM",E122/E$112) -> 0.6881935 | F123: =IF(F122/F$112<0,"NM",F122/F$112) -> 0.58135542 | G123: =IF(G122/G$112<0,"NM",G122/G$112) -> 0.67841209 | H123: =IF(H122/H$112<0,"NM",H122/H$112) -> 0.56053947 | I123: =IF(I122/I$112<0,"NM",I122/I$112) -> 0.54975319 | J123: =IF(J122/J$112<0,"NM",J122/J$112) -> 0.67255269 | K123: =IF(K122/K$112<0,"NM",K122/K$112) -> 0.71807206 | L123: =IF(L122/L$112<0,"NM",L122/L$112) -> 0.7432095
B125: Professional Services Gross Profit | E125: =E113+E117 -> -216.001 | F125: =F113+F117 -> -136.948 | G125: =G113+G117 -> 1563.3854 | H125: =H113+H117 -> 9297.1191 | I125: =I113+I117 -> 15180.362 | J125: =J113+J117 -> 18957.242 | K125: =K113+K117 -> 23959.42 | L125: =L113+L117 -> 31154.828 | N125: =IFERROR(RATE($G$108-$D$108,0,-$D125,$G125),"N/A") -> N/A | O125: =IFERROR(RATE($L$108-$H$108,0,-$H125,$L125),"N/A") -> 0.35298892
B126: Professional Services Gross Margin % | E126: =IF(E125/E$112<0,"NM",E125/E$112) -> NM | F126: =IF(F125/F$112<0,"NM",F125/F$112) -> NM | G126: =IF(G125/G$112<0,"NM",G125/G$112) -> 0.13096429 | H126: =IF(H125/H$112<0,"NM",H125/H$112) -> 0.54964875 | I126: =IF(I125/I$112<0,"NM",I125/I$112) -> 0.61376952 | J126: =IF(J125/J$112<0,"NM",J125/J$112) -> 0.38950418 | K126: =IF(K125/K$112<0,"NM",K125/K$112) -> 0.32948357 | L126: =IF(L125/L$112<0,"NM",L125/L$112) -> 0.29681203
B128: Operating Expenses
B129: Total Personnel Expenses | D129: -6340.5862 | E129: -11467.276 | F129: -16185.352 | G129: -25229.878 | H129: =-PRODUCT(H$38,H$115) -> -28327.955 | I129: =-PRODUCT(I$38,I$115) -> -32011.486 | J129: =-PRODUCT(J$38,J$115) -> -40312.83 | K129: =-PRODUCT(K$38,K$115) -> -50972.619 | L129: =-PRODUCT(L$38,L$115) -> -63256.732 | N129: =IFERROR(RATE($G$108-$D$108,0,-$D129,$G129),"N/A") -> 0.58463259 | O129: =IFERROR(RATE($L$108-$H$108,0,-$H129,$L129),"N/A") -> 0.22242685
B130: (+) Non-Staff Expenses | D130: -10059.776 | E130: -5057.2005 | F130: -7954.0113 | G130: -9387.2908 | H130: =-PRODUCT(H$39,H$115) -> -10414.902 | I130: =-PRODUCT(I$39,I$115) -> -12670.973 | J130: =-PRODUCT(J$39,J$115) -> -14650.681 | K130: =-PRODUCT(K$39,K$115) -> -16892.155 | L130: =-PRODUCT(L$39,L$115) -> -19324.917 | N130: =IFERROR(RATE($G$108-$D$108,0,-$D130,$G130),"N/A") -> -0.022798797 | O130: =IFERROR(RATE($L$108-$H$108,0,-$H130,$L130),"N/A") -> 0.16712026
B131: Total Operating Expenses | D131: =SUM(D129:D130) -> -16400.362 | E131: =SUM(E129:E130) -> -16524.476 | F131: =SUM(F129:F130) -> -24139.363 | G131: =SUM(G129:G130) -> -34617.169 | H131: =SUM(H129:H130) -> -38742.857 | I131: =SUM(I129:I130) -> -44682.459 | J131: =SUM(J129:J130) -> -54963.512 | K131: =SUM(K129:K130) -> -67864.774 | L131: =SUM(L129:L130) -> -82581.648 | N131: =IFERROR(RATE($G$108-$D$108,0,-$D131,$G131),"N/A") -> 0.28276187 | O131: =IFERROR(RATE($L$108-$H$108,0,-$H131,$L131),"N/A") -> 0.20829499
B132: Y-O-Y Growth % | E132: =E131/D131-1 -> 0.0075677794 | F132: =F131/E131-1 -> 0.46082474 | G132: =G131/F131-1 -> 0.43405476 | H132: =H131/G131-1 -> 0.1191804 | I132: =I131/H131-1 -> 0.1533083 | J132: =J131/I131-1 -> 0.23009147 | K132: =K131/J131-1 -> 0.23472413 | L132: =L131/K131-1 -> 0.21685587
B133: % of Total Revenue | D133: =-D131/D115 -> 1.5914326 | E133: =-E131/E115 -> 1.574971 | F133: =-F131/F115 -> 1.8672948 | G133: =-G131/G115 -> 2.166065 | H133: =-H131/H115 -> 1.3174629 | I133: =-I131/I115 -> 1.0141736 | J133: =-J131/J115 -> 0.72028034 | K133: =-K131/K115 -> 0.62426422 | L133: =-L131/L115 -> 0.54095482
B134: OpEx per FTE | D134: =D131/D136 -> -315.39157 | E134: =E131/E136 -> -211.85226 | F134: =F131/F136 -> -194.67229 | G134: =G131/G136 -> -237.1039 | H134: =H131/H136 -> -237.68624 | I134: =I131/I136 -> -215.85729 | J134: =J131/J136 -> -208.19512 | K134: =K131/K136 -> -206.9048 | L134: =L131/L136 -> -207.49158
B136: Full Time Employees (FTEs) | D136: 52 | E136: 78 | F136: 124 | G136: 146 | H136: 163 | I136: 207 | J136: 264 | K136: 328 | L136: 398 | N136: =IFERROR(RATE($G$108-$D$108,0,-$D136,$G136),"N/A") -> 0.41074928 | O136: =IFERROR(RATE($L$108-$H$108,0,-$H136,$L136),"N/A") -> 0.25003988
B138: Total Gross Profit | D138: =D119 -> 6595.2424 | E138: =E119 -> 6545.42 | F138: =F119 -> 6747.43 | G138: =G119 -> 9661.9392 | H138: =H119 -> 18670.451 | I138: =I119 -> 28777.421 | J138: =J119 -> 51690.522 | K138: =K119 -> 76176.271 | L138: =L119 -> 109165.71
B139: (–) OpEx: Personnel Expenses | D139: =D129 -> -6340.5862 | E139: =E129 -> -11467.276 | F139: =F129 -> -16185.352 | G139: =G129 -> -25229.878 | H139: =H129 -> -28327.955 | I139: =I129 -> -32011.486 | J139: =J129 -> -40312.83 | K139: =K129 -> -50972.619 | L139: =L129 -> -63256.732
...
