Workbook
Name AA.AlternatePriceSourceStartPeriod: "Q1-2018"
Name AA.CIK: "887596"
Name AA.ColorizerVersion: "2.0.4.0"
Name AA.CompareQuarters.LatestMRQ: "Q3-2018"
Name AA.CSIN: "B1ICH30103"
Name AA.CurationVersion: "2023.11.1.0"
Name AA.DBMacroVersion: "1.0.13.0"
Name AA.FreeCashFlow: "TRUE"
Name AA.HardcodeChecker.LatestMRQ: "Q3-2019"
Name AA.ModelChecks.LatestMRQ: "Q3-2021"
Name AA.ModelChecks.LatestVersionNumber: "2.38.22.0"
Name AA.ModelColorScheme: "Classic"
Name AA.ModelVersion: "FY2023.23"
Name AA.NonLibraryWideCurationVersion: "5"
Name AA.PartialUpdate.BsAvailable: "FALSE"
Name AA.PartialUpdate.CfsAvailable: "FALSE"
Name AA.PartialUpdate.IsAvailable: "TRUE"
Name AA.PeriodLayout: "QFY"
Name AA.PersonalMacro.VersionNumber: "1.5.3.0"
Name AA.RowNameEnforcerVersion: "2023.11.1.0"
Name AA.SessionToUploadId: ""
Name AA.StartWorkModelVersion: "FY2023.22"
Name AA.StartWorkType: ""
Name AA.SubyearType: "Q"
Name AA.TemplateUpgradeAttempted: "TRUE"
Name AA.TemplateVersion: "7.4.8.0"
Name AA.UpdateType: "Regular"
Name AA.VerifyUnitsAtModelVersion: "Q1-2018.24"
Name HP.MRFX: Historicals!$B$934
Name HP.ReportCurrency: Historicals!$B$933
Name HP.Ticker: Historicals!$A$2
Name HP.TradeCurrency: Historicals!$B$931
Name HP.TradeCurrency.HardCoded: Historicals!$B$932
Name IQ_CH: 110000
Name IQ_CQ: 5000
Name IQ_CY: 10000
Name IQ_DAILY: 500000
Name IQ_FH: 100000
Name IQ_FQ: 500
Name IQ_FY: 1000
Name IQ_LTM: 2000
Name IQ_MONTH: 15000
Name IQ_NTM: 6000
Name IQ_WEEK: 50000
Name IQ_YTD: 3000
Name MO_AN_NI_NONGAAP_Diluted: Historicals!$377:$377
Name MO_BS_AP: Historicals!$764:$764
Name MO_BS_AR: Historicals!$746:$746
Name MO_BS_CA: Historicals!$751:$751
Name MO_BS_Cash: Historicals!$743:$743
Name MO_BS_CL: Historicals!$769:$769
Name MO_BS_CommonStock: Historicals!$784:$784
Name MO_BS_ContributedSurplus: Historicals!$785:$785
Name MO_BS_Intangibles: Historicals!$755:$755
Name MO_BS_INV: Historicals!$748:$748
Name MO_BS_NCA: Historicals!$760:$760
Name MO_BS_NCI: Historicals!$790:$790
Name MO_BS_NCL: Historicals!$780:$780
Name MO_BS_OCI: Historicals!$787:$787
Name MO_BS_OL_Current: Historicals!$767:$767

Sheet Cover
C16: Cheesecake Factory LBO Analysis
C19: To toggle between cases, please refer to 'Forecast Assumptions'
C21: Operating Model Build
C23: Forecast Assumptions
C24: Consolidated IS Build
C25: Consolidated BS Build
C26: BS Link
C27: CFS Link
C28: Revenue Build -- CK F.
C29: Revenue Build -- North Italia
C30: Revenue Build -- FRC & Others
C31: Revenue Build -- Franchising
... C42: Historicals (Publicly Available Raw Data)
AQ208: -

Sheet Transaction
B3: $ in millions
B5: 2023 EBITDA | E5: ='Consolidated IS Build'!BG27 -> 267.874 | H5: Share Price | J5: 34
B6: Entry Purchase Multiple | E6: =E7/E5 -> 10.148877 | H6: Total Shares outstanding | J6: 50.97
B7: Enterprise Value | E7: =E10-E9-E8 -> 2718.6204 | H7: Purchase Premium | J7: 0.33
B8: (-Debt) | E8: =-'Balance Sheet Link'!AV42 -> -470.047 | H8: Purchase Price per Share | J8: =J5*(1+J7) -> 45.22
B9: (+Cash) | E9: ='Balance Sheet Link'!AV9 -> 56.29
B10: Purchase Equity Value | E10: =J8*J6 -> 2304.8634
B11: (+Transaction Costs) | E11: =0.05*E7 -> 135.93102
B16: Sources | E16: Amount | F16: Interest Rate | G16: Capita/EBITDA | H16: % Capital
B17: Revolver | E17: 100 | F17: 0.0175 | G17: =E17/$E$5 -> 0.37330984 | H17: =E17/$E$23 -> 0.034354328
B18: Senior Secured TL (S + 175) | E18: =2.7*E5 -> 723.25981 | F18: =0.0532+0.0175 -> 0.0707 | G18: =E18/$E$5 -> 2.7 | H18: =E18/$E$23 -> 0.24847104 | J18: Senior Secured TL interest rate determined from S&P credit rating data for cumulative 5.3x Capital/EBITDA tranche
B19: 7.500% Senior Unsecured Notes | E19: =0.51*E23-(E17+E18) -> 661.26932 | F19: 0.075 | G19: =E19/$E$5 -> 2.4685834 | H19: =E19/$E$23 -> 0.22717463 | J19: Senior Secured TL interest rate determined from S&P credit rating data for cumulative 5.6x Capital/EBITDA tranche
B20: Cash | E20: =E9 -> 56.29 | G20: =E20/$E$5 -> 0.21013611 | H20: =E20/$E$23 -> 0.019338051
B21: Existing Roark Equity | E21: =0.05*E10 -> 115.24317 | G21: =E21/$E$5 -> 0.43021409 | H21: =E21/$E$23 -> 0.039591016 | J21: 57% Debt/Capital Buyout Financing
B22: New Roark Equity | E22: =E23-SUM(E17:E21) -> 1254.7791 | G22: =E22/$E$5 -> 4.6842139 | H22: =E22/$E$23 -> 0.43107093
B23: Total | E23: =E29 -> 2910.8414 | G23: =E23/$E$5 -> 10.866457 | H23: =E23/$E$23 -> 1
B25: Uses
B26: Refinance Old Debt | E26: =-E8 -> 470.047 | G26: =E26/$E$5 -> 1.7547317 | H26: =E26/$E$23 -> 0.16148149
B27: Equity Purchase | E27: =E10 -> 2304.8634 | G27: =E27/$E$5 -> 8.6042818 | H27: =E27/$E$23 -> 0.79182033
B28: Transaction Fees | E28: =E11 -> 135.93102 | G28: =E28/$E$5 -> 0.50744387 | H28: =E28/$E$23 -> 0.046698188
B29: Total | E29: =SUM(E26:E28) -> 2910.8414 | G29: =E29/$E$5 -> 10.866457 | H29: =E29/$E$23 -> 1
B32: 2028 Exit | E32: Returns Analysis and Value Bridge
B33: EBITDA | C33: =LBO!N40 -> 616.09628
B34: EV/EBITDA (entry) | C34: =E6 -> 10.148877 | E34: Source of Returns | F34: Entry Value | G34: Exit Value | H34: Attributed Returns
B35: EV/EBITDA (exit) | C35: 8.2 | E35: Entry Equity | H35: =E21+E22 -> 1370.0223
B36: Enterprise Value | C36: =C33*C35 -> 5051.9895 | E36: EBITDA Expansion | F36: =E5 -> 267.874 | G36: =C33 -> 616.09628 | H36: =H44*F45 -> 3534.0652
B37: (-) Outstanding debt | C37: =LBO!N42 -> 799.14797 | E37: Multiple Re-Rate | F37: =C34 -> 10.148877 | G37: =C35 -> 8.2 | H37: =G44*H45 -> -1200.6961
B38: (+) Cash | C38: ='Valuation and Cash Flow'!H31 -> 0 | E38: Fees | F38: =E11 -> 135.93102 | H38: =-F38 -> -135.93102
B39: Equity Value | C39: =C36-C37+C38 -> 4252.8415 | E39: Debt Paydown | F39: =SUM(E17:E19) -> 1484.5291 | G39: =LBO!N43 -> 799.14797 | H39: =H40-SUM(H36:H38) -> 685.38115
E40: Exit Equity | F40: =C41 -> 1370.0223 | G40: =C39 -> 4252.8415 | H40: =G40-F40 -> 2882.8192
B41: Equity Investment | C41: =E21+E22 -> 1370.0223
B42: MOIC | C42: =C39/C41 -> 3.1042134
B43: Holding Period (yrs) | C43: 5 | F43: Entry Value | G43: Exit Value | H43: Growth
E44: EBITDA | F44: =E5 -> 267.874 | G44: =C33 -> 616.09628 | H44: =G44-F44 -> 348.22228
B45: IRR | C45: =C42^(1/C43)-1 -> 0.25426792 | E45: EV/EBITDA | F45: =E6 -> 10.148877 | G45: =C35 -> 8.2 | H45: =G45-F45 -> -1.9488774
E47: LBO Value Creation
E49: Source of Returns | F49: Attributed Returns | G49: % Return
E50: EBITDA Expansion | F50: =H36 -> 3534.0652 | G50: =F50/F54 -> 1.2259059
E51: Multiple Re-Rate | F51: =H37 -> -1200.6961 | G51: =F51/F54 -> -0.41650065
E52: Debt Paydown | F52: =H39 -> 685.38115 | G52: =F52/F54 -> 0.23774684
E53: Fees | F53: =-F38 -> -135.93102 | G53: =F53/F54 -> -0.047152113
E54: Total Returns | F54: =F50+F51+F52+F53 -> 2882.8192 | G54: =G50+G51+G52+G53 -> 1 | J54: Exit Multiple
J56: =C45 -> 0.25426792 | K56: 7.8 | L56: 8 | M56: 8.2 | N56: 8.4 | O56: 8.6
I57: Purchase Premium | J57: 0.25 | K57: 0.25849236 | L57: 0.26596786 | M57: 0.27327085 | N57: 0.28041004 | O57: 0.28739347
J58: 0.28 | K58: 0.25122324 | L58: 0.25871883 | M58: 0.26604001 | N58: 0.27319566 | O58: 0.28019397
J59: 0.3 | K59: 0.24644692 | L59: 0.2539565 | M59: 0.26129039 | N59: 0.26845756 | O59: 0.27546632
J60: 0.33 | K60: 0.23938262 | L60: 0.24691411 | M60: 0.25426792 | N60: 0.2614532 | O60: 0.26847841
J61: 0.35 | K61: 0.23473741 | L61: 0.24228412 | M61: 0.24965178 | N61: 0.25684967 | O61: 0.26388636
J62: 0.37 | K62: 0.23014179 | L62: 0.23770419 | M62: 0.24508615 | N62: 0.25229709 | O62: 0.25934567
J63: 0.4 | K63: 0.22333796 | L63: 0.2309248 | M63: 0.23832908 | N63: 0.24556039 | O63: 0.25262757

Sheet Valuation and Cash Flow
B2: FCF Build
J3: Tax Rate | K3: 0.21
B4: $ in millions | D4: 2024E | E4: 2025E | F4: 2026E | G4: 2027E | H4: 2028E
B5: EBIT | D5: ='Consolidated IS Build'!BH22 -> 254.936 | E5: ='Consolidated IS Build'!BI22 -> 282.91409 | F5: ='Consolidated IS Build'!BJ22 -> 356.36516 | G5: ='Consolidated IS Build'!BK22 -> 424.36341 | H5: ='Consolidated IS Build'!BL22 -> 490.44355 | L5: UFCF Build
B6: (-) Interest Expense | D6: =LBO!J44 -> 102.47967 | E6: =LBO!K44 -> 98.828925 | F6: =LBO!L44 -> 90.053149 | G6: =LBO!M44 -> 77.448072 | H6: =LBO!N44 -> 59.34322 | L6: $ in millions | N6: 2024E | O6: 2025E | P6: 2026E | Q6: 2027E | R6: 2028E
L7: EBIT | N7: =D5 -> 254.936 | O7: =E5 -> 282.91409 | P7: =F5 -> 356.36516 | Q7: =G5 -> 424.36341 | R7: =H5 -> 490.44355
B8: EBT | D8: =D5-D6 -> 152.45634 | E8: =E5-E6 -> 184.08516 | F8: =F5-F6 -> 266.31201 | G8: =G5-G6 -> 346.91534 | H8: =H5-H6 -> 431.10033
B9: Tax Rate | D9: =$K$3 -> 0.21 | E9: =$K$3 -> 0.21 | F9: =$K$3 -> 0.21 | G9: =$K$3 -> 0.21 | H9: =$K$3 -> 0.21 | L9: (-) Taxes on EBIT | N9: =N7*$K$3 -> 53.536561 | O9: =O7*$K$3 -> 59.411958 | P9: =P7*$K$3 -> 74.836683 | Q9: =Q7*$K$3 -> 89.116316 | R9: =R7*$K$3 -> 102.99315
B10: (-) Tax Expense | D10: =D8*D9 -> 32.01583 | E10: =E8*E9 -> 38.657884 | F10: =F8*F9 -> 55.925522 | G10: =G8*G9 -> 72.852221 | H10: =H8*H9 -> 90.53107 | L10: (+) D&A | N10: =D16 -> 93.136 | O10: =E16 -> 100.01489 | P10: =F16 -> 110.25205 | Q10: =G16 -> 117.94024 | R10: =H16 -> 125.65273
B11: Net Income | D11: =D8-D10 -> 120.44051 | E11: =E8-E10 -> 145.42728 | F11: =F8-F10 -> 210.38649 | G11: =G8-G10 -> 274.06312 | H11: =H8-H10 -> 340.56926 | L11: (+/-) Changes in NWC | N11: =D18 -> 65.000886 | O11: =E18 -> 13.51059 | P11: =F18 -> 0.1402224 | Q11: =G18 -> 23.384323 | R11: =H18 -> 32.419836
L12: (-) CapEx | N12: =L24 -> 180.09 | O12: =M24 -> 165.318 | P12: =N24 -> 175.7616 | Q12: =O24 -> 195.19392 | R12: =P24 -> 193.9217
B13: $ in millions | D13: 2024E | E13: 2025E | F13: 2026E | G13: 2027E | H13: 2027E | L13: UFCF | N13: =N7-N9+N10+N11-N12 -> 179.44633 | O13: =O7-O9+O10+O11-O12 -> 171.70961 | P13: =P7-P9+P10+P11-P12 -> 216.15915 | Q13: =Q7-Q9+Q10+Q11-Q12 -> 281.37774 | R13: =R7-R9+R10+R11-R12 -> 351.60127
B15: Net Income | D15: =D11 -> 120.44051 | E15: =E11 -> 145.42728 | F15: =F11 -> 210.38649 | G15: =G11 -> 274.06312 | H15: =H11 -> 340.56926
B16: (+) D&A | D16: ='Consolidated IS Build'!BH25 -> 93.136 | E16: ='Consolidated IS Build'!BI25 -> 100.01489 | F16: ='Consolidated IS Build'!BJ25 -> 110.25205 | G16: ='Consolidated IS Build'!BK25 -> 117.94024 | H16: ='Consolidated IS Build'!BL25 -> 125.65273
B17: (+) SBC | D17: ='Consolidated IS Build'!BH26 -> 28.397224 | E17: ='Consolidated IS Build'!BI26 -> 30.492194 | F17: ='Consolidated IS Build'!BJ26 -> 33.272473 | G17: ='Consolidated IS Build'!BK26 -> 35.886188 | H17: ='Consolidated IS Build'!BL26 -> 38.658514
B18: (+/-) Changes in NWC | D18: ='Consolidated BS Build'!AX18 -> 65.000886 | E18: ='Consolidated BS Build'!AY18 -> 13.51059 | F18: ='Consolidated BS Build'!AZ18 -> 0.1402224 | G18: ='Consolidated BS Build'!BA18 -> 23.384323 | H18: ='Consolidated BS Build'!BB18 -> 32.419836
B19: Cash Flow from Operations | D19: =D15+D16+D17+D18 -> 306.97461 | E19: =E15+E16+E17+E18 -> 289.44495 | F19: =F15+F16+F17+F18 -> 354.05124 | G19: =G15+G16+G17+G18 -> 451.27387 | H19: =H15+H16+H17+H18 -> 537.30034 | L19: 2024 | M19: 2025 | N19: 2026 | O19: 2027 | P19: 2028
J20: Cumulative Owned Stores | L20: ='Consolidated IS Build'!BH15 -> 345.6 | M20: ='Consolidated IS Build'!BI15 -> 361.12 | N20: ='Consolidated IS Build'!BJ15 -> 373.744 | O20: ='Consolidated IS Build'!BK15 -> 389.2928 | P20: ='Consolidated IS Build'!BL15 -> 404.75136
B21: (-) CapEx | D21: =L24 -> 180.09 | E21: =M24 -> 165.318 | F21: =N24 -> 175.7616 | G21: =O24 -> 195.19392 | H21: =P24 -> 193.9217 | J21: New Store Openings | L21: ='Forecast Assumptions'!G9+'Forecast Assumptions'!G10+'Forecast Assumptions'!G11 -> 15 | M21: ='Forecast Assumptions'!H9+'Forecast Assumptions'!H10+'Forecast Assumptions'!H11 -> 13 | N21: ='Forecast Assumptions'!I9+'Forecast Assumptions'!I10+'Forecast Assumptions'!I11 -> 14 | O21: ='Forecast Assumptions'!J9+'Forecast Assumptions'!J10+'Forecast Assumptions'!J11 -> 16 | P21: ='Forecast Assumptions'!K9+'Forecast Assumptions'!K10+'Forecast Assumptions'!K11 -> 15.58
B22: Cash Flow from Investing | D22: =D19-D21 -> 126.88461 | E22: =E19-E21 -> 124.12695 | F22: =F19-F21 -> 178.28964 | G22: =G19-G21 -> 256.07995 | H22: =H19-H21 -> 343.37864 | J22: Per Store Upront CapEx (mn) | L22: 8.55 | M22: 8.55 | N22: 8.55 | O22: 8.55 | P22: 8.55
J23: Maintenance CapEx/Store | L23: 0.15 | M23: 0.15 | N23: 0.15 | O23: 0.15 | P23: 0.15
B24: (-) Revolver Repayment | D24: =LBO!J13 -> 100 | E24: =LBO!K13 -> 0 | F24: =LBO!L13 -> 0 | G24: =LBO!M13 -> 0 | H24: =LBO!N13 -> 0 | J24: Total CapEx | L24: =(L20*L23+L21*L22) -> 180.09 | M24: =(M20*M23+M21*M22) -> 165.318 | N24: =(N20*N23+N21*N22) -> 175.7616 | O24: =(O20*O23+O21*O22) -> 195.19392 | P24: =(P20*P23+P21*P22) -> 193.9217
B25: (-) TL Repayment | D25: =LBO!J24 -> 26.884615 | E25: =LBO!K24 -> 124.12695 | F25: =LBO!L24 -> 178.28964 | G25: =LBO!M24 -> 256.07995 | H25: =LBO!N24 -> 137.87865
B26: (-) Notes Repayment | D26: =LBO!J32 -> 0 | E26: =LBO!K32 -> 0 | F26: =LBO!L32 -> 0 | G26: =LBO!M32 -> 0 | H26: =LBO!N32 -> 205.49999
B27: Cash Flow from Financing | D27: =D22-D24-D25-D26 -> 0 | E27: =E22-E24-E25-E26 -> 0 | F27: =F22-F24-F25-F26 -> 0 | G27: =G22-G24-G25-G26 -> 0 | H27: =H22-H24-H25-H26 -> 0
B29: Beginning Cash | D29: 0 | E29: =D31 -> 0 | F29: =E31 -> 0 | G29: =F31 -> 0 | H29: =G31 -> 0
B30: Change in Cash | D30: =D27 -> 0 | E30: =E27 -> 0 | F30: =F27 -> 0 | G30: =G27 -> 0 | H30: =H27 -> 0
B31: Ending Cash | D31: =D29+D30 -> 0 | E31: =E29+E30 -> 0 | F31: =F29+F30 -> 0 | G31: =G29+G30 -> 0 | H31: =H29+H30 -> 0

Sheet Forecast Assumptions
D2: Active Assumptions
F4: 2023A | G4: 2024E | H4: 2025E | I4: 2026E | J4: 2027E | K4: 2028E | N4: Case Toggle: | O4: Base Case
D5: AlcBev Spend/Customer | F5: {=_xlfn.XLOOKUP($O$4,$D$19:$D$21,F19:K21)} -> 3.3594 | G5: 4 | H5: 4.5 | I5: 4.9 | J5: 5.2 | K5: 5.5
D6: Food Spend/Customer | F6: {=_xlfn.XLOOKUP(O4,D24:D26,F24:K26)} -> 21.9888 | G6: 22.868352 | H6: 23.783086 | I6: 24.73441 | J6: 25.723786 | K6: 26.752737 | O6: Bear Case
D7: Dessert Spend/Customer | F7: {=_xlfn.XLOOKUP(O4,D29:D31,F29:K31)} -> 5.1918 | G7: 5.347554 | H7: 5.5079806 | I7: 5.67322 | J7: 5.8434166 | K7: 6.0187191 | O7: Base Case
D8: Table Turnover Rate | F8: {=_xlfn.XLOOKUP(O4,D36:D38,F36:K38)} -> 0.38465779 | G8: 0.39 | H8: 0.395 | I8: 0.4 | J8: 0.405 | K8: 0.41 | O8: Bull Case
D9: New Stores - CK F. | F9: {=_xlfn.XLOOKUP(O4,D43:D45,F43:K45)} -> 6 | G9: 4 | H9: 5 | I9: 5 | J9: 6 | K9: 6
D10: New Stores - North Italia | F10: {=_xlfn.XLOOKUP(O4,D48:D50,F48:K50)} -> 3 | G10: 4 | H10: 4 | I10: 4 | J10: 5 | K10: 5
D11: New Stores - FRC & Others | F11: {=_xlfn.XLOOKUP(O4,D53:D55,F53:K55)} -> 7 | G11: 7 | H11: 4 | I11: 5 | J11: 5 | K11: 4.58
D12: New Franchises - South America | F12: {=_xlfn.XLOOKUP(O4,D60:D62,F60:K62)} -> 0 | G12: 4 | H12: 2 | I12: 2 | J12: 1 | K12: 0
D13: =D64 -> SSS Growth, Franchise | F13: {=_xlfn.XLOOKUP(O4,D65:D67,F65:K67)} -> 0 | G13: 0.045 | H13: 0.045 | I13: 0.045 | J13: 0.045 | K13: 0.045
D14: =D70 -> SSS Growth, North Italia | F14: {=_xlfn.XLOOKUP(O4,D71:D73,F71:K73)} -> 0 | G14: 0.04 | H14: 0.04 | I14: 0.04 | J14: 0.04 | K14: 0.04
D15: =D75 -> SSS Growth, FRC & Others | F15: {=_xlfn.XLOOKUP(O4,D76:D78,F76:K78)} -> 0 | G15: 0.05 | H15: 0.05 | I15: 0.05 | J15: 0.05 | K15: 0.05
D18: AlcBev Spend/Customer | F18: 2023A | G18: 2024E | H18: 2025E | I18: 2026E | J18: 2027E | K18: 2028E
D19: Bear Case | F19: ='Revenue Build - CK F.'!BG33 -> 3.3594 | G19: =F19*(1.04) -> 3.493776 | H19: =G19*(1.04) -> 3.633527 | I19: =H19*(1.03) -> 3.7425329 | J19: =I19*(1.03) -> 3.8548088 | K19: =J19*(1.03) -> 3.9704531
D20: Base Case | F20: ='Revenue Build - CK F.'!BG33 -> 3.3594 | G20: 4 | H20: 4.5 | I20: 4.9 | J20: 5.2 | K20: 5.5
D21: Bull Case | F21: ='Revenue Build - CK F.'!BG33 -> 3.3594 | G21: 4.5 | H21: 5 | I21: 5.5 | J21: 5.9 | K21: 6.3
D23: Food Spend/Customer | F23: 2023A | G23: 2024E | H23: 2025E | I23: 2026E | J23: 2027E | K23: 2028E
D24: Bear Case | F24: ='Revenue Build - CK F.'!BG37 -> 21.9888 | G24: =F24*(1.03) -> 22.648464 | H24: =G24*(1.03) -> 23.327918 | I24: =H24*(1.03) -> 24.027755 | J24: =I24*(1.03) -> 24.748588 | K24: =J24*(1.03) -> 25.491046 | M24: inability to pass on COGS escalation to customers
D25: Base Case | F25: ='Revenue Build - CK F.'!BG37 -> 21.9888 | G25: =F25*(1.04) -> 22.868352 | H25: =G25*(1.04) -> 23.783086 | I25: =H25*(1.04) -> 24.73441 | J25: =I25*(1.04) -> 25.723786 | K25: =J25*(1.04) -> 26.752737
D26: Bull Case | F26: ='Revenue Build - CK F.'!BG37 -> 21.9888 | G26: =F26*(1.06) -> 23.308128 | H26: =G26*(1.06) -> 24.706616 | I26: =H26*(1.06) -> 26.189013 | J26: =I26*(1.06) -> 27.760353 | K26: =J26*(1.06) -> 29.425975
D28: Dessert Spend/Customer | F28: 2023A | G28: 2024E | H28: 2025E | I28: 2026E | J28: 2027E | K28: 2028E
D29: Bear Case | F29: ='Revenue Build - CK F.'!BG35 -> 5.1918 | G29: =F29*(0.99) -> 5.139882 | H29: =G29*(0.99) -> 5.0884832 | I29: =H29*(0.99) -> 5.0375983 | J29: =I29*(0.99) -> 4.9872224 | K29: =J29*(0.99) -> 4.9373501
D30: Base Case | F30: ='Revenue Build - CK F.'!BG35 -> 5.1918 | G30: =F30*(1.03) -> 5.347554 | H30: =G30*(1.03) -> 5.5079806 | I30: =H30*(1.03) -> 5.67322 | J30: =I30*(1.03) -> 5.8434166 | K30: =J30*(1.03) -> 6.0187191
D31: Bull Case | F31: ='Revenue Build - CK F.'!BG35 -> 5.1918 | G31: =F31*(1.05) -> 5.45139 | H31: =G31*(1.05) -> 5.7239595 | I31: =H31*(1.05) -> 6.0101575 | J31: =I31*(1.05) -> 6.3106653 | K31: =J31*(1.05) -> 6.6261986
D35: Table Turnover Rate | F35: 2023A | G35: 2024E | H35: 2025E | I35: 2026E | J35: 2027E | K35: 2028E
D36: Bear Case | F36: ='Revenue Build - CK F.'!BG28 -> 0.38465779 | G36: =$F$36+0.01 -> 0.39465779 | H36: =$F$36+0.01 -> 0.39465779 | I36: =$F$36+0.02 -> 0.40465779 | J36: =$F$36+0.02 -> 0.40465779 | K36: =$F$36+0.02 -> 0.40465779
D37: Base Case | F37: ='Revenue Build - CK F.'!BG28 -> 0.38465779 | G37: 0.39 | H37: 0.395 | I37: 0.4 | J37: 0.405 | K37: 0.41 | L37: Olive Garden
D38: Bull Case | F38: ='Revenue Build - CK F.'!BG28 -> 0.38465779 | G38: 0.4 | H38: 0.41 | I38: 0.42 | J38: 0.42 | K38: 0.43 | L38: Bloomin' Brands
D42: New Stores - CK F. | F42: 2023A | G42: 2024E | H42: 2025E | I42: 2026E | J42: 2027E | K42: 2028E
D43: Bear Case | F43: ='Revenue Build - CK F.'!BG10 -> 6 | G43: =2 -> 2 | H43: =G43+1 -> 3 | I43: =H43 -> 3 | J43: =I43 -> 3 | K43: =J43 -> 3
D44: Base Case | F44: ='Revenue Build - CK F.'!BG10 -> 6 | G44: 4 | H44: 5 | I44: 5 | J44: 6 | K44: 6
D45: Bull Case | F45: ='Revenue Build - CK F.'!BG10 -> 6 | G45: 6 | H45: 6 | I45: 7 | J45: 7 | K45: 8
D47: New Stores - North Italia | F47: 2023A | G47: 2024E | H47: 2025E | I47: 2026E | J47: 2027E | K47: 2028E
D48: Bear Case | F48: ='Revenue Build - North Italia'!BC10 -> 3 | G48: 2 | H48: 2 | I48: 2 | J48: 2 | K48: 2
D49: Base Case | F49: ='Revenue Build - North Italia'!BC10 -> 3 | G49: 4 | H49: 4 | I49: 4 | J49: 5 | K49: 5
D50: Bull Case | F50: ='Revenue Build - North Italia'!BC10 -> 3 | G50: 5 | H50: 5 | I50: 6 | J50: 6 | K50: 7
D52: New Stores - FRC & Others | F52: 2023A | G52: 2024E | H52: 2025E | I52: 2026E | J52: 2027E | K52: 2028E
D53: Bear Case | F53: ='Revenue Build - FRC & Others'!BG10+'Revenue Build - FRC & Others'!BG42 -> 7 | G53: 5 | H53: 4 | I53: 4 | J53: 4 | K53: 3
D54: Base Case | F54: ='Revenue Build - FRC & Others'!BG10+'Revenue Build - FRC & Others'!BG42 -> 7 | G54: 7 | H54: 4 | I54: 5 | J54: 5 | K54: 4.58
D55: Bull Case | F55: ='Revenue Build - FRC & Others'!BG10+'Revenue Build - FRC & Others'!BG42 -> 7 | G55: 7 | H55: 6 | I55: 6 | J55: 6 | K55: 6
D59: New Franchises - South America | F59: 2023A | G59: 2024E | H59: 2025E | I59: 2026E | J59: 2027E | K59: 2028E
D60: Bear Case | F60: ='Revenue Build - CK F.'!BG76 -> 0 | G60: =G61-1 -> 3 | H60: =H61 -> 2 | I60: =I61-1 -> 1 | J60: =J61-1 -> 0 | K60: =K61 -> 0
D61: Base Case | F61: ='Revenue Build - CK F.'!BG76 -> 0 | G61: 4 | H61: 2 | I61: 2 | J61: 1 | K61: 0
D62: Bull Case | F62: ='Revenue Build - CK F.'!BG76 -> 0 | G62: =G61+1 -> 5 | H62: =H61+1 -> 3 | I62: =I61+1 -> 3 | J62: =J61+1 -> 2 | K62: =K61+1 -> 1
D64: SSS Growth, Franchise | F64: 2023A | G64: 2024E | H64: 2025E | I64: 2026E | J64: 2027E | K64: 2028E
D65: Bear Case | F65: ='Revenue Build - CK F.'!BG81 -> 0 | G65: =G66-0.006 -> 0.039 | H65: =H66-0.006 -> 0.039 | I65: =I66-0.006 -> 0.039 | J65: =J66-0.006 -> 0.039 | K65: =K66-0.006 -> 0.039
D66: Base Case | F66: ='Revenue Build - CK F.'!BG81 -> 0 | G66: 0.045 | H66: 0.045 | I66: 0.045 | J66: 0.045 | K66: 0.045
D67: Bull Case | F67: ='Revenue Build - CK F.'!BG81 -> 0 | G67: =G66+0.01 -> 0.055 | H67: =H66+0.01 -> 0.055 | I67: =I66+0.01 -> 0.055 | J67: =J66+0.01 -> 0.055 | K67: =K66+0.01 -> 0.055
D70: SSS Growth, North Italia | F70: 2023A | G70: 2024E | H70: 2025E | I70: 2026E | J70: 2027E | K70: 2028E
D71: Bear Case | F71: ='Revenue Build - CK F.'!BG87 -> 0 | G71: =G72-0.0075 -> 0.0325 | H71: =H72-0.0075 -> 0.0325 | I71: =I72-0.0075 -> 0.0325 | J71: =J72-0.0075 -> 0.0325 | K71: =K72-0.0075 -> 0.0325
D72: Base Case | F72: ='Revenue Build - CK F.'!BG87 -> 0 | G72: 0.04 | H72: 0.04 | I72: 0.04 | J72: 0.04 | K72: 0.04
D73: Bull Case | F73: ='Revenue Build - CK F.'!BG87 -> 0 | G73: =G72+0.01 -> 0.05 | H73: =H72+0.01 -> 0.05 | I73: =I72+0.01 -> 0.05 | J73: =J72+0.01 -> 0.05 | K73: =K72+0.01 -> 0.05
D75: SSS Growth, FRC & Others | F75: 2023A | G75: 2024E | H75: 2025E | I75: 2026E | J75: 2027E | K75: 2028E
D76: Bear Case | F76: ='Revenue Build - CK F.'!BG92 -> 0 | G76: =G77-0.008 -> 0.042 | H76: =H77-0.008 -> 0.042 | I76: =I77-0.008 -> 0.042 | J76: =J77-0.008 -> 0.042 | K76: =K77-0.008 -> 0.042
D77: Base Case | F77: ='Revenue Build - CK F.'!BG92 -> 0 | G77: 0.05 | H77: 0.05 | I77: 0.05 | J77: 0.05 | K77: 0.05
D78: Bull Case | F78: ='Revenue Build - CK F.'!BG92 -> 0 | G78: =G77+0.01 -> 0.06 | H78: =H77+0.01 -> 0.06 | I78: =I77+0.01 -> 0.06 | J78: =J77+0.01 -> 0.06 | K78: =K77+0.01 -> 0.06

Sheet LBO
B2: $ in millions | J2: 2024E | K2: 2025E | L2: 2026E | M2: 2027E | N2: 2028E
B4: Cash Beginning Balance: | J4: ='Valuation and Cash Flow'!D29 -> 0 | K4: ='Valuation and Cash Flow'!E29 -> 0 | L4: ='Valuation and Cash Flow'!F29 -> 0 | M4: ='Valuation and Cash Flow'!G29 -> 0 | N4: ='Valuation and Cash Flow'!H29 -> 0
B5: (+) Free Cash Flow | J5: ='Valuation and Cash Flow'!D22 -> 126.88461 | K5: ='Valuation and Cash Flow'!E22 -> 124.12695 | L5: ='Valuation and Cash Flow'!F22 -> 178.28964 | M5: ='Valuation and Cash Flow'!G22 -> 256.07995 | N5: ='Valuation and Cash Flow'!H22 -> 343.37864
B7: Cash Availble for Repayment of Debt | J7: =J4+J5 -> 126.88461 | K7: =K4+K5 -> 124.12695 | L7: =L4+L5 -> 178.28964 | M7: =M4+M5 -> 256.07995 | N7: =N4+N5 -> 343.37864
B10: Revolver (Max: $100)
B12: Beginning Balance | J12: =I16 -> 100 | K12: =J16 -> 0 | L12: =K16 -> 0 | M12: =L16 -> 0 | N12: =M16 -> 0
B13: Repayment | J13: =IF(J7>J12,J12,J7) -> 100 | K13: =IF(K7>K12,K12,K7) -> 0 | L13: =IF(L7>L12,L12,L7) -> 0 | M13: =IF(M7>M12,M12,M7) -> 0 | N13: =IF(N7>N12,N12,N7) -> 0
B14: Interest Expense | C14: Rate | D14: =Transaction!F17 -> 0.0175 | J14: =J12*$D$14 -> 1.75 | K14: =K12*$D$14 -> 0 | L14: =L12*$D$14 -> 0 | M14: =M12*$D$14 -> 0 | N14: =N12*$D$14 -> 0
B16: Ending Balance | I16: =Transaction!E17 -> 100 | J16: =J12-J13 -> 0 | K16: =K12-K13 -> 0 | L16: =L12-L13 -> 0 | M16: =M12-M13 -> 0 | N16: =N12-N13 -> 0
B18: Revolver Capacity | F18: Within Capacity?
B21: Senior Secured TL
B23: Beginning Balance | J23: =I27 -> 723.25981 | K23: =J27 -> 696.37519 | L23: =K27 -> 572.24824 | M23: =L27 -> 393.9586 | N23: =M27 -> 137.87865
B24: Principal Repayment | J24: =IF(J7-J13>0,MIN(J23,J7-J13),0) -> 26.884615 | K24: =IF(K7-K13>0,MIN(K23,K7-K13),0) -> 124.12695 | L24: =IF(L7-L13>0,MIN(L23,L7-L13),0) -> 178.28964 | M24: =IF(M7-M13>0,MIN(M23,M7-M13),0) -> 256.07995 | N24: =IF(N7-N13>0,MIN(N23,N7-N13),0) -> 137.87865
B25: Interest Expense | C25: Rate | D25: =Transaction!F18 -> 0.0707 | J25: =J23*$D$25 -> 51.134468 | K25: =K23*$D$25 -> 49.233726 | L25: =L23*$D$25 -> 40.45795 | M25: =M23*$D$25 -> 27.852873 | N25: =N23*$D$25 -> 9.7480207
B27: Ending Balance | I27: =Transaction!E18 -> 723.25981 | J27: =J23-J24 -> 696.37519 | K27: =K23-K24 -> 572.24824 | L27: =L23-L24 -> 393.9586 | M27: =M23-M24 -> 137.87865 | N27: =N23-N24 -> 0
B30: Senior Unsecured Notes
B31: Beginning Balance | J31: =I35 -> 661.26932 | K31: =J35 -> 661.26932 | L31: =K35 -> 661.26932 | M31: =L35 -> 661.26932 | N31: =M35 -> 661.26932
B32: Principal Repayment | J32: =IF(J7-J13-J24>0,MIN(J31,J7-J13-J24),0) -> 0 | K32: =IF(K7-K13-K24>0,MIN(K31,K7-K13-K24),0) -> 0 | L32: =IF(L7-L13-L24>0,MIN(L31,L7-L13-L24),0) -> 0 | M32: =IF(M7-M13-M24>0,MIN(M31,M7-M13-M24),0) -> 0 | N32: =IF(N7-N13-N24>0,MIN(N31,N7-N13-N24),0) -> 205.49999
B33: Interest Expense | C33: Rate | D33: =Transaction!F19 -> 0.075 | J33: =J31*$D$33 -> 49.595199 | K33: =K31*$D$33 -> 49.595199 | L33: =L31*$D$33 -> 49.595199 | M33: =M31*$D$33 -> 49.595199 | N33: =N31*$D$33 -> 49.595199
B35: Ending Balance | I35: =Transaction!E19 -> 661.26932 | J35: =J31-J32 -> 661.26932 | K35: =K31-K32 -> 661.26932 | L35: =L31-L32 -> 661.26932 | M35: =M31-M32 -> 661.26932 | N35: =N31-N32 -> 455.76933
B38: Leverage Calculations
B40: EBITDA | J40: ='Valuation and Cash Flow'!D5+'Valuation and Cash Flow'!D16 -> 348.072 | K40: ='Valuation and Cash Flow'!E5+'Valuation and Cash Flow'!E16 -> 382.92898 | L40: ='Valuation and Cash Flow'!F5+'Valuation and Cash Flow'!F16 -> 466.61721 | M40: ='Valuation and Cash Flow'!G5+'Valuation and Cash Flow'!G16 -> 542.30365 | N40: ='Valuation and Cash Flow'!H5+'Valuation and Cash Flow'!H16 -> 616.09628
B42: Total Beginning Debt | J42: =J12+J23+J31 -> 1484.5291 | K42: =K12+K23+K31 -> 1357.6445 | L42: =L12+L23+L31 -> 1233.5176 | M42: =M12+M23+M31 -> 1055.2279 | N42: =N12+N23+N31 -> 799.14797
B43: Beginning Net Debt | J43: =J42-J4 -> 1484.5291 | K43: =K42-K4 -> 1357.6445 | L43: =L42-L4 -> 1233.5176 | M43: =M42-M4 -> 1055.2279 | N43: =N42-N4 -> 799.14797
B44: Total Interest Expense | J44: =J33+J25+J14 -> 102.47967 | K44: =K33+K25+K14 -> 98.828925 | L44: =L33+L25+L14 -> 90.053149 | M44: =M33+M25+M14 -> 77.448072 | N44: =N33+N25+N14 -> 59.34322
B46: Leverage (Debt/EBITDA) | J46: =J42/J40 -> 4.2650058 | K46: =K42/K40 -> 3.5454212 | L46: =L42/L40 -> 2.643532 | M46: =M42/M40 -> 1.9458248 | N46: =N42/N40 -> 1.2971154
B47: Interest Coverage (EBITDA/Interest) | J47: =J40/J44 -> 3.3964982 | K47: =K40/K44 -> 3.874665 | L47: =L40/L44 -> 5.1815757 | M47: =M40/M44 -> 7.0021582 | N47: =IFERROR(N40/N44,0) -> 10.381915

Sheet Consolidated IS Build
B1: Period Ended | J1: 41730 | K1: 41821 | L1: 41912 | M1: 42003 | N1: 42003 | O1: 42094 | P1: 42185 | Q1: 42276 | R1: 42367 | S1: 42367 | T1: 42458 | U1: 42549 | V1: 42640 | W1: 42738 | X1: 42738 | Y1: 42829 | Z1: 42920 | AA1: 43011 | AB1: 43102 | AC1: 43102 | AD1: 43193 | AE1: 43284 | AF1: 43375 | AG1: 43466 | AH1: 43466 | AI1: 43557 | AJ1: 43648 | AK1: 43739 | AL1: 43830 | AM1: 43830 | AN1: 43921 | AO1: 44012 | AP1: 44103 | AQ1: 44194 | AR1: 44194 | AS1: 44285 | AT1: 44376 | AU1: 44467 | AV1: 44558 | AW1: 44558 | AX1: 44649 | AY1: 44740 | AZ1: 44831 | BA1: 44929 | BB1: 44929 | BC1: 45019 | BD1: 45111 | BE1: 45202 | BF1: 45293 | BG1: 45293 | BH1: Projected
J2: Q1-2014 | K2: Q2-2014 | L2: Q3-2014 | M2: Q4-2014 | N2: FY2014 | O2: Q1-2015 | P2: Q2-2015 | Q2: Q3-2015 | R2: Q4-2015 | S2: FY2015 | T2: Q1-2016 | U2: Q2-2016 | V2: Q3-2016 | W2: Q4-2016 | X2: FY2016 | Y2: Q1-2017 | Z2: Q2-2017 | AA2: Q3-2017 | AB2: Q4-2017 | AC2: FY2017 | AD2: Q1-2018 | AE2: Q2-2018 | AF2: Q3-2018 | AG2: Q4-2018 | AH2: FY2018 | AI2: Q1-2019 | AJ2: Q2-2019 | AK2: Q3-2019 | AL2: Q4-2019 | AM2: FY2019 | AN2: Q1-2020 | AO2: Q2-2020 | AP2: Q3-2020 | AQ2: Q4-2020 | AR2: FY2020 | AS2: Q1-2021 | AT2: Q2-2021 | AU2: Q3-2021 | AV2: Q4-2021 | AW2: FY2021 | AX2: Q1-2022 | AY2: Q2-2022 | AZ2: Q3-2022 | BA2: Q4-2022 | BB2: FY2022 | BC2: Q1-2023 | BD2: Q2-2023 | BE2: Q3-2023 | BF2: Q4-2023 | BG2: FY2023 | BH2: FY2024E | BI2: FY2025E | BJ2: FY2026E | BK2: FY2027E | BL2: FY2028E
B4: Restaurant-level revenue | J4: =J5+J6+J7 -> 481.431 | K4: =K5+K6+K7 -> 496.406 | L4: =L5+L6+L7 -> 499.114 | M4: =M5+M6+M7 -> 499.673 | N4: =N5+N6+N7 -> 1792.796 | O4: =O5+O6+O7 -> 472.817 | P4: =P5+P6+P7 -> 483.285 | Q4: =Q5+Q6+Q7 -> 481.076 | ... BG4: =BG5+BG6+BG7 -> 3339.3629 | BH4: =BH5+BH7+BH6 -> 3668.0853 | BI4: =BI5+BI7+BI6 -> 3974.6378 | BJ4: =BJ5+BJ7+BJ6 -> 4301.9083 | BK4: =BK5+BK7+BK6 -> 4650.2874 | BL4: =BL5+BL7+BL6 -> 5018.012
B5: Cheesecake Factory | J5: ='Revenue Build - CK F.'!J53 -> 436.606 | K5: ='Revenue Build - CK F.'!K53 -> 451.454 | L5: ='Revenue Build - CK F.'!L53 -> 454.271 | M5: ='Revenue Build - CK F.'!M53 -> 450.465 | N5: ='Revenue Build - CK F.'!N53 -> 1792.796 | O5: ='Revenue Build - CK F.'!O53 -> 472.817 | P5: ='Revenue Build - CK F.'!P53 -> 483.285 | Q5: ='Revenue Build - CK F.'!Q53 -> 481.076 | ... BG5: ='Revenue Build - CK F.'!BG53 -> 2595.066 | BH5: {='Revenue Build - CK F.'!BH53:BL53} -> 2861.822 | BI5: 3098.5756 | BJ5: 3351.6877 | BK5: 3616.9345 | BL5: 3891.7756
B6: North Italia | J6: 0 | K6: 0 | L6: 0 | M6: 0 | N6: 0 | O6: 0 | P6: 0 | Q6: 0 | R6: 0 | S6: 0 | T6: 0 | U6: 0 | V6: 0 | W6: 0 | X6: 0 | Y6: 0 | Z6: 0 | AA6: 0 | AB6: 0 | AC6: 0 | AD6: 0 | AE6: 0 | AF6: 0 | AG6: 0 | AH6: 0 | AI6: 0 | AJ6: 0 | AK6: 0 | AL6: ='Revenue Build - North Italia'!AH24 -> 35.268 | AM6: ='Revenue Build - North Italia'!AI24 -> 35.268 | AN6: ='Revenue Build - North Italia'!AJ24 -> 30.512 | AO6: ='Revenue Build - North Italia'!AK24 -> 13.759 | AP6: ='Revenue Build - North Italia'!AL24 -> 27.99 | AQ6: ='Revenue Build - North Italia'!AM24 -> 30.324 | AR6: ='Revenue Build - North Italia'!AN24 -> 102.585 | AS6: ='Revenue Build - North Italia'!AO24 -> 32.823 | ... BL6: ='Revenue Build - North Italia'!BH24 -> 506.70519
B7: FRC & all other restaurant | J7: ='Revenue Build - FRC & Others'!J47 -> 44.825 | K7: ='Revenue Build - FRC & Others'!K47 -> 44.952 | L7: ='Revenue Build - FRC & Others'!L47 -> 44.843 | M7: ='Revenue Build - FRC & Others'!M47 -> 49.208 | S7: ='Revenue Build - FRC & Others'!S49 -> 125.96444 | T7: ='Revenue Build - FRC & Others'!T49 -> 47.377 | U7: ='Revenue Build - FRC & Others'!U49 -> 46.944 | V7: ='Revenue Build - FRC & Others'!V49 -> 47.978 | W7: ='Revenue Build - FRC & Others'!W49 -> 55.337 | X7: ='Revenue Build - FRC & Others'!X49 -> 132.80961 | Y7: ='Revenue Build - FRC & Others'!Y49 -> 48.192 | Z7: ='Revenue Build - FRC & Others'!Z49 -> 49.641 | ... BL7: ='Revenue Build - FRC & Others'!BL49 -> 619.53116
B8: Bakery revenue | N8: 53.2 | S8: 52.8 | X8: 53.6 | AC8: 55.1 | AH8: 54.4 | AM8: 58.4 | AR8: 66.6 | AW8: 66.2 | BB8: 68.186 | BG8: 70.23158 | BH8: =BH9*(BH5+BH10) -> 77.524554 | BI8: =BI9*(BI5+BI10) -> 83.94897 | BJ8: =BJ9*(BJ5+BJ10) -> 90.790903 | BK8: =BK9*(BK5+BK10) -> 98.009003 | BL8: =BL9*(BL5+BL10) -> 105.39054
B9: Bakery % of CKF & Franchise | S9: =S8/(S5+S10) -> 0.027473606 | T9: =T8/(T5+T10) -> 0 | U9: =U8/(U5+U10) -> 0 | V9: =V8/(V5+V10) -> 0 | W9: =W8/(W5+W10) -> 0 | X9: =X8/(X5+X10) -> 0.02565441 | Y9: =Y8/(Y5+Y10) -> 0 | Z9: =Z8/(Z5+Z10) -> 0 | ... BG9: =BG8/(BG5+BG10) -> 0.026755147 | BH9: =$BG$9 -> 0.026755147 | BI9: =$BG$9 -> 0.026755147 | BJ9: =$BG$9 -> 0.026755147 | BK9: =$BG$9 -> 0.026755147 | BL9: =$BG$9 -> 0.026755147
B10: Franchise revenue | S10: ='Revenue Build - Franchising'!L36 -> 8.0865596 | T10: ='Revenue Build - Franchising'!M36 -> 2.377773 | U10: ='Revenue Build - Franchising'!N36 -> 2.609778 | V10: ='Revenue Build - Franchising'!O36 -> 2.8175746 | W10: ='Revenue Build - Franchising'!P36 -> 3.4212607 | X10: ='Revenue Build - Franchising'!Q36 -> 11.226386 | Y10: ='Revenue Build - Franchising'!R36 -> 3.3994821 | Z10: ='Revenue Build - Franchising'!S36 -> 3.4392507 | ... BL10: ='Revenue Build - Franchising'!BE36 -> 47.299832
B11: Total Revenue | N11: =N4+N8+N10 -> 1845.996 | O11: =O4+O8+O10 -> 472.817 | P11: =P4+P8+P10 -> 483.285 | Q11: =Q4+Q8+Q10 -> 481.076 | R11: =R4+R8+R10 -> 476.58 | S11: =S4+S8+S10 -> 2100.609 | T11: =T4+T8+T10 -> 556.07077 | U11: =U4+U8+U10 -> 561.47178 | ... BL11: =BL4+BL8+BL10 -> 5170.7023
B12: year-on-year growth (%) | BH12: =BH11/BG11-1 -> 0.099386872 | BI12: =BI11/BH11-1 -> 0.083658681 | BJ12: =BJ11/BI11-1 -> 0.082174247 | BK12: =BK11/BJ11-1 -> 0.081213463 | BL12: =BL11/BK11-1 -> 0.078455287
B14: Restaurant-level operating expenses
B15: Total number of restaurants (non franchise) | N15: ='Revenue Build - CK F.'!N12+'Revenue Build - FRC & Others'!N52 -> 177 | O15: ='Revenue Build - CK F.'!O12+'Revenue Build - FRC & Others'!O52 -> 177 | P15: ='Revenue Build - CK F.'!P12+'Revenue Build - FRC & Others'!P52 -> 179 | Q15: ='Revenue Build - CK F.'!Q12+'Revenue Build - FRC & Others'!Q52 -> 181 | R15: ='Revenue Build - CK F.'!R12+'Revenue Build - FRC & Others'!R52 -> 187 | S15: ='Revenue Build - CK F.'!S12+'Revenue Build - FRC & Others'!S52 -> 188 | T15: ='Revenue Build - CK F.'!T12+'Revenue Build - FRC & Others'!T52 -> 189 | U15: ='Revenue Build - CK F.'!U12+'Revenue Build - FRC & Others'!U52 -> 190 | ... AC15: ='Revenue Build - CK F.'!AC12+'Revenue Build - FRC & Others'!AC52 -> 213 | AH15: ='Revenue Build - CK F.'!AH12+'Revenue Build - North Italia'!AD12+'Revenue Build - FRC & Others'!AH52 -> 218 | AI15: ='Revenue Build - CK F.'!AI12+'Revenue Build - North Italia'!AE12+'Revenue Build - FRC & Others'!AI52 -> 218 | AJ15: ='Revenue Build - CK F.'!AJ12+'Revenue Build - North Italia'!AF12+'Revenue Build - FRC & Others'!AJ52 -> 219 | AK15: ='Revenue Build - CK F.'!AK12+'Revenue Build - North Italia'!AG12+'Revenue Build - FRC & Others'!AK52 -> 266 | AL15: ='Revenue Build - CK F.'!AL12+'Revenue Build - North Italia'!AH12+'Revenue Build - FRC & Others'!AL52 -> 292 | AM15: ='Revenue Build - CK F.'!AM12+'Revenue Build - North Italia'!AI12+'Revenue Build - FRC & Others'!AM52 -> 292 | AN15: ='Revenue Build - CK F.'!AN12+'Revenue Build - North Italia'!AJ12+'Revenue Build - FRC & Others'!AN52 -> 294 | AO15: ='Revenue Build - CK F.'!AO12+'Revenue Build - North Italia'!AK12+'Revenue Build - FRC & Others'!AO52 -> 294 | ... BL15: ='Revenue Build - CK F.'!BL12+'Revenue Build - North Italia'!BH12+'Revenue Build - FRC & Others'!BL52 -> 404.75136
B16: Labor expenses | J16: ='Cost Build - Aggregate'!J21 -> 0 | K16: ='Cost Build - Aggregate'!K21 -> 0 | L16: ='Cost Build - Aggregate'!L21 -> 0 | M16: ='Cost Build - Aggregate'!M21 -> 0 | N16: ='Cost Build - Aggregate'!N21 -> 646.102 | O16: ='Cost Build - Aggregate'!O21 -> 171.169 | P16: ='Cost Build - Aggregate'!P21 -> 168.495 | Q16: ='Cost Build - Aggregate'!Q21 -> 172.101 | ... BG16: ='Cost Build - Aggregate'!BG21 -> 1227.895 | BH16: =BH11*BH17 -> 1361.284 | BI16: =BI11*BI17 -> 1475.1672 | BJ16: =BJ11*BJ17 -> 1596.388 | BK16: =BK11*BK17 -> 1726.0362 | BL16: =BL11*BL17 -> 1861.4528
B17: Labor as % revenue | N17: =N16/N11 -> 0.35000184 | O17: =O16/O11 -> 0.36201956 | P17: =P16/P11 -> 0.34864521 | Q17: =Q16/Q11 -> 0.35774181 | R17: =R16/R11 -> 0.36311427 | S17: =S16/S11 -> 0.32600927 | T17: =T16/T11 -> 0.33387477 | U17: =U16/U11 -> 0.32986698 | ... BG17: =BG16/BG11 -> 0.3569978 | BH17: 0.36 | BI17: 0.36 | BJ17: 0.36 | BK17: 0.36 | BL17: 0.36
B18: F&B Cost of Sales | J18: ='Cost Build - Aggregate'!J20 -> 0 | K18: ='Cost Build - Aggregate'!K20 -> 0 | L18: ='Cost Build - Aggregate'!L20 -> 0 | M18: ='Cost Build - Aggregate'!M20 -> 0 | N18: ='Cost Build - Aggregate'!N20 -> 490.306 | O18: ='Cost Build - Aggregate'!O20 -> 126.612 | P18: ='Cost Build - Aggregate'!P20 -> 126.623 | Q18: ='Cost Build - Aggregate'!Q20 -> 125.605 | ... BG18: ='Cost Build - Aggregate'!BG20 -> 803.5 | BH18: =AVERAGE((AW18/AW15),(BB18/BB15),(BG18/BG15))*BH15 -> 817.70526 | BI18: =AVERAGE((BB18/BB15),(BG18/BG15),(BH18/BH15))*BI15 -> 883.97596 | BJ18: =AVERAGE((BG18/BG15),(BH18/BH15),(BI18/BI15))*BJ15 -> 902.14463 | BK18: =AVERAGE((BH18/BH15),(BI18/BI15),(BJ18/BJ15))*BK15 -> 937.90006 | BL18: =AVERAGE((BI18/BI15),(BJ18/BJ15),(BK18/BK15))*BL15 -> 980.97125
B19: G&A | N19: ='Cost Build - Aggregate'!N23 -> 119.094 | O19: ='Cost Build - Aggregate'!O23 -> 33.075 | P19: ='Cost Build - Aggregate'!P23 -> 35.345 | Q19: ='Cost Build - Aggregate'!Q23 -> 33.277 | R19: ='Cost Build - Aggregate'!R23 -> 35.705 | S19: ='Cost Build - Aggregate'!S23 -> 137.402 | T19: ='Cost Build - Aggregate'!T23 -> 35.337 | U19: ='Cost Build - Aggregate'!U23 -> 35.785 | ... BG19: ='Cost Build - Aggregate'!BG23 -> 217.449 | BH19: =AVERAGE((AW19/AW11),(BB19/BB11),(BG19/BG11))*BH11 -> 238.34054 | BI19: =AVERAGE((BB19/BB11),(BG19/BG11),(BH19/BH11))*BI11 -> 257.52801 | BJ19: =AVERAGE((BG19/BG11),(BH19/BH11),(BI19/BI11))*BJ11 -> 279.51402 | BK19: =AVERAGE((BH19/BH11),(BI19/BI11),(BJ19/BJ11))*BK11 -> 301.9137 | BL19: =AVERAGE((BI19/BI11),(BJ19/BJ11),(BK19/BK11))*BL11 -> 325.49636
B20: D&A | N20: ='Cost Build - Aggregate'!N24 -> 82.835 | O20: ='Cost Build - Aggregate'!O24 -> 21.177 | P20: ='Cost Build - Aggregate'!P24 -> 21.158 | Q20: ='Cost Build - Aggregate'!Q24 -> 21.317 | R20: ='Cost Build - Aggregate'!R24 -> 21.911 | S20: ='Cost Build - Aggregate'!S24 -> 85.563 | T20: ='Cost Build - Aggregate'!T24 -> 21.464 | U20: ='Cost Build - Aggregate'!U24 -> 21.461 | ... BG20: ='Cost Build - Aggregate'!BG24 -> 93.136 | BH20: ='Consolidated BS Build'!AX23 -> 93.136 | BI20: ='Consolidated BS Build'!AY23 -> 100.01489 | BJ20: ='Consolidated BS Build'!AZ23 -> 110.25205 | BK20: ='Consolidated BS Build'!BA23 -> 117.94024 | BL20: ='Consolidated BS Build'!BB23 -> 125.65273
B21: Other operating expense | N21: 478.504 | S21: 500.64 | X21: 540.365 | AC21: 552.791 | AH21: 566.825 | AM21: 631.613 | AR21: 616.069 | AW21: 792.311 | BB21: 881.627 | BG21: 922.428 | BH21: =AVERAGE((AW21/AW11),(BB21/BB11),(BG21/BG11))*BH11 -> 1015.5826 | BI21: =AVERAGE((BB21/BB11),(BG21/BG11),(BH21/BH11))*BI11 -> 1097.7266 | BJ21: =AVERAGE((BG21/BG11),(BH21/BH11),(BI21/BI11))*BJ11 -> 1189.3872 | BK21: =AVERAGE((BH21/BH11),(BI21/BI11),(BJ21/BJ11))*BK11 -> 1286.0313 | BL21: =AVERAGE((BI21/BI11),(BJ21/BJ11),(BK21/BK11))*BL11 -> 1386.3256
B22: EBIT | N22: =N11-SUM(N16:N21) -> 28.804998 | O22: =O11-SUM(O16:O21) -> 120.42198 | P22: =P11-SUM(P16:P21) -> 131.31535 | Q22: =Q11-SUM(Q16:Q21) -> 128.41826 | R22: =R11-SUM(R16:R21) -> 120.35689 | S22: =S11-SUM(S16:S21) -> 187.82899 | T22: =T11-SUM(T16:T21) -> 182.5049 | U22: =U11-SUM(U16:U21) -> 191.75191 | ... BL22: =BL11-SUM(BL16:BL21) -> 490.44355
B23: Adjusted EBIT (No Adjustments)
B25: Add back: D&A | N25: =N20 -> 82.835 | O25: =O20 -> 21.177 | P25: =P20 -> 21.158 | Q25: =Q20 -> 21.317 | R25: =R20 -> 21.911 | S25: =S20 -> 85.563 | T25: =T20 -> 21.464 | U25: =U20 -> 21.461 | ... BL25: =BL20 -> 125.65273
B26: Add back: SBC | N26: =Historicals!P639 -> 16.817 | O26: =Historicals!Q639 -> 4.731 | P26: =Historicals!R639 -> 4.946 | Q26: =Historicals!S639 -> 4.872 | R26: =Historicals!T639 -> 5.504 | S26: =Historicals!U639 -> 20.053 | T26: =Historicals!V639 -> 5.185 | U26: =Historicals!W639 -> 6.119 | ... BG26: =Historicals!BI639 -> 25.781 | BH26: =AVERAGE((AW26/AW16),(BB26/BB16),(BG26/BG16))*BH16 -> 28.397224 | BI26: =AVERAGE((BB26/BB16),(BG26/BG16),(BH26/BH16))*BI16 -> 30.492194 | BJ26: =AVERAGE((BG26/BG16),(BH26/BH16),(BI26/BI16))*BJ16 -> 33.272473 | BK26: =AVERAGE((BH26/BH16),(BI26/BI16),(BJ26/BJ16))*BK16 -> 35.886188 | BL26: =AVERAGE((BI26/BI16),(BJ26/BJ16),(BK26/BK16))*BL16 -> 38.658514
B27: EBITDA | N27: =N22+N25 -> 111.64 | O27: =O22+O25 -> 141.59898 | P27: =P22+P25 -> 152.47335 | Q27: =Q22+Q25 -> 149.73526 | R27: =R22+R25 -> 142.26789 | S27: =S22+S25 -> 273.39199 | T27: =T22+T25 -> 203.9689 | U27: =U22+U25 -> 213.21291 | ... BL27: =BL22+BL25 -> 616.09628
B28: Adjusted EBITDA (No Adjustments)
B30: Interest expense | N30: 6.187 | O30: 1.895 | P30: 1.432 | Q30: 0.722 | R30: 1.845 | S30: 5.894 | T30: 2.304 | U30: 2.181 | V30: 2.477 | W30: 2.263 | X30: 9.225 | Y30: 1.256 | Z30: 1.57 | AA30: 1.6 | AB30: 1.953 | AC30: 6.379 | AD30: 1.506 | AE30: 2.908 | AF30: 3.29 | AG30: 1.765 | AH30: 6.783 | AI30: -0.002 | AJ30: 0.025 | AK30: -0.006 | AL30: 2.48 | AM30: 2.497 | AN30: 1.518 | AO30: 2.566 | AP30: 2.935 | AQ30: 1.58 | AR30: 8.599 | AS30: 2.694 | AT30: 4.706 | AU30: 1.794 | AV30: 1.504 | AW30: 10.698 | AX30: 1.461 | AY30: 1.13 | AZ30: 1.315 | BA30: 2.137 | BB30: 6.043 | BC30: 1.88 | BD30: 2.162 | BE30: 2.027 | BF30: 2.483 | BG30: 8.552
B31: EBT | N31: =N22-N30 -> 22.617998 | O31: =O22-O30 -> 118.52698 | P31: =P22-P30 -> 129.88335 | Q31: =Q22-Q30 -> 127.69626 | R31: =R22-R30 -> 118.51189 | S31: =S22-S30 -> 181.93499 | T31: =T22-T30 -> 180.2009 | U31: =U22-U30 -> 189.57091 | ... BG31: =BG22-BG30 -> 166.186
B33: Current tax | N33: 37.064 | O33: 9.521 | P33: 13.666 | Q33: 9.217 | R33: 9.241 | S33: 41.645 | T33: 9.175 | U33: 16.372 | V33: 13.661 | W33: 14.071 | X33: 53.279 | Y33: 4.078 | Z33: 11.404 | AA33: 7.397 | AB33: -8.625 | AC33: 14.254 | AD33: 2.859 | AE33: 3.634 | AF33: 1.619 | AG33: 5.774 | AH33: 13.886 | AI33: -0.076 | AJ33: 7.001 | AK33: 0.886 | AL33: 7.427 | AM33: 15.238 | AN33: -44.182 | AO33: -29.795 | AP33: 32.359 | AQ33: 6.175 | AR33: -35.443 | AS33: 3.79 | AT33: 4.084 | AU33: -0.765 | AV33: 12.987 | AW33: 20.096 | AX33: -0.172 | AY33: 4.746 | AZ33: 1.79 | BA33: 2.051 | BB33: 8.415 | BC33: 0.804 | BD33: 3.357 | BE33: -0.086 | BF33: 10.303 | BG33: 14.378
B34: Net Income to Common Shareholders | N34: =N31-N33 -> -14.446002 | O34: =O31-O33 -> 109.00598 | P34: =P31-P33 -> 116.21735 | Q34: =Q31-Q33 -> 118.47926 | R34: =R31-R33 -> 109.27089 | S34: =S31-S33 -> 140.28999 | T34: =T31-T33 -> 171.0259 | U34: =U31-U33 -> 173.19891 | ... BG34: =BG31-BG33 -> 151.808

Sheet Consolidated BS Build
D2: FY2014 | E2: Q1-2015 | F2: Q2-2015 | G2: Q3-2015 | H2: Q4-2015 | I2: FY2015 | J2: Q1-2016 | K2: Q2-2016 | L2: Q3-2016 | M2: Q4-2016 | N2: FY2016 | O2: Q1-2017 | P2: Q2-2017 | Q2: Q3-2017 | R2: Q4-2017 | S2: FY2017 | T2: Q1-2018 | U2: Q2-2018 | V2: Q3-2018 | W2: Q4-2018 | X2: FY2018 | Y2: Q1-2019 | Z2: Q2-2019 | AA2: Q3-2019 | AB2: Q4-2019 | AC2: FY2019 | AD2: Q1-2020 | AE2: Q2-2020 | AF2: Q3-2020 | AG2: Q4-2020 | AH2: FY2020 | AI2: Q1-2021 | AJ2: Q2-2021 | AK2: Q3-2021 | AL2: Q4-2021 | AM2: FY2021 | AN2: Q1-2022 | AO2: Q2-2022 | AP2: Q3-2022 | AQ2: Q4-2022 | AR2: FY2022 | AS2: Q1-2023 | AT2: Q2-2023 | AU2: Q3-2023 | AV2: Q4-2023 | AW2: FY2023 | AX2: FY2024E | AY2: FY2025E | AZ2: FY2026E | BA2: FY2027E | BB2: FY2028E
B5: Net Working Capital
B6: Accounts Receivable | D6: 77.497 | E6: 42.335 | F6: 42.224 | G6: 45.87 | H6: 86.817 | I6: 86.817 | J6: 43.667 | K6: 41.618 | L6: 44.715 | M6: 80.224 | N6: 80.224 | O6: 44.788 | P6: 48.815 | Q6: 47.092 | R6: 87.383 | S6: 87.383 | T6: 42.724 | U6: 49.621 | V6: 50.901 | W6: 89.121 | X6: 89.121 | Y6: 46.188 | Z6: 47.671 | AA6: 47.801 | AB6: 90.302 | AC6: 90.302 | AD6: 50.145 | AE6: 48.584 | AF6: 51.733 | AG6: 75.787 | AH6: 75.787 | AI6: 57.815 | AJ6: 57.934 | AK6: 66.663 | AL6: 100.504 | AM6: 100.504 | AN6: 66.451 | AO6: 71.338 | AP6: 67.661 | AQ6: 105.511 | AR6: 105.511 | AS6: 68.456 | AT6: 71.366 | AU6: 70.236 | AV6: 103.094 | AW6: 103.094 | AX6: ='Consolidated IS Build'!BH11*'Consolidated BS Build'!AX7 -> 129.19581 | AY6: ='Consolidated IS Build'!BI11*'Consolidated BS Build'!AY7 -> 138.19627 | AZ6: ='Consolidated IS Build'!BJ11*'Consolidated BS Build'!AZ7 -> 145.5716 | BA6: ='Consolidated IS Build'!BK11*'Consolidated BS Build'!BA7 -> 155.95292 | BB6: ='Consolidated IS Build'!BL11*'Consolidated BS Build'!BB7 -> 168.79288
B7: % Revenue | D7: =D6/'Consolidated IS Build'!$N$11 -> 0.041981131 | H7: =H6/'Consolidated IS Build'!N11 -> 0.047029896 | I7: =I6/'Consolidated IS Build'!$S$11 -> 0.041329443 | N7: =N6/'Consolidated IS Build'!$X$11 -> 0.035252155 | S7: =S6/'Consolidated IS Build'!$AC$11 -> 0.038656458 | X7: =X6/'Consolidated IS Build'!$AH$11 -> 0.038211129 | AC7: =AC6/'Consolidated IS Build'!$AM$11 -> 0.036372615 | AH7: =AH6/'Consolidated IS Build'!$AR$11 -> 0.03821402 | AM7: =AM6/'Consolidated IS Build'!$AW$11 -> 0.03433053 | AR7: =AR6/'Consolidated IS Build'!$BB$11 -> 0.031942482 | AW7: =AW6/'Consolidated IS Build'!$BG$11 -> 0.029973517 | AX7: =AVERAGE(AC7,AH7,AM7,AR7,AW7) -> 0.034166633 | AY7: =AVERAGE(AX7,AW7,AR7,AM7,AH7) -> 0.033725436 | AZ7: =AVERAGE(AY7,AX7,AW7,AR7,AM7) -> 0.032827719 | BA7: =AVERAGE(AZ7,AY7,AX7,AW7,AR7) -> 0.032527157 | BB7: =AVERAGE(BA7,AZ7,AY7,AX7,AW7) -> 0.032644092
B8: Inventory | D8: 33.255 | E8: 32.525 | F8: 36.466 | G8: 36.742 | H8: 34.01 | I8: 34.01 | J8: 35.543 | K8: 34.571 | L8: 35.541 | M8: 34.926 | N8: 34.926 | O8: 38.541 | P8: 40.246 | Q8: 44.195 | R8: 42.56 | S8: 42.56 | T8: 40.959 | U8: 34.691 | V8: 39.769 | W8: 38.886 | X8: 38.886 | Y8: 42.028 | Z8: 46.011 | AA8: 47.778 | AB8: 47.225 | AC8: 47.225 | AD8: 47.822 | AE8: 40.511 | AF8: 37.727 | AG8: 39.288 | AH8: 39.288 | AI8: 38.955 | AJ8: 41.868 | AK8: 43.27 | AL8: 42.839 | AM8: 42.839 | AN8: 46.68 | AO8: 52.286 | AP8: 62.275 | AQ8: 55.559 | AR8: 55.559 | AS8: 58.989 | AT8: 60.868 | AU8: 58.672 | AV8: 57.654 | AW8: 57.654 | AX8: ='Consolidated IS Build'!BH11*AX9 -> 65.831115 | AY8: ='Consolidated IS Build'!BI11*AY9 -> 70.017165 | AZ8: ='Consolidated IS Build'!BJ11*AZ9 -> 73.35565 | BA8: ='Consolidated IS Build'!BK11*BA9 -> 81.143924 | BB8: ='Consolidated IS Build'!BL11*BB9 -> 87.617896
B9: % Revenue | D9: =D8/'Consolidated IS Build'!$N$11 -> 0.018014665 | H9: =H8/'Consolidated IS Build'!N11 -> 0.018423659 | I9: =I8/'Consolidated IS Build'!$S$11 -> 0.016190543 | N9: =N8/'Consolidated IS Build'!$X$11 -> 0.015347238 | S9: =S8/'Consolidated IS Build'!$AC$11 -> 0.018827676 | X9: =X8/'Consolidated IS Build'!$AH$11 -> 0.016672591 | AC9: =AC8/'Consolidated IS Build'!$AM$11 -> 0.019021691 | AH9: =AH8/'Consolidated IS Build'!$AR$11 -> 0.019810158 | AM9: =AM8/'Consolidated IS Build'!$AW$11 -> 0.014633105 | AR9: =AR8/'Consolidated IS Build'!$BB$11 -> 0.016819975 | AW9: =AW8/'Consolidated IS Build'!$BG$11 -> 0.016762305 | AX9: =AVERAGE(AC9,AH9,AM9,AR9,AW9) -> 0.017409447 | AY9: =AVERAGE(AX9,AW9,AR9,AM9,AH9) -> 0.017086998 | AZ9: =AVERAGE(AY9,AX9,AW9,AR9,AM9) -> 0.016542366 | BA9: =AVERAGE(AZ9,AY9,AX9,AW9,AR9) -> 0.016924218 | BB9: =AVERAGE(BA9,AZ9,AY9,AX9,AW9) -> 0.016945067
B10: Accounts Payable | D10: 57.325 | E10: 54.152 | F10: 52.171 | G10: 44.208 | H10: 47.77 | I10: 47.77 | J10: 38.363 | K10: 38.573 | L10: 38.906 | M10: 41.564 | N10: 41.564 | O10: 34.937 | P10: 46.219 | Q10: 46.572 | R10: 50.984 | S10: 50.984 | T10: 38.805 | U10: 38.312 | V10: 39.13 | W10: 49.071 | X10: 49.071 | Y10: 36.394 | Z10: 35.96 | AA10: 36.095 | AB10: 61.946 | AC10: 61.946 | AD10: 55.894 | AE10: 57.532 | AF10: 61.549 | AG10: 58.432 | AH10: 58.432 | AI10: 56.047 | AJ10: 55.377 | AK10: 52.89 | AL10: 54.086 | AM10: 54.086 | AN10: 61.741 | AO10: 58.927 | AP10: 59.03 | AQ10: 66.638 | AR10: 66.638 | AS10: 57.001 | AT10: 72.682 | AU10: 53.392 | AV10: 63.152 | AW10: 63.152 | AX10: ='Consolidated IS Build'!BH11*AX11 -> 84.266499 | AY10: ='Consolidated IS Build'!BI11*AY11 -> 89.130955 | AZ10: ='Consolidated IS Build'!BJ11*AZ11 -> 89.615951 | BA10: ='Consolidated IS Build'!BK11*BA11 -> 98.557022 | BB10: ='Consolidated IS Build'!BL11*BB11 -> 106.68442
B11: % Revenue | D11: =D10/'Consolidated IS Build'!$N$11 -> 0.031053697 | H11: =H10/'Consolidated IS Build'!N11 -> 0.025877629 | I11: =I10/'Consolidated IS Build'!$S$11 -> 0.022741024 | N11: =N10/'Consolidated IS Build'!$X$11 -> 0.018264118 | S11: =S10/'Consolidated IS Build'!$AC$11 -> 0.022554282 | X11: =X10/'Consolidated IS Build'!$AH$11 -> 0.021039467 | AC11: =AC10/'Consolidated IS Build'!$AM$11 -> 0.024951142 | AH11: =AH10/'Consolidated IS Build'!$AR$11 -> 0.029463122 | AM11: =AM10/'Consolidated IS Build'!$AW$11 -> 0.018474897 | AR11: =AR10/'Consolidated IS Build'!$BB$11 -> 0.02017404 | AW11: =AW10/'Consolidated IS Build'!$BG$11 -> 0.018360792 | AX11: =AVERAGE(AC11,AH11,AM11,AR11,AW11) -> 0.022284799 | AY11: =AVERAGE(AX11,AW11,AR11,AM11,AH11) -> 0.02175153 | AZ11: =AVERAGE(AY11,AX11,AW11,AR11,AM11) -> 0.020209211 | BA11: =AVERAGE(AZ11,AY11,AX11,AW11,AR11) -> 0.020556074 | BB11: =AVERAGE(BA11,AZ11,AY11,AX11,AW11) -> 0.020632481
B12: Prepaid Expenses | D12: 38.233 | E12: 46.579 | F12: 46.622 | G12: 44.08 | H12: 41.976 | I12: 41.976 | J12: 40.637 | K12: 37.824 | L12: 36.337 | M12: 52.438 | N12: 52.438 | O12: 52.585 | P12: 50.919 | Q12: 48.521 | R12: 57.666 | S12: 57.666 | T12: 54.036 | U12: 52.946 | V12: 48.327 | W12: 40.645 | X12: 40.645 | Y12: 46.771 | Z12: 39.524 | AA12: 38.895 | AB12: 43.946 | AC12: 43.946 | AD12: 42.489 | AE12: 36.342 | AF12: 32.188 | AG12: 35.31 | AH12: 35.31 | AI12: 30.727 | AJ12: 32.039 | AK12: 29.714 | AL12: 36.446 | AM12: 36.446 | AN12: 33.741 | AO12: 33.373 | AP12: 30.953 | AQ12: 48.399 | AR12: 48.399 | AS12: 48.387 | AT12: 52.641 | AU12: 55.558 | AV12: 63.09 | AW12: 63.09 | AX12: ='Consolidated IS Build'!BH11*AX13 -> 61.219784 | AY12: ='Consolidated IS Build'!BI11*AY13 -> 65.103033 | AZ12: ='Consolidated IS Build'!BJ11*AZ13 -> 68.753044 | BA12: ='Consolidated IS Build'!BK11*BA13 -> 77.266256 | BB12: ='Consolidated IS Build'!BL11*BB13 -> 84.841254
B13: % Revenue | D13: =D12/'Consolidated IS Build'!$N$11 -> 0.020711312 | H13: =H12/'Consolidated IS Build'!N11 -> 0.022738944 | I13: =I12/'Consolidated IS Build'!$S$11 -> 0.019982776 | N13: =N12/'Consolidated IS Build'!$X$11 -> 0.023042388 | S13: =S12/'Consolidated IS Build'!$AC$11 -> 0.025510263 | X13: =X12/'Consolidated IS Build'!$AH$11 -> 0.017426772 | AC13: =AC12/'Consolidated IS Build'!$AM$11 -> 0.017700947 | AH13: =AH12/'Consolidated IS Build'!$AR$11 -> 0.017804334 | AM13: =AM12/'Consolidated IS Build'!$AW$11 -> 0.01244936 | AR13: =AR12/'Consolidated IS Build'!$BB$11 -> 0.014652351 | AW13: =AW12/'Consolidated IS Build'!$BG$11 -> 0.018342766 | AX13: =AVERAGE(AC13,AH13,AM13,AR13,AW13) -> 0.016189952 | AY13: =AVERAGE(AX13,AW13,AR13,AM13,AH13) -> 0.015887753 | AZ13: =AVERAGE(AY13,AX13,AW13,AR13,AM13) -> 0.015504436 | BA13: =AVERAGE(AZ13,AY13,AX13,AW13,AR13) -> 0.016115452 | BB13: =AVERAGE(BA13,AZ13,AY13,AX13,AW13) -> 0.016408072
B14: Accrued Expenses | D14: 264.686 | E14: 243.623 | F14: 246.07 | G14: 246.428 | H14: 302.456 | I14: 302.456 | J14: 267.857 | K14: 265.851 | L14: 265.197 | M14: 179.034 | N14: 179.034 | O14: 155.081 | P14: 160.046 | Q14: 159.823 | R14: 183.016 | S14: 183.016 | T14: 167.367 | U14: 182.659 | V14: 179.062 | W14: 194.381 | X14: 194.381 | Y14: 171.315 | Z14: 172.973 | AA14: 172.098 | AB14: 236.582 | AC14: 236.582 | AD14: 166.828 | AE14: 192.549 | AF14: 194.575 | AG14: 210.461 | AH14: 210.461 | AI14: 203.211 | AJ14: 241.488 | AK14: 210.155 | AL14: 239.187 | AM14: 239.187 | AN14: 202.217 | AO14: 237.453 | AP14: 225 | AQ14: 231.133 | AR14: 231.133 | AS14: 237.293 | AT14: 220.917 | AU14: 240.44 | AV14: 239.699 | AW14: 239.699 | AX14: ='Consolidated IS Build'!BH11*AX15 -> 319.73452 | AY14: ='Consolidated IS Build'!BI11*AY15 -> 337.68393 | AZ14: ='Consolidated IS Build'!BJ11*AZ15 -> 344.40296 | BA14: ='Consolidated IS Build'!BK11*BA15 -> 368.50258 | BB14: ='Consolidated IS Build'!BL11*BB15 -> 404.53397
B15: % Revenue | D15: =D14/'Consolidated IS Build'!$N$11 -> 0.14338384 | H15: =H14/'Consolidated IS Build'!N11 -> 0.16384434 | I15: =I14/'Consolidated IS Build'!$S$11 -> 0.14398491 | N15: =N14/'Consolidated IS Build'!$X$11 -> 0.0786714 | S15: =S14/'Consolidated IS Build'!$AC$11 -> 0.080962547 | X15: =X14/'Consolidated IS Build'!$AH$11 -> 0.083341944 | AC15: =AC14/'Consolidated IS Build'!$AM$11 -> 0.095292529 | AH15: =AH14/'Consolidated IS Build'!$AR$11 -> 0.10612059 | AM15: =AM14/'Consolidated IS Build'!$AW$11 -> 0.081702385 | AR15: =AR14/'Consolidated IS Build'!$BB$11 -> 0.069973383 | AW15: =AW14/'Consolidated IS Build'!$BG$11 -> 0.06969001 | AX15: =AVERAGE(AC15,AH15,AM15,AR15,AW15) -> 0.084555779 | AY15: =AVERAGE(AX15,AW15,AR15,AM15,AH15) -> 0.082408429 | AZ15: =AVERAGE(AY15,AX15,AW15,AR15,AM15) -> 0.077665997 | BA15: =AVERAGE(AZ15,AY15,AX15,AW15,AR15) -> 0.07685872 | BB15: =AVERAGE(BA15,AZ15,AY15,AX15,AW15) -> 0.078235787
B17: Change in NWC
B18: Cash Change | I18: =-(I6-D6)-(I8-D8)+(I10-D10)+(I12-D12)+(I14-D14) -> 21.883 | J18: =-(J6-E6)-(J8-E8)+(J10-E10)+(J12-E12)+(J14-E14) -> -1.847 | K18: =-(K6-F6)-(K8-F8)+(K10-F10)+(K12-F12)+(K14-F14) -> -0.114 | L18: =-(L6-G6)-(L8-G8)+(L10-G10)+(L12-G12)+(L14-G14) -> 8.08 | M18: =-(M6-H6)-(M8-H8)+(M10-H10)+(M12-H12)+(M14-H14) -> -113.489 | N18: =-(N6-I6)-(N8-I8)+(N10-I10)+(N12-I12)+(N14-I14) -> -113.489 | O18: =-(O6-J6)-(O8-J8)+(O10-J10)+(O12-J12)+(O14-J14) -> -108.373 | P18: =-(P6-K6)-(P8-K8)+(P10-K10)+(P12-K12)+(P14-K14) -> -97.936 | ... AW18: =-(AW6-AR6)-(AW8-AR8)+(AW10-AR10)+(AW12-AR12)+(AW14-AR14) -> 20.093 | AX18: =-(AX6-AW6)-(AX8-AW8)+(AX10-AW10)+(AX12-AW12)+(AX14-AW14) -> 65.000886 | AY18: =-(AY6-AX6)-(AY8-AX8)+(AY10-AX10)+(AY12-AX12)+(AY14-AX14) -> 13.51059 | AZ18: =-(AZ6-AY6)-(AZ8-AY8)+(AZ10-AY10)+(AZ12-AY12)+(AZ14-AY14) -> 0.1402224 | BA18: =-(BA6-AZ6)-(BA8-AZ8)+(BA10-AZ10)+(BA12-AZ12)+(BA14-AZ14) -> 23.384323 | BB18: =-(BB6-BA6)-(BB8-BA8)+(BB10-BA10)+(BB12-BA12)+(BB14-BA14) -> 32.419836
B20: CapEx | D20: 113.982 | E20: -24.151 | F20: -59.473 | G20: -108.593 | H20: =I20 -> 153.941 | I20: 153.941 | J20: -22.441 | K20: -40.208 | L20: -70.607 | M20: =N20 -> 115.821 | N20: 115.821 | O20: -19.223 | P20: -43.699 | Q20: -73.417 | R20: =S20 -> 120.779 | S20: 120.779 | T20: -30.688 | U20: -51.87 | V20: -78.716 | W20: =X20 -> 102.909 | X20: 102.909 | Y20: -13.351 | Z20: -29.371 | AA20: -46.702 | AB20: =AC20 -> 73.765 | AC20: 73.765 | AD20: -15.775 | AE20: -29.424 | AF20: -38.27 | AG20: =AH20 -> 50.329 | AH20: 50.329 | AI20: -7.227 | AJ20: -30.902 | AK20: -49.158 | AL20: =AM20 -> 66.943 | AM20: 66.943 | AN20: -29.093 | AO20: -46.382 | AP20: -78.053 | AQ20: =AR20 -> 112.464 | AR20: 112.464 | AS20: -37.962 | AT20: -62.66 | AU20: -99.923 | AV20: =AW20 -> 151.565 | AW20: 151.565 | AX20: ='Valuation and Cash Flow'!L24 -> 180.09 | AY20: ='Valuation and Cash Flow'!M24 -> 165.318 | AZ20: ='Valuation and Cash Flow'!N24 -> 175.7616 | BA20: ='Valuation and Cash Flow'!O24 -> 195.19392 | BB20: ='Valuation and Cash Flow'!P24 -> 193.9217
B21: % Revenue | H21: =H20/'Consolidated IS Build'!N11 -> 0.083391838 | I21: =I20/'Consolidated IS Build'!O11 -> 0.32558262 | J21: =J20/'Consolidated IS Build'!P11 -> -0.046434299 | K21: =K20/'Consolidated IS Build'!Q11 -> -0.08357931 | L21: =L20/'Consolidated IS Build'!R11 -> -0.14815351 | M21: =M20/'Consolidated IS Build'!S11 -> 0.055136867 | N21: =N20/'Consolidated IS Build'!T11 -> 0.20828464 | O21: =O20/'Consolidated IS Build'!U11 -> -0.034236805 | ... BB21: =BB20/'Consolidated IS Build'!BH11 -> 0.051283798
B23: D&A | D23: 82.835 | E23: 21.177 | F23: 42.335 | G23: 63.652 | H23: =I23 -> 85.563 | I23: 85.563 | J23: 21.464 | K23: 42.925 | L23: 64.559 | M23: =N23 -> 88.01 | N23: 88.01 | O23: 23.196 | P23: 46.493 | Q23: 69.492 | R23: =S23 -> 92.729 | S23: 92.729 | T23: 24.002 | U23: 47.729 | V23: 71.819 | W23: =X23 -> 95.976 | X23: 95.976 | Y23: 21.362 | Z23: 43.021 | AA23: 64.363 | AB23: =AC23 -> 88.133 | AC23: 88.133 | AD23: 23.562 | AE23: 46.152 | AF23: 68.803 | AG23: =AH23 -> 91.415 | AH23: 91.415 | AI23: 22.006 | AJ23: 44.229 | AK23: 66.805 | AL23: =AM23 -> 89.654 | AM23: 89.654 | AN23: 21.505 | AO23: 44.113 | AP23: 66.764 | AQ23: =AR23 -> 92.38 | AR23: 92.38 | AS23: 22.955 | AT23: 46.287 | AU23: 69.124 | AV23: =AW23 -> 93.136 | AW23: 93.136 | AX23: =AX25*AW26 -> 93.136 | AY23: =AY25*AX26 -> 100.01489 | AZ23: =AZ25*AY26 -> 110.25205 | BA23: =BA25*AZ26 -> 117.94024 | BB23: =BB25*BA26 -> 125.65273
B24: % CapEx | H24: =H23/H20 -> 0.55581684 | I24: =I23/I20 -> 0.55581684 | J24: =J23/J20 -> -0.95646362 | K24: =K23/K20 -> -1.0675736 | L24: =L23/L20 -> -0.91434277 | M24: =M23/M20 -> 0.75987947 | N24: =N23/N20 -> 0.75987947 | O24: =O23/O20 -> -1.2066795 | ... AW24: =AW23/AW20 -> 0.61449543
B25: % PP&E | H25: =H23/G26 -> 0.0978601 | I25: =I23/H26 -> 0.095902111 | J25: =J23/I26 -> 0.024057629 | K25: =K23/J26 -> 0.04845005 | L25: =L23/K26 -> 0.072632134 | M25: =M23/L26 -> 0.097509254 | N25: =N23/M26 -> 0.096700046 | O25: =O23/N26 -> 0.025486357 | ... AW25: =AW23/AV26 -> 0.11773079 | AX25: =$AW$25 -> 0.11773079 | AY25: =$AW$25 -> 0.11773079 | AZ25: =$AW$25 -> 0.11773079 | BA25: =$AW$25 -> 0.11773079 | BB25: =$AW$25 -> 0.11773079
B26: PP&E | E26: =Historicals!Q724 -> 828.966 | F26: =Historicals!R724 -> 851.477 | G26: =Historicals!S724 -> 874.34 | H26: =Historicals!T724 -> 892.191 | I26: =Historicals!U724 -> 892.191 | J26: =Historicals!V724 -> 885.964 | K26: =Historicals!W724 -> 888.849 | L26: =Historicals!X724 -> 902.581 | ... AW26: =Historicals!BI724 -> 791.093 | AX26: =AW26-AW23+'Consolidated BS Build'!AW20 -> 849.522 | AY26: =AX26-AX23+'Consolidated BS Build'!AX20 -> 936.476 | AZ26: =AY26-AY23+'Consolidated BS Build'!AY20 -> 1001.7791 | BA26: =AZ26-AZ23+'Consolidated BS Build'!AZ20 -> 1067.2887 | BB26: =BA26-BA23+'Consolidated BS Build'!BA20 -> 1144.5423

Sheet Revenue Build - CK F.
N2: Actual
B4: Period Ended | J4: 41730 | K4: 41821 | L4: 41912 | M4: 42003 | N4: 42003 | O4: 42094 | P4: 42185 | Q4: 42276 | R4: 42367 | S4: 42367 | T4: 42458 | U4: 42549 | V4: 42640 | W4: 42738 | X4: 42738 | Y4: 42829 | Z4: 42920 | AA4: 43011 | AB4: 43102 | AC4: 43102 | AD4: 43193 | AE4: 43284 | AF4: 43375 | AG4: 43466 | AH4: 43466 | AI4: 43557 | AJ4: 43648 | AK4: 43739 | AL4: 43830 | AM4: 43830 | AN4: 43921 | AO4: 44012 | AP4: 44103 | AQ4: 44194 | AR4: 44194 | AS4: 44285 | AT4: 44376 | AU4: 44467 | AV4: 44558 | AW4: 44558 | AX4: 44649 | AY4: 44740 | AZ4: 44831 | BA4: 44929 | BB4: 44929 | BC4: 45019 | BD4: 45111 | BE4: 45202 | BF4: 45293 | BG4: 45293
J5: Q1-2014 | K5: Q2-2014 | L5: Q3-2014 | M5: Q4-2014 | N5: FY2014 | O5: Q1-2015 | P5: Q2-2015 | Q5: Q3-2015 | R5: Q4-2015 | S5: FY2015 | T5: Q1-2016 | U5: Q2-2016 | V5: Q3-2016 | W5: Q4-2016 | X5: FY2016 | Y5: Q1-2017 | Z5: Q2-2017 | AA5: Q3-2017 | AB5: Q4-2017 | AC5: FY2017 | AD5: Q1-2018 | AE5: Q2-2018 | AF5: Q3-2018 | AG5: Q4-2018 | AH5: FY2018 | AI5: Q1-2019 | AJ5: Q2-2019 | AK5: Q3-2019 | AL5: Q4-2019 | AM5: FY2019 | AN5: Q1-2020 | AO5: Q2-2020 | AP5: Q3-2020 | AQ5: Q4-2020 | AR5: FY2020 | AS5: Q1-2021 | AT5: Q2-2021 | AU5: Q3-2021 | AV5: Q4-2021 | AW5: FY2021 | AX5: Q1-2022 | AY5: Q2-2022 | AZ5: Q3-2022 | BA5: Q4-2022 | BB5: FY2022 | BC5: Q1-2023 | BD5: Q2-2023 | BE5: Q3-2023 | BF5: Q4-2023 | BG5: FY2023 | BH5: FY2024E | BI5: FY2025E | BJ5: FY2026E | BK5: FY2027E | BL5: FY2028E
B7: Cheesecake Factory Revenue Build
B9: The Cheesecake Factory restaurants - BoP, # of restaurants | J9: 168 | K9: =J12 -> 169 | L9: =K12 -> 170 | M9: =L12 -> 172 | N9: =J12 -> 169 | O9: =N12 -> 177 | P9: =O12 -> 177 | Q9: =P12 -> 179 | R9: =Q12 -> 181 | S9: =N12 -> 177 | T9: =S12 -> 187 | U9: =T12 -> 188 | V9: =U12 -> 189 | W9: =V12 -> 189 | X9: =S12 -> 187 | Y9: =X12 -> 194 | Z9: =Y12 -> 194 | AA9: =Z12 -> 193 | AB9: =AA12 -> 194 | AC9: =X12 -> 194 | AD9: =AC12 -> 199 | AE9: =AD12 -> 199 | AF9: =AE12 -> 198 | AG9: =AF12 -> 199 | AH9: =AC12 -> 199 | AI9: =AH12 -> 201 | AJ9: =AI12 -> 201 | AK9: =AJ12 -> 202 | AL9: =AK12 -> 203 | AM9: =AH12 -> 201 | AN9: =AM12 -> 206 | AO9: =AN12 -> 206 | AP9: =AO12 -> 206 | AQ9: =AP12 -> 205 | AR9: =AM12 -> 206 | AS9: =AR12 -> 206 | AT9: =AS12 -> 207 | AU9: =AT12 -> 207 | AV9: =AU12 -> 207 | AW9: =AR12 -> 206 | AX9: =AW12 -> 208 | AY9: =AX12 -> 208 | AZ9: =AY12 -> 208 | BA9: =AZ12 -> 209 | BB9: =AW12 -> 208 | BC9: =BB12 -> 211 | BD9: =BC12 -> 210 | BE9: =BD12 -> 211 | BF9: =BE12 -> 213 | BG9: =BB12 -> 211 | BH9: =BG12 -> 216 | BI9: =BH12 -> 219.6 | BJ9: =BI12 -> 224.12 | BK9: =BJ12 -> 228.744 | BL9: =BK12 -> 234.2928
B10: CF restaurants opened, # of restaurants | J10: 1 | K10: 2 | L10: 2 | M10: 5 | N10: 10 | O10: 0 | P10: 2 | Q10: 2 | R10: 6 | S10: 10 | T10: 1 | U10: 1 | V10: 0 | W10: 5 | X10: 7 | Y10: 0 | Z10: 1 | AA10: 1 | AB10: 5 | AC10: 7 | AD10: 0 | AE10: 0 | AF10: 1 | AG10: 3 | AH10: 4 | AI10: 0 | AJ10: 1 | AK10: 1 | AL10: 3 | AM10: =SUM(AI10,AJ10,AK10,AL10) -> 5 | AN10: 0 | AO10: 0 | AP10: 0 | AQ10: 1 | AR10: =SUM(AN10,AO10,AP10,AQ10) -> 1 | AS10: 1 | AT10: 0 | AU10: 0 | AV10: 1 | AW10: =SUM(AS10,AT10,AU10,AV10) -> 2 | AX10: 0 | AY10: 0 | AZ10: 1 | BA10: 2 | BB10: =SUM(AX10,AY10,AZ10,BA10) -> 3 | BC10: 0 | BD10: 1 | BE10: 2 | BF10: 3 | BG10: =SUM(BC10,BD10,BE10,BF10) -> 6 | BH10: ='Forecast Assumptions'!G9 -> 4 | BI10: ='Forecast Assumptions'!H9 -> 5 | BJ10: ='Forecast Assumptions'!I9 -> 5 | BK10: ='Forecast Assumptions'!J9 -> 6 | BL10: ='Forecast Assumptions'!K9 -> 6
B11: CF restaurants closed, # of restaurants | J11: =J12-J9-J10 -> 0 | K11: =K12-K9-K10 -> -1 | L11: =L12-L9-L10 -> 0 | M11: =M12-M9-M10 -> 0 | N11: =-(N10-(N12-N9)) -> -2 | O11: =O12-O9-O10 -> 0 | P11: =P12-P9-P10 -> 0 | Q11: =Q12-Q9-Q10 -> 0 | R11: =R12-R9-R10 -> 0 | S11: =-(S10-(S12-S9)) -> 0 | T11: =T12-T9-T10 -> 0 | U11: =U12-U9-U10 -> 0 | V11: =V12-V9-V10 -> 0 | W11: =W12-W9-W10 -> 0 | X11: =-(X10-(X12-X9)) -> 0 | Y11: =Y12-Y9-Y10 -> 0 | Z11: =Z12-Z9-Z10 -> -2 | AA11: =AA12-AA9-AA10 -> 0 | AB11: =AB12-AB9-AB10 -> 0 | AC11: =-(AC10-(AC12-AC9)) -> -2 | AD11: =AD12-AD9-AD10 -> 0 | AE11: =AE12-AE9-AE10 -> -1 | AF11: =AF12-AF9-AF10 -> 0 | AG11: =AG12-AG9-AG10 -> -1 | AH11: =-(AH10-(AH12-AH9)) -> -2 | AI11: =AI12-AI9-AI10 -> 0 | AJ11: =AJ12-AJ9-AJ10 -> 0 | AK11: =AK12-AK9-AK10 -> 0 | AL11: =AL12-AL9-AL10 -> 0 | AM11: =-(AM10-(AM12-AM9)) -> 0 | AN11: =AN12-AN9-AN10 -> 0 | AO11: =AO12-AO9-AO10 -> 0 | AP11: =AP12-AP9-AP10 -> -1 | AQ11: =AQ12-AQ9-AQ10 -> 0 | AR11: =-(AR10-(AR12-AR9)) -> -1 | AS11: =AS12-AS9-AS10 -> 0 | AT11: =AT12-AT9-AT10 -> 0 | AU11: =AU12-AU9-AU10 -> 0 | AV11: =AV12-AV9-AV10 -> 0 | AW11: =-(AW10-(AW12-AW9)) -> 0 | AX11: =AX12-AX9-AX10 -> 0 | AY11: =AY12-AY9-AY10 -> 0 | AZ11: =AZ12-AZ9-AZ10 -> 0 | BA11: =BA12-BA9-BA10 -> 0 | BB11: 0 | BC11: =BC12-BC9-BC10 -> -1 | BD11: =BD12-BD9-BD10 -> 0 | BE11: =BE12-BE9-BE10 -> 0 | BF11: =BF12-BF9-BF10 -> 0 | BG11: =-(BG10-(BG12-BG9)) -> -1 | BH11: =AVERAGE(BG11,BB11,AW11,AR11,AM11) -> -0.4 | BI11: =AVERAGE(BH11,BG11,BB11,AW11,AR11) -> -0.48 | BJ11: =AVERAGE(BI11,BH11,BG11,BB11,AW11) -> -0.376 | BK11: =AVERAGE(BJ11,BI11,BH11,BG11,BB11) -> -0.4512 | BL11: =AVERAGE(BK11,BJ11,BI11,BH11,BG11) -> -0.54144
B12: The Cheesecake Factory restaurants - EoP, # of restaurants | J12: 169 | K12: 170 | L12: 172 | M12: =N12 -> 177 | N12: 177 | O12: 177 | P12: 179 | Q12: 181 | R12: =S12 -> 187 | S12: 187 | T12: 188 | U12: 189 | V12: 189 | W12: 194 | X12: 194 | Y12: 194 | Z12: 193 | AA12: 194 | AB12: 199 | AC12: 199 | AD12: 199 | AE12: 198 | AF12: 199 | AG12: 201 | AH12: 201 | AI12: 201 | AJ12: 202 | AK12: 203 | AL12: 206 | AM12: =AL12 -> 206 | AN12: 206 | AO12: 206 | AP12: 205 | AQ12: 206 | AR12: =AQ12 -> 206 | AS12: 207 | AT12: 207 | AU12: 207 | AV12: 208 | AW12: =AV12 -> 208 | AX12: 208 | AY12: 208 | AZ12: 209 | BA12: 211 | BB12: =BA12 -> 211 | BC12: 210 | BD12: 211 | BE12: 213 | BF12: 216 | BG12: =BF12 -> 216 | BH12: =BH9+BH10+BH11 -> 219.6 | BI12: =BI9+BI10+BI11 -> 224.12 | BJ12: =BJ9+BJ10+BJ11 -> 228.744 | BK12: =BK9+BK10+BK11 -> 234.2928 | BL12: =BL9+BL10+BL11 -> 239.75136
B13: Y/Y CF restaurant growth, % | J13: 0 | K13: 0 | L13: 0 | M13: 0 | O13: =O12/J12-1 -> 0.047337278 | P13: =P12/K12-1 -> 0.052941176 | Q13: =Q12/L12-1 -> 0.052325581 | R13: =R12/M12-1 -> 0.056497175 | S13: =S12/N12-1 -> 0.056497175 | T13: =T12/O12-1 -> 0.062146893 | U13: =U12/P12-1 -> 0.055865922 | V13: =V12/Q12-1 -> 0.044198895 | ... BG13: =BG12/BB12-1 -> 0.023696682 | BH13: =BH12/BG12-1 -> 0.016666667 | BI13: =BI12/BH12-1 -> 0.020582878 | BJ13: =BJ12/BI12-1 -> 0.020631804 | BK13: =BK12/BJ12-1 -> 0.024257685 | BL13: =BL12/BK12-1 -> 0.023298027
B14: The Cheesecake Factory restaurants - Average, # of restaurants | J14: =AVERAGE(J9,J12) -> 168.5 | K14: =AVERAGE(K9,K12) -> 169.5 | L14: =AVERAGE(L9,L12) -> 171 | M14: =AVERAGE(M9,M12) -> 174.5 | N14: =AVERAGE(J14,K14,L14,M14) -> 170.875 | O14: =AVERAGE(O9,O12) -> 177 | P14: =AVERAGE(P9,P12) -> 178 | Q14: =AVERAGE(Q9,Q12) -> 180 | R14: =AVERAGE(R9,R12) -> 184 | S14: =AVERAGE(O14,P14,Q14,R14) -> 179.75 | T14: =AVERAGE(T9,T12) -> 187.5 | U14: =AVERAGE(U9,U12) -> 188.5 | V14: =AVERAGE(V9,V12) -> 189 | W14: =AVERAGE(W9,W12) -> 191.5 | X14: =AVERAGE(T14,U14,V14,W14) -> 189.125 | Y14: =AVERAGE(Y9,Y12) -> 194 | Z14: =AVERAGE(Z9,Z12) -> 193.5 | AA14: =AVERAGE(AA9,AA12) -> 193.5 | AB14: =AVERAGE(AB9,AB12) -> 196.5 | AC14: =AVERAGE(Y14,Z14,AA14,AB14) -> 194.375 | AD14: =AVERAGE(AD9,AD12) -> 199 | AE14: =AVERAGE(AE9,AE12) -> 198.5 | AF14: =AVERAGE(AF9,AF12) -> 198.5 | AG14: =AVERAGE(AG9,AG12) -> 200 | AH14: =AVERAGE(AD14,AE14,AF14,AG14) -> 199 | AI14: =AVERAGE(AI9,AI12) -> 201 | AJ14: =AVERAGE(AJ9,AJ12) -> 201.5 | AK14: =AVERAGE(AK9,AK12) -> 202.5 | AL14: =AVERAGE(AL9,AL12) -> 204.5 | AM14: =AVERAGE(AI14,AJ14,AK14,AL14) -> 202.375 | AN14: =AVERAGE(AN9,AN12) -> 206 | AO14: =AVERAGE(AO9,AO12) -> 206 | AP14: =AVERAGE(AP9,AP12) -> 205.5 | AQ14: =AVERAGE(AQ9,AQ12) -> 205.5 | AR14: =AVERAGE(AN14,AO14,AP14,AQ14) -> 205.75 | AS14: =AVERAGE(AS9,AS12) -> 206.5 | AT14: =AVERAGE(AT9,AT12) -> 207 | AU14: =AVERAGE(AU9,AU12) -> 207 | AV14: =AVERAGE(AV9,AV12) -> 207.5 | AW14: =AVERAGE(AS14,AT14,AU14,AV14) -> 207 | AX14: =AVERAGE(AX9,AX12) -> 208 | AY14: =AVERAGE(AY9,AY12) -> 208 | AZ14: =AVERAGE(AZ9,AZ12) -> 208.5 | BA14: =AVERAGE(BA9,BA12) -> 210 | BB14: =AVERAGE(AX14,AY14,AZ14,BA14) -> 208.625 | BC14: =AVERAGE(BC9,BC12) -> 210.5 | BD14: =AVERAGE(BD9,BD12) -> 210.5 | BE14: =AVERAGE(BE9,BE12) -> 212 | BF14: =AVERAGE(BF9,BF12) -> 214.5 | BG14: =AVERAGE(BC14,BD14,BE14,BF14) -> 211.875 | BH14: =AVERAGE(BH9,BH12) -> 217.8 | BI14: =AVERAGE(BI9,BI12) -> 221.86 | BJ14: =AVERAGE(BJ9,BJ12) -> 226.432 | BK14: =AVERAGE(BK9,BK12) -> 231.5184 | BL14: =AVERAGE(BL9,BL12) -> 237.02208
B17: Total Operating Weeks | J17: 0 | K17: 0 | L17: 0 | M17: 0 | N17: 8886 | O17: 2301 | P17: 2310 | Q17: 2336 | R17: 2394 | S17: 9341 | T17: 2436 | U17: 2448 | V17: 2457 | W17: =X17-SUM(T17,U17,V17) -> 2690 | X17: 10031 | Y17: 2522 | Z17: 2517 | AA17: 2511 | AB17: =AC17-SUM(Y17,Z17,AA17) -> 2552 | AC17: 10102 | AD17: 2587 | AE17: 2582 | AF17: 2580 | AG17: 2595 | AH17: 10344 | AI17: 2613 | AJ17: 2624 | AK17: 2628 | AL17: 2655 | AM17: 10520 | AN17: 2674 | AO17: 2640 | AP17: 2662 | AQ17: 2666 | AR17: 10642 | AS17: 2678 | AT17: 2691 | AU17: 2689 | AV17: 2700 | AW17: 10758 | AX17: 2704 | AY17: 2704 | AZ17: 2705 | BA17: 2939 | BB17: 11052 | BC17: 2737 | BD17: 2734 | BE17: 2756 | BF17: 2783 | BG17: 11010 | BH17: =BH14*BH18 -> 11352.464 | BI17: =BI14*BI18 -> 11570.326 | BJ17: =BJ14*BJ18 -> 11828.168 | BK17: =BK14*BK18 -> 12106.191 | BL17: =BL14*BL18 -> 12361.507
B18: Operating Weeks / Store | J18: =J17/J14 -> 0 | K18: =K17/K14 -> 0 | L18: =L17/L14 -> 0 | M18: =M17/M14 -> 0 | N18: =N17/N14 -> 52.002926 | O18: =O17/O14 -> 13 | P18: =P17/P14 -> 12.977528 | Q18: =Q17/Q14 -> 12.977778 | ... BG18: =BG17/BG14 -> 51.964602 | BH18: =AVERAGE(BG18,BB18,AW18,AR18,AM18) -> 52.123344 | BI18: =AVERAGE(BH18,BG18,BB18,AW18,AR18) -> 52.151472 | BJ18: =AVERAGE(BI18,BH18,BG18,BB18,AW18) -> 52.237173 | BK18: =AVERAGE(BJ18,BI18,BH18,BG18,BB18) -> 52.290405 | BL18: =AVERAGE(BK18,BJ18,BI18,BH18,BG18) -> 52.153399
B20: Table Turnover Metrics
B21: Average Cheque Size / Customer | N21: 0 | O21: 0 | P21: 0 | Q21: 0 | R21: 0 | S21: 0 | T21: 0 | U21: 0 | V21: 0 | W21: 0 | X21: 0 | Y21: 0 | Z21: 0 | AA21: 0 | AB21: 0 | AC21: 0 | AD21: 0 | AE21: 0 | AF21: 0 | AG21: 0 | AH21: 0 | AI21: 0 | AJ21: 0 | AK21: 0 | AL21: 0 | AM21: 0 | AN21: 0 | AO21: 0 | AP21: 0 | AQ21: 0 | AR21: 0 | AS21: 0 | AT21: 0 | AU21: 0 | AV21: 0 | AW21: 0 | AX21: 0 | AY21: 0 | AZ21: 0 | BA21: 0 | BB21: 0 | BG21: =BG41 -> 30.54 | BH21: =BH41 -> 32.215906 | BI21: =BI41 -> 33.791067 | BJ21: =BJ41 -> 35.30763 | BK21: =BK41 -> 36.767203 | BL21: =BL41 -> 38.271456
B22: Number of Customers Served / Week | N22: 0 | O22: 0 | P22: 0 | Q22: 0 | R22: 0 | S22: 0 | T22: 0 | U22: 0 | V22: 0 | W22: 0 | X22: 0 | Y22: 0 | Z22: 0 | AA22: 0 | AB22: 0 | AC22: 0 | AD22: 0 | AE22: 0 | AF22: 0 | AG22: 0 | AH22: 0 | AI22: 0 | AJ22: 0 | AK22: 0 | AL22: 0 | AM22: 0 | AN22: 0 | AO22: 0 | AP22: 0 | AQ22: 0 | AR22: 0 | AS22: 0 | AT22: 0 | AU22: 0 | AV22: 0 | AW22: 0 | AX22: 0 | AY22: 0 | AZ22: 0 | BA22: 0 | BB22: 0 | BG22: =BG50/BG21*1000 -> 7717.774 | BH22: =BH24*BH23 -> 7824.96 | BI22: =BI24*BI23 -> 7925.28 | BJ22: =BJ24*BJ23 -> 8025.6 | BK22: =BK24*BK23 -> 8125.92 | BL22: =BL24*BL23 -> 8226.24
B23: Average Table Size | N23: 0 | O23: 0 | P23: 0 | Q23: 0 | R23: 0 | S23: 0 | T23: 0 | U23: 0 | V23: 0 | W23: 0 | X23: 0 | Y23: 0 | Z23: 0 | AA23: 0 | AB23: 0 | AC23: 0 | AD23: 0 | AE23: 0 | AF23: 0 | AG23: 0 | AH23: 0 | AI23: 0 | AJ23: 0 | AK23: 0 | AL23: 0 | AM23: 0 | AN23: 0 | AO23: 0 | AP23: 0 | AQ23: 0 | AR23: 0 | AS23: 0 | AT23: 0 | AU23: 0 | AV23: 0 | AW23: 0 | AX23: 0 | AY23: 0 | AZ23: 0 | BA23: 0 | BB23: 0 | BG23: 4.4 | BH23: 4.4 | BI23: 4.4 | BJ23: 4.4 | BK23: 4.4 | BL23: 4.4
B24: Number of Tables Served / Week | N24: 0 | O24: 0 | P24: 0 | Q24: 0 | R24: 0 | S24: 0 | T24: 0 | U24: 0 | V24: 0 | W24: 0 | X24: 0 | Y24: 0 | Z24: 0 | AA24: 0 | AB24: 0 | AC24: 0 | AD24: 0 | AE24: 0 | AF24: 0 | AG24: 0 | AH24: 0 | AI24: 0 | AJ24: 0 | AK24: 0 | AL24: 0 | AM24: 0 | AN24: 0 | AO24: 0 | AP24: 0 | AQ24: 0 | AR24: 0 | AS24: 0 | AT24: 0 | AU24: 0 | AV24: 0 | AW24: 0 | AX24: 0 | AY24: 0 | AZ24: 0 | BA24: 0 | BB24: 0 | BG24: =BG22/BG23 -> 1754.0395 | BH24: =BH27*BH25 -> 1778.4 | BI24: =BI27*BI25 -> 1801.2 | BJ24: =BJ27*BJ25 -> 1824 | BK24: =BK27*BK25 -> 1846.8 | BL24: =BL27*BL25 -> 1869.6
B25: Operating Hours / Week | N25: 0 | O25: 0 | P25: 0 | Q25: 0 | R25: 0 | S25: 0 | T25: 0 | U25: 0 | V25: 0 | W25: 0 | X25: 0 | Y25: 0 | Z25: 0 | AA25: 0 | AB25: 0 | AC25: 0 | AD25: 0 | AE25: 0 | AF25: 0 | AG25: 0 | AH25: 0 | AI25: 0 | AJ25: 0 | AK25: 0 | AL25: 0 | AM25: 0 | AN25: 0 | AO25: 0 | AP25: 0 | AQ25: 0 | AR25: 0 | AS25: 0 | AT25: 0 | AU25: 0 | AV25: 0 | AW25: 0 | AX25: 0 | AY25: 0 | AZ25: 0 | BA25: 0 | BB25: 0 | BG25: 76 | BH25: 76 | BI25: 76 | BJ25: 76 | BK25: 76 | BL25: 76
B26: # Tables, Average/Store | N26: 0 | O26: 0 | P26: 0 | Q26: 0 | R26: 0 | S26: 0 | T26: 0 | U26: 0 | V26: 0 | W26: 0 | X26: 0 | Y26: 0 | Z26: 0 | AA26: 0 | AB26: 0 | AC26: 0 | AD26: 0 | AE26: 0 | AF26: 0 | AG26: 0 | AH26: 0 | AI26: 0 | AJ26: 0 | AK26: 0 | AL26: 0 | AM26: 0 | AN26: 0 | AO26: 0 | AP26: 0 | AQ26: 0 | AR26: 0 | AS26: 0 | AT26: 0 | AU26: 0 | AV26: 0 | AW26: 0 | AX26: 0 | AY26: 0 | AZ26: 0 | BA26: 0 | BB26: 0 | BG26: 60 | BH26: 60 | BI26: 60 | BJ26: 60 | BK26: 60 | BL26: 60
B27: Tables Served / Hour | N27: 0 | O27: 0 | P27: 0 | Q27: 0 | R27: 0 | S27: 0 | T27: 0 | U27: 0 | V27: 0 | W27: 0 | X27: 0 | Y27: 0 | Z27: 0 | AA27: 0 | AB27: 0 | AC27: 0 | AD27: 0 | AE27: 0 | AF27: 0 | AG27: 0 | AH27: 0 | AI27: 0 | AJ27: 0 | AK27: 0 | AL27: 0 | AM27: 0 | AN27: 0 | AO27: 0 | AP27: 0 | AQ27: 0 | AR27: 0 | AS27: 0 | AT27: 0 | AU27: 0 | AV27: 0 | AW27: 0 | AX27: 0 | AY27: 0 | AZ27: 0 | BA27: 0 | BB27: 0 | BG27: =BG24/BG25 -> 23.079468 | BH27: =BH26*BH28 -> 23.4 | BI27: =BI26*BI28 -> 23.7 | BJ27: =BJ26*BJ28 -> 24 | BK27: =BK26*BK28 -> 24.3 | BL27: =BL26*BL28 -> 24.6
B28: Table Turnover (per hour) | N28: 0 | O28: 0 | P28: 0 | Q28: 0 | R28: 0 | S28: 0 | T28: 0 | U28: 0 | V28: 0 | W28: 0 | X28: 0 | Y28: 0 | Z28: 0 | AA28: 0 | AB28: 0 | AC28: 0 | AD28: 0 | AE28: 0 | AF28: 0 | AG28: 0 | AH28: 0 | AI28: 0 | AJ28: 0 | AK28: 0 | AL28: 0 | AM28: 0 | AN28: 0 | AO28: 0 | AP28: 0 | AQ28: 0 | AR28: 0 | AS28: 0 | AT28: 0 | AU28: 0 | AV28: 0 | AW28: 0 | AX28: 0 | AY28: 0 | AZ28: 0 | BA28: 0 | BB28: 0 | BG28: =BG27/BG26 -> 0.38465779 | BH28: ='Forecast Assumptions'!G8 -> 0.39 | BI28: ='Forecast Assumptions'!H8 -> 0.395 | BJ28: ='Forecast Assumptions'!I8 -> 0.4 | BK28: ='Forecast Assumptions'!J8 -> 0.405 | BL28: ='Forecast Assumptions'!K8 -> 0.41
B30: Cheque Mix
B31: Sales from off-premise business, % | S31: 0.09 | X31: 0.11 | AC31: 0.12 | AF31: 0.135 | AG31: 0.15 | AH31: 0.14 | AI31: 0.16 | AJ31: 0.16 | AK31: 0.16 | AL31: 0.17 | AM31: 0.16 | AN31: 0.22 | AO31: 0.79 | AP31: 0.45 | AQ31: 0.447 | AR31: 0.43 | AS31: 0.43 | AT31: 0.31 | AU31: 0.28 | AV31: 0.278 | AW31: 0.32 | AX31: 0.28 | AY31: 0.25 | AZ31: 0.23 | BA31: 0.24075353 | BB31: 0.25 | BC31: 0.23 | BD31: 0.22 | BE31: 0.21 | BF31: 0.22 | BG31: 0.22
B32: Sales from alcoholic beverages, % | S32: 0.13 | X32: 0.13 | AC32: 0.13 | AH32: 0.12 | AM32: 0.12 | AR32: 0.09 | AW32: 0.11 | BB32: 0.12 | BG32: 0.11 | BH32: =BH33/(BH33+BH35+BH37) -> 0.12416227 | BI32: =BI33/(BI33+BI35+BI37) -> 0.13317129 | BJ32: =BJ33/(BJ33+BJ35+BJ37) -> 0.1387802 | BK32: =BK33/(BK33+BK35+BK37) -> 0.1414304 | BL32: =BL33/(BL33+BL35+BL37) -> 0.14371023
B33: Spend per Customer | S33: =S32*S41 -> 2.704 | T33: =T32*T41 -> 0 | U33: =U32*U41 -> 0 | V33: =V32*V41 -> 0 | W33: =W32*W41 -> 0 | X33: =X32*X41 -> 2.782 | Y33: =Y32*Y41 -> 0 | Z33: =Z32*Z41 -> 0 | ... BG33: =BG32*BG41 -> 3.3594 | BH33: ='Forecast Assumptions'!G5 -> 4 | BI33: ='Forecast Assumptions'!H5 -> 4.5 | BJ33: ='Forecast Assumptions'!I5 -> 4.9 | BK33: ='Forecast Assumptions'!J5 -> 5.2 | BL33: ='Forecast Assumptions'!K5 -> 5.5
B34: Sales from desserts, % | S34: 0.16 | X34: 0.16 | AC34: 0.16 | AH34: 0.16 | AM34: 0.16 | AR34: 0.21 | AW34: 0.19 | BB34: 0.17 | BG34: 0.17 | BH34: =BH35/(BH35+BH33+BH37) -> 0.16599111 | BI34: =BI35/(BI35+BI33+BI37) -> 0.16300109 | BJ34: =BJ35/(BJ35+BJ33+BJ37) -> 0.16067972 | BK34: =BK35/(BK35+BK33+BK37) -> 0.15893014 | BL34: =BL35/(BL35+BL33+BL37) -> 0.15726392
B35: Spend per Customer | S35: =S34*S41 -> 3.328 | T35: =T34*T41 -> 0 | U35: =U34*U41 -> 0 | V35: =V34*V41 -> 0 | W35: =W34*W41 -> 0 | X35: =X34*X41 -> 3.424 | Y35: =Y34*Y41 -> 0 | Z35: =Z34*Z41 -> 0 | ... BG35: =BG34*BG41 -> 5.1918 | BH35: ='Forecast Assumptions'!G7 -> 5.347554 | BI35: ='Forecast Assumptions'!H7 -> 5.5079806 | BJ35: ='Forecast Assumptions'!I7 -> 5.67322 | BK35: ='Forecast Assumptions'!J7 -> 5.8434166 | BL35: ='Forecast Assumptions'!K7 -> 6.0187191
B36: Sales from on-premise food | S36: =1-S34-S32 -> 0.71 | T36: =1-T34-T32 -> 1 | U36: =1-U34-U32 -> 1 | V36: =1-V34-V32 -> 1 | W36: =1-W34-W32 -> 1 | X36: =1-X34-X32 -> 0.71 | Y36: =1-Y34-Y32 -> 1 | Z36: =1-Z34-Z32 -> 1 | ... BL36: =1-BL34-BL32 -> 0.69902585
B37: Spend per Customer | S37: =S36*S41 -> 14.768 | T37: =T36*T41 -> 0 | U37: =U36*U41 -> 0 | V37: =V36*V41 -> 0 | W37: =W36*W41 -> 0 | X37: =X36*X41 -> 15.194 | Y37: =Y36*Y41 -> 0 | Z37: =Z36*Z41 -> 0 | ... BG37: =BG36*BG41 -> 21.9888 | BH37: ='Forecast Assumptions'!G6 -> 22.868352 | BI37: ='Forecast Assumptions'!H6 -> 23.783086 | BJ37: ='Forecast Assumptions'!I6 -> 24.73441 | BK37: ='Forecast Assumptions'!J6 -> 25.723786 | BL37: ='Forecast Assumptions'!K6 -> 26.752737
B39: Average sales per Cheesecake factory restaurant, mm | N39: 10.5 | S39: 10.6 | X39: 10.7 | AC39: 10.6 | AH39: 10.7 | AM39: 10.7 | AR39: 7.8 | AW39: 11.1 | BB39: 12.1 | BG39: 12.2
B40: Average sales per productive square foot, $/sq ft | N40: 942 | S40: 967 | X40: 971 | AC40: 962 | AH40: 978 | AM40: 986 | AR40: 716 | AW40: 1019 | BB40: 1116 | BG40: 1132
B41: Average check per customer, $/check | S41: 20.8 | X41: 21.4 | AC41: 21.85 | AH41: 22.6 | AM41: 23.5 | AR41: 28.9 | AW41: 29.3 | BB41: 29.4 | BG41: 30.54 | BH41: =BH37+BH35+BH33 -> 32.215906 | BI41: =BI37+BI35+BI33 -> 33.791067 | BJ41: =BJ37+BJ35+BJ33 -> 35.30763 | BK41: =BK37+BK35+BK33 -> 36.767203 | BL41: =BL37+BL35+BL33 -> 38.271456
B43: Spend Growth Metrics
B44: Cheesecake Factory Menu pricing growth, % | N44: 0.02 | O44: 0.02 | P44: 0.02 | Q44: 0.021 | R44: 0.025 | S44: 0.022 | T44: 0.027 | U44: 0.029 | V44: 0.026 | W44: 0.025 | X44: 0.027 | Y44: 0.024 | Z44: 0.022 | AA44: 0.024 | AB44: 0.025 | AC44: 0.024 | AD44: 0.027 | AE44: 0.029 | AF44: 0.029 | AG44: 0.029 | AH44: 0.028 | AI44: 0.03 | AJ44: 0.031 | AK44: 0.032 | AL44: 0.032 | AM44: 0.031 | AN44: 0.032 | AO44: 0.031 | AP44: 0.03 | AQ44: 0.031 | AR44: 0.031 | AS44: 0.03 | AT44: 0.03 | AU44: 0.03 | AV44: 0.03 | AW44: 0.03 | AX44: 0.036 | AY44: 0.047 | AZ44: 0.06 | BA44: 0.06 | BB44: 0.059 | BC44: 0.104 | BD44: 0.106 | BE44: 0.095 | BF44: 0.07119185 | BG44: 0.094
B45: Cheesecake Factory Menu mix growth, % | N45: 0.005 | O45: 0.013 | P45: 0.01 | Q45: 0.006 | R45: 0.005 | S45: 0.008 | T45: -0.005 | U45: 0.001 | V45: 0.005 | W45: 0.004 | X45: 0.001 | Y45: 0.002 | Z45: -0.003 | AA45: -0.004 | AB45: -0.006 | AC45: -0.003 | AD45: 0 | AE45: 0.006 | AF45: 0.006 | AG45: 0.006 | AH45: 0.005 | AI45: 0.008 | AJ45: 0.007 | AK45: 0.009 | AL45: 0.012 | AM45: 0.009 | AN45: 0.019 | AO45: 0.117 | AP45: 0.141 | AQ45: 0.117 | AR45: 0.102 | AS45: 0.166 | AT45: -0.557 | AU45: 0.021 | AV45: 0.021 | AW45: -0.004 | AX45: -0.082 | AY45: -0.057 | AZ45: -0.05 | BA45: -0.05 | BB45: -0.057 | BC45: -0.057 | BD45: -0.054 | BE45: -0.061 | BF45: -0.044333316 | BG45: -0.054
B46: Cheesecake Factory Average check growth, % | N46: =N44+N45 -> 0.025 | O46: =O44+O45 -> 0.033 | P46: =P44+P45 -> 0.03 | Q46: =Q44+Q45 -> 0.027 | R46: =R44+R45 -> 0.03 | S46: =S44+S45 -> 0.03 | T46: =T44+T45 -> 0.022 | U46: =U44+U45 -> 0.03 | ... AP46: =AP44+AP45 -> 0.171 | AQ46: 0.148 | AR46: =AR44+AR45 -> 0.133 | AS46: =AS44+AS45 -> 0.196 | AT46: =AT44+AT45 -> -0.527 | AU46: =AU44+AU45 -> 0.051 | AV46: =AV44+AV45 -> 0.051 | AW46: =AW44+AW45 -> 0.026 | AX46: =AX44+AX45 -> -0.046 | AY46: =AY44+AY45 -> -0.01 | ... BE46: =BE44+BE45 -> 0.034 | BF46: 0.026858535 | BG46: =BG44+BG45 -> 0.04
B47: Cheesecake Factory Customer traffic growth, % | N47: -0.01 | O47: 0.009 | P47: -0.002 | Q47: -0.005 | R47: -0.019 | S47: -0.004 | T47: -0.005 | U47: -0.027 | V47: -0.014 | W47: -0.018 | X47: -0.016 | Y47: -0.023 | Z47: -0.024 | AA47: -0.043 | AB47: -0.028 | AC47: -0.029 | AD47: -0.006 | AE47: -0.021 | AF47: -0.02 | AG47: -0.016 | AH47: -0.016 | AI47: -0.025 | AJ47: -0.028 | AK47: -0.037 | AL47: -0.038 | AM47: -0.032 | AN47: -0.18 | AO47: -0.717 | AP47: -0.404 | AQ47: -0.717 | AR47: -0.415 | AS47: -0.168 | AT47: 2.027 | AU47: 0.429 | AV47: 0.429 | AW47: 0.414 | AX47: 0.253 | AY47: 0.057 | AZ47: 0.001 | BA47: 0.001 | BB47: 0.068 | BC47: 0.01 | BD47: -0.037 | BE47: -0.01 | BF47: -0.0018585349 | BG47: -0.01
B49: Aggregate Revenue
B50: Weekly Store Level Revenue (avg in $k) | J50: 0 | K50: 0 | L50: 0 | M50: 0 | N50: =N53/N17*1000 -> 201.75512 | O50: =O53/O17*1000 -> 205.48327 | P50: =P53/P17*1000 -> 209.21429 | Q50: =Q53/Q17*1000 -> 205.94007 | R50: =R53/R17*1000 -> 199.07268 | S50: =S53/S17*1000 -> 204.87721 | T50: =T53/T17*1000 -> 207.84729 | U50: =U53/U17*1000 -> 209.11683 | ... BG50: =BG53/BG17*1000 -> 235.70082 | BH50: =BH22*BH41/1000 -> 252.08818 | BI50: =BI22*BI41/1000 -> 267.80367 | BJ50: =BJ22*BJ41/1000 -> 283.36491 | BK50: =BK22*BK41/1000 -> 298.76735 | BL50: =BL22*BL41/1000 -> 314.83019
B51: Annual Store Level Revenue (avg in $mm) | J51: =J50*J18/1000 -> 0 | K51: =K50*K18/1000 -> 0 | L51: =L50*L18/1000 -> 0 | M51: =M50*M18/1000 -> 0 | N51: =N50*N18/1000 -> 10.491857 | O51: =O50*O18/1000 -> 2.6712825 | P51: =P50*P18/1000 -> 2.7150843 | Q51: =Q50*Q18/1000 -> 2.6726444 | ... BL51: =BL50*BL18/1000 -> 16.419464
B53: The Cheesecake Factory revenue, mm | J53: 436.606 | K53: 451.454 | L53: 454.271 | M53: 450.465 | N53: 1792.796 | O53: 472.817 | P53: 483.285 | Q53: 481.076 | R53: 476.58 | S53: 1913.758 | T53: 506.316 | U53: 511.918 | V53: 512.04 | W53: 547.809 | X53: 2078.083 | Y53: 515.234 | Z53: 520.228 | AA53: 507.572 | AB53: 514.782 | AC53: 2057.816 | AD53: 540.773 | AE53: 542.102 | AF53: 530.21 | AG53: 530.786 | AH53: 2127.347 | AI53: 548.633 | AJ53: 551.519 | AK53: 536.101 | AL53: =AM53-SUM(AI53,AJ53,AK53) -> 544.629 | AM53: 2180.882 | AN53: 488.471 | AO53: 241.068 | AP53: 416.984 | AQ53: =AR53-SUM(AN53,AO53,AP53) -> 438.485 | AR53: 1585.008 | AS53: 499.389 | AT53: 606.691 | AU53: 592.555 | AV53: =AW53-SUM(AS53,AT53,AU53) -> 594.59 | AW53: 2293.225 | AX53: 609.816 | AY53: 640.858 | AZ53: 602.902 | BA53: =BB53-SUM(AX53,AY53,AZ53) -> 674.467 | BB53: 2528.043 | BC53: 656 | BD53: 652.481 | BE53: 628.14 | BF53: =BG53-SUM(BC53,BD53,BE53) -> 658.445 | BG53: 2595.066 | BH53: =BH51*BH14 -> 2861.822 | BI53: =BI51*BI14 -> 3098.5756 | BJ53: =BJ51*BJ14 -> 3351.6877 | BK53: =BK51*BK14 -> 3616.9345 | BL53: =BL51*BL14 -> 3891.7756

Sheet Revenue Build - North Italia
B4: Period Ended | J4: 41730 | K4: 41821 | L4: 41912 | M4: 42003 | N4: 42094 | O4: 42185 | P4: 42276 | Q4: 42367 | R4: 42458 | S4: 42549 | T4: 42640 | U4: 42738 | V4: 42829 | W4: 42920 | X4: 43011 | Y4: 43102 | Z4: 43193 | AA4: 43284 | AB4: 43375 | AC4: 43466 | AD4: 43466 | AE4: 43557 | AF4: 43648 | AG4: 43739 | AH4: 43830 | AI4: 43830 | AJ4: 43921 | AK4: 44012 | AL4: 44103 | AM4: 44194 | AN4: 44194 | AO4: 44285 | AP4: 44376 | AQ4: 44467 | AR4: 44558 | AS4: 44558 | AT4: 44649 | AU4: 44740 | AV4: 44831 | AW4: 44929 | AX4: 44929 | AY4: 45019 | AZ4: 45111 | BA4: 45202 | BB4: 45293 | BC4: 45293
J5: Q1-2014 | K5: Q2-2014 | L5: Q3-2014 | M5: Q4-2014 | N5: Q1-2015 | O5: Q2-2015 | P5: Q3-2015 | Q5: Q4-2015 | R5: Q1-2016 | S5: Q2-2016 | T5: Q3-2016 | U5: Q4-2016 | V5: Q1-2017 | W5: Q2-2017 | X5: Q3-2017 | Y5: Q4-2017 | Z5: Q1-2018 | AA5: Q2-2018 | AB5: Q3-2018 | AC5: Q4-2018 | AD5: FY2018 | AE5: Q1-2019 | AF5: Q2-2019 | AG5: Q3-2019 | AH5: Q4-2019 | AI5: FY2019 | AJ5: Q1-2020 | AK5: Q2-2020 | AL5: Q3-2020 | AM5: Q4-2020 | AN5: FY2020 | AO5: Q1-2021 | AP5: Q2-2021 | AQ5: Q3-2021 | AR5: Q4-2021 | AS5: FY2021 | AT5: Q1-2022 | AU5: Q2-2022 | AV5: Q3-2022 | AW5: Q4-2022 | AX5: FY2022 | AY5: Q1-2023 | AZ5: Q2-2023 | BA5: Q3-2023 | BB5: Q4-2023 | BC5: FY2023 | BD5: FY2024E | BE5: FY2025E | BF5: FY2026E | BG5: FY2027E | BH5: FY2028E
B7: North Italia Revenue Build
B9: North Italia restaurants - BoP, # of restaurants | J9: 0 | K9: 0 | L9: 0 | M9: 0 | N9: 0 | O9: 0 | P9: 0 | Q9: 0 | R9: 0 | S9: 0 | T9: 0 | U9: 0 | V9: 0 | W9: 0 | X9: 0 | Y9: 0 | Z9: 0 | AA9: 0 | AB9: 0 | AC9: 0 | AD9: 0 | AH9: =AG12 -> 21 | AI9: =AD12 -> 0 | AJ9: =AI12 -> 22 | AK9: =AJ12 -> 23 | AL9: =AK12 -> 23 | AM9: =AL12 -> 23 | AN9: =AI12 -> 22 | AO9: =AN12 -> 23 | AP9: =AO12 -> 24 | AQ9: =AP12 -> 26 | AR9: =AQ12 -> 28 | AS9: =AN12 -> 23 | AT9: =AS12 -> 29 | AU9: =AT12 -> 29 | AV9: =AU12 -> 30 | AW9: =AV12 -> 31 | AX9: =AS12 -> 29 | AY9: =AX12 -> 33 | AZ9: =AY12 -> 33 | BA9: =AZ12 -> 33 | BB9: =BA12 -> 33 | BC9: =AX12 -> 33 | BD9: =BC12 -> 36 | BE9: =BD12 -> 40 | BF9: =BE12 -> 44 | BG9: =BF12 -> 48 | BH9: =BG12 -> 53
B10: NI restaurants opened, # of restaurants | J10: 0 | K10: 0 | L10: 0 | M10: 0 | N10: 0 | O10: 0 | P10: 0 | Q10: 0 | R10: 0 | S10: 0 | T10: 0 | U10: 0 | V10: 0 | W10: 0 | X10: 0 | Y10: 0 | Z10: 0 | AA10: 0 | AB10: 0 | AC10: 0 | AD10: 0 | AH10: 1 | AI10: =AH10+AG12 -> 22 | AJ10: 1 | AK10: 0 | AL10: 0 | AM10: 0 | AN10: =SUM(AJ10,AK10,AL10,AM10) -> 1 | AO10: 1 | AP10: 2 | AQ10: 2 | AR10: 1 | AS10: =SUM(AO10,AP10,AQ10,AR10) -> 6 | AT10: 0 | AU10: 1 | AV10: 1 | AW10: 2 | AX10: =SUM(AT10,AU10,AV10,AW10) -> 4 | AY10: 0 | AZ10: 0 | BA10: 0 | BB10: 3 | BC10: =SUM(AY10,AZ10,BA10,BB10) -> 3 | BD10: ='Forecast Assumptions'!G10 -> 4 | BE10: ='Forecast Assumptions'!H10 -> 4 | BF10: ='Forecast Assumptions'!I10 -> 4 | BG10: ='Forecast Assumptions'!J10 -> 5 | BH10: ='Forecast Assumptions'!K10 -> 5
B11: NI restaurants closed, # of restaurants | J11: 0 | K11: 0 | L11: 0 | M11: 0 | N11: 0 | O11: 0 | P11: 0 | Q11: 0 | R11: 0 | S11: 0 | T11: 0 | U11: 0 | V11: 0 | W11: 0 | X11: 0 | Y11: 0 | Z11: 0 | AA11: 0 | AB11: 0 | AC11: 0 | AD11: 0 | AH11: 0 | AI11: 0 | AJ11: =-(AJ10-(AJ12-AJ9)) -> 0 | AK11: =-(AK10-(AK12-AK9)) -> 0 | AL11: =-(AL10-(AL12-AL9)) -> 0 | AM11: 0 | AN11: =SUM(AJ11,AK11,AL11,AM11) -> 0 | AO11: =-(AO10-(AO12-AO9)) -> 0 | AP11: =-(AP10-(AP12-AP9)) -> 0 | AQ11: =-(AQ10-(AQ12-AQ9)) -> 0 | AR11: =-(AR10-(AR12-AR9)) -> 0 | AS11: =SUM(AO11,AP11,AQ11,AR11) -> 0 | AT11: =-(AT10-(AT12-AT9)) -> 0 | AU11: =-(AU10-(AU12-AU9)) -> 0 | AV11: =-(AV10-(AV12-AV9)) -> 0 | AW11: =-(AW10-(AW12-AW9)) -> 0 | AX11: =SUM(AT11,AU11,AV11,AW11) -> 0 | AY11: =-(AY10-(AY12-AY9)) -> 0 | AZ11: =-(AZ10-(AZ12-AZ9)) -> 0 | BA11: =-(BA10-(BA12-BA9)) -> 0 | BB11: =-(BB10-(BB12-BB9)) -> 0 | BC11: =SUM(AY11,AZ11,BA11,BB11) -> 0
B12: North Italia restaurants - EoP, # of restaurants | J12: 0 | K12: 0 | L12: 0 | M12: 0 | N12: 0 | O12: 0 | P12: 0 | Q12: 0 | R12: 0 | S12: 0 | T12: 0 | U12: 0 | V12: 0 | W12: 0 | X12: 0 | Y12: 0 | Z12: 0 | AA12: 0 | AB12: 0 | AC12: 0 | AD12: 0 | AG12: 21 | AH12: =AH9+AH10+AH11 -> 22 | AI12: =AH12 -> 22 | AJ12: 23 | AK12: 23 | AL12: 23 | AM12: =AM9+AM10+AM11 -> 23 | AN12: =AM12 -> 23 | AO12: 24 | AP12: 26 | AQ12: 28 | AR12: 29 | AS12: =AR12 -> 29 | AT12: 29 | AU12: 30 | AV12: 31 | AW12: 33 | AX12: =AW12 -> 33 | AY12: 33 | AZ12: 33 | BA12: 33 | BB12: 36 | BC12: =BB12 -> 36 | BD12: =BD9+BD10 -> 40 | BE12: =BE9+BE10 -> 44 | BF12: =BF9+BF10 -> 48 | BG12: =BG9+BG10 -> 53 | BH12: =BH9+BH10 -> 58
B13: Y/Y NI restaurant growth, % | J13: 0 | K13: 0 | L13: 0 | M13: 0 | N13: 0 | O13: 0 | P13: 0 | Q13: 0 | R13: 0 | S13: 0 | T13: 0 | U13: 0 | V13: 0 | W13: 0 | X13: 0 | Y13: 0 | Z13: 0 | AA13: 0 | AB13: 0 | AC13: 0 | AD13: 0 | AL13: =AL12/AG12-1 -> 0.095238095 | AM13: =AM12/AH12-1 -> 0.045454545 | AN13: =AN12/AI12-1 -> 0.045454545 | AO13: =AO12/AJ12-1 -> 0.043478261 | AP13: =AP12/AK12-1 -> 0.13043478 | AQ13: =AQ12/AL12-1 -> 0.2173913 | AR13: =AR12/AM12-1 -> 0.26086957 | AS13: =AS12/AN12-1 -> 0.26086957 | ... BC13: =BC12/AX12-1 -> 0.090909091
B14: North Italia restaurants - Average, # of restaurants | J14: 0 | K14: 0 | L14: 0 | M14: 0 | N14: 0 | O14: 0 | P14: 0 | Q14: 0 | R14: 0 | S14: 0 | T14: 0 | U14: 0 | V14: 0 | W14: 0 | X14: 0 | Y14: 0 | Z14: 0 | AA14: 0 | AB14: 0 | AC14: 0 | AD14: 0 | AH14: =AVERAGE(AH9,AH12) -> 21.5 | AI14: =AH14 -> 21.5 | AJ14: =AVERAGE(AJ9,AJ12) -> 22.5 | AK14: =AVERAGE(AK9,AK12) -> 23 | AL14: =AVERAGE(AL9,AL12) -> 23 | AM14: =AVERAGE(AM9,AM12) -> 23 | AN14: =AM14 -> 23 | AO14: =AVERAGE(AO9,AO12) -> 23.5 | AP14: =AVERAGE(AP9,AP12) -> 25 | AQ14: =AVERAGE(AQ9,AQ12) -> 27 | AR14: =AVERAGE(AR9,AR12) -> 28.5 | AS14: =AR14 -> 28.5 | AT14: =AVERAGE(AT9,AT12) -> 29 | AU14: =AVERAGE(AU9,AU12) -> 29.5 | AV14: =AVERAGE(AV9,AV12) -> 30.5 | AW14: =AVERAGE(AW9,AW12) -> 32 | AX14: =AW14 -> 32 | AY14: =AVERAGE(AY9,AY12) -> 33 | AZ14: =AVERAGE(AZ9,AZ12) -> 33 | BA14: =AVERAGE(BA9,BA12) -> 33 | BB14: =AVERAGE(BB9,BB12) -> 34.5 | BC14: =BB14 -> 34.5 | BD14: =AVERAGE(BD9,BD12) -> 38 | BE14: =AVERAGE(BE9,BE12) -> 42 | BF14: =AVERAGE(BF9,BF12) -> 46 | BG14: =AVERAGE(BG9,BG12) -> 50.5 | BH14: =AVERAGE(BH9,BH12) -> 55.5
J15: 0 | K15: 0 | L15: 0 | M15: 0 | N15: 0 | O15: 0 | P15: 0 | Q15: 0 | R15: 0 | S15: 0 | T15: 0 | U15: 0 | V15: 0 | W15: 0 | X15: 0 | Y15: 0 | Z15: 0 | AA15: 0 | AB15: 0 | AC15: 0 | AD15: 0
J16: 0 | K16: 0 | L16: 0 | M16: 0 | N16: 0 | O16: 0 | P16: 0 | Q16: 0 | R16: 0 | S16: 0 | T16: 0 | U16: 0 | V16: 0 | W16: 0 | X16: 0 | Y16: 0 | Z16: 0 | AA16: 0 | AB16: 0 | AC16: 0 | AD16: 0
B17: Total Operating Weeks | J17: 0 | K17: 0 | L17: 0 | M17: 0 | N17: 0 | O17: 0 | P17: 0 | Q17: 0 | R17: 0 | S17: 0 | T17: 0 | U17: 0 | V17: 0 | W17: 0 | X17: 0 | Y17: 0 | Z17: 0 | AA17: 0 | AB17: 0 | AC17: 0 | AD17: 0 | AH17: 280 | AI17: =AH17 -> 280 | AJ17: 290 | AK17: 261 | AL17: 296 | AM17: 299 | AN17: 1146 | AO17: 303 | AP17: 328 | AQ17: 349 | AR17: 372 | AS17: 1352 | AT17: 377 | AU17: 378 | AV17: 395 | AW17: 454 | AX17: 1604 | AY17: 429 | AZ17: 429 | BA17: 429 | BB17: 442 | BC17: 1729 | BD17: =BD14*BD18 -> 1904.5779 | BE17: =BE14*BE18 -> 2104.9647 | BF17: =BF14*BF18 -> 2305.4375 | BG17: =BG14*BG18 -> 2530.9694 | BH17: =BH14*BH18 -> 2781.5605
B18: Operating Weeks / Store | J18: 0 | K18: 0 | L18: 0 | M18: 0 | N18: 0 | O18: 0 | P18: 0 | Q18: 0 | R18: 0 | S18: 0 | T18: 0 | U18: 0 | V18: 0 | W18: 0 | X18: 0 | Y18: 0 | Z18: 0 | AA18: 0 | AB18: 0 | AC18: 0 | AD18: 0 | AH18: =AH17/AH14 -> 13.023256 | AI18: =AI17/AI14 -> 13.023256 | AJ18: =AJ17/AJ14 -> 12.888889 | AK18: =AK17/AK14 -> 11.347826 | AL18: =AL17/AL14 -> 12.869565 | AM18: =AM17/AM14 -> 13 | AN18: =AN17/AN14 -> 49.826087 | AO18: =AO17/AO14 -> 12.893617 | ... BC18: =BC17/BC14 -> 50.115942 | BD18: =AVERAGE(BC18,AX18) -> 50.120471 | BE18: =AVERAGE(BD18,BC18) -> 50.118207 | BF18: =AVERAGE(BC18,BD18) -> 50.118207 | BG18: =AVERAGE(BF18,BE18) -> 50.118207 | BH18: =AVERAGE(BG18,BF18) -> 50.118207
J19: 0 | K19: 0 | L19: 0 | M19: 0 | N19: 0 | O19: 0 | P19: 0 | Q19: 0 | R19: 0 | S19: 0 | T19: 0 | U19: 0 | V19: 0 | W19: 0 | X19: 0 | Y19: 0 | Z19: 0 | AA19: 0 | AB19: 0 | AC19: 0 | AD19: 0
B20: Aggregate Revenue | J20: 0 | K20: 0 | L20: 0 | M20: 0 | N20: 0 | O20: 0 | P20: 0 | Q20: 0 | R20: 0 | S20: 0 | T20: 0 | U20: 0 | V20: 0 | W20: 0 | X20: 0 | Y20: 0 | Z20: 0 | AA20: 0 | AB20: 0 | AC20: 0 | AD20: 0
B21: Weekly Store Level Revenue (avg in $k) | J21: 0 | K21: 0 | L21: 0 | M21: 0 | N21: 0 | O21: 0 | P21: 0 | Q21: 0 | R21: 0 | S21: 0 | T21: 0 | U21: 0 | V21: 0 | W21: 0 | X21: 0 | Y21: 0 | Z21: 0 | AA21: 0 | AB21: 0 | AC21: 0 | AD21: 0 | AH21: =AH24/AH17*1000 -> 125.95714 | AI21: =AI24/AI17*1000 -> 125.95714 | AJ21: =AJ24/AJ17*1000 -> 105.21379 | AK21: =AK24/AK17*1000 -> 52.716475 | AL21: =AL24/AL17*1000 -> 94.560811 | AM21: =AM24/AM17*1000 -> 101.41806 | AN21: =AN24/AN17*1000 -> 89.515707 | AO21: =AO24/AO17*1000 -> 108.32673 | ... BC21: =BC24/BC17*1000 -> 149.72701 | BD21: =BC21*(1+'Forecast Assumptions'!G14) -> 155.71609 | BE21: =BD21*(1+'Forecast Assumptions'!H14) -> 161.94473 | BF21: =BE21*(1+'Forecast Assumptions'!I14) -> 168.42252 | BG21: =BF21*(1+'Forecast Assumptions'!J14) -> 175.15942 | BH21: =BG21*(1+'Forecast Assumptions'!K14) -> 182.1658
B22: Annual Store Level Revenue (avg in $mm) | J22: 0 | K22: 0 | L22: 0 | M22: 0 | N22: 0 | O22: 0 | P22: 0 | Q22: 0 | R22: 0 | S22: 0 | T22: 0 | U22: 0 | V22: 0 | W22: 0 | X22: 0 | Y22: 0 | Z22: 0 | AA22: 0 | AB22: 0 | AC22: 0 | AD22: 0 | AH22: =AH21*AH18/1000 -> 1.6403721 | AI22: =AI21*AI18/1000 -> 1.6403721 | AJ22: =AJ21*AJ18/1000 -> 1.3560889 | AK22: =AK21*AK18/1000 -> 0.59821739 | AL22: =AL21*AL18/1000 -> 1.2169565 | AM22: =AM21*AM18/1000 -> 1.3184348 | AN22: =AN21*AN18/1000 -> 4.4602174 | AO22: =AO21*AO18/1000 -> 1.3967234 | ... BH22: =BH21*BH18/1000 -> 9.1298232
J23: 0 | K23: 0 | L23: 0 | M23: 0 | N23: 0 | O23: 0 | P23: 0 | Q23: 0 | R23: 0 | S23: 0 | T23: 0 | U23: 0 | V23: 0 | W23: 0 | X23: 0 | Y23: 0 | Z23: 0 | AA23: 0 | AB23: 0 | AC23: 0 | AD23: 0
B24: North Italia Revenue, mm | J24: 0 | K24: 0 | L24: 0 | M24: 0 | N24: 0 | O24: 0 | P24: 0 | Q24: 0 | R24: 0 | S24: 0 | T24: 0 | U24: 0 | V24: 0 | W24: 0 | X24: 0 | Y24: 0 | Z24: 0 | AA24: 0 | AB24: 0 | AC24: 0 | AD24: 0 | AH24: =AI24-SUM(AE24,AF24,AG24) -> 35.268 | AI24: 35.268 | AJ24: 30.512 | AK24: 13.759 | AL24: 27.99 | AM24: =AN24-SUM(AJ24,AK24,AL24) -> 30.324 | AN24: 102.585 | AO24: 32.823 | AP24: 43.566 | AQ24: 44.357 | AR24: =AS24-SUM(AO24,AP24,AQ24) -> 51.155 | AS24: 171.901 | AT24: 52.757 | AU24: 56.238 | AV24: 54.113 | AW24: =AX24-SUM(AT24,AU24,AV24) -> 65.514 | AX24: 228.622 | AY24: 63.303 | AZ24: 65.934 | BA24: 62.417 | BB24: =BC24-SUM(AY24,AZ24,BA24) -> 67.224 | BC24: 258.878 | BD24: =BD22*BD14 -> 296.57342 | BE24: =BE22*BE14 -> 340.88794 | BF24: =BF22*BF14 -> 388.2876 | BG24: =BG22*BG14 -> 443.32315 | BH24: =BH22*BH14 -> 506.70519

Sheet Revenue Build - FRC & Others
N2: Actual
B4: Period Ended | J4: 41730 | K4: 41821 | L4: 41912 | M4: 42003 | N4: 42003 | O4: 42094 | P4: 42185 | Q4: 42276 | R4: 42367 | S4: 42367 | T4: 42458 | U4: 42549 | V4: 42640 | W4: 42738 | X4: 42738 | Y4: 42829 | Z4: 42920 | AA4: 43011 | AB4: 43102 | AC4: 43102 | AD4: 43193 | AE4: 43284 | AF4: 43375 | AG4: 43466 | AH4: 43466 | AI4: 43557 | AJ4: 43648 | AK4: 43739 | AL4: 43830 | AM4: 43830 | AN4: 43921 | AO4: 44012 | AP4: 44103 | AQ4: 44194 | AR4: 44194 | AS4: 44285 | AT4: 44376 | AU4: 44467 | AV4: 44558 | AW4: 44558 | AX4: 44649 | AY4: 44740 | AZ4: 44831 | BA4: 44929 | BB4: 44929 | BC4: 45019 | BD4: 45111 | BE4: 45202 | BF4: 45293 | BG4: 45293 | BH4: Consolidated Below from Forecast Assumptions
J5: Q1-2014 | K5: Q2-2014 | L5: Q3-2014 | M5: Q4-2014 | N5: FY2014 | O5: Q1-2015 | P5: Q2-2015 | Q5: Q3-2015 | R5: Q4-2015 | S5: FY2015 | T5: Q1-2016 | U5: Q2-2016 | V5: Q3-2016 | W5: Q4-2016 | X5: FY2016 | Y5: Q1-2017 | Z5: Q2-2017 | AA5: Q3-2017 | AB5: Q4-2017 | AC5: FY2017 | AD5: Q1-2018 | AE5: Q2-2018 | AF5: Q3-2018 | AG5: Q4-2018 | AH5: FY2018 | AI5: Q1-2019 | AJ5: Q2-2019 | AK5: Q3-2019 | AL5: Q4-2019 | AM5: FY2019 | AN5: Q1-2020 | AO5: Q2-2020 | AP5: Q3-2020 | AQ5: Q4-2020 | AR5: FY2020 | AS5: Q1-2021 | AT5: Q2-2021 | AU5: Q3-2021 | AV5: Q4-2021 | AW5: FY2021 | AX5: Q1-2022 | AY5: Q2-2022 | AZ5: Q3-2022 | BA5: Q4-2022 | BB5: FY2022 | BC5: Q1-2023 | BD5: Q2-2023 | BE5: Q3-2023 | BF5: Q4-2023 | BG5: FY2023 | BH5: FY2024E | BI5: FY2025E | BJ5: FY2026E | BK5: FY2027E | BL5: FY2028E
B7: FRC Revenue Build
B9: Fox Restaurant Concepts restaurants - BoP, # of restaurants | J9: 0 | K9: 0 | L9: 0 | M9: 0 | N9: 0 | O9: 0 | P9: 0 | Q9: 0 | R9: 0 | S9: 0 | T9: 0 | U9: 0 | V9: 0 | W9: 0 | X9: 0 | Y9: 0 | Z9: 0 | AA9: 0 | AB9: 0 | AC9: 0 | AD9: 0 | AE9: 0 | AF9: 0 | AG9: 0 | AH9: 0 | AI9: 0 | AJ9: 0 | AL9: =AK12 -> 25 | AM9: =AH12 -> 0 | AN9: =AM12 -> 25 | AO9: =AN12 -> 25 | AP9: =AO12 -> 25 | AQ9: =AP12 -> 25 | AR9: =AM12 -> 25 | AS9: =AR12 -> 27 | AT9: =AS12 -> 28 | AU9: =AT12 -> 28 | AV9: =AU12 -> 29 | AW9: =AR12 -> 27 | AX9: =AW12 -> 31 | AY9: =AX12 -> 31 | AZ9: =AY12 -> 31 | BA9: =AZ12 -> 32 | BB9: =AW12 -> 31 | BC9: =BB12 -> 34 | BD9: =BC12 -> 35 | BE9: =BD12 -> 37 | BF9: =BE12 -> 37 | BG9: =BB12 -> 34
B10: Fox Restaurant Concepts opened, # of restaurants | J10: 0 | K10: 0 | L10: 0 | M10: 0 | N10: 0 | O10: 0 | P10: 0 | Q10: 0 | R10: 0 | S10: 0 | T10: 0 | U10: 0 | V10: 0 | W10: 0 | X10: 0 | Y10: 0 | Z10: 0 | AA10: 0 | AB10: 0 | AC10: 0 | AD10: 0 | AE10: 0 | AF10: 0 | AG10: 0 | AH10: 0 | AI10: 0 | AJ10: 0 | AL10: 0 | AM10: =AL10+AK12 -> 25 | AN10: 0 | AO10: 0 | AP10: 0 | AQ10: 2 | AR10: =SUM(AN10,AO10,AP10,AQ10) -> 2 | AS10: 1 | AT10: 0 | AU10: 1 | AV10: 2 | AW10: =SUM(AS10,AT10,AU10,AV10) -> 4 | AX10: 0 | AY10: 0 | AZ10: 1 | BA10: 2 | BB10: =SUM(AX10,AY10,AZ10,BA10) -> 3 | BC10: 1 | BD10: 2 | BE10: 0 | BF10: 3 | BG10: =SUM(BC10,BD10,BE10,BF10) -> 6
B11: Fox Restaurant Concepts closed, # of restaurants | J11: 0 | K11: 0 | L11: 0 | M11: 0 | N11: 0 | O11: 0 | P11: 0 | Q11: 0 | R11: 0 | S11: 0 | T11: 0 | U11: 0 | V11: 0 | W11: 0 | X11: 0 | Y11: 0 | Z11: 0 | AA11: 0 | AB11: 0 | AC11: 0 | AD11: 0 | AE11: 0 | AF11: 0 | AG11: 0 | AH11: 0 | AI11: 0 | AJ11: 0 | AL11: 0 | AM11: 0 | AN11: =AN12-AN9-AN10 -> 0 | AO11: =AO12-AO9-AO10 -> 0 | AP11: =AP12-AP9-AP10 -> 0 | AQ11: 0 | AR11: =SUM(AN11,AO11,AP11,AQ11) -> 0 | AS11: =AS12-AS9-AS10 -> 0 | AT11: =AT12-AT9-AT10 -> 0 | AU11: =AU12-AU9-AU10 -> 0 | AV11: =AV12-AV9-AV10 -> 0 | AW11: =SUM(AS11,AT11,AU11,AV11) -> 0 | AX11: =AX12-AX9-AX10 -> 0 | AY11: =AY12-AY9-AY10 -> 0 | AZ11: =AZ12-AZ9-AZ10 -> 0 | BA11: =BA12-BA9-BA10 -> 0 | BB11: =SUM(AX11,AY11,AZ11,BA11) -> 0 | BC11: =BC12-BC9-BC10 -> 0 | BD11: =BD12-BD9-BD10 -> 0 | BE11: =BE12-BE9-BE10 -> 0 | BF11: =BF12-BF9-BF10 -> 0 | BG11: =SUM(BC11,BD11,BE11,BF11) -> 0
B12: Fox Restaurant Concepts restaurants - EoP, # of restaurants | J12: 0 | K12: 0 | L12: 0 | M12: 0 | N12: 0 | O12: 0 | P12: 0 | Q12: 0 | R12: 0 | S12: 0 | T12: 0 | U12: 0 | V12: 0 | W12: 0 | X12: 0 | Y12: 0 | Z12: 0 | AA12: 0 | AB12: 0 | AC12: 0 | AD12: 0 | AE12: 0 | AF12: 0 | AG12: 0 | AH12: 0 | AI12: 0 | AJ12: 0 | AK12: 25 | AL12: =AL9+AL10+AL11 -> 25 | AM12: =AL12 -> 25 | AN12: 25 | AO12: 25 | AP12: 25 | AQ12: =AQ9+AQ10+AQ11 -> 27 | AR12: =AQ12 -> 27 | AS12: 28 | AT12: 28 | AU12: 29 | AV12: 31 | AW12: =AV12 -> 31 | AX12: 31 | AY12: 31 | AZ12: 32 | BA12: 34 | BB12: =BA12 -> 34 | BC12: 35 | BD12: 37 | BE12: 37 | BF12: 40 | BG12: =BF12 -> 40
B13: Fox Restaurant Concepts restaurants - Average, # of restaurants | J13: 0 | K13: 0 | L13: 0 | M13: 0 | N13: 0 | O13: 0 | P13: 0 | Q13: 0 | R13: 0 | S13: 0 | T13: 0 | U13: 0 | V13: 0 | W13: 0 | X13: 0 | Y13: 0 | Z13: 0 | AA13: 0 | AB13: 0 | AC13: 0 | AD13: 0 | AE13: 0 | AF13: 0 | AG13: 0 | AH13: 0 | AI13: 0 | AJ13: 0 | AL13: =AVERAGE(AL9,AL12) -> 25 | AM13: =AL13 -> 25 | AN13: =AVERAGE(AN9,AN12) -> 25 | AO13: =AVERAGE(AO9,AO12) -> 25 | AP13: =AVERAGE(AP9,AP12) -> 25 | AQ13: =AVERAGE(AQ9,AQ12) -> 26 | AR13: =AQ13 -> 26 | AS13: =AVERAGE(AS9,AS12) -> 27.5 | AT13: =AVERAGE(AT9,AT12) -> 28 | AU13: =AVERAGE(AU9,AU12) -> 28.5 | AV13: =AVERAGE(AV9,AV12) -> 30 | AW13: =AV13 -> 30 | AX13: =AVERAGE(AX9,AX12) -> 31 | AY13: =AVERAGE(AY9,AY12) -> 31 | AZ13: =AVERAGE(AZ9,AZ12) -> 31.5 | BA13: =AVERAGE(BA9,BA12) -> 33 | BB13: =BA13 -> 33 | BC13: =AVERAGE(BC9,BC12) -> 34.5 | BD13: =AVERAGE(BD9,BD12) -> 36 | BE13: =AVERAGE(BE9,BE12) -> 37 | BF13: =AVERAGE(BF9,BF12) -> 38.5 | BG13: =BF13 -> 38.5
B15: FRC Revenue | J15: 0 | K15: 0 | L15: 0 | M15: 0 | N15: 0 | O15: 0 | P15: 0 | Q15: 0 | R15: 0 | S15: 0 | T15: 0 | U15: 0 | V15: 0 | W15: 0 | X15: 0 | Y15: 0 | Z15: 0 | AA15: 0 | AB15: 0 | AC15: 0 | AD15: 0 | AE15: 0 | AF15: 0 | AG15: 0 | AH15: 0 | AI15: 0 | AJ15: 0 | AL15: =AM15-SUM(AI15,AJ15,AK15) -> 39.335 | AM15: 39.335 | AN15: 35.583 | AO15: 12.208 | AP15: 20.273 | AQ15: =AR15-SUM(AN15,AO15,AP15) -> 28.792 | AR15: 96.856 | AS15: 36.194 | AT15: 47.458 | AU15: 44.326 | AV15: =AW15-SUM(AS15,AT15,AU15) -> 54.197 | AW15: 182.175 | AX15: 58.832 | AY15: 60.02 | AZ15: 52.193 | BA15: =BB15-SUM(AX15,AY15,AZ15) -> 66.507 | BB15: 237.552 | BC15: 68.64 | BD15: 65.728 | BE15: 58.642 | BF15: =BG15-SUM(BC15,BD15,BE15) -> 70.913 | BG15: 263.923
B17: FRC Sales/Store | J17: 0 | K17: 0 | L17: 0 | M17: 0 | N17: 0 | O17: 0 | P17: 0 | Q17: 0 | R17: 0 | S17: 0 | T17: 0 | U17: 0 | V17: 0 | W17: 0 | X17: 0 | Y17: 0 | Z17: 0 | AA17: 0 | AB17: 0 | AC17: 0 | AD17: 0 | AE17: 0 | AF17: 0 | AG17: 0 | AH17: 0 | AI17: 0 | AJ17: 0 | AL17: =AL15/AL13 -> 1.5734 | AM17: =AM15/AM13 -> 1.5734 | AN17: =AN15/AN13 -> 1.42332 | AO17: =AO15/AO13 -> 0.48832 | AP17: =AP15/AP13 -> 0.81092 | AQ17: =AQ15/AQ13 -> 1.1073846 | AR17: =AR15/AR13 -> 3.7252308 | AS17: =AS15/AS13 -> 1.3161455 | ... BG17: =BG15/BG13 -> 6.8551429
B19: Other Restaurants
B21: Grand Lux Cafe restaurants BoP, # of restaurants | J21: =I24 -> 0 | K21: =J24 -> 0 | L21: =K24 -> 0 | M21: =L24 -> 0 | N21: =I24 -> 0 | O21: =N24 -> 0 | P21: =O24 -> 0 | Q21: =P24 -> 1 | R21: =Q24 -> 1 | S21: =N24 -> 0 | T21: =S24 -> 1 | U21: =T24 -> 1 | V21: =U24 -> 1 | W21: =V24 -> 1 | X21: =S24 -> 1 | Y21: =X24 -> 13 | Z21: =Y24 -> 13 | AA21: =Z24 -> 13 | AB21: =AA24 -> 13 | AC21: =X24 -> 13 | AD21: =AC24 -> 13 | AE21: =AD24 -> 13 | AF21: =AE24 -> 13 | AG21: =AF24 -> 14 | AH21: =AC24 -> 13 | AI21: =AH24 -> 14 | AJ21: =AI24 -> 14 | AK21: 14 | AL21: =AK24 -> 14 | AM21: =AH24 -> 14 | AN21: =AM24 -> 13
B22: Grand Lux Number of restaurants opened, # of restaurants | J22: 0 | K22: 0 | L22: 0 | M22: 0 | N22: =SUM(J22,K22,L22,M22) -> 0 | O22: 0 | P22: 1 | Q22: 0 | R22: 0 | S22: =SUM(O22,P22,Q22,R22) -> 1 | T22: 0 | U22: 0 | V22: 0 | W22: 1 | X22: =SUM(T22,U22,V22,W22) -> 1 | Y22: 0 | Z22: 0 | AA22: 0 | AB22: 0 | AC22: =SUM(Y22,Z22,AA22,AB22) -> 0 | AD22: 0 | AE22: 0 | AF22: 1 | AG22: 0 | AH22: =SUM(AD22,AE22,AF22,AG22) -> 1 | AI22: 0 | AJ22: 0 | AK22: 0 | AL22: 0 | AM22: =SUM(AI22,AJ22,AK22,AL22) -> 0 | AN22: 0
B23: Grand Lux Number of restaurants closed, # of restaurants | J23: 0 | K23: 0 | L23: 0 | M23: 0 | N23: =SUM(J23,K23,L23,M23) -> 0 | O23: 0 | P23: 0 | Q23: 0 | R23: 0 | S23: =SUM(O23,P23,Q23,R23) -> 0 | T23: 0 | U23: 0 | V23: 0 | W23: 0 | X23: =SUM(T23,U23,V23,W23) -> 0 | Y23: 0 | Z23: 0 | AA23: 0 | AB23: 0 | AC23: =SUM(Y23,Z23,AA23,AB23) -> 0 | AD23: 0 | AE23: 0 | AF23: 0 | AG23: =-(AG22-(AG24-AG21)) -> 0 | AH23: =SUM(AD23,AE23,AF23,AG23) -> 0 | AI23: =-(AI22-(AI24-AI21)) -> 0 | AJ23: =-(AJ22-(AJ24-AJ21)) -> 0 | AK23: 0 | AL23: =-(AL22-(AL24-AL21)) -> -1 | AM23: =SUM(AI23,AJ23,AK23,AL23) -> -1 | AN23: =-(AN22-(AN24-AN21)) -> 0
B24: Grand Lux Cafe restaurants EoP, # of restaurants | J24: =SUM(J21:J23) -> 0 | K24: =SUM(K21:K23) -> 0 | L24: =SUM(L21:L23) -> 0 | M24: =SUM(M21:M23) -> 0 | N24: =SUM(N21:N23) -> 0 | O24: =SUM(O21:O23) -> 0 | P24: =SUM(P21:P23) -> 1 | Q24: =SUM(Q21:Q23) -> 1 | ... W24: =SUM(W21:W23) -> 2 | X24: 13 | Y24: =SUM(Y21:Y23) -> 13 | Z24: =SUM(Z21:Z23) -> 13 | AA24: =SUM(AA21:AA23) -> 13 | AB24: =SUM(AB21:AB23) -> 13 | AC24: =SUM(AC21:AC23) -> 13 | AD24: =SUM(AD21:AD23) -> 13 | AE24: =SUM(AE21:AE23) -> 13 | AF24: =SUM(AF21:AF23) -> 14 | AG24: 14 | AH24: =SUM(AH21:AH23) -> 14 | AI24: 14 | AJ24: 14 | AK24: 14 | AL24: 13 | AM24: =SUM(AM21:AM23) -> 13 | AN24: 13
B26: RockSugar Southeast Asian Kitchen restaurants BOP, # of restaurants | J26: =I29 -> 0 | K26: =J29 -> 0 | L26: =K29 -> 0 | M26: =L29 -> 0 | N26: =I29 -> 0 | O26: =N29 -> 0 | P26: =O29 -> 0 | Q26: =P29 -> 0 | R26: =Q29 -> 0 | S26: =N29 -> 0 | T26: =S29 -> 0 | U26: =T29 -> 0 | V26: =U29 -> 0 | W26: =V29 -> 0 | X26: =S29 -> 0 | Y26: =X29 -> 0 | Z26: =Y29 -> 0 | AA26: =Z29 -> 0 | AB26: =AA29 -> 0 | AC26: =X29 -> 0 | AD26: =AC29 -> 1 | AE26: =AD29 -> 1 | AF26: =AE29 -> 1 | AG26: =AF29 -> 1 | AH26: =AC29 -> 1 | AI26: =AH29 -> 2 | AJ26: =AI29 -> 2 | AK26: =AJ29 -> 2 | AL26: =AK29 -> 2 | AM26: =AH29 -> 2 | AN26: =AM29 -> 1
B27: RockSugar Number of restaurants opened, # of restaurants | J27: 0 | K27: 0 | L27: 0 | M27: 0 | N27: =SUM(J27,K27,L27,M27) -> 0 | O27: 0 | P27: 0 | Q27: 0 | R27: 0 | S27: =SUM(O27,P27,Q27,R27) -> 0 | T27: 0 | U27: 0 | V27: 0 | W27: 0 | X27: =SUM(T27,U27,V27,W27) -> 0 | Y27: 0 | Z27: 0 | AA27: 0 | AB27: 1 | AC27: =SUM(Y27,Z27,AA27,AB27) -> 1 | AD27: 0 | AE27: 0 | AF27: 0 | AG27: 0 | AH27: =SUM(AD27,AE27,AF27,AG27) -> 0 | AI27: 0 | AJ27: 0 | AK27: 0 | AM27: =SUM(AI27,AJ27,AK27,AL27) -> 0 | AN27: 0
B28: RockSugar Number of restaurants closed, # of restaurants | J28: 0 | K28: 0 | L28: 0 | M28: 0 | N28: =SUM(J28,K28,L28,M28) -> 0 | O28: 0 | P28: 0 | Q28: 0 | R28: 0 | S28: =SUM(O28,P28,Q28,R28) -> 0 | T28: 0 | U28: 0 | V28: 0 | W28: 0 | X28: =SUM(T28,U28,V28,W28) -> 0 | Y28: 0 | Z28: 0 | AA28: 0 | AB28: 0 | AC28: =SUM(Y28,Z28,AA28,AB28) -> 0 | AD28: 0 | AE28: 0 | AF28: 0 | AG28: =-(AG27-(AG29-AG26)) -> 1 | AH28: =SUM(AD28,AE28,AF28,AG28) -> 1 | AI28: =-(AI27-(AI29-AI26)) -> 0 | AJ28: =-(AJ27-(AJ29-AJ26)) -> 0 | AK28: 0 | AL28: =-(AL27-(AL29-AL26)) -> -1 | AM28: =SUM(AI28,AJ28,AK28,AL28) -> -1 | AN28: =-(AN27-(AN29-AN26)) -> 0
B29: RockSugar Southeast Asian Kitchen restaurants EoP, # of restaurants | J29: =SUM(J26:J28) -> 0 | K29: =SUM(K26:K28) -> 0 | L29: =SUM(L26:L28) -> 0 | M29: =SUM(M26:M28) -> 0 | N29: =SUM(N26:N28) -> 0 | O29: =SUM(O26:O28) -> 0 | P29: =SUM(P26:P28) -> 0 | Q29: =SUM(Q26:Q28) -> 0 | ... AF29: =SUM(AF26:AF28) -> 1 | AG29: 2 | AH29: =SUM(AH26:AH28) -> 2 | AI29: 2 | AJ29: 2 | AK29: 2 | AL29: 1 | AM29: =SUM(AM26:AM28) -> 1 | AN29: 1
B31: Social Monk Asian Kitchen BoP, # of restaurants | J31: 0 | K31: 0 | L31: 0 | M31: 0 | N31: 0 | O31: 0 | P31: 0 | Q31: 0 | R31: 0 | S31: 0 | T31: 0 | U31: 0 | V31: 0 | W31: 0 | X31: 0 | Y31: 0 | Z31: 0 | AA31: 0 | AB31: 0 | AC31: 0 | AD31: 0 | AE31: 0 | AF31: 0 | AG31: 0 | AH31: 0 | AI31: =AH34 -> 1 | AJ31: =AI34 -> 1 | AK31: =AJ34 -> 1 | AL31: =AK34 -> 1 | AM31: =AH34 -> 1 | AN31: =AM34 -> 1
B32: Social Monk Number of restaurants opened, # of restaurants | J32: 0 | K32: 0 | L32: 0 | M32: 0 | N32: 0 | O32: 0 | P32: 0 | Q32: 0 | R32: 0 | S32: 0 | T32: 0 | U32: 0 | V32: 0 | W32: 0 | X32: 0 | Y32: 0 | Z32: 0 | AA32: 0 | AB32: 0 | AC32: 0 | AD32: 0 | AE32: 0 | AF32: 0 | AG32: 1 | AH32: 1 | AI32: 0 | AJ32: 0 | AK32: 0 | AN32: 0
B33: Social Monk Number of restaurants closed, # of restaurants | J33: 0 | K33: 0 | L33: 0 | M33: 0 | N33: 0 | O33: 0 | P33: 0 | Q33: 0 | R33: 0 | S33: 0 | T33: 0 | U33: 0 | V33: 0 | W33: 0 | X33: 0 | Y33: 0 | Z33: 0 | AA33: 0 | AB33: 0 | AC33: 0 | AD33: 0 | AE33: 0 | AF33: 0 | AG33: =-(AG32-(AG34-AG31)) -> 0 | AH33: =-(AH32-(AH34-AH31)) -> 0 | AI33: =-(AI32-(AI34-AI31)) -> 0 | AJ33: =-(AJ32-(AJ34-AJ31)) -> 0 | AK33: 0 | AL33: =-(AL32-(AL34-AL31)) -> 0 | AM33: =-(AM32-(AM34-AM31)) -> 0 | AN33: =-(AN32-(AN34-AN31)) -> 0
B34: Social Monk Asian Kitchen EoP, # of restaurants | J34: 0 | K34: 0 | L34: 0 | M34: 0 | N34: 0 | O34: 0 | P34: 0 | Q34: 0 | R34: 0 | S34: 0 | T34: 0 | U34: 0 | V34: 0 | W34: 0 | X34: 0 | Y34: 0 | Z34: 0 | AA34: 0 | AB34: 0 | AC34: 0 | AD34: 0 | AE34: 0 | AF34: 0 | AG34: 1 | AH34: 1 | AI34: 1 | AJ34: 1 | AK34: 1 | AL34: 1 | AM34: =AL34 -> 1 | AN34: 1
B36: Flower Child restaurants BOP, # of restaurants | J36: 0 | K36: 0 | L36: 0 | M36: 0 | N36: 0 | O36: 0 | P36: 0 | Q36: 0 | R36: 0 | S36: 0 | T36: 0 | U36: 0 | V36: 0 | W36: 0 | X36: 0 | Y36: 0 | Z36: 0 | AA36: 0 | AB36: 0 | AC36: 0 | AD36: 0 | AE36: 0 | AF36: 0 | AG36: 0 | AH36: 0 | AI36: 0 | AJ36: 0 | AL36: =AK39 -> 22 | AN36: =AM39 -> 24
B37: Flower Child restaurants opened, # of restaurants | J37: 0 | K37: 0 | L37: 0 | M37: 0 | N37: 0 | O37: 0 | P37: 0 | Q37: 0 | R37: 0 | S37: 0 | T37: 0 | U37: 0 | V37: 0 | W37: 0 | X37: 0 | Y37: 0 | Z37: 0 | AA37: 0 | AB37: 0 | AC37: 0 | AD37: 0 | AE37: 0 | AF37: 0 | AG37: 0 | AH37: 0 | AI37: 0 | AJ37: 0 | AL37: 2 | AM37: =AK39+AL37 -> 24 | AN37: 1
B38: Flower Child restaurants closed, # of restaurants | J38: 0 | K38: 0 | L38: 0 | M38: 0 | N38: 0 | O38: 0 | P38: 0 | Q38: 0 | R38: 0 | S38: 0 | T38: 0 | U38: 0 | V38: 0 | W38: 0 | X38: 0 | Y38: 0 | Z38: 0 | AA38: 0 | AB38: 0 | AC38: 0 | AD38: 0 | AE38: 0 | AF38: 0 | AG38: 0 | AH38: 0 | AI38: 0 | AJ38: 0 | AL38: 0 | AN38: 0
B39: Flower Child restaurants EoP, # of restaurants | J39: 0 | K39: 0 | L39: 0 | M39: 0 | N39: 0 | O39: 0 | P39: 0 | Q39: 0 | R39: 0 | S39: 0 | T39: 0 | U39: 0 | V39: 0 | W39: 0 | X39: 0 | Y39: 0 | Z39: 0 | AA39: 0 | AB39: 0 | AC39: 0 | AD39: 0 | AE39: 0 | AF39: 0 | AG39: 0 | AH39: 0 | AI39: 0 | AJ39: 0 | AK39: 22 | AL39: 24 | AM39: =AL39 -> 24 | AN39: 25
B41: Other restaurants - BoP, # of restaurants | J41: =J21+J26+J31 -> 0 | K41: =K21+K26+K31 -> 0 | L41: =L21+L26+L31 -> 0 | M41: =M21+M26+M31 -> 0 | N41: =N21+N26+N31 -> 0 | O41: =O21+O26+O31 -> 0 | P41: =P21+P26+P31 -> 0 | Q41: =Q21+Q26+Q31 -> 1 | ... AJ41: =AJ21+AJ26+AJ31 -> 17 | AK41: =AK21+AK26+AK31+AK36 -> 17 | AL41: =AL21+AL26+AL31+AL36 -> 39 | AM41: =AM21+AM26+AM31+AM36 -> 17 | AN41: =AM44 -> 39 | AO41: =AN44 -> 40 | AP41: =AO44 -> 40 | AQ41: =AP44 -> 41 | AR41: =AM44 -> 39 | AS41: =AR44 -> 39 | AT41: =AS44 -> 38 | AU41: =AT44 -> 39 | AV41: =AU44 -> 40 | AW41: =AR44 -> 39 | AX41: =AW44 -> 40 | AY41: =AX44 -> 38 | AZ41: =AY44 -> 39 | BA41: =AZ44 -> 39 | BB41: =AW44 -> 40 | BC41: =BB44 -> 40 | BD41: =BC44 -> 40 | BE41: =BD44 -> 40 | BF41: =BE44 -> 40 | BG41: =BB44 -> 40
B42: Other restaurants opened, # of restaurants | J42: =J22+J27+J32 -> 0 | K42: =K22+K27+K32 -> 0 | L42: =L22+L27+L32 -> 0 | M42: =M22+M27+M32 -> 0 | N42: =N22+N27+N32 -> 0 | O42: =O22+O27+O32 -> 0 | P42: =P22+P27+P32 -> 1 | Q42: =Q22+Q27+Q32 -> 0 | ... AJ42: =AJ22+AJ27+AJ32 -> 0 | AK42: =AK22+AK27+AK32+AK37 -> 0 | AL42: =AL22+AL27+AL32+AL37 -> 2 | AM42: =AM22+AM27+AM32+AM37 -> 24 | AN42: =AN22+AN27+AN32+AN37 -> 1 | AO42: =AO22+AO27+AO32+AO37 -> 0 | AP42: 2 | AQ42: 0 | AR42: =SUM(AN42,AO42,AP42,AQ42) -> 3 | AS42: 0 | AT42: 1 | AU42: 1 | AV42: 0 | AW42: =SUM(AS42,AT42,AU42,AV42) -> 2 | AX42: 0 | AY42: 1 | AZ42: 0 | BA42: 2 | BB42: =SUM(AX42,AY42,AZ42,BA42) -> 3 | BC42: 1 | BD42: 0 | BE42: 0 | BF42: 0 | BG42: =SUM(BC42,BD42,BE42,BF42) -> 1
B43: Other restaurants closed, # of restaurants | J43: =J23+J28+J33 -> 0 | K43: =K23+K28+K33 -> 0 | L43: =L23+L28+L33 -> 0 | M43: =M23+M28+M33 -> 0 | N43: =N23+N28+N33 -> 0 | O43: =O23+O28+O33 -> 0 | P43: =P23+P28+P33 -> 0 | Q43: =Q23+Q28+Q33 -> 0 | ... AJ43: =AJ23+AJ28+AJ33 -> 0 | AK43: =AK23+AK28+AK33+AK38 -> 0 | AL43: =AL23+AL28+AL33+AL38 -> -2 | AM43: =AM23+AM28+AM33+AM38 -> -2 | AN43: =AN23+AN28+AN33+AN38 -> 0 | AO43: =AO44-AO42-AO41 -> 0 | AP43: =AP44-AP42-AP41 -> -1 | AQ43: -2 | AR43: =SUM(AN43,AO43,AP43,AQ43) -> -3 | AS43: =AS44-AS41-AS42 -> -1 | AT43: =AT44-AT42-AT41 -> 0 | AU43: =AU44-AU42-AU41 -> 0 | AV43: =AV44-AV42-AV41 -> 0 | AW43: =SUM(AS43,AT43,AU43,AV43) -> -1 | AX43: =AX44-AX41-AX42 -> -2 | AY43: =AY44-AY42-AY41 -> 0 | AZ43: =AZ44-AZ42-AZ41 -> 0 | BA43: =BA44-BA42-BA41 -> -1 | BB43: =SUM(AX43,AY43,AZ43,BA43) -> -3 | BC43: =BC44-BC41-BC42 -> -1 | BD43: =BD44-BD42-BD41 -> 0 | BE43: =BE44-BE42-BE41 -> 0 | BF43: =BF44-BF42-BF41 -> -1 | BG43: =SUM(BC43,BD43,BE43,BF43) -> -2
B44: Other restaurants - EoP, # of restaurants | J44: =SUM(J41:J43) -> 0 | K44: =SUM(K41:K43) -> 0 | L44: =SUM(L41:L43) -> 0 | M44: =SUM(M41:M43) -> 0 | N44: =SUM(N41:N43) -> 0 | O44: =SUM(O41:O43) -> 0 | P44: =SUM(P41:P43) -> 1 | Q44: =SUM(Q41:Q43) -> 1 | ... AN44: =SUM(AN41:AN43) -> 40 | AO44: 40 | AP44: 41 | AQ44: =SUM(AQ41:AQ43) -> 39 | AR44: =SUM(AR41:AR43) -> 39 | AS44: 38 | AT44: 39 | AU44: 40 | AV44: 40 | AW44: =SUM(AW41:AW43) -> 40 | AX44: 38 | AY44: 39 | AZ44: 39 | BA44: 40 | BB44: =SUM(BB41:BB43) -> 40 | BC44: 40 | BD44: 40 | BE44: 40 | BF44: 39 | BG44: =SUM(BG41:BG43) -> 39
B47: Other restaurants -- total revenue | J47: 44.825 | K47: 44.952 | L47: 44.843 | M47: 49.208 | O47: 45.156 | P47: 45.822 | Q47: 45.612 | R47: 50.261 | S47: 125.96444 | T47: 47.377 | U47: 46.944 | V47: 47.978 | W47: 55.337 | X47: 132.80961 | Y47: 48.192 | Z47: 49.641 | AA47: 47.82 | AB47: 57.033 | AC47: 132.7675 | AD47: 49.918 | AE47: 51.076 | AF47: 50.672 | AG47: 54.369 | AH47: 132.4778 | AI47: 50.848 | AJ47: 51.126 | AK47: 50.435 | AL47: =AM47-SUM(AI47,AJ47,AK47) -> -2.9859999 | AM47: 149.423 | AN47: 60.54 | AO47: 28.816 | AP47: 52.469 | AQ47: =AR47-SUM(AN47,AO47,AP47) -> -25.911665 | AR47: 115.91334 | AS47: 59.011 | AT47: 71.241 | AU47: 73.236 | AV47: =AW47-SUM(AS47,AT47,AU47) -> -14.538397 | AW47: 188.9496 | AX47: 72.305 | AY47: 75.527 | AZ47: 74.793 | BA47: =BB47-SUM(AX47,AY47,AZ47) -> -10.254833 | BB47: 212.37017 | BC47: 78.171 | BD47: 82.027 | BE47: 81.011 | BF47: =BG47-SUM(BC47,BD47,BE47) -> -19.713127 | BG47: 221.49587
B49: Total Revenue | S49: =S15+S47 -> 125.96444 | T49: =T15+T47 -> 47.377 | U49: =U15+U47 -> 46.944 | V49: =V15+V47 -> 47.978 | W49: =W15+W47 -> 55.337 | X49: =X15+X47 -> 132.80961 | Y49: =Y15+Y47 -> 48.192 | Z49: =Z15+Z47 -> 49.641 | ... BG49: =BG15+BG47 -> 485.41887 | BH49: =BG49*'Forecast Assumptions'!G15+'Revenue Build - FRC & Others'!BG49 -> 509.68982 | BI49: =BH49*'Forecast Assumptions'!H15+'Revenue Build - FRC & Others'!BH49 -> 535.17431 | BJ49: =BI49*'Forecast Assumptions'!I15+'Revenue Build - FRC & Others'!BI49 -> 561.93302 | BK49: =BJ49*'Forecast Assumptions'!J15+'Revenue Build - FRC & Others'!BJ49 -> 590.02967 | BL49: =BK49*'Forecast Assumptions'!K15+'Revenue Build - FRC & Others'!BK49 -> 619.53116
B51: Net restaurants change | J51: Net restaurants change | S51: =S10+S11+S42+S43 -> 1 | T51: =T10+T11+T42+T43 -> 0 | U51: =U10+U11+U42+U43 -> 0 | V51: =V10+V11+V42+V43 -> 0 | W51: =W10+W11+W42+W43 -> 1 | X51: =X10+X11+X42+X43 -> 1 | Y51: =Y10+Y11+Y42+Y43 -> 0 | Z51: =Z10+Z11+Z42+Z43 -> 0 | ... BG51: =BG10+BG11+BG42+BG43 -> 5 | BH51: ='Forecast Assumptions'!F11 -> 7 | BI51: ='Forecast Assumptions'!G11 -> 7 | BJ51: ='Forecast Assumptions'!H11 -> 4 | BK51: ='Forecast Assumptions'!I11 -> 5 | BL51: ='Forecast Assumptions'!J11 -> 5
B52: Total FRC & Others Restaurants EOP | S52: =S12+S44 -> 1 | T52: =T12+T44 -> 1 | U52: =U12+U44 -> 1 | V52: =V12+V44 -> 1 | W52: =W12+W44 -> 2 | X52: =X12+X44 -> 2 | Y52: =Y12+Y44 -> 13 | Z52: =Z12+Z44 -> 13 | ... BG52: =BG12+BG44 -> 79 | BH52: =BG52+BH51 -> 86 | BI52: =BH52+BI51 -> 93 | BJ52: =BI52+BJ51 -> 97 | BK52: =BJ52+BK51 -> 102 | BL52: =BK52+BL51 -> 107

Sheet Revenue Build - Franchising
B4: Period Ended | C4: 41730 | D4: 41821 | E4: 41912 | F4: 42003 | G4: 42003 | H4: 42094 | I4: 42185 | J4: 42276 | K4: 42367 | L4: 42367 | M4: 42458 | N4: 42549 | O4: 42640 | P4: 42738 | Q4: 42738 | R4: 42829 | S4: 42920 | T4: 43011 | U4: 43102 | V4: 43102 | W4: 43193 | X4: 43284 | Y4: 43375 | Z4: 43466 | AA4: 43466 | AB4: 43557 | AC4: 43648 | AD4: 43739 | AE4: 43830 | AF4: 43830 | AG4: 43921 | AH4: 44012 | AI4: 44103 | AJ4: 44194 | AK4: 44194 | AL4: 44285 | AM4: 44376 | AN4: 44467 | AO4: 44558 | AP4: 44558 | AQ4: 44649 | AR4: 44740 | AS4: 44831 | AT4: 44929 | AU4: 44929 | AV4: 45019 | AW4: 45111 | AX4: 45202 | AY4: 45293 | AZ4: 45293
C5: Q1-2014 | D5: Q2-2014 | E5: Q3-2014 | F5: Q4-2014 | G5: FY2014 | H5: Q1-2015 | I5: Q2-2015 | J5: Q3-2015 | K5: Q4-2015 | L5: FY2015 | M5: Q1-2016 | N5: Q2-2016 | O5: Q3-2016 | P5: Q4-2016 | Q5: FY2016 | R5: Q1-2017 | S5: Q2-2017 | T5: Q3-2017 | U5: Q4-2017 | V5: FY2017 | W5: Q1-2018 | X5: Q2-2018 | Y5: Q3-2018 | Z5: Q4-2018 | AA5: FY2018 | AB5: Q1-2019 | AC5: Q2-2019 | AD5: Q3-2019 | AE5: Q4-2019 | AF5: FY2019 | AG5: Q1-2020 | AH5: Q2-2020 | AI5: Q3-2020 | AJ5: Q4-2020 | AK5: FY2020 | AL5: Q1-2021 | AM5: Q2-2021 | AN5: Q3-2021 | AO5: Q4-2021 | AP5: FY2021 | AQ5: Q1-2022 | AR5: Q2-2022 | AS5: Q3-2022 | AT5: Q4-2022 | AU5: FY2022 | AV5: Q1-2023 | AW5: Q2-2023 | AX5: Q3-2023 | AY5: Q4-2023 | AZ5: FY2023 | BA5: FY2024E | BB5: FY2025E | BC5: FY2026E | BD5: FY2027E | BE5: FY2028E
B7: Franchising Revenue Build
B11: Kingdom of Saudi Arabia, # of restaurants | L11: 1 | Q11: 1 | V11: 1 | AA11: 2 | AF11: 4 | AK11: 4 | AP11: 4 | AU11: 4 | AZ11: 4 | BA11: 5 | BB11: 5 | BC11: 5 | BD11: 5 | BE11: 5
B12: Kuwait, # of restaurants | L12: 3 | Q12: 3 | V12: 3 | AA12: 3 | AF12: 3 | AK12: 3 | AP12: 3 | AU12: 3 | AZ12: 3 | BA12: 3 | BB12: 3 | BC12: 3 | BD12: 3 | BE12: 3
B13: Lebanon, # of restaurants | L13: 1 | Q13: 1 | V13: 1 | AA13: 1 | BA13: 0 | BB13: 0 | BC13: 0 | BD13: 0 | BE13: 0
B14: Qatar, # of restaurants | Q14: 1 | V14: 3 | AA14: 3 | AF14: 3 | AK14: 3 | AP14: 3 | AU14: 3 | AZ14: 3 | BA14: 3 | BB14: 3 | BC14: 3 | BD14: 3 | BE14: 3
B15: United Arab Emirates, # of restaurants | L15: 4 | Q15: 5 | V15: 5 | AA15: 5 | AF15: 6 | AK15: 6 | AP15: 6 | AU15: 6 | AZ15: 6 | BA15: 7 | BB15: 7 | BC15: 7 | BD15: 7 | BE15: 7
B16: Bahrain, # of restaurants | V16: 1 | AA16: 1 | AF16: 1 | AK16: 1 | AP16: 1 | AU16: 1 | AZ16: 1 | BA16: 1 | BB16: 1 | BC16: 1 | BD16: 1 | BE16: 1
B17: Middle East Licensee restaurants, # of restaurants | L17: =SUM(L11:L16) -> 9 | Q17: =SUM(Q11:Q16) -> 11 | V17: =SUM(V11:V16) -> 14 | AA17: =SUM(AA11:AA16) -> 15 | AF17: =SUM(AF11:AF16) -> 17 | AK17: =SUM(AK11:AK16) -> 17 | AP17: =SUM(AP11:AP16) -> 17 | AU17: =SUM(AU11:AU16) -> 17 | AZ17: =IFERROR(SUM(AZ11:AZ16),"n/a") -> 17 | BA17: =IFERROR(SUM(BA11:BA16),"n/a") -> 19 | BB17: =IFERROR(SUM(BB11:BB16),"n/a") -> 19 | BC17: =IFERROR(SUM(BC11:BC16),"n/a") -> 19 | BD17: =IFERROR(SUM(BD11:BD16),"n/a") -> 19 | BE17: =IFERROR(SUM(BE11:BE16),"n/a") -> 19
B18: Mexico licensee restaurants, # of restaurants | L18: 2 | Q18: 3 | V18: 3 | AA18: 3 | AF18: 5 | AK18: 6 | AP18: 6 | AU18: 7 | AZ18: 7 | BA18: 8 | BB18: 8 | BC18: 8 | BD18: 9 | BE18: 9
B19: Beijing, # of restaurants | AF19: 1 | AK19: 1 | AP19: 1 | AU19: 1 | AZ19: 1 | BA19: 1 | BB19: 2 | BC19: 2 | BD19: 3 | BE19: 3
B20: Shanghai, # of restaurants | AF20: 1 | AK20: 1 | AP20: 3 | AU20: 3 | AZ20: 3 | BA20: 3 | BB20: 3 | BC20: 3 | BD20: 4 | BE20: 4
B21: Chengdu, # of restaurants | AZ21: 1 | BA21: 1 | BB21: 1 | BC21: 2 | BD21: 2 | BE21: 3
B22: Chinese mainland, # of restaurants | Q22: 1 | V22: 2 | AA22: 2 | AF22: =SUM(AF19:AF21) -> 2 | AK22: =SUM(AK19:AK21) -> 2 | AP22: =SUM(AP19:AP21) -> 4 | AU22: =SUM(AU19:AU21) -> 4 | AZ22: =IFERROR(SUM(AZ19:AZ21),"n/a") -> 5 | BA22: =IFERROR(SUM(BA19:BA21),"n/a") -> 5 | BB22: =IFERROR(SUM(BB19:BB21),"n/a") -> 6 | BC22: =IFERROR(SUM(BC19:BC21),"n/a") -> 7 | BD22: =IFERROR(SUM(BD19:BD21),"n/a") -> 9 | BE22: =IFERROR(SUM(BE19:BE21),"n/a") -> 10
B23: Hong Kong, # of restaurants | AF23: 1 | AK23: 1 | AP23: 1 | AU23: 1 | AZ23: 1 | BA23: 1 | BB23: 1 | BC23: 1 | BD23: 1 | BE23: 1
B24: Macau, # of restaurants | AF24: 1 | AK24: 1 | AP24: 1 | AU24: 1 | AZ24: 1 | BA24: 1 | BB24: 1 | BC24: 1 | BD24: 1 | BE24: 1
B25: Special administrative regions, # of restaurants | V25: 1 | AA25: 1 | AF25: =SUM(AF23:AF24) -> 2 | AK25: =SUM(AK23:AK24) -> 2 | AP25: =SUM(AP23:AP24) -> 2 | AU25: =SUM(AU23:AU24) -> 2 | AZ25: =IFERROR(SUM(AZ23:AZ24),"n/a") -> 2 | BA25: =IFERROR(SUM(BA23:BA24),"n/a") -> 2 | BB25: =IFERROR(SUM(BB23:BB24),"n/a") -> 2 | BC25: =IFERROR(SUM(BC23:BC24),"n/a") -> 2 | BD25: =IFERROR(SUM(BD23:BD24),"n/a") -> 2 | BE25: =IFERROR(SUM(BE23:BE24),"n/a") -> 2
B26: China licensee restaurants, # of restaurants | L26: =L25+L22 -> 0 | Q26: =Q25+Q22 -> 1 | V26: =V25+V22 -> 3 | AA26: =AA25+AA22 -> 3 | AF26: =AF25+AF22 -> 4 | AK26: =AK25+AK22 -> 4 | AP26: =AP25+AP22 -> 6 | AU26: =AU25+AU22 -> 6 | AZ26: =IFERROR(AZ25+AZ22,"n/a") -> 7 | BA26: =IFERROR(BA25+BA22,"n/a") -> 7 | BB26: =IFERROR(BB25+BB22,"n/a") -> 8 | BC26: =IFERROR(BC25+BC22,"n/a") -> 9 | BD26: =IFERROR(BD25+BD22,"n/a") -> 11 | BE26: =IFERROR(BE25+BE22,"n/a") -> 12
B27: Thailand licensee restaurants, # of restaurants | AZ27: 1 | BA27: 1 | BB27: 1 | BC27: 1 | BD27: 2 | BE27: 2
B28: new sa fran | AZ28: ='Forecast Assumptions'!F12 -> 0 | BA28: ='Forecast Assumptions'!G12 -> 4 | BB28: ='Forecast Assumptions'!H12 -> 2 | BC28: ='Forecast Assumptions'!I12 -> 2 | BD28: ='Forecast Assumptions'!J12 -> 1 | BE28: ='Forecast Assumptions'!K12 -> 0
B29: South America licensee restaurants, # of restaurants | AZ29: 0 | BA29: =AZ29+BA28 -> 4 | BB29: =BA29+BB28 -> 6 | BC29: =BB29+BC28 -> 8 | BD29: =BC29+BD28 -> 9 | BE29: =BD29+BE28 -> 9
B30: Total Franchisees, # of restaurants | G30: 8 | H30: 9 | I30: 9 | J30: 9 | K30: =L30 -> 11 | L30: =L17+L18+L26 -> 11 | M30: 11 | N30: 12 | O30: 13 | P30: =Q30 -> 15 | Q30: =Q17+Q18+Q26 -> 15 | R30: 16 | S30: 16 | T30: 18 | U30: =V30 -> 20 | V30: =V17+V18+V26 -> 20 | W30: 21 | X30: 21 | Y30: 21 | Z30: =AA30 -> 21 | AA30: =AA17+AA18+AA26 -> 21 | AB30: 20 | AC30: 21 | AD30: 23 | AE30: =AF30 -> 26 | AF30: =AF17+AF18+AF26 -> 26 | AG30: 26 | AH30: 26 | AI30: 26 | AJ30: =AK30 -> 27 | AK30: =AK17+AK18+AK26 -> 27 | AL30: 27 | AM30: 28 | AN30: 29 | AO30: 29 | AP30: =AP17+AP18+AP26 -> 29 | AQ30: 29 | AR30: 29 | AS30: 29 | AT30: 30 | AU30: =AT30 -> 30 | AV30: 30 | AW30: 30 | AX30: 30 | AY30: 32 | AZ30: =IFERROR(AY30,"n/a") -> 32 | BA30: =BA29+BA27+BA26+BA18+BA17 -> 39 | BB30: =BB29+BB27+BB26+BB18+BB17 -> 42 | BC30: =BC29+BC27+BC26+BC18+BC17 -> 45 | BD30: =BD29+BD27+BD26+BD18+BD17 -> 50 | BE30: =BE29+BE27+BE26+BE18+BE17 -> 51
B31: Net Change in Total Franchisees, # of restaurants | G31: 8 | H31: =H30-F30 -> 9 | I31: =I30-H30 -> 0 | J31: =J30-I30 -> 0 | K31: =K30-J30 -> 2 | L31: =L30-G30 -> 3 | M31: =M30-K30 -> 0 | N31: =N30-M30 -> 1 | O31: =O30-N30 -> 1 | P31: =P30-O30 -> 2 | Q31: =Q30-L30 -> 4 | R31: =R30-P30 -> 1 | S31: =S30-R30 -> 0 | T31: =T30-S30 -> 2 | U31: =U30-T30 -> 2 | V31: =V30-Q30 -> 5 | W31: =W30-U30 -> 1 | X31: =X30-W30 -> 0 | Y31: =Y30-X30 -> 0 | Z31: =Z30-Y30 -> 0 | AA31: =AA30-V30 -> 1 | AB31: =AB30-Z30 -> -1 | AC31: =AC30-AB30 -> 1 | AD31: =AD30-AC30 -> 2 | AE31: =AE30-AD30 -> 3 | AF31: =AF30-AA30 -> 5 | AG31: =AG30-AE30 -> 0 | AH31: =AH30-AG30 -> 0 | AI31: =AI30-AH30 -> 0 | AJ31: =AJ30-AI30 -> 1 | AK31: =AK30-AF30 -> 1 | AL31: =AL30-AJ30 -> 0 | AM31: =AM30-AL30 -> 1 | AN31: =AN30-AM30 -> 1 | AO31: =AO30-AN30 -> 0 | AP31: =AP30-AK30 -> 2 | AQ31: =AQ30-AO30 -> 0 | AR31: =AR30-AQ30 -> 0 | AS31: =AS30-AR30 -> 0 | AT31: =AT30-AS30 -> 1 | AU31: =AU30-AP30 -> 1 | AV31: =AV30-AT30 -> 0 | AW31: =AW30-AV30 -> 0 | AX31: =AX30-AW30 -> 0 | AY31: =IFERROR(AY30-AX30,"n/a") -> 2 | AZ31: =IFERROR(AZ30-AU30,"n/a") -> 2 | BA31: =BA30-AZ30 -> 7 | BB31: =BB30-BA30 -> 3 | BC31: =BC30-BB30 -> 3 | BD31: =BD30-BC30 -> 5 | BE31: =BE30-BD30 -> 1
B32: Avg # of Franchisees, # of restaurants | H32: =AVERAGE(H30,G30) -> 8.5 | I32: =AVERAGE(I30,H30) -> 9 | J32: =AVERAGE(J30,I30) -> 9 | K32: =AVERAGE(K30,J30) -> 10 | L32: =AVERAGE(K32,J32,I32,H32) -> 9.125 | M32: =AVERAGE(M30,L30) -> 11 | N32: =AVERAGE(N30,M30) -> 11.5 | O32: =AVERAGE(O30,N30) -> 12.5 | P32: =AVERAGE(P30,O30) -> 14 | Q32: =AVERAGE(P32,O32,N32,M32) -> 12.25 | R32: =AVERAGE(R30,Q30) -> 15.5 | S32: =AVERAGE(S30,R30) -> 16 | T32: =AVERAGE(T30,S30) -> 17 | U32: =AVERAGE(U30,T30) -> 19 | V32: =AVERAGE(U32,T32,S32,R32) -> 16.875 | W32: =AVERAGE(W30,V30) -> 20.5 | X32: =AVERAGE(X30,W30) -> 21 | Y32: =AVERAGE(Y30,X30) -> 21 | Z32: =AVERAGE(Z30,Y30) -> 21 | AA32: =AVERAGE(Z32,Y32,X32,W32) -> 20.875 | AB32: =AVERAGE(AB30,AA30) -> 20.5 | AC32: =AVERAGE(AC30,AB30) -> 20.5 | AD32: =AVERAGE(AD30,AC30) -> 22 | AE32: =AVERAGE(AE30,AD30) -> 24.5 | AF32: =AVERAGE(AE32,AD32,AC32,AB32) -> 21.875 | AG32: =AVERAGE(AG30,AF30) -> 26 | AH32: =AVERAGE(AH30,AG30) -> 26 | AI32: =AVERAGE(AI30,AH30) -> 26 | AJ32: =AVERAGE(AJ30,AI30) -> 26.5 | AK32: =AVERAGE(AJ32,AI32,AH32,AG32) -> 26.125 | AL32: =AVERAGE(AL30,AK30) -> 27 | AM32: =AVERAGE(AM30,AL30) -> 27.5 | AN32: =AVERAGE(AN30,AM30) -> 28.5 | AO32: =AVERAGE(AO30,AN30) -> 29 | AP32: =AVERAGE(AO32,AN32,AM32,AL32) -> 28 | AQ32: =AVERAGE(AQ30,AP30) -> 29 | AR32: =AVERAGE(AR30,AQ30) -> 29 | AS32: =AVERAGE(AS30,AR30) -> 29 | AT32: =AVERAGE(AT30,AS30) -> 29.5 | AU32: =AVERAGE(AT32,AS32,AR32,AQ32) -> 29.125 | AV32: =AVERAGE(AV30,AU30) -> 30 | AW32: =AVERAGE(AW30,AV30) -> 30 | AX32: =AVERAGE(AX30,AW30) -> 30 | AY32: =IFERROR(AVERAGE(AY30,AX30),"n/a") -> 31 | AZ32: =IFERROR(AVERAGE(AY32,AX32,AW32,AV32),"n/a") -> 30.25 | BA32: =AVERAGE(AZ30,BA30) -> 35.5 | BB32: =AVERAGE(BA30,BB30) -> 40.5 | BC32: =AVERAGE(BB30,BC30) -> 43.5 | BD32: =AVERAGE(BC30,BD30) -> 47.5 | BE32: =AVERAGE(BD30,BE30) -> 50.5
B33: Total Number of Systemwide restaurants EOY | G33: 197 | H33: 198 | I33: 201 | J33: 203 | K33: 211 | L33: 211 | M33: 212 | N33: 214 | O33: 215 | P33: 223 | Q33: 223 | R33: 224 | S33: 223 | T33: 226 | U33: 234 | V33: 234 | W33: 235 | X33: 234 | Y33: 236 | Z33: 239 | AA33: 239 | AB33: 238 | AC33: 240 | AD33: 289 | AE33: 318 | AF33: 318 | AG33: 320 | AH33: 320 | AI33: 320 | AJ33: 322 | AK33: 322 | AL33: 324 | AM33: 328 | AN33: 333 | AO33: 337 | AP33: 337 | AQ33: 335 | AR33: 337 | AS33: 340 | AT33: 348 | AU33: 348 | AV33: 348 | AW33: 351 | AX33: 353 | AY33: 363 | AZ33: 363 | BA33: ='Revenue Build - FRC & Others'!BH52+'Revenue Build - North Italia'!BD12+'Revenue Build - CK F.'!BH12+BA30 -> 384.6 | BB33: ='Revenue Build - FRC & Others'!BI52+'Revenue Build - North Italia'!BE12+'Revenue Build - CK F.'!BI12+BB30 -> 403.12 | BC33: ='Revenue Build - FRC & Others'!BJ52+'Revenue Build - North Italia'!BF12+'Revenue Build - CK F.'!BJ12+BC30 -> 418.744 | BD33: ='Revenue Build - FRC & Others'!BK52+'Revenue Build - North Italia'!BG12+'Revenue Build - CK F.'!BK12+BD30 -> 439.2928 | BE33: ='Revenue Build - FRC & Others'!BL52+'Revenue Build - North Italia'!BH12+'Revenue Build - CK F.'!BL12+BE30 -> 455.75136
B34: Royalty rate (Estimated), % | H34: 0.1 | I34: 0.1 | J34: 0.1 | K34: 0.1 | L34: =L36/L38 -> 0.1 | M34: 0.1 | N34: 0.1 | O34: 0.1 | P34: 0.1 | Q34: =Q36/Q38 -> 0.1 | R34: 0.1 | S34: 0.1 | T34: 0.1 | U34: 0.1 | V34: =V36/V38 -> 0.1 | W34: 0.1 | X34: 0.1 | Y34: 0.1 | Z34: 0.1 | AA34: =AA36/AA38 -> 0.1 | AB34: 0.1 | AC34: 0.1 | AD34: 0.1 | AE34: 0.1 | AF34: =AF36/AF38 -> 0.1 | AG34: 0.1 | AH34: 0.1 | AI34: 0.1 | AJ34: 0.1 | AK34: =AK36/AK38 -> 0.1 | AL34: 0.1 | AM34: 0.1 | AN34: 0.1 | AO34: 0.1 | AP34: =AP36/AP38 -> 0.1 | AQ34: 0.1 | AR34: 0.1 | AS34: 0.1 | AT34: 0.1 | AU34: =AU36/AU38 -> 0.1 | AV34: 0.1 | AW34: 0.1 | AX34: 0.1 | AY34: 0.1 | AZ34: =AZ36/AZ38 -> 0.1 | BA34: 0.1 | BB34: 0.1 | BC34: 0.1 | BD34: 0.1 | BE34: 0.1
B35: Percentage of restaurants franchised, % | H35: =H30/H33 -> 0.045454545 | I35: =I30/I33 -> 0.044776119 | J35: =J30/J33 -> 0.044334975 | K35: =K30/K33 -> 0.052132701 | L35: =L30/L33 -> 0.052132701 | M35: =M30/M33 -> 0.051886792 | N35: =N30/N33 -> 0.056074766 | O35: =O30/O33 -> 0.060465116 | ... BE35: =BE30/BE33 -> 0.11190312
B36: International Franchisees Sales going to Parent Company (Estimated), mm | H36: 1.9233234 | I36: 1.9582457 | J36: 1.927599 | K36: 2.2773915 | L36: 8.0865596 | M36: 2.377773 | N36: 2.609778 | O36: 2.8175746 | P36: 3.4212607 | Q36: 11.226386 | R36: 3.3994821 | S36: 3.4392507 | T36: 3.7840493 | U36: 4.1957154 | V36: 14.818497 | W36: 4.5653198 | X36: 4.5854019 | Y36: 4.4882893 | Z36: 4.4671932 | AA36: 18.106204 | AB36: 4.3672279 | AC36: 4.5903868 | AD36: 4.8795799 | AE36: 5.5468053 | AF36: 19.384 | AG36: 4.9395123 | AH36: 2.4691207 | AI36: 4.2356301 | AJ36: 4.6184017 | AK36: 16.262665 | AL36: 5.2363118 | AM36: 6.5651586 | AN36: 6.6461357 | AO36: 6.6417905 | AP36: 25.089397 | AQ36: 6.8017938 | AR36: 7.1480315 | AS36: 6.7221901 | AT36: 7.710817 | AU36: 28.382833 | AV36: 7.3957931 | AW36: 7.5278402 | AX36: 7.1110189 | AY36: 7.8738949 | AZ36: 29.908547 | BA36: =BA38*BA34 -> 35.734618 | BB36: =BB38*BB34 -> 39.09992 | BC36: =BC38*BC34 -> 41.711848 | BD36: =BD38*BD34 -> 46.248566 | BE36: =BE38*BE34 -> 47.299832
B37: Sales per franchise | L37: =L38/L32 -> 8.8619831 | Q37: =Q38/Q32 -> 9.164397 | R37: =R38/R32 -> 2.1932142 | S37: =S38/S32 -> 2.1495317 | T37: =T38/T32 -> 2.2259114 | U37: =U38/U32 -> 2.2082712 | V37: =V38/V32 -> 8.7813318 | W37: =W38/W32 -> 2.2269853 | X37: =X38/X32 -> 2.1835247 | ... AZ37: =AZ38/AZ32 -> 9.887123
B38: International Franchisees Sales (Estimated), mm | H38: =H36/H34 -> 19.233234 | I38: =I36/I34 -> 19.582457 | J38: =J36/J34 -> 19.27599 | K38: =K36/K34 -> 22.773915 | L38: =SUM(H38:K38) -> 80.865596 | M38: =M36/M34 -> 23.77773 | N38: =N36/N34 -> 26.09778 | O38: =O36/O34 -> 28.175746 | P38: =P36/P34 -> 34.212607 | Q38: =SUM(M38:P38) -> 112.26386 | R38: =R36/R34 -> 33.994821 | S38: =S36/S34 -> 34.392507 | T38: =T36/T34 -> 37.840493 | U38: =U36/U34 -> 41.957154 | V38: =SUM(R38:U38) -> 148.18497 | W38: =W36/W34 -> 45.653198 | X38: =X36/X34 -> 45.854019 | Y38: =Y36/Y34 -> 44.882893 | Z38: =Z36/Z34 -> 44.671932 | AA38: =SUM(W38:Z38) -> 181.06204 | AB38: =AB36/AB34 -> 43.672279 | AC38: =AC36/AC34 -> 45.903868 | AD38: =AD36/AD34 -> 48.795799 | AE38: =AE36/AE34 -> 55.468053 | AF38: =SUM(AB38:AE38) -> 193.84 | AG38: =AG36/AG34 -> 49.395123 | AH38: =AH36/AH34 -> 24.691207 | AI38: =AI36/AI34 -> 42.356301 | AJ38: =AJ36/AJ34 -> 46.184017 | AK38: =SUM(AG38:AJ38) -> 162.62665 | AL38: =AL36/AL34 -> 52.363118 | AM38: =AM36/AM34 -> 65.651586 | AN38: =AN36/AN34 -> 66.461357 | AO38: =AO36/AO34 -> 66.417905 | AP38: =SUM(AL38:AO38) -> 250.89397 | AQ38: =AQ36/AQ34 -> 68.017938 | AR38: =AR36/AR34 -> 71.480315 | AS38: =AS36/AS34 -> 67.221901 | AT38: =AT36/AT34 -> 77.10817 | AU38: =SUM(AQ38:AT38) -> 283.82833 | AV38: =AV36/AV34 -> 73.957931 | AW38: =AW36/AW34 -> 75.278402 | AX38: =AX36/AX34 -> 71.110189 | AY38: =AY36/AY34 -> 78.738949 | AZ38: =SUM(AV38:AY38) -> 299.08547 | BA38: =BA30*(AVERAGE(AZ38,AU38,AP38)/AVERAGE(AZ30,AU30,AP30)) -> 357.34618 | BB38: =BB30*(AVERAGE(BA38,AZ38,AU38)/AVERAGE(BA30,AZ30,AU30)) -> 390.9992 | BC38: =BC30*(AVERAGE(BB38,BA38,AZ38)/AVERAGE(BB30,BA30,AZ30)) -> 417.11848 | BD38: =BD30*(AVERAGE(BC38,BB38,BA38)/AVERAGE(BC30,BB30,BA30)) -> 462.48566 | BE38: =BE30*(AVERAGE(BD38,BC38,BB38)/AVERAGE(BD30,BC30,BB30)) -> 472.99832

Sheet Cost Build - Aggregate
B4: Period Ended | J4: 41730 | K4: 41821 | L4: 41912 | M4: 42003 | N4: 42003 | O4: 42094 | P4: 42185 | Q4: 42276 | R4: 42367 | S4: 42367 | T4: 42458 | U4: 42549 | V4: 42640 | W4: 42738 | X4: 42738 | Y4: 42829 | Z4: 42920 | AA4: 43011 | AB4: 43102 | AC4: 43102 | AD4: 43193 | AE4: 43284 | AF4: 43375 | AG4: 43466 | AH4: 43466 | AI4: 43557 | AJ4: 43648 | AK4: 43739 | AL4: 43830 | AM4: 43830 | AN4: 43921 | AO4: 44012 | AP4: 44103 | AQ4: 44194 | AR4: 44194 | AS4: 44285 | AT4: 44376 | AU4: 44467 | AV4: 44558 | AW4: 44558 | AX4: 44649 | AY4: 44740 | AZ4: 44831 | BA4: 44929 | BB4: 44929 | BC4: 45019 | BD4: 45111 | BE4: 45202 | BF4: 45293 | BG4: 45293
J5: Q1-2014 | K5: Q2-2014 | L5: Q3-2014 | M5: Q4-2014 | N5: FY2014 | O5: Q1-2015 | P5: Q2-2015 | Q5: Q3-2015 | R5: Q4-2015 | S5: FY2015 | T5: Q1-2016 | U5: Q2-2016 | V5: Q3-2016 | W5: Q4-2016 | X5: FY2016 | Y5: Q1-2017 | Z5: Q2-2017 | AA5: Q3-2017 | AB5: Q4-2017 | AC5: FY2017 | AD5: Q1-2018 | AE5: Q2-2018 | AF5: Q3-2018 | AG5: Q4-2018 | AH5: FY2018 | AI5: Q1-2019 | AJ5: Q2-2019 | AK5: Q3-2019 | AL5: Q4-2019 | AM5: FY2019 | AN5: Q1-2020 | AO5: Q2-2020 | AP5: Q3-2020 | AQ5: Q4-2020 | AR5: FY2020 | AS5: Q1-2021 | AT5: Q2-2021 | AU5: Q3-2021 | AV5: Q4-2021 | AW5: FY2021 | AX5: Q1-2022 | AY5: Q2-2022 | AZ5: Q3-2022 | BA5: Q4-2022 | BB5: FY2022 | BC5: Q1-2023 | BD5: Q2-2023 | BE5: Q3-2023 | BF5: Q4-2023 | BG5: FY2023
B7: Cheesecake Factory Cost Build
B9: The Cheesecake Factory restaurants - BoP, # of restaurants | J9: 168 | K9: =J12 -> 169 | L9: =K12 -> 170 | M9: =L12 -> 172 | N9: =J12 -> 169 | O9: =N12 -> 177 | P9: =O12 -> 177 | Q9: =P12 -> 179 | R9: =Q12 -> 181 | S9: =N12 -> 177 | T9: =S12 -> 187 | U9: =T12 -> 188 | V9: =U12 -> 189 | W9: =V12 -> 189 | X9: =S12 -> 187 | Y9: =X12 -> 194 | Z9: =Y12 -> 194 | AA9: =Z12 -> 193 | AB9: =AA12 -> 194 | AC9: =X12 -> 194 | AD9: =AC12 -> 199 | AE9: =AD12 -> 199 | AF9: =AE12 -> 198 | AG9: =AF12 -> 199 | AH9: =AC12 -> 199 | AI9: =AH12 -> 201 | AJ9: =AI12 -> 201 | AK9: =AJ12 -> 202 | AL9: =AK12 -> 203 | AM9: =AH12 -> 201 | AN9: =AM12 -> 206 | AO9: =AN12 -> 206 | AP9: =AO12 -> 206 | AQ9: =AP12 -> 205 | AR9: =AM12 -> 206 | AS9: =AR12 -> 206 | AT9: =AS12 -> 207 | AU9: =AT12 -> 207 | AV9: =AU12 -> 207 | AW9: =AR12 -> 206 | AX9: =AW12 -> 208 | AY9: =AX12 -> 208 | AZ9: =AY12 -> 208 | BA9: =AZ12 -> 209 | BB9: =AW12 -> 208 | BC9: =BB12 -> 211 | BD9: =BC12 -> 210 | BE9: =BD12 -> 211 | BF9: =BE12 -> 213 | BG9: =BB12 -> 211
B10: CF restaurants opened, # of restaurants | J10: 1 | K10: 2 | L10: 2 | M10: 5 | N10: 10 | O10: 0 | P10: 2 | Q10: 2 | R10: 6 | S10: 10 | T10: 1 | U10: 1 | V10: 0 | W10: 5 | X10: 7 | Y10: 0 | Z10: 1 | AA10: 1 | AB10: 5 | AC10: 7 | AD10: 0 | AE10: 0 | AF10: 1 | AG10: 3 | AH10: 4 | AI10: 0 | AJ10: 1 | AK10: 1 | AL10: 3 | AM10: =SUM(AI10,AJ10,AK10,AL10) -> 5 | AN10: 0 | AO10: 0 | AP10: 0 | AQ10: 1 | AR10: =SUM(AN10,AO10,AP10,AQ10) -> 1 | AS10: 1 | AT10: 0 | AU10: 0 | AV10: 1 | AW10: =SUM(AS10,AT10,AU10,AV10) -> 2 | AX10: 0 | AY10: 0 | AZ10: 1 | BA10: 2 | BB10: =SUM(AX10,AY10,AZ10,BA10) -> 3 | BC10: 0 | BD10: 1 | BE10: 2 | BF10: 3 | BG10: =SUM(BC10,BD10,BE10,BF10) -> 6
B11: CF restaurants closed, # of restaurants | J11: =J12-J9-J10 -> 0 | K11: =K12-K9-K10 -> -1 | L11: =L12-L9-L10 -> 0 | M11: =M12-M9-M10 -> 0 | N11: =-(N10-(N12-N9)) -> -2 | O11: =O12-O9-O10 -> 0 | P11: =P12-P9-P10 -> 0 | Q11: =Q12-Q9-Q10 -> 0 | R11: =R12-R9-R10 -> 0 | S11: =-(S10-(S12-S9)) -> 0 | T11: =T12-T9-T10 -> 0 | U11: =U12-U9-U10 -> 0 | V11: =V12-V9-V10 -> 0 | W11: =W12-W9-W10 -> 0 | X11: =-(X10-(X12-X9)) -> 0 | Y11: =Y12-Y9-Y10 -> 0 | Z11: =Z12-Z9-Z10 -> -2 | AA11: =AA12-AA9-AA10 -> 0 | AB11: =AB12-AB9-AB10 -> 0 | AC11: =-(AC10-(AC12-AC9)) -> -2 | AD11: =AD12-AD9-AD10 -> 0 | AE11: =AE12-AE9-AE10 -> -1 | AF11: =AF12-AF9-AF10 -> 0 | AG11: =AG12-AG9-AG10 -> -1 | AH11: =-(AH10-(AH12-AH9)) -> -2 | AI11: =AI12-AI9-AI10 -> 0 | AJ11: =AJ12-AJ9-AJ10 -> 0 | AK11: =AK12-AK9-AK10 -> 0 | AL11: =AL12-AL9-AL10 -> 0 | AM11: =-(AM10-(AM12-AM9)) -> 0 | AN11: =AN12-AN9-AN10 -> 0 | AO11: =AO12-AO9-AO10 -> 0 | AP11: =AP12-AP9-AP10 -> -1 | AQ11: =AQ12-AQ9-AQ10 -> 0 | AR11: =-(AR10-(AR12-AR9)) -> -1 | AS11: =AS12-AS9-AS10 -> 0 | AT11: =AT12-AT9-AT10 -> 0 | AU11: =AU12-AU9-AU10 -> 0 | AV11: =AV12-AV9-AV10 -> 0 | AW11: =-(AW10-(AW12-AW9)) -> 0 | AX11: =AX12-AX9-AX10 -> 0 | AY11: =AY12-AY9-AY10 -> 0 | AZ11: =AZ12-AZ9-AZ10 -> 0 | BA11: =BA12-BA9-BA10 -> 0 | BB11: =-(BB10-(BB12-BB9)) -> 0 | BC11: =BC12-BC9-BC10 -> -1 | BD11: =BD12-BD9-BD10 -> 0 | BE11: =BE12-BE9-BE10 -> 0 | BF11: =BF12-BF9-BF10 -> 0 | BG11: =-(BG10-(BG12-BG9)) -> -1
B12: The Cheesecake Factory restaurants - EoP, # of restaurants | J12: 169 | K12: 170 | L12: 172 | M12: =N12 -> 177 | N12: 177 | O12: 177 | P12: 179 | Q12: 181 | R12: =S12 -> 187 | S12: 187 | T12: 188 | U12: 189 | V12: 189 | W12: 194 | X12: 194 | Y12: 194 | Z12: 193 | AA12: 194 | AB12: 199 | AC12: 199 | AD12: 199 | AE12: 198 | AF12: 199 | AG12: 201 | AH12: 201 | AI12: 201 | AJ12: 202 | AK12: 203 | AL12: 206 | AM12: =AL12 -> 206 | AN12: 206 | AO12: 206 | AP12: 205 | AQ12: 206 | AR12: =AQ12 -> 206 | AS12: 207 | AT12: 207 | AU12: 207 | AV12: 208 | AW12: =AV12 -> 208 | AX12: 208 | AY12: 208 | AZ12: 209 | BA12: 211 | BB12: =BA12 -> 211 | BC12: 210 | BD12: 211 | BE12: 213 | BF12: 216 | BG12: =BF12 -> 216
B14: The Cheesecake Factory restaurants - Average, # of restaurants | J14: =AVERAGE(J9,J12) -> 168.5 | K14: =AVERAGE(K9,K12) -> 169.5 | L14: =AVERAGE(L9,L12) -> 171 | M14: =AVERAGE(M9,M12) -> 174.5 | N14: =AVERAGE(J14,K14,L14,M14) -> 170.875 | O14: =AVERAGE(O9,O12) -> 177 | P14: =AVERAGE(P9,P12) -> 178 | Q14: =AVERAGE(Q9,Q12) -> 180 | R14: =AVERAGE(R9,R12) -> 184 | S14: =AVERAGE(O14,P14,Q14,R14) -> 179.75 | T14: =AVERAGE(T9,T12) -> 187.5 | U14: =AVERAGE(U9,U12) -> 188.5 | V14: =AVERAGE(V9,V12) -> 189 | W14: =AVERAGE(W9,W12) -> 191.5 | X14: =AVERAGE(T14,U14,V14,W14) -> 189.125 | Y14: =AVERAGE(Y9,Y12) -> 194 | Z14: =AVERAGE(Z9,Z12) -> 193.5 | AA14: =AVERAGE(AA9,AA12) -> 193.5 | AB14: =AVERAGE(AB9,AB12) -> 196.5 | AC14: =AVERAGE(Y14,Z14,AA14,AB14) -> 194.375 | AD14: =AVERAGE(AD9,AD12) -> 199 | AE14: =AVERAGE(AE9,AE12) -> 198.5 | AF14: =AVERAGE(AF9,AF12) -> 198.5 | AG14: =AVERAGE(AG9,AG12) -> 200 | AH14: =AVERAGE(AD14,AE14,AF14,AG14) -> 199 | AI14: =AVERAGE(AI9,AI12) -> 201 | AJ14: =AVERAGE(AJ9,AJ12) -> 201.5 | AK14: =AVERAGE(AK9,AK12) -> 202.5 | AL14: =AVERAGE(AL9,AL12) -> 204.5 | AM14: =AVERAGE(AI14,AJ14,AK14,AL14) -> 202.375 | AN14: =AVERAGE(AN9,AN12) -> 206 | AO14: =AVERAGE(AO9,AO12) -> 206 | AP14: =AVERAGE(AP9,AP12) -> 205.5 | AQ14: =AVERAGE(AQ9,AQ12) -> 205.5 | AR14: =AVERAGE(AN14,AO14,AP14,AQ14) -> 205.75 | AS14: =AVERAGE(AS9,AS12) -> 206.5 | AT14: =AVERAGE(AT9,AT12) -> 207 | AU14: =AVERAGE(AU9,AU12) -> 207 | AV14: =AVERAGE(AV9,AV12) -> 207.5 | AW14: =AVERAGE(AS14,AT14,AU14,AV14) -> 207 | AX14: =AVERAGE(AX9,AX12) -> 208 | AY14: =AVERAGE(AY9,AY12) -> 208 | AZ14: =AVERAGE(AZ9,AZ12) -> 208.5 | BA14: =AVERAGE(BA9,BA12) -> 210 | BB14: =AVERAGE(AX14,AY14,AZ14,BA14) -> 208.625 | BC14: =AVERAGE(BC9,BC12) -> 210.5 | BD14: =AVERAGE(BD9,BD12) -> 210.5 | BE14: =AVERAGE(BE9,BE12) -> 212 | BF14: =AVERAGE(BF9,BF12) -> 214.5 | BG14: =AVERAGE(BC14,BD14,BE14,BF14) -> 211.875
B18: Total number of employees across all subsidiaries | N18: 35700 | O18: =N18+380 -> 36080 | P18: =O18+380 -> 36460 | Q18: =P18+380 -> 36840 | R18: =Q18+380 -> 37220 | S18: 37600 | T18: =S18+240 -> 37840 | U18: =T18+240 -> 38080 | V18: =U18+240 -> 38320 | W18: =V18+240 -> 38560 | X18: 38800 | Y18: =X18+60 -> 38860 | Z18: =Y18+60 -> 38920 | AA18: =Z18+60 -> 38980 | AB18: =AA18+60 -> 39040 | AC18: 39100 | AD18: =AC18-80 -> 39020 | AE18: =AD18-80 -> 38940 | AF18: =AE18-80 -> 38860 | AG18: =AF18-80 -> 38780 | AH18: 38700 | AI18: =AH18+1510 -> 40210 | AJ18: =AI18+1510 -> 41720 | AK18: =AJ18+1510 -> 43230 | AL18: =AK18+1510 -> 44740 | AM18: 46250 | AN18: =AM18-750 -> 45500 | AO18: =AN18-750 -> 44750 | AP18: =AO18-750 -> 44000 | AQ18: =AP18-750 -> 43250 | AR18: 42500 | AS18: =AR18+660 -> 43160 | AT18: =AS18+660 -> 43820 | AU18: =AT18+660 -> 44480 | AV18: =AU18+660 -> 45140 | AW18: 45800 | AX18: =AW18+340 -> 46140 | AY18: =AX18+340 -> 46480 | AZ18: =AY18+340 -> 46820 | BA18: =AZ18+340 -> 47160 | BB18: 47500 | BC18: =BB18+80 -> 47580 | BD18: =BC18+80 -> 47660 | BE18: =BD18+80 -> 47740 | BF18: =BE18+80 -> 47820 | BG18: 47900
B20: Consolidated Food and Beverage | N20: 490.306 | O20: 126.612 | P20: 126.623 | Q20: 125.605 | R20: 125.191 | S20: 504.031 | T20: 130.773 | U20: 126.933 | V20: 128.838 | W20: 140.084 | X20: 526.628 | Y20: 129.139 | Z20: 128.781 | AA20: 127.453 | AB20: 134.015 | AC20: 519.388 | AD20: 135.719 | AE20: 133.136 | AF20: 133.598 | AG20: 134.821 | AH20: 532.88 | AI20: 136.187 | AJ20: 134.438 | AK20: 132.941 | AL20: =AM20-SUM(AI20,AJ20,AK20) -> 158.217 | AM20: 561.783 | AN20: 140.905 | AO20: 72.139 | AP20: 118.093 | AQ20: =AR20-SUM(AN20,AO20,AP20) -> 127.195 | AR20: 458.332 | AS20: 135.875 | AT20: 168.944 | AU20: 169.418 | AV20: =AW20-SUM(AS20,AT20,AU20) -> 178.896 | AW20: 653.133 | AX20: 188.501 | AY20: 204.182 | AZ20: 197.774 | BA20: =BB20-SUM(AX20,AY20,AZ20) -> 220.469 | BB20: 810.926 | BC20: 206.224 | BD20: 201.094 | BE20: 194.733 | BF20: =BG20-SUM(BC20,BD20,BE20) -> 201.449 | BG20: 803.5
B21: Consolidated Labor Expense | N21: 646.102 | O21: 171.169 | P21: 168.495 | Q21: 172.101 | R21: 173.053 | S21: 684.818 | T21: 185.658 | U21: 185.211 | V21: 186.567 | W21: 202.562 | X21: 759.998 | Y21: 193.835 | Z21: 193.063 | AA21: 193.466 | AB21: 197.231 | AC21: 777.595 | AD21: 210.714 | AE21: 212.521 | AF21: 204.537 | AG21: 209.702 | AH21: 834.134 | AI21: 217.31 | AJ21: 217.921 | AK21: 213.6 | AL21: =AM21-SUM(AI21,AJ21,AK21) -> 250.836 | AM21: 899.667 | AN21: 236.982 | AO21: 122.812 | AP21: 200.666 | AQ21: =AR21-SUM(AN21,AO21,AP21) -> 218.126 | AR21: 778.586 | AS21: 229.732 | AT21: 274.812 | AU21: 279.957 | AV21: =AW21-SUM(AS21,AT21,AU21) -> 288.127 | AW21: 1072.628 | AX21: 295.763 | AY21: 304.519 | AZ21: 293.04 | BA21: =BB21-SUM(AX21,AY21,AZ21) -> 318.629 | BB21: 1211.951 | BC21: 311.528 | BD21: 306.149 | BE21: 301.663 | BF21: =BG21-SUM(BC21,BD21,BE21) -> 308.555 | BG21: 1227.895
B22: Consolidated Other Operating Costs | N22: 478.504 | O22: 123.435 | P22: 123.675 | Q22: 128.427 | R22: 125.103 | S22: 500.64 | T22: 129.557 | U22: 131.98 | V22: 134.877 | W22: 143.951 | X22: 540.365 | Y22: 135.65 | Z22: 137.461 | AA22: 138.423 | AB22: 141.257 | AC22: 552.791 | AD22: 148.332 | AE22: 143.796 | AF22: 144.18 | AG22: 140.359 | AH22: 566.825 | AI22: 153.221 | AJ22: 149.106 | AK22: 149.397 | AL22: =AM22-SUM(AI22,AJ22,AK22) -> 179.889 | AM22: 631.613 | AN22: 167.97 | AO22: 121.675 | AP22: 159.095 | AQ22: =AR22-SUM(AN22,AO22,AP22) -> 167.329 | AR22: 616.069 | AS22: 181.533 | AT22: 199.495 | AU22: 201.49 | AV22: =AW22-SUM(AS22,AT22,AU22) -> 209.793 | AW22: 792.311 | AX22: 207.635 | AY22: 219.2 | AZ22: 217.009 | BA22: =BB22-SUM(AX22,AY22,AZ22) -> 237.783 | BB22: 881.627 | BC22: 230.929 | BD22: 226.996 | BE22: 229.534 | BF22: =BG22-SUM(BC22,BD22,BE22) -> 234.969 | BG22: 922.428
B23: Consolidated General and Administrative Expenses | N23: 119.094 | O23: 33.075 | P23: 35.345 | Q23: 33.277 | R23: 35.705 | S23: 137.402 | T23: 35.337 | U23: 35.785 | V23: 36.057 | W23: 38.863 | X23: 146.042 | Y23: 36.287 | Z23: 35.295 | AA23: 35.364 | AB23: 34.587 | AC23: 141.533 | AD23: 39.274 | AE23: 41.423 | AF23: 37.469 | AG23: 36.604 | AH23: 154.77 | AI23: 39.123 | AJ23: 37.247 | AK23: 39.746 | AL23: 47.273 | AM23: 160.199 | AN23: 43.96 | AO23: 35.712 | AP23: 37.795 | AQ23: =AR23-SUM(AN23,AO23,AP23) -> 40.177 | AR23: 157.644 | AS23: 44.427 | AT23: 48.228 | AU23: 45.802 | AV23: =AW23-SUM(AS23,AT23,AU23) -> 47.679 | AW23: 186.136 | AX23: 49.123 | AY23: 50.191 | AZ23: 50.324 | BA23: =BB23-SUM(AX23,AY23,AZ23) -> 56.115 | BB23: 205.753 | BC23: 54.069 | BD23: 54.488 | BE23: 54.209 | BF23: =BG23-SUM(BC23,BD23,BE23) -> 54.683 | BG23: 217.449
B24: Consolidated Depreciation and Amortization | N24: 82.835 | O24: 21.177 | P24: 21.158 | Q24: 21.317 | R24: 21.911 | S24: 85.563 | T24: 21.464 | U24: 21.461 | V24: 21.634 | W24: 23.451 | X24: 88.01 | Y24: 23.196 | Z24: 23.297 | AA24: 22.999 | AB24: 23.237 | AC24: 92.729 | AD24: 24.002 | AE24: 23.727 | AF24: 24.09 | AG24: 24.157 | AH24: 95.976 | AI24: 21.362 | AJ24: 21.659 | AK24: 21.342 | AL24: =AM24-SUM(AI24,AJ24,AK24) -> 23.77 | AM24: 88.133 | AN24: 23.562 | AO24: 22.59 | AP24: 22.651 | AQ24: =AR24-SUM(AN24,AO24,AP24) -> 22.612 | AR24: 91.415 | AS24: 22.006 | AT24: 22.223 | AU24: 22.576 | AV24: =AW24-SUM(AS24,AT24,AU24) -> 22.849 | AW24: 89.654 | AX24: 21.505 | AY24: 22.608 | AZ24: 22.651 | BA24: =BB24-SUM(AX24,AY24,AZ24) -> 25.616 | BB24: 92.38 | BC24: 22.955 | BD24: 23.332 | BE24: 22.837 | BF24: =BG24-SUM(BC24,BD24,BE24) -> 24.012 | BG24: 93.136
B25: Consolidated Impairment of assets and lease terminations | N25: 0.696 | Q25: 6.011 | R25: 0 | S25: 6.011 | W25: 0.114 | X25: 0.114 | Y25: 0.786 | Z25: 0.445 | AB25: 9.112 | AC25: 10.343 | AE25: 2.583 | AF25: 0.263 | AG25: 15.015 | AH25: 17.861 | AL25: =AM25-SUM(AI25,AJ25,AK25) -> 18.247 | AM25: 18.247 | AN25: 191.896 | AO25: 2.433 | AP25: 10.402 | AQ25: =AR25-SUM(AN25,AO25,AP25) -> 14.602 | AR25: 219.333 | AS25: 0.594 | AV25: =AW25-SUM(AS25,AT25,AU25) -> 17.545 | AW25: 18.139 | AX25: 0.207 | AY25: 0.106 | BA25: =BB25-SUM(AX25,AY25,AZ25) -> 31.074 | BB25: 31.387 | BC25: 2.242 | BD25: -0.653 | BE25: 0.048 | BF25: =BG25-SUM(BC25,BD25,BE25) -> 27.827 | BG25: 29.464
B26: Consolidated Acquisition-related costs | AL26: 2.08 | AM26: 5.27 | AN26: 1.236 | AO26: 1.068 | AP26: 0.039 | AQ26: =AR26-SUM(AN26,AO26,AP26) -> 0.356 | AR26: 2.699 | AV26: =AW26-SUM(AS26,AT26,AU26) -> 0 | BA26: =BB26-SUM(AX26,AY26,AZ26) -> 0 | BF26: =BG26-SUM(BC26,BD26,BE26) -> 0
B27: Consolidated Acquisition-related contingent consideration, compensation and amortization expenses | AL27: =AM27-SUM(AI27,AJ27,AK27) -> 1.033 | AM27: 1.033 | AN27: -4.466 | AO27: -0.965 | AP27: 1.439 | AQ27: =AR27-SUM(AN27,AO27,AP27) -> 0.12 | AR27: -3.872 | AS27: 0.55 | AT27: 11.357 | AU27: 0.685 | AV27: =AW27-SUM(AS27,AT27,AU27) -> 6.918 | AW27: 19.51 | AX27: 0.891 | AY27: 0.948 | AZ27: 1.081 | BA27: =BB27-SUM(AX27,AY27,AZ27) -> 10.448 | BB27: 13.368 | BC27: 1.189 | BD27: 1.287 | BE27: 1.414 | BF27: =BG27-SUM(BC27,BD27,BE27) -> 7.796 | BG27: 11.686
B28: Consolidated Pre-Opening Costs | N28: 14.356 | O28: 1.451 | P28: 4.058 | Q28: 4.306 | R28: 7.083 | S28: 16.898 | T28: 2.31 | U28: 2.302 | V28: 1.982 | W28: 6.975 | X28: 13.569 | Y28: 0.97 | Z28: 1.309 | AA28: 3.37 | AB28: 7.629 | AC28: 13.278 | AD28: 1.099 | AE28: 1.449 | AF28: 3.25 | AG28: 5.138 | AH28: 10.937 | AI28: 2.13 | AJ28: 2.175 | AK28: 2.546 | AL28: =AM28-SUM(AI28,AJ28,AK28) -> 6.298 | AM28: 13.149 | AN28: 3.119 | AO28: 2.097 | AP28: 2.394 | AQ28: =AR28-SUM(AN28,AO28,AP28) -> 2.846 | AR28: 10.456 | AS28: 3.856 | AT28: 2.779 | AU28: 3.169 | AV28: =AW28-SUM(AS28,AT28,AU28) -> 3.907 | AW28: 13.711 | AX28: 1.764 | AY28: 2.947 | AZ28: 4.327 | BA28: =BB28-SUM(AX28,AY28,AZ28) -> 7.791 | BB28: 16.829 | BC28: 3.052 | BD28: 6.006 | BE28: 6.742 | BF28: =BG28-SUM(BC28,BD28,BE28) -> 9.579 | BG28: 25.379
B29: Consolidated Operating Margin (%) | J29: 0.13281998 | K29: 0.14408112 | L29: 0.13034951 | M29: 0.12991908 | N29: 0.13430084 | O29: 0.14107149 | P29: 0.15993048 | Q29: 0.14025435 | R29: 0.13475177 | S29: 0.14405479 | T29: 0.13932603 | U29: 0.16073863 | V29: 0.15000391 | W29: 0.14315573 | X29: 0.14824143 | Y29: 0.13691449 | Z29: 0.14606865 | AA29: 0.11918703 | AB29: 0.10985815 | AC29: 0.12808774 | AD29: 0.11486705 | AE29: 0.12892223 | AF29: 0.1168405 | AG29: 0.10975045 | AH29: 0.11855612 | AI29: 0.12018781 | AJ29: 0.13346775 | AK29: 0.11985428 | AL29: 0.10019848 | AM29: 0.11847225 | AN29: 0.080504267 | AO29: -0.11179833 | AP29: 0.045171997 | AQ29: 0.032682988 | AR29: 0.028731716 | AS29: 0.089070845 | AT29: 0.13713406 | AU29: 0.11271696 | AV29: 0.080944853 | AW29: 0.10578944 | AX29: 0.10403794 | AY29: 0.10037637 | AZ29: 0.069865418 | BA29: 0.075425484 | BB29: 0.087326442 | BC29: 0.11949085 | BD29: 0.13130957 | BE29: 0.10767822 | BF29: 0.099268732 | BG29: 0.11447223
B32: Total costs, mm | N32: =N20+N21+N22+N23+N24+N25+N26+N27+N28 -> 1831.893 | O32: =O20+O21+O22+O23+O24+O25+O26+O27+O28 -> 476.919 | P32: =P20+P21+P22+P23+P24+P25+P26+P27+P28 -> 479.354 | Q32: =Q20+Q21+Q22+Q23+Q24+Q25+Q26+Q27+Q28 -> 491.044 | R32: =R20+R21+R22+R23+R24+R25+R26+R27+R28 -> 488.046 | S32: =S20+S21+S22+S23+S24+S25+S26+S27+S28 -> 1935.363 | T32: =T20+T21+T22+T23+T24+T25+T26+T27+T28 -> 505.099 | U32: =U20+U21+U22+U23+U24+U25+U26+U27+U28 -> 503.672 | ... BG32: =BG20+BG21+BG22+BG23+BG24+BG25+BG26+BG27+BG28 -> 3330.937

Sheet Balance Sheet Link
B3: Period Ended | C3: 42003 | D3: 42094 | E3: 42185 | F3: 42276 | G3: 42367 | H3: 42367 | I3: 42458 | J3: 42549 | K3: 42640 | L3: 42738 | M3: 42738 | N3: 42829 | O3: 42920 | P3: 43011 | Q3: 43102 | R3: 43102 | S3: 43193 | T3: 43284 | U3: 43375 | V3: 43466 | W3: 43466 | X3: 43557 | Y3: 43648 | Z3: 43739 | AA3: 43830 | AB3: 43830 | AC3: 43921 | AD3: 44012 | AE3: 44103 | AF3: 44194 | AG3: 44194 | AH3: 44285 | AI3: 44376 | AJ3: 44467 | AK3: 44558 | AL3: 44558 | AM3: 44649 | AN3: 44740 | AO3: 44831 | AP3: 44929 | AQ3: 44929 | AR3: 45019 | AS3: 45111 | AT3: 45202 | AU3: 45293 | AV3: 45293
C4: FY2014 | D4: Q1-2015 | E4: Q2-2015 | F4: Q3-2015 | G4: Q4-2015 | H4: FY2015 | I4: Q1-2016 | J4: Q2-2016 | K4: Q3-2016 | L4: Q4-2016 | M4: FY2016 | N4: Q1-2017 | O4: Q2-2017 | P4: Q3-2017 | Q4: Q4-2017 | R4: FY2017 | S4: Q1-2018 | T4: Q2-2018 | U4: Q3-2018 | V4: Q4-2018 | W4: FY2018 | X4: Q1-2019 | Y4: Q2-2019 | Z4: Q3-2019 | AA4: Q4-2019 | AB4: FY2019 | AC4: Q1-2020 | AD4: Q2-2020 | AE4: Q3-2020 | AF4: Q4-2020 | AG4: FY2020 | AH4: Q1-2021 | AI4: Q2-2021 | AJ4: Q3-2021 | AK4: Q4-2021 | AL4: FY2021 | AM4: Q1-2022 | AN4: Q2-2022 | AO4: Q3-2022 | AP4: Q4-2022 | AQ4: FY2022 | AR4: Q1-2023 | AS4: Q2-2023 | AT4: Q3-2023 | AU4: Q4-2023 | AV4: FY2023
B6: Cheesecake Factory CFS
B8: Current Assets
B9: Cash and cash equivalents | C9: 58.018 | D9: 39.478 | E9: 61.548 | F9: 29.607 | G9: =H9 -> 43.854 | H9: 43.854 | I9: 53.922 | J9: 79.618 | K9: 65.845 | L9: =M9 -> 53.839 | M9: 53.839 | N9: 65.666 | O9: 66.314 | P9: 19.795 | Q9: =R9 -> 6.008 | R9: 6.008 | S9: 24.801 | T9: 29.369 | U9: 12.639 | V9: =W9 -> 26.578 | W9: 26.578 | X9: 22.529 | Y9: 22.604 | Z9: 306.252 | AA9: =AB9 -> 58.416 | AB9: 58.416 | AC9: 81.023 | AD9: 250.155 | AE9: 243.768 | AF9: =AG9 -> 154.085 | AG9: 154.085 | AH9: 181.345 | AI9: 161.768 | AJ9: 131.03 | AK9: =AL9 -> 189.627 | AL9: 189.627 | AM9: 183.556 | AN9: 194.891 | AO9: 133.157 | AP9: =AQ9 -> 114.777 | AQ9: 114.777 | AR9: 116.164 | AS9: 91.557 | AT9: 63.987 | AU9: =AV9 -> 56.29 | AV9: 56.29
B10: Accounts receivable | C10: 15.17 | D10: 12.643 | E10: 8.811 | F10: 10.866 | G10: =H10 -> 14.159 | H10: 14.159 | I10: 13.079 | J10: 14.468 | K10: 13.95 | L10: =M10 -> 15.632 | M10: 15.632 | N10: 12.46 | O10: 14.073 | P10: 13.195 | Q10: =R10 -> 19.865 | R10: 19.865 | S10: 16.348 | T10: 17.806 | U10: 15.985 | V10: =W10 -> 20.928 | W10: 20.928 | X10: 17.742 | Y10: 16.874 | Z10: 16.356 | AA10: =AB10 -> 25.619 | AB10: 25.619 | AC10: 22.862 | AD10: 22.932 | AE10: 26.265 | AK10: =AL10 -> 0
B11: Other receivables | C11: 62.327 | D11: 29.692 | E11: 33.413 | F11: 35.004 | G11: =H11 -> 72.658 | H11: 72.658 | I11: 30.588 | J11: 27.15 | K11: 30.765 | L11: =M11 -> 64.592 | M11: 64.592 | N11: 32.328 | O11: 34.742 | P11: 33.897 | Q11: =R11 -> 67.518 | R11: 67.518 | S11: 26.376 | T11: 31.815 | U11: 34.916 | V11: =W11 -> 68.193 | W11: 68.193 | X11: 28.446 | Y11: 30.797 | Z11: 31.445 | AA11: =AB11 -> 64.683 | AB11: 64.683 | AC11: 27.283 | AD11: 25.652 | AE11: 25.468 | AK11: =AL11 -> 0
B12: Total Account Receivable | C12: =C10+C11 -> 77.497 | D12: =D10+D11 -> 42.335 | E12: =E10+E11 -> 42.224 | F12: =F10+F11 -> 45.87 | G12: =G10+G11 -> 86.817 | H12: =H10+H11 -> 86.817 | I12: =I10+I11 -> 43.667 | J12: =J10+J11 -> 41.618 | ... AE12: =AE10+AE11 -> 51.733 | AF12: =AG12 -> 75.787 | AG12: 75.787 | AH12: 57.815 | AI12: 57.934 | AJ12: 66.663 | AK12: =AL12 -> 100.504 | AL12: 100.504 | AM12: 66.451 | AN12: 71.338 | AO12: 67.661 | AP12: =AQ12 -> 105.511 | AQ12: 105.511 | AR12: 68.456 | AS12: 71.366 | AT12: 70.236 | AU12: =AV12 -> 103.094 | AV12: 103.094
B13: Income tax receivable | C13: 17.383 | D13: 12.783 | E13: 5.917 | F13: 16.031 | G13: =H13 -> 18.739 | H13: 18.739 | I13: 16.021 | J13: 4.341 | K13: 0.459 | L13: =M13 -> 0 | O13: 4.198 | P13: 5.038 | Q13: =R13 -> 15.016 | R13: 15.016 | S13: 1.348 | T13: 2.433 | U13: 3.185 | V13: =W13 -> 0 | W13: 0 | Y13: 2.382 | Z13: 8.415 | AA13: =AB13 -> 4.626 | AB13: 4.626 | AC13: 49.179 | AD13: 79.013 | AE13: 45.603 | AF13: =AG13 -> 36.889 | AG13: 36.889 | AH13: 34.973 | AI13: 34.655 | AJ13: 39.51 | AK13: =AL13 -> 36.173 | AL13: 36.173 | AM13: 36.893 | AN13: 39.791 | AO13: 23.692 | AP13: =AQ13 -> 21.522 | AQ13: 21.522 | AR13: 21.64 | AS13: 22.739 | AT13: 23.923 | AU13: =AV13 -> 20.67 | AV13: 20.67
B14: Inventories | C14: 33.255 | D14: 32.525 | E14: 36.466 | F14: 36.742 | G14: =H14 -> 34.01 | H14: 34.01 | I14: 35.543 | J14: 34.571 | K14: 35.541 | L14: =M14 -> 34.926 | M14: 34.926 | N14: 38.541 | O14: 40.246 | P14: 44.195 | Q14: =R14 -> 42.56 | R14: 42.56 | S14: 40.959 | T14: 34.691 | U14: 39.769 | V14: =W14 -> 38.886 | W14: 38.886 | X14: 42.028 | Y14: 46.011 | Z14: 47.778 | AA14: =AB14 -> 47.225 | AB14: 47.225 | AC14: 47.822 | AD14: 40.511 | AE14: 37.727 | AF14: =AG14 -> 39.288 | AG14: 39.288 | AH14: 38.955 | AI14: 41.868 | AJ14: 43.27 | AK14: =AL14 -> 42.839 | AL14: 42.839 | AM14: 46.68 | AN14: 52.286 | AO14: 62.275 | AP14: =AQ14 -> 55.559 | AQ14: 55.559 | AR14: 58.989 | AS14: 60.868 | AT14: 58.672 | AU14: =AV14 -> 57.654 | AV14: 57.654
B15: Prepaid expenses | C15: 38.233 | D15: 46.579 | E15: 46.622 | F15: 44.08 | G15: =H15 -> 41.976 | H15: 41.976 | I15: 40.637 | J15: 37.824 | K15: 36.337 | L15: =M15 -> 52.438 | M15: 52.438 | N15: 52.585 | O15: 50.919 | P15: 48.521 | Q15: =R15 -> 57.666 | R15: 57.666 | S15: 54.036 | T15: 52.946 | U15: 48.327 | V15: =W15 -> 40.645 | W15: 40.645 | X15: 46.771 | Y15: 39.524 | Z15: 38.895 | AA15: =AB15 -> 43.946 | AB15: 43.946 | AC15: 42.489 | AD15: 36.342 | AE15: 32.188 | AF15: =AG15 -> 35.31 | AG15: 35.31 | AH15: 30.727 | AI15: 32.039 | AJ15: 29.714 | AK15: =AL15 -> 36.446 | AL15: 36.446 | AM15: 33.741 | AN15: 33.373 | AO15: 30.953 | AP15: =AQ15 -> 48.399 | AQ15: 48.399 | AR15: 48.387 | AS15: 52.641 | AT15: 55.558 | AU15: =AV15 -> 63.09 | AV15: 63.09
B16: Deferred income taxes | D16: 15.076 | E16: 15.076 | F16: 15.076 | G16: =H16 -> 0 | L16: =M16 -> 0 | Q16: =R16 -> 0 | AK16: =AL16 -> 0 | AP16: =AQ16 -> 0 | AU16: =AV16 -> 0
B17: Total Current Assets | C17: =SUM(C9,C12:C16) -> 224.386 | D17: =SUM(D9,D12:D16) -> 188.776 | E17: =SUM(E9,E12:E16) -> 207.853 | F17: =SUM(F9,F12:F16) -> 187.406 | G17: =SUM(G9,G12:G16) -> 225.396 | H17: =SUM(H9,H12:H16) -> 225.396 | I17: =SUM(I9,I12:I16) -> 189.79 | J17: =SUM(J9,J12:J16) -> 197.972 | ... AV17: =SUM(AV9,AV12:AV16) -> 300.798
B19: Non-Current Assets
B20: Property and equipment, net | C20: 828.305 | D20: 828.966 | E20: 851.477 | F20: 874.34 | G20: =H20 -> 892.191 | H20: 892.191 | I20: 885.964 | J20: 888.849 | K20: 902.581 | L20: =M20 -> 910.134 | M20: 910.134 | N20: 910.581 | O20: 913.375 | P20: 933.484 | Q20: =R20 -> 935.045 | R20: 935.045 | S20: 935.279 | T20: 936.469 | U20: 940.077 | V20: =W20 -> 913.275 | W20: 913.275 | X20: 763.884 | Y20: 758.496 | Z20: 759.243 | AA20: =AB20 -> 831.599 | AB20: 831.599 | AC20: 818.283 | AD20: 805.889 | AE20: 789.604 | AF20: =AG20 -> 774.137 | AG20: 774.137 | AH20: 760.722 | AI20: 761.589 | AJ20: 755.64 | AK20: =AL20 -> 741.746 | AL20: 741.746 | AM20: 744.751 | AN20: 745.251 | AO20: 755.524 | AP20: =AQ20 -> 746.051 | AQ20: 746.051 | AR20: 754.895 | AS20: 770.315 | AT20: 777.669 | AU20: =AV20 -> 791.093 | AV20: 791.093
B21: Intangible assets, net | C21: 20.781 | D21: 21.215 | E21: 21.504 | F21: 21.607 | G21: =H21 -> 21.972 | H21: 21.972 | I21: 22.471 | J21: 22.597 | K21: 22.844 | L21: =M21 -> 23.054 | M21: 23.054 | N21: 23.214 | O21: 23.392 | P21: 23.546 | Q21: =R21 -> 24.065 | R21: 24.065 | S21: 24.233 | T21: 24.524 | U21: 26.327 | V21: =W21 -> 26.209 | W21: 26.209 | X21: 20.094 | Y21: 20.157 | Z21: 20.271 | AA21: =AB21 -> 437.207 | AB21: 437.207 | AC21: 254.401 | AD21: 254.33 | AE21: 253.577 | AF21: =AG21 -> 253.16 | AG21: 253.16 | AH21: 253.152 | AI21: 253.143 | AJ21: 253.154 | AK21: =AL21 -> 251.701 | AL21: 251.701 | AM21: 251.655 | AN21: 251.618 | AO21: 251.639 | AP21: =AQ21 -> 251.524 | AQ21: 251.524 | AR21: 251.526 | AS21: 251.559 | AT21: 251.529 | AU21: =AV21 -> 251.727 | AV21: 251.727
B22: Operating lease assets | X22: 968.741 | Y22: 963.724 | Z22: 984.838 | AA22: =AB22 -> 1240.976 | AB22: 1240.976 | AC22: 1257.428 | AD22: 1268.137 | AE22: 1267.27 | AF22: =AG22 -> 1251.027 | AG22: 1251.027 | AH22: 1245.892 | AI22: 1241.197 | AJ22: 1258.851 | AK22: =AL22 -> 1241.237 | AL22: 1241.237 | AM22: 1240.552 | AN22: 1241.699 | AO22: 1267.241 | AP22: =AQ22 -> 1268.986 | AQ22: 1268.986 | AR22: 1259.026 | AS22: 1280.758 | AT22: 1307.345 | AU22: =AV22 -> 1302.15 | AV22: 1302.15
B23: Prepaid rent | C23: 46.212 | D23: 47.067 | E23: 46.109 | F23: 46.844 | G23: =H23 -> 46.881 | H23: 46.881 | I23: 45.521 | J23: 44.386 | K23: 43.251 | L23: =M23 -> 42.162 | M23: 42.162 | N23: 41.362 | O23: 40.736 | P23: 39.652 | Q23: =R23 -> 39.399 | R23: 39.399 | S23: 37.875 | T23: 36.759 | U23: 35.814 | V23: =W23 -> 34.961 | W23: 34.961 | AA23: =AB23 -> 0 | AF23: =AG23 -> 0 | AK23: =AL23 -> 0 | AP23: =AQ23 -> 0 | AU23: =AV23 -> 0
B24: Investments in unconsolidated affiliates | V24: =W24 -> 79.767 | W24: 79.767 | X24: 81.317 | Y24: 79.674 | Z24: 69.328 | AA24: =AB24 -> 0 | AF24: =AG24 -> 0 | AK24: =AL24 -> 0 | AP24: =AQ24 -> 0 | AU24: =AV24 -> 0
B25: Other | C25: 41.692 | D25: 42.702 | E25: 47.847 | F25: 45.659 | G25: =H25 -> 46.906 | H25: 46.906 | I25: 48.905 | J25: 50.514 | K25: 52.806 | L25: =M25 -> 96.542 | M25: 96.542 | N25: 100.091 | O25: 111.32 | P25: 114.005 | Q25: =R25 -> 125.918 | R25: 125.918 | S25: 126.088 | T25: 139.827 | U25: 151.024 | V25: =W25 -> 64.691 | W25: 64.691 | X25: 84.528 | Y25: 93.547 | Z25: 98.949 | AA25: =AB25 -> 86.296 | AB25: 86.296 | AC25: 75.012 | AD25: 84.32 | AE25: 106.593 | AF25: =AG25 -> 127.371 | AG25: 127.371 | AH25: 131.858 | AI25: 138.097 | AJ25: 139.886 | AK25: =AL25 -> 157.852 | AL25: 157.852 | AM25: 149.462 | AN25: 142.186 | AO25: 141.932 | AP25: =AQ25 -> 162.891 | AQ25: 162.891 | AR25: 163.405 | AS25: 167.905 | AT25: 167.971 | AU25: =AV25 -> 194.615 | AV25: 194.615
B26: Total Non-Current Assets | C26: =SUM(C20:C25) -> 936.99 | D26: =SUM(D20:D25) -> 939.95 | E26: =SUM(E20:E25) -> 966.937 | F26: =SUM(F20:F25) -> 988.45 | G26: =SUM(G20:G25) -> 1007.95 | H26: =SUM(H20:H25) -> 1007.95 | I26: =SUM(I20:I25) -> 1002.861 | J26: =SUM(J20:J25) -> 1006.346 | ... AV26: =SUM(AV20:AV25) -> 2539.585
B27: Total Assets | C27: =C17+C26 -> 1161.376 | D27: =D17+D26 -> 1128.726 | E27: =E17+E26 -> 1174.79 | F27: =F17+F26 -> 1175.856 | G27: =G17+G26 -> 1233.346 | H27: =H17+H26 -> 1233.346 | I27: =I17+I26 -> 1192.651 | J27: =J17+J26 -> 1204.318 | ... AV27: =AV17+AV26 -> 2840.383
B29: Current Liabilities
B30: Accounts payable | C30: 57.325 | D30: 54.152 | E30: 52.171 | F30: 44.208 | G30: =H30 -> 47.77 | H30: 47.77 | I30: 38.363 | J30: 38.573 | K30: 38.906 | L30: =M30 -> 41.564 | M30: 41.564 | N30: 34.937 | O30: 46.219 | P30: 46.572 | Q30: =R30 -> 50.984 | R30: 50.984 | S30: 38.805 | T30: 38.312 | U30: 39.13 | V30: =W30 -> 49.071 | W30: 49.071 | X30: 36.394 | Y30: 35.96 | Z30: 36.095 | AA30: =AB30 -> 61.946 | AB30: 61.946 | AC30: 55.894 | AD30: 57.532 | AE30: 61.549 | AF30: =AG30 -> 58.432 | AG30: 58.432 | AH30: 56.047 | AI30: 55.377 | AJ30: 52.89 | AK30: =AL30 -> 54.086 | AL30: 54.086 | AM30: 61.741 | AN30: 58.927 | AO30: 59.03 | AP30: =AQ30 -> 66.638 | AQ30: 66.638 | AR30: 57.001 | AS30: 72.682 | AT30: 53.392 | AU30: =AV30 -> 63.152 | AV30: 63.152
B31: Income taxes payable | G31: =H31 -> 0 | L31: =M31 -> 2.299 | M31: 2.299 | N31: 5.463 | O31: 0 | P31: 0 | Q31: =R31 -> 0 | R31: 0 | S31: =R31 -> 0 | V31: =W31 -> 0.712 | W31: 0.712 | X31: 0.031 | AA31: =AB31 -> 0 | AF31: =AG31 -> 0 | AK31: =AL31 -> 0 | AP31: =AQ31 -> 0 | AU31: =AV31 -> 0
B32: Gift card liabilities | G32: =H32 -> 0 | L32: =M32 -> 153.629 | M32: 153.629 | N32: 127.618 | O32: 123.64 | P32: 116.419 | Q32: =R32 -> 163.951 | R32: 163.951 | S32: 138.134 | T32: 133.617 | U32: 125.342 | V32: =W32 -> 172.336 | W32: 172.336 | X32: 145.745 | Y32: 142.361 | Z32: 135.566 | AA32: =AB32 -> 187.978 | AB32: 187.978 | AC32: 161.215 | AD32: 162.241 | AE32: 155.486 | AF32: =AG32 -> 184.655 | AG32: 184.655 | AH32: 166.178 | AI32: 169.098 | AJ32: 161.513 | AK32: =AL32 -> 211.182 | AL32: 211.182 | AM32: 185.512 | AN32: 182.295 | AO32: 174.725 | AP32: =AQ32 -> 219.808 | AQ32: 219.808 | AR32: 191.908 | AS32: 187.483 | AT32: 180.2 | AU32: =AV32 -> 222.915 | AV32: 222.915
B33: Operating lease liabilities | X33: 93.151 | Y33: 85.669 | Z33: 90.027 | AA33: =AB33 -> 128.081 | AB33: 128.081 | AC33: 123.189 | AD33: 120.35 | AE33: 128.767 | AF33: =AG33 -> 132.519 | AG33: 132.519 | AH33: 132.521 | AI33: 131.189 | AJ33: 132.55 | AK33: =AL33 -> 131.818 | AL33: 131.818 | AM33: 144.966 | AN33: 144.829 | AO33: 147.413 | AP33: =AQ33 -> 139.099 | AQ33: 139.099 | AR33: 140.493 | AS33: 142.37 | AT33: 144.488 | AU33: =AV33 -> 134.905 | AV33: 134.905
B34: Other accrued expenses | C34: 264.686 | D34: 243.623 | E34: 246.07 | F34: 246.428 | G34: =H34 -> 302.456 | H34: 302.456 | I34: 267.857 | J34: 265.851 | K34: 265.197 | L34: =M34 -> 179.034 | M34: 179.034 | N34: 155.081 | O34: 160.046 | P34: 159.823 | Q34: =R34 -> 183.016 | R34: 183.016 | S34: 167.367 | T34: 182.659 | U34: 179.062 | V34: =W34 -> 194.381 | W34: 194.381 | X34: 171.315 | Y34: 172.973 | Z34: 172.098 | AA34: =AB34 -> 236.582 | AB34: 236.582 | AC34: 166.828 | AD34: 192.549 | AE34: 194.575 | AF34: =AG34 -> 210.461 | AG34: 210.461 | AH34: 203.211 | AI34: 241.488 | AJ34: 210.155 | AK34: =AL34 -> 239.187 | AL34: 239.187 | AM34: 202.217 | AN34: 237.453 | AO34: 225 | AP34: =AQ34 -> 231.133 | AQ34: 231.133 | AR34: 237.293 | AS34: 220.917 | AT34: 240.44 | AU34: =AV34 -> 239.699 | AV34: 239.699
B35: Total Current Liabilities | C35: =SUM(C30:C34) -> 322.011 | D35: =SUM(D30:D34) -> 297.775 | E35: =SUM(E30:E34) -> 298.241 | F35: =SUM(F30:F34) -> 290.636 | G35: =SUM(G30:G34) -> 350.226 | H35: =SUM(H30:H34) -> 350.226 | I35: =SUM(I30:I34) -> 306.22 | J35: =SUM(J30:J34) -> 304.424 | ... AV35: =SUM(AV30:AV34) -> 660.671
B37: Non-Current Liabilities
B38: Income tax payable | G38: =H38 -> 0 | L38: =M38 -> 0
B39: Deferred income taxes | C39: 81.433 | D39: 97.724 | E39: 97.655 | F39: 97.184 | G39: =H39 -> 82.524 | H39: 82.524 | I39: 85.685 | J39: 83.737 | K39: 83.088 | L39: =M39 -> 82.401 | M39: 82.401 | N39: 85.587 | O39: 84.665 | P39: 83.54 | Q39: =R39 -> 57.216 | R39: 57.216 | S39: 57.122 | T39: 56.77 | U39: 56.881 | V39: =W39 -> 52.123 | W39: 52.123 | X39: 43.048 | Y39: 38.902 | Z39: 38.449 | AA39: =AB39 -> 33.847 | AB39: 33.847 | AC39: 23.838 | AD39: 23.479 | AF39: =AG39 -> 0
B40: Deferred rent | C40: 73.857 | D40: 73.451 | E40: 73.101 | F40: 72.858 | G40: =H40 -> 72.911 | H40: 72.911 | I40: 72.58 | J40: 72.255 | K40: 71.808 | L40: =M40 -> 71.575 | M40: 71.575 | N40: 70.857 | O40: 75.261 | P40: 74.784 | Q40: =R40 -> 74.761 | R40: 74.761 | S40: 73.666 | T40: 71.497 | U40: 70.437 | V40: =W40 -> 79.697 | W40: 79.697 | AA40: =AB40 -> 0 | AF40: =AG40 -> 0
B41: Deemed landlord financing liability | C41: 77.165 | D41: 76.552 | E41: 79.221 | F41: 85.259 | G41: =H41 -> 87.841 | H41: 87.841 | I41: 89.173 | J41: 91.973 | K41: 98.501 | L41: =M41 -> 100.576 | M41: 100.576 | N41: 107.541 | O41: 104.606 | P41: 113.607 | Q41: =R41 -> 108.627 | R41: 108.627 | S41: 112.895 | T41: 114.79 | U41: 125.564 | V41: =W41 -> 113.095 | W41: 113.095 | AA41: =AB41 -> 0 | AF41: =AG41 -> 0
B42: Long term debt | D42: 25 | E42: 25 | G42: =H42 -> 0 | L42: =M42 -> 0 | O42: 0 | P42: 30 | Q42: =R42 -> 10 | R42: 10 | S42: 30 | T42: 20 | U42: 20 | V42: =W42 -> 10 | W42: 10 | X42: 20 | Y42: 35 | Z42: 335 | AA42: =AB42 -> 290 | AB42: 290 | AC42: 380 | AD42: 376 | AE42: 376 | AF42: =AG42 -> 280 | AG42: 280 | AH42: 280 | AI42: 465.01 | AJ42: 465.514 | AK42: =AL42 -> 466.017 | AL42: 466.017 | AM42: 466.521 | AN42: 467.025 | AO42: 467.528 | AP42: =AQ42 -> 468.032 | AQ42: 468.032 | AR42: 468.536 | AS42: 469.04 | AT42: 469.543 | AU42: =AV42 -> 470.047 | AV42: 470.047
B43: Operating lease liabilities | X43: 946.786 | Y43: 942.586 | Z43: 959.632 | AA43: =AB43 -> 1189.869 | AB43: 1189.869 | AC43: 1217.582 | AD43: 1242.035 | AE43: 1236.612 | AF43: =AG43 -> 1224.321 | AG43: 1224.321 | AH43: 1216.473 | AI43: 1211.878 | AJ43: 1227.705 | AK43: =AL43 -> 1218.269 | AL43: 1218.269 | AM43: 1201.55 | AN43: 1195.912 | AO43: 1215.009 | AP43: =AQ43 -> 1233.497 | AQ43: 1233.497 | AR43: 1218.024 | AS43: 1228.664 | AT43: 1246.819 | AU43: =AV43 -> 1254.955 | AV43: 1254.955
B44: Other noncurrent liabilities | C44: 50.4 | D44: 51.72 | E44: 52.453 | F44: 50.38 | G44: =H44 -> 51.305 | H44: 51.305 | I44: 53.433 | J44: 55.087 | K44: 57.348 | L44: =M44 -> 59.034 | M44: 59.034 | N44: 62.209 | O44: 64.347 | P44: 67.224 | Q44: =R44 -> 70.975 | R44: 70.975 | S44: 75.161 | T44: 76.212 | U44: 78.241 | V44: =W44 -> 71.659 | W44: 71.659 | X44: 77.366 | Y44: 80.06 | Z44: 81.087 | AA44: =AB44 -> 140.548 | AB44: 140.548 | AC44: 128.265 | AD44: 137.087 | AE44: 142.872 | AF44: =AG44 -> 149.725 | AG44: 149.725 | AH44: 151.01 | AI44: 163.642 | AJ44: 145.445 | AK44: =AL44 -> 147.4 | AL44: 147.4 | AM44: 135.908 | AN44: 124.308 | AO44: 121.873 | AP44: =AQ44 -> 125.01 | AQ44: 125.01 | AR44: 129.394 | AS44: 122.649 | AT44: 120.364 | AU44: =AV44 -> 136.648 | AV44: 136.648
B45: Convertible preferred stock | AD45: 204.079 | AE45: 209.926 | AF45: =AG45 -> 218.248 | AG45: 218.248 | AH45: 213.485 | AQ45: =AP45 -> 0 | AV45: =AU45 -> 0
B46: Total Non-Current liabilities | C46: =SUM(C38:C45) -> 282.855 | D46: =SUM(D38:D45) -> 324.447 | E46: =SUM(E38:E45) -> 327.43 | F46: =SUM(F38:F45) -> 305.681 | G46: =SUM(G38:G45) -> 294.581 | H46: =SUM(H38:H45) -> 294.581 | I46: =SUM(I38:I45) -> 300.871 | J46: =SUM(J38:J45) -> 303.052 | ... AV46: =SUM(AV38:AV45) -> 1861.65
B47: Total Liabilities | C47: =C35+C46 -> 604.866 | D47: =D35+D46 -> 622.222 | E47: =E35+E46 -> 625.671 | F47: =F35+F46 -> 596.317 | G47: =G35+G46 -> 644.807 | H47: =H35+H46 -> 644.807 | I47: =I35+I46 -> 607.091 | J47: =J35+J46 -> 607.476 | ... AV47: =AV35+AV46 -> 2522.321
B49: Shareholders' Equity
B50: Common stock | C50: 0.918 | D50: 0.921 | E50: 0.926 | F50: 0.93 | G50: =H50 -> 0.931 | H50: 0.931 | I50: 0.938 | J50: 0.939 | K50: 0.942 | L50: =M50 -> 0.947 | M50: 0.947 | N50: 0.951 | O50: 0.952 | P50: 0.953 | Q50: =R50 -> 0.954 | R50: 0.954 | S50: 0.96 | T50: 0.962 | U50: 0.963 | V50: =W50 -> 0.967 | W50: 0.967 | X50: 0.974 | Y50: 0.975 | Z50: 0.975 | AA50: =AB50 -> 0.977 | AB50: 0.977 | AC50: 0.985 | AD50: 0.985 | AE50: 0.984 | AF50: =AG50 -> 0.986 | AG50: 0.986 | AH50: 0.995 | AI50: 1.052 | AJ50: 1.053 | AK50: =AL50 -> 1.054 | AL50: 1.054 | AM50: 1.06 | AN50: 1.06 | AO50: 1.062 | AP50: =AQ50 -> 1.063 | AQ50: 1.063 | AR50: 1.069 | AS50: 1.07 | AT50: 1.071 | AU50: =AV50 -> 1.072 | AV50: 1.072
B51: Additional paid-in capital | C51: 654.033 | D51: 664.236 | E51: 683.976 | F51: 701.274 | G51: =H51 -> 710.242 | H51: 710.242 | I51: 733.078 | J51: 742.041 | K51: 754.034 | L51: =M51 -> 774.137 | M51: 774.137 | N51: 784.172 | O51: 791.777 | P51: 797.505 | Q51: =R51 -> 799.862 | R51: 799.862 | S51: 806.479 | T51: 817.384 | U51: 823.206 | V51: =W51 -> 828.676 | W51: 828.676 | X51: 840.12 | Y51: 845.461 | Z51: 850.485 | AA51: =AB51 -> 855.989 | AB51: 855.989 | AC51: 861.641 | AD51: 866.803 | AE51: 871.771 | AF51: =AG51 -> 878.148 | AG51: 878.148 | AH51: 904.045 | AI51: 850.601 | AJ51: 856.042 | AK51: =AL51 -> 862.758 | AL51: 862.758 | AM51: 868.41 | AN51: 874.551 | AO51: 880.215 | AP51: =AQ51 -> 887.485 | AQ51: 887.485 | AR51: 893.423 | AS51: 899.792 | AT51: 906.458 | AU51: =AV51 -> 913.442 | AV51: 913.442
B52: Retained earnings | C52: 1060.211 | D52: 1080.388 | E52: 1107.066 | F52: 1123.411 | G52: =H52 -> 1140.788 | H52: 1140.788 | I52: 1165.012 | J52: 1193.914 | K52: 1216.978 | L52: =M52 -> 1238.012 | M52: 1238.012 | N52: 1261.592 | O52: 1288.245 | P52: 1301.209 | Q52: =R52 -> 1345.666 | R52: 1345.666 | S52: 1354.855 | T52: 1369.912 | U52: 1383.305 | V52: =W52 -> 1384.494 | W52: 1384.494 | X52: 1355.06 | Y52: 1375.671 | Z52: 1375.69 | AA52: =AB52 -> 1408.333 | AB52: 1408.333 | AC52: 1255.794 | AD52: 1184.919 | AE52: 1150.726 | AF52: =AG52 -> 1110.087 | AG52: 1110.087 | AH52: 1114.047 | AI52: 1134.186 | AJ52: 1167.001 | AK52: =AL52 -> 1169.15 | AL52: 1169.15 | AM52: 1192.335 | AN52: 1203.731 | AO52: 1187.28 | AP52: =AQ52 -> 1170.078 | AQ52: 1170.078 | AR52: 1184.199 | AS52: 1213.115 | AT52: 1217.271 | AU52: =AV52 -> 1216.239 | AV52: 1216.239
B53: Accumulated other comprehensive loss | G53: =H53 -> 0 | L53: =M53 -> 0 | O53: 0 | P53: -0.039 | Q53: =R53 -> -0.088 | R53: -0.088 | S53: -0.334 | T53: -0.583 | U53: -0.311 | V53: =W53 -> -0.938 | W53: -0.938 | X53: -0.699 | Y53: -0.524 | Z53: -0.633 | AA53: =AB53 -> -0.435 | AB53: -0.435 | AC53: -3.741 | AD53: -4.804 | AE53: -4.841 | AF53: =AG53 -> -3.785 | AG53: -3.785 | AH53: -1.873 | AI53: 0.072 | AJ53: -0.166 | AK53: =AL53 -> -0.287 | AL53: -0.287 | AM53: -0.032 | AN53: -0.332 | AO53: -1.056 | AP53: =AQ53 -> -0.982 | AQ53: -0.982 | AR53: -0.835 | AS53: -0.655 | AT53: -1.066 | AU53: =AV53 -> -0.694 | AV53: -0.694
B54: Treasury stock | C54: -1158.652 | D54: -1239.041 | E54: -1242.849 | F54: -1246.076 | G54: =H54 -> -1263.422 | H54: -1263.422 | I54: -1313.468 | J54: -1340.052 | K54: -1382.423 | L54: =M54 -> -1409.889 | M54: -1409.889 | N54: -1419.18 | O54: -1440.443 | P54: -1516.269 | Q54: =R54 -> -1532.864 | R54: -1532.864 | S54: -1567.767 | T54: -1574.893 | U54: -1593.757 | V54: =W54 -> -1642.14 | W54: -1642.14 | X54: -1653.211 | Y54: -1681.304 | Z54: -1692.701 | AA54: =AB54 -> -1693.122 | AB54: -1693.122 | AC54: -1695.708 | AD54: -1695.974 | AE54: -1696.364 | AF54: =AG54 -> -1696.743 | AG54: -1696.743 | AH54: -1700.7 | AI54: -1701.303 | AJ54: -1701.984 | AK54: =AL54 -> -1702.509 | AL54: -1702.509 | AM54: -1706.447 | AN54: -1717.326 | AO54: -1744.005 | AP54: =AQ54 -> -1765.641 | AQ54: -1765.641 | AR54: -1778.017 | AS54: -1787.419 | AT54: -1802.09 | AU54: =AV54 -> -1811.997 | AV54: -1811.997
B55: Total SE | C55: =SUM(C50:C54) -> 556.51 | D55: =SUM(D50:D54) -> 506.504 | E55: =SUM(E50:E54) -> 549.119 | F55: =SUM(F50:F54) -> 579.539 | G55: =SUM(G50:G54) -> 588.539 | H55: =SUM(H50:H54) -> 588.539 | I55: =SUM(I50:I54) -> 585.56 | J55: =SUM(J50:J54) -> 596.842 | ... AV55: =SUM(AV50:AV54) -> 318.062
B56: Total Liabilities & SE | C56: =C55+C47 -> 1161.376 | D56: =D55+D47 -> 1128.726 | E56: =E55+E47 -> 1174.79 | F56: =F55+F47 -> 1175.856 | G56: =G55+G47 -> 1233.346 | H56: =H55+H47 -> 1233.346 | I56: =I55+I47 -> 1192.651 | J56: =J55+J47 -> 1204.318 | ... AV56: =AV55+AV47 -> 2840.383

Sheet Cash Flow Statement Link
B3: Period Ended | C3: 42003 | D3: 42094 | E3: 42185 | F3: 42276 | G3: 42367 | H3: 42367 | I3: 42458 | J3: 42549 | K3: 42640 | L3: 42738 | M3: 42738 | N3: 42829 | O3: 42920 | P3: 43011 | Q3: 43102 | R3: 43102 | S3: 43193 | T3: 43284 | U3: 43375 | V3: 43466 | W3: 43466 | X3: 43557 | Y3: 43648 | Z3: 43739 | AA3: 43830 | AB3: 43830 | AC3: 43921 | AD3: 44012 | AE3: 44103 | AF3: 44194 | AG3: 44194 | AH3: 44285 | AI3: 44376 | AJ3: 44467 | AK3: 44558 | AL3: 44558 | AM3: 44649 | AN3: 44740 | AO3: 44831 | AP3: 44929 | AQ3: 44929 | AR3: 45019 | AS3: 45111 | AT3: 45202 | AU3: 45293 | AV3: 45293
C4: FY2014 | D4: Q1-2015 | E4: Q2-2015 | F4: Q3-2015 | G4: Q4-2015 | H4: FY2015 | I4: Q1-2016 | J4: Q2-2016 | K4: Q3-2016 | L4: Q4-2016 | M4: FY2016 | N4: Q1-2017 | O4: Q2-2017 | P4: Q3-2017 | Q4: Q4-2017 | R4: FY2017 | S4: Q1-2018 | T4: Q2-2018 | U4: Q3-2018 | V4: Q4-2018 | W4: FY2018 | X4: Q1-2019 | Y4: Q2-2019 | Z4: Q3-2019 | AA4: Q4-2019 | AB4: FY2019 | AC4: Q1-2020 | AD4: Q2-2020 | AE4: Q3-2020 | AF4: Q4-2020 | AG4: FY2020 | AH4: Q1-2021 | AI4: Q2-2021 | AJ4: Q3-2021 | AK4: Q4-2021 | AL4: FY2021 | AM4: Q1-2022 | AN4: Q2-2022 | AO4: Q3-2022 | AP4: Q4-2022 | AQ4: FY2022 | AR4: Q1-2023 | AS4: Q2-2023 | AT4: Q3-2023 | AU4: Q4-2023 | AV4: FY2023
B6: Cheesecake Factory CFS
B8: Cash Flow from Operations
B9: Net income | C9: 101.276 | D9: 28.423 | E9: 63.147 | F9: 89.323 | G9: =H9 -> 116.523 | H9: 116.523 | I9: 33.954 | J9: 72.539 | K9: 107.113 | L9: =M9 -> 139.494 | M9: 139.494 | N9: 35.043 | O9: 73.209 | P9: 99.654 | Q9: =R9 -> 157.392 | R9: 157.392 | S9: 26.029 | T9: 54.382 | U9: 82.857 | V9: =W9 -> 99.035 | W9: 99.035 | X9: 26.984 | Y9: 62.494 | Z9: 78.584 | AA9: =AB9 -> 127.293 | AB9: 127.293 | AC9: -136.163 | AD9: -192.702 | AE9: -221.048 | AF9: =AG9 -> -253.365 | AG9: -253.365 | AH9: 3.868 | AI9: 37.583 | AJ9: 70.263 | AK9: =AL9 -> 72.373 | AL9: 72.373 | AM9: 23.163 | AN9: 48.819 | AO9: 46.421 | AP9: =AQ9 -> 43.123 | AQ9: 43.123 | AR9: 28.05 | AS9: 70.725 | AT9: 88.67 | AU9: =AV9 -> 101.351 | AV9: 101.351
B10: Depreciation and amortization expenses | C10: 82.835 | D10: 21.177 | E10: 42.335 | F10: 63.652 | G10: =H10 -> 85.563 | H10: 85.563 | I10: 21.464 | J10: 42.925 | K10: 64.559 | L10: =M10 -> 88.01 | M10: 88.01 | N10: 23.196 | O10: 46.493 | P10: 69.492 | Q10: =R10 -> 92.729 | R10: 92.729 | S10: 24.002 | T10: 47.729 | U10: 71.819 | V10: =W10 -> 95.976 | W10: 95.976 | X10: 21.362 | Y10: 43.021 | Z10: 64.363 | AA10: =AB10 -> 88.133 | AB10: 88.133 | AC10: 23.562 | AD10: 46.152 | AE10: 68.803 | AF10: =AG10 -> 91.415 | AG10: 91.415 | AH10: 22.006 | AI10: 44.229 | AJ10: 66.805 | AK10: =AL10 -> 89.654 | AL10: 89.654 | AM10: 21.505 | AN10: 44.113 | AO10: 66.764 | AP10: =AQ10 -> 92.38 | AQ10: 92.38 | AR10: 22.955 | AS10: 46.287 | AT10: 69.124 | AU10: =AV10 -> 93.136 | AV10: 93.136
B11: Impairment of assets and lease terminations | C11: 0.245 | F11: 6.011 | G11: =H11 -> 6.011 | H11: 6.011 | L11: =M11 -> 0.114 | M11: 0.114 | N11: 0.786 | O11: 1.489 | P11: 1.491 | Q11: =R11 -> 10.586 | R11: 10.586 | S11: 0 | T11: 2.493 | U11: 2.532 | V11: =W11 -> 16.411 | W11: 16.411 | AA11: =AB11 -> 16.223 | AB11: 16.223 | AC11: 191.571 | AD11: 193.889 | AE11: 195.981 | AF11: =AG11 -> 208.066 | AG11: 208.066 | AH11: 0.431 | AI11: 0.394 | AJ11: 0.394 | AK11: =AL11 -> 17.937 | AL11: 17.937 | AM11: 0.149 | AN11: 0.25 | AO11: 0.25 | AP11: =AQ11 -> 31.327 | AQ11: 31.327 | AR11: -0.014 | AS11: -0.768 | AT11: -0.753 | AU11: =AV11 -> 26.998 | AV11: 26.998
B12: Deferred income taxes | C12: 0.204 | D12: 1.215 | E12: 1.146 | F12: 0.675 | G12: =H12 -> 1.184 | H12: 1.184 | I12: 3.161 | J12: 1.213 | K12: 0.564 | L12: =M12 -> -1.005 | M12: -1.005 | N12: 3.186 | O12: 2.264 | P12: 1.139 | Q12: =R12 -> -25.18 | R12: -25.18 | S12: 1.157 | T12: 0.805 | U12: 0.916 | V12: =W12 -> -5.51 | W12: -5.51 | X12: 1.792 | Y12: -2.289 | Z12: -2.64 | AA12: =AB12 -> -2.197 | AB12: -2.197 | AC12: -11.231 | AD12: -11.173 | AE12: -52.979 | AF12: =AG12 -> -67.228 | AG12: -67.228 | AH12: -1.508 | AI12: -2.895 | AJ12: -5.227 | AK12: =AL12 -> -20.849 | AL12: -20.849 | AM12: 3.869 | AN12: 0.279 | AO12: -2.633 | AP12: =AQ12 -> -18.646 | AQ12: -18.646 | AR12: 3.192 | AS12: 2.469 | AT12: 1.613 | AU12: =AV12 -> -15.715 | AV12: -15.715
B13: Stock-based compensation | C13: 16.817 | D13: 4.731 | E13: 9.677 | F13: 14.549 | G13: =H13 -> 20.053 | H13: 20.053 | I13: 5.185 | J13: 11.304 | K13: 16.177 | L13: =M13 -> 21.473 | M13: 21.473 | N13: 4.615 | O13: 9.788 | P13: 15.067 | Q13: =R13 -> 16.457 | R13: 16.457 | S13: 6.013 | T13: 11.075 | U13: 15.807 | V13: =W13 -> 19.988 | W13: 19.988 | X13: 5.847 | Y13: 10.488 | Z13: 15.135 | AA13: =AB13 -> 19.373 | AB13: 19.373 | AC13: 5.507 | AD13: 10.617 | AE13: 15.533 | AF13: =AG13 -> 21.35 | AG13: 21.35 | AH13: 5.444 | AI13: 10.935 | AJ13: 16.329 | AK13: =AL13 -> 22.988 | AL13: 22.988 | AM13: 5.518 | AN13: 11.607 | AO13: 17.22 | AP13: =AQ13 -> 24.426 | AQ13: 24.426 | AR13: 5.902 | AS13: 12.227 | AT13: 18.85 | AU13: =AV13 -> 25.781 | AV13: 25.781
B14: Loss from investments in unconsolidated affiliates | V14: =W14 -> 4.754 | W14: 4.754 | X14: 1.45 | Y14: 3.094 | Z14: 13.439 | AA14: =AB14 -> -39.233 | AB14: -39.233 | AF14: =AG14 -> 0 | AK14: =AL14 -> 0 | AP14: =AQ14 -> 0 | AU14: =AV14 -> 0
B15: Tax impact of stock options exercised, net of cancellations | C15: 8.906 | D15: 4.34 | E15: 7.838 | F15: 11.647 | G15: =H15 -> 12.501 | H15: 12.501 | I15: 5.94 | J15: 6.559 | K15: 8.45 | L15: =M15 -> 13.722 | M15: 13.722 | Q15: =R15 -> 0 | R15: 0 | V15: =W15 -> 0 | AA15: =AB15 -> 0 | AF15: =AG15 -> 0 | AK15: =AL15 -> 0 | AP15: =AQ15 -> 0 | AU15: =AV15 -> 0
B16: Excess tax benefit related to stock options exercised | C16: -8.861 | D16: -4.317 | E16: -7.826 | F16: -11.66 | G16: =H16 -> -12.309 | H16: -12.309 | I16: -6.034 | J16: -6.635 | K16: -8.521 | L16: =M16 -> -13.861 | M16: -13.861 | Q16: =R16 -> 0 | R16: 0 | V16: =W16 -> 0 | AA16: =AB16 -> 0 | AF16: =AG16 -> 0 | AK16: =AL16 -> 0 | AP16: =AQ16 -> 0 | AU16: =AV16 -> 0
B17: Other | C17: 2.059 | D17: 0.814 | E17: 1.346 | F17: 2.072 | G17: =H17 -> 2.615 | H17: 2.615 | I17: 0.834 | J17: 1.342 | K17: 2.945 | L17: =M17 -> 3.592 | M17: 3.592 | Q17: =R17 -> 0 | R17: 0 | V17: =W17 -> 0 | AA17: =AB17 -> 0 | AF17: =AG17 -> 0 | AK17: =AL17 -> 0 | AP17: =AQ17 -> 0 | AU17: =AV17 -> 0
B18: Cash Flow from Operations without Working Capital | C18: =SUM(C9:C17) -> 203.481 | D18: =SUM(D9:D17) -> 56.383 | E18: =SUM(E9:E17) -> 117.663 | F18: =SUM(F9:F17) -> 176.269 | G18: =SUM(G9:G17) -> 232.141 | H18: =SUM(H9:H17) -> 232.141 | I18: =SUM(I9:I17) -> 64.504 | J18: =SUM(J9:J17) -> 129.247 | ... AV18: =SUM(AV9:AV17) -> 231.551
B19: Accounts and other receivable | C19: -11.946 | D19: 35.162 | E19: 35.273 | F19: 31.627 | G19: -9.32 | H19: -9.32 | I19: 43.15 | J19: 45.199 | K19: 42.102 | L19: 6.593 | M19: 6.593 | N19: 35.436 | O19: 31.455 | P19: 33.132 | Q19: -7.188 | R19: -7.188 | S19: 44.594 | T19: 37.75 | U19: 35.747 | V19: 3.68 | W19: 3.68 | X19: 43.295 | Y19: 43.123 | Z19: 40.634 | AA19: =AB19 -> 3.777 | AB19: 3.777 | AC19: 38.312 | AD19: 41.404 | AE19: 40.46 | AF19: =AG19 -> 15.148 | AG19: 15.148 | AH19: 15.517 | AI19: 17.048 | AJ19: 8.121 | AK19: =AL19 -> -24.816 | AL19: -24.816 | AM19: 34.287 | AN19: 23.781 | AO19: 23.835 | AP19: =AQ19 -> -12.266 | AQ19: -12.266 | AR19: 38.013 | AS19: 31.74 | AT19: 32.107 | AU19: =AV19 -> -0.098 | AV19: -0.098
B20: Income taxes receivable/payable | C20: -12.854 | D20: 4.6 | E20: 11.466 | F20: 1.352 | G20: =H20 -> -1.356 | H20: -1.356 | I20: 2.718 | J20: 14.398 | K20: 18.28 | L20: =M20 -> 21.837 | M20: 21.837 | N20: 3.164 | O20: -6.497 | P20: -7.337 | Q20: =R20 -> -17.315 | R20: -17.315 | S20: 13.668 | T20: 12.583 | U20: 11.832 | V20: =W20 -> 15.729 | W20: 15.729 | X20: -0.681 | Y20: -3.095 | Z20: -9.127 | AA20: =AB20 -> -5.338 | AB20: -5.338 | AC20: -44.553 | AD20: -74.387 | AE20: -40.977 | AF20: =AG20 -> -32.263 | AG20: -32.263 | AH20: 1.916 | AI20: 1.106 | AJ20: -3.749 | AK20: =AL20 -> 0.715 | AL20: 0.715 | AM20: -0.72 | AN20: -3.618 | AO20: 12.481 | AP20: =AQ20 -> 14.651 | AQ20: 14.651 | AR20: -0.118 | AS20: -1.216 | AT20: -2.401 | AU20: =AV20 -> 0.852 | AV20: 0.852
B21: Inventories | C21: 2.223 | D21: 0.73 | E21: -3.211 | F21: -3.487 | G21: =H21 -> -0.755 | H21: -0.755 | I21: -1.533 | J21: -0.561 | K21: -1.531 | L21: =M21 -> -0.916 | M21: -0.916 | N21: -3.615 | O21: -5.32 | P21: -9.269 | Q21: =R21 -> -7.634 | R21: -7.634 | S21: 1.601 | T21: 7.865 | U21: 2.789 | V21: =W21 -> 3.667 | W21: 3.667 | X21: -3.142 | Y21: -7.122 | Z21: -8.89 | AA21: =AB21 -> -5.766 | AB21: -5.766 | AC21: -0.605 | AD21: 6.709 | AE21: 9.495 | AF21: =AG21 -> 7.921 | AG21: 7.921 | AH21: 0.408 | AI21: -2.504 | AJ21: -3.907 | AK21: =AL21 -> -3.478 | AL21: -3.478 | AM21: -3.839 | AN21: -9.447 | AO21: -19.442 | AP21: =AQ21 -> -12.725 | AQ21: -12.725 | AR21: -3.428 | AS21: -5.306 | AT21: -3.113 | AU21: =AV21 -> -2.092 | AV21: -2.092
B22: Prepaid expenses | C22: 4.362 | D22: -8.346 | E22: -8.389 | F22: -5.847 | G22: =H22 -> -3.743 | H22: -3.743 | I22: 1.339 | J22: 4.152 | K22: 5.639 | L22: =M22 -> -10.462 | M22: -10.462 | N22: -0.147 | O22: 1.519 | P22: 3.917 | Q22: =R22 -> -5.227 | R22: -5.227 | S22: 3.63 | T22: 4.717 | U22: 10.163 | V22: =W22 -> 6.262 | W22: 6.262 | X22: -10.621 | Y22: -3.372 | Z22: -2.746 | AA22: =AB22 -> -4.133 | AB22: -4.133 | AC22: 1.452 | AD22: 7.6 | AE22: 11.695 | AF22: =AG22 -> 8.563 | AG22: 8.563 | AH22: 4.584 | AI22: 3.274 | AJ22: 5.596 | AK22: =AL22 -> -1.137 | AL22: -1.137 | AM22: 2.707 | AN22: 3.071 | AO22: 5.487 | AP22: =AQ22 -> -11.96 | AQ22: -11.96 | AR22: 0.014 | AS22: -4.24 | AT22: -7.159 | AU22: =AV22 -> -14.694 | AV22: -14.694
B23: Operating lease assets/liabilities | X23: 1.13 | Y23: -5.504 | Z23: -5.234 | AA23: =AB23 -> 5.019 | AB23: 5.019 | AC23: 1.851 | AD23: 12.895 | AE23: 17.465 | AF23: =AG23 -> 22.958 | AG23: 22.958 | AH23: -2.684 | AI23: -3.883 | AJ23: -4.386 | AK23: =AL23 -> -4.106 | AL23: -4.106 | AM23: -2.852 | AN23: -9.813 | AO23: -13.758 | AP23: =AQ23 -> -18.404 | AQ23: -18.404 | AR23: -3.777 | AS23: -12.218 | AT23: -18.572 | AU23: =AV23 -> -27.113 | AV23: -27.113
B24: Other assets | C24: -3.645 | D24: -1.847 | E24: -6.01 | F24: -4.537 | G24: =H24 -> -5.799 | H24: -5.799 | I24: -0.619 | J24: -1.071 | K24: -2.201 | L24: =M24 -> -2.818 | M24: -2.818 | N24: -2.65 | O24: -4.28 | P24: -6.045 | Q24: =R24 -> -9.034 | R24: -9.034 | S24: 1.276 | T24: 1.089 | U24: 2.965 | V24: =W24 -> 7.406 | W24: 7.406 | X24: -5.896 | Y24: -7.984 | Z24: -8.985 | AA24: =AB24 -> -11.989 | AB24: -11.989 | AC24: 13.279 | AD24: 4.294 | AE24: 0.54 | AF24: =AG24 -> -6.019 | AG24: -6.019 | AH24: -2.113 | AI24: -6.612 | AJ24: -5.682 | AK24: =AL24 -> -9.227 | AL24: -9.227 | AM24: 4.049 | AN24: 14.992 | AO24: 18.447 | AP24: =AQ24 -> 13.739 | AQ24: 13.739 | AR24: -3.592 | AS24: -7.107 | AT24: -6.086 | AU24: =AV24 -> -14.504 | AV24: -14.504
B25: Accounts payable | C25: 18.18 | D25: -1.334 | E25: -8.562 | F25: -14.858 | G25: =H25 -> -12.931 | H25: -12.931 | I25: -0.509 | J25: -5.992 | K25: -4.526 | L25: =M25 -> 0.752 | M25: 0.752 | N25: -3.56 | O25: 3.767 | P25: -2.042 | Q25: =R25 -> 3.771 | R25: 3.771 | S25: -3.645 | T25: -4.839 | U25: -8.392 | V25: =W25 -> 5.601 | W25: 5.601 | X25: -11.623 | Y25: -13.417 | Z25: -15.654 | AA25: =AB25 -> 2.326 | AB25: 2.326 | AC25: -3.464 | AD25: 0.226 | AE25: 3.101 | AF25: =AG25 -> -2.005 | AG25: -2.005 | AH25: -1.588 | AI25: -3.072 | AJ25: -3.771 | AK25: =AL25 -> -3.678 | AL25: -3.678 | AM25: 12.106 | AN25: 8.937 | AO25: 11.177 | AP25: =AQ25 -> 17.586 | AQ25: 17.586 | AR25: -4.543 | AS25: 0.627 | AT25: -10.985 | AU25: =AV25 -> 3.971 | AV25: 3.971
B26: Gift card liabilities | X26: -26.594 | Y26: -29.98 | Z26: -36.774 | AA26: =AB26 -> 9.695 | AB26: 9.695 | AC26: -26.753 | AD26: -25.731 | AE26: -32.488 | AF26: =AG26 -> -3.324 | AG26: -3.324 | AH26: -18.48 | AI26: -15.562 | AJ26: -23.143 | AK26: =AL26 -> 26.527 | AL26: 26.527 | AM26: -25.674 | AN26: -28.887 | AO26: -36.448 | AP26: =AQ26 -> 8.634 | AQ26: 8.634 | AR26: -27.902 | AS26: -32.328 | AT26: -39.608 | AU26: =AV26 -> 3.104 | AV26: 3.104
B27: Other accrued expenses | C27: 39.848 | D27: -20 | E27: -17.264 | F27: -19.433 | G27: =H27 -> 37.186 | H27: 37.186 | I27: -32.742 | J27: -33.586 | K27: -32.52 | L27: =M27 -> 35.995 | M27: 35.995 | N27: -47.35 | O27: -39.948 | P27: -44.989 | Q27: =R27 -> 29.439 | R27: 29.439 | S27: -43.382 | T27: -35.101 | U27: -46.929 | V27: =W27 -> 18.316 | W27: 18.316 | X27: -9.787 | Y27: -5.688 | Z27: -5.898 | AA27: =AB27 -> 15.578 | AB27: 15.578 | AC27: -85.745 | AD27: -55.477 | AE27: -48.317 | AF27: =AG27 -> -8.309 | AG27: -8.309 | AH27: -6.159 | AI27: 50.397 | AJ27: 1.517 | AK27: =AL27 -> 50.103 | AL27: 50.103 | AM27: -40.756 | AN27: -16.567 | AO27: -30.904 | AP27: =AQ27 -> -9.939 | AQ27: -9.939 | AR27: 10.283 | AS27: 0.624 | AT27: 28.859 | AU27: =AV27 -> 37.424 | AV27: 37.424
B28: Lease terminations | G28: =H28 -> 0 | L28: =M28 -> 0 | Q28: =R28 -> 0 | V28: =W28 -> 0 | AA28: =AB28 -> 0 | AF28: =AG28 -> 0 | AK28: =AL28 -> 0 | AP28: =AQ28 -> 0 | AU28: =AV28 -> 0
B29: Realized loss on derivative financial instruments | G29: =H29 -> 0 | L29: =M29 -> 0 | Q29: =R29 -> 0 | V29: =W29 -> 0 | AA29: =AB29 -> 0 | AF29: =AG29 -> 0 | AK29: =AL29 -> 0 | AP29: =AQ29 -> 0 | AU29: =AV29 -> 0
B30: Net Cash Flow from Operations | C30: =SUM(C18:C29) -> 239.649 | D30: =SUM(D18:D29) -> 65.348 | E30: =SUM(E18:E29) -> 120.966 | F30: =SUM(F18:F29) -> 161.086 | G30: =SUM(G18:G29) -> 235.423 | H30: =SUM(H18:H29) -> 235.423 | I30: =SUM(I18:I29) -> 76.308 | J30: =SUM(J18:J29) -> 151.786 | ... AV30: =SUM(AV18:AV29) -> 218.401
B32: Cash Flow from Investing
B33: Additions to property and equipment | C33: -113.982 | D33: -24.151 | E33: -59.473 | F33: -108.593 | G33: =H33 -> -153.941 | H33: -153.941 | I33: -22.441 | J33: -40.208 | K33: -70.607 | L33: =M33 -> -115.821 | M33: -115.821 | N33: -19.223 | O33: -43.699 | P33: -73.417 | Q33: =R33 -> -120.779 | R33: -120.779 | S33: -30.688 | T33: -51.87 | U33: -78.716 | V33: =W33 -> -102.909 | W33: -102.909 | X33: -13.351 | Y33: -29.371 | Z33: -46.702 | AA33: =AB33 -> -73.765 | AB33: -73.765 | AC33: -15.775 | AD33: -29.424 | AE33: -38.27 | AF33: =AG33 -> -50.329 | AG33: -50.329 | AH33: -7.227 | AI33: -30.902 | AJ33: -49.158 | AK33: =AL33 -> -66.943 | AL33: -66.943 | AM33: -29.093 | AN33: -46.382 | AO33: -78.053 | AP33: =AQ33 -> -112.464 | AQ33: -112.464 | AR33: -37.962 | AS33: -62.66 | AT33: -99.923 | AU33: =AV33 -> -151.565 | AV33: -151.565
B34: Additions to intangible assets | C34: -1.879 | D34: -0.547 | E34: -0.948 | F34: -1.276 | G34: =H34 -> -1.76 | H34: -1.76 | I34: -0.62 | J34: -0.924 | K34: -1.294 | L34: =M34 -> -1.64 | M34: -1.64 | N34: -0.302 | O34: -0.619 | P34: -0.903 | Q34: =R34 -> -1.654 | R34: -1.654 | S34: -0.307 | T34: -0.735 | U34: -2.677 | V34: =W34 -> -3.02 | W34: -3.02 | X34: -0.096 | Y34: -0.198 | Z34: -0.353 | AA34: =AB34 -> -2.1 | AB34: -2.1 | AC34: -0.128 | AD34: -0.227 | AE34: -0.365 | AF34: =AG34 -> -0.585 | AG34: -0.585 | AH34: -0.48 | AI34: -0.312 | AJ34: -0.482 | AK34: =AL34 -> -0.606 | AL34: -0.606 | AM34: -0.139 | AN34: -0.282 | AO34: -0.489 | AP34: =AQ34 -> -0.68 | AQ34: -0.68 | AR34: -0.182 | AS34: -0.392 | AT34: -0.567 | AU34: =AV34 -> -1.658 | AV34: -1.658
B35: Investments in unconsolidated affiliates | G35: =H35 -> 0 | L35: =M35 -> -42 | M35: -42 | N35: -0.088 | O35: -9 | P35: -9 | Q35: =R35 -> -18 | R35: -18 | S35: 0 | T35: -14 | U35: -25 | V35: =W35 -> -25 | W35: -25 | X35: -3 | Y35: -3 | Z35: -3 | AA35: =0+(AB35) -> -3 | AB35: -3 | AF35: =AG35 -> 0 | AK35: =AL35 -> 0 | AP35: =AQ35 -> 0 | AU35: =AV35 -> 0
B36: Loans made to unconsolidated affiliates | X36: -11 | Y36: -18 | Z36: -22.5 | AA36: =0+(AB36) -> -22.5 | AB36: -22.5 | AF36: =AG36 -> 0 | AK36: =AL36 -> 0 | AP36: =AQ36 -> 0 | AU36: =AV36 -> 0
B37: Sales of available-for-sale securities | G37: =H37 -> 0 | L37: =M37 -> 0 | Q37: =R37 -> 0 | V37: =W37 -> 0 | AA37: =AB37 -> 0 | AF37: =AG37 -> 0 | AK37: =AL37 -> 0 | AP37: =AQ37 -> 0 | AU37: =AV37 -> 0
B38: Proceeds from variable life insurance contract | T38: 0.54 | U38: 0.54 | V38: =W38 -> 0.54 | W38: 0.54 | AF38: =AG38 -> 0 | AK38: =AL38 -> 0 | AP38: =AQ38 -> 0 | AU38: =AV38 -> 0
B39: Acquisitions | G39: =H39 -> 0 | L39: =M39 -> 0 | Q39: =R39 -> 0 | V39: =W39 -> 0 | AA39: =AB39 -> -261.695 | AB39: -261.695 | AF39: =AG39 -> 0 | AK39: =AL39 -> 0 | AP39: =AQ39 -> 0 | AU39: =AV39 -> 0
B40: Divestitures | G40: =H40 -> 0 | L40: =M40 -> 0 | Q40: =R40 -> 0 | V40: =W40 -> 0 | AA40: =AB40 -> 0 | AF40: =AG40 -> 0 | AK40: =AL40 -> 0 | AP40: =AQ40 -> 0 | AU40: =AV40 -> 0
B41: Other | AH41: -1 | AI41: -1 | AJ41: -1.283 | AK41: =AL41 -> -1.061 | AL41: -1.061 | AM41: 0.6 | AN41: 0.646 | AO41: 0.485 | AP41: =AQ41 -> 0.329 | AQ41: 0.329 | AR41: -0.018 | AS41: -0.156 | AT41: -0.158 | AU41: =AV41 -> -0.274 | AV41: -0.274
B42: Net Cash Flow from Investing | C42: =SUM(C33:C41) -> -115.861 | D42: =SUM(D33:D41) -> -24.698 | E42: =SUM(E33:E41) -> -60.421 | F42: =SUM(F33:F41) -> -109.869 | G42: =SUM(G33:G41) -> -155.701 | H42: =SUM(H33:H41) -> -155.701 | I42: =SUM(I33:I41) -> -23.061 | J42: =SUM(J33:J41) -> -41.132 | ... AV42: =SUM(AV33:AV41) -> -153.497
B44: Cash Flow from Financing
B45: Acquisition-related deferred consideration | AF45: =AG45 -> -17.25 | AG45: -17.25 | AK45: =AL45 -> -17 | AL45: -17 | AM45: -7.187 | AN45: -7.187 | AO45: -7.187 | AP45: =AQ45 -> -18.316 | AQ45: -18.316 | AS45: -12.994 | AT45: -24.243 | AU45: =AV45 -> -24.243 | AV45: -24.243
B46: Deemed landlord financing proceeds | C46: 14.143 | F46: 3.774 | G46: =H46 -> 14.266 | H46: 14.266 | J46: 2.673 | K46: 2.673 | L46: =M46 -> 17.246 | M46: 17.246 | P46: 3.216 | Q46: =R46 -> 12.128 | R46: 12.128 | S46: 3.61 | T46: 3.631 | U46: 19.156 | V46: =W46 -> 21.788 | W46: 21.788 | AA46: =AB46 -> 0 | AF46: =AG46 -> 0 | AK46: =AL46 -> 0 | AP46: =AQ46 -> 0 | AU46: =AV46 -> 0
B47: Deemed landlord financing payments | C47: -2.65 | D47: -0.743 | E47: -1.497 | F47: -2.278 | G47: =H47 -> -3.118 | H47: -3.118 | I47: -0.873 | J47: -1.78 | K47: -2.705 | L47: =M47 -> -3.721 | M47: -3.721 | N47: -1.056 | O47: -2.124 | P47: -3.214 | Q47: =R47 -> -4.391 | R47: -4.391 | S47: -1.251 | T47: -2.509 | U47: -3.799 | V47: =W47 -> -5.128 | W47: -5.128 | AA47: =AB47 -> 0 | AF47: =AG47 -> 0 | AK47: =AL47 -> 0 | AP47: =AQ47 -> 0 | AU47: =AV47 -> 0
B48: Borrowings on credit facility | C48: 25 | D48: 25 | E48: 25 | F48: 25 | G48: =H48 -> 60 | H48: 60 | L48: =M48 -> 35 | M48: 35 | P48: 30 | Q48: =R48 -> 85 | R48: 85 | S48: 30 | T48: 30 | U48: 45 | V48: =W48 -> 70 | W48: 70 | X48: 20 | Y48: 35 | Z48: 335 | AA48: =AB48 -> 335 | AB48: 335 | AC48: 90 | AD48: 90 | AE48: 90 | AF48: =AG48 -> 90 | AG48: 90 | AK48: =AL48 -> 0 | AP48: =AQ48 -> 130 | AQ48: 130 | AU48: =AV48 -> 15 | AV48: 15
B49: Repayments on credit facility | C49: -25 | F49: -25 | G49: =H49 -> -60 | H49: -60 | L49: =M49 -> -35 | M49: -35 | Q49: =R49 -> -75 | R49: -75 | S49: -10 | T49: -20 | U49: -35 | V49: =W49 -> -70 | W49: -70 | X49: -10 | Y49: -10 | Z49: -10 | AA49: =AB49 -> -55 | AB49: -55 | AD49: -4 | AE49: -4 | AF49: =AG49 -> -100 | AG49: -100 | AI49: -150 | AJ49: -150 | AK49: =AL49 -> -150 | AL49: -150 | AP49: =AQ49 -> -130 | AQ49: -130 | AU49: =AV49 -> -15 | AV49: -15
B50: Convertible debt issuance | AI50: 345 | AJ50: 345 | AK50: =AL50 -> 345 | AL50: 345 | AP50: =AQ50 -> 0 | AU50: =AV50 -> 0
B51: Convertible debt direct and incremental costs | AI51: -10.074 | AJ51: -10.074 | AK51: =AL51 -> -10.074 | AL51: -10.074 | AP51: =AQ51 -> 0 | AU51: =AV51 -> 0
B52: Proceeds from exercise of stock options | C52: 22.94 | D52: 5.669 | E52: 16.892 | F52: 25.448 | G52: =H52 -> 27.997 | H52: 27.997 | I52: 11.645 | J52: 13.795 | K52: 18.923 | L52: =M52 -> 28.378 | M52: 28.378 | N52: 5.368 | O52: 7.709 | P52: 8.1 | Q52: =R52 -> 9.036 | R52: 9.036 | S52: 0.54 | T52: 6.317 | U52: 7.337 | V52: =W52 -> 8.576 | W52: 8.576 | X52: 5.541 | Y52: 6.191 | Z52: 6.516 | AA52: =AB52 -> 7.724 | AB52: 7.724 | AC52: 0.113 | AD52: 0.113 | AE52: 0.113 | AF52: =AG52 -> 0.611 | AG52: 0.611 | AH52: 20.423 | AI52: 24.785 | AJ52: 24.785 | AK52: =AL52 -> 24.786 | AL52: 24.786 | AM52: 0.083 | AN52: 0.083 | AO52: 0.084 | AP52: =AQ52 -> 0.084 | AQ52: 0.084 | AU52: =AV52 -> 0
B53: Excess tax benefit related to stock options exercised | C53: 8.861 | D53: 4.317 | E53: 7.826 | F53: 11.66 | G53: =H53 -> 12.309 | H53: 12.309 | I53: 6.034 | J53: 6.635 | K53: 8.521 | L53: =M53 -> 13.861 | M53: 13.861 | Q53: =R53 -> 0 | R53: 0 | V53: =W53 -> 0 | AA53: =AB53 -> 0 | AF53: =AG53 -> 0 | AK53: =AL53 -> 0 | AP53: =AQ53 -> 0 | AU53: =AV53 -> 0
B54: Repayment of credit facility | G54: =H54 -> 0 | L54: =M54 -> 0 | Q54: =R54 -> 0 | V54: =W54 -> 0 | AA54: =AB54 -> 0 | AF54: =AG54 -> 0 | AK54: =AL54 -> 0 | AP54: =AQ54 -> 0 | AU54: =AV54 -> 0
B55: Cash dividends paid | C55: -30.332 | D55: -8.443 | E55: -16.438 | F55: -26.207 | G55: =H55 -> -35.969 | H55: -35.969 | I55: -9.939 | J55: -19.583 | K55: -31.049 | L55: =M55 -> -42.371 | M55: -42.371 | N55: -11.685 | O55: -23.177 | P55: -36.632 | Q55: =R55 -> -49.889 | R55: -49.889 | S55: -13.168 | T55: -26.521 | U55: -41.449 | V55: =W55 -> -56.251 | W55: -56.251 | X55: -14.628 | Y55: -29.287 | Z55: -44.99 | AA55: =AB55 -> -60.722 | AB55: -60.722 | AC55: -15.791 | AD55: -15.791 | AE55: -15.791 | AF55: =AG55 -> -15.791 | AG55: -15.791 | AH55: -2.179 | AI55: -0.337 | AJ55: -0.337 | AK55: =AL55 -> -0.337 | AL55: -0.337 | AN55: -14.288 | AO55: -28.35 | AP55: =AQ55 -> -42.272 | AQ55: -42.272 | AR55: -13.182 | AS55: -26.998 | AT55: -40.126 | AU55: =AV55 -> -53.207 | AV55: -53.207
B56: Preferred stock issuance | AD56: 200 | AE56: 200 | AF56: =AG56 -> 200 | AG56: 200 | AK56: =AL56 -> 0 | AP56: =AQ56 -> 0 | AU56: =AV56 -> 0
B57: Preferred stock direct costs | AD57: -10.257 | AE57: -10.257 | AF57: =AG57 -> -10.257 | AG57: -10.257 | AK57: =AL57 -> 0 | AP57: =AQ57 -> 0 | AU57: =AV57 -> 0
B58: Preferred stock cash-settled conversion | AI58: -443.751 | AJ58: -443.751 | AK58: =AL58 -> -443.751 | AL58: -443.751 | AP58: =AQ58 -> 0 | AU58: =AV58 -> 0
B59: Preferred stock conversion direct and incremental costs | AI59: -0.074 | AJ59: -0.074 | AK59: =AL59 -> -0.074 | AL59: -0.074 | AP59: =AQ59 -> 0 | AU59: =AV59 -> 0
B60: Preferred stock dividends paid | AI60: -18.661 | AJ60: -18.661 | AK60: =AL60 -> -18.661 | AL60: -18.661 | AP60: =AQ60 -> 0 | AU60: =AV60 -> 0
B61: Common stock issuance | AI61: 175 | AJ61: 175 | AK61: =AL61 -> 175 | AL61: 175 | AP61: =AQ61 -> 0 | AU61: =AV61 -> 0
B62: Common stock issuance direct and incremental costs | AI62: -7.95 | AJ62: -7.95 | AK62: =AL62 -> -7.95 | AL62: -7.95 | AP62: =AQ62 -> 0 | AU62: =AV62 -> 0
B63: Treasury stock purchases | C63: -140.483 | D63: -80.389 | E63: -84.197 | F63: -92.025 | G63: =H63 -> -109.371 | H63: -109.371 | I63: -50.046 | J63: -76.63 | K63: -119.001 | L63: =M63 -> -146.467 | M63: -146.467 | N63: -9.291 | O63: -30.554 | P63: -106.38 | Q63: =R63 -> -122.975 | R63: -122.975 | S63: -34.903 | T63: -42.029 | U63: -60.893 | V63: =W63 -> -109.276 | W63: -109.276 | X63: -11.071 | Y63: -39.164 | Z63: -50.561 | AA63: =AB63 -> -50.982 | AB63: -50.982 | AC63: -2.586 | AD63: -2.852 | AE63: -3.242 | AF63: =AG63 -> -3.621 | AG63: -3.621 | AH63: -3.957 | AI63: -4.56 | AJ63: -5.241 | AK63: =AL63 -> -5.766 | AL63: -5.766 | AM63: -3.938 | AN63: -14.817 | AO63: -41.496 | AP63: =AQ63 -> -63.132 | AQ63: -63.132 | AR63: -12.376 | AS63: -21.695 | AT63: -36.26 | AU63: =AV63 -> -46.085 | AV63: -46.085
B64: Payment for future treasury stock purchases under accelerated stock repurchase agreement | D64: -4.601 | E64: -4.601 | G64: =H64 -> 0 | L64: =M64 -> 0 | Q64: =R64 -> 0 | V64: =W64 -> 0 | AA64: =AB64 -> 0 | AF64: =AG64 -> 0 | AK64: =AL64 -> 0 | AP64: =AQ64 -> 0 | AU64: =AV64 -> 0
B65: Net Cash Flow from Financing | C65: =SUM(C45:C64) -> -127.521 | D65: =SUM(D45:D64) -> -59.19 | E65: =SUM(E45:E64) -> -57.015 | F65: =SUM(F45:F64) -> -79.628 | G65: =SUM(G45:G64) -> -93.886 | H65: =SUM(H45:H64) -> -93.886 | I65: =SUM(I45:I64) -> -43.179 | J65: =SUM(J45:J64) -> -74.89 | ... AV65: =SUM(AV45:AV64) -> -123.535
B67: Foreign Exchange Adjustments | G67: =H67 -> 0 | L67: =M67 -> 0 | P67: -0.024 | Q67: =R67 -> -0.103 | R67: -0.103 | S67: 0.017 | T67: -0.011 | U67: 0.026 | V67: =W67 -> -0.065 | W67: -0.065 | X67: 0.04 | Y67: 0.086 | Z67: 0.057 | AA67: =AB67 -> 0.117 | AB67: 0.117 | AC67: -0.246 | AD67: -0.139 | AE67: -0.1 | AF67: =AG67 -> -0.017 | AG67: -0.017 | AH67: 0.038 | AI67: 0.081 | AJ67: 0.011 | AK67: =AL67 -> -0.027 | AL67: -0.027 | AM67: 0.091 | AN67: -0.026 | AO67: -0.361 | AP67: =AQ67 -> -0.325 | AQ67: -0.325 | AR67: 0.072 | AS67: 0.159 | AT67: -0.059 | AU67: =AV67 -> 0.144 | AV67: 0.144
B68: Net Change in Cash | C68: =C65+C42+C30+C67 -> -3.733 | D68: =D65+D42+D30+D67 -> -18.54 | E68: =E65+E42+E30+E67 -> 3.53 | F68: =F65+F42+F30+F67 -> -28.411 | G68: =G65+G42+G30+G67 -> -14.164 | H68: =H65+H42+H30+H67 -> -14.164 | I68: =I65+I42+I30+I67 -> 10.068 | J68: =J65+J42+J30+J67 -> 35.764 | ... AE68: =AE65+AE42+AE30+AE67 -> 185.352 | AF68: =$AS$627-$AS$626 -> 0 | AG68: =$AT$627-$AT$626 -> 0 | AH68: =AH65+AH42+AH30+AH67 -> 27.26 | AI68: =AI65+AI42+AI30+AI67 -> 7.683 | AJ68: =AJ65+AJ42+AJ30+AJ67 -> -23.055 | AK68: =$AS$627-$AS$626 -> 0 | AL68: =$AT$627-$AT$626 -> 0 | AM68: =$AZ$627-$AZ$626 -> 0 | AN68: =AN65+AN42+AN30+AN67 -> 5.264 | AO68: =AO65+AO42+AO30+AO67 -> -56.47 | AP68: =AP65+AP42+AP30+AP67 -> -74.85 | AQ68: =AQ65+AQ42+AQ30+AQ67 -> -74.85 | AR68: =AR65+AR42+AR30+AR67 -> 1.387 | AS68: =AS65+AS42+AS30+AS67 -> -23.22 | AT68: =AT65+AT42+AT30+AT67 -> -50.79 | AU68: =AU65+AU42+AU30+AU67 -> -58.487 | AV68: =AV65+AV42+AV30+AV67 -> -58.487
B70: Beginning Cash | C70: 61.8 | D70: =C71 -> 58.067 | E70: =D70 -> 58.067 | F70: =E70 -> 58.067 | G70: =F70 -> 58.067 | H70: =G70 -> 58.067 | I70: =H71 -> 43.903 | J70: =I70 -> 43.903 | K70: =J70 -> 43.903 | L70: =K70 -> 43.903 | M70: =L70 -> 43.903 | N70: =M71 -> 53.888 | O70: =N70 -> 53.888 | P70: =O70 -> 53.888 | Q70: =P70 -> 53.888 | R70: =Q70 -> 53.888 | S70: =R71 -> 6.057 | T70: =S70 -> 6.057 | U70: =T70 -> 6.057 | V70: =U70 -> 6.057 | W70: =V70 -> 6.057 | X70: =W71 -> 26.627 | Y70: =X70 -> 26.627 | Z70: =Y70 -> 26.627 | AA70: =Z70 -> 26.627 | AB70: =AA70 -> 26.627 | AC70: =AB71 -> 58.465 | AD70: =AC70 -> 58.465 | AE70: =AD70 -> 58.465 | AF70: =AE70 -> 58.465 | AG70: =AF70 -> 58.465 | AH70: =AG71 -> 0 | AI70: =AH70 -> 0 | AJ70: =AI70 -> 0 | AK70: =AJ70 -> 0 | AL70: =AK70 -> 0 | AM70: =AL71 -> 0 | AN70: =AM70 -> 0 | AO70: =AN70 -> 0 | AP70: =AO70 -> 0 | AQ70: =AP70 -> 0 | AR70: =AQ71 -> -74.85 | AS70: =AR70 -> -74.85 | AT70: =AS70 -> -74.85 | AU70: =AT70 -> -74.85 | AV70: =AU70 -> -74.85
B71: Ending Cash | C71: =C68+C70 -> 58.067 | D71: =D68+D70 -> 39.527 | E71: =E68+E70 -> 61.597 | F71: =F68+F70 -> 29.656 | G71: =G68+G70 -> 43.903 | H71: =H68+H70 -> 43.903 | I71: =I68+I70 -> 53.971 | J71: =J68+J70 -> 79.667 | ... AE71: =AE68+AE70 -> 243.817 | AF71: =AF138 -> 0 | AG71: =AG138 -> 0 | AH71: =AH138 -> 0 | AI71: =AI68+AI70 -> 7.683 | AJ71: =AJ68+AJ70 -> -23.055 | AK71: =AK138 -> 0 | AL71: =AL138 -> 0 | AM71: =AM138 -> 0 | AN71: =AN68+AN70 -> 5.264 | AO71: =AO68+AO70 -> -56.47 | AP71: =AP68+AP70 -> -74.85 | AQ71: =AQ68+AQ70 -> -74.85 | AR71: =AR68+AR70 -> -73.463 | AS71: =AS68+AS70 -> -98.07 | AT71: =AT68+AT70 -> -125.64 | AU71: =AU68+AU70 -> -133.337 | AV71: =AV68+AV70 -> -133.337
B73: Interest paid | C73: 5.43 | D73: 1.455 | E73: 2.988 | F73: 4.418 | G73: =H73 -> 6.057 | H73: 6.057 | I73: 1.483 | J73: 3.055 | K73: 4.719 | L73: =M73 -> 6.038 | M73: 6.038 | N73: 1.627 | O73: 3.375 | P73: 5.155 | Q73: =R73 -> 7.128 | R73: 7.128 | S73: 2.03 | T73: 4.145 | U73: 6.156 | V73: =W73 -> 8.156 | W73: 8.156 | X73: 0.316 | Y73: 0.636 | Z73: 0.854 | AA73: =AB73 -> 1.646 | AB73: 1.646 | AC73: 0.253 | AD73: 7.289 | AE73: 10.347 | AF73: =AG73 -> 13.045 | AG73: 13.045 | AH73: 1.742 | AI73: 6.884 | AJ73: 7.749 | AK73: =AL73 -> 9.586 | AL73: 9.586 | AM73: 1.136 | AN73: 2.726 | AO73: 4.706 | AP73: =AQ73 -> 7.233 | AQ73: 7.233 | AR73: 2.184 | AS73: 5.308 | AT73: 6.386 | AU73: =AV73 -> 9.764 | AV73: 9.764
B74: Income taxes paid | C74: 41.074 | D74: 0.543 | E74: 3.85 | F74: 19.215 | G74: =H74 -> 30.41 | H74: 30.41 | I74: 0.909 | J74: 5.034 | K74: 12.769 | L74: =M74 -> 17.932 | M74: 17.932 | N74: 0.894 | O74: 21.949 | P74: 30.195 | Q74: =R74 -> 31.582 | R74: 31.582 | S74: 0.61 | T74: 5.291 | U74: 8.144 | V74: =W74 -> 10.149 | W74: 10.149 | X74: 0.566 | Y74: 9.939 | Z74: 16.966 | AA74: =AB74 -> 20.778 | AB74: 20.778 | AC74: 0.352 | AD74: 0.423 | AE74: 6.712 | AF74: =AG74 -> 2.968 | AG74: 2.968 | AH74: 0.327 | AI74: 4.877 | AJ74: 9.128 | AK74: =AL74 -> 13.031 | AL74: 13.031 | AM74: 0.465 | AN74: 9.72 | AO74: 13.603 | AP74: =AQ74 -> 14.688 | AQ74: 14.688 | AR74: 0.693 | AS74: 5.175 | AT74: 7.068 | AU74: =AV74 -> 14.473 | AV74: 14.473

Sheet Comps Analysis
B1: Casual Dining Comparables
B2: Company Name | C2: Total Mkt Cap | D2: LTM Net Debt | E2: Total Revenue | F2: EBITDA | G2: Net Debt/EBITDA | H2: TEV/Total Revenue | I2: TEV/EBITDA before excluding operating leases | J2: Price/Diluted EPS Before Extra
B4: The Cheesecake Factory, Inc. (CAKE) | C4: 1749.7 | D4: ='Balance Sheet Link'!AV42 -> 470.047 | E4: 3439.5 | F4: 243.3 | G4: =D4/F4 -> 1.9319647 | H4: 1 | I4: 7.5 | J4: 16.5
B6: Texas Roadhouse, Inc. (TXRH) | C6: 10084.6 | D6: 669.3 | E6: 4631.7 | F6: 507.5 | G6: =D6/F6 -> 1.3188177 | H6: 2.3 | I6: 18.3 | J6: 33.2
B7: Brinker International, Inc. (EAT) | C7: 2002.6 | D7: 2069.6 | E7: 4245.3 | F7: 405.7 | G7: =D7/F7 -> 5.1013064 | H7: 1 | I7: 6.3 | J7: 13.4
B8: Bloomin' Brands, Inc. (BLMN) | C8: 2352.6 | D8: 1986.9 | E8: 4671.5 | F8: 550.3 | G8: =D8/F8 -> 3.610576 | H8: 0.9 | I8: 5.8 | J8: 10.6
B9: Domino's Pizza, Inc. (DPZ) | C9: 16.951.0 | D9: 5095.2 | E9: 4479.4 | F9: 872.1 | G9: =D9/F9 -> 5.8424493 | H9: 4.9 | I9: 23 | J9: 33.2
B10: Darden Restaurants, Inc. (DRI) | C10: 18398 | D10: 6611.8 | E10: 11201.7 | F10: 1724.8 | G10: =D10/F10 -> 3.833372 | H10: 2.2 | I10: 11.7 | J10: 18.1
B11: Cracker Barrel Old Country Store, Inc. (CBRL) | C11: 1134.1 | D11: 1183.7 | E11: 3428.7 | F11: 222.8 | G11: =D11/F11 -> 5.3128366 | H11: 0.7 | I11: 7.4 | J11: 16
B13: Median | C13: =MEDIAN(C6:C11) -> 2352.6 | D13: =MEDIAN(D6:D11) -> 2028.25 | E13: =MEDIAN(E6:E11) -> 4555.55 | F13: =MEDIAN(F6:F11) -> 528.9 | G13: =MEDIAN(G6:G11) -> 4.4673392 | H13: =MEDIAN(H6:H11) -> 1.6 | I13: =MEDIAN(I6:I11) -> 9.55 | J13: =MEDIAN(J6:J11) -> 17.05
B14: Mean | C14: =AVERAGE(C6:C11) -> 6794.38 | D14: =AVERAGE(D6:D11) -> 2936.0833 | E14: =AVERAGE(E6:E11) -> 5443.05 | F14: =AVERAGE(F6:F11) -> 713.86667 | G14: =AVERAGE(G6:G11) -> 4.169893 | H14: =AVERAGE(H6:H11) -> 2 | I14: =AVERAGE(I6:I11) -> 12.083333 | J14: =AVERAGE(J6:J11) -> 20.75
B15: High | C15: =MAX(C6:C11) -> 18398 | D15: =MAX(D6:D11) -> 6611.8 | E15: =MAX(E6:E11) -> 11201.7 | F15: =MAX(F6:F11) -> 1724.8 | G15: =MAX(G6:G11) -> 5.8424493 | H15: =MAX(H6:H11) -> 4.9 | I15: =MAX(I6:I11) -> 23 | J15: =MAX(J6:J11) -> 33.2
B16: Low | C16: =MIN(C6:C11) -> 1134.1 | D16: =MIN(D6:D11) -> 669.3 | E16: =MIN(E6:E11) -> 3428.7 | F16: =MIN(F6:F11) -> 222.8 | G16: =MIN(G6:G11) -> 1.3188177 | H16: =MIN(H6:H11) -> 0.7 | I16: =MIN(I6:I11) -> 5.8 | J16: =MIN(J6:J11) -> 10.6

Sheet Historicals
A2: =CHOOSE(MO.DataSourceIndex,MO.Ticker.Bloomberg,MO.Ticker.CapIQ,MO.Ticker.FactSet,MO.Ticker.Thomson) -> CAKE US | C2: =EOMONTH(C4,-12) -> 39813
A3: =HP.TradeCurrency -> USD | B3: =IF(MO.RealTime="OFF",MO.LastPriceHardcoded,MO.LastPriceFormula) -> 35.48 | C3: 364 | D3: =D4-C4 -> 364 | E3: =E4-D4 -> 371 | F3: =F4-E4 -> 364 | G3: =G4-F4 -> 91 | H3: =H4-G4 -> 91 | I3: =I4-H4 -> 91 | J3: =J4-I4 -> 91 | K3: =K4-F4 -> 364 | L3: =L4-K4 -> 91 | M3: =M4-L4 -> 91 | N3: =N4-M4 -> 91 | O3: =O4-N4 -> 91 | P3: =P4-K4 -> 364 | Q3: =Q4-P4 -> 91 | R3: =R4-Q4 -> 91 | S3: =S4-R4 -> 91 | T3: =T4-S4 -> 91 | U3: =U4-P4 -> 364 | V3: =V4-U4 -> 91 | W3: =W4-V4 -> 91 | X3: =X4-W4 -> 91 | Y3: =Y4-X4 -> 98 | Z3: =Z4-U4 -> 371 | AA3: =AA4-Z4 -> 91 | AB3: =AB4-AA4 -> 91 | AC3: =AC4-AB4 -> 91 | AD3: =AD4-AC4 -> 91 | AE3: =AE4-Z4 -> 364 | AF3: =AF4-AE4 -> 91 | AG3: =AG4-AF4 -> 91 | AH3: =AH4-AG4 -> 91 | AI3: =AI4-AH4 -> 91 | AJ3: =AJ4-AE4 -> 364 | AK3: =AK4-AJ4 -> 91 | AL3: =AL4-AK4 -> 91 | AM3: =AM4-AL4 -> 91 | AN3: =AN4-AM4 -> 91 | AO3: =AO4-AJ4 -> 364 | AP3: =AP4-AO4 -> 91 | AQ3: =AQ4-AP4 -> 91 | AR3: =AR4-AQ4 -> 91 | AS3: =AS4-AR4 -> 91 | AT3: =AT4-AO4 -> 364 | AU3: =AU4-AT4 -> 91 | AV3: =AV4-AU4 -> 91 | AW3: =AW4-AV4 -> 91 | AX3: =AX4-AW4 -> 91 | AY3: =AY4-AT4 -> 364 | AZ3: =AZ4-AY4 -> 91 | BA3: =BA4-AZ4 -> 91 | BB3: =BB4-BA4 -> 91 | BC3: =BC4-BB4 -> 98 | BD3: =BD4-AY4 -> 371 | BE3: =BE4-BD4 -> 90 | BF3: =BF4-BE4 -> 92 | BG3: =BG4-BF4 -> 91 | BH3: =BH4-BG4 -> 91 | BI3: =BI4-BD4 -> 364 | BJ3: 91 | BK3: 91 | BL3: 91 | BM3: 91 | BN3: =BN4-BI4 -> 364 | BO3: 91 | BP3: 91 | BQ3: 91 | BR3: 91 | BS3: =BS4-BN4 -> 364 | BT3: 364 | BU3: 364 | BV3: 371
A4: Bloomberg | B4: =IF(AND(MO.RealTimeStockPriceToggle,MO.LastPriceFormula<>"N/A"),"ON","OFF") -> OFF | C4: 40176 | D4: 40540 | E4: 40911 | F4: 41275 | G4: 41366 | H4: 41457 | I4: 41548 | J4: =K4 -> 41639 | K4: 41639 | L4: 41730 | M4: 41821 | N4: 41912 | O4: =P4 -> 42003 | P4: 42003 | Q4: 42094 | R4: 42185 | S4: 42276 | T4: =U4 -> 42367 | U4: 42367 | V4: 42458 | W4: 42549 | X4: 42640 | Y4: =Z4 -> 42738 | Z4: 42738 | AA4: 42829 | AB4: 42920 | AC4: 43011 | AD4: =AE4 -> 43102 | AE4: 43102 | AF4: 43193 | AG4: 43284 | AH4: 43375 | AI4: =AJ4 -> 43466 | AJ4: 43466 | AK4: 43557 | AL4: 43648 | AM4: 43739 | AN4: =AO4 -> 43830 | AO4: 43830 | AP4: 43921 | AQ4: 44012 | AR4: 44103 | AS4: =AT4 -> 44194 | AT4: 44194 | AU4: 44285 | AV4: 44376 | AW4: 44467 | AX4: =AY4 -> 44558 | AY4: 44558 | AZ4: 44649 | BA4: 44740 | BB4: 44831 | BC4: =BD4 -> 44929 | BD4: 44929 | BE4: 45019 | BF4: 45111 | BG4: 45202 | BH4: =BI4 -> 45293 | BI4: 45293 | BJ4: =BI4+BJ3 -> 45384 | BK4: =BJ4+BK3 -> 45475 | BL4: =BK4+BL3 -> 45566 | BM4: =BL4+BM3 -> 45657 | BN4: =BM4 -> 45657 | BO4: =BN4+BO3 -> 45748 | BP4: =BO4+BP3 -> 45839 | BQ4: =BP4+BQ3 -> 45930 | BR4: =BQ4+BR3 -> 46021 | BS4: =BR4 -> 46021 | BT4: =BS4+BT3 -> 46385 | BU4: =BT4+BU3 -> 46749 | BV4: =BU4+BV3 -> 47120
