Workbook
Name \0: #REF!
Name \i: #REF!
Name \L: #REF!
Name \m: #REF!
Name \R: #REF!
Name \t: #REF!
Name __FDS_HYPERLINK_TOGGLE_STATE__: "ON"
Name __FDS_UNIQUE_RANGE_ID_GENERATOR_COUNTER: 1
Name _1: #REF!
Name _1111_19th_Street: #REF!
Name _14180_Accumulated_Depreciation___Equipment________________Courtyard___Plano__TX______0000: #REF!
Name _14182_Accumulated_Depreciation___Equipment___Capital_Leas_Courtyard___Philadelphia___0000: #REF!
Name _25_0: #REF!
Name _45STEP_UP: #REF!
Name _500_Marquette: #REF!
Name _60_Spear: #REF!
Name _bdm.028285451B4742929125DFB41D546413.edm: #REF!
Name _bdm.16AA9A3EFC28404BA85B049587C880C8.edm: #REF!
Name _bdm.1D26AA9B3391447F9A7D401C2A2957EC.edm: #REF!
Name _bdm.1F34719A23B34845A4C25E45C3DDF83D.edm: #REF!
Name _bdm.22432391224B438D8EFBF7683098DD3E.edm: #REF!
Name _bdm.23D8DF48031241CBB016C38B4F807196.edm: #REF!
Name _bdm.450AC11AD54948929B5DFCF6E68CAEE5.edm: #REF!
Name _bdm.5A8BDDFBFD3842C2ABEA35DD2CA102C7.edm: #REF!
Name _bdm.619D0A075BCE49F3AE2DFCAB7922D2FB.edm: #REF!
Name _bdm.6698C999A3DB4955B72A8DE986E8E059.edm: #REF!
Name _bdm.716E8AC41D7F44889A91B9561AB5E54A.edm: #REF!
Name _bdm.8664FDAB4C71436BBE09980F3B0196AB.edm: #REF!
Name _bdm.8AB906D8C9734F2286D5C9AF62741447.edm: #REF!
Name _bdm.9A173BE4CFF34FAE89F3FA5B0BC17717.edm: #REF!
Name _bdm.A5D1906AC03742F2A1DCEBD455574B86.edm: #REF!
Name _bdm.A9DB6556387A48C986268CFFA66D14C5.edm: #REF!
Name _bdm.B1CD14597A1448FBBAD91ADC116AA817.edm: #REF!
Name _bdm.BD200F3830E14C118FAEF247DA56A648.edm: #REF!
Name _bdm.BE01C6A9B87D4520B2B9A588797491FA.edm: #REF!
Name _bdm.CAF081D66FB74576B10C513AD7F2BD14.edm: #REF!
Name _bdm.CD342BFF8027460E98352C7B8C9343A6.edm: #REF!
Name _bdm.D84D0266F6A548778138E8EDADA2A502.edm: #REF!
Name _bdm.DC24C60BD8804AD3B3B483F23A282A8E.edm: #REF!
Name _bdm.DC5CF1FCF3F649CC85B6C35F227B6EE3.edm: #REF!
Name _bdm.ED95D5371F0B4032AE81D39228F05494.edm: #REF!
Name _bdm.F05EE0B050FD40D196B178505BC36B9D.edm: #REF!
Name _bdm.ToolkitBookmark.1_24_2004_11_15_31_PM.edm: #REF!
Name _bdm.ToolkitBookmark.1_24_2004_8_24_02_PM.edm: #REF!
Name _bdm.ToolkitBookmark.1_24_2004_8_54_41_PM.edm: #REF!
Name _bdm.ToolkitBookmark.1_25_2004_9_47_15_PM.edm: #REF!
Name _bdm.ToolkitBookmark.1_25_2004_9_47_23_PM.edm: #REF!
Name _DCF2: #REF!
Name _DCF22: #REF!
Name _Dev2000: #REF!,#REF!,#REF!,#REF!,#REF!,#REF!
Name _Dev98: #REF!,#REF!,#REF!,#REF!,#REF!,#REF!
Name _FAC05: #REF!
Name _FAC11: #REF!
Name _FAC12: #REF!
Name _FAC14: #REF!
Name _FAC16: #REF!
Name _FAC18: #REF!
Name _FFO1: #REF!
Name _FFO2: #REF!
Name _FFO3: #REF!

Sheet Cover
F28: Northwind Industries - FINANCIAL MODEL
F35: =TODAY() -> 46081

Sheet Historical Financials
B2: Northwind Industries
B3: Historical Financials | J3: Draft - Preliminary & Confidential
B5: $ in millions, except where otherwise denoted
A6: x | B6: Financials | K6: x
A8: x | B8: Income Statement | K8: x
D10: 42004 | E10: =EOMONTH(D10,12) -> 42369 | F10: =EOMONTH(E10,12) -> 42735 | G10: =EOMONTH(F10,12) -> 43100 | H10: =EOMONTH(G10,12) -> 43465 | J10: ="'14A - '18A CAGR" -> '14A - '18A CAGR
D11: =YEAR(D10) -> 2014 | E11: =YEAR(E10) -> 2015 | F11: =YEAR(F10) -> 2016 | G11: =YEAR(G10) -> 2017 | H11: =YEAR(H10) -> 2018
B13: Products Revenue | D13: 236.277 | E13: 148.565 | F13: 134.755 | G13: 211.313 | H13: 238.459 | J13: =RATE($H$11-$D$11,0,-$D13,$H13) -> 0.0023007783
B14: (+) Services Revenue | D14: 298.665 | E14: 208.283 | F14: 243.91 | G14: 301.656 | H14: 314.68 | J14: =RATE($H$11-$D$11,0,-$D14,$H14) -> 0.01314406
B15: Total Revenue | D15: =SUM(D13:D14) -> 534.942 | E15: =SUM(E13:E14) -> 356.848 | F15: =SUM(F13:F14) -> 378.665 | G15: =SUM(G13:G14) -> 512.969 | H15: =SUM(H13:H14) -> 553.139 | J15: =RATE($H$11-$D$11,0,-$D15,$H15) -> 0.0083978146
B16: % Y-O-Y Growth | E16: =E15/D15-1 -> -0.33292207 | F16: =F15/E15-1 -> 0.061138076 | G16: =G15/F15-1 -> 0.35467762 | H16: =H15/G15-1 -> 0.078308826
B18: (–) Product Cost of Goods Sold (COGS) | D18: -141.08299 | E18: -101.54867 | F18: -85.732825 | G18: -140.56916 | H18: -158.4088
B19: (–) Services Cost of Goods Sold (COGS) | D19: -227.01605 | E19: -184.62581 | F19: -185.29518 | G19: -229.76384 | H19: -219.6612
B20: Gross Profit | D20: =SUM(D15,D18:D19) -> 166.84297 | E20: =SUM(E15,E18:E19) -> 70.673517 | F20: =SUM(F15,F18:F19) -> 107.637 | G20: =SUM(G15,G18:G19) -> 142.636 | H20: =SUM(H15,H18:H19) -> 175.069 | J20: =RATE($H$11-$D$11,0,-$D20,$H20) -> 0.012104455
B21: Gross Margin % | D21: =D20/D15 -> 0.31188983 | E21: =E20/E15 -> 0.19804936 | F21: =F20/F15 -> 0.28425389 | G21: =G20/G15 -> 0.27805969 | H21: =H20/H15 -> 0.31650092
B23: (–) Selling, Generative, & Administrative (SG&A) | D23: -49.069 | E23: -43.735 | F23: -47.117 | G23: -49.146 | H23: -44.828
B24: (–) Research & Development (R&D) | D24: -11.049 | E24: -7.431 | F24: -9.075 | G24: -12.512 | H24: -10.457
B25: EBITDA | D25: =SUM(D20,D23:D24) -> 106.72497 | E25: =SUM(E20,E23:E24) -> 19.507517 | F25: =SUM(F20,F23:F24) -> 51.445 | G25: =SUM(G20,G23:G24) -> 80.978 | H25: =SUM(H20,H23:H24) -> 119.784 | J25: =RATE($H$11-$D$11,0,-$D25,$H25) -> 0.029279198
B26: EBITDA Margin % | D26: =D25/D15 -> 0.19950755 | E26: =E25/E15 -> 0.05466618 | F26: =F25/F15 -> 0.13585887 | G26: =G25/G15 -> 0.15786139 | H26: =H25/H15 -> 0.21655316
B28: (–) Depreciation & Amortization (D&A) | D28: -31.877967 | E28: -33.936517 | F28: -36.128 | G28: -38.461 | H28: -42.989
B29: Earnings Before Interest & Taxes (EBIT) | D29: =SUM(D25,D28) -> 74.847 | E29: =SUM(E25,E28) -> -14.429 | F29: =SUM(F25,F28) -> 15.317 | G29: =SUM(G25,G28) -> 42.517 | H29: =SUM(H25,H28) -> 76.795 | J29: =RATE($H$11-$D$11,0,-$D29,$H29) -> 0.0064440501
B30: EBIT Margin % | D30: =D29/D15 -> 0.1399161 | E30: =E29/E15 -> -0.040434583 | F30: =F29/F15 -> 0.040450002 | G30: =G29/G15 -> 0.082884151 | H30: =H29/H15 -> 0.1388349
B32: (–) Interest Expense | D32: -2.5 | E32: =D32-0.4 -> -2.9 | F32: =E32-0.4 -> -3.3 | G32: =F32-0.4 -> -3.7 | H32: =G32-0.4 -> -4.1
B33: Income (Loss) Before Income Taxes | D33: =SUM(D29,D32) -> 72.347 | E33: =SUM(E29,E32) -> -17.329 | F33: =SUM(F29,F32) -> 12.017 | G33: =SUM(G29,G32) -> 38.817 | H33: =SUM(H29,H32) -> 72.695
B34: (–) Income Taxes | D34: -20.849 | E34: 12.34 | F34: -6.777 | G34: -14.276 | H34: -24.781
B35: Net Income | D35: =SUM(D33:D34) -> 51.498 | E35: =SUM(E33:E34) -> -4.989 | F35: =SUM(F33:F34) -> 5.24 | G35: =SUM(G33:G34) -> 24.541 | H35: =SUM(H33:H34) -> 47.914 | J35: =RATE($H$11-$D$11,0,-$D35,$H35) -> -0.017872173
B36: Net Income Margin % | D36: =D35/D15 -> 0.09626838 | E36: =E35/E15 -> -0.013980743 | F36: =F35/F15 -> 0.013838089 | G36: =G35/G15 -> 0.047841098 | H36: =H35/H15 -> 0.086621988
A38: x | B38: Balance Sheet | K38: x
D40: 42004 | E40: =EOMONTH(D40,12) -> 42369 | F40: =EOMONTH(E40,12) -> 42735 | G40: =EOMONTH(F40,12) -> 43100 | H40: =EOMONTH(G40,12) -> 43465
D41: =YEAR(D40) -> 2014 | E41: =YEAR(E40) -> 2015 | F41: =YEAR(F40) -> 2016 | G41: =YEAR(G40) -> 2017 | H41: =YEAR(H40) -> 2018
B43: Assets
B45: Cash and Cash Equivalents | D45: 35.937 | E45: =D45+E114 -> 39.93 | F45: =E45+F114 -> 60.603 | G45: =F45+G114 -> 23.069 | H45: =G45+H114 -> 22.014
B46: Accounts Receivable | D46: 48.573 | E46: 53.97 | F46: 72.971 | G46: 117.711 | H46: 130.769
B47: Inventory | D47: 66.9051 | E47: 74.339 | F47: 59.19 | G47: 111.769 | H47: 124.506
B48: Income Tax Recoverable | D48: 9.8505 | E48: 10.945 | F48: 2.343 | G48: 3.02 | H48: 4.228
B49: Deferred Income Taxes | D49: 12.4524 | E49: 13.836 | F49: 8.11 | G49: 4.909 | H49: 4.367
B50: Prepaid Expenses and Other Assets | D50: 16.812 | E50: 18.68 | F50: 22.768 | G50: 33.326 | H50: 40.331
B51: Total Current Assets | D51: =SUM(D45:D50) -> 190.53 | E51: =SUM(E45:E50) -> 211.7 | F51: =SUM(F45:F50) -> 225.985 | G51: =SUM(G45:G50) -> 293.804 | H51: =SUM(H45:H50) -> 326.215
B53: Net Plant, Property, & Equipment (PP&E) | D53: 178 | E53: 183.025 | F53: 182.686 | G53: 203.068 | H53: 209.933
B54: Goodwill | D54: 29.394 | E54: 29.394 | F54: 29.394 | G54: 32.732 | H54: 32.732
B55: Deferred Income Taxes | D55: 12.6 | E55: 12.986 | F55: 12.69 | G55: 12.416 | H55: 11.792
B56: Intangible and Other Assets | D56: 5.4 | E56: 5.45 | F56: 4.153 | G56: 7.195 | H56: 6.438
B57: Total Assets | D57: =SUM(D51,D53:D56) -> 415.924 | E57: =SUM(E51,E53:E56) -> 442.555 | F57: =SUM(F51,F53:F56) -> 454.908 | G57: =SUM(G51,G53:G56) -> 549.215 | H57: =SUM(H51,H53:H56) -> 587.11
B59: Liabilities & Shareholder's Equity
B61: Accounts Payable | D61: 13 | E61: 15.992 | F61: 23.785 | G61: 57.443 | H61: 43.603
B62: Deferred Revenue | D62: 16 | E62: 14.007 | F62: 11.987 | G62: 25.924 | H62: 10.65
B63: Warranty Reserves | D63: 2.5 | E63: 2.251 | F63: 1.698 | G63: 3.103 | H63: 3.719
B64: Income Taxes Payable | D64: 0 | E64: 0 | F64: 3.433 | G64: 2.336 | H64: 6.894
B65: Accrued and Other Current Liabilities | D65: 23 | E65: 27.075 | F65: 32.289 | G65: 34.069 | H65: 41.572
B66: Total Current Liabilities | D66: =SUM(D61:D65) -> 54.5 | E66: =SUM(E61:E65) -> 59.325 | F66: =SUM(F61:F65) -> 73.192 | G66: =SUM(G61:G65) -> 122.875 | H66: =SUM(H61:H65) -> 106.438
B68: Long-term Debt | D68: 6 | E68: 8.6 | F68: 0 | G68: 6.625 | H68: 0.261
B69: Other Liabilities | D69: 0 | E69: 0 | F69: 1.168 | G69: 2.434 | H69: 2.416
B70: Deferred Tax Liability | D70: 6.7 | E70: 12.471 | F70: 4.879 | G70: 4.474 | H70: 8.487
B71: Total Liabilities | D71: =D66+SUM(D68:D70) -> 67.2 | E71: =E66+SUM(E68:E70) -> 80.396 | F71: =F66+SUM(F68:F70) -> 79.239 | G71: =G66+SUM(G68:G70) -> 136.408 | H71: =H66+SUM(H68:H70) -> 117.602
B73: Shareholder's Equity | D73: 348.724 | E73: 362.159 | F73: 375.669 | G73: 412.807 | H73: 469.508
B74: Total Liabilities & Shareholder's Equity | D74: =SUM(D71,D73) -> 415.924 | E74: =SUM(E71,E73) -> 442.555 | F74: =SUM(F71,F73) -> 454.908 | G74: =SUM(G71,G73) -> 549.215 | H74: =SUM(H71,H73) -> 587.11
B76: Net Working Capital Schedule
B77: Accounts Receivable | D77: =D46 -> 48.573 | E77: =E46 -> 53.97 | F77: =F46 -> 72.971 | G77: =G46 -> 117.711 | H77: =H46 -> 130.769
B78: Inventory | D78: =D47 -> 66.9051 | E78: =E47 -> 74.339 | F78: =F47 -> 59.19 | G78: =G47 -> 111.769 | H78: =H47 -> 124.506
B79: Income Tax Recoverable | D79: =D48 -> 9.8505 | E79: =E48 -> 10.945 | F79: =F48 -> 2.343 | G79: =G48 -> 3.02 | H79: =H48 -> 4.228
B80: Deferred Income Taxes | D80: =D49 -> 12.4524 | E80: =E49 -> 13.836 | F80: =F49 -> 8.11 | G80: =G49 -> 4.909 | H80: =H49 -> 4.367
B81: Prepaid Expenses and Other Assets | D81: =D50 -> 16.812 | E81: =E50 -> 18.68 | F81: =F50 -> 22.768 | G81: =G50 -> 33.326 | H81: =H50 -> 40.331
B82: Current Assets (Excluding Cash) | D82: =SUM(D77:D81) -> 154.593 | E82: =SUM(E77:E81) -> 171.77 | F82: =SUM(F77:F81) -> 165.382 | G82: =SUM(G77:G81) -> 270.735 | H82: =SUM(H77:H81) -> 304.201
B84: Accounts Payable | D84: =D61 -> 13 | E84: =E61 -> 15.992 | F84: =F61 -> 23.785 | G84: =G61 -> 57.443 | H84: =H61 -> 43.603
B85: Deferred Revenue | D85: =D62 -> 16 | E85: =E62 -> 14.007 | F85: =F62 -> 11.987 | G85: =G62 -> 25.924 | H85: =H62 -> 10.65
B86: Warranty Reserves | D86: =D63 -> 2.5 | E86: =E63 -> 2.251 | F86: =F63 -> 1.698 | G86: =G63 -> 3.103 | H86: =H63 -> 3.719
B87: Income Taxes Payable | D87: =D64 -> 0 | E87: =E64 -> 0 | F87: =F64 -> 3.433 | G87: =G64 -> 2.336 | H87: =H64 -> 6.894
B88: Accrued and Other Current Liabilities | D88: =D65 -> 23 | E88: =E65 -> 27.075 | F88: =F65 -> 32.289 | G88: =G65 -> 34.069 | H88: =H65 -> 41.572
B89: Current Liabilities | D89: =SUM(D84:D88) -> 54.5 | E89: =SUM(E84:E88) -> 59.325 | F89: =SUM(F84:F88) -> 73.192 | G89: =SUM(G84:G88) -> 122.875 | H89: =SUM(H84:H88) -> 106.438
B91: Net Working Capital (NWC) | D91: =D82-D89 -> 100.093 | E91: =E82-E89 -> 112.445 | F91: =F82-F89 -> 92.19 | G91: =G82-G89 -> 147.86 | H91: =H82-H89 -> 197.763
B92: Δ NWC | D92: -8.7 | E92: =D91-E91 -> -12.352 | F92: =E91-F91 -> 20.255 | G92: =F91-G91 -> -55.67 | H92: =G91-H91 -> -49.903
A94: x | B94: Cash Flow Statement | K94: x
D96: 42004 | E96: =EOMONTH(D96,12) -> 42369 | F96: =EOMONTH(E96,12) -> 42735 | G96: =EOMONTH(F96,12) -> 43100 | H96: =EOMONTH(G96,12) -> 43465
D97: =YEAR(D96) -> 2014 | E97: =YEAR(E96) -> 2015 | F97: =YEAR(F96) -> 2016 | G97: =YEAR(G96) -> 2017 | H97: =YEAR(H96) -> 2018
B99: Net Income | D99: =D35 -> 51.498 | E99: =E35 -> -4.989 | F99: =F35 -> 5.24 | G99: =G35 -> 24.541 | H99: =H35 -> 47.914
B100: (+) Depreciation & Amortization (D&A) | D100: =-D28 -> 31.877967 | E100: =-E28 -> 33.936517 | F100: =-F28 -> 36.128 | G100: =-G28 -> 38.461 | H100: =-H28 -> 42.989
B101: Funds from Operation (FFO) | D101: =SUM(D99:D100) -> 83.375967 | E101: =SUM(E99:E100) -> 28.947517 | F101: =SUM(F99:F100) -> 41.368 | G101: =SUM(G99:G100) -> 63.002 | H101: =SUM(H99:H100) -> 90.903
B102: (+/–) Change in Net Working Capital | D102: =D92 -> -8.7 | E102: =E92 -> -12.352 | F102: =F92 -> 20.255 | G102: =G92 -> -55.67 | H102: =H92 -> -49.903
B103: Cash Flow from Operations (CFO) | D103: =SUM(D101:D102) -> 74.675967 | E103: =SUM(E101:E102) -> 16.595517 | F103: =SUM(F101:F102) -> 61.623 | G103: =SUM(G101:G102) -> 7.332 | H103: =SUM(H101:H102) -> 41
B105: (–) Capital Expenditures | D105: -52.373218 | E105: -34.937018 | F105: -37.073 | G105: -47.387 | H105: -63.662
B106: (+) Asset Sales | D106: 0 | E106: 19.734501 | F106: 4.723 | G106: 0 | H106: 27.971
B107: Cash Flow from Investing (CFI) | D107: =SUM(D105:D106) -> -52.373218 | E107: =SUM(E105:E106) -> -15.202517 | F107: =SUM(F105:F106) -> -32.35 | G107: =SUM(G105:G106) -> -47.387 | H107: =SUM(H105:H106) -> -35.691
B109: (+/–) Debt Issued / (Retired) | D109: =D68-C68 -> 6 | E109: =E68-D68 -> 2.6 | F109: =F68-E68 -> -8.6 | G109: =G68-F68 -> 6.625 | H109: =H68-G68 -> -6.364
B110: (+/–) Common Stock Issued / (Retired) | D110: 0 | E110: 0 | F110: 0 | G110: 0 | H110: 0
B111: (–) Dividends Paid | D111: 0 | E111: 0 | F111: 0 | G111: -4.104 | H111: 0
B112: Cash Flow from Financing (CFF) | D112: =SUM(D109:D111) -> 6 | E112: =SUM(E109:E111) -> 2.6 | F112: =SUM(F109:F111) -> -8.6 | G112: =SUM(G109:G111) -> 2.521 | H112: =SUM(H109:H111) -> -6.364
B114: Net Change in Cash | D114: =SUM(D103,D107,D112) -> 28.302749 | E114: =SUM(E103,E107,E112) -> 3.993 | F114: =SUM(F103,F107,F112) -> 20.673 | G114: =SUM(G103,G107,G112) -> -37.534 | H114: =SUM(H103,H107,H112) -> -1.055

Sheet Capex & NWC Drivers
B2: Northwind Industries
B3: Capex & NWC Drivers | M3: Draft - Preliminary & Confidential
B5: $ in millions, except where otherwise denoted
A6: x | B6: Capex Drivers | N6: x
B8: Select Case ([=1] Base Case; [=2] Upside Case; [=3] Downside Case) >>> | E8: ='P&L Drivers'!$E$8 -> 1
B10: Operating Scenario >>> | E10: =CHOOSE($E$8,B22,B23,B24) -> Base Case
D12: 42004 | E12: =EOMONTH(D12,12) -> 42369 | F12: =EOMONTH(E12,12) -> 42735 | G12: =EOMONTH(F12,12) -> 43100 | H12: =EOMONTH(G12,12) -> 43465 | I12: =EOMONTH(H12,12) -> 43830 | J12: =EOMONTH(I12,12) -> 44196 | K12: =EOMONTH(J12,12) -> 44561 | L12: =EOMONTH(K12,12) -> 44926 | M12: =EOMONTH(L12,12) -> 45291
D13: =YEAR(D12) -> 2014 | E13: =YEAR(E12) -> 2015 | F13: =YEAR(F12) -> 2016 | G13: =YEAR(G12) -> 2017 | H13: =YEAR(H12) -> 2018 | I13: =YEAR(I12) -> 2019 | J13: =YEAR(J12) -> 2020 | K13: =YEAR(K12) -> 2021 | ... M13: =YEAR(M12) -> 2023
A15: x | B15: Capex: % of Total Revenue | N15: x
B17: Capex | D17: ='Historical Financials'!D105 -> -52.373218 | E17: ='Historical Financials'!E105 -> -34.937018 | F17: ='Historical Financials'!F105 -> -37.073 | G17: ='Historical Financials'!G105 -> -47.387 | H17: ='Historical Financials'!H105 -> -63.662 | I17: =-PRODUCT(I$20,SUM('P&L Drivers'!I17,'P&L Drivers'!I28)) -> -74.902428 | J17: =-PRODUCT(J$20,SUM('P&L Drivers'!J17,'P&L Drivers'!J28)) -> -84.563963 | K17: =-PRODUCT(K$20,SUM('P&L Drivers'!K17,'P&L Drivers'!K28)) -> -95.517345 | L17: =-PRODUCT(L$20,SUM('P&L Drivers'!L17,'P&L Drivers'!L28)) -> -107.94061 | M17: =-PRODUCT(M$20,SUM('P&L Drivers'!M17,'P&L Drivers'!M28)) -> -122.03694
B18: % of Total Revenue | D18: =-D17/'Historical Financials'!D15 -> 0.09790448 | E18: =-E17/'Historical Financials'!E15 -> 0.09790448 | F18: =-F17/'Historical Financials'!F15 -> 0.09790448 | G18: =-G17/'Historical Financials'!G15 -> 0.092377902 | H18: =-H17/'Historical Financials'!H15 -> 0.11509223 | I18: =-I17/SUM('P&L Drivers'!I17,'P&L Drivers'!I28) -> 0.12 | J18: =-J17/SUM('P&L Drivers'!J17,'P&L Drivers'!J28) -> 0.12 | K18: =-K17/SUM('P&L Drivers'!K17,'P&L Drivers'!K28) -> 0.12 | L18: =-L17/SUM('P&L Drivers'!L17,'P&L Drivers'!L28) -> 0.12 | M18: =-M17/SUM('P&L Drivers'!M17,'P&L Drivers'!M28) -> 0.12
B20: ="Operating Scenario: "&$E$10&" % of Total Revenue" -> Operating Scenario: Base Case % of Total Revenue | I20: =INDEX(I$22:I$24,MATCH($E$10,$B$22:$B$24,0),0) -> 0.12 | J20: =INDEX(J$22:J$24,MATCH($E$10,$B$22:$B$24,0),0) -> 0.12 | K20: =INDEX(K$22:K$24,MATCH($E$10,$B$22:$B$24,0),0) -> 0.12 | L20: =INDEX(L$22:L$24,MATCH($E$10,$B$22:$B$24,0),0) -> 0.12 | M20: =INDEX(M$22:M$24,MATCH($E$10,$B$22:$B$24,0),0) -> 0.12
B22: Base Case | I22: 0.12 | J22: 0.12 | K22: 0.12 | L22: 0.12 | M22: 0.12
B23: Upside Case | I23: 0.1 | J23: 0.1 | K23: 0.1 | L23: 0.1 | M23: 0.1
B24: Downside Case | I24: 0.15 | J24: 0.15 | K24: 0.15 | L24: 0.15 | M24: 0.15
A26: x | B26: NWC Drivers | N26: x
D28: 42004 | E28: =EOMONTH(D28,12) -> 42369 | F28: =EOMONTH(E28,12) -> 42735 | G28: =EOMONTH(F28,12) -> 43100 | H28: =EOMONTH(G28,12) -> 43465 | I28: =EOMONTH(H28,12) -> 43830 | J28: =EOMONTH(I28,12) -> 44196 | K28: =EOMONTH(J28,12) -> 44561 | L28: =EOMONTH(K28,12) -> 44926 | M28: =EOMONTH(L28,12) -> 45291
D29: =YEAR(D28) -> 2014 | E29: =YEAR(E28) -> 2015 | F29: =YEAR(F28) -> 2016 | G29: =YEAR(G28) -> 2017 | H29: =YEAR(H28) -> 2018 | I29: =YEAR(I28) -> 2019 | J29: =YEAR(J28) -> 2020 | K29: =YEAR(K28) -> 2021 | ... M29: =YEAR(M28) -> 2023
B31: Total Revenue | D31: =SUM('P&L Drivers'!D17,'P&L Drivers'!D28) -> 534.942 | E31: =SUM('P&L Drivers'!E17,'P&L Drivers'!E28) -> 356.848 | F31: =SUM('P&L Drivers'!F17,'P&L Drivers'!F28) -> 378.665 | G31: =SUM('P&L Drivers'!G17,'P&L Drivers'!G28) -> 512.969 | H31: =SUM('P&L Drivers'!H17,'P&L Drivers'!H28) -> 553.139 | I31: =SUM('P&L Drivers'!I17,'P&L Drivers'!I28) -> 624.1869 | J31: =SUM('P&L Drivers'!J17,'P&L Drivers'!J28) -> 704.69969 | K31: =SUM('P&L Drivers'!K17,'P&L Drivers'!K28) -> 795.97787 | ... M31: =SUM('P&L Drivers'!M17,'P&L Drivers'!M28) -> 1016.9745
B32: Total COGs | D32: =-SUM('P&L Drivers'!D41,'P&L Drivers'!D52) -> 368.09903 | E32: =-SUM('P&L Drivers'!E41,'P&L Drivers'!E52) -> 286.17448 | F32: =-SUM('P&L Drivers'!F41,'P&L Drivers'!F52) -> 271.028 | G32: =-SUM('P&L Drivers'!G41,'P&L Drivers'!G52) -> 370.333 | H32: =-SUM('P&L Drivers'!H41,'P&L Drivers'!H52) -> 378.07 | I32: =-SUM('P&L Drivers'!I41,'P&L Drivers'!I52) -> 405.72149 | J32: =-SUM('P&L Drivers'!J41,'P&L Drivers'!J52) -> 458.0548 | K32: =-SUM('P&L Drivers'!K41,'P&L Drivers'!K52) -> 517.38562 | ... M32: =-SUM('P&L Drivers'!M41,'P&L Drivers'!M52) -> 661.03341
B34: Net Working Capital Schedule
B35: Accounts Receivable | D35: ='Historical Financials'!D77 -> 48.573 | E35: ='Historical Financials'!E77 -> 53.97 | F35: ='Historical Financials'!F77 -> 72.971 | G35: ='Historical Financials'!G77 -> 117.711 | H35: ='Historical Financials'!H77 -> 130.769 | I35: =PRODUCT(I$54/365.25)*I$31 -> 145.2591 | J35: =PRODUCT(J$54/365.25)*J$31 -> 163.99582 | K35: =PRODUCT(K$54/365.25)*K$31 -> 185.23784 | L35: =PRODUCT(L$54/365.25)*L$31 -> 209.33042 | M35: =PRODUCT(M$54/365.25)*M$31 -> 236.66757
B36: Inventory | D36: ='Historical Financials'!D78 -> 66.9051 | E36: ='Historical Financials'!E78 -> 74.339 | F36: ='Historical Financials'!F78 -> 59.19 | G36: ='Historical Financials'!G78 -> 111.769 | H36: ='Historical Financials'!H78 -> 124.506 | I36: =PRODUCT(I$55/365.25)*I$32 -> 111.08049 | J36: =PRODUCT(J$55/365.25)*J$32 -> 125.40857 | K36: =PRODUCT(K$55/365.25)*K$32 -> 141.65246 | L36: =PRODUCT(L$55/365.25)*L$32 -> 160.0762 | M36: =PRODUCT(M$55/365.25)*M$32 -> 180.98109
B37: Income Tax Recoverable | D37: ='Historical Financials'!D79 -> 9.8505 | E37: ='Historical Financials'!E79 -> 10.945 | F37: ='Historical Financials'!F79 -> 2.343 | G37: ='Historical Financials'!G79 -> 3.02 | H37: ='Historical Financials'!H79 -> 4.228 | I37: =PRODUCT(I$56,I$31) -> 6.241869 | J37: =PRODUCT(J$56,J$31) -> 7.0469969 | K37: =PRODUCT(K$56,K$31) -> 7.9597787 | L37: =PRODUCT(L$56,L$31) -> 8.9950511 | M37: =PRODUCT(M$56,M$31) -> 10.169745
B38: Deferred Income Taxes | D38: ='Historical Financials'!D80 -> 12.4524 | E38: ='Historical Financials'!E80 -> 13.836 | F38: ='Historical Financials'!F80 -> 8.11 | G38: ='Historical Financials'!G80 -> 4.909 | H38: ='Historical Financials'!H80 -> 4.367 | I38: =PRODUCT(I$57,I$31) -> 9.3628035 | J38: =PRODUCT(J$57,J$31) -> 10.570495 | K38: =PRODUCT(K$57,K$31) -> 11.939668 | L38: =PRODUCT(L$57,L$31) -> 13.492577 | M38: =PRODUCT(M$57,M$31) -> 15.254617
B39: Prepaid Expenses and Other Assets | D39: ='Historical Financials'!D81 -> 16.812 | E39: ='Historical Financials'!E81 -> 18.68 | F39: ='Historical Financials'!F81 -> 22.768 | G39: ='Historical Financials'!G81 -> 33.326 | H39: ='Historical Financials'!H81 -> 40.331 | I39: =PRODUCT(I$58,I$32) -> 34.486326 | J39: =PRODUCT(J$58,J32) -> 38.934658 | K39: =PRODUCT(K$58,K32) -> 43.977778 | L39: =PRODUCT(L$58,L32) -> 49.697657 | M39: =PRODUCT(M$58,M32) -> 56.18784
B40: Current Assets (Excluding Cash) | D40: =SUM(D35:D39) -> 154.593 | E40: =SUM(E35:E39) -> 171.77 | F40: =SUM(F35:F39) -> 165.382 | G40: =SUM(G35:G39) -> 270.735 | H40: =SUM(H35:H39) -> 304.201 | I40: =SUM(I35:I39) -> 306.43059 | J40: =SUM(J35:J39) -> 345.95654 | K40: =SUM(K35:K39) -> 390.76752 | ... M40: =SUM(M35:M39) -> 499.26086
B42: Accounts Payable | D42: ='Historical Financials'!D84 -> 13 | E42: ='Historical Financials'!E84 -> 15.992 | F42: ='Historical Financials'!F84 -> 23.785 | G42: ='Historical Financials'!G84 -> 57.443 | H42: ='Historical Financials'!H84 -> 43.603 | I42: =(I60/365.25)*I32 -> 44.432195 | J42: =(J60/365.25)*J32 -> 50.163428 | K42: =(K60/365.25)*K32 -> 56.660985 | L42: =(L60/365.25)*L32 -> 64.03048 | M42: =(M60/365.25)*M32 -> 72.392434
B43: Deferred Revenue | D43: ='Historical Financials'!D85 -> 16 | E43: ='Historical Financials'!E85 -> 14.007 | F43: ='Historical Financials'!F85 -> 11.987 | G43: ='Historical Financials'!G85 -> 25.924 | H43: ='Historical Financials'!H85 -> 10.65 | I43: =PRODUCT(I$61,I$31) -> 18.725607 | J43: =PRODUCT(J$61,J$31) -> 21.140991 | K43: =PRODUCT(K$61,K$31) -> 23.879336 | L43: =PRODUCT(L$61,L$31) -> 26.985153 | M43: =PRODUCT(M$61,M$31) -> 30.509235
B44: Warranty Reserves | D44: ='Historical Financials'!D86 -> 2.5 | E44: ='Historical Financials'!E86 -> 2.251 | F44: ='Historical Financials'!F86 -> 1.698 | G44: ='Historical Financials'!G86 -> 3.103 | H44: ='Historical Financials'!H86 -> 3.719 | I44: =PRODUCT(I$62,I$31) -> 3.1209345 | J44: =PRODUCT(J$62,J$31) -> 3.5234985 | K44: =PRODUCT(K$62,K$31) -> 3.9798894 | L44: =PRODUCT(L$62,L$31) -> 4.4975255 | M44: =PRODUCT(M$62,M$31) -> 5.0848724
B45: Income Taxes Payable | D45: ='Historical Financials'!D87 -> 0 | E45: ='Historical Financials'!E87 -> 0 | F45: ='Historical Financials'!F87 -> 3.433 | G45: ='Historical Financials'!G87 -> 2.336 | H45: ='Historical Financials'!H87 -> 6.894 | I45: =PRODUCT(I$63,I$32) -> 4.0572149 | J45: =PRODUCT(J$63,J$32) -> 4.580548 | K45: =PRODUCT(K$63,K$32) -> 5.1738562 | L45: =PRODUCT(L$63,L$32) -> 5.8467832 | M45: =PRODUCT(M$63,M$32) -> 6.6103341
B46: Accrued and Other Current Liabilities | D46: ='Historical Financials'!D88 -> 23 | E46: ='Historical Financials'!E88 -> 27.075 | F46: ='Historical Financials'!F88 -> 32.289 | G46: ='Historical Financials'!G88 -> 34.069 | H46: ='Historical Financials'!H88 -> 41.572 | I46: =PRODUCT(I$64,I$32) -> 40.572149 | J46: =PRODUCT(J$64,J$32) -> 45.80548 | K46: =PRODUCT(K$64,K$32) -> 51.738562 | L46: =PRODUCT(L$64,L$32) -> 58.467832 | M46: =PRODUCT(M$64,M$32) -> 66.103341
B47: Current Liabilities | D47: =SUM(D42:D46) -> 54.5 | E47: =SUM(E42:E46) -> 59.325 | F47: =SUM(F42:F46) -> 73.192 | G47: =SUM(G42:G46) -> 122.875 | H47: =SUM(H42:H46) -> 106.438 | I47: =SUM(I42:I46) -> 110.9081 | J47: =SUM(J42:J46) -> 125.21394 | K47: =SUM(K42:K46) -> 141.43263 | ... M47: =SUM(M42:M46) -> 180.70022
B49: Net Working Capital (NWC) | D49: =D40-D47 -> 100.093 | E49: =E40-E47 -> 112.445 | F49: =F40-F47 -> 92.19 | G49: =G40-G47 -> 147.86 | H49: =H40-H47 -> 197.763 | I49: =I40-I47 -> 195.52249 | J49: =J40-J47 -> 220.7426 | K49: =K40-K47 -> 249.33489 | ... M49: =M40-M47 -> 318.56064
B50: Δ NWC | D50: ='Historical Financials'!D92 -> -8.7 | E50: =D49-E49 -> -12.352 | F50: =E49-F49 -> 20.255 | G50: =F49-G49 -> -55.67 | H50: =G49-H49 -> -49.903 | I50: =H49-I49 -> 2.2405123 | J50: =I49-J49 -> -25.220108 | K50: =J49-K49 -> -28.592298 | L50: =K49-L49 -> -32.429233 | M50: =L49-M49 -> -36.796518
B52: NWC Drivers
B54: Days Sales Outstanding (DSO) | D54: =D35/D31*365.25 -> 33.164882 | E54: =E35/E31*365.25 -> 55.240726 | F54: =F35/F31*365.25 -> 70.38585 | G54: =G35/G31*365.25 -> 83.81392 | H54: =H35/H31*365.25 -> 86.349683 | I54: 85 | J54: =$I$54 -> 85 | K54: =$I$54 -> 85 | L54: =$I$54 -> 85 | M54: =$I$54 -> 85
B55: Inventory Days | D55: =D36/D32*365.25 -> 66.387264 | E55: =E36/E32*365.25 -> 94.880296 | F55: =F36/F32*365.25 -> 79.76721 | G55: =G36/G32*365.25 -> 110.23492 | H55: =H36/H32*365.25 -> 120.28412 | I55: 100 | J55: =$I$55 -> 100 | K55: =$I$55 -> 100 | L55: =$I$55 -> 100 | M55: =$I$55 -> 100
B56: Income Tax Recoverable as % of Total Revenue | D56: =D37/D31 -> 0.018414146 | E56: =E37/E31 -> 0.030671322 | F56: =F37/F31 -> 0.0061875272 | G56: =G37/G31 -> 0.0058872953 | H56: =H37/H31 -> 0.0076436483 | I56: 0.01 | J56: =$I$56 -> 0.01 | K56: =$I$56 -> 0.01 | L56: =$I$56 -> 0.01 | M56: =$I$56 -> 0.01
B57: Deferred Income Taxes as % of Total Revenue | D57: =D38/D31 -> 0.023278038 | E57: =E38/E31 -> 0.038772811 | F57: =F38/F31 -> 0.021417348 | G57: =G38/G31 -> 0.0095697791 | H57: =H38/H31 -> 0.0078949414 | I57: 0.015 | J57: =$I$57 -> 0.015 | K57: =$I$57 -> 0.015 | L57: =$I$57 -> 0.015 | M57: =$I$57 -> 0.015
B58: Prepaid Expenses and Other Assets as % of Total COGS | D58: =D39/D32 -> 0.045672492 | E58: =E39/E32 -> 0.065274862 | F58: =F39/F32 -> 0.084006081 | G58: =G39/G32 -> 0.08998928 | H58: =H39/H32 -> 0.10667601 | I58: 0.085 | J58: =$I$58 -> 0.085 | K58: =$I$58 -> 0.085 | L58: =$I$58 -> 0.085 | M58: =$I$58 -> 0.085
B60: Days Payables Outstanding (DPO) | D60: =D42/D32*365.25 -> 12.899382 | E60: =E42/E32*365.25 -> 20.410897 | F60: =F42/F32*365.25 -> 32.053778 | G60: =G42/G32*365.25 -> 56.654567 | H60: =H42/H32*365.25 -> 42.124463 | I60: 40 | J60: =$I$60 -> 40 | K60: =$I$60 -> 40 | L60: =$I$60 -> 40 | M60: =$I$60 -> 40
B61: Deferred Revenue as % of Total Revenue | D61: =D43/D31 -> 0.029909785 | E61: =E43/E31 -> 0.039252006 | F61: =F43/F31 -> 0.031655949 | G61: =G43/G31 -> 0.050537167 | H61: =H43/H31 -> 0.01925375 | I61: 0.03 | J61: =$I$61 -> 0.03 | K61: =$I$61 -> 0.03 | L61: =$I$61 -> 0.03 | M61: =$I$61 -> 0.03
B62: Warranty Reserves as % of Total Revenue | D62: =D44/D31 -> 0.0046734038 | E62: =E44/E31 -> 0.0063080079 | F62: =F44/F31 -> 0.0044841747 | G62: =G44/G31 -> 0.0060490985 | H62: =H44/H31 -> 0.0067234456 | I62: 0.005 | J62: =$I$62 -> 0.005 | K62: =$I$62 -> 0.005 | L62: =$I$62 -> 0.005 | M62: =$I$62 -> 0.005
B63: Income Taxes Payable as % of Total COGS | D63: =D45/D32 -> 0 | E63: =E45/E32 -> 0 | F63: =F45/F32 -> 0.012666588 | G63: =G45/G32 -> 0.0063078365 | H63: =H45/H32 -> 0.018234718 | I63: 0.01 | J63: =$I$63 -> 0.01 | K63: =$I$63 -> 0.01 | L63: =$I$63 -> 0.01 | M63: =$I$63 -> 0.01
B64: Accrued and Other Current Liabilities as % of Total COGS | D64: =D46/D32 -> 0.062483185 | E64: =E46/E32 -> 0.094610112 | F64: =F46/F32 -> 0.11913529 | G64: =G46/G32 -> 0.091995582 | H64: =H46/H32 -> 0.10995847 | I64: 0.1 | J64: =$I$64 -> 0.1 | K64: =$I$64 -> 0.1 | L64: =$I$64 -> 0.1 | M64: =$I$64 -> 0.1

Sheet P&L Drivers
B2: Northwind Industries
B3: P&L Drivers | M3: Draft - Preliminary & Confidential
B5: $ in millions, except where otherwise denoted
A6: x | B6: Revenue Drivers | N6: x
B8: Select Case ([=1] Base Case; [=2] Upside Case; [=3] Downside Case) >>> | E8: 1
B10: Operating Scenario >>> | E10: =CHOOSE($E$8,B22,B23,B24) -> Base Case
D12: 42004 | E12: =EOMONTH(D12,12) -> 42369 | F12: =EOMONTH(E12,12) -> 42735 | G12: =EOMONTH(F12,12) -> 43100 | H12: =EOMONTH(G12,12) -> 43465 | I12: =EOMONTH(H12,12) -> 43830 | J12: =EOMONTH(I12,12) -> 44196 | K12: =EOMONTH(J12,12) -> 44561 | L12: =EOMONTH(K12,12) -> 44926 | M12: =EOMONTH(L12,12) -> 45291
D13: =YEAR(D12) -> 2014 | E13: =YEAR(E12) -> 2015 | F13: =YEAR(F12) -> 2016 | G13: =YEAR(G12) -> 2017 | H13: =YEAR(H12) -> 2018 | I13: =YEAR(I12) -> 2019 | J13: =YEAR(J12) -> 2020 | K13: =YEAR(K12) -> 2021 | ... M13: =YEAR(M12) -> 2023
A15: x | B15: Products Revenue: Annual Growth Rates | N15: x
B17: Products Revenue | D17: ='Historical Financials'!D13 -> 236.277 | E17: ='Historical Financials'!E13 -> 148.565 | F17: ='Historical Financials'!F13 -> 134.755 | G17: ='Historical Financials'!G13 -> 211.313 | H17: ='Historical Financials'!H13 -> 238.459 | I17: =PRODUCT(H17,1+I$20) -> 262.3049 | J17: =PRODUCT(I17,1+J$20) -> 288.53539 | K17: =PRODUCT(J17,1+K$20) -> 317.38893 | L17: =PRODUCT(K17,1+L$20) -> 349.12782 | M17: =PRODUCT(L17,1+M$20) -> 384.0406
B18: Y-O-Y Growth % | E18: =E17/D17-1 -> -0.3712253 | F18: =F17/E17-1 -> -0.092955945 | G18: =G17/F17-1 -> 0.56812734 | H18: =H17/G17-1 -> 0.12846346 | I18: =I17/H17-1 -> 0.1 | J18: =J17/I17-1 -> 0.1 | K18: =K17/J17-1 -> 0.1 | L18: =L17/K17-1 -> 0.1 | M18: =M17/L17-1 -> 0.1
B20: ="Operating Scenario: "&$E$10&" Escalation Factors Per Annum" -> Operating Scenario: Base Case Escalation Factors Per Annum | I20: =INDEX(I$22:I$24,MATCH($E$10,$B$22:$B$24,0),0) -> 0.1 | J20: =INDEX(J$22:J$24,MATCH($E$10,$B$22:$B$24,0),0) -> 0.1 | K20: =INDEX(K$22:K$24,MATCH($E$10,$B$22:$B$24,0),0) -> 0.1 | L20: =INDEX(L$22:L$24,MATCH($E$10,$B$22:$B$24,0),0) -> 0.1 | M20: =INDEX(M$22:M$24,MATCH($E$10,$B$22:$B$24,0),0) -> 0.1
B22: Base Case | I22: 0.1 | J22: 0.1 | K22: 0.1 | L22: 0.1 | M22: 0.1
B23: Upside Case | I23: 0.2 | J23: 0.2 | K23: 0.2 | L23: 0.2 | M23: 0.2
B24: Downside Case | I24: 0.05 | J24: 0.05 | K24: 0.05 | L24: 0.05 | M24: 0.05
A26: x | B26: Services Revenue: Annual Growth Rates | N26: x
B28: Services Revenue | D28: ='Historical Financials'!D14 -> 298.665 | E28: ='Historical Financials'!E14 -> 208.283 | F28: ='Historical Financials'!F14 -> 243.91 | G28: ='Historical Financials'!G14 -> 301.656 | H28: ='Historical Financials'!H14 -> 314.68 | I28: =PRODUCT(H28,1+I$31) -> 361.882 | J28: =PRODUCT(I28,1+J$31) -> 416.1643 | K28: =PRODUCT(J28,1+K$31) -> 478.58894 | L28: =PRODUCT(K28,1+L$31) -> 550.37729 | M28: =PRODUCT(L28,1+M$31) -> 632.93388
B29: Y-O-Y Growth % | E29: =E28/D28-1 -> -0.30261999 | F29: =F28/E28-1 -> 0.17105093 | G29: =G28/F28-1 -> 0.23675126 | H29: =H28/G28-1 -> 0.043175007 | I29: =I28/H28-1 -> 0.15 | J29: =J28/I28-1 -> 0.15 | K29: =K28/J28-1 -> 0.15 | L29: =L28/K28-1 -> 0.15 | M29: =M28/L28-1 -> 0.15
B31: ="Operating Scenario: "&$E$10&" Escalation Factors Per Annum" -> Operating Scenario: Base Case Escalation Factors Per Annum | I31: =INDEX(I$33:I$35,MATCH($E$10,$B$33:$B$35,0),0) -> 0.15 | J31: =INDEX(J$33:J$35,MATCH($E$10,$B$33:$B$35,0),0) -> 0.15 | K31: =INDEX(K$33:K$35,MATCH($E$10,$B$33:$B$35,0),0) -> 0.15 | L31: =INDEX(L$33:L$35,MATCH($E$10,$B$33:$B$35,0),0) -> 0.15 | M31: =INDEX(M$33:M$35,MATCH($E$10,$B$33:$B$35,0),0) -> 0.15
B33: Base Case | I33: 0.15 | J33: 0.15 | K33: 0.15 | L33: 0.15 | M33: 0.15
B34: Upside Case | I34: 0.2 | J34: 0.2 | K34: 0.2 | L34: 0.2 | M34: 0.2
B35: Downside Case | I35: 0.1 | J35: 0.1 | K35: 0.1 | L35: 0.1 | M35: 0.1
A37: x | B37: Expense Drivers | N37: x
A39: x | B39: Products COGS: % of Products Revenue | N39: x
B41: Products COGS | D41: ='Historical Financials'!D18 -> -141.08299 | E41: ='Historical Financials'!E18 -> -101.54867 | F41: ='Historical Financials'!F18 -> -85.732825 | G41: ='Historical Financials'!G18 -> -140.56916 | H41: ='Historical Financials'!H18 -> -158.4088 | I41: =-PRODUCT(I$44,I17) -> -170.49819 | J41: =-PRODUCT(J$44,J17) -> -187.548 | K41: =-PRODUCT(K$44,K17) -> -206.3028 | L41: =-PRODUCT(L$44,L17) -> -226.93308 | M41: =-PRODUCT(M$44,M17) -> -249.62639
B42: % of Products Revenue | D42: =-D41/D17 -> 0.59710842 | E42: =-E41/E17 -> 0.68353023 | F42: =-F41/F17 -> 0.63621257 | G42: =-G41/G17 -> 0.66521778 | H42: =-H41/H17 -> 0.66430204 | I42: =-I41/I17 -> 0.65 | J42: =-J41/J17 -> 0.65 | K42: =-K41/K17 -> 0.65 | ... M42: =-M41/M17 -> 0.65
B44: ="Operating Scenario: "&$E$10&" % of Products Revenue" -> Operating Scenario: Base Case % of Products Revenue | I44: =INDEX(I$46:I$48,MATCH($E$10,$B$46:$B$48,0),0) -> 0.65 | J44: =INDEX(J$46:J$48,MATCH($E$10,$B$46:$B$48,0),0) -> 0.65 | K44: =INDEX(K$46:K$48,MATCH($E$10,$B$46:$B$48,0),0) -> 0.65 | L44: =INDEX(L$46:L$48,MATCH($E$10,$B$46:$B$48,0),0) -> 0.65 | M44: =INDEX(M$46:M$48,MATCH($E$10,$B$46:$B$48,0),0) -> 0.65
B46: Base Case | I46: 0.65 | J46: 0.65 | K46: 0.65 | L46: 0.65 | M46: 0.65
B47: Upside Case | I47: 0.6 | J47: 0.6 | K47: 0.6 | L47: 0.6 | M47: 0.6
B48: Downside Case | I48: 0.7 | J48: 0.7 | K48: 0.7 | L48: 0.7 | M48: 0.7
A50: x | B50: Services COGS: % of Services Revenue | N50: x
B52: Services COGS | D52: ='Historical Financials'!D19 -> -227.01605 | E52: ='Historical Financials'!E19 -> -184.62581 | F52: ='Historical Financials'!F19 -> -185.29518 | G52: ='Historical Financials'!G19 -> -229.76384 | H52: ='Historical Financials'!H19 -> -219.6612 | I52: =-PRODUCT(I$55,I28) -> -235.2233 | J52: =-PRODUCT(J$55,J28) -> -270.5068 | K52: =-PRODUCT(K$55,K28) -> -311.08281 | L52: =-PRODUCT(L$55,L28) -> -357.74524 | M52: =-PRODUCT(M$55,M28) -> -411.40702
B53: % of Services Revenue | D53: =-D52/D28 -> 0.76010261 | E53: =-E52/E28 -> 0.88641807 | F53: =-F52/F28 -> 0.75968667 | G53: =-G52/G28 -> 0.76167501 | H53: =-H52/H28 -> 0.69804627 | I53: =-I52/I28 -> 0.65 | J53: =-J52/J28 -> 0.65 | K53: =-K52/K28 -> 0.65 | ... M53: =-M52/M28 -> 0.65
B55: ="Operating Scenario: "&$E$10&" % of Services Revenue" -> Operating Scenario: Base Case % of Services Revenue | I55: =INDEX(I$57:I$59,MATCH($E$10,$B$57:$B$59,0),0) -> 0.65 | J55: =INDEX(J$57:J$59,MATCH($E$10,$B$57:$B$59,0),0) -> 0.65 | K55: =INDEX(K$57:K$59,MATCH($E$10,$B$57:$B$59,0),0) -> 0.65 | L55: =INDEX(L$57:L$59,MATCH($E$10,$B$57:$B$59,0),0) -> 0.65 | M55: =INDEX(M$57:M$59,MATCH($E$10,$B$57:$B$59,0),0) -> 0.65
B57: Base Case | I57: 0.65 | J57: 0.65 | K57: 0.65 | L57: 0.65 | M57: 0.65
B58: Upside Case | I58: 0.6 | J58: 0.6 | K58: 0.6 | L58: 0.6 | M58: 0.6
B59: Downside Case | I59: 0.75 | J59: 0.75 | K59: 0.75 | L59: 0.75 | M59: 0.75
A61: x | B61: SG&A: % of Revenue | N61: x
B63: SG&A | D63: ='Historical Financials'!D23 -> -49.069 | E63: ='Historical Financials'!E23 -> -43.735 | F63: ='Historical Financials'!F23 -> -47.117 | G63: ='Historical Financials'!G23 -> -49.146 | H63: ='Historical Financials'!H23 -> -44.828 | I63: =-PRODUCT(I$66,SUM(I17,I28)) -> -62.41869 | J63: =-PRODUCT(J$66,SUM(J17,J28)) -> -70.469969 | K63: =-PRODUCT(K$66,SUM(K17,K28)) -> -79.597787 | L63: =-PRODUCT(L$66,SUM(L17,L28)) -> -89.950511 | M63: =-PRODUCT(M$66,SUM(M17,M28)) -> -101.69745
B64: % of Revenue | D64: =-D63/SUM(D17,D28) -> 0.091727701 | E64: =-E63/SUM(E17,E28) -> 0.12255918 | F64: =-F63/SUM(F17,F28) -> 0.12442924 | G64: =-G63/SUM(G17,G28) -> 0.095806959 | H64: =-H63/SUM(H17,H28) -> 0.08104292 | I64: =-I63/SUM(I17,I28) -> 0.1 | J64: =-J63/SUM(J17,J28) -> 0.1 | K64: =-K63/SUM(K17,K28) -> 0.1 | ... M64: =-M63/SUM(M17,M28) -> 0.1
B66: ="Operating Scenario: "&$E$10&" % of Total Revenue" -> Operating Scenario: Base Case % of Total Revenue | I66: =INDEX(I$68:I$70,MATCH($E$10,$B$68:$B$70,0),0) -> 0.1 | J66: =INDEX(J$68:J$70,MATCH($E$10,$B$68:$B$70,0),0) -> 0.1 | K66: =INDEX(K$68:K$70,MATCH($E$10,$B$68:$B$70,0),0) -> 0.1 | L66: =INDEX(L$68:L$70,MATCH($E$10,$B$68:$B$70,0),0) -> 0.1 | M66: =INDEX(M$68:M$70,MATCH($E$10,$B$68:$B$70,0),0) -> 0.1
B68: Base Case | I68: 0.1 | J68: 0.1 | K68: 0.1 | L68: 0.1 | M68: 0.1
B69: Upside Case | I69: 0.08 | J69: 0.08 | K69: 0.08 | L69: 0.08 | M69: 0.08
B70: Downside Case | I70: 0.12 | J70: 0.12 | K70: 0.12 | L70: 0.12 | M70: 0.12
A72: x | B72: R&D: % of Revenue | N72: x
B74: R&D | D74: ='Historical Financials'!D24 -> -11.049 | E74: ='Historical Financials'!E24 -> -7.431 | F74: ='Historical Financials'!F24 -> -9.075 | G74: ='Historical Financials'!G24 -> -12.512 | H74: ='Historical Financials'!H24 -> -10.457 | I74: =-PRODUCT(I$77,SUM(I17,I28)) -> -12.483738 | J74: =-PRODUCT(J$77,SUM(J17,J28)) -> -14.093994 | K74: =-PRODUCT(K$77,SUM(K17,K28)) -> -15.919557 | L74: =-PRODUCT(L$77,SUM(L17,L28)) -> -17.990102 | M74: =-PRODUCT(M$77,SUM(M17,M28)) -> -20.33949
B75: % of Revenue | D75: =-D74/SUM(D17,D28) -> 0.020654576 | E75: =-E74/SUM(E17,E28) -> 0.020823992 | F75: =-F74/SUM(F17,F28) -> 0.023965774 | G75: =-G74/SUM(G17,G28) -> 0.024391337 | H75: =-H74/SUM(H17,H28) -> 0.018904832 | I75: =-I74/SUM(I17,I28) -> 0.02 | J75: =-J74/SUM(J17,J28) -> 0.02 | K75: =-K74/SUM(K17,K28) -> 0.02 | ... M75: =-M74/SUM(M17,M28) -> 0.02
B77: ="Operating Scenario: "&$E$10&" % of Total Revenue" -> Operating Scenario: Base Case % of Total Revenue | I77: =INDEX(I$79:I$81,MATCH($E$10,$B$79:$B$81,0),0) -> 0.02 | J77: =INDEX(J$79:J$81,MATCH($E$10,$B$79:$B$81,0),0) -> 0.02 | K77: =INDEX(K$79:K$81,MATCH($E$10,$B$79:$B$81,0),0) -> 0.02 | L77: =INDEX(L$79:L$81,MATCH($E$10,$B$79:$B$81,0),0) -> 0.02 | M77: =INDEX(M$79:M$81,MATCH($E$10,$B$79:$B$81,0),0) -> 0.02
B79: Base Case | I79: 0.02 | J79: 0.02 | K79: 0.02 | L79: 0.02 | M79: 0.02
B80: Upside Case | I80: 0.01 | J80: 0.01 | K80: 0.01 | L80: 0.01 | M80: 0.01
B81: Downside Case | I81: 0.03 | J81: 0.03 | K81: 0.03 | L81: 0.03 | M81: 0.03
A83: x | B83: D&A: % of Capex | N83: x
B85: D&A | D85: ='Historical Financials'!D28 -> -31.877967 | E85: ='Historical Financials'!E28 -> -33.936517 | F85: ='Historical Financials'!F28 -> -36.128 | G85: ='Historical Financials'!G28 -> -38.461 | H85: ='Historical Financials'!H28 -> -42.989 | I85: =PRODUCT(I$88,'Capex & NWC Drivers'!I17) -> -56.176821 | J85: =PRODUCT(J$88,'Capex & NWC Drivers'!J17) -> -71.879368 | K85: =PRODUCT(K$88,'Capex & NWC Drivers'!K17) -> -85.96561 | L85: =PRODUCT(L$88,'Capex & NWC Drivers'!L17) -> -102.54358 | M85: =PRODUCT(M$88,'Capex & NWC Drivers'!M17) -> -122.03694
B86: % of Capex | D86: =D85/'Capex & NWC Drivers'!D17 -> 0.60866924 | E86: =E85/'Capex & NWC Drivers'!E17 -> 0.97136273 | F86: =F85/'Capex & NWC Drivers'!F17 -> 0.97450975 | G86: =G85/'Capex & NWC Drivers'!G17 -> 0.8116361 | H86: =H85/'Capex & NWC Drivers'!H17 -> 0.67526939 | I86: =I85/'Capex & NWC Drivers'!I17 -> 0.75 | J86: =J85/'Capex & NWC Drivers'!J17 -> 0.85 | K86: =K85/'Capex & NWC Drivers'!K17 -> 0.9 | ... M86: =M85/'Capex & NWC Drivers'!M17 -> 1
B88: ="Operating Scenario: "&$E$10&" % of Capex" -> Operating Scenario: Base Case % of Capex | I88: =INDEX(I$90:I$92,MATCH($E$10,$B$90:$B$92,0),0) -> 0.75 | J88: =INDEX(J$90:J$92,MATCH($E$10,$B$90:$B$92,0),0) -> 0.85 | K88: =INDEX(K$90:K$92,MATCH($E$10,$B$90:$B$92,0),0) -> 0.9 | L88: =INDEX(L$90:L$92,MATCH($E$10,$B$90:$B$92,0),0) -> 0.95 | M88: =INDEX(M$90:M$92,MATCH($E$10,$B$90:$B$92,0),0) -> 1
B90: Base Case | I90: 0.75 | J90: 0.85 | K90: 0.9 | L90: 0.95 | M90: 1
B91: Upside Case | I91: 0.7 | J91: 0.8 | K91: 0.85 | L91: 0.9 | M91: 0.95
B92: Downside Case | I92: 0.8 | J92: 0.9 | K92: 0.95 | L92: 1 | M92: 1

Sheet Returns Model
B2: Northwind Industries
B3: Illustrative Transaction Overview & Returns Analysis | O3: Draft - Preliminary & Confidential
B5: $ in millions, except where otherwise denoted
A6: x | B6: Transaction Assumptions | P6: x
A8: x | B8: General Inputs | P8: x
B10: Effective Federal Corporate Tax Rate | E10: 0.21 | G10: Transaction Expenses (% Purchase Price) | J10: 0.01 | L10: Dividend Sweep | N10: 0
B11: Write-Up % of Identifiable Intangibles | E11: 0.15 | G11: Seller Equity Rollover (% of NewCo) | J11: 0.05 | L11: Exit Multiple | N11: 5
B12: Acquisition Purchase Date | E12: 43465 | G12: Circularity Switch | J12: 0 | L12: Sponsor Preferred Hurdle | N12: 0.08
L13: Mgmt. Promote | N13: 0.05
A15: x | B15: Purchase Assumptions | P15: x
B17: Purchase Price Derivation | G17: Net Identifiable Assets | L17: Identifiable Intangibles Write-Up
B18: LTM EBITDA (2018A) | E18: ='Historical Financials'!H25 -> 119.784 | G18: Equity Purchase Price | J18: =E23 -> 620.673 | L18: Goodwill & Identifiable Intangibles Created | O18: =J21 -> 183.897
B19: (x) Entry EV / EBITDA Multiple | E19: 5 | G19: (–) Book Value of Net Assets | J19: =-G153 -> -469.508 | L19: (–) Identifiable Intangibles Write-Up | O19: =-PRODUCT(O18,$E$11) -> -27.58455
B20: Enterprise Value | E20: =PRODUCT(E18:E19) -> 598.92 | G20: (+) Write-off of Existing Goodwill | J20: =G132 -> 32.732 | L20: (+) Deferred Tax Liability | O20: =-PRODUCT($O$19,$E$10) -> 5.7927555
B21: (–) Debt Outstanding (12/31/2018) | E21: =-'Historical Financials'!H68 -> -0.261 | G21: Goodwill & Identifiable Intangibles Created | J21: =SUM(J18:J20) -> 183.897 | L21: Goodwill Created in Transaction | O21: =SUM(O18:O20) -> 162.10521
B22: (+) Cash Balance (12/31/2018) | E22: ='Historical Financials'!H45 -> 22.014
B23: Equity Purchase Price | E23: =SUM(E20:E22) -> 620.673 | L23: Identifiable Intangibles Write-Up | O23: =O19 -> -27.58455
B24: (–) Seller Rollover | E24: =-D35 -> -16.833226 | L24: (÷) Total Amortization Period | O24: 15
B25: Adjusted Equity Purchase Price | E25: =SUM(E23:E24) -> 603.83977 | L25: Intangibles Amortization Per Annum | O25: =O23/O24 -> -1.83897
A27: x | B27: Sources & Uses (S&U) | P27: x
B29: Sources of Capital | D29: $mm | E29: % of Total | F29: Entry Multiple (LTM EBITDA) | H29: Uses of Capital | J29: $mm | K29: % of Total | L29: Entry Multiple (LTM EBITDA)
B32: Revolver | D32: =E44 -> 0 | E32: =D32/$D$37 -> 0 | F32: =D32/$E$18 -> 0 | H32: Purchase of Equity: Sponsor | J32: =E25 -> 603.83977 | K32: =J32/$J$37 -> 0.94924774 | L32: =J32/$E$18 -> 5.041072
B33: 1st Lien Bank Debt | D33: =E45 -> 179.676 | E33: =D33/$D$37 -> 0.28245413 | F33: =D33/$E$18 -> 1.5 | H33: Rollover of Equity: Seller | J33: =D35 -> 16.833226 | K33: =J33/$J$37 -> 0.026462156 | L33: =J33/$E$18 -> 0.14052984
B34: Senior Unsecured Notes | D34: =E46 -> 119.784 | E34: =D34/$D$37 -> 0.18830275 | F34: =D34/$E$18 -> 1 | H34: Refinanced Debt | J34: =-E21 -> 0.261 | K34: =J34/$J$37 -> 0.00041029702 | L34: =J34/$E$18 -> 0.0021789221
B35: Seller Rollover Equity | D35: =(D37-SUM(D32:D34))*$J$11 -> 16.833226 | E35: =D35/$D$37 -> 0.026462156 | F35: =D35/$E$18 -> 0.14052984 | H35: Financing Fees & OID | J35: =J47+H47 -> 8.9838 | K35: =J35/$J$37 -> 0.014122706 | L35: =J35/$E$18 -> 0.075
B36: Sponsor Equity | D36: =D37-SUM(D32:D35) -> 319.8313 | E36: =D36/$D$37 -> 0.50278096 | F36: =D36/$E$18 -> 2.670067 | H36: Transaction Expenses | J36: =PRODUCT($J$10,$E$23) -> 6.20673 | K36: =J36/$J$37 -> 0.009757099 | L36: =J36/$E$18 -> 0.051816019
B37: Total Sources of Capital | D37: =$J$37 -> 636.12453 | E37: =SUM(E32:E36) -> 1 | F37: =SUM(F32:F36) -> 5.3105968 | H37: Total Uses of Capital | J37: =SUM(J32:J36) -> 636.12453 | K37: =SUM(K32:K36) -> 1 | L37: =SUM(L32:L36) -> 5.3105968
A39: x | B39: Debt Capital Stack Assumptions | P39: x
D41: Leverage Multiple | E41: Debt Quantum | F41: Floor | G41: Spread to Libor | H41: OID % | I41: Commitment Fee % | J41: Financing Fee % | K41: Mandatory Amort % | L41: Sweep % | M41: Close Date | N41: Tenor | O41: Maturity Date
B44: Revolver | D44: 0 | E44: =PRODUCT($D44,$E$18) -> 0 | F44: 0.015 | G44: 400 | H44: 0.99 | I44: 0.0075 | J44: 0.02 | K44: 0 | L44: 1 | M44: =$E$12 -> 43465 | N44: 3 | O44: =EOMONTH(M44,12*N44) -> 44561
B45: 1st Lien Bank Debt (Term Loan) | D45: =$D$49*0.6 -> 1.5 | E45: =PRODUCT($D45,$E$18) -> 179.676 | F45: 0.015 | G45: 400 | H45: 0.99 | I45: N/A | J45: 0.02 | K45: 0.05 | L45: 1 | M45: =$E$12 -> 43465 | N45: 6 | O45: =EOMONTH(M45,12*N45) -> 45657
B46: Senior Unsecured Notes | D46: =$D$49*0.4 -> 1 | E46: =PRODUCT($D46,$E$18) -> 119.784 | F46: N/A | G46: 750 | H46: 0.99 | I46: N/A | J46: 0.02 | K46: 0 | L46: 1 | M46: =$E$12 -> 43465 | N46: 8 | O46: =EOMONTH(M46,12*N46) -> 46387
B47: Total Leverage | D47: =SUM(D44:D46) -> 2.5 | E47: =SUM(E44:E46) -> 299.46 | H47: =(1-H44)*E44+(1-H45)*E45+(1-H46)*E46 -> 2.9946 | J47: =SUMPRODUCT($J$44:$J$46,$E$44:$E$46) -> 5.9892
B49: Total Leverage Multiple | D49: 2.5 | F49: Revolver Undrawn Amount | H49: 50
A51: x | B51: Income Statement | P51: x
F53: Historical FYE | K53: Projected FYE
D54: ="'19E - '23E Total" -> '19E - '23E Total | E54: ="'19E - '23E CAGR" -> '19E - '23E CAGR | F54: 42004 | G54: =EOMONTH(F54,12) -> 42369 | H54: =EOMONTH(G54,12) -> 42735 | I54: =EOMONTH(H54,12) -> 43100 | J54: =EOMONTH(I54,12) -> 43465 | K54: =EOMONTH(J54,12) -> 43830 | L54: =EOMONTH(K54,12) -> 44196 | M54: =EOMONTH(L54,12) -> 44561 | N54: =EOMONTH(M54,12) -> 44926 | O54: =EOMONTH(N54,12) -> 45291
F55: =YEAR(F54) -> 2014 | G55: =YEAR(G54) -> 2015 | H55: =YEAR(H54) -> 2016 | I55: =YEAR(I54) -> 2017 | J55: =YEAR(J54) -> 2018 | K55: =YEAR(K54) -> 2019 | L55: =YEAR(L54) -> 2020 | M55: =YEAR(M54) -> 2021 | ... O55: =YEAR(O54) -> 2023
B57: Products Revenue | D57: =SUM(K57:O57) -> 1601.3976 | E57: =RATE($O$55-$K$55,0,-$K57,$O57) -> 0.1 | F57: ='Historical Financials'!D13 -> 236.277 | G57: ='Historical Financials'!E13 -> 148.565 | H57: ='Historical Financials'!F13 -> 134.755 | I57: ='Historical Financials'!G13 -> 211.313 | J57: ='Historical Financials'!H13 -> 238.459 | K57: ='P&L Drivers'!I17 -> 262.3049 | L57: ='P&L Drivers'!J17 -> 288.53539 | M57: ='P&L Drivers'!K17 -> 317.38893 | N57: ='P&L Drivers'!L17 -> 349.12782 | O57: ='P&L Drivers'!M17 -> 384.0406
B58: (+) Services Revenue | D58: =SUM(K58:O58) -> 2439.9464 | E58: =RATE($O$55-$K$55,0,-$K58,$O58) -> 0.15 | F58: ='Historical Financials'!D14 -> 298.665 | G58: ='Historical Financials'!E14 -> 208.283 | H58: ='Historical Financials'!F14 -> 243.91 | I58: ='Historical Financials'!G14 -> 301.656 | J58: ='Historical Financials'!H14 -> 314.68 | K58: ='P&L Drivers'!I28 -> 361.882 | L58: ='P&L Drivers'!J28 -> 416.1643 | M58: ='P&L Drivers'!K28 -> 478.58894 | N58: ='P&L Drivers'!L28 -> 550.37729 | O58: ='P&L Drivers'!M28 -> 632.93388
B59: Total Revenue | D59: =SUM(K59:O59) -> 4041.3441 | E59: =RATE($O$55-$K$55,0,-$K59,$O59) -> 0.12979293 | F59: =SUM(F57:F58) -> 534.942 | G59: =SUM(G57:G58) -> 356.848 | H59: =SUM(H57:H58) -> 378.665 | I59: =SUM(I57:I58) -> 512.969 | J59: =SUM(J57:J58) -> 553.139 | K59: =SUM(K57:K58) -> 624.1869 | L59: =SUM(L57:L58) -> 704.69969 | M59: =SUM(M57:M58) -> 795.97787 | ... O59: =SUM(O57:O58) -> 1016.9745
B60: % Y-O-Y Growth | G60: =G59/F59-1 -> -0.33292207 | H60: =H59/G59-1 -> 0.061138076 | I60: =I59/H59-1 -> 0.35467762 | J60: =J59/I59-1 -> 0.078308826 | K60: =K59/J59-1 -> 0.12844493 | L60: =L59/K59-1 -> 0.12898827 | M60: =M59/L59-1 -> 0.12952778 | N60: =N59/M59-1 -> 0.13006296 | O60: =O59/N59-1 -> 0.13059334
B62: (–) Product COGS | D62: =SUM(K62:O62) -> -1040.9085 | F62: ='Historical Financials'!D18 -> -141.08299 | G62: ='Historical Financials'!E18 -> -101.54867 | H62: ='Historical Financials'!F18 -> -85.732825 | I62: ='Historical Financials'!G18 -> -140.56916 | J62: ='Historical Financials'!H18 -> -158.4088 | K62: ='P&L Drivers'!I41 -> -170.49819 | L62: ='P&L Drivers'!J41 -> -187.548 | M62: ='P&L Drivers'!K41 -> -206.3028 | N62: ='P&L Drivers'!L41 -> -226.93308 | O62: ='P&L Drivers'!M41 -> -249.62639
B63: (–) Services COGS | D63: =SUM(K63:O63) -> -1585.9652 | F63: ='Historical Financials'!D19 -> -227.01605 | G63: ='Historical Financials'!E19 -> -184.62581 | H63: ='Historical Financials'!F19 -> -185.29518 | I63: ='Historical Financials'!G19 -> -229.76384 | J63: ='Historical Financials'!H19 -> -219.6612 | K63: ='P&L Drivers'!I52 -> -235.2233 | L63: ='P&L Drivers'!J52 -> -270.5068 | M63: ='P&L Drivers'!K52 -> -311.08281 | N63: ='P&L Drivers'!L52 -> -357.74524 | O63: ='P&L Drivers'!M52 -> -411.40702
B64: Gross Profit | D64: =SUM(K64:O64) -> 1414.4704 | E64: =RATE($O$55-$K$55,0,-$K64,$O64) -> 0.12979293 | F64: =SUM(F59,F62:F63) -> 166.84297 | G64: =SUM(G59,G62:G63) -> 70.673517 | H64: =SUM(H59,H62:H63) -> 107.637 | I64: =SUM(I59,I62:I63) -> 142.636 | J64: =SUM(J59,J62:J63) -> 175.069 | K64: =SUM(K59,K62:K63) -> 218.46541 | L64: =SUM(L59,L62:L63) -> 246.64489 | M64: =SUM(M59,M62:M63) -> 278.59226 | ... O64: =SUM(O59,O62:O63) -> 355.94107
B65: Gross Margin % | D65: =D64/D$59 -> 0.35 | F65: =F64/F59 -> 0.31188983 | G65: =G64/G59 -> 0.19804936 | H65: =H64/H59 -> 0.28425389 | I65: =I64/I59 -> 0.27805969 | J65: =J64/J59 -> 0.31650092 | K65: =K64/K59 -> 0.35 | L65: =L64/L59 -> 0.35 | M65: =M64/M59 -> 0.35 | ... O65: =O64/O59 -> 0.35
B67: (–) SG&A | D67: =SUM(K67:O67) -> -404.13441 | F67: ='Historical Financials'!D23 -> -49.069 | G67: ='Historical Financials'!E23 -> -43.735 | H67: ='Historical Financials'!F23 -> -47.117 | I67: ='Historical Financials'!G23 -> -49.146 | J67: ='Historical Financials'!H23 -> -44.828 | K67: ='P&L Drivers'!I63 -> -62.41869 | L67: ='P&L Drivers'!J63 -> -70.469969 | M67: ='P&L Drivers'!K63 -> -79.597787 | N67: ='P&L Drivers'!L63 -> -89.950511 | O67: ='P&L Drivers'!M63 -> -101.69745
B68: (–) R&D | D68: =SUM(K68:O68) -> -80.826881 | F68: ='Historical Financials'!D24 -> -11.049 | G68: ='Historical Financials'!E24 -> -7.431 | H68: ='Historical Financials'!F24 -> -9.075 | I68: ='Historical Financials'!G24 -> -12.512 | J68: ='Historical Financials'!H24 -> -10.457 | K68: ='P&L Drivers'!I74 -> -12.483738 | L68: ='P&L Drivers'!J74 -> -14.093994 | M68: ='P&L Drivers'!K74 -> -15.919557 | N68: ='P&L Drivers'!L74 -> -17.990102 | O68: ='P&L Drivers'!M74 -> -20.33949
B69: EBITDA | D69: =SUM(K69:O69) -> 929.50913 | E69: =RATE($O$55-$K$55,0,-$K69,$O69) -> 0.12979293 | F69: =F64+SUM(F67:F68) -> 106.72497 | G69: =G64+SUM(G67:G68) -> 19.507517 | H69: =H64+SUM(H67:H68) -> 51.445 | I69: =I64+SUM(I67:I68) -> 80.978 | J69: =J64+SUM(J67:J68) -> 119.784 | K69: =K64+SUM(K67:K68) -> 143.56299 | L69: =L64+SUM(L67:L68) -> 162.08093 | M69: =M64+SUM(M67:M68) -> 183.07491 | ... O69: =O64+SUM(O67:O68) -> 233.90413
B70: EBITDA Margin % | D70: =D69/D$59 -> 0.23 | F70: =F69/F59 -> 0.19950755 | G70: =G69/G59 -> 0.05466618 | H70: =H69/H59 -> 0.13585887 | I70: =I69/I59 -> 0.15786139 | J70: =J69/J59 -> 0.21655316 | K70: =K69/K59 -> 0.23 | L70: =L69/L59 -> 0.23 | M70: =M69/M59 -> 0.23 | ... O70: =O69/O59 -> 0.23
B72: (–) D&A | D72: =SUM(K72:O72) -> -438.60232 | F72: ='Historical Financials'!D28 -> -31.877967 | G72: ='Historical Financials'!E28 -> -33.936517 | H72: ='Historical Financials'!F28 -> -36.128 | I72: ='Historical Financials'!G28 -> -38.461 | J72: ='Historical Financials'!H28 -> -42.989 | K72: ='P&L Drivers'!I85 -> -56.176821 | L72: ='P&L Drivers'!J85 -> -71.879368 | M72: ='P&L Drivers'!K85 -> -85.96561 | N72: ='P&L Drivers'!L85 -> -102.54358 | O72: ='P&L Drivers'!M85 -> -122.03694
B73: (–) Amort of Acquisition Intangibles | D73: =SUM(K73:O73) -> -9.19485 | F73: 0 | G73: 0 | H73: 0 | I73: 0 | J73: 0 | K73: =$O$25 -> -1.83897 | L73: =$O$25 -> -1.83897 | M73: =$O$25 -> -1.83897 | N73: =$O$25 -> -1.83897 | O73: =$O$25 -> -1.83897
B74: (–) Amort of Capitalized Financing Fees | D74: =SUM(K74:O74) -> 0 | F74: 0 | G74: 0 | H74: 0 | I74: 0 | J74: 0
B75: (–) Amort of OID | D75: =SUM(K75:O75) -> 0 | F75: 0 | G75: 0 | H75: 0 | I75: 0 | J75: 0
B76: Earnings Before Interest & Taxes (EBIT) | D76: =SUM(K76:O76) -> 481.71196 | E76: =RATE($O$55-$K$55,0,-$K76,$O76) -> 0.064938628 | F76: =SUM(F69,F72:F75) -> 74.847 | G76: =SUM(G69,G72:G75) -> -14.429 | H76: =SUM(H69,H72:H75) -> 15.317 | I76: =SUM(I69,I72:I75) -> 42.517 | J76: =SUM(J69,J72:J75) -> 76.795 | K76: =SUM(K69,K72:K75) -> 85.547196 | L76: =SUM(L69,L72:L75) -> 88.36259 | M76: =SUM(M69,M72:M75) -> 95.270331 | ... O76: =SUM(O69,O72:O75) -> 110.02822
B77: EBIT Margin % | D77: =D97/D$59 -> 0.20449105 | F77: =F76/F59 -> 0.1399161 | G77: =G76/G59 -> -0.040434583 | H77: =H76/H59 -> 0.040450002 | I77: =I76/I59 -> 0.082884151 | J77: =J76/J59 -> 0.1388349 | K77: =K76/K59 -> 0.13705382 | L77: =L76/L59 -> 0.12539042 | M77: =M76/M59 -> 0.11968967 | ... O77: =O76/O59 -> 0.10819172
B79: (–) Interest Expense | D79: =SUM(K79:O79) -> 0 | F79: ='Historical Financials'!D32 -> -2.5 | G79: ='Historical Financials'!E32 -> -2.9 | H79: ='Historical Financials'!F32 -> -3.3 | I79: ='Historical Financials'!G32 -> -3.7 | J79: ='Historical Financials'!H32 -> -4.1
B80: Income (Loss) Before Income Taxes | D80: =SUM(K80:O80) -> 481.71196 | F80: =SUM(F76,F79) -> 72.347 | G80: =SUM(G76,G79) -> -17.329 | H80: =SUM(H76,H79) -> 12.017 | I80: =SUM(I76,I79) -> 38.817 | J80: =SUM(J76,J79) -> 72.695 | K80: =SUM(K76,K79) -> 85.547196 | L80: =SUM(L76,L79) -> 88.36259 | M80: =SUM(M76,M79) -> 95.270331 | ... O80: =SUM(O76,O79) -> 110.02822
B81: (–) Income Taxes | D81: =SUM(K81:O81) -> -101.15951 | F81: ='Historical Financials'!D34 -> -20.849 | G81: ='Historical Financials'!E34 -> 12.34 | H81: ='Historical Financials'!F34 -> -6.777 | I81: ='Historical Financials'!G34 -> -14.276 | J81: ='Historical Financials'!H34 -> -24.781 | K81: =-PRODUCT(K$80,$E$10) -> -17.964911 | L81: =-PRODUCT(L$80,$E$10) -> -18.556144 | M81: =-PRODUCT(M$80,$E$10) -> -20.006769 | N81: =-PRODUCT(N$80,$E$10) -> -21.525761 | O81: =-PRODUCT(O$80,$E$10) -> -23.105927
B82: Net Income | D82: =SUM(K82:O82) -> 380.55245 | E82: =RATE($O$55-$K$55,0,-$K82,$O82) -> 0.064938628 | F82: =SUM(F80:F81) -> 51.498 | G82: =SUM(G80:G81) -> -4.989 | H82: =SUM(H80:H81) -> 5.24 | I82: =SUM(I80:I81) -> 24.541 | J82: =SUM(J80:J81) -> 47.914 | K82: =SUM(K80:K81) -> 67.582285 | L82: =SUM(L80:L81) -> 69.806446 | M82: =SUM(M80:M81) -> 75.263561 | ... O82: =SUM(O80:O81) -> 86.922296
B83: Net Income Margin % | D83: =D82/D$59 -> 0.094164824 | F83: =F82/F59 -> 0.09626838 | G83: =G82/G59 -> -0.013980743 | H83: =H82/H59 -> 0.013838089 | I83: =I82/I59 -> 0.047841098 | J83: =J82/J59 -> 0.086621988 | K83: =K82/K59 -> 0.10827251 | L83: =L82/L59 -> 0.099058432 | M83: =M82/M59 -> 0.094554841 | ... O83: =O82/O59 -> 0.085471462
A85: x | B85: Cash Flow Statement | P85: x
F87: Historical FYE | K87: Projected FYE
D88: ="'19E - '23E Total" -> '19E - '23E Total | E88: ="'19E - '23E CAGR" -> '19E - '23E CAGR | F88: 42004 | G88: =EOMONTH(F88,12) -> 42369 | H88: =EOMONTH(G88,12) -> 42735 | I88: =EOMONTH(H88,12) -> 43100 | J88: =EOMONTH(I88,12) -> 43465 | K88: =EOMONTH(J88,12) -> 43830 | L88: =EOMONTH(K88,12) -> 44196 | M88: =EOMONTH(L88,12) -> 44561 | N88: =EOMONTH(M88,12) -> 44926 | O88: =EOMONTH(N88,12) -> 45291
F89: =YEAR(F88) -> 2014 | G89: =YEAR(G88) -> 2015 | H89: =YEAR(H88) -> 2016 | I89: =YEAR(I88) -> 2017 | J89: =YEAR(J88) -> 2018 | K89: =YEAR(K88) -> 2019 | L89: =YEAR(L88) -> 2020 | M89: =YEAR(M88) -> 2021 | ... O89: =YEAR(O88) -> 2023
B91: Net Income | D91: =SUM(K91:O91) -> 380.55245 | F91: =F82 -> 51.498 | G91: =G82 -> -4.989 | H91: =H82 -> 5.24 | I91: =I82 -> 24.541 | J91: =J82 -> 47.914 | K91: =K82 -> 67.582285 | L91: =L82 -> 69.806446 | M91: =M82 -> 75.263561 | ... O91: =O82 -> 86.922296
B92: (+) Depreciation & Amortization | D92: =SUM(K92:O92) -> 438.60232 | F92: =-F72 -> 31.877967 | G92: =-G72 -> 33.936517 | H92: =-H72 -> 36.128 | I92: =-I72 -> 38.461 | J92: =-J72 -> 42.989 | K92: =-K72 -> 56.176821 | L92: =-L72 -> 71.879368 | M92: =-M72 -> 85.96561 | ... O92: =-O72 -> 122.03694
B93: (+) Amort of Acquisition Intangibles | D93: =SUM(K93:O93) -> 9.19485 | F93: 0 | G93: 0 | H93: 0 | I93: 0 | J93: 0 | K93: =-K73 -> 1.83897 | L93: =-L73 -> 1.83897 | M93: =-M73 -> 1.83897 | N93: =-N73 -> 1.83897 | O93: =-O73 -> 1.83897
B94: (+) Amort of Capitalized Financing Fees | D94: =SUM(K94:O94) -> 0 | F94: 0 | G94: 0 | H94: 0 | I94: 0 | J94: 0 | K94: =-K74 -> 0 | L94: =-L74 -> 0 | M94: =-M74 -> 0 | N94: =-N74 -> 0 | O94: =-O74 -> 0
B95: (+) Amort of OID | D95: =SUM(K95:O95) -> 0 | F95: 0 | G95: 0 | H95: 0 | I95: 0 | J95: 0 | K95: =-K75 -> 0 | L95: =-L75 -> 0 | M95: =-M75 -> 0 | N95: =-N75 -> 0 | O95: =-O75 -> 0
B96: (+/–) Δ in Deferred Tax Liabilities | D96: =SUM(K96:O96) -> -1.9309185 | F96: =-SUM(F93:F95)*$E$10 -> 0 | G96: =-SUM(G93:G95)*$E$10 -> 0 | H96: =-SUM(H93:H95)*$E$10 -> 0 | I96: =-SUM(I93:I95)*$E$10 -> 0 | J96: =-SUM(J93:J95)*$E$10 -> 0 | K96: =-SUM(K93:K95)*$E$10 -> -0.3861837 | L96: =-SUM(L93:L95)*$E$10 -> -0.3861837 | M96: =-SUM(M93:M95)*$E$10 -> -0.3861837 | ... O96: =-SUM(O93:O95)*$E$10 -> -0.3861837
B97: Funds from Operations (FFO) | D97: =SUM(K97:O97) -> 826.4187 | E97: =RATE($O$89-$K$89,0,-$K97,$O97) -> 0.13856084 | F97: =SUM(F91:F96) -> 83.375967 | G97: =SUM(G91:G96) -> 28.947517 | H97: =SUM(H91:H96) -> 41.368 | I97: =SUM(I91:I96) -> 63.002 | J97: =SUM(J91:J96) -> 90.903 | K97: =SUM(K91:K96) -> 125.21189 | L97: =SUM(L91:L96) -> 143.1386 | M97: =SUM(M91:M96) -> 162.68196 | ... O97: =SUM(O91:O96) -> 210.41202
B98: (+/–) Δ in NWC | D98: =SUM(K98:O98) -> -120.79764 | F98: ='Capex & NWC Drivers'!D50 -> -8.7 | G98: ='Capex & NWC Drivers'!E50 -> -12.352 | H98: ='Capex & NWC Drivers'!F50 -> 20.255 | I98: ='Capex & NWC Drivers'!G50 -> -55.67 | J98: ='Capex & NWC Drivers'!H50 -> -49.903 | K98: ='Capex & NWC Drivers'!I50 -> 2.2405123 | L98: ='Capex & NWC Drivers'!J50 -> -25.220108 | M98: ='Capex & NWC Drivers'!K50 -> -28.592298 | ... O98: ='Capex & NWC Drivers'!M50 -> -36.796518
B99: Cash Flow from Operations (CFO) | D99: =SUM(K78:O78) -> 0 | E99: =RATE($O$89-$K$89,0,-$K99,$O99) -> 0.080339157 | F99: =SUM(F97:F98) -> 74.675967 | G99: =SUM(G97:G98) -> 16.595517 | H99: =SUM(H97:H98) -> 61.623 | I99: =SUM(I97:I98) -> 7.332 | J99: =SUM(J97:J98) -> 41 | K99: =SUM(K97:K98) -> 127.4524 | L99: =SUM(L97:L98) -> 117.91849 | M99: =SUM(M97:M98) -> 134.08966 | ... O99: =SUM(O97:O98) -> 173.6155
B101: (–) Capital Expenditures | D101: =SUM(K101:O101) -> -484.96129 | F101: ='Capex & NWC Drivers'!D17 -> -52.373218 | G101: ='Capex & NWC Drivers'!E17 -> -34.937018 | H101: ='Capex & NWC Drivers'!F17 -> -37.073 | I101: ='Capex & NWC Drivers'!G17 -> -47.387 | J101: ='Capex & NWC Drivers'!H17 -> -63.662 | K101: ='Capex & NWC Drivers'!I17 -> -74.902428 | L101: ='Capex & NWC Drivers'!J17 -> -84.563963 | M101: ='Capex & NWC Drivers'!K17 -> -95.517345 | ... O101: ='Capex & NWC Drivers'!M17 -> -122.03694
B102: (+) Asset Sales | D102: =SUM(K102:O102) -> 0 | F102: ='Historical Financials'!D106 -> 0 | G102: ='Historical Financials'!E106 -> 19.734501 | H102: ='Historical Financials'!F106 -> 4.723 | I102: ='Historical Financials'!G106 -> 0 | J102: ='Historical Financials'!H106 -> 27.971 | K102: 0 | L102: 0 | M102: 0 | N102: 0 | O102: 0
B103: Cash Flow from Investing (CFI) | D103: =SUM(K82:O82) -> 380.55245 | F103: =SUM(F101:F102) -> -52.373218 | G103: =SUM(G101:G102) -> -15.202517 | H103: =SUM(H101:H102) -> -32.35 | I103: =SUM(I101:I102) -> -47.387 | J103: =SUM(J101:J102) -> -35.691 | K103: =SUM(K101:K102) -> -74.902428 | L103: =SUM(L101:L102) -> -84.563963 | M103: =SUM(M101:M102) -> -95.517345 | ... O103: =SUM(O101:O102) -> -122.03694
B105: (+/–) Debt Issued / (Retired) | D105: =SUM(K105:O105) -> 0 | F105: ='Historical Financials'!D109 -> 6 | G105: ='Historical Financials'!E109 -> 2.6 | H105: ='Historical Financials'!F109 -> -8.6 | I105: ='Historical Financials'!G109 -> 6.625 | J105: ='Historical Financials'!H109 -> -6.364
B106: (+/–) Common Stock Issued / (Retired) | D106: =SUM(K106:O106) -> 0 | F106: ='Historical Financials'!D110 -> 0 | G106: ='Historical Financials'!E110 -> 0 | H106: ='Historical Financials'!F110 -> 0 | I106: ='Historical Financials'!G110 -> 0 | J106: ='Historical Financials'!H110 -> 0 | K106: 0 | L106: 0 | M106: 0 | N106: 0 | O106: 0
B107: (–) Dividends Paid | D107: =SUM(K107:O107) -> 0 | F107: ='Historical Financials'!D111 -> 0 | G107: ='Historical Financials'!E111 -> 0 | H107: ='Historical Financials'!F111 -> 0 | I107: ='Historical Financials'!G111 -> -4.104 | J107: ='Historical Financials'!H111 -> 0 | K107: =K170 -> 0 | L107: =L170 -> 0 | M107: =M170 -> 0 | N107: =N170 -> 0 | O107: =O170 -> 0
B108: Cash Flow from Financing (CFF) | D108: =SUM(K87:O87) -> 0 | F108: =SUM(F105:F107) -> 6 | G108: =SUM(G105:G107) -> 2.6 | H108: =SUM(H105:H107) -> -8.6 | I108: =SUM(I105:I107) -> 2.521 | J108: =SUM(J105:J107) -> -6.364 | K108: =SUM(K105:K107) -> 0 | L108: =SUM(L105:L107) -> 0 | M108: =SUM(M105:M107) -> 0 | ... O108: =SUM(O105:O107) -> 0
B110: Change in Cash | F110: =SUM(F99,F103,F108) -> 28.302749 | G110: =SUM(G99,G103,G108) -> 3.993 | H110: =SUM(H99,H103,H108) -> 20.673 | I110: =SUM(I99,I103,I108) -> -37.534 | J110: =SUM(J99,J103,J108) -> -1.055 | K110: =SUM(K99,K103,K108) -> 52.549976 | L110: =SUM(L99,L103,L108) -> 33.35453 | M110: =SUM(M99,M103,M108) -> 38.572315 | ... O110: =SUM(O99,O103,O108) -> 51.578565
B112: Levered Free Cash Flow (excluding principal repayment) | F112: =F99+F103 -> 22.302749 | G112: =G99+G103 -> 1.393 | H112: =H99+H103 -> 29.273 | I112: =I99+I103 -> -40.055 | J112: =J99+J103 -> 5.309 | K112: =K99+K103 -> 52.549976 | L112: =L99+L103 -> 33.35453 | M112: =M99+M103 -> 38.572315 | ... O112: =O99+O103 -> 51.578565
B113: LFCF Conversion % | F113: =F112/F69 -> 0.20897405 | G113: =G112/G69 -> 0.07140837 | H113: =H112/H69 -> 0.56901545 | I113: =I112/I69 -> -0.49464052 | J113: =J112/J69 -> 0.044321445 | K113: =K112/K69 -> 0.36604126 | L113: =L112/L69 -> 0.20578936 | M113: =M112/M69 -> 0.21069143 | ... O113: =O112/O69 -> 0.22051156
A115: x | B115: Balance Sheet | P115: x
G117: Historical FYE | K117: Projected FYE
G118: 43465 | H118: Transaction Adjustments | J118: 43465 | K118: =EOMONTH(J118,12) -> 43830 | L118: =EOMONTH(K118,12) -> 44196 | M118: =EOMONTH(L118,12) -> 44561 | N118: =EOMONTH(M118,12) -> 44926 | O118: =EOMONTH(N118,12) -> 45291
G119: 2018 | H119: + | I119: – | J119: =YEAR(J118) -> 2018 | K119: =YEAR(K118) -> 2019 | L119: =YEAR(L118) -> 2020 | M119: =YEAR(M118) -> 2021 | N119: =YEAR(N118) -> 2022 | O119: =YEAR(O118) -> 2023
B121: Assets
B123: Cash and Cash Equivalents | G123: ='Historical Financials'!H45 -> 22.014 | J123: =SUM(G123:I123) -> 22.014 | K123: =J123+K110 -> 74.563976 | L123: =K123+L110 -> 107.91851 | M123: =L123+M110 -> 146.49082 | N123: =M123+N110 -> 191.09521 | O123: =N123+O110 -> 242.67377
B124: Accounts Receivable | G124: ='Historical Financials'!H46 -> 130.769 | J124: =SUM(G124:I124) -> 130.769 | K124: ='Capex & NWC Drivers'!I35 -> 145.2591 | L124: ='Capex & NWC Drivers'!J35 -> 163.99582 | M124: ='Capex & NWC Drivers'!K35 -> 185.23784 | N124: ='Capex & NWC Drivers'!L35 -> 209.33042 | O124: ='Capex & NWC Drivers'!M35 -> 236.66757
B125: Inventory | G125: ='Historical Financials'!H47 -> 124.506 | J125: =SUM(G125:I125) -> 124.506 | K125: ='Capex & NWC Drivers'!I36 -> 111.08049 | L125: ='Capex & NWC Drivers'!J36 -> 125.40857 | M125: ='Capex & NWC Drivers'!K36 -> 141.65246 | N125: ='Capex & NWC Drivers'!L36 -> 160.0762 | O125: ='Capex & NWC Drivers'!M36 -> 180.98109
B126: Income Tax Recoverable | G126: ='Historical Financials'!H48 -> 4.228 | J126: =SUM(G126:I126) -> 4.228 | K126: ='Capex & NWC Drivers'!I37 -> 6.241869 | L126: ='Capex & NWC Drivers'!J37 -> 7.0469969 | M126: ='Capex & NWC Drivers'!K37 -> 7.9597787 | N126: ='Capex & NWC Drivers'!L37 -> 8.9950511 | O126: ='Capex & NWC Drivers'!M37 -> 10.169745
B127: Deferred Income Taxes | G127: ='Historical Financials'!H49 -> 4.367 | J127: =SUM(G127:I127) -> 4.367 | K127: ='Capex & NWC Drivers'!I38 -> 9.3628035 | L127: ='Capex & NWC Drivers'!J38 -> 10.570495 | M127: ='Capex & NWC Drivers'!K38 -> 11.939668 | N127: ='Capex & NWC Drivers'!L38 -> 13.492577 | O127: ='Capex & NWC Drivers'!M38 -> 15.254617
B128: Prepaid Expenses and Other Assets | G128: ='Historical Financials'!H50 -> 40.331 | J128: =SUM(G128:I128) -> 40.331 | K128: ='Capex & NWC Drivers'!I39 -> 34.486326 | L128: ='Capex & NWC Drivers'!J39 -> 38.934658 | M128: ='Capex & NWC Drivers'!K39 -> 43.977778 | N128: ='Capex & NWC Drivers'!L39 -> 49.697657 | O128: ='Capex & NWC Drivers'!M39 -> 56.18784
B129: Total Current Assets | G129: =SUM(G123:G128) -> 326.215 | J129: =SUM(J123:J128) -> 326.215 | K129: =SUM(K123:K128) -> 380.99456 | L129: =SUM(L123:L128) -> 453.87505 | M129: =SUM(M123:M128) -> 537.25834 | N129: =SUM(N123:N128) -> 632.68711 | O129: =SUM(O123:O128) -> 741.93463
B131: Net Plant, Property, & Equipment (PP&E) | G131: ='Historical Financials'!H53 -> 209.933 | J131: =SUM(G131:I131) -> 209.933 | K131: =J131-K101+K72 -> 228.65861 | L131: =K131-L101+L72 -> 241.3432 | M131: =L131-M101+M72 -> 250.89494 | N131: =M131-N101+N72 -> 256.29197 | O131: =N131-O101+O72 -> 256.29197
B132: Goodwill | G132: ='Historical Financials'!H54 -> 32.732 | H132: =$O$21 -> 162.10521 | I132: =-G132 -> -32.732 | J132: =SUM(G132:I132) -> 162.10521 | K132: =J132 -> 162.10521 | L132: =K132 -> 162.10521 | M132: =L132 -> 162.10521 | N132: =M132 -> 162.10521 | O132: =N132 -> 162.10521
B133: Deferred Income Taxes | G133: ='Historical Financials'!H55 -> 11.792 | J133: =SUM(G133:I133) -> 11.792 | K133: =J133 -> 11.792 | L133: =K133 -> 11.792 | M133: =L133 -> 11.792 | N133: =M133 -> 11.792 | O133: =N133 -> 11.792
B134: Intangible and Other Assets | G134: ='Historical Financials'!H56 -> 6.438 | H134: =-$O$23 -> 27.58455 | J134: =SUM(G134:I134) -> 34.02255 | K134: =J134+K73 -> 32.18358 | L134: =K134+L73 -> 30.34461 | M134: =L134+M73 -> 28.50564 | N134: =M134+N73 -> 26.66667 | O134: =N134+O73 -> 24.8277
...
