Workbook

Sheet Input
B2: PROPERTY OVERVIEW | H2: ASSUMPTIONS | Y2: SUMMARY
B3: Property Name | C3: Waverider
B4: Keys | C4: 182 | H4: ENTRY | O4: EXIT | T4: FINANCING | Y4: SUMMARY TABLE
B5: Scale | C5: Full Service | E5: Labor / Tenure | F5: Fee Simple / Non-Union | H5: Purchase Price | I5: 48000000 | J5: =I5/$C$4 -> 263736.26 | K5: Guidance | L5: 50000000 | M5: =L5/$C$4 -> 274725.27 | O5: Sale Price | P5: =INDEX(M16:W45,28,MATCH(P8,M16:W16,0))/P6 -> 78512207 | Q5: =P5/$C$4 -> 431385.75 | T5: Loan Proceeds / LTC | U5: =V5*I10 -> 33536990 | V5: 0.65 | Y5: Property | AB5: =+C3 -> Waverider
B6: Year Opened | C6: 2022 | E6: Last Reno | F6: 2022 | H6: =J6& " Going-In Cap Rate" -> 2023 Going-In Cap Rate | I6: =$M$6/I5 -> 0.039958836 | J6: 2023 | K6: <--Input | M6: =INDEX(I43:K43,MATCH(J6,I17:K17,0)) -> 1918024.1 | O6: Exit Cap Rate | P6: 0.08 | Q6: =P6*100 -> 8 | T6: Financing Costs | U6: =U5*V6 -> 335369.9 | V6: 0.01 | Y6: Keys | AB6: =+C4 -> 182
B7: Seller | C7: Seller | E7: Brand | F7: TBD | H7: Closing Costs | I7: =J7*I5 -> 1440000 | J7: 0.03 | O7: Hold Period | P7: 5 | T7: Interest Rate | U7: 0.075 | Y7: Seller | AB7: =+C7 -> Seller
B8: CapEx (Historical) | C8: 20000000 | D8: =C8/C4 -> 109890.11 | E8: Term | F8: 2022 | H8: Renovation | I8: =J8*C4 -> 1820000 | J8: 10000 | O8: Exit | P8: =P7 -> 5 | T8: IO | U8: Yes | Y8: Current Management | AB8: =C10 -> Manager
B9: Seller's Basis | C9: 100000000 | D9: =IFERROR(I5/C9-1,"") -> -0.52 | H9: Financing Costs | I9: =U6 -> 335369.9 | J9: Note: This is the Interest Reserve (linked to respective Amort Tab) | O9: Selling Costs | P9: =Q9*P5 -> 1570244.1 | Q9: 0.02 | T9: IO TERM | U9: 5
B10: Manager | C10: Manager | H10: Total Acquisition Costs | I10: =I5+I7+I8+I9 -> 51595370 | J10: =I10/$C$4 -> 283491.04 | O10: Net Proceeds | P10: =P5-P9 -> 76941963 | Q10: =P10/$C$4 -> 422758.04 | T10: Amort Period | U10: 30
B11: Acquisition Date | C11: 45444 | H11: =J6& " Going-In Cap Rate" -> 2023 Going-In Cap Rate | I11: =$M$6/I10 -> 0.037174346 | Y11: =+H5 -> Purchase Price | AB11: =+I5 -> 48000000
Y12: Per Key | AB12: =+AB11/AB6 -> 263736.26
B13: SOURCES & USES | H13: PROFORMA WALKDOWN | Y13: =H6 -> 2023 Going-In Cap Rate | AB13: =I6 -> 0.039958836
B14: SOURCES | H14: OPERATING ASSUMPTIONS
B15: Closing | M15: =YEAR(M17) -> 2025 | N15: =M15+1 -> 2026 | O15: =N15+1 -> 2027 | P15: =O15+1 -> 2028 | Q15: =P15+1 -> 2029 | R15: =Q15+1 -> 2030 | S15: =R15+1 -> 2031 | T15: =S15+1 -> 2032 | U15: =T15+1 -> 2033 | ... W15: =V15+1 -> 2035 | Y15: Last Reno | AB15: =+F6 -> 2022
B16: Debt | C16: =IF(M8=0,U5,(I5+I7)*V5) -> 33536990 | D16: =C16/$C$18 -> 0.65 | I16: ACT | J16: A/F | K16: Budget | M16: =1 -> 1 | N16: =M16+1 -> 2 | O16: =N16+1 -> 3 | P16: =O16+1 -> 4 | Q16: =P16+1 -> 5 | R16: =Q16+1 -> 6 | S16: =R16+1 -> 7 | T16: =S16+1 -> 8 | U16: =T16+1 -> 9 | ... W16: =V16+1 -> 11 | Y16: Capex Assumption | AB16: =+J8 -> 10000
B17: Equity | C17: =IF(M8=0,I10-U5,(I5+I7)*(1-V5)+I9) -> 18058379 | D17: =C17/$C$18 -> 0.35 | I17: 2022 | J17: 2023 | K17: 2024 | L17: =C11 -> 45444 | M17: =EOMONTH(Input!C11,12) -> 45838 | N17: =EOMONTH(M17,12) -> 46203 | O17: =EOMONTH(N17,12) -> 46568 | P17: =EOMONTH(O17,12) -> 46934 | Q17: =EOMONTH(P17,12) -> 47299 | R17: =EOMONTH(Q17,12) -> 47664 | S17: =EOMONTH(R17,12) -> 48029 | T17: =EOMONTH(S17,12) -> 48395 | U17: =EOMONTH(T17,12) -> 48760 | ... W17: =EOMONTH(V17,12) -> 49490
B18: Total | C18: =SUM(C16:C17) -> 51595370 | D18: =C18/SUM(C18,C23) -> 1 | H18: # Days open | M18: =IF(M16<=$P$8,1*IF(IF(MOD(YEAR(M17),4)=0,IF(MOD(YEAR(M17),100)=0,IF(MOD(YEAR(M17),400)=0,TRUE,FALSE),TRUE),FALSE)=TRUE,366,365),0) -> 365 | N18: =IF(N16<=$P$8,1*IF(IF(MOD(YEAR(N17),4)=0,IF(MOD(YEAR(N17),100)=0,IF(MOD(YEAR(N17),400)=0,TRUE,FALSE),TRUE),FALSE)=TRUE,366,365),0) -> 365 | O18: =IF(O16<=$P$8,1*IF(IF(MOD(YEAR(O17),4)=0,IF(MOD(YEAR(O17),100)=0,IF(MOD(YEAR(O17),400)=0,TRUE,FALSE),TRUE),FALSE)=TRUE,366,365),0) -> 365 | P18: =IF(P16<=$P$8,1*IF(IF(MOD(YEAR(P17),4)=0,IF(MOD(YEAR(P17),100)=0,IF(MOD(YEAR(P17),400)=0,TRUE,FALSE),TRUE),FALSE)=TRUE,366,365),0) -> 366 | Q18: =IF(Q16<=$P$8,1*IF(IF(MOD(YEAR(Q17),4)=0,IF(MOD(YEAR(Q17),100)=0,IF(MOD(YEAR(Q17),400)=0,TRUE,FALSE),TRUE),FALSE)=TRUE,366,365),0) -> 365 | R18: =IF(R16<=$P$8,1*IF(IF(MOD(YEAR(R17),4)=0,IF(MOD(YEAR(R17),100)=0,IF(MOD(YEAR(R17),400)=0,TRUE,FALSE),TRUE),FALSE)=TRUE,366,365),0) -> 0 | S18: =IF(S16<=$P$8,1*IF(IF(MOD(YEAR(S17),4)=0,IF(MOD(YEAR(S17),100)=0,IF(MOD(YEAR(S17),400)=0,TRUE,FALSE),TRUE),FALSE)=TRUE,366,365),0) -> 0 | T18: =IF(T16<=$P$8,1*IF(IF(MOD(YEAR(T17),4)=0,IF(MOD(YEAR(T17),100)=0,IF(MOD(YEAR(T17),400)=0,TRUE,FALSE),TRUE),FALSE)=TRUE,366,365),0) -> 0 | ... W18: =IF(W16<=$P$8,1*IF(IF(MOD(YEAR(W17),4)=0,IF(MOD(YEAR(W17),100)=0,IF(MOD(YEAR(W17),400)=0,TRUE,FALSE),TRUE),FALSE)=TRUE,366,365),0) -> 0 | Y18: =H10 -> Total Acquisition Costs | AB18: =I10 -> 51595370
H19: # Rooms available | M19: =M18*$C$4 -> 66430 | N19: =N18*$C$4 -> 66430 | O19: =O18*$C$4 -> 66430 | P19: =P18*$C$4 -> 66612 | Q19: =Q18*$C$4 -> 66430 | R19: =R18*$C$4 -> 0 | S19: =S18*$C$4 -> 0 | T19: =T18*$C$4 -> 0 | ... W19: =W18*$C$4 -> 0 | Y19: Per Key | AB19: =+AB18/AB6 -> 283491.04
B20: Post-Closing | H20: # Occupied Rooms | M20: =M19*M22 -> 49158.2 | N20: =N19*N22 -> 40522.3 | O20: =O19*O22 -> 41718.04 | P20: =P19*P22 -> 43963.92 | Q20: =Q19*Q22 -> 43843.8 | R20: =R19*R22 -> 0 | S20: =S19*S22 -> 0 | T20: =T19*T22 -> 0 | ... W20: =W19*W22 -> 0 | Y20: =+H11 -> 2023 Going-In Cap Rate | AB20: =+I11 -> 0.037174346
B21: Debt | C21: =IF(M8=0,0,I8*V5) -> 0 | D21: =IFERROR(C21/$C$23,0) -> 0
B22: Equity | C22: =IF(M8=0,0,I8-C21) -> 0 | D22: =IFERROR(C22/$C$23,0) -> 0 | H22: Occupancy | I22: 0.728 | J22: 0.735 | K22: 0.65 | M22: 0.74 | N22: 0.61 | O22: 0.628 | P22: 0.66 | Q22: 0.66 | R22: =Q22 -> 0.66 | S22: =R22 -> 0.66 | T22: =S22 -> 0.66 | U22: =T22 -> 0.66 | V22: =U22 -> 0.66 | W22: =V22 -> 0.66 | Y22: LTV | AB22: =+V5 -> 0.65
B23: Total | C23: =SUM(C21:C22) -> 0 | D23: =C23/SUM(C23,C18) -> 0 | H23: ADR | I23: 363.87 | J23: 356.82 | K23: 450 | M23: 363.87 | N23: =M23*(1+N24) -> 365.68935 | O23: =N23*(1+O24) -> 379.59238 | P23: =O23*(1+P24) -> 391.33902 | Q23: =P23*(1+Q24) -> 401.12249 | R23: =Q23*(1+R24) -> 411.15056 | S23: =R23*(1+S24) -> 421.42932 | T23: =S23*(1+T24) -> 431.96505 | U23: =T23*(1+U24) -> 442.76418 | ... W23: =V23*(1+W24) -> 465.17911 | Y23: All-in Interest Rate | AB23: =+U7 -> 0.075
H24: ADR % Change | N24: 0.005 | O24: 0.038018683 | P24: 0.030945405 | Q24: 0.025 | R24: =Q24 -> 0.025 | S24: =R24 -> 0.025 | T24: =S24 -> 0.025 | U24: =T24 -> 0.025 | V24: =U24 -> 0.025 | W24: =V24 -> 0.025 | Y24: UW Stab NOI | AB24: =+Q43 -> 6280976.6
B25: Summary | H25: RevPAR | I25: =I23*I22 -> 264.89736 | J25: =J23*J22 -> 262.2627 | K25: =K23*K22 -> 292.5 | M25: =M23*M22 -> 269.2638 | N25: =N23*N22 -> 223.0705 | O25: =O23*O22 -> 238.38401 | P25: =P23*P22 -> 258.28375 | Q25: =Q23*Q22 -> 264.74085 | R25: =R23*R22 -> 271.35937 | S25: =S23*S22 -> 278.14335 | T25: =T23*T22 -> 285.09693 | ... W25: =W23*W22 -> 307.01822
B26: Debt | C26: =C16+C21 -> 33536990 | D26: =C26/$C$28 -> 0.65 | H26: RevPAR % Change | N26: =(N25-M25)/M25 -> -0.17155405 | O26: =(O25-N25)/N25 -> 0.068648743 | P26: =(P25-O25)/O25 -> 0.083477654 | Q26: =(Q25-P25)/P25 -> 0.025 | R26: =(R25-Q25)/Q25 -> 0.025 | S26: =(S25-R25)/R25 -> 0.025 | T26: =(T25-S25)/S25 -> 0.025 | U26: =(U25-T25)/T25 -> 0.025 | ... W26: =(W25-V25)/V25 -> 0.025 | Y26: Sale Price | AB26: =+P5 -> 78512207
B27: Equity | C27: =C17+C22 -> 18058379 | D27: =C27/$C$28 -> 0.35 | Y27: Per Key | AB27: =+AB26/AB6 -> 431385.75
B28: Total | C28: =C26+C27 -> 51595370 | D28: =D18+D23 -> 1 | H28: Revenue | Y28: Exit Cap | AB28: =+P6 -> 0.08
H29: Rooms | I29: 14107062 | J29: 13980018 | K29: 13950000 | M29: =IF(M16<=$P$8,M25*$C$4*IF(IF(MOD(YEAR(M17),4)=0,IF(MOD(YEAR(M17),100)=0,IF(MOD(YEAR(M17),400)=0,TRUE,FALSE),TRUE),FALSE)=TRUE,366,365),0) -> 17887194 | N29: =IF(N16<=$P$8,N25*$C$4*IF(IF(MOD(YEAR(N17),4)=0,IF(MOD(YEAR(N17),100)=0,IF(MOD(YEAR(N17),400)=0,TRUE,FALSE),TRUE),FALSE)=TRUE,366,365),0) -> 14818574 | O29: =IF(O16<=$P$8,O25*$C$4*IF(IF(MOD(YEAR(O17),4)=0,IF(MOD(YEAR(O17),100)=0,IF(MOD(YEAR(O17),400)=0,TRUE,FALSE),TRUE),FALSE)=TRUE,366,365),0) -> 15835850 | P29: =IF(P16<=$P$8,P25*$C$4*IF(IF(MOD(YEAR(P17),4)=0,IF(MOD(YEAR(P17),100)=0,IF(MOD(YEAR(P17),400)=0,TRUE,FALSE),TRUE),FALSE)=TRUE,366,365),0) -> 17204797 | Q29: =IF(Q16<=$P$8,Q25*$C$4*IF(IF(MOD(YEAR(Q17),4)=0,IF(MOD(YEAR(Q17),100)=0,IF(MOD(YEAR(Q17),400)=0,TRUE,FALSE),TRUE),FALSE)=TRUE,366,365),0) -> 17586734 | R29: =IF(R16<=$P$8,R25*$C$4*IF(IF(MOD(YEAR(R17),4)=0,IF(MOD(YEAR(R17),100)=0,IF(MOD(YEAR(R17),400)=0,TRUE,FALSE),TRUE),FALSE)=TRUE,366,365),0) -> 0 | S29: =IF(S16<=$P$8,S25*$C$4*IF(IF(MOD(YEAR(S17),4)=0,IF(MOD(YEAR(S17),100)=0,IF(MOD(YEAR(S17),400)=0,TRUE,FALSE),TRUE),FALSE)=TRUE,366,365),0) -> 0 | T29: =IF(T16<=$P$8,T25*$C$4*IF(IF(MOD(YEAR(T17),4)=0,IF(MOD(YEAR(T17),100)=0,IF(MOD(YEAR(T17),400)=0,TRUE,FALSE),TRUE),FALSE)=TRUE,366,365),0) -> 0 | ... W29: =IF(W16<=$P$8,W25*$C$4*IF(IF(MOD(YEAR(W17),4)=0,IF(MOD(YEAR(W17),100)=0,IF(MOD(YEAR(W17),400)=0,TRUE,FALSE),TRUE),FALSE)=TRUE,366,365),0) -> 0
B30: USES | H30: % of Total Revenue | I30: =I29/I32 -> 0.70562212 | J30: =J29/J32 -> 0.76922338 | K30: =K29/K32 -> 0.76755662 | M30: 0.75 | N30: 0.72 | O30: 0.72 | P30: 0.71 | Q30: 0.7 | R30: =Q30 -> 0.7 | S30: =R30 -> 0.7 | T30: =S30 -> 0.7 | U30: =T30 -> 0.7 | V30: =U30 -> 0.7 | W30: =V30 -> 0.7 | Y30: =D42 -> IRR | AB30: =+F42 -> 0.28159189
B31: Purchase Price | C31: =I5 -> 48000000 | D31: =C31/$C$4 -> 263736.26 | F31: =C31/$C$36 -> 0.93031604 | H31: Other Revenue | I31: =I32-I29 -> 5885313 | J31: =J32-J29 -> 4194180 | K31: =K32-K29 -> 4224555 | M31: =M32-M29 -> 5962398.1 | N31: =N32-N29 -> 5762778.6 | O31: =O32-O29 -> 6158386.1 | P31: =P32-P29 -> 7027311.6 | Q31: =Q32-Q29 -> 7537171.9 | R31: =R32-R29 -> 0 | S31: =S32-S29 -> 0 | T31: =T32-T29 -> 0 | ... W31: =W32-W29 -> 0 | Y31: =D43 -> Profit | AB31: =+F43 -> 38713121
B32: Closing Costs | C32: =I7 -> 1440000 | D32: =C32/$C$4 -> 7912.0879 | F32: =C32/$C$36 -> 0.027909481 | H32: Total Revenue | I32: 19992375 | J32: 18174198 | K32: 18174555 | M32: =M29/M30 -> 23849592 | N32: =N29/N30 -> 20581352 | O32: =O29/O30 -> 21994236 | P32: =P29/P30 -> 24232109 | Q32: =Q29/Q30 -> 25123906 | R32: =R29/R30 -> 0 | S32: =S29/S30 -> 0 | T32: =T29/T30 -> 0 | ... W32: =W29/W30 -> 0 | Y32: =D44 -> MOIC | AB32: =+F44 -> 3.143776
B33: Renovation | C33: =I8 -> 1820000 | D33: =C33/$C$4 -> 10000 | F33: =C33/$C$36 -> 0.035274483
H34: Expense
B35: Financing Costs | C35: =I9 -> 335369.9 | D35: =C35/$C$4 -> 1842.6918 | F35: =C35/$C$36 -> 0.0065 | H35: Reported Management Fee | I35: 605472 | J35: 567571 | K35: 650000
B36: Total | C36: =SUM(C31:C35) -> 51595370 | D36: =SUM(D31:D35) -> 283491.04 | F36: =SUM(F31:F35) -> 1 | H36: 0.03 | I36: =$H$36*I32 -> 599771.25 | J36: =$H$36*J32 -> 545225.94 | K36: =$H$36*K32 -> 545236.65 | M36: =$H$36*M32 -> 715487.77 | N36: =$H$36*N32 -> 617440.56 | O36: =$H$36*O32 -> 659827.08 | P36: =$H$36*P32 -> 726963.26 | Q36: =$H$36*Q32 -> 753717.19 | R36: =$H$36*R32 -> 0 | S36: =$H$36*S32 -> 0 | T36: =$H$36*T32 -> 0 | ... W36: =$H$36*W32 -> 0
H37: Total Expenses | I37: =I32-I39+I35-I36 -> 16938029 | J37: =J32-J39+J35-J36 -> 15573896 | K37: =K32-K39+K35-K36 -> 15529318 | M37: =M32-M43-M41 -> 19318170 | N37: =N32-N43-N41 -> 15230201 | O37: =O32-O43-O41 -> 15615908 | P37: =P32-P43-P41 -> 17204797 | Q37: =Q32-Q43-Q41 -> 17837973 | R37: =R32-R43-R41 -> 0 | S37: =S32-S43-S41 -> 0 | T37: =T32-T43-T41 -> 0 | ... W37: =W32-W43-W41 -> 0
B38: Check: S&U | C38: =C36=C28 -> TRUE
H39: EBITDA | I39: 3060047 | J39: 2622647 | K39: 2750000 | M39: =M32-M37 -> 4531422.5 | N39: =N32-N37 -> 5351151.6 | O39: =O32-O37 -> 6378328.5 | P39: =P32-P37 -> 7027311.6 | Q39: =Q32-Q37 -> 7285932.8 | R39: =R32-R37 -> 0 | S39: =S32-S37 -> 0 | T39: =T32-T37 -> 0 | ... W39: =W32-W37 -> 0
B40: RETURN METRICS
B41: Unlevered Returns | D41: Levered Returns | H41: 0.04 | I41: =$H$41*I32 -> 799695 | J41: =$H$41*J32 -> 726967.92 | K41: =$H$41*K32 -> 726982.2 | M41: =$H$41*M32 -> 953983.69 | N41: =$H$41*N32 -> 823254.09 | O41: =$H$41*O32 -> 879769.44 | P41: =$H$41*P32 -> 969284.35 | Q41: =$H$41*Q32 -> 1004956.2 | R41: =$H$41*R32 -> 0 | S41: =$H$41*S32 -> 0 | T41: =$H$41*T32 -> 0 | ... W41: =$H$41*W32 -> 0
B42: IRR | C42: =IFERROR(XIRR(L70:W70,L17:W17),"") -> 0.16525335 | D42: =B42 -> IRR | F42: =IFERROR(XIRR(L83:W83,L17:W17),"") -> 0.28159189
B43: Profit | C43: =SUM(L70:W70) -> 51624862 | D43: =B43 -> Profit | F43: =SUM(L83:W83) -> 38713121 | H43: Adjusted NOI | I43: =+I35-I36+I39-I41 -> 2266052.8 | J43: =+J35-J36+J39-J41 -> 1918024.1 | K43: =+K35-K36+K39-K41 -> 2127781.1 | M43: =M32*M44 -> 3577438.8 | N43: =N32*N44 -> 4527897.5 | O43: =O32*O44 -> 5498559 | P43: =P32*P44 -> 6058027.2 | Q43: =Q32*Q44 -> 6280976.6 | R43: =R32*R44 -> 0 | S43: =S32*S44 -> 0 | T43: =T32*T44 -> 0 | ... W43: =W32*W44 -> 0
B44: MOIC | C44: =SUMIF(L70:W70,">=0")/-SUMIF(L70:W70,"<=0") -> 2.0071179 | D44: =B44 -> MOIC | F44: =SUMIF(L83:W83,">=0")/-SUMIF(L83:W83,"<=0") -> 3.143776 | H44: NOI Margin | I44: =I43/I32 -> 0.11334585 | J44: =J43/J32 -> 0.10553556 | K44: =K43/K32 -> 0.11707473 | M44: =M45+$J$45 -> 0.15 | N44: =N45+$J$45 -> 0.22 | O44: =O45+$J$45 -> 0.25 | P44: =P45+$J$45 -> 0.25 | Q44: =Q45+$J$45 -> 0.25 | R44: =R45+$J$45 -> 0.25 | S44: =S45+$J$45 -> 0.25 | T44: =T45+$J$45 -> 0.25 | ... W44: =W45+$J$45 -> 0.25 | AD44: NOI Dummy Cell
H45: NOI Toggle > | I45: 0 | J45: =IF(AE44=0,I45,AE44) -> 0 | M45: 0.15 | N45: 0.22 | O45: 0.25 | P45: =$O$44 -> 0.25 | Q45: =$O$44 -> 0.25 | R45: =$O$44 -> 0.25 | S45: =$O$44 -> 0.25 | T45: =$O$44 -> 0.25 | U45: =$O$44 -> 0.25 | V45: =$O$44 -> 0.25 | W45: =$O$44 -> 0.25
H47: Unlevered Cash Flow | M47: =M43 -> 3577438.8 | N47: =N43 -> 4527897.5 | O47: =O43 -> 5498559 | P47: =P43 -> 6058027.2 | Q47: =Q43 -> 6280976.6 | R47: =R43 -> 0 | S47: =S43 -> 0 | T47: =T43 -> 0 | ... W47: =W43 -> 0
H48: =AVERAGE(M48:W48) -> 0.10122083 | M48: =IF(M47=0,"",M47/-$L$70) -> 0.069790067 | N48: =IF(N47=0,"",N47/-$L$70) -> 0.088331983 | O48: =IF(O47=0,"",O47/-$L$70) -> 0.10726803 | P48: =IF(P47=0,"",P47/-$L$70) -> 0.11818235 | Q48: =IF(Q47=0,"",Q47/-$L$70) -> 0.12253173 | R48: =IF(R47=0,"",R47/-$L$70) | S48: =IF(S47=0,"",S47/-$L$70) | T48: =IF(T47=0,"",T47/-$L$70) | ... W48: =IF(W47=0,"",W47/-$L$70)
H50: DEBT SCHEDULE
H51: Debt
H52: Beginning Balance | M52: =IF(M16>$P$8,0,IF(M16=$M$8,L55+$C$21,L55)) -> 33536990 | N52: =IF(N16>$P$8,0,IF(N16=$M$8,M55+$C$21,M55)) -> 33536990 | O52: =IF(O16>$P$8,0,IF(O16=$M$8,N55+$C$21,N55)) -> 33536990 | P52: =IF(P16>$P$8,0,IF(P16=$M$8,O55+$C$21,O55)) -> 33536990 | Q52: =IF(Q16>$P$8,0,IF(Q16=$M$8,P55+$C$21,P55)) -> 33536990 | R52: =IF(R16>$P$8,0,IF(R16=$M$8,Q55+$C$21,Q55)) -> 0 | S52: =IF(S16>$P$8,0,IF(S16=$M$8,R55+$C$21,R55)) -> 0 | T52: =IF(T16>$P$8,0,IF(T16=$M$8,S55+$C$21,S55)) -> 0 | ... W52: =IF(W16>$P$8,0,IF(W16=$M$8,V55+$C$21,V55)) -> 0
H53: Interest Expense | M53: =-IF(M16>$P$8,0,M52*$U$7) -> -2515274.3 | N53: =-IF(N16>$P$8,0,N52*$U$7) -> -2515274.3 | O53: =-IF(O16>$P$8,0,O52*$U$7) -> -2515274.3 | P53: =-IF(P16>$P$8,0,P52*$U$7) -> -2515274.3 | Q53: =-IF(Q16>$P$8,0,Q52*$U$7) -> -2515274.3 | R53: =-IF(R16>$P$8,0,R52*$U$7) -> 0 | S53: =-IF(S16>$P$8,0,S52*$U$7) -> 0 | T53: =-IF(T16>$P$8,0,T52*$U$7) -> 0 | ... W53: =-IF(W16>$P$8,0,W52*$U$7) -> 0
H54: Amortization Expense | M54: =IF(OR(M16>$P$8,AND(M16<=$U$9,$U$8="Yes")),0,PPMT($U$7,M16,$U$10,$U$5)) -> 0 | N54: =IF(OR(N16>$P$8,AND(N16<=$U$9,$U$8="Yes")),0,PPMT($U$7,N16,$U$10,$U$5)) -> 0 | O54: =IF(OR(O16>$P$8,AND(O16<=$U$9,$U$8="Yes")),0,PPMT($U$7,O16,$U$10,$U$5)) -> 0 | P54: =IF(OR(P16>$P$8,AND(P16<=$U$9,$U$8="Yes")),0,PPMT($U$7,P16,$U$10,$U$5)) -> 0 | Q54: =IF(OR(Q16>$P$8,AND(Q16<=$U$9,$U$8="Yes")),0,PPMT($U$7,Q16,$U$10,$U$5)) -> 0 | R54: =IF(OR(R16>$P$8,AND(R16<=$U$9,$U$8="Yes")),0,PPMT($U$7,R16,$U$10,$U$5)) -> 0 | S54: =IF(OR(S16>$P$8,AND(S16<=$U$9,$U$8="Yes")),0,PPMT($U$7,S16,$U$10,$U$5)) -> 0 | T54: =IF(OR(T16>$P$8,AND(T16<=$U$9,$U$8="Yes")),0,PPMT($U$7,T16,$U$10,$U$5)) -> 0 | ... W54: =IF(OR(W16>$P$8,AND(W16<=$U$9,$U$8="Yes")),0,PPMT($U$7,W16,$U$10,$U$5)) -> 0
H55: Ending Balance | L55: =C16 -> 33536990 | M55: =M52+M54 -> 33536990 | N55: =N52+N54 -> 33536990 | O55: =O52+O54 -> 33536990 | P55: =P52+P54 -> 33536990 | Q55: =Q52+Q54 -> 33536990 | R55: =R52+R54 -> 0 | S55: =S52+S54 -> 0 | T55: =T52+T54 -> 0 | ... W55: =W52+W54 -> 0
H57: =MIN(M57:W57) -> 1.4222858 | M57: =IFERROR(M43/-SUM(M53:M54),"") -> 1.4222858 | N57: =IFERROR(N43/-SUM(N53:N54),"") -> 1.8001605 | O57: =IFERROR(O43/-SUM(O53:O54),"") -> 2.1860674 | P57: =IFERROR(P43/-SUM(P53:P54),"") -> 2.4084957 | Q57: =IFERROR(Q43/-SUM(Q53:Q54),"") -> 2.4971338 | R57: =IFERROR(R43/-SUM(R53:R54),"") | S57: =IFERROR(S43/-SUM(S53:S54),"") | T57: =IFERROR(T43/-SUM(T53:T54),"") | ... W57: =IFERROR(W43/-SUM(W53:W54),"")
H58: =MIN(M58:W58) -> 0.10667143 | M58: =IF(M43=0,"",M43/M$55) -> 0.10667143 | N58: =IF(N43=0,"",N43/N$55) -> 0.13501204 | O58: =IF(O43=0,"",O43/O$55) -> 0.16395505 | P58: =IF(P43=0,"",P43/P$55) -> 0.18063717 | Q58: =IF(Q43=0,"",Q43/Q$55) -> 0.18728504 | R58: =IF(R43=0,"",R43/R$55) | S58: =IF(S43=0,"",S43/S$55) | T58: =IF(T43=0,"",T43/T$55) | ... W58: =IF(W43=0,"",W43/W$55)
H60: Levered Cash Flow | M60: =M47+SUM(M53:M54) -> 1062164.6 | N60: =N47+SUM(N53:N54) -> 2012623.2 | O60: =O47+SUM(O53:O54) -> 2983284.7 | P60: =P47+SUM(P53:P54) -> 3542752.9 | Q60: =Q47+SUM(Q53:Q54) -> 3765702.3 | R60: =R47+SUM(R53:R54) -> 0 | S60: =S47+SUM(S53:S54) -> 0 | T60: =T47+SUM(T53:T54) -> 0 | ... W60: =W47+SUM(W53:W54) -> 0
H61: =AVERAGE(M61:W61) -> 0.14803685 | M61: =IF(M60=0,"",M60/-$L$83) -> 0.058818377 | N61: =IF(N60=0,"",N60/-$L$83) -> 0.11145093 | O61: =IF(O60=0,"",O60/-$L$83) -> 0.16520224 | P61: =IF(P60=0,"",P60/-$L$83) -> 0.19618332 | Q61: =IF(Q60=0,"",Q60/-$L$83) -> 0.20852936 | R61: =IF(R60=0,"",R60/-$L$83) | S61: =IF(S60=0,"",S60/-$L$83) | T61: =IF(T60=0,"",T60/-$L$83) | ... W61: =IF(W60=0,"",W60/-$L$83)
H63: Unlevered Returns | L63: =C11 -> 45444 | M63: =M16 -> 1 | N63: =N16 -> 2 | O63: =O16 -> 3 | P63: =P16 -> 4 | Q63: =Q16 -> 5 | R63: =R16 -> 6 | S63: =S16 -> 7 | T63: =T16 -> 8 | ... W63: =W16 -> 11
H64: Purchase Price | L64: =-I5 -> -48000000
H65: Closing Costs | L65: =-I7 -> -1440000
H66: Renovation | L66: =IF(L16=$M$8,-$I$8,0) -> -1820000 | M66: =IF(M16=$M$8,-$I$8,0) -> 0 | N66: =IF(N16=$M$8,-$I$8,0) -> 0 | O66: =IF(O16=$M$8,-$I$8,0) -> 0 | P66: =IF(P16=$M$8,-$I$8,0) -> 0 | Q66: =IF(Q16=$M$8,-$I$8,0) -> 0 | R66: =IF(R16=$M$8,-$I$8,0) -> 0 | S66: =IF(S16=$M$8,-$I$8,0) -> 0 | ... W66: =IF(W16=$M$8,-$I$8,0) -> 0
H67: Unlevered FCF | M67: =M47 -> 3577438.8 | N67: =N47 -> 4527897.5 | O67: =O47 -> 5498559 | P67: =P47 -> 6058027.2 | Q67: =Q47 -> 6280976.6 | R67: =R47 -> 0 | S67: =S47 -> 0 | T67: =T47 -> 0 | ... W67: =W47 -> 0
H68: Reversion | M68: =IF(M$16=$P$8,$P$5,0) -> 0 | N68: =IF(N$16=$P$8,$P$5,0) -> 0 | O68: =IF(O$16=$P$8,$P$5,0) -> 0 | P68: =IF(P$16=$P$8,$P$5,0) -> 0 | Q68: =IF(Q$16=$P$8,$P$5,0) -> 78512207 | R68: =IF(R$16=$P$8,$P$5,0) -> 0 | S68: =IF(S$16=$P$8,$P$5,0) -> 0 | T68: =IF(T$16=$P$8,$P$5,0) -> 0 | ... W68: =IF(W$16=$P$8,$P$5,0) -> 0
H69: Selling Costs | M69: =IF(M$16=$P$7,-$P$9,0) -> 0 | N69: =IF(N$16=$P$7,-$P$9,0) -> 0 | O69: =IF(O$16=$P$7,-$P$9,0) -> 0 | P69: =IF(P$16=$P$7,-$P$9,0) -> 0 | Q69: =IF(Q$16=$P$7,-$P$9,0) -> -1570244.1 | R69: =IF(R$16=$P$7,-$P$9,0) -> 0 | S69: =IF(S$16=$P$7,-$P$9,0) -> 0 | T69: =IF(T$16=$P$7,-$P$9,0) -> 0 | ... W69: =IF(W$16=$P$7,-$P$9,0) -> 0
H70: Total Unlevered Proceeds | L70: =SUM(L64:L69) -> -51260000 | M70: =SUM(M64:M69) -> 3577438.8 | N70: =SUM(N64:N69) -> 4527897.5 | O70: =SUM(O64:O69) -> 5498559 | P70: =SUM(P64:P69) -> 6058027.2 | Q70: =SUM(Q64:Q69) -> 83222939 | R70: =SUM(R64:R69) -> 0 | S70: =SUM(S64:S69) -> 0 | ... W70: =SUM(W64:W69) -> 0
H73: Levered Returns
H74: Purchase Price | L74: =-I5 -> -48000000
H75: Renovation | L75: =IF(L$16=$M$8,-$I$8,0) -> -1820000 | M75: =IF(M$16=$M$8,-$I$8*(1-$V$5),0) -> 0 | N75: =IF(N$16=$M$8,-$I$8*(1-$V$5),0) -> 0 | O75: =IF(O$16=$M$8,-$I$8*(1-$V$5),0) -> 0 | P75: =IF(P$16=$M$8,-$I$8*(1-$V$5),0) -> 0 | Q75: =IF(Q$16=$M$8,-$I$8*(1-$V$5),0) -> 0 | R75: =IF(R$16=$M$8,-$I$8*(1-$V$5),0) -> 0 | S75: =IF(S$16=$M$8,-$I$8*(1-$V$5),0) -> 0 | T75: =IF(T$16=$M$8,-$I$8*(1-$V$5),0) -> 0 | ... W75: =IF(W$16=$M$8,-$I$8*(1-$V$5),0) -> 0
H76: Closing Costs | L76: =-I7 -> -1440000
H77: Debt | L77: =+U5 -> 33536990
H78: Financing Costs | L78: =-I9 -> -335369.9
H79: Levered FCF | M79: =IF(M63>$P$8,0,M60) -> 1062164.6 | N79: =IF(N63>$P$8,0,N60) -> 2012623.2 | O79: =IF(O63>$P$8,0,O60) -> 2983284.7 | P79: =IF(P63>$P$8,0,P60) -> 3542752.9 | Q79: =IF(Q63>$P$8,0,Q60) -> 3765702.3 | R79: =IF(R63>$P$8,0,R60) -> 0 | S79: =IF(S63>$P$8,0,S60) -> 0 | T79: =IF(T63>$P$8,0,T60) -> 0 | ... W79: =IF(W63>$P$8,0,W60) -> 0
H80: Reversion | M80: =IF(M$16=$P$8,$P$5,0) -> 0 | N80: =IF(N$16=$P$8,$P$5,0) -> 0 | O80: =IF(O$16=$P$8,$P$5,0) -> 0 | P80: =IF(P$16=$P$8,$P$5,0) -> 0 | Q80: =IF(Q$16=$P$8,$P$5,0) -> 78512207 | R80: =IF(R$16=$P$8,$P$5,0) -> 0 | S80: =IF(S$16=$P$8,$P$5,0) -> 0 | T80: =IF(T$16=$P$8,$P$5,0) -> 0 | ... W80: =IF(W$16=$P$8,$P$5,0) -> 0
H81: Loan Payoff | M81: =IF(M$63=$P$8,-M$55,0) -> 0 | N81: =IF(N$63=$P$8,-N$55,0) -> 0 | O81: =IF(O$63=$P$8,-O$55,0) -> 0 | P81: =IF(P$63=$P$8,-P$55,0) -> 0 | Q81: =IF(Q$63=$P$8,-Q$55,0) -> -33536990 | R81: =IF(R$63=$P$8,-R$55,0) -> 0 | S81: =IF(S$63=$P$8,-S$55,0) -> 0 | T81: =IF(T$63=$P$8,-T$55,0) -> 0 | ... W81: =IF(W$63=$P$8,-W$55,0) -> 0
H82: Selling Costs | M82: =IF(M$16=$P$7,-$P$9,0) -> 0 | N82: =IF(N$16=$P$7,-$P$9,0) -> 0 | O82: =IF(O$16=$P$7,-$P$9,0) -> 0 | P82: =IF(P$16=$P$7,-$P$9,0) -> 0 | Q82: =IF(Q$16=$P$7,-$P$9,0) -> -1570244.1 | R82: =IF(R$16=$P$7,-$P$9,0) -> 0 | S82: =IF(S$16=$P$7,-$P$9,0) -> 0 | T82: =IF(T$16=$P$7,-$P$9,0) -> 0 | ... W82: =IF(W$16=$P$7,-$P$9,0) -> 0
H83: Total Levered Proceeds | L83: =SUM(L74:L82) -> -18058379 | M83: =SUM(M74:M82) -> 1062164.6 | N83: =SUM(N74:N82) -> 2012623.2 | O83: =SUM(O74:O82) -> 2983284.7 | P83: =SUM(P74:P82) -> 3542752.9 | Q83: =SUM(Q74:Q82) -> 47170675 | R83: =SUM(R74:R82) -> 0 | S83: =SUM(S74:S82) -> 0 | ... W83: =SUM(W74:W82) -> 0

Sheet JV Waterfall
B2: GP / LP Joint Venture Waterfall
B4: JV Structure
B5: Total Equity | C5: =Input!C17 -> 18058379
B6: GP Co-Invest (%) | C6: 0.1
B7: LP Equity (%) | C7: =1-C6 -> 0.9
B8: GP Equity ($) | C8: =C5*C6 -> 1805837.9
B9: LP Equity ($) | C9: =C5*C7 -> 16252542
B11: Waterfall Terms
B12: LP Preferred Return | C12: 0.08
B13: Tier 1 Split (LP / GP) | C13: 0.7 | D13: =1-C13 -> 0.3
B14: Tier 1 LP MOIC Hurdle | C14: 2
B15: Tier 2 Split (LP / GP) | C15: 0.5 | D15: =1-C15 -> 0.5
B18: Distributable Cash Flows
D19: =Input!L17 -> 45444 | E19: =Input!M17 -> 45838 | F19: =Input!N17 -> 46203 | G19: =Input!O17 -> 46568 | H19: =Input!P17 -> 46934 | I19: =Input!Q17 -> 47299
B20: Total Levered Proceeds | D20: =Input!L83 -> -18058379 | E20: =Input!M83 -> 1062164.6 | F20: =Input!N83 -> 2012623.2 | G20: =Input!O83 -> 2983284.7 | H20: =Input!P83 -> 3542752.9 | I20: =Input!Q83 -> 47170675
B21: Cumulative | D21: =D20 -> -18058379 | E21: =D21+E20 -> -16996215 | F21: =E21+F20 -> -14983592 | G21: =F21+G20 -> -12000307 | H21: =G21+H20 -> -8457554.1 | I21: =H21+I20 -> 38713121
B24: LP Preferred Return Tracker
D25: =D19 -> 45444 | E25: =E19 -> 45838 | F25: =F19 -> 46203 | G25: =G19 -> 46568 | H25: =H19 -> 46934 | I25: =I19 -> 47299
B27: LP Unreturned Capital (BoP) | D27: =$C$9 -> 16252542 | E27: =D42 -> 16252542 | F27: =E42 -> 16252542 | G27: =F42 -> 15778160 | H27: =G42 -> 14057128 | I27: =H42 -> 11638946
B28: Pref Accrual | E28: =E27*$C$12 -> 1300203.3 | F28: =F27*$C$12 -> 1300203.3 | G28: =G27*$C$12 -> 1262252.8 | H28: =H27*$C$12 -> 1124570.3 | I28: =I27*$C$12 -> 931115.67
B29: Pref Paid | E29: =E38 -> 1062164.6 | F29: =F38 -> 1538242.1 | G29: =G38 -> 1262252.8 | H29: =H38 -> 1124570.3 | I29: =I38 -> 931115.67
B30: Unpaid Pref (BoP) | D30: 0 | E30: =D31 -> 0 | F30: =E31 -> 238038.76 | G30: =F31 -> 0 | H30: =G31 -> 0 | I30: =H31 -> 0
B31: Unpaid Pref (EoP) | D31: 0 | E31: =E30+E28-E29 -> 238038.76 | F31: =F30+F28-F29 -> 0 | G31: =G30+G28-G29 -> 0 | H31: =H30+H28-H29 -> 0 | I31: =I30+I28-I29 -> 0
B34: Distribution Waterfall
D35: =D19 -> 45444 | E35: =E19 -> 45838 | F35: =F19 -> 46203 | G35: =G19 -> 46568 | H35: =H19 -> 46934 | I35: =I19 -> 47299
B37: Cash Available | E37: =E20 -> 1062164.6 | F37: =F20 -> 2012623.2 | G37: =G20 -> 2983284.7 | H37: =H20 -> 3542752.9 | I37: =I20 -> 47170675
B38: Tier 1: LP Preferred Return | E38: =MIN(E37,E30+E28) -> 1062164.6 | F38: =MIN(F37,F30+F28) -> 1538242.1 | G38: =MIN(G37,G30+G28) -> 1262252.8 | H38: =MIN(H37,H30+H28) -> 1124570.3 | I38: =MIN(I37,I30+I28) -> 931115.67
B39: Remaining after Tier 1 | E39: =E37-E38 -> 0 | F39: =F37-F38 -> 474381.11 | G39: =G37-G38 -> 1721031.9 | H39: =H37-H38 -> 2418182.6 | I39: =I37-I38 -> 46239559
B41: Tier 2: Return of LP Capital | E41: =MIN(E39,E27) -> 0 | F41: =MIN(F39,F27) -> 474381.11 | G41: =MIN(G39,G27) -> 1721031.9 | H41: =MIN(H39,H27) -> 2418182.6 | I41: =MIN(I39,I27) -> 11638946
B42: LP Unreturned Capital (EoP) | D42: =D27 -> 16252542 | E42: =E27-E41 -> 16252542 | F42: =F27-F41 -> 15778160 | G42: =G27-G41 -> 14057128 | H42: =H27-H41 -> 11638946 | I42: =I27-I41 -> 0
B43: Remaining after Tier 2 | E43: =E39-E41 -> 0 | F43: =F39-F41 -> 0 | G43: =G39-G41 -> 0 | H43: =H39-H41 -> 0 | I43: =I39-I41 -> 34600613
B45: Tier 3: Return of GP Capital
B46: GP Unreturned Capital (BoP) | D46: =$C$8 -> 1805837.9 | E46: =D48 -> 1805837.9 | F46: =E48 -> 1805837.9 | G46: =F48 -> 1805837.9 | H46: =G48 -> 1805837.9 | I46: =H48 -> 1805837.9
B47: GP Capital Return | E47: =MIN(E43,E46) -> 0 | F47: =MIN(F43,F46) -> 0 | G47: =MIN(G43,G46) -> 0 | H47: =MIN(H43,H46) -> 0 | I47: =MIN(I43,I46) -> 1805837.9
B48: GP Unreturned Capital (EoP) | D48: =D46 -> 1805837.9 | E48: =E46-E47 -> 1805837.9 | F48: =F46-F47 -> 1805837.9 | G48: =G46-G47 -> 1805837.9 | H48: =H46-H47 -> 1805837.9 | I48: =I46-I47 -> 0
B49: Remaining after Tier 3 | E49: =E43-E47 -> 0 | F49: =F43-F47 -> 0 | G49: =G43-G47 -> 0 | H49: =H43-H47 -> 0 | I49: =I43-I47 -> 32794775
B51: Tier 4: Promote Split to LP 2.0x
B52: Cumulative LP (End of Prior Period) | E52: 0 | F52: =E52+E38+E41+E57+E62 -> 1062164.6 | G52: =F52+F38+F41+F57+F62 -> 3074787.8 | H52: =G52+G38+G41+G57+G62 -> 6058072.5 | I52: =H52+H38+H41+H57+H62 -> 9600825.4
B53: LP This Period Before Tier 4 | E53: =E38+E41 -> 1062164.6 | F53: =F38+F41 -> 2012623.2 | G53: =G38+G41 -> 2983284.7 | H53: =H38+H41 -> 3542752.9 | I53: =I38+I41 -> 12570062
B54: Total LP Before Tier 4 | E54: =E52+E53 -> 1062164.6 | F54: =F52+F53 -> 3074787.8 | G54: =G52+G53 -> 6058072.5 | H54: =H52+H53 -> 9600825.4 | I54: =I52+I53 -> 22170887
B55: LP Remaining to 2.0x | E55: =MAX(0,$C$9*$C$14-E54) -> 31442918 | F55: =MAX(0,$C$9*$C$14-F54) -> 29430295 | G55: =MAX(0,$C$9*$C$14-G54) -> 26447011 | H55: =MAX(0,$C$9*$C$14-H54) -> 22904258 | I55: =MAX(0,$C$9*$C$14-I54) -> 10334196
B56: Tier 4 Total | E56: =IF(E55=0,0,MIN(E49,E55/$C$13)) -> 0 | F56: =IF(F55=0,0,MIN(F49,F55/$C$13)) -> 0 | G56: =IF(G55=0,0,MIN(G49,G55/$C$13)) -> 0 | H56: =IF(H55=0,0,MIN(H49,H55/$C$13)) -> 0 | I56: =IF(I55=0,0,MIN(I49,I55/$C$13)) -> 14763137
B57: Tier 4 to LP | E57: =E56*$C$13 -> 0 | F57: =F56*$C$13 -> 0 | G57: =G56*$C$13 -> 0 | H57: =H56*$C$13 -> 0 | I57: =I56*$C$13 -> 10334196
B58: Tier 4 to GP | E58: =E56*$D$13 -> 0 | F58: =F56*$D$13 -> 0 | G58: =G56*$D$13 -> 0 | H58: =H56*$D$13 -> 0 | I58: =I56*$D$13 -> 4428941.2
B59: Remaining after Tier 4 | E59: =E49-E56 -> 0 | F59: =F49-F56 -> 0 | G59: =G49-G56 -> 0 | H59: =H49-H56 -> 0 | I59: =I49-I56 -> 18031638
B61: Tier 5: Residual Split
B62: Tier 5 to LP | E62: =E59*$C$15 -> 0 | F62: =F59*$C$15 -> 0 | G62: =G59*$C$15 -> 0 | H62: =H59*$C$15 -> 0 | I62: =I59*$C$15 -> 9015818.9
B63: Tier 5 to GP | E63: =E59*$D$15 -> 0 | F63: =F59*$D$15 -> 0 | G63: =G59*$D$15 -> 0 | H63: =H59*$D$15 -> 0 | I63: =I59*$D$15 -> 9015818.9
B65: Check: Remaining | E65: =E59-E62-E63 -> 0 | F65: =F59-F62-F63 -> 0 | G65: =G59-G62-G63 -> 0 | H65: =H59-H62-H63 -> 0 | I65: =I59-I62-I63 -> 0
B68: Cash Flow Summary
D69: =D19 -> 45444 | E69: =E19 -> 45838 | F69: =F19 -> 46203 | G69: =G19 -> 46568 | H69: =H19 -> 46934 | I69: =I19 -> 47299
B71: LP Cash Flows
B72: Equity Contribution | D72: =-$C$9 -> -16252542
B73: Pref Distributions | E73: =E38 -> 1062164.6 | F73: =F38 -> 1538242.1 | G73: =G38 -> 1262252.8 | H73: =H38 -> 1124570.3 | I73: =I38 -> 931115.67
B74: Capital Return | E74: =E41 -> 0 | F74: =F41 -> 474381.11 | G74: =G41 -> 1721031.9 | H74: =H41 -> 2418182.6 | I74: =I41 -> 11638946
B75: Promote Distributions | E75: =E57+E62 -> 0 | F75: =F57+F62 -> 0 | G75: =G57+G62 -> 0 | H75: =H57+H62 -> 0 | I75: =I57+I62 -> 19350015
B76: Total LP Cash Flow | D76: =D72 -> -16252542 | E76: =SUM(E73:E75) -> 1062164.6 | F76: =SUM(F73:F75) -> 2012623.2 | G76: =SUM(G73:G75) -> 2983284.7 | H76: =SUM(H73:H75) -> 3542752.9 | I76: =SUM(I73:I75) -> 31920077
B78: GP Cash Flows
B79: Equity Contribution | D79: =-$C$8 -> -1805837.9
B80: Capital Return | E80: =E47 -> 0 | F80: =F47 -> 0 | G80: =G47 -> 0 | H80: =H47 -> 0 | I80: =I47 -> 1805837.9
B81: Promote Distributions | E81: =E58+E63 -> 0 | F81: =F58+F63 -> 0 | G81: =G58+G63 -> 0 | H81: =H58+H63 -> 0 | I81: =I58+I63 -> 13444760
B82: Total GP Cash Flow | D82: =D79 -> -1805837.9 | E82: =SUM(E80:E81) -> 0 | F82: =SUM(F80:F81) -> 0 | G82: =SUM(G80:G81) -> 0 | H82: =SUM(H80:H81) -> 0 | I82: =SUM(I80:I81) -> 15250598
B84: Check: Total | D84: =D76+D82 -> -18058379 | E84: =E76+E82 -> 1062164.6 | F84: =F76+F82 -> 2012623.2 | G84: =G76+G82 -> 2983284.7 | H84: =H76+H82 -> 3542752.9 | I84: =I76+I82 -> 47170675
B87: Return Metrics
C88: LP | D88: GP
B90: Equity Invested | C90: =$C$9 -> 16252542 | D90: =$C$8 -> 1805837.9
B91: Total Distributions | C91: =SUM(E76:I76) -> 41520902 | D91: =SUM(E82:I82) -> 15250598
B92: Profit | C92: =C91+D76 -> 25268360 | D92: =D91+D82 -> 13444760
B94: IRR | C94: =XIRR(D76:I76,D69:I69) -> 0.23261892 | D94: =XIRR(D82:I82,D69:I69) -> 0.5216841
B95: MOIC | C95: =C91/C90 -> 2.5547329 | D95: =D91/D90 -> 8.4451642
B97: GP Promote Analysis
B98: GP Pro Rata Share (at co-invest %) | C98: =(C91+D91)*$C$6 -> 5677150
B99: Actual GP Distributions | C99: =D91 -> 15250598
B100: GP Promote ($) | C100: =C99-C98 -> 9573448.1
B101: Promote as % of LP Profit | C101: =C100/C92 -> 0.37887096
