Workbook
Name circ: 'LBO Model'!$O$5
Name circ2: #REF!
Name IQ_CH: 110000
Name IQ_CQ: 5000
Name IQ_CY: 10000
Name IQ_DAILY: 500000
Name IQ_FH: 100000
Name IQ_FQ: 500
Name IQ_FY: 1000
Name IQ_LTM: 2000
Name IQ_MONTH: 15000
Name IQ_NTM: 6000
Name IQ_WEEK: 50000
Name IQ_YTD: 3000
Name recap: 'LBO Model'!$D$23

Sheet Assumptions
B2: Balance Sheet Assumptions
F3: Pre-
B4: Balance Sheet Item | F4: Transaction | H4: Operating Assumptions
B5: Cash | F5: ='LBO Model'!F55 -> 200
B6: Accounts Receivable | F6: ='LBO Model'!F56 -> 200 | H6: 30 Days Sales
B7: Inventory | F7: ='LBO Model'!F57 -> 250 | H7: 60 Days COGS
B8: Prepaid Expenses | F8: ='LBO Model'!F58 -> 50 | H8: 2.0% of Revenue
B9: Total Current Assets | F9: =SUM(F5:F8) -> 700
B11: Property, Plant & Equipment | F11: ='LBO Model'!F61 -> 2000
B12: Capitalized Financing Fees | F12: ='LBO Model'!F77 -> 0 | H12: Amortized over 7 years
B13: Goodwill | F13: ='LBO Model'!F62 -> 1300
B14: Intangible Assets | F14: ='LBO Model'!F63 -> 0 | H14: 10% of Step-Up. Amortized over 15 years
B15: Total Assets | F15: =SUM(F11:F14)+F9 -> 4000
B17: Accounts Payable | F17: ='LBO Model'!F66 -> 200 | H17: 60 Days COGS
B18: Accrued Liabilities | F18: ='LBO Model'!F67 -> 50 | H18: 2.0% of Revenue
B19: Total Current Liabilities | F19: =SUM(F17:F18) -> 250
B21: Existing Debt | F21: ='LBO Model'!F70 -> 2500 | H21: Paid down
B22: Revolver | F22: ='LBO Model'!F71 -> 0
B23: Recap Debt | F23: ='LBO Model'!F72 -> 0
B24: Bank Debt | F24: ='LBO Model'!F73 -> 0
B25: Senior Notes | F25: ='LBO Model'!F74 -> 0
B26: Total Debt Outstanding | F26: =SUM(F21:F25) -> 2500
B28: Deferred Tax Liability | F28: ='LBO Model'!F78 -> 0 | H28: 10% of Step-Up. Amortized over 15 years
B30: Shareholder Equity | F30: ='LBO Model'!F80 -> 1250
B31: Total Liabilities and Equity | F31: =F26+F28+F30+F19 -> 4000

Sheet LBO Model
B4: Transaction Drivers | O4: Circ
O5: 1
B6: Model Assumptions
B7: Entry Valuation
B8: Entry LTM EBITDA | F8: =G129 -> 500 | I8: 5 Year Returns
B9: (x) Entry Multiple | F9: 10 | I9: IRR
B10: Purchase Enterprise Value | F10: =F8*F9 -> 5000 | I10: MoM
B11: Less: Debt | F11: =-F75 -> -2500
B12: Plus: Cash | F12: =F55 -> 200
B13: Equity Value | F13: =SUM(F10:F12) -> 2700
B15: Transaction
B16: LTM Exit Multiple | F16: 10
B17: Tax Rate | F17: 0.38
B18: Cash to B/S | F18: 100
B19: Transaction Expenses | F19: 25
B21: Debt | F21: (x) EBITDA
B22: Total Leverage | F22: 6 | H22: L+ Floor | I22: Rate | J22: Fee (%) | K22: Fee ($) | L22: Year | M22: Multiple
B23: Recap Debt | D23: 1 | F23: 0 | H23: 0.01 | I23: 400 | J23: 0 | K23: =J23*F32 -> 0 | L23: 2023 | M23: 6
B24: PIK Debt | F24: =F33/F29 -> 3 | H24: 0 | I24: 0.08 | J24: 0.02 | K24: =J24*F33 -> 30
B25: Senior Notes | F25: =MAX(F22-F24,0) -> 3 | H25: 0 | I25: 0.07 | J25: 0.02 | K25: =J25*F34 -> 30
B28: Revolver Capacity | F28: 300 | H28: 0.01 | I28: 400 | J28: 0 | K28: =J28*F28 -> 0
B29: Leverageable EBITDA | F29: =G129 -> 500
B31: Sources & Uses
B32: Sources | I32: Uses
B33: PIK Debt | F33: 1500 | I33: Purchase Equity Value | M33: =F13 -> 2700
B34: Senior Notes | F34: =F25*$F$29 -> 1500 | I34: Refinancing Net Debt | M34: =-SUM(F11:F12) -> 2300
B35: Total Debt | F35: =SUM(F33:F34) -> 3000 | I35: Cash to B/S | M35: =F18 -> 100
I36: Underwriting Fees | M36: =SUM(K23:K28) -> 60
B37: Equity Investment | F37: =MAX(F38-F35,0) -> 2185 | I37: Transaction Expenses | M37: =F19 -> 25 | O37: Check
B38: Total Sources | F38: =M38 -> 5185 | I38: Total Uses | M38: =SUM(M33:M37) -> 5185 | O38: =M38-F38 -> 0
B40: Goodwill Calculation
B42: Purchase Equity Value | F42: =M33 -> 2700
B43: Less: Book Value of Equity | F43: =-F80 -> -1250
B44: Plus: Existing Goodwill | F44: =F62 -> 1300 | H44: % of
B45: Step-Up of Equity | F45: =SUM(F42:F44) -> 2750 | H45: Step-Up | I45: Years | J45: Annual
B46: Less: Write-Up of Intangible Assets | F46: =-H46*$F$45 -> -275 | H46: 0.1 | I46: 15 | J46: =-F46/I46 -> 18.333333
B47: Plus: Deferred Tax Liability | F47: =-F17*$F$46 -> 104.5 | I47: 15 | J47: =F47/I47 -> 6.9666667
B48: Pro Forma Goodwill | F48: =SUM(F45:F47) -> 2579.5
B51: Closing Balance Sheet
F53: Pre- | K53: Pro
F54: Transaction | H54: Debits | I54: Credits | K54: Forma
B55: Cash | F55: 200 | H55: =F18 -> 100 | I55: =-F55 -> -200 | K55: =F55+H55+I55 -> 100
B56: Accounts Receivable | F56: 200 | H56: 0 | I56: 0 | K56: =F56+H56+I56 -> 200
B57: Inventory | F57: 250 | H57: 0 | I57: 0 | K57: =F57+H57+I57 -> 250
B58: Prepaid Expenses | F58: 50 | H58: 0 | I58: 0 | K58: =F58+H58+I58 -> 50 | O58: Check
B59: Total Current Assets | F59: =SUM(F55:F58) -> 700 | H59: =SUM(H55:H58) -> 100 | I59: =SUM(I55:I58) -> -200 | K59: =SUM(K55:K58) -> 600 | O59: =F59+H59+I59-K59 -> 0
B61: Property, Plant & Equipment | F61: 2000 | H61: 0 | I61: 0 | K61: =F61+H61+I61 -> 2000
B62: Goodwill | F62: 1300 | H62: =F48 -> 2579.5 | I62: =-F62 -> -1300 | K62: =F62+H62+I62 -> 2579.5
B63: Intangible Assets | F63: 0 | H63: =-F46 -> 275 | I63: 0 | K63: =F63+H63+I63 -> 275
B64: Total Assets | F64: =SUM(F61:F63)+F59 -> 4000 | H64: =SUM(H61:H63)+H59 -> 2954.5 | I64: =SUM(I61:I63)+I59 -> -1500 | K64: =SUM(K61:K63)+K59 -> 5454.5 | O64: =F64+H64+I64-K64 -> 0
B66: Accounts Payable | F66: 200 | H66: 0 | I66: 0 | K66: =F66+H66+I66 -> 200
B67: Accrued Liabilities | F67: 50 | H67: 0 | I67: 0 | K67: =F67+H67+I67 -> 50
B68: Total Current Liabilities | F68: =SUM(F66:F67) -> 250 | H68: =SUM(H66:H67) -> 0 | I68: =SUM(I66:I67) -> 0 | K68: =SUM(K66:K67) -> 250 | O68: =F68+H68+I68-K68 -> 0
B70: Existing Debt | F70: 2500 | H70: =-F70 -> -2500 | I70: 0 | K70: =F70+H70+I70 -> 0
B71: Revolver | F71: 0 | H71: 0 | I71: 0 | K71: =F71+H71+I71 -> 0
B72: Recap Debt | F72: 0 | H72: 0 | I72: 0 | K72: =F72+H72+I72 -> 0
B73: PIK Debt | F73: 0 | H73: 0 | I73: =F33 -> 1500 | K73: =F73+H73+I73 -> 1500
B74: Senior Notes | F74: 0 | H74: 0 | I74: =F34 -> 1500 | K74: =F74+H74+I74 -> 1500
B75: Total Debt Outstanding | F75: =SUM(F70:F74) -> 2500 | H75: =SUM(H70:H74) -> -2500 | I75: =SUM(I70:I74) -> 3000 | K75: =SUM(K70:K74) -> 3000 | O75: =F75+H75+I75-K75 -> 0
B77: Capitalized Financing Fees | F77: 0 | H77: =-M36 -> -60 | I77: 0 | K77: =F77+H77+I77 -> -60
B78: Deferred Tax Liability | F78: 0 | H78: 0 | I78: =F47 -> 104.5 | K78: =F78+H78+I78 -> 104.5
B80: Shareholder Equity | F80: 1250 | H80: =-F80-M37 -> -1275 | I80: =F37 -> 2185 | K80: =F80+H80+I80 -> 2160
B81: Total Liabilities and Equity | F81: =F75+F77+F78+F80+F68 -> 4000 | H81: =H75+H77+H78+H80+H68 -> -3835 | I81: =I75+I77+I78+I80+I68 -> 5289.5 | K81: =K75+K77+K78+K80+K68 -> 5454.5 | O81: =F81+H81+I81-K81 -> 0
B83: Check | F83: =F64-F81 -> 0 | K83: =K64-K81 -> 0
B87: Driver Forecast
G89: =H89-1 -> 2020 | H89: 2021 | I89: =H89+1 -> 2022 | J89: =I89+1 -> 2023 | K89: =J89+1 -> 2024 | L89: =K89+1 -> 2025
B90: E-Commerce Channel
B91: Units Sold (in millions) | G91: 400 | H91: =G91*(1+H107) -> 420 | I91: =H91*(1+I107) -> 441 | J91: =I91*(1+J107) -> 463.05 | K91: =J91*(1+K107) -> 486.2025 | L91: =K91*(1+L107) -> 510.51263
B92: Price per Unit | G92: 4 | H92: =G92*(1+H108) -> 4.08 | I92: =H92*(1+I108) -> 4.1616 | J92: =I92*(1+J108) -> 4.244832 | K92: =J92*(1+K108) -> 4.3297286 | L92: =K92*(1+L108) -> 4.4163232
B93: E-Commerce Revenue | G93: =G91*G92 -> 1600 | H93: =H91*H92 -> 1713.6 | I93: =I91*I92 -> 1835.2656 | J93: =J91*J92 -> 1965.5695 | K93: =K91*K92 -> 2105.1249 | L93: =L91*L92 -> 2254.5888
B95: E-Commerce COGS | H95: =-H109*H93 -> -856.8 | I95: =-I109*I93 -> -917.6328 | J95: =-J109*J93 -> -982.78473 | K95: =-K109*K93 -> -1052.5624 | L95: =-L109*L93 -> -1127.2944
B96: E-Commerce Gross Profit | H96: =H93+H95 -> 856.8 | I96: =I93+I95 -> 917.6328 | J96: =J93+J95 -> 982.78473 | K96: =K93+K95 -> 1052.5624 | L96: =L93+L95 -> 1127.2944
B98: Inside Sales Team
B99: Inside Sales Groups | G99: 5 | H99: =G99+H112 -> 6 | I99: =H99+I112 -> 7 | J99: =I99+J112 -> 8 | K99: =J99+K112 -> 9 | L99: =K99+L112 -> 10
B100: Sales per Group (in millions) | G100: 200 | H100: =G100*(1+H113) -> 204 | I100: =H100*(1+I113) -> 208.08 | J100: =I100*(1+J113) -> 212.2416 | K100: =J100*(1+K113) -> 216.48643 | L100: =K100*(1+L113) -> 220.81616
B101: Inside Sales Revenue | G101: =G99*G100 -> 1000 | H101: =H99*H100 -> 1224 | I101: =I99*I100 -> 1456.56 | J101: =J99*J100 -> 1697.9328 | K101: =K99*K100 -> 1948.3779 | L101: =L99*L100 -> 2208.1616
B103: Inside Sales COGS | H103: =-H114*H101 -> -612 | I103: =-I114*I101 -> -728.28 | J103: =-J114*J101 -> -848.9664 | K103: =-K114*K101 -> -974.18894 | L103: =-L114*L101 -> -1104.0808
B104: Inside Sales Gross Profit | H104: =H101+H103 -> 612 | I104: =I101+I103 -> 728.28 | J104: =J101+J103 -> 848.9664 | K104: =K101+K103 -> 974.18894 | L104: =L101+L103 -> 1104.0808
B106: E-Commerce Channel Assumptions
B107: Units Sold Growth % YoY | H107: 0.05 | I107: 0.05 | J107: 0.05 | K107: 0.05 | L107: 0.05
B108: Units Price Growth % YoY | H108: 0.02 | I108: 0.02 | J108: 0.02 | K108: 0.02 | L108: 0.02
B109: E-Commerce COGS % of Revenue | H109: 0.5 | I109: 0.5 | J109: 0.5 | K109: 0.5 | L109: 0.5
B111: Inside Sales Assumptions
B112: Sales Group Adds | H112: 1 | I112: 1 | J112: 1 | K112: 1 | L112: 1
B113: Sales Per Group Growth | H113: 0.02 | I113: 0.02 | J113: 0.02 | K113: 0.02 | L113: 0.02
B114: Inside Sales COGS % of Revenue | H114: 0.5 | I114: 0.5 | J114: 0.5 | K114: 0.5 | L114: 0.5
B115: Salary Per Group (millions) | H115: 50 | I115: 50 | J115: 50 | K115: 50 | L115: 50
B118: Financial Forecast
G120: =H120-1 -> 2020 | H120: 2021 | I120: =H120+1 -> 2022 | J120: =I120+1 -> 2023 | K120: =J120+1 -> 2024 | L120: =K120+1 -> 2025
B121: Revenue | G121: =G93+G101 -> 2600 | H121: =H93+H101 -> 2937.6 | I121: =I93+I101 -> 3291.8256 | J121: =J93+J101 -> 3663.5023 | K121: =K93+K101 -> 4053.5028 | L121: =L93+L101 -> 4462.7504
B122: Less: COGS | H122: =H95+H103 -> -1468.8 | I122: =I95+I103 -> -1645.9128 | J122: =J95+J103 -> -1831.7511 | K122: =K95+K103 -> -2026.7514 | L122: =L95+L103 -> -2231.3752
B123: Gross Profit | H123: =SUM(H121:H122) -> 1468.8 | I123: =SUM(I121:I122) -> 1645.9128 | J123: =SUM(J121:J122) -> 1831.7511 | K123: =SUM(K121:K122) -> 2026.7514 | L123: =SUM(L121:L122) -> 2231.3752
B124: % Margin | H124: =H123/H$121 -> 0.5 | I124: =I123/I$121 -> 0.5 | J124: =J123/J$121 -> 0.5 | K124: =K123/K$121 -> 0.5 | L124: =L123/L$121 -> 0.5
B126: Less: SG&A | H126: =-H155*H$121 -> -293.76 | I126: =-I155*I$121 -> -329.18256 | J126: =-J155*J$121 -> -366.35023 | K126: =-K155*K$121 -> -405.35028 | L126: =-L155*L$121 -> -446.27504
B127: Less: R&D | H127: =-H156*H$121 -> -264.384 | I127: =-I156*I$121 -> -296.2643 | J127: =-J156*J$121 -> -329.7152 | K127: =-K156*K$121 -> -364.81525 | L127: =-L156*L$121 -> -401.64753
B128: Less: Inside Sales Salaries | H128: =-H115*H99 -> -300 | I128: =-I115*I99 -> -350 | J128: =-J115*J99 -> -400 | K128: =-K115*K99 -> -450 | L128: =-L115*L99 -> -500
B129: EBITDA | G129: 500 | H129: =H123+SUM(H126:H128) -> 610.656 | I129: =I123+SUM(I126:I128) -> 670.46594 | J129: =J123+SUM(J126:J128) -> 735.6857 | K129: =K123+SUM(K126:K128) -> 806.58586 | L129: =L123+SUM(L126:L128) -> 883.45261
B130: % Margin | G130: =G129/G$121 -> 0.19230769 | H130: =H129/H$121 -> 0.20787582 | I130: =I129/I$121 -> 0.20367602 | J130: =J129/J$121 -> 0.20081486 | K130: =K129/K$121 -> 0.1989849 | L130: =L129/L$121 -> 0.19796147
B132: Less: D&A | H132: =-H157*H$121 -> -58.752 | I132: =-I157*I$121 -> -65.836512 | J132: =-J157*J$121 -> -73.270045 | K132: =-K157*K$121 -> -81.070056 | L132: =-L157*L$121 -> -89.255007
B133: Less: Amortization of Intangible Writeup | H133: =-$J$46 -> -18.333333 | I133: =-$J$46 -> -18.333333 | J133: =-$J$46 -> -18.333333 | K133: =-$J$46 -> -18.333333 | L133: =-$J$46 -> -18.333333
...
