Workbook

Sheet Budget Assumption Driver
C2: Happy Pets Vets | P2: =TODAY() -> 45999
D3: Budget Assumptions Driver | P3: ($ in 000s)
D5: MoM Change in Employed Vets
E6: 45658 | F6: =EOMONTH(E6,1) -> 45716 | G6: =EOMONTH(F6,1) -> 45747 | H6: =EOMONTH(G6,1) -> 45777 | I6: =EOMONTH(H6,1) -> 45808 | J6: =EOMONTH(I6,1) -> 45838 | K6: =EOMONTH(J6,1) -> 45869 | L6: =EOMONTH(K6,1) -> 45900 | M6: =EOMONTH(L6,1) -> 45930 | ... P6: =EOMONTH(O6,1) -> 46022
A7: 1 | D7: Sites with 1 Doctor at YE-24 | E7: 0 | F7: 1 | G7: 0 | H7: 0 | I7: 0 | J7: 0 | K7: 1 | L7: 0 | M7: 0 | N7: 0 | O7: 0 | P7: 0
A8: =A7+1 -> 2 | D8: Sites with 2 Doctors at YE-24 | E8: 0 | F8: 0 | G8: 0 | H8: 1 | I8: 0 | J8: 0 | K8: 0 | L8: 0 | M8: 0 | N8: 0 | O8: 0 | P8: 0
A9: =A8+1 -> 3 | D9: Sites with 3 Doctors at YE-24 | E9: 0 | F9: 0 | G9: 0 | H9: 0 | I9: 0 | J9: 0 | K9: 1 | L9: 0 | M9: 0 | N9: 0 | O9: 0 | P9: 0
A10: =A9+1 -> 4 | D10: Sites with 4 Doctors at YE-24 | E10: 0 | F10: 0 | G10: 0 | H10: 0 | I10: 0 | J10: 0 | K10: 0 | L10: 0 | M10: 0 | N10: 0 | O10: 0 | P10: 0
A11: =A10+1 -> 5 | D11: Sites with 5 Doctors at YE-24 | E11: 0 | F11: 0 | G11: 0 | H11: 0 | I11: 0 | J11: 0 | K11: 0 | L11: 0 | M11: 0 | N11: 0 | O11: 0 | P11: 0
D13: MoM Change in Production per Vet per Workday
E14: 45658 | F14: =EOMONTH(E14,1) -> 45716 | G14: =EOMONTH(F14,1) -> 45747 | H14: =EOMONTH(G14,1) -> 45777 | I14: =EOMONTH(H14,1) -> 45808 | J14: =EOMONTH(I14,1) -> 45838 | K14: =EOMONTH(J14,1) -> 45869 | L14: =EOMONTH(K14,1) -> 45900 | M14: =EOMONTH(L14,1) -> 45930 | ... P14: =EOMONTH(O14,1) -> 46022
A15: 1 | D15: Sites with 1 Doctor at YE-24 | E15: =E$23+IF(E7>0,$E26,0) -> 0.41480875 | F15: =F$23+IF(F7>0,$E26,0) -> -0.11745397 | G15: =G$23+IF(G7>0,$E26,0) -> 0.073789234 | H15: =H$23+IF(H7>0,$E26,0) -> 0.071161542 | I15: =I$23+IF(I7>0,$E26,0) -> 0.089469046 | J15: =J$23+IF(J7>0,$E26,0) -> -0.040287147 | K15: =K$23+IF(K7>0,$E26,0) -> -0.28016608 | L15: =L$23+IF(L7>0,$E26,0) -> -0.14250917 | ... P15: =P$23+IF(P7>0,$E26,0) -> -0.18378745
A16: =A15+1 -> 2 | D16: Sites with 2 Doctors at YE-24 | E16: =E$23+IF(E8>0,$E27,0) -> 0.41480875 | F16: =F$23+IF(F8>0,$E27,0) -> 0.082546031 | G16: =G$23+IF(G8>0,$E27,0) -> 0.073789234 | H16: =H$23+IF(H8>0,$E27,0) -> -0.078838458 | I16: =I$23+IF(I8>0,$E27,0) -> 0.089469046 | J16: =J$23+IF(J8>0,$E27,0) -> -0.040287147 | K16: =K$23+IF(K8>0,$E27,0) -> -0.080166078 | L16: =L$23+IF(L8>0,$E27,0) -> -0.14250917 | ... P16: =P$23+IF(P8>0,$E27,0) -> -0.18378745
A17: =A16+1 -> 3 | D17: Sites with 3 Doctors at YE-24 | E17: =E$23+IF(E9>0,$E28,0) -> 0.41480875 | F17: =F$23+IF(F9>0,$E28,0) -> 0.082546031 | G17: =G$23+IF(G9>0,$E28,0) -> 0.073789234 | H17: =H$23+IF(H9>0,$E28,0) -> 0.071161542 | I17: =I$23+IF(I9>0,$E28,0) -> 0.089469046 | J17: =J$23+IF(J9>0,$E28,0) -> -0.040287147 | K17: =K$23+IF(K9>0,$E28,0) -> -0.18016608 | L17: =L$23+IF(L9>0,$E28,0) -> -0.14250917 | ... P17: =P$23+IF(P9>0,$E28,0) -> -0.18378745
A18: =A17+1 -> 4 | D18: Sites with 4 Doctors at YE-24 | E18: =E$23+IF(E10>0,$E29,0) -> 0.41480875 | F18: =F$23+IF(F10>0,$E29,0) -> 0.082546031 | G18: =G$23+IF(G10>0,$E29,0) -> 0.073789234 | H18: =H$23+IF(H10>0,$E29,0) -> 0.071161542 | I18: =I$23+IF(I10>0,$E29,0) -> 0.089469046 | J18: =J$23+IF(J10>0,$E29,0) -> -0.040287147 | K18: =K$23+IF(K10>0,$E29,0) -> -0.080166078 | L18: =L$23+IF(L10>0,$E29,0) -> -0.14250917 | ... P18: =P$23+IF(P10>0,$E29,0) -> -0.18378745
A19: =A18+1 -> 5 | D19: Sites with 5 Doctors at YE-24 | E19: =E$23 -> 0.41480875 | F19: =F$23 -> 0.082546031 | G19: =G$23 -> 0.073789234 | H19: =H$23 -> 0.071161542 | I19: =I$23 -> 0.089469046 | J19: =J$23 -> -0.040287147 | K19: =K$23 -> -0.080166078 | L19: =L$23 -> -0.14250917 | ... P19: =P$23 -> -0.18378745
D21: All Sites - 2024 | E21: ='Cons. Financials - ''23 ''24'!P11/'Cons. Financials - ''23 ''24'!O11-1 -> 0.41147542 | F21: ='Cons. Financials - ''23 ''24'!Q11/'Cons. Financials - ''23 ''24'!P11-1 -> 0.079212697 | G21: ='Cons. Financials - ''23 ''24'!R11/'Cons. Financials - ''23 ''24'!Q11-1 -> 0.070455901 | H21: ='Cons. Financials - ''23 ''24'!S11/'Cons. Financials - ''23 ''24'!R11-1 -> 0.067828209 | I21: ='Cons. Financials - ''23 ''24'!T11/'Cons. Financials - ''23 ''24'!S11-1 -> 0.086135713 | J21: ='Cons. Financials - ''23 ''24'!U11/'Cons. Financials - ''23 ''24'!T11-1 -> -0.043620481 | K21: ='Cons. Financials - ''23 ''24'!V11/'Cons. Financials - ''23 ''24'!U11-1 -> -0.083499412 | L21: ='Cons. Financials - ''23 ''24'!W11/'Cons. Financials - ''23 ''24'!V11-1 -> -0.1458425 | ... P21: ='Cons. Financials - ''23 ''24'!AA11/'Cons. Financials - ''23 ''24'!Z11-1 -> -0.18712078
D22: 2025 Year over Year Growth Adjustment | E22: =4%/12 -> 0.0033333333 | F22: =4%/12 -> 0.0033333333 | G22: =4%/12 -> 0.0033333333 | H22: =4%/12 -> 0.0033333333 | I22: =4%/12 -> 0.0033333333 | J22: =4%/12 -> 0.0033333333 | K22: =4%/12 -> 0.0033333333 | L22: =4%/12 -> 0.0033333333 | ... P22: =4%/12 -> 0.0033333333
D23: Baseline Assumption for 2025 | E23: =SUM(E21:E22) -> 0.41480875 | F23: =SUM(F21:F22) -> 0.082546031 | G23: =SUM(G21:G22) -> 0.073789234 | H23: =SUM(H21:H22) -> 0.071161542 | I23: =SUM(I21:I22) -> 0.089469046 | J23: =SUM(J21:J22) -> -0.040287147 | K23: =SUM(K21:K22) -> -0.080166078 | L23: =SUM(L21:L22) -> -0.14250917 | ... P23: =SUM(P21:P22) -> -0.18378745
D25: MoM Adjustment for Adding New Doctor
D26: Sites with 1 Doctor at YE-24 | E26: -0.2
D27: Sites with 2 Doctors at YE-24 | E27: -0.15
D28: Sites with 3 Doctors at YE-24 | E28: -0.1
D29: Sites with 4 Doctors at YE-24 | E29: -0.05
D31: Other Site Level Assumptions
E32: 45658 | F32: =EOMONTH(E32,1) -> 45716 | G32: =EOMONTH(F32,1) -> 45747 | H32: =EOMONTH(G32,1) -> 45777 | I32: =EOMONTH(H32,1) -> 45808 | J32: =EOMONTH(I32,1) -> 45838 | K32: =EOMONTH(J32,1) -> 45869 | L32: =EOMONTH(K32,1) -> 45900 | M32: =EOMONTH(L32,1) -> 45930 | ... P32: =EOMONTH(O32,1) -> 46022
A33: % of Revenue - Doctor Compensation | D33: YoY Change - % of Revenue - Doctor Compensation | E33: 0 | F33: 0 | G33: 0 | H33: 0 | I33: 0 | J33: 0 | K33: 0 | L33: 0 | M33: 0 | N33: 0 | O33: 0 | P33: 0
A34: % of Revenue - Administrative Staff Compensation | D34: YoY Change - % of Revenue - Administrative Staff Compensation | E34: 0 | F34: 0 | G34: 0 | H34: 0 | I34: 0 | J34: 0 | K34: 0 | L34: 0 | M34: 0 | N34: 0 | O34: 0 | P34: 0
A35: % of Revenue - Office Supplies | D35: YoY Change - % of Revenue - Office Supplies | E35: 0 | F35: 0 | G35: 0 | H35: 0 | I35: 0 | J35: 0 | K35: 0 | L35: 0 | M35: 0 | N35: 0 | O35: 0 | P35: 0
A36: % of Revenue - General and Administrative Expense | D36: YoY Change - % of Revenue - General and Administrative Expense | E36: 0 | F36: 0 | G36: 0 | H36: 0 | I36: 0 | J36: 0 | K36: 0 | L36: 0 | M36: 0 | N36: 0 | O36: 0 | P36: 0
A37: % of Revenue - Marketing | D37: YoY Change - % of Revenue - Marketing | E37: 0 | F37: 0 | G37: 0 | H37: 0 | I37: 0 | J37: 0 | K37: 0 | L37: 0 | M37: 0 | N37: 0 | O37: 0 | P37: 0
A38: % YoY Growth | D38: % YoY Change - Office Rent | E38: 0.03 | F38: 0.03 | G38: 0.03 | H38: 0.03 | I38: 0.03 | J38: 0.03 | K38: 0.03 | L38: 0.03 | M38: 0.03 | N38: 0.03 | O38: 0.03 | P38: 0.03
A39: Collections as a % of Production | D39: YoY Change - Collections as a % of Production | E39: 0 | F39: 0 | G39: 0 | H39: 0 | I39: 0 | J39: 0 | K39: 0 | L39: 0 | M39: 0 | N39: 0 | O39: 0 | P39: 0
D41: Corporate Level & NWC Assumptions
E42: 45658 | F42: =EOMONTH(E42,1) -> 45716 | G42: =EOMONTH(F42,1) -> 45747 | H42: =EOMONTH(G42,1) -> 45777 | I42: =EOMONTH(H42,1) -> 45808 | J42: =EOMONTH(I42,1) -> 45838 | K42: =EOMONTH(J42,1) -> 45869 | L42: =EOMONTH(K42,1) -> 45900 | M42: =EOMONTH(L42,1) -> 45930 | ... P42: =EOMONTH(O42,1) -> 46022
D43: YoY Change - % of Revenue - SG&A | E43: 0 | F43: 0 | G43: 0 | H43: 0 | I43: 0 | J43: 0 | K43: 0 | L43: 0 | M43: 0 | N43: 0 | O43: 0 | P43: 0
D44: YoY Change - Corporate Office Rent | E44: 0.03 | F44: 0.03 | G44: 0.03 | H44: 0.03 | I44: 0.03 | J44: 0.03 | K44: 0.03 | L44: 0.03 | M44: 0.03 | N44: 0.03 | O44: 0.03 | P44: 0.03
D45: Income Tax Rate | E45: 0.25663562 | F45: 0.25663562 | G45: 0.25663562 | H45: 0.25663562 | I45: 0.25663562 | J45: 0.25663562 | K45: 0.25663562 | L45: 0.25663562 | M45: 0.25663562 | N45: 0.25663562 | O45: 0.25663562 | P45: 0.25663562
A46: Accounts Receivable - Days Outstanding | D46: ="YoY Change - "&A46 -> YoY Change - Accounts Receivable - Days Outstanding | E46: 0 | F46: 0 | G46: 0 | H46: 0 | I46: 0 | J46: 0 | K46: 0 | L46: 0 | M46: 0 | N46: 0 | O46: 0 | P46: 0
A47: Inventories - Days Outstanding | D47: ="YoY Change - "&A47 -> YoY Change - Inventories - Days Outstanding | E47: 0 | F47: 0 | G47: 0 | H47: 0 | I47: 0 | J47: 0 | K47: 0 | L47: 0 | M47: 0 | N47: 0 | O47: 0 | P47: 0
A48: Accrued Compensation - % of L3M Corporate Headcount Expenses | D48: ="YoY Change - "&A48 -> YoY Change - Accrued Compensation - % of L3M Corporate Headcount Expenses | E48: 0 | F48: 0 | G48: 0 | H48: 0 | I48: 0 | J48: 0 | K48: 0 | L48: 0 | M48: 0 | N48: 0 | O48: 0 | P48: 0
A49: Prepaid expenses and other current assets - % of L3M Sales | D49: ="YoY Change - "&A49 -> YoY Change - Prepaid expenses and other current assets - % of L3M Sales | E49: 0 | F49: 0 | G49: 0 | H49: 0 | I49: 0 | J49: 0 | K49: 0 | L49: 0 | M49: 0 | N49: 0 | O49: 0 | P49: 0
A50: Accounts Payable - % of L3M SG&A | D50: ="YoY Change - "&A50 -> YoY Change - Accounts Payable - % of L3M SG&A | E50: 0 | F50: 0 | G50: 0 | H50: 0 | I50: 0 | J50: 0 | K50: 0 | L50: 0 | M50: 0 | N50: 0 | O50: 0 | P50: 0
A51: Deferred Revenue - % of L3M Sales | D51: ="YoY Change - "&A51 -> YoY Change - Deferred Revenue - % of L3M Sales | E51: 0 | F51: 0 | G51: 0 | H51: 0 | I51: 0 | J51: 0 | K51: 0 | L51: 0 | M51: 0 | N51: 0 | O51: 0 | P51: 0
A52: Accrued expenses and other current liabilities - % of L3M Sales | D52: ="YoY Change - "&A52 -> YoY Change - Accrued expenses and other current liabilities - % of L3M Sales | E52: 0 | F52: 0 | G52: 0 | H52: 0 | I52: 0 | J52: 0 | K52: 0 | L52: 0 | M52: 0 | N52: 0 | O52: 0 | P52: 0
D53: Capital Expenditures | E53: 500 | F53: 500 | G53: 500 | H53: 500 | I53: 500 | J53: 500 | K53: 1000 | L53: 1000 | M53: 1000 | N53: 1000 | O53: 1000 | P53: 1000
D55: Financing Assumptions
E56: 45658 | F56: =EOMONTH(E56,1) -> 45716 | G56: =EOMONTH(F56,1) -> 45747 | H56: =EOMONTH(G56,1) -> 45777 | I56: =EOMONTH(H56,1) -> 45808 | J56: =EOMONTH(I56,1) -> 45838 | K56: =EOMONTH(J56,1) -> 45869 | L56: =EOMONTH(K56,1) -> 45900 | M56: =EOMONTH(L56,1) -> 45930 | ... P56: =EOMONTH(O56,1) -> 46022
D57: SOFR - 30 Day Average | E57: 0.045 | F57: 0.045 | G57: 0.045 | H57: 0.045 | I57: 0.045 | J57: 0.045 | K57: 0.045 | L57: 0.045 | M57: 0.045 | N57: 0.045 | O57: 0.045 | P57: 0.045
D58: Revolver - Max Capacity | E58: 25000 | F58: 25000 | G58: 25000 | H58: 25000 | I58: 25000 | J58: 25000 | K58: 25000 | L58: 25000 | M58: 25000 | N58: 25000 | O58: 25000 | P58: 25000

Sheet Consolidated Budget - '25
B2: Happy Pets Vets | AE2: =TODAY() -> 45999
C3: Income Statement | AE3: ($ in 000s)
D5: 2024A | P5: 2025 Budget | AC5: Historicals | AE5: Budget
D6: 44957 | E6: =EOMONTH(D6,1) -> 44985 | F6: =EOMONTH(E6,1) -> 45016 | G6: =EOMONTH(F6,1) -> 45046 | H6: =EOMONTH(G6,1) -> 45077 | I6: =EOMONTH(H6,1) -> 45107 | J6: =EOMONTH(I6,1) -> 45138 | K6: =EOMONTH(J6,1) -> 45169 | L6: =EOMONTH(K6,1) -> 45199 | ... AA6: =EOMONTH(Z6,1) -> 45657 | AC6: 45291 | AD6: 45657 | AE6: 46022
C8: Employed Vets | D8: =_xlfn.XLOOKUP($C8,'Cons. Financials - ''23 ''24'!$C$8:$C$79,'Cons. Financials - ''23 ''24'!P$8:P$79) -> 116 | E8: =_xlfn.XLOOKUP($C8,'Cons. Financials - ''23 ''24'!$C$8:$C$79,'Cons. Financials - ''23 ''24'!Q$8:Q$79) -> 106 | F8: =_xlfn.XLOOKUP($C8,'Cons. Financials - ''23 ''24'!$C$8:$C$79,'Cons. Financials - ''23 ''24'!R$8:R$79) -> 98 | G8: =_xlfn.XLOOKUP($C8,'Cons. Financials - ''23 ''24'!$C$8:$C$79,'Cons. Financials - ''23 ''24'!S$8:S$79) -> 86 | H8: =_xlfn.XLOOKUP($C8,'Cons. Financials - ''23 ''24'!$C$8:$C$79,'Cons. Financials - ''23 ''24'!T$8:T$79) -> 72 | I8: =_xlfn.XLOOKUP($C8,'Cons. Financials - ''23 ''24'!$C$8:$C$79,'Cons. Financials - ''23 ''24'!U$8:U$79) -> 79 | J8: =_xlfn.XLOOKUP($C8,'Cons. Financials - ''23 ''24'!$C$8:$C$79,'Cons. Financials - ''23 ''24'!V$8:V$79) -> 92 | K8: =_xlfn.XLOOKUP($C8,'Cons. Financials - ''23 ''24'!$C$8:$C$79,'Cons. Financials - ''23 ''24'!W$8:W$79) -> 113 | ... O8: =_xlfn.XLOOKUP($C8,'Cons. Financials - ''23 ''24'!$C$8:$C$79,'Cons. Financials - ''23 ''24'!AA$8:AA$79) -> 125 | P8: =SUMIFS('Site Level Budget - ''25'!S:S,'Site Level Budget - ''25'!$F:$F,'Consolidated Budget - ''25'!$C8) -> 125 | Q8: =SUMIFS('Site Level Budget - ''25'!T:T,'Site Level Budget - ''25'!$F:$F,'Consolidated Budget - ''25'!$C8) -> 127 | R8: =SUMIFS('Site Level Budget - ''25'!U:U,'Site Level Budget - ''25'!$F:$F,'Consolidated Budget - ''25'!$C8) -> 127 | S8: =SUMIFS('Site Level Budget - ''25'!V:V,'Site Level Budget - ''25'!$F:$F,'Consolidated Budget - ''25'!$C8) -> 129 | T8: =SUMIFS('Site Level Budget - ''25'!W:W,'Site Level Budget - ''25'!$F:$F,'Consolidated Budget - ''25'!$C8) -> 129 | U8: =SUMIFS('Site Level Budget - ''25'!X:X,'Site Level Budget - ''25'!$F:$F,'Consolidated Budget - ''25'!$C8) -> 129 | V8: =SUMIFS('Site Level Budget - ''25'!Y:Y,'Site Level Budget - ''25'!$F:$F,'Consolidated Budget - ''25'!$C8) -> 137 | W8: =SUMIFS('Site Level Budget - ''25'!Z:Z,'Site Level Budget - ''25'!$F:$F,'Consolidated Budget - ''25'!$C8) -> 137 | X8: =SUMIFS('Site Level Budget - ''25'!AA:AA,'Site Level Budget - ''25'!$F:$F,'Consolidated Budget - ''25'!$C8) -> 137 | Y8: =SUMIFS('Site Level Budget - ''25'!AB:AB,'Site Level Budget - ''25'!$F:$F,'Consolidated Budget - ''25'!$C8) -> 137 | Z8: =SUMIFS('Site Level Budget - ''25'!AC:AC,'Site Level Budget - ''25'!$F:$F,'Consolidated Budget - ''25'!$C8) -> 137 | AA8: =SUMIFS('Site Level Budget - ''25'!AD:AD,'Site Level Budget - ''25'!$F:$F,'Consolidated Budget - ''25'!$C8) -> 137 | AC8: ='Cons. Financials - ''23 ''24'!AC8 -> 91.75 | AD8: =AVERAGE(D8:O8) -> 103.08333 | AE8: =AVERAGE(P8:AA8) -> 132.33333
C9: Workdays in Month / Year | D9: =_xlfn.XLOOKUP($C9,'Cons. Financials - ''23 ''24'!$C$8:$C$79,'Cons. Financials - ''23 ''24'!P$8:P$79) -> 22.801724 | E9: =_xlfn.XLOOKUP($C9,'Cons. Financials - ''23 ''24'!$C$8:$C$79,'Cons. Financials - ''23 ''24'!Q$8:Q$79) -> 21.792453 | F9: =_xlfn.XLOOKUP($C9,'Cons. Financials - ''23 ''24'!$C$8:$C$79,'Cons. Financials - ''23 ''24'!R$8:R$79) -> 21.77551 | G9: =_xlfn.XLOOKUP($C9,'Cons. Financials - ''23 ''24'!$C$8:$C$79,'Cons. Financials - ''23 ''24'!S$8:S$79) -> 21.744186 | H9: =_xlfn.XLOOKUP($C9,'Cons. Financials - ''23 ''24'!$C$8:$C$79,'Cons. Financials - ''23 ''24'!T$8:T$79) -> 24 | I9: =_xlfn.XLOOKUP($C9,'Cons. Financials - ''23 ''24'!$C$8:$C$79,'Cons. Financials - ''23 ''24'!U$8:U$79) -> 21 | J9: =_xlfn.XLOOKUP($C9,'Cons. Financials - ''23 ''24'!$C$8:$C$79,'Cons. Financials - ''23 ''24'!V$8:V$79) -> 23 | K9: =_xlfn.XLOOKUP($C9,'Cons. Financials - ''23 ''24'!$C$8:$C$79,'Cons. Financials - ''23 ''24'!W$8:W$79) -> 22.79646 | ... O9: =_xlfn.XLOOKUP($C9,'Cons. Financials - ''23 ''24'!$C$8:$C$79,'Cons. Financials - ''23 ''24'!AA$8:AA$79) -> 22 | P9: =P10/P8 -> 23 | Q9: =Q10/Q8 -> 22 | R9: =R10/R8 -> 22 | S9: =S10/S8 -> 22 | T9: =T10/T8 -> 24 | U9: =U10/U8 -> 21 | V9: =V10/V8 -> 23 | W9: =W10/W8 -> 23 | ... AA9: =AA10/AA8 -> 22 | AC9: ='Cons. Financials - ''23 ''24'!AC9 -> 270.16784 | AD9: =SUM(D9:O9) -> 267.72449 | AE9: =SUM(P9:AA9) -> 269
C10: Total Vet Days | D10: =_xlfn.XLOOKUP($C10,'Cons. Financials - ''23 ''24'!$C$8:$C$79,'Cons. Financials - ''23 ''24'!P$8:P$79) -> 2645 | E10: =_xlfn.XLOOKUP($C10,'Cons. Financials - ''23 ''24'!$C$8:$C$79,'Cons. Financials - ''23 ''24'!Q$8:Q$79) -> 2310 | F10: =_xlfn.XLOOKUP($C10,'Cons. Financials - ''23 ''24'!$C$8:$C$79,'Cons. Financials - ''23 ''24'!R$8:R$79) -> 2134 | G10: =_xlfn.XLOOKUP($C10,'Cons. Financials - ''23 ''24'!$C$8:$C$79,'Cons. Financials - ''23 ''24'!S$8:S$79) -> 1870 | H10: =_xlfn.XLOOKUP($C10,'Cons. Financials - ''23 ''24'!$C$8:$C$79,'Cons. Financials - ''23 ''24'!T$8:T$79) -> 1728 | I10: =_xlfn.XLOOKUP($C10,'Cons. Financials - ''23 ''24'!$C$8:$C$79,'Cons. Financials - ''23 ''24'!U$8:U$79) -> 1659 | J10: =_xlfn.XLOOKUP($C10,'Cons. Financials - ''23 ''24'!$C$8:$C$79,'Cons. Financials - ''23 ''24'!V$8:V$79) -> 2116 | K10: =_xlfn.XLOOKUP($C10,'Cons. Financials - ''23 ''24'!$C$8:$C$79,'Cons. Financials - ''23 ''24'!W$8:W$79) -> 2576 | ... O10: =_xlfn.XLOOKUP($C10,'Cons. Financials - ''23 ''24'!$C$8:$C$79,'Cons. Financials - ''23 ''24'!AA$8:AA$79) -> 2750 | P10: =SUMIFS('Site Level Budget - ''25'!S:S,'Site Level Budget - ''25'!$F:$F,'Consolidated Budget - ''25'!$C10) -> 2875 | Q10: =SUMIFS('Site Level Budget - ''25'!T:T,'Site Level Budget - ''25'!$F:$F,'Consolidated Budget - ''25'!$C10) -> 2794 | R10: =SUMIFS('Site Level Budget - ''25'!U:U,'Site Level Budget - ''25'!$F:$F,'Consolidated Budget - ''25'!$C10) -> 2794 | S10: =SUMIFS('Site Level Budget - ''25'!V:V,'Site Level Budget - ''25'!$F:$F,'Consolidated Budget - ''25'!$C10) -> 2838 | T10: =SUMIFS('Site Level Budget - ''25'!W:W,'Site Level Budget - ''25'!$F:$F,'Consolidated Budget - ''25'!$C10) -> 3096 | U10: =SUMIFS('Site Level Budget - ''25'!X:X,'Site Level Budget - ''25'!$F:$F,'Consolidated Budget - ''25'!$C10) -> 2709 | V10: =SUMIFS('Site Level Budget - ''25'!Y:Y,'Site Level Budget - ''25'!$F:$F,'Consolidated Budget - ''25'!$C10) -> 3151 | W10: =SUMIFS('Site Level Budget - ''25'!Z:Z,'Site Level Budget - ''25'!$F:$F,'Consolidated Budget - ''25'!$C10) -> 3151 | X10: =SUMIFS('Site Level Budget - ''25'!AA:AA,'Site Level Budget - ''25'!$F:$F,'Consolidated Budget - ''25'!$C10) -> 2877 | Y10: =SUMIFS('Site Level Budget - ''25'!AB:AB,'Site Level Budget - ''25'!$F:$F,'Consolidated Budget - ''25'!$C10) -> 3288 | Z10: =SUMIFS('Site Level Budget - ''25'!AC:AC,'Site Level Budget - ''25'!$F:$F,'Consolidated Budget - ''25'!$C10) -> 3014 | AA10: =SUMIFS('Site Level Budget - ''25'!AD:AD,'Site Level Budget - ''25'!$F:$F,'Consolidated Budget - ''25'!$C10) -> 3014 | AC10: ='Cons. Financials - ''23 ''24'!AC10 -> 24725 | AD10: =SUM(D10:O10) -> 27576 | AE10: =SUM(P10:AA10) -> 35601
C11: Production per Vet Workday | D11: =_xlfn.XLOOKUP($C11,'Cons. Financials - ''23 ''24'!$C$8:$C$79,'Cons. Financials - ''23 ''24'!P$8:P$79) -> 5.2302827 | E11: =_xlfn.XLOOKUP($C11,'Cons. Financials - ''23 ''24'!$C$8:$C$79,'Cons. Financials - ''23 ''24'!Q$8:Q$79) -> 5.6445875 | F11: =_xlfn.XLOOKUP($C11,'Cons. Financials - ''23 ''24'!$C$8:$C$79,'Cons. Financials - ''23 ''24'!R$8:R$79) -> 6.042282 | G11: =_xlfn.XLOOKUP($C11,'Cons. Financials - ''23 ''24'!$C$8:$C$79,'Cons. Financials - ''23 ''24'!S$8:S$79) -> 6.4521191 | H11: =_xlfn.XLOOKUP($C11,'Cons. Financials - ''23 ''24'!$C$8:$C$79,'Cons. Financials - ''23 ''24'!T$8:T$79) -> 7.007877 | I11: =_xlfn.XLOOKUP($C11,'Cons. Financials - ''23 ''24'!$C$8:$C$79,'Cons. Financials - ''23 ''24'!U$8:U$79) -> 6.70219 | J11: =_xlfn.XLOOKUP($C11,'Cons. Financials - ''23 ''24'!$C$8:$C$79,'Cons. Financials - ''23 ''24'!V$8:V$79) -> 6.1425611 | K11: =_xlfn.XLOOKUP($C11,'Cons. Financials - ''23 ''24'!$C$8:$C$79,'Cons. Financials - ''23 ''24'!W$8:W$79) -> 5.2467146 | ... O11: =_xlfn.XLOOKUP($C11,'Cons. Financials - ''23 ''24'!$C$8:$C$79,'Cons. Financials - ''23 ''24'!AA$8:AA$79) -> 3.672441 | P11: =P12/P10 -> 5.1958017 | Q11: =Q12/Q10 -> 5.6081573 | R11: =R12/R10 -> 6.0219789 | S11: =S12/S10 -> 6.4128139 | T11: =T12/T10 -> 6.9865623 | U11: =U12/U10 -> 6.7050936 | V11: =V12/V10 -> 5.9939802 | W11: =W12/W10 -> 5.139783 | ... AA11: =AA12/AA10 -> 3.6505511 | AC11: ='Cons. Financials - ''23 ''24'!AC11 -> 5.2426569 | AD11: =AD12/AD10 -> 5.4597704 | AE11: =AE12/AE10 -> 5.5305807
C12: Total Production | D12: =_xlfn.XLOOKUP($C12,'Cons. Financials - ''23 ''24'!$C$8:$C$79,'Cons. Financials - ''23 ''24'!P$8:P$79) -> 13834.098 | E12: =_xlfn.XLOOKUP($C12,'Cons. Financials - ''23 ''24'!$C$8:$C$79,'Cons. Financials - ''23 ''24'!Q$8:Q$79) -> 13038.997 | F12: =_xlfn.XLOOKUP($C12,'Cons. Financials - ''23 ''24'!$C$8:$C$79,'Cons. Financials - ''23 ''24'!R$8:R$79) -> 12894.23 | G12: =_xlfn.XLOOKUP($C12,'Cons. Financials - ''23 ''24'!$C$8:$C$79,'Cons. Financials - ''23 ''24'!S$8:S$79) -> 12065.463 | H12: =_xlfn.XLOOKUP($C12,'Cons. Financials - ''23 ''24'!$C$8:$C$79,'Cons. Financials - ''23 ''24'!T$8:T$79) -> 12109.611 | I12: =_xlfn.XLOOKUP($C12,'Cons. Financials - ''23 ''24'!$C$8:$C$79,'Cons. Financials - ''23 ''24'!U$8:U$79) -> 11118.933 | J12: =_xlfn.XLOOKUP($C12,'Cons. Financials - ''23 ''24'!$C$8:$C$79,'Cons. Financials - ''23 ''24'!V$8:V$79) -> 12997.659 | K12: =_xlfn.XLOOKUP($C12,'Cons. Financials - ''23 ''24'!$C$8:$C$79,'Cons. Financials - ''23 ''24'!W$8:W$79) -> 13515.537 | ... O12: =_xlfn.XLOOKUP($C12,'Cons. Financials - ''23 ''24'!$C$8:$C$79,'Cons. Financials - ''23 ''24'!AA$8:AA$79) -> 10099.213 | P12: =SUMIFS('Site Level Budget - ''25'!S:S,'Site Level Budget - ''25'!$F:$F,'Consolidated Budget - ''25'!$C12) -> 14937.93 | Q12: =SUMIFS('Site Level Budget - ''25'!T:T,'Site Level Budget - ''25'!$F:$F,'Consolidated Budget - ''25'!$C12) -> 15669.191 | R12: =SUMIFS('Site Level Budget - ''25'!U:U,'Site Level Budget - ''25'!$F:$F,'Consolidated Budget - ''25'!$C12) -> 16825.409 | S12: =SUMIFS('Site Level Budget - ''25'!V:V,'Site Level Budget - ''25'!$F:$F,'Consolidated Budget - ''25'!$C12) -> 18199.566 | T12: =SUMIFS('Site Level Budget - ''25'!W:W,'Site Level Budget - ''25'!$F:$F,'Consolidated Budget - ''25'!$C12) -> 21630.397 | U12: =SUMIFS('Site Level Budget - ''25'!X:X,'Site Level Budget - ''25'!$F:$F,'Consolidated Budget - ''25'!$C12) -> 18164.099 | V12: =SUMIFS('Site Level Budget - ''25'!Y:Y,'Site Level Budget - ''25'!$F:$F,'Consolidated Budget - ''25'!$C12) -> 18887.032 | W12: =SUMIFS('Site Level Budget - ''25'!Z:Z,'Site Level Budget - ''25'!$F:$F,'Consolidated Budget - ''25'!$C12) -> 16195.456 | X12: =SUMIFS('Site Level Budget - ''25'!AA:AA,'Site Level Budget - ''25'!$F:$F,'Consolidated Budget - ''25'!$C12) -> 14848.594 | Y12: =SUMIFS('Site Level Budget - ''25'!AB:AB,'Site Level Budget - ''25'!$F:$F,'Consolidated Budget - ''25'!$C12) -> 17053.503 | Z12: =SUMIFS('Site Level Budget - ''25'!AC:AC,'Site Level Budget - ''25'!$F:$F,'Consolidated Budget - ''25'!$C12) -> 13480.265 | AA12: =SUMIFS('Site Level Budget - ''25'!AD:AD,'Site Level Budget - ''25'!$F:$F,'Consolidated Budget - ''25'!$C12) -> 11002.761 | AC12: ='Cons. Financials - ''23 ''24'!AC12 -> 129624.69 | AD12: =SUM(D12:O12) -> 150558.63 | AE12: =SUM(P12:AA12) -> 196894.2
C13: Revenue as a % of Production | D13: =_xlfn.XLOOKUP($C13,'Cons. Financials - ''23 ''24'!$C$8:$C$79,'Cons. Financials - ''23 ''24'!P$8:P$79) -> 0.97968328 | E13: =_xlfn.XLOOKUP($C13,'Cons. Financials - ''23 ''24'!$C$8:$C$79,'Cons. Financials - ''23 ''24'!Q$8:Q$79) -> 0.97955179 | F13: =_xlfn.XLOOKUP($C13,'Cons. Financials - ''23 ''24'!$C$8:$C$79,'Cons. Financials - ''23 ''24'!R$8:R$79) -> 0.97940904 | G13: =_xlfn.XLOOKUP($C13,'Cons. Financials - ''23 ''24'!$C$8:$C$79,'Cons. Financials - ''23 ''24'!S$8:S$79) -> 0.97938359 | H13: =_xlfn.XLOOKUP($C13,'Cons. Financials - ''23 ''24'!$C$8:$C$79,'Cons. Financials - ''23 ''24'!T$8:T$79) -> 0.97919883 | I13: =_xlfn.XLOOKUP($C13,'Cons. Financials - ''23 ''24'!$C$8:$C$79,'Cons. Financials - ''23 ''24'!U$8:U$79) -> 0.97919968 | J13: =_xlfn.XLOOKUP($C13,'Cons. Financials - ''23 ''24'!$C$8:$C$79,'Cons. Financials - ''23 ''24'!V$8:V$79) -> 0.97923242 | K13: =_xlfn.XLOOKUP($C13,'Cons. Financials - ''23 ''24'!$C$8:$C$79,'Cons. Financials - ''23 ''24'!W$8:W$79) -> 0.9795568 | ... O13: =_xlfn.XLOOKUP($C13,'Cons. Financials - ''23 ''24'!$C$8:$C$79,'Cons. Financials - ''23 ''24'!AA$8:AA$79) -> 0.9797479 | P13: =P14/P12 -> 0.98001835 | Q13: =Q14/Q12 -> 0.98003254 | R13: =R14/R12 -> 0.98003254 | S13: =S14/S12 -> 0.98006934 | T13: =T14/T12 -> 0.98006934 | U13: =U14/U12 -> 0.98006934 | V13: =V14/V12 -> 0.98001182 | W13: =W14/W12 -> 0.98001182 | ... AA13: =AA14/AA12 -> 0.98001182 | AC13: ='Cons. Financials - ''23 ''24'!AC13 -> 0.98043866 | AD13: =AD14/AD12 -> 0.97946656 | AE13: =AE14/AE12 -> 0.98003268
C14: Total Revenue | D14: =_xlfn.XLOOKUP($C14,'Cons. Financials - ''23 ''24'!$C$8:$C$79,'Cons. Financials - ''23 ''24'!P$8:P$79) -> 13553.034 | E14: =_xlfn.XLOOKUP($C14,'Cons. Financials - ''23 ''24'!$C$8:$C$79,'Cons. Financials - ''23 ''24'!Q$8:Q$79) -> 12772.373 | F14: =_xlfn.XLOOKUP($C14,'Cons. Financials - ''23 ''24'!$C$8:$C$79,'Cons. Financials - ''23 ''24'!R$8:R$79) -> 12628.725 | G14: =_xlfn.XLOOKUP($C14,'Cons. Financials - ''23 ''24'!$C$8:$C$79,'Cons. Financials - ''23 ''24'!S$8:S$79) -> 11816.716 | H14: =_xlfn.XLOOKUP($C14,'Cons. Financials - ''23 ''24'!$C$8:$C$79,'Cons. Financials - ''23 ''24'!T$8:T$79) -> 11857.717 | I14: =_xlfn.XLOOKUP($C14,'Cons. Financials - ''23 ''24'!$C$8:$C$79,'Cons. Financials - ''23 ''24'!U$8:U$79) -> 10887.656 | J14: =_xlfn.XLOOKUP($C14,'Cons. Financials - ''23 ''24'!$C$8:$C$79,'Cons. Financials - ''23 ''24'!V$8:V$79) -> 12727.729 | K14: =_xlfn.XLOOKUP($C14,'Cons. Financials - ''23 ''24'!$C$8:$C$79,'Cons. Financials - ''23 ''24'!W$8:W$79) -> 13239.236 | ... O14: =_xlfn.XLOOKUP($C14,'Cons. Financials - ''23 ''24'!$C$8:$C$79,'Cons. Financials - ''23 ''24'!AA$8:AA$79) -> 9894.6826 | P14: =SUMIFS('Site Level Budget - ''25'!S:S,'Site Level Budget - ''25'!$F:$F,'Consolidated Budget - ''25'!$C14) -> 14639.446 | Q14: =SUMIFS('Site Level Budget - ''25'!T:T,'Site Level Budget - ''25'!$F:$F,'Consolidated Budget - ''25'!$C14) -> 15356.317 | R14: =SUMIFS('Site Level Budget - ''25'!U:U,'Site Level Budget - ''25'!$F:$F,'Consolidated Budget - ''25'!$C14) -> 16489.448 | S14: =SUMIFS('Site Level Budget - ''25'!V:V,'Site Level Budget - ''25'!$F:$F,'Consolidated Budget - ''25'!$C14) -> 17836.837 | T14: =SUMIFS('Site Level Budget - ''25'!W:W,'Site Level Budget - ''25'!$F:$F,'Consolidated Budget - ''25'!$C14) -> 21199.289 | U14: =SUMIFS('Site Level Budget - ''25'!X:X,'Site Level Budget - ''25'!$F:$F,'Consolidated Budget - ''25'!$C14) -> 17802.076 | V14: =SUMIFS('Site Level Budget - ''25'!Y:Y,'Site Level Budget - ''25'!$F:$F,'Consolidated Budget - ''25'!$C14) -> 18509.514 | W14: =SUMIFS('Site Level Budget - ''25'!Z:Z,'Site Level Budget - ''25'!$F:$F,'Consolidated Budget - ''25'!$C14) -> 15871.739 | X14: =SUMIFS('Site Level Budget - ''25'!AA:AA,'Site Level Budget - ''25'!$F:$F,'Consolidated Budget - ''25'!$C14) -> 14551.798 | Y14: =SUMIFS('Site Level Budget - ''25'!AB:AB,'Site Level Budget - ''25'!$F:$F,'Consolidated Budget - ''25'!$C14) -> 16712.634 | Z14: =SUMIFS('Site Level Budget - ''25'!AC:AC,'Site Level Budget - ''25'!$F:$F,'Consolidated Budget - ''25'!$C14) -> 13210.819 | AA14: =SUMIFS('Site Level Budget - ''25'!AD:AD,'Site Level Budget - ''25'!$F:$F,'Consolidated Budget - ''25'!$C14) -> 10782.836 | AC14: ='Cons. Financials - ''23 ''24'!AC14 -> 127089.06 | AD14: =SUM(D14:O14) -> 147467.14 | AE14: =SUM(P14:AA14) -> 192962.75
C15: % YoY Revenue Growth | D15: =_xlfn.XLOOKUP($C15,'Cons. Financials - ''23 ''24'!$C$8:$C$79,'Cons. Financials - ''23 ''24'!P$8:P$79) -> 0.48161848 | E15: =_xlfn.XLOOKUP($C15,'Cons. Financials - ''23 ''24'!$C$8:$C$79,'Cons. Financials - ''23 ''24'!Q$8:Q$79) -> 0.44537408 | F15: =_xlfn.XLOOKUP($C15,'Cons. Financials - ''23 ''24'!$C$8:$C$79,'Cons. Financials - ''23 ''24'!R$8:R$79) -> 0.30956681 | G15: =_xlfn.XLOOKUP($C15,'Cons. Financials - ''23 ''24'!$C$8:$C$79,'Cons. Financials - ''23 ''24'!S$8:S$79) -> 0.3299737 | H15: =_xlfn.XLOOKUP($C15,'Cons. Financials - ''23 ''24'!$C$8:$C$79,'Cons. Financials - ''23 ''24'!T$8:T$79) -> 0.20921941 | I15: =_xlfn.XLOOKUP($C15,'Cons. Financials - ''23 ''24'!$C$8:$C$79,'Cons. Financials - ''23 ''24'!U$8:U$79) -> 0.14250038 | J15: =_xlfn.XLOOKUP($C15,'Cons. Financials - ''23 ''24'!$C$8:$C$79,'Cons. Financials - ''23 ''24'!V$8:V$79) -> 0.25017714 | K15: =_xlfn.XLOOKUP($C15,'Cons. Financials - ''23 ''24'!$C$8:$C$79,'Cons. Financials - ''23 ''24'!W$8:W$79) -> 0.02419435 | ... O15: =_xlfn.XLOOKUP($C15,'Cons. Financials - ''23 ''24'!$C$8:$C$79,'Cons. Financials - ''23 ''24'!AA$8:AA$79) -> -0.13453179 | P15: =P14/D14-1 -> 0.080160003 | Q15: =Q14/E14-1 -> 0.20230732 | R15: =R14/F14-1 -> 0.30570966 | S15: =S14/G14-1 -> 0.50945798 | T15: =T14/H14-1 -> 0.7878052 | U15: =U14/I14-1 -> 0.6350697 | V15: =V14/J14-1 -> 0.45426678 | W15: =W14/K14-1 -> 0.19884097 | ... AA15: =AA14/O14-1 -> 0.089760678 | AC15: ='Cons. Financials - ''23 ''24'!AC15 -> 0 | AD15: =AD14/AC14-1 -> 0.1603449 | AE15: =AE14/AD14-1 -> 0.30851355
D16: =_xlfn.XLOOKUP($C16,'Cons. Financials - ''23 ''24'!$C$8:$C$79,'Cons. Financials - ''23 ''24'!P$8:P$79) -> 0 | E16: =_xlfn.XLOOKUP($C16,'Cons. Financials - ''23 ''24'!$C$8:$C$79,'Cons. Financials - ''23 ''24'!Q$8:Q$79) -> 0 | F16: =_xlfn.XLOOKUP($C16,'Cons. Financials - ''23 ''24'!$C$8:$C$79,'Cons. Financials - ''23 ''24'!R$8:R$79) -> 0 | G16: =_xlfn.XLOOKUP($C16,'Cons. Financials - ''23 ''24'!$C$8:$C$79,'Cons. Financials - ''23 ''24'!S$8:S$79) -> 0 | H16: =_xlfn.XLOOKUP($C16,'Cons. Financials - ''23 ''24'!$C$8:$C$79,'Cons. Financials - ''23 ''24'!T$8:T$79) -> 0 | I16: =_xlfn.XLOOKUP($C16,'Cons. Financials - ''23 ''24'!$C$8:$C$79,'Cons. Financials - ''23 ''24'!U$8:U$79) -> 0 | J16: =_xlfn.XLOOKUP($C16,'Cons. Financials - ''23 ''24'!$C$8:$C$79,'Cons. Financials - ''23 ''24'!V$8:V$79) -> 0 | K16: =_xlfn.XLOOKUP($C16,'Cons. Financials - ''23 ''24'!$C$8:$C$79,'Cons. Financials - ''23 ''24'!W$8:W$79) -> 0 | ... O16: =_xlfn.XLOOKUP($C16,'Cons. Financials - ''23 ''24'!$C$8:$C$79,'Cons. Financials - ''23 ''24'!AA$8:AA$79) -> 0 | AC16: ='Cons. Financials - ''23 ''24'!AC16 -> 0
C17: Doctor Compensation | D17: =_xlfn.XLOOKUP($C17,'Cons. Financials - ''23 ''24'!$C$8:$C$79,'Cons. Financials - ''23 ''24'!P$8:P$79) -> -4032.1322 | E17: =_xlfn.XLOOKUP($C17,'Cons. Financials - ''23 ''24'!$C$8:$C$79,'Cons. Financials - ''23 ''24'!Q$8:Q$79) -> -4085.7998 | F17: =_xlfn.XLOOKUP($C17,'Cons. Financials - ''23 ''24'!$C$8:$C$79,'Cons. Financials - ''23 ''24'!R$8:R$79) -> -4099.6397 | G17: =_xlfn.XLOOKUP($C17,'Cons. Financials - ''23 ''24'!$C$8:$C$79,'Cons. Financials - ''23 ''24'!S$8:S$79) -> -4139.5895 | H17: =_xlfn.XLOOKUP($C17,'Cons. Financials - ''23 ''24'!$C$8:$C$79,'Cons. Financials - ''23 ''24'!T$8:T$79) -> -4349.17 | I17: =_xlfn.XLOOKUP($C17,'Cons. Financials - ''23 ''24'!$C$8:$C$79,'Cons. Financials - ''23 ''24'!U$8:U$79) -> -3780.9726 | J17: =_xlfn.XLOOKUP($C17,'Cons. Financials - ''23 ''24'!$C$8:$C$79,'Cons. Financials - ''23 ''24'!V$8:V$79) -> -4111.7717 | K17: =_xlfn.XLOOKUP($C17,'Cons. Financials - ''23 ''24'!$C$8:$C$79,'Cons. Financials - ''23 ''24'!W$8:W$79) -> -3704.5698 | ... O17: =_xlfn.XLOOKUP($C17,'Cons. Financials - ''23 ''24'!$C$8:$C$79,'Cons. Financials - ''23 ''24'!AA$8:AA$79) -> -2724.9779 | P17: =SUMIFS('Site Level Budget - ''25'!S:S,'Site Level Budget - ''25'!$F:$F,'Consolidated Budget - ''25'!$C17) -> -4392.0461 | Q17: =SUMIFS('Site Level Budget - ''25'!T:T,'Site Level Budget - ''25'!$F:$F,'Consolidated Budget - ''25'!$C17) -> -4946.5038 | R17: =SUMIFS('Site Level Budget - ''25'!U:U,'Site Level Budget - ''25'!$F:$F,'Consolidated Budget - ''25'!$C17) -> -5448.4466 | S17: =SUMIFS('Site Level Budget - ''25'!V:V,'Site Level Budget - ''25'!$F:$F,'Consolidated Budget - ''25'!$C17) -> -6518.3659 | T17: =SUMIFS('Site Level Budget - ''25'!W:W,'Site Level Budget - ''25'!$F:$F,'Consolidated Budget - ''25'!$C17) -> -7933.2706 | U17: =SUMIFS('Site Level Budget - ''25'!X:X,'Site Level Budget - ''25'!$F:$F,'Consolidated Budget - ''25'!$C17) -> -6322.0703 | V17: =SUMIFS('Site Level Budget - ''25'!Y:Y,'Site Level Budget - ''25'!$F:$F,'Consolidated Budget - ''25'!$C17) -> -6127.642 | W17: =SUMIFS('Site Level Budget - ''25'!Z:Z,'Site Level Budget - ''25'!$F:$F,'Consolidated Budget - ''25'!$C17) -> -4485.0988 | X17: =SUMIFS('Site Level Budget - ''25'!AA:AA,'Site Level Budget - ''25'!$F:$F,'Consolidated Budget - ''25'!$C17) -> -4425.6795 | Y17: =SUMIFS('Site Level Budget - ''25'!AB:AB,'Site Level Budget - ''25'!$F:$F,'Consolidated Budget - ''25'!$C17) -> -5194.4768 | Z17: =SUMIFS('Site Level Budget - ''25'!AC:AC,'Site Level Budget - ''25'!$F:$F,'Consolidated Budget - ''25'!$C17) -> -3610.5648 | AA17: =SUMIFS('Site Level Budget - ''25'!AD:AD,'Site Level Budget - ''25'!$F:$F,'Consolidated Budget - ''25'!$C17) -> -3013.6255 | AC17: ='Cons. Financials - ''23 ''24'!AC17 -> -38614.057 | AD17: =SUM(D17:O17) -> -46137.125 | AE17: =SUM(P17:AA17) -> -62417.791
C18: % of Revenue | D18: =-(D17/D$14) -> 0.29750771 | E18: =-(E17/E$14) -> 0.31989356 | F18: =-(F17/F$14) -> 0.32462815 | G18: =-(G17/G$14) -> 0.3503164 | H18: =-(H17/H$14) -> 0.36677969 | I18: =-(I17/I$14) -> 0.3472715 | J18: =-(J17/J$14) -> 0.32305618 | K18: =-(K17/K$14) -> 0.27981749 | ... AA18: =-(AA17/AA$14) -> 0.27948357 | AC18: ='Cons. Financials - ''23 ''24'!AC18 -> 0.30383463 | AD18: =-(AD17/AD$14) -> 0.31286376 | AE18: =-(AE17/AE$14) -> 0.32347067
AC19: ='Cons. Financials - ''23 ''24'!AC19 -> 0
C20: Administrative Staff Compensation | D20: =_xlfn.XLOOKUP($C20,'Cons. Financials - ''23 ''24'!$C$8:$C$79,'Cons. Financials - ''23 ''24'!P$8:P$79) -> -2181.494 | E20: =_xlfn.XLOOKUP($C20,'Cons. Financials - ''23 ''24'!$C$8:$C$79,'Cons. Financials - ''23 ''24'!Q$8:Q$79) -> -2236.7333 | F20: =_xlfn.XLOOKUP($C20,'Cons. Financials - ''23 ''24'!$C$8:$C$79,'Cons. Financials - ''23 ''24'!R$8:R$79) -> -2394.2282 | G20: =_xlfn.XLOOKUP($C20,'Cons. Financials - ''23 ''24'!$C$8:$C$79,'Cons. Financials - ''23 ''24'!S$8:S$79) -> -2591.1156 | H20: =_xlfn.XLOOKUP($C20,'Cons. Financials - ''23 ''24'!$C$8:$C$79,'Cons. Financials - ''23 ''24'!T$8:T$79) -> -2967.9251 | I20: =_xlfn.XLOOKUP($C20,'Cons. Financials - ''23 ''24'!$C$8:$C$79,'Cons. Financials - ''23 ''24'!U$8:U$79) -> -2556.2504 | J20: =_xlfn.XLOOKUP($C20,'Cons. Financials - ''23 ''24'!$C$8:$C$79,'Cons. Financials - ''23 ''24'!V$8:V$79) -> -2600.6546 | K20: =_xlfn.XLOOKUP($C20,'Cons. Financials - ''23 ''24'!$C$8:$C$79,'Cons. Financials - ''23 ''24'!W$8:W$79) -> -2253.4917 | ... O20: =_xlfn.XLOOKUP($C20,'Cons. Financials - ''23 ''24'!$C$8:$C$79,'Cons. Financials - ''23 ''24'!AA$8:AA$79) -> -1537.826 | P20: =SUMIFS('Site Level Budget - ''25'!S:S,'Site Level Budget - ''25'!$F:$F,'Consolidated Budget - ''25'!$C20) -> -2424.9389 | Q20: =SUMIFS('Site Level Budget - ''25'!T:T,'Site Level Budget - ''25'!$F:$F,'Consolidated Budget - ''25'!$C20) -> -2783.5486 | R20: =SUMIFS('Site Level Budget - ''25'!U:U,'Site Level Budget - ''25'!$F:$F,'Consolidated Budget - ''25'!$C20) -> -3222.5747 | S20: =SUMIFS('Site Level Budget - ''25'!V:V,'Site Level Budget - ''25'!$F:$F,'Consolidated Budget - ''25'!$C20) -> -4147.0553 | T20: =SUMIFS('Site Level Budget - ''25'!W:W,'Site Level Budget - ''25'!$F:$F,'Consolidated Budget - ''25'!$C20) -> -5732.5853 | U20: =SUMIFS('Site Level Budget - ''25'!X:X,'Site Level Budget - ''25'!$F:$F,'Consolidated Budget - ''25'!$C20) -> -4424.2605 | V20: =SUMIFS('Site Level Budget - ''25'!Y:Y,'Site Level Budget - ''25'!$F:$F,'Consolidated Budget - ''25'!$C20) -> -4034.7727 | W20: =SUMIFS('Site Level Budget - ''25'!Z:Z,'Site Level Budget - ''25'!$F:$F,'Consolidated Budget - ''25'!$C20) -> -2765.7384 | X20: =SUMIFS('Site Level Budget - ''25'!AA:AA,'Site Level Budget - ''25'!$F:$F,'Consolidated Budget - ''25'!$C20) -> -2573.0033 | Y20: =SUMIFS('Site Level Budget - ''25'!AB:AB,'Site Level Budget - ''25'!$F:$F,'Consolidated Budget - ''25'!$C20) -> -2990.7535 | Z20: =SUMIFS('Site Level Budget - ''25'!AC:AC,'Site Level Budget - ''25'!$F:$F,'Consolidated Budget - ''25'!$C20) -> -2056.3073 | AA20: =SUMIFS('Site Level Budget - ''25'!AD:AD,'Site Level Budget - ''25'!$F:$F,'Consolidated Budget - ''25'!$C20) -> -1701.0435 | AC20: ='Cons. Financials - ''23 ''24'!AC20 -> -22557.406 | AD20: =SUM(D20:O20) -> -27690.66 | AE20: =SUM(P20:AA20) -> -38856.582
C21: % of Revenue | D21: =-(D20/D$14) -> 0.16095982 | E21: =-(E20/E$14) -> 0.17512277 | F21: =-(F20/F$14) -> 0.1895859 | G21: =-(G20/G$14) -> 0.21927544 | H21: =-(H20/H$14) -> 0.25029481 | I21: =-(I20/I$14) -> 0.23478427 | J21: =-(J20/J$14) -> 0.20432982 | K21: =-(K20/K$14) -> 0.17021312 | ... AA21: =-(AA20/AA$14) -> 0.15775474 | AC21: ='Cons. Financials - ''23 ''24'!AC21 -> 0.1774929 | AD21: =-(AD20/AD$14) -> 0.18777512 | AE21: =-(AE20/AE$14) -> 0.2013683
AC22: ='Cons. Financials - ''23 ''24'!AC22 -> 0
C23: Office Supplies | D23: =_xlfn.XLOOKUP($C23,'Cons. Financials - ''23 ''24'!$C$8:$C$79,'Cons. Financials - ''23 ''24'!P$8:P$79) -> -772.78999 | E23: =_xlfn.XLOOKUP($C23,'Cons. Financials - ''23 ''24'!$C$8:$C$79,'Cons. Financials - ''23 ''24'!Q$8:Q$79) -> -790.629 | F23: =_xlfn.XLOOKUP($C23,'Cons. Financials - ''23 ''24'!$C$8:$C$79,'Cons. Financials - ''23 ''24'!R$8:R$79) -> -853.76672 | G23: =_xlfn.XLOOKUP($C23,'Cons. Financials - ''23 ''24'!$C$8:$C$79,'Cons. Financials - ''23 ''24'!S$8:S$79) -> -921.87788 | H23: =_xlfn.XLOOKUP($C23,'Cons. Financials - ''23 ''24'!$C$8:$C$79,'Cons. Financials - ''23 ''24'!T$8:T$79) -> -1103.8376 | I23: =_xlfn.XLOOKUP($C23,'Cons. Financials - ''23 ''24'!$C$8:$C$79,'Cons. Financials - ''23 ''24'!U$8:U$79) -> -915.14327 | J23: =_xlfn.XLOOKUP($C23,'Cons. Financials - ''23 ''24'!$C$8:$C$79,'Cons. Financials - ''23 ''24'!V$8:V$79) -> -925.59907 | K23: =_xlfn.XLOOKUP($C23,'Cons. Financials - ''23 ''24'!$C$8:$C$79,'Cons. Financials - ''23 ''24'!W$8:W$79) -> -791.1068 | ... O23: =_xlfn.XLOOKUP($C23,'Cons. Financials - ''23 ''24'!$C$8:$C$79,'Cons. Financials - ''23 ''24'!AA$8:AA$79) -> -524.25461 | P23: =SUMIFS('Site Level Budget - ''25'!S:S,'Site Level Budget - ''25'!$F:$F,'Consolidated Budget - ''25'!$C23) -> -832.89153 | Q23: =SUMIFS('Site Level Budget - ''25'!T:T,'Site Level Budget - ''25'!$F:$F,'Consolidated Budget - ''25'!$C23) -> -952.34169 | R23: =SUMIFS('Site Level Budget - ''25'!U:U,'Site Level Budget - ''25'!$F:$F,'Consolidated Budget - ''25'!$C23) -> -1122.9915 | S23: =SUMIFS('Site Level Budget - ''25'!V:V,'Site Level Budget - ''25'!$F:$F,'Consolidated Budget - ''25'!$C23) -> -1451.2514 | T23: =SUMIFS('Site Level Budget - ''25'!W:W,'Site Level Budget - ''25'!$F:$F,'Consolidated Budget - ''25'!$C23) -> -2074.2657 | U23: =SUMIFS('Site Level Budget - ''25'!X:X,'Site Level Budget - ''25'!$F:$F,'Consolidated Budget - ''25'!$C23) -> -1546.451 | V23: =SUMIFS('Site Level Budget - ''25'!Y:Y,'Site Level Budget - ''25'!$F:$F,'Consolidated Budget - ''25'!$C23) -> -1407.69 | W23: =SUMIFS('Site Level Budget - ''25'!Z:Z,'Site Level Budget - ''25'!$F:$F,'Consolidated Budget - ''25'!$C23) -> -954.56583 | X23: =SUMIFS('Site Level Budget - ''25'!AA:AA,'Site Level Budget - ''25'!$F:$F,'Consolidated Budget - ''25'!$C23) -> -876.25142 | Y23: =SUMIFS('Site Level Budget - ''25'!AB:AB,'Site Level Budget - ''25'!$F:$F,'Consolidated Budget - ''25'!$C23) -> -1013.4337 | Z23: =SUMIFS('Site Level Budget - ''25'!AC:AC,'Site Level Budget - ''25'!$F:$F,'Consolidated Budget - ''25'!$C23) -> -694.01026 | AA23: =SUMIFS('Site Level Budget - ''25'!AD:AD,'Site Level Budget - ''25'!$F:$F,'Consolidated Budget - ''25'!$C23) -> -577.9311 | AC23: ='Cons. Financials - ''23 ''24'!AC23 -> -9020.3982 | AD23: =SUM(D23:O23) -> -9791.4808 | AE23: =SUM(P23:AA23) -> -13504.075
C24: % of Revenue | D24: =-(D23/D$14) -> 0.057019703 | E24: =-(E23/E$14) -> 0.061901496 | F24: =-(F23/F$14) -> 0.067605139 | G24: =-(G23/G$14) -> 0.078014726 | H24: =-(H23/H$14) -> 0.093090223 | I24: =-(I23/I$14) -> 0.084053287 | J24: =-(J23/J$14) -> 0.072723032 | K24: =-(K23/K$14) -> 0.059754716 | ... AA24: =-(AA23/AA$14) -> 0.053597319 | AC24: ='Cons. Financials - ''23 ''24'!AC24 -> 0.070976984 | AD24: =-(AD23/AD$14) -> 0.066397712 | AE24: =-(AE23/AE$14) -> 0.069982808
AC25: ='Cons. Financials - ''23 ''24'!AC25 -> 0
C26: Office Gross Profit | D26: =D14+D17+D20+D23 -> 6566.618 | E26: =E14+E17+E20+E23 -> 5659.2109 | F26: =F14+F17+F20+F23 -> 5281.0905 | G26: =G14+G17+G20+G23 -> 4164.1334 | H26: =H14+H17+H20+H23 -> 3436.7847 | I26: =I14+I17+I20+I23 -> 3635.2896 | J26: =J14+J17+J20+J23 -> 5089.704 | K26: =K14+K17+K20+K23 -> 6490.0678 | ... AA26: =AA14+AA17+AA20+AA23 -> 5490.2359 | AC26: ='Cons. Financials - ''23 ''24'!AC26 -> 56897.198 | AD26: =SUM(D26:O26) -> 63847.876 | AE26: =SUM(P26:AA26) -> 78184.305
C27: % of Revenue | D27: =(D26/D$14) -> 0.48451276 | E27: =(E26/E$14) -> 0.44308218 | F27: =(F26/F$14) -> 0.41818081 | G27: =(G26/G$14) -> 0.35239344 | H27: =(H26/H$14) -> 0.28983527 | I27: =(I26/I$14) -> 0.33389094 | J27: =(J26/J$14) -> 0.39989097 | K27: =(K26/K$14) -> 0.49021467 | ... AA27: =(AA26/AA$14) -> 0.50916437 | AC27: ='Cons. Financials - ''23 ''24'!AC27 -> 0.44769548 | AD27: =(AD26/AD$14) -> 0.43296341 | AE27: =(AE26/AE$14) -> 0.40517822
AC28: ='Cons. Financials - ''23 ''24'!AC28 -> 0
C29: General and Administrative Expense | D29: =_xlfn.XLOOKUP($C29,'Cons. Financials - ''23 ''24'!$C$8:$C$79,'Cons. Financials - ''23 ''24'!P$8:P$79) -> -520.2268 | E29: =_xlfn.XLOOKUP($C29,'Cons. Financials - ''23 ''24'!$C$8:$C$79,'Cons. Financials - ''23 ''24'!Q$8:Q$79) -> -531.73365 | F29: =_xlfn.XLOOKUP($C29,'Cons. Financials - ''23 ''24'!$C$8:$C$79,'Cons. Financials - ''23 ''24'!R$8:R$79) -> -581.61048 | G29: =_xlfn.XLOOKUP($C29,'Cons. Financials - ''23 ''24'!$C$8:$C$79,'Cons. Financials - ''23 ''24'!S$8:S$79) -> -625.21945 | H29: =_xlfn.XLOOKUP($C29,'Cons. Financials - ''23 ''24'!$C$8:$C$79,'Cons. Financials - ''23 ''24'!T$8:T$79) -> -755.27144 | I29: =_xlfn.XLOOKUP($C29,'Cons. Financials - ''23 ''24'!$C$8:$C$79,'Cons. Financials - ''23 ''24'!U$8:U$79) -> -632.69583 | J29: =_xlfn.XLOOKUP($C29,'Cons. Financials - ''23 ''24'!$C$8:$C$79,'Cons. Financials - ''23 ''24'!V$8:V$79) -> -642.35044 | K29: =_xlfn.XLOOKUP($C29,'Cons. Financials - ''23 ''24'!$C$8:$C$79,'Cons. Financials - ''23 ''24'!W$8:W$79) -> -540.61414 | ... O29: =_xlfn.XLOOKUP($C29,'Cons. Financials - ''23 ''24'!$C$8:$C$79,'Cons. Financials - ''23 ''24'!AA$8:AA$79) -> -352.57552 | P29: =SUMIFS('Site Level Budget - ''25'!S:S,'Site Level Budget - ''25'!$F:$F,'Consolidated Budget - ''25'!$C29) -> -557.18909 | Q29: =SUMIFS('Site Level Budget - ''25'!T:T,'Site Level Budget - ''25'!$F:$F,'Consolidated Budget - ''25'!$C29) -> -645.80606 | R29: =SUMIFS('Site Level Budget - ''25'!U:U,'Site Level Budget - ''25'!$F:$F,'Consolidated Budget - ''25'!$C29) -> -771.0925 | S29: =SUMIFS('Site Level Budget - ''25'!V:V,'Site Level Budget - ''25'!$F:$F,'Consolidated Budget - ''25'!$C29) -> -1012.1301 | T29: =SUMIFS('Site Level Budget - ''25'!W:W,'Site Level Budget - ''25'!$F:$F,'Consolidated Budget - ''25'!$C29) -> -1543.0779 | U29: =SUMIFS('Site Level Budget - ''25'!X:X,'Site Level Budget - ''25'!$F:$F,'Consolidated Budget - ''25'!$C29) -> -1172.5585 | V29: =SUMIFS('Site Level Budget - ''25'!Y:Y,'Site Level Budget - ''25'!$F:$F,'Consolidated Budget - ''25'!$C29) -> -1063.4297 | W29: =SUMIFS('Site Level Budget - ''25'!Z:Z,'Site Level Budget - ''25'!$F:$F,'Consolidated Budget - ''25'!$C29) -> -689.95019 | X29: =SUMIFS('Site Level Budget - ''25'!AA:AA,'Site Level Budget - ''25'!$F:$F,'Consolidated Budget - ''25'!$C29) -> -625.91029 | Y29: =SUMIFS('Site Level Budget - ''25'!AB:AB,'Site Level Budget - ''25'!$F:$F,'Consolidated Budget - ''25'!$C29) -> -712.87715 | Z29: =SUMIFS('Site Level Budget - ''25'!AC:AC,'Site Level Budget - ''25'!$F:$F,'Consolidated Budget - ''25'!$C29) -> -482.23418 | AA29: =SUMIFS('Site Level Budget - ''25'!AD:AD,'Site Level Budget - ''25'!$F:$F,'Consolidated Budget - ''25'!$C29) -> -399.8247 | AC29: ='Cons. Financials - ''23 ''24'!AC29 -> -6556.3033 | AD29: =SUM(D29:O29) -> -6665.974 | AE29: =SUM(P29:AA29) -> -9676.0802
C30: % of Revenue | D30: =(D29/D$14) -> -0.038384526 | E30: =(E29/E$14) -> -0.041631547 | F30: =(F29/F$14) -> -0.046054568 | G30: =(G29/G$14) -> -0.052909745 | H30: =(H29/H$14) -> -0.063694506 | I30: =(I29/I$14) -> -0.058111299 | J30: =(J29/J$14) -> -0.050468581 | K30: =(K29/K$14) -> -0.040834239 | ... AA30: =(AA29/AA$14) -> -0.037079735 | AC30: ='Cons. Financials - ''23 ''24'!AC30 -> -0.051588259 | AD30: =(AD29/AD$14) -> -0.045203114 | AE30: =(AE29/AE$14) -> -0.050144808
AC31: ='Cons. Financials - ''23 ''24'!AC31 -> 0
C32: Marketing | D32: =_xlfn.XLOOKUP($C32,'Cons. Financials - ''23 ''24'!$C$8:$C$79,'Cons. Financials - ''23 ''24'!P$8:P$79) -> -297.75131 | E32: =_xlfn.XLOOKUP($C32,'Cons. Financials - ''23 ''24'!$C$8:$C$79,'Cons. Financials - ''23 ''24'!Q$8:Q$79) -> -301.20967 | F32: =_xlfn.XLOOKUP($C32,'Cons. Financials - ''23 ''24'!$C$8:$C$79,'Cons. Financials - ''23 ''24'!R$8:R$79) -> -326.88367 | G32: =_xlfn.XLOOKUP($C32,'Cons. Financials - ''23 ''24'!$C$8:$C$79,'Cons. Financials - ''23 ''24'!S$8:S$79) -> -350.03651 | H32: =_xlfn.XLOOKUP($C32,'Cons. Financials - ''23 ''24'!$C$8:$C$79,'Cons. Financials - ''23 ''24'!T$8:T$79) -> -435.78904 | I32: =_xlfn.XLOOKUP($C32,'Cons. Financials - ''23 ''24'!$C$8:$C$79,'Cons. Financials - ''23 ''24'!U$8:U$79) -> -364.36409 | J32: =_xlfn.XLOOKUP($C32,'Cons. Financials - ''23 ''24'!$C$8:$C$79,'Cons. Financials - ''23 ''24'!V$8:V$79) -> -365.15346 | K32: =_xlfn.XLOOKUP($C32,'Cons. Financials - ''23 ''24'!$C$8:$C$79,'Cons. Financials - ''23 ''24'!W$8:W$79) -> -315.68593 | ... O32: =_xlfn.XLOOKUP($C32,'Cons. Financials - ''23 ''24'!$C$8:$C$79,'Cons. Financials - ''23 ''24'!AA$8:AA$79) -> -215.9737 | P32: =SUMIFS('Site Level Budget - ''25'!S:S,'Site Level Budget - ''25'!$F:$F,'Consolidated Budget - ''25'!$C32) -> -310.04096 | Q32: =SUMIFS('Site Level Budget - ''25'!T:T,'Site Level Budget - ''25'!$F:$F,'Consolidated Budget - ''25'!$C32) -> -356.51836 | R32: =SUMIFS('Site Level Budget - ''25'!U:U,'Site Level Budget - ''25'!$F:$F,'Consolidated Budget - ''25'!$C32) -> -425.23513 | S32: =SUMIFS('Site Level Budget - ''25'!V:V,'Site Level Budget - ''25'!$F:$F,'Consolidated Budget - ''25'!$C32) -> -566.30635 | T32: =SUMIFS('Site Level Budget - ''25'!W:W,'Site Level Budget - ''25'!$F:$F,'Consolidated Budget - ''25'!$C32) -> -858.87611 | U32: =SUMIFS('Site Level Budget - ''25'!X:X,'Site Level Budget - ''25'!$F:$F,'Consolidated Budget - ''25'!$C32) -> -638.06316 | V32: =SUMIFS('Site Level Budget - ''25'!Y:Y,'Site Level Budget - ''25'!$F:$F,'Consolidated Budget - ''25'!$C32) -> -584.95211 | W32: =SUMIFS('Site Level Budget - ''25'!Z:Z,'Site Level Budget - ''25'!$F:$F,'Consolidated Budget - ''25'!$C32) -> -393.83011 | X32: =SUMIFS('Site Level Budget - ''25'!AA:AA,'Site Level Budget - ''25'!$F:$F,'Consolidated Budget - ''25'!$C32) -> -358.84187 | Y32: =SUMIFS('Site Level Budget - ''25'!AB:AB,'Site Level Budget - ''25'!$F:$F,'Consolidated Budget - ''25'!$C32) -> -429.33301 | Z32: =SUMIFS('Site Level Budget - ''25'!AC:AC,'Site Level Budget - ''25'!$F:$F,'Consolidated Budget - ''25'!$C32) -> -292.86784 | AA32: =SUMIFS('Site Level Budget - ''25'!AD:AD,'Site Level Budget - ''25'!$F:$F,'Consolidated Budget - ''25'!$C32) -> -247.5068 | AC32: ='Cons. Financials - ''23 ''24'!AC32 -> -3833.03 | AD32: =SUM(D32:O32) -> -3861.6931 | AE32: =SUM(P32:AA32) -> -5462.3718
C33: % of Revenue | D33: =(D32/D$14) -> -0.021969347 | E33: =(E32/E$14) -> -0.023582906 | F33: =(F32/F$14) -> -0.025884139 | G33: =(G32/G$14) -> -0.029622147 | H33: =(H32/H$14) -> -0.036751512 | I33: =(I32/I$14) -> -0.033465798 | J33: =(J32/J$14) -> -0.028689599 | K33: =(K32/K$14) -> -0.023844724 | ... AA33: =(AA32/AA$14) -> -0.022953776 | AC33: ='Cons. Financials - ''23 ''24'!AC33 -> -0.030160188 | AD33: =(AD32/AD$14) -> -0.026186804 | AE33: =(AE32/AE$14) -> -0.028307908
AC34: ='Cons. Financials - ''23 ''24'!AC34 -> 0
C35: Office Rent | D35: =_xlfn.XLOOKUP($C35,'Cons. Financials - ''23 ''24'!$C$8:$C$79,'Cons. Financials - ''23 ''24'!P$8:P$79) -> -799.23691 | E35: =_xlfn.XLOOKUP($C35,'Cons. Financials - ''23 ''24'!$C$8:$C$79,'Cons. Financials - ''23 ''24'!Q$8:Q$79) -> -800.70615 | F35: =_xlfn.XLOOKUP($C35,'Cons. Financials - ''23 ''24'!$C$8:$C$79,'Cons. Financials - ''23 ''24'!R$8:R$79) -> -803.94851 | G35: =_xlfn.XLOOKUP($C35,'Cons. Financials - ''23 ''24'!$C$8:$C$79,'Cons. Financials - ''23 ''24'!S$8:S$79) -> -806.67021 | H35: =_xlfn.XLOOKUP($C35,'Cons. Financials - ''23 ''24'!$C$8:$C$79,'Cons. Financials - ''23 ''24'!T$8:T$79) -> -806.67021 | I35: =_xlfn.XLOOKUP($C35,'Cons. Financials - ''23 ''24'!$C$8:$C$79,'Cons. Financials - ''23 ''24'!U$8:U$79) -> -811.58748 | J35: =_xlfn.XLOOKUP($C35,'Cons. Financials - ''23 ''24'!$C$8:$C$79,'Cons. Financials - ''23 ''24'!V$8:V$79) -> -815.64517 | K35: =_xlfn.XLOOKUP($C35,'Cons. Financials - ''23 ''24'!$C$8:$C$79,'Cons. Financials - ''23 ''24'!W$8:W$79) -> -818.54817 | ... O35: =_xlfn.XLOOKUP($C35,'Cons. Financials - ''23 ''24'!$C$8:$C$79,'Cons. Financials - ''23 ''24'!AA$8:AA$79) -> -823.21401 | P35: =SUMIFS('Site Level Budget - ''25'!S:S,'Site Level Budget - ''25'!$F:$F,'Consolidated Budget - ''25'!$C35) -> -823.21401 | Q35: =SUMIFS('Site Level Budget - ''25'!T:T,'Site Level Budget - ''25'!$F:$F,'Consolidated Budget - ''25'!$C35) -> -824.72733 | R35: =SUMIFS('Site Level Budget - ''25'!U:U,'Site Level Budget - ''25'!$F:$F,'Consolidated Budget - ''25'!$C35) -> -828.06697 | S35: =SUMIFS('Site Level Budget - ''25'!V:V,'Site Level Budget - ''25'!$F:$F,'Consolidated Budget - ''25'!$C35) -> -830.87031 | T35: =SUMIFS('Site Level Budget - ''25'!W:W,'Site Level Budget - ''25'!$F:$F,'Consolidated Budget - ''25'!$C35) -> -830.87031 | U35: =SUMIFS('Site Level Budget - ''25'!X:X,'Site Level Budget - ''25'!$F:$F,'Consolidated Budget - ''25'!$C35) -> -835.9351 | V35: =SUMIFS('Site Level Budget - ''25'!Y:Y,'Site Level Budget - ''25'!$F:$F,'Consolidated Budget - ''25'!$C35) -> -840.11452 | W35: =SUMIFS('Site Level Budget - ''25'!Z:Z,'Site Level Budget - ''25'!$F:$F,'Consolidated Budget - ''25'!$C35) -> -843.10462 | X35: =SUMIFS('Site Level Budget - ''25'!AA:AA,'Site Level Budget - ''25'!$F:$F,'Consolidated Budget - ''25'!$C35) -> -843.59253 | Y35: =SUMIFS('Site Level Budget - ''25'!AB:AB,'Site Level Budget - ''25'!$F:$F,'Consolidated Budget - ''25'!$C35) -> -846.9492 | Z35: =SUMIFS('Site Level Budget - ''25'!AC:AC,'Site Level Budget - ''25'!$F:$F,'Consolidated Budget - ''25'!$C35) -> -846.9492 | AA35: =SUMIFS('Site Level Budget - ''25'!AD:AD,'Site Level Budget - ''25'!$F:$F,'Consolidated Budget - ''25'!$C35) -> -847.91043 | AC35: ='Cons. Financials - ''23 ''24'!AC35 -> -9465.8118 | AD35: =SUM(D35:O35) -> -9749.8102 | AE35: =SUM(P35:AA35) -> -10042.305
C36: % YoY Growth | D36: =_xlfn.XLOOKUP($C36,'Cons. Financials - ''23 ''24'!$C$8:$C$79,'Cons. Financials - ''23 ''24'!P$8:P$79) -> 0.030002533 | E36: =_xlfn.XLOOKUP($C36,'Cons. Financials - ''23 ''24'!$C$8:$C$79,'Cons. Financials - ''23 ''24'!Q$8:Q$79) -> 0.030002556 | F36: =_xlfn.XLOOKUP($C36,'Cons. Financials - ''23 ''24'!$C$8:$C$79,'Cons. Financials - ''23 ''24'!R$8:R$79) -> 0.030002537 | G36: =_xlfn.XLOOKUP($C36,'Cons. Financials - ''23 ''24'!$C$8:$C$79,'Cons. Financials - ''23 ''24'!S$8:S$79) -> 0.030002544 | H36: =_xlfn.XLOOKUP($C36,'Cons. Financials - ''23 ''24'!$C$8:$C$79,'Cons. Financials - ''23 ''24'!T$8:T$79) -> 0.030002544 | I36: =_xlfn.XLOOKUP($C36,'Cons. Financials - ''23 ''24'!$C$8:$C$79,'Cons. Financials - ''23 ''24'!U$8:U$79) -> 0.030002573 | J36: =_xlfn.XLOOKUP($C36,'Cons. Financials - ''23 ''24'!$C$8:$C$79,'Cons. Financials - ''23 ''24'!V$8:V$79) -> 0.030002553 | K36: =_xlfn.XLOOKUP($C36,'Cons. Financials - ''23 ''24'!$C$8:$C$79,'Cons. Financials - ''23 ''24'!W$8:W$79) -> 0.030002544 | ... O36: =_xlfn.XLOOKUP($C36,'Cons. Financials - ''23 ''24'!$C$8:$C$79,'Cons. Financials - ''23 ''24'!AA$8:AA$79) -> 0.030002533 | P36: =P35/D35-1 -> 0.03 | Q36: =Q35/E35-1 -> 0.03 | R36: =R35/F35-1 -> 0.03 | S36: =S35/G35-1 -> 0.03 | T36: =T35/H35-1 -> 0.03 | U36: =U35/I35-1 -> 0.03 | V36: =V35/J35-1 -> 0.03 | W36: =W35/K35-1 -> 0.03 | ... AA36: =AA35/O35-1 -> 0.03 | AC36: ='Cons. Financials - ''23 ''24'!AC36 -> 0 | AD36: =AD35/AC35-1 -> 0.030002542 | AE36: =AE35/AD35-1 -> 0.03
AC37: ='Cons. Financials - ''23 ''24'!AC37 -> 0
C38: Office EBITDA | D38: =D26+D29+D32+D35 -> 4949.403 | E38: =E26+E29+E32+E35 -> 4025.5614 | F38: =F26+F29+F32+F35 -> 3568.6478 | G38: =G26+G29+G32+G35 -> 2382.2072 | H38: =H26+H29+H32+H35 -> 1439.054 | I38: =I26+I29+I32+I35 -> 1826.6422 | J38: =J26+J29+J32+J35 -> 3266.555 | K38: =K26+K29+K32+K35 -> 4815.2195 | ... AA38: =AA26+AA29+AA32+AA35 -> 3994.994 | AC38: ='Cons. Financials - ''23 ''24'!AC38 -> 37042.053 | AD38: =SUM(D38:O38) -> 43570.399 | AE38: =SUM(P38:AA38) -> 53003.548
C39: % of Revenue | D39: =(D38/D$14) -> 0.36518782 | E39: =(E38/E$14) -> 0.31517725 | F39: =(F38/F$14) -> 0.28258179 | G39: =(G38/G$14) -> 0.20159638 | H39: =(H38/H$14) -> 0.12136012 | I39: =(I38/I$14) -> 0.16777186 | J39: =(J38/J$14) -> 0.25664868 | K39: =(K38/K$14) -> 0.36370826 | ... AA39: =(AA38/AA$14) -> 0.37049566 | AC39: ='Cons. Financials - ''23 ''24'!AC39 -> 0.29146532 | AD39: =(AD38/AD$14) -> 0.29545835 | AE39: =(AE38/AE$14) -> 0.2746828
AC40: ='Cons. Financials - ''23 ''24'!AC40 -> 0
C41: Headcount Expenses | D41: =_xlfn.XLOOKUP($C41,'Cons. Financials - ''23 ''24'!$C$8:$C$79,'Cons. Financials - ''23 ''24'!P$8:P$79) -> -756.41667 | E41: =_xlfn.XLOOKUP($C41,'Cons. Financials - ''23 ''24'!$C$8:$C$79,'Cons. Financials - ''23 ''24'!Q$8:Q$79) -> -765.97917 | F41: =_xlfn.XLOOKUP($C41,'Cons. Financials - ''23 ''24'!$C$8:$C$79,'Cons. Financials - ''23 ''24'!R$8:R$79) -> -775.54167 | G41: =_xlfn.XLOOKUP($C41,'Cons. Financials - ''23 ''24'!$C$8:$C$79,'Cons. Financials - ''23 ''24'!S$8:S$79) -> -758.54167 | H41: =_xlfn.XLOOKUP($C41,'Cons. Financials - ''23 ''24'!$C$8:$C$79,'Cons. Financials - ''23 ''24'!T$8:T$79) -> -743.54167 | I41: =_xlfn.XLOOKUP($C41,'Cons. Financials - ''23 ''24'!$C$8:$C$79,'Cons. Financials - ''23 ''24'!U$8:U$79) -> -747.54167 | J41: =_xlfn.XLOOKUP($C41,'Cons. Financials - ''23 ''24'!$C$8:$C$79,'Cons. Financials - ''23 ''24'!V$8:V$79) -> -705.875 | K41: =_xlfn.XLOOKUP($C41,'Cons. Financials - ''23 ''24'!$C$8:$C$79,'Cons. Financials - ''23 ''24'!W$8:W$79) -> -712.375 | ... O41: =_xlfn.XLOOKUP($C41,'Cons. Financials - ''23 ''24'!$C$8:$C$79,'Cons. Financials - ''23 ''24'!AA$8:AA$79) -> -678.64583 | P41: =-'Corporate Monthly - ''25'!I353/1000 -> -817.70833 | Q41: =-'Corporate Monthly - ''25'!J353/1000 -> -876.5 | R41: =-'Corporate Monthly - ''25'!K353/1000 -> -876.5 | S41: =-'Corporate Monthly - ''25'!L353/1000 -> -876.5 | T41: =-'Corporate Monthly - ''25'!M353/1000 -> -876.5 | U41: =-'Corporate Monthly - ''25'!N353/1000 -> -876.5 | V41: =-'Corporate Monthly - ''25'!O353/1000 -> -876.5 | W41: =-'Corporate Monthly - ''25'!P353/1000 -> -876.5 | ... AA41: =-'Corporate Monthly - ''25'!T353/1000 -> -876.5 | AC41: ='Cons. Financials - ''23 ''24'!AC41 -> -8381.875 | AD41: =SUM(D41:O41) -> -8701.9792 | AE41: =SUM(P41:AA41) -> -10459.208
C42: % of Revenue | D42: =(D41/D$14) -> -0.05581161 | E42: =(E41/E$14) -> -0.059971563 | F42: =(F41/F$14) -> -0.061410923 | G42: =(G41/G$14) -> -0.064192255 | H42: =(H41/H$14) -> -0.062705295 | I42: =(I41/I$14) -> -0.06865956 | J42: =(J41/J$14) -> -0.055459617 | K42: =(K41/K$14) -> -0.053807863 | ... AA42: =(AA41/AA$14) -> -0.081286593 | AC42: ='Cons. Financials - ''23 ''24'!AC42 -> -0.065952766 | AD42: =(AD41/AD$14) -> -0.059009615 | AE42: =(AE41/AE$14) -> -0.05420325
AC43: ='Cons. Financials - ''23 ''24'!AC43 -> 0
C44: SG&A | D44: =_xlfn.XLOOKUP($C44,'Cons. Financials - ''23 ''24'!$C$8:$C$79,'Cons. Financials - ''23 ''24'!P$8:P$79) -> -221.76982 | E44: =_xlfn.XLOOKUP($C44,'Cons. Financials - ''23 ''24'!$C$8:$C$79,'Cons. Financials - ''23 ''24'!Q$8:Q$79) -> -225.61785 | F44: =_xlfn.XLOOKUP($C44,'Cons. Financials - ''23 ''24'!$C$8:$C$79,'Cons. Financials - ''23 ''24'!R$8:R$79) -> -243.38009 | G44: =_xlfn.XLOOKUP($C44,'Cons. Financials - ''23 ''24'!$C$8:$C$79,'Cons. Financials - ''23 ''24'!S$8:S$79) -> -257.63444 | H44: =_xlfn.XLOOKUP($C44,'Cons. Financials - ''23 ''24'!$C$8:$C$79,'Cons. Financials - ''23 ''24'!T$8:T$79) -> -310.74378 | I44: =_xlfn.XLOOKUP($C44,'Cons. Financials - ''23 ''24'!$C$8:$C$79,'Cons. Financials - ''23 ''24'!U$8:U$79) -> -257.19287 | J44: =_xlfn.XLOOKUP($C44,'Cons. Financials - ''23 ''24'!$C$8:$C$79,'Cons. Financials - ''23 ''24'!V$8:V$79) -> -262.23583 | K44: =_xlfn.XLOOKUP($C44,'Cons. Financials - ''23 ''24'!$C$8:$C$79,'Cons. Financials - ''23 ''24'!W$8:W$79) -> -225.53316 | ... O44: =_xlfn.XLOOKUP($C44,'Cons. Financials - ''23 ''24'!$C$8:$C$79,'Cons. Financials - ''23 ''24'!AA$8:AA$79) -> -161.22548 | P44: =P45*P14 -> -239.54689 | Q44: =Q45*Q14 -> -271.26199 | R44: =R45*R14 -> -317.78373 | S44: =S45*S14 -> -388.88836 | T44: =T45*T14 -> -555.54934 | U44: =U45*U14 -> -420.52827 | V44: =V45*V14 -> -381.36085 | W44: =W45*W14 -> -270.37839 | ... AA44: =AA45*AA14 -> -175.69719 | AC44: ='Cons. Financials - ''23 ''24'!AC44 -> -2836.9304 | AD44: =SUM(D44:O44) -> -2817.1179 | AE44: =SUM(P44:AA44) -> -3783.9376
C45: % of Revenue | D45: =(D44/D$14) -> -0.016363112 | E45: =(E44/E$14) -> -0.017664521 | F45: =(F44/F$14) -> -0.019271944 | G45: =(G44/G$14) -> -0.021802541 | H45: =(H44/H$14) -> -0.026206037 | I45: =(I44/I$14) -> -0.023622428 | J45: =(J44/J$14) -> -0.020603504 | K45: =(K44/K$14) -> -0.017035209 | ... O45: =(O44/O$14) -> -0.016294154 | P45: =D45+'Budget Assumption Driver'!E43 -> -0.016363112 | Q45: =E45+'Budget Assumption Driver'!F43 -> -0.017664521 | R45: =F45+'Budget Assumption Driver'!G43 -> -0.019271944 | S45: =G45+'Budget Assumption Driver'!H43 -> -0.021802541 | T45: =H45+'Budget Assumption Driver'!I43 -> -0.026206037 | U45: =I45+'Budget Assumption Driver'!J43 -> -0.023622428 | V45: =J45+'Budget Assumption Driver'!K43 -> -0.020603504 | W45: =K45+'Budget Assumption Driver'!L43 -> -0.017035209 | ... AA45: =O45+'Budget Assumption Driver'!P43 -> -0.016294154 | AC45: ='Cons. Financials - ''23 ''24'!AC45 -> -0.022322381 | AD45: =(AD44/AD$14) -> -0.01910336 | AE45: =(AE44/AE$14) -> -0.019609679
AC46: ='Cons. Financials - ''23 ''24'!AC46 -> 0
C47: Corporate Office Rent | D47: =_xlfn.XLOOKUP($C47,'Cons. Financials - ''23 ''24'!$C$8:$C$79,'Cons. Financials - ''23 ''24'!P$8:P$79) -> -32.873984 | E47: =_xlfn.XLOOKUP($C47,'Cons. Financials - ''23 ''24'!$C$8:$C$79,'Cons. Financials - ''23 ''24'!Q$8:Q$79) -> -32.873984 | F47: =_xlfn.XLOOKUP($C47,'Cons. Financials - ''23 ''24'!$C$8:$C$79,'Cons. Financials - ''23 ''24'!R$8:R$79) -> -32.873984 | G47: =_xlfn.XLOOKUP($C47,'Cons. Financials - ''23 ''24'!$C$8:$C$79,'Cons. Financials - ''23 ''24'!S$8:S$79) -> -32.873984 | H47: =_xlfn.XLOOKUP($C47,'Cons. Financials - ''23 ''24'!$C$8:$C$79,'Cons. Financials - ''23 ''24'!T$8:T$79) -> -32.873984 | I47: =_xlfn.XLOOKUP($C47,'Cons. Financials - ''23 ''24'!$C$8:$C$79,'Cons. Financials - ''23 ''24'!U$8:U$79) -> -32.873984 | J47: =_xlfn.XLOOKUP($C47,'Cons. Financials - ''23 ''24'!$C$8:$C$79,'Cons. Financials - ''23 ''24'!V$8:V$79) -> -33.860203 | K47: =_xlfn.XLOOKUP($C47,'Cons. Financials - ''23 ''24'!$C$8:$C$79,'Cons. Financials - ''23 ''24'!W$8:W$79) -> -33.860203 | ... O47: =_xlfn.XLOOKUP($C47,'Cons. Financials - ''23 ''24'!$C$8:$C$79,'Cons. Financials - ''23 ''24'!AA$8:AA$79) -> -33.860203 | P47: =(1+P48)*D47 -> -33.860203 | Q47: =(1+Q48)*E47 -> -33.860203 | R47: =(1+R48)*F47 -> -33.860203 | S47: =(1+S48)*G47 -> -33.860203 | T47: =(1+T48)*H47 -> -33.860203 | U47: =(1+U48)*I47 -> -33.860203 | V47: =(1+V48)*J47 -> -34.876009 | W47: =(1+W48)*K47 -> -34.876009 | ... AA47: =(1+AA48)*O47 -> -34.876009 | AC47: ='Cons. Financials - ''23 ''24'!AC47 -> -388.745 | AD47: =SUM(D47:O47) -> -400.40512 | AE47: =SUM(P47:AA47) -> -412.41728
C48: % YoY Growth | D48: =_xlfn.XLOOKUP($C48,'Cons. Financials - ''23 ''24'!$C$8:$C$79,'Cons. Financials - ''23 ''24'!P$8:P$79) -> 0.030002533 | E48: =_xlfn.XLOOKUP($C48,'Cons. Financials - ''23 ''24'!$C$8:$C$79,'Cons. Financials - ''23 ''24'!Q$8:Q$79) -> 0.030002556 | F48: =_xlfn.XLOOKUP($C48,'Cons. Financials - ''23 ''24'!$C$8:$C$79,'Cons. Financials - ''23 ''24'!R$8:R$79) -> 0.030002537 | G48: =_xlfn.XLOOKUP($C48,'Cons. Financials - ''23 ''24'!$C$8:$C$79,'Cons. Financials - ''23 ''24'!S$8:S$79) -> 0.030002544 | H48: =_xlfn.XLOOKUP($C48,'Cons. Financials - ''23 ''24'!$C$8:$C$79,'Cons. Financials - ''23 ''24'!T$8:T$79) -> 0.030002544 | I48: =_xlfn.XLOOKUP($C48,'Cons. Financials - ''23 ''24'!$C$8:$C$79,'Cons. Financials - ''23 ''24'!U$8:U$79) -> 0.030002573 | J48: =_xlfn.XLOOKUP($C48,'Cons. Financials - ''23 ''24'!$C$8:$C$79,'Cons. Financials - ''23 ''24'!V$8:V$79) -> 0.030002553 | K48: =_xlfn.XLOOKUP($C48,'Cons. Financials - ''23 ''24'!$C$8:$C$79,'Cons. Financials - ''23 ''24'!W$8:W$79) -> 0.030002544 | ... O48: =_xlfn.XLOOKUP($C48,'Cons. Financials - ''23 ''24'!$C$8:$C$79,'Cons. Financials - ''23 ''24'!AA$8:AA$79) -> 0.030002533 | P48: ='Budget Assumption Driver'!E44 -> 0.03 | Q48: ='Budget Assumption Driver'!F44 -> 0.03 | R48: ='Budget Assumption Driver'!G44 -> 0.03 | S48: ='Budget Assumption Driver'!H44 -> 0.03 | T48: ='Budget Assumption Driver'!I44 -> 0.03 | U48: ='Budget Assumption Driver'!J44 -> 0.03 | V48: ='Budget Assumption Driver'!K44 -> 0.03 | W48: ='Budget Assumption Driver'!L44 -> 0.03 | ... AA48: ='Budget Assumption Driver'!P44 -> 0.03 | AC48: ='Cons. Financials - ''23 ''24'!AC48 -> 0 | AD48: =AD47/AC47-1 -> 0.029994268 | AE48: =AE47/AD47-1 -> 0.03
AC49: ='Cons. Financials - ''23 ''24'!AC49 -> 0
C50: Total Corporate Expenses | D50: =D41+D44+D47 -> -1011.0605 | E50: =E41+E44+E47 -> -1024.471 | F50: =F41+F44+F47 -> -1051.7957 | G50: =G41+G44+G47 -> -1049.0501 | H50: =H41+H44+H47 -> -1087.1594 | I50: =I41+I44+I47 -> -1037.6085 | J50: =J41+J44+J47 -> -1001.971 | K50: =K41+K44+K47 -> -971.76836 | ... AA50: =AA41+AA44+AA47 -> -1087.0732 | AC50: ='Cons. Financials - ''23 ''24'!AC50 -> -11607.55 | AD50: =SUM(D50:O50) -> -11919.502 | AE50: =SUM(P50:AA50) -> -14655.563
C51: % of Revenue | D51: =(D50/D$14) -> -0.074600304 | E51: =(E50/E$14) -> -0.080209919 | F51: =(F50/F$14) -> -0.083285979 | G51: =(G50/G$14) -> -0.088776786 | H51: =(H50/H$14) -> -0.091683702 | I51: =(I50/I$14) -> -0.09530137 | J51: =(J50/J$14) -> -0.07872347 | K51: =(K50/K$14) -> -0.073400637 | ... AA51: =(AA50/AA$14) -> -0.10081515 | AC51: ='Cons. Financials - ''23 ''24'!AC51 -> -0.091333986 | AD51: =(AD50/AD$14) -> -0.08082819 | AE51: =(AE50/AE$14) -> -0.075950218
AC52: ='Cons. Financials - ''23 ''24'!AC52 -> 0
C53: Adjusted EBITDA | D53: =D38+D50 -> 3938.3425 | E53: =E38+E50 -> 3001.0904 | F53: =F38+F50 -> 2516.8521 | G53: =G38+G50 -> 1333.1571 | H53: =H38+H50 -> 351.89461 | I53: =I38+I50 -> 789.03371 | J53: =J38+J50 -> 2264.5839 | K53: =K38+K50 -> 3843.4512 | ... AA53: =AA38+AA50 -> 2907.9208 | AC53: ='Cons. Financials - ''23 ''24'!AC53 -> 25434.502 | AD53: =SUM(D53:O53) -> 31650.897 | AE53: =SUM(P53:AA53) -> 38347.985
C54: % of Revenue | D54: =(D53/D$14) -> 0.29058751 | E54: =(E53/E$14) -> 0.23496733 | F54: =(F53/F$14) -> 0.19929581 | G54: =(G53/G$14) -> 0.11281959 | H54: =(H53/H$14) -> 0.029676421 | I54: =(I53/I$14) -> 0.072470486 | J54: =(J53/J$14) -> 0.17792521 | K54: =(K53/K$14) -> 0.29030762 | ... AA54: =(AA53/AA$14) -> 0.26968052 | AC54: ='Cons. Financials - ''23 ''24'!AC54 -> 0.20013133 | AD54: =(AD53/AD$14) -> 0.21463016 | AE54: =(AE53/AE$14) -> 0.19873258
AC55: ='Cons. Financials - ''23 ''24'!AC55 -> 0
C56: Depreciation and Amortization - PP&E | D56: =_xlfn.XLOOKUP($C56,'Cons. Financials - ''23 ''24'!$C$8:$C$79,'Cons. Financials - ''23 ''24'!P$8:P$79) -> -270.50629 | E56: =_xlfn.XLOOKUP($C56,'Cons. Financials - ''23 ''24'!$C$8:$C$79,'Cons. Financials - ''23 ''24'!Q$8:Q$79) -> -272.72645 | F56: =_xlfn.XLOOKUP($C56,'Cons. Financials - ''23 ''24'!$C$8:$C$79,'Cons. Financials - ''23 ''24'!R$8:R$79) -> -273.79266 | G56: =_xlfn.XLOOKUP($C56,'Cons. Financials - ''23 ''24'!$C$8:$C$79,'Cons. Financials - ''23 ''24'!S$8:S$79) -> -276.30401 | H56: =_xlfn.XLOOKUP($C56,'Cons. Financials - ''23 ''24'!$C$8:$C$79,'Cons. Financials - ''23 ''24'!T$8:T$79) -> -277.40447 | I56: =_xlfn.XLOOKUP($C56,'Cons. Financials - ''23 ''24'!$C$8:$C$79,'Cons. Financials - ''23 ''24'!U$8:U$79) -> -277.71562 | J56: =_xlfn.XLOOKUP($C56,'Cons. Financials - ''23 ''24'!$C$8:$C$79,'Cons. Financials - ''23 ''24'!V$8:V$79) -> -280.01495 | K56: =_xlfn.XLOOKUP($C56,'Cons. Financials - ''23 ''24'!$C$8:$C$79,'Cons. Financials - ''23 ''24'!W$8:W$79) -> -281.12455 | ... O56: =_xlfn.XLOOKUP($C56,'Cons. Financials - ''23 ''24'!$C$8:$C$79,'Cons. Financials - ''23 ''24'!AA$8:AA$79) -> -283.21799 | P56: =O56-P138/10/12 -> -287.38466 | Q56: =P56-Q138/10/12 -> -291.55133 | R56: =Q56-R138/10/12 -> -295.71799 | S56: =R56-S138/10/12 -> -299.88466 | T56: =S56-T138/10/12 -> -304.05133 | U56: =T56-U138/10/12 -> -308.21799 | V56: =U56-V138/10/12 -> -316.55133 | W56: =V56-W138/10/12 -> -324.88466 | ... AA56: =Z56-AA138/10/12 -> -358.21799 | AC56: ='Cons. Financials - ''23 ''24'!AC56 -> -3158.2223 | AD56: =SUM(D56:O56) -> -3338.4178 | AE56: =SUM(P56:AA56) -> -3811.1159
C57: % of Revenue | D57: =(D56/D$14) -> -0.019959094 | E57: =(E56/E$14) -> -0.021352841 | F57: =(F56/F$14) -> -0.02168015 | G57: =(G56/G$14) -> -0.02338247 | H57: =(H56/H$14) -> -0.023394424 | I57: =(I56/I$14) -> -0.025507384 | J57: =(J56/J$14) -> -0.022000385 | K57: =(K56/K$14) -> -0.021234197 | ... AA57: =(AA56/AA$14) -> -0.03322113 | AC57: ='Cons. Financials - ''23 ''24'!AC57 -> -0.024850466 | AD57: =(AD56/AD$14) -> -0.022638384 | AE57: =(AE56/AE$14) -> -0.019750526
AC58: ='Cons. Financials - ''23 ''24'!AC58 -> 0
C59: Intangible Amortization | D59: =_xlfn.XLOOKUP($C59,'Cons. Financials - ''23 ''24'!$C$8:$C$79,'Cons. Financials - ''23 ''24'!P$8:P$79) -> -12.132 | E59: =_xlfn.XLOOKUP($C59,'Cons. Financials - ''23 ''24'!$C$8:$C$79,'Cons. Financials - ''23 ''24'!Q$8:Q$79) -> -12.132 | F59: =_xlfn.XLOOKUP($C59,'Cons. Financials - ''23 ''24'!$C$8:$C$79,'Cons. Financials - ''23 ''24'!R$8:R$79) -> -12.132 | G59: =_xlfn.XLOOKUP($C59,'Cons. Financials - ''23 ''24'!$C$8:$C$79,'Cons. Financials - ''23 ''24'!S$8:S$79) -> -12.132 | H59: =_xlfn.XLOOKUP($C59,'Cons. Financials - ''23 ''24'!$C$8:$C$79,'Cons. Financials - ''23 ''24'!T$8:T$79) -> -12.132 | I59: =_xlfn.XLOOKUP($C59,'Cons. Financials - ''23 ''24'!$C$8:$C$79,'Cons. Financials - ''23 ''24'!U$8:U$79) -> -12.132 | J59: =_xlfn.XLOOKUP($C59,'Cons. Financials - ''23 ''24'!$C$8:$C$79,'Cons. Financials - ''23 ''24'!V$8:V$79) -> -12.132 | K59: =_xlfn.XLOOKUP($C59,'Cons. Financials - ''23 ''24'!$C$8:$C$79,'Cons. Financials - ''23 ''24'!W$8:W$79) -> -12.132 | ... O59: =_xlfn.XLOOKUP($C59,'Cons. Financials - ''23 ''24'!$C$8:$C$79,'Cons. Financials - ''23 ''24'!AA$8:AA$79) -> -12.132 | P59: =$O59 -> -12.132 | Q59: =$O59 -> -12.132 | R59: =$O59 -> -12.132 | S59: =$O59 -> -12.132 | T59: =$O59 -> -12.132 | U59: =$O59 -> -12.132 | V59: =$O59 -> -12.132 | W59: =$O59 -> -12.132 | ... AA59: =$O59 -> -12.132 | AC59: ='Cons. Financials - ''23 ''24'!AC59 -> -145.584 | AD59: =SUM(D59:O59) -> -145.584 | AE59: =SUM(P59:AA59) -> -145.584
AC60: ='Cons. Financials - ''23 ''24'!AC60 -> 0
C61: Operating Income (EBIT) | D61: =D53+D56+D59 -> 3655.7042 | E61: =E53+E56+E59 -> 2716.232 | F61: =F53+F56+F59 -> 2230.9274 | G61: =G53+G56+G59 -> 1044.7211 | H61: =H53+H56+H59 -> 62.358147 | I61: =I53+I56+I59 -> 499.18608 | J61: =J53+J56+J59 -> 1972.437 | K61: =K53+K56+K59 -> 3550.1946 | ... AA61: =AA53+AA56+AA59 -> 2537.5708 | AC61: ='Cons. Financials - ''23 ''24'!AC61 -> 22130.696 | AD61: =SUM(D61:O61) -> 28166.895 | AE61: =SUM(P61:AA61) -> 34391.285
C62: % of Revenue | D62: =(D61/D$14) -> 0.26973327 | E62: =(E61/E$14) -> 0.21266463 | F62: =(F61/F$14) -> 0.176655 | G62: =(G61/G$14) -> 0.08841044 | H62: =(H61/H$14) -> 0.005258866 | I62: =(I61/I$14) -> 0.045848812 | J62: =(J61/J$14) -> 0.15497163 | K62: =(K61/K$14) -> 0.26815706 | ... AA62: =(AA61/AA$14) -> 0.23533427 | AC62: ='Cons. Financials - ''23 ''24'!AC62 -> 0.17413534 | AD62: =(AD61/AD$14) -> 0.19100455 | AE62: =(AE61/AE$14) -> 0.17822758
AC63: ='Cons. Financials - ''23 ''24'!AC63 -> 0
C64: Net Interest Expense | D64: =_xlfn.XLOOKUP($C64,'Cons. Financials - ''23 ''24'!$C$8:$C$79,'Cons. Financials - ''23 ''24'!P$8:P$79) -> -847.23427 | E64: =_xlfn.XLOOKUP($C64,'Cons. Financials - ''23 ''24'!$C$8:$C$79,'Cons. Financials - ''23 ''24'!Q$8:Q$79) -> -846.30253 | F64: =_xlfn.XLOOKUP($C64,'Cons. Financials - ''23 ''24'!$C$8:$C$79,'Cons. Financials - ''23 ''24'!R$8:R$79) -> -845.42542 | G64: =_xlfn.XLOOKUP($C64,'Cons. Financials - ''23 ''24'!$C$8:$C$79,'Cons. Financials - ''23 ''24'!S$8:S$79) -> -844.76013 | H64: =_xlfn.XLOOKUP($C64,'Cons. Financials - ''23 ''24'!$C$8:$C$79,'Cons. Financials - ''23 ''24'!T$8:T$79) -> -844.50778 | I64: =_xlfn.XLOOKUP($C64,'Cons. Financials - ''23 ''24'!$C$8:$C$79,'Cons. Financials - ''23 ''24'!U$8:U$79) -> -829.74491 | J64: =_xlfn.XLOOKUP($C64,'Cons. Financials - ''23 ''24'!$C$8:$C$79,'Cons. Financials - ''23 ''24'!V$8:V$79) -> -815.15385 | K64: =_xlfn.XLOOKUP($C64,'Cons. Financials - ''23 ''24'!$C$8:$C$79,'Cons. Financials - ''23 ''24'!W$8:W$79) -> -814.78688 | ... O64: =_xlfn.XLOOKUP($C64,'Cons. Financials - ''23 ''24'!$C$8:$C$79,'Cons. Financials - ''23 ''24'!AA$8:AA$79) -> -747.32583 | P64: =-(AVERAGE(O107:P107)*P146+AVERAGE(O108:P108)*P149)/12 -> -744.16667 | Q64: =-(AVERAGE(P107:Q107)*Q146+AVERAGE(P108:Q108)*Q149)/12 -> -744.16667 | R64: =-(AVERAGE(Q107:R107)*R146+AVERAGE(Q108:R108)*R149)/12 -> -743.17708 | S64: =-(AVERAGE(R107:S107)*S146+AVERAGE(R108:S108)*S149)/12 -> -742.1875 | T64: =-(AVERAGE(S107:T107)*T146+AVERAGE(S108:T108)*T149)/12 -> -742.1875 | U64: =-(AVERAGE(T107:U107)*U146+AVERAGE(T108:U108)*U149)/12 -> -782.86458 | V64: =-(AVERAGE(U107:V107)*V146+AVERAGE(U108:V108)*V149)/12 -> -823.54167 | W64: =-(AVERAGE(V107:W107)*W146+AVERAGE(V108:W108)*W149)/12 -> -823.54167 | ... AA64: =-(AVERAGE(Z107:AA107)*AA146+AVERAGE(Z108:AA108)*AA149)/12 -> -820.57292 | AC64: ='Cons. Financials - ''23 ''24'!AC64 -> -10430.028 | AD64: =SUM(D64:O64) -> -9767.3038 | AE64: =SUM(P64:AA64) -> -9432.0833
AC65: ='Cons. Financials - ''23 ''24'!AC65 -> 0
C66: Pre Tax Income | D66: =D61+D64 -> 2808.47 | E66: =E61+E64 -> 1869.9294 | F66: =F61+F64 -> 1385.502 | G66: =G61+G64 -> 199.96095 | H66: =H61+H64 -> -782.14964 | I66: =I61+I64 -> -330.55882 | J66: =J61+J64 -> 1157.2831 | K66: =K61+K64 -> 2735.4077 | ... AA66: =AA61+AA64 -> 1716.9979 | AC66: ='Cons. Financials - ''23 ''24'!AC66 -> 11700.668 | AD66: =SUM(D66:O66) -> 18399.591 | AE66: =SUM(P66:AA66) -> 24959.202
C67: % of Revenue | D67: =(D66/D$14) -> 0.20722075 | E67: =(E66/E$14) -> 0.14640423 | F67: =(F66/F$14) -> 0.10971036 | G67: =(G66/G$14) -> 0.016921871 | H67: =(H66/H$14) -> -0.065961231 | I67: =(I66/I$14) -> -0.030360881 | J67: =(J66/J$14) -> 0.090926127 | K67: =(K66/K$14) -> 0.20661371 | ... AA67: =(AA66/AA$14) -> 0.15923435 | AC67: ='Cons. Financials - ''23 ''24'!AC67 -> 0.092066684 | AD67: =(AD66/AD$14) -> 0.12477079 | AE67: =(AE66/AE$14) -> 0.12934725
AC68: ='Cons. Financials - ''23 ''24'!AC68 -> 0
C69: Income Taxes | D69: =_xlfn.XLOOKUP($C69,'Cons. Financials - ''23 ''24'!$C$8:$C$79,'Cons. Financials - ''23 ''24'!P$8:P$79) -> -711.84198 | E69: =_xlfn.XLOOKUP($C69,'Cons. Financials - ''23 ''24'!$C$8:$C$79,'Cons. Financials - ''23 ''24'!Q$8:Q$79) -> -532.24318 | F69: =_xlfn.XLOOKUP($C69,'Cons. Financials - ''23 ''24'!$C$8:$C$79,'Cons. Financials - ''23 ''24'!R$8:R$79) -> -398.24081 | G69: =_xlfn.XLOOKUP($C69,'Cons. Financials - ''23 ''24'!$C$8:$C$79,'Cons. Financials - ''23 ''24'!S$8:S$79) -> -69.889674 | H69: =_xlfn.XLOOKUP($C69,'Cons. Financials - ''23 ''24'!$C$8:$C$79,'Cons. Financials - ''23 ''24'!T$8:T$79) -> 293.18322 | I69: =_xlfn.XLOOKUP($C69,'Cons. Financials - ''23 ''24'!$C$8:$C$79,'Cons. Financials - ''23 ''24'!U$8:U$79) -> 124.39043 | J69: =_xlfn.XLOOKUP($C69,'Cons. Financials - ''23 ''24'!$C$8:$C$79,'Cons. Financials - ''23 ''24'!V$8:V$79) -> -245.89639 | K69: =_xlfn.XLOOKUP($C69,'Cons. Financials - ''23 ''24'!$C$8:$C$79,'Cons. Financials - ''23 ''24'!W$8:W$79) -> -672.15419 | ... O69: =_xlfn.XLOOKUP($C69,'Cons. Financials - ''23 ''24'!$C$8:$C$79,'Cons. Financials - ''23 ''24'!AA$8:AA$79) -> -465 | P69: =P70*P66 -> -812.0788 | Q69: =Q70*Q66 -> -671.71792 | R69: =R70*R66 -> -613.83903 | S69: =S70*S66 -> -245.70411 | T69: =T70*T66 -> 76.461357 | U69: =U70*U66 -> -110.00292 | V69: =V70*V66 -> -514.79855 | W69: =W70*W66 -> -871.82661 | ... AA69: =AA70*AA66 -> -440.64281 | AC69: ='Cons. Financials - ''23 ''24'!AC69 -> -3008.2699 | AD69: =SUM(D69:O69) -> -4721.9904 | AE69: =SUM(P69:AA69) -> -6405.4202
C70: % of Pre Tax Income | D70: =D69/D66 -> -0.25346256 | E70: =E69/E66 -> -0.28463277 | F70: =F69/F66 -> -0.28743431 | G70: =G69/G66 -> -0.34951662 | H70: =H69/H66 -> -0.37484288 | I70: =I69/I66 -> -0.37630346 | J70: =J69/J66 -> -0.21247729 | K70: =K69/K66 -> -0.24572358 | ... O70: =O69/O66 -> -0.25841179 | P70: =-('Budget Assumption Driver'!E45) -> -0.25663562 | Q70: =-('Budget Assumption Driver'!F45) -> -0.25663562 | R70: =-('Budget Assumption Driver'!G45) -> -0.25663562 | S70: =-('Budget Assumption Driver'!H45) -> -0.25663562 | T70: =-('Budget Assumption Driver'!I45) -> -0.25663562 | U70: =-('Budget Assumption Driver'!J45) -> -0.25663562 | V70: =-('Budget Assumption Driver'!K45) -> -0.25663562 | W70: =-('Budget Assumption Driver'!L45) -> -0.25663562 | ... AA70: =-('Budget Assumption Driver'!P45) -> -0.25663562 | AC70: ='Cons. Financials - ''23 ''24'!AC70 -> -0.2571024 | AD70: =AD69/AD66 -> -0.25663562 | AE70: =AE69/AE66 -> -0.25663562
AC71: ='Cons. Financials - ''23 ''24'!AC71 -> 0
C72: Net Income (Loss) | D72: =D66+D69 -> 2096.628 | E72: =E66+E69 -> 1337.6862 | F72: =F66+F69 -> 987.26119 | G72: =G66+G69 -> 130.07127 | H72: =H66+H69 -> -488.96641 | I72: =I66+I69 -> -206.1684 | J72: =J66+J69 -> 911.38675 | K72: =K66+K69 -> 2063.2536 | ... AA72: =AA66+AA69 -> 1276.3551 | AC72: ='Cons. Financials - ''23 ''24'!AC72 -> 8692.3983 | AD72: =SUM(D72:O72) -> 13677.601 | AE72: =SUM(P72:AA72) -> 18553.782
C73: % of Revenue | D73: =(D72/D$14) -> 0.15469805 | E73: =(E72/E$14) -> 0.10473279 | F73: =(F72/F$14) -> 0.078175839 | G73: =(G72/G$14) -> 0.011007396 | H73: =(H72/H$14) -> -0.041236133 | I73: =(I72/I$14) -> -0.018935976 | J73: =(J72/J$14) -> 0.07160639 | K73: =(K72/K$14) -> 0.15584385 | ... AA73: =(AA72/AA$14) -> 0.11836914 | AC73: ='Cons. Financials - ''23 ''24'!AC73 -> 0.068396118 | AD73: =(AD72/AD$14) -> 0.092750158 | AE73: =(AE72/AE$14) -> 0.096152141
C75: Memo:
C76: Collections | D76: =_xlfn.XLOOKUP($C76,'Cons. Financials - ''23 ''24'!$C$8:$C$79,'Cons. Financials - ''23 ''24'!P$8:P$79) -> 13573.705 | E76: =_xlfn.XLOOKUP($C76,'Cons. Financials - ''23 ''24'!$C$8:$C$79,'Cons. Financials - ''23 ''24'!Q$8:Q$79) -> 12769.686 | F76: =_xlfn.XLOOKUP($C76,'Cons. Financials - ''23 ''24'!$C$8:$C$79,'Cons. Financials - ''23 ''24'!R$8:R$79) -> 12650.005 | G76: =_xlfn.XLOOKUP($C76,'Cons. Financials - ''23 ''24'!$C$8:$C$79,'Cons. Financials - ''23 ''24'!S$8:S$79) -> 11793.304 | H76: =_xlfn.XLOOKUP($C76,'Cons. Financials - ''23 ''24'!$C$8:$C$79,'Cons. Financials - ''23 ''24'!T$8:T$79) -> 11858.264 | I76: =_xlfn.XLOOKUP($C76,'Cons. Financials - ''23 ''24'!$C$8:$C$79,'Cons. Financials - ''23 ''24'!U$8:U$79) -> 10888.355 | J76: =_xlfn.XLOOKUP($C76,'Cons. Financials - ''23 ''24'!$C$8:$C$79,'Cons. Financials - ''23 ''24'!V$8:V$79) -> 12742.519 | K76: =_xlfn.XLOOKUP($C76,'Cons. Financials - ''23 ''24'!$C$8:$C$79,'Cons. Financials - ''23 ''24'!W$8:W$79) -> 13239.373 | ... O76: =_xlfn.XLOOKUP($C76,'Cons. Financials - ''23 ''24'!$C$8:$C$79,'Cons. Financials - ''23 ''24'!AA$8:AA$79) -> 9886.5489 | P76: =SUMIFS('Site Level Budget - ''25'!S:S,'Site Level Budget - ''25'!$F:$F,'Consolidated Budget - ''25'!$C76) -> 14639.446 | Q76: =SUMIFS('Site Level Budget - ''25'!T:T,'Site Level Budget - ''25'!$F:$F,'Consolidated Budget - ''25'!$C76) -> 15356.317 | R76: =SUMIFS('Site Level Budget - ''25'!U:U,'Site Level Budget - ''25'!$F:$F,'Consolidated Budget - ''25'!$C76) -> 16489.448 | S76: =SUMIFS('Site Level Budget - ''25'!V:V,'Site Level Budget - ''25'!$F:$F,'Consolidated Budget - ''25'!$C76) -> 17836.837 | T76: =SUMIFS('Site Level Budget - ''25'!W:W,'Site Level Budget - ''25'!$F:$F,'Consolidated Budget - ''25'!$C76) -> 21199.289 | U76: =SUMIFS('Site Level Budget - ''25'!X:X,'Site Level Budget - ''25'!$F:$F,'Consolidated Budget - ''25'!$C76) -> 17802.076 | V76: =SUMIFS('Site Level Budget - ''25'!Y:Y,'Site Level Budget - ''25'!$F:$F,'Consolidated Budget - ''25'!$C76) -> 18509.514 | W76: =SUMIFS('Site Level Budget - ''25'!Z:Z,'Site Level Budget - ''25'!$F:$F,'Consolidated Budget - ''25'!$C76) -> 15871.739 | X76: =SUMIFS('Site Level Budget - ''25'!AA:AA,'Site Level Budget - ''25'!$F:$F,'Consolidated Budget - ''25'!$C76) -> 14551.798 | Y76: =SUMIFS('Site Level Budget - ''25'!AB:AB,'Site Level Budget - ''25'!$F:$F,'Consolidated Budget - ''25'!$C76) -> 16712.634 | Z76: =SUMIFS('Site Level Budget - ''25'!AC:AC,'Site Level Budget - ''25'!$F:$F,'Consolidated Budget - ''25'!$C76) -> 13210.819 | AA76: =SUMIFS('Site Level Budget - ''25'!AD:AD,'Site Level Budget - ''25'!$F:$F,'Consolidated Budget - ''25'!$C76) -> 10782.836 | AC76: ='Cons. Financials - ''23 ''24'!AC76 -> 127053.22 | AD76: =SUM(D76:O76) -> 147518.45 | AE76: =SUM(P76:AA76) -> 192962.75
C77: Collections as a % of Production | D77: =(D76/D$12) -> 0.98117744 | E77: =(E76/E$12) -> 0.97934571 | F77: =(F76/F$12) -> 0.9810594 | G77: =(G76/G$12) -> 0.97744312 | H77: =(H76/H$12) -> 0.97924396 | I77: =(I76/I$12) -> 0.97926259 | J77: =(J76/J$12) -> 0.9803703 | K77: =(K76/K$12) -> 0.97956696 | ... AA77: =(AA76/AA$12) -> 0.98001182 | AC77: ='Cons. Financials - ''23 ''24'!AC77 -> 0.98016221 | AD77: =(AD76/AD$12) -> 0.97980734 | AE77: =(AE76/AE$12) -> 0.98003268
C79: Production per Vet Workday - YoY Change | D79: =_xlfn.XLOOKUP($C79,'Cons. Financials - ''23 ''24'!$C$8:$C$79,'Cons. Financials - ''23 ''24'!P$8:P$79) -> 0.048216688 | E79: =_xlfn.XLOOKUP($C79,'Cons. Financials - ''23 ''24'!$C$8:$C$79,'Cons. Financials - ''23 ''24'!Q$8:Q$79) -> 0.06506965 | F79: =_xlfn.XLOOKUP($C79,'Cons. Financials - ''23 ''24'!$C$8:$C$79,'Cons. Financials - ''23 ''24'!R$8:R$79) -> 0.031560101 | G79: =_xlfn.XLOOKUP($C79,'Cons. Financials - ''23 ''24'!$C$8:$C$79,'Cons. Financials - ''23 ''24'!S$8:S$79) -> 0.046129847 | H79: =_xlfn.XLOOKUP($C79,'Cons. Financials - ''23 ''24'!$C$8:$C$79,'Cons. Financials - ''23 ''24'!T$8:T$79) -> 0.031249017 | I79: =_xlfn.XLOOKUP($C79,'Cons. Financials - ''23 ''24'!$C$8:$C$79,'Cons. Financials - ''23 ''24'!U$8:U$79) -> 0.046651515 | J79: =_xlfn.XLOOKUP($C79,'Cons. Financials - ''23 ''24'!$C$8:$C$79,'Cons. Financials - ''23 ''24'!V$8:V$79) -> 0.041243933 | K79: =_xlfn.XLOOKUP($C79,'Cons. Financials - ''23 ''24'!$C$8:$C$79,'Cons. Financials - ''23 ''24'!W$8:W$79) -> 0.012501749 | ... O79: =_xlfn.XLOOKUP($C79,'Cons. Financials - ''23 ''24'!$C$8:$C$79,'Cons. Financials - ''23 ''24'!AA$8:AA$79) -> -0.0089330595 | P79: =P11/D11-1 -> -0.0065925607 | Q79: =Q11/E11-1 -> -0.0064540076 | R79: =R11/F11-1 -> -0.003360167 | S79: =S11/G11-1 -> -0.006091827 | T79: =T11/H11-1 -> -0.0030415385 | U79: =U11/I11-1 -> 0.0004332273 | V79: =V11/J11-1 -> -0.024188761 | W79: =W11/K11-1 -> -0.020380677 | ... AA79: =AA11/O11-1 -> -0.005960587 | AD79: =AD11/AC11-1 -> 0.041412867 | AE79: =AE11/AD11-1 -> 0.012969467
B83: Happy Pets Vets | AE83: =TODAY() -> 45999
C84: Balance Sheet and Supporting Schedules | AE84: ($ in 000s)
D86: 2024A | P86: 2025 Budget
D87: 44957 | E87: =EOMONTH(D87,1) -> 44985 | F87: =EOMONTH(E87,1) -> 45016 | G87: =EOMONTH(F87,1) -> 45046 | H87: =EOMONTH(G87,1) -> 45077 | I87: =EOMONTH(H87,1) -> 45107 | J87: =EOMONTH(I87,1) -> 45138 | K87: =EOMONTH(J87,1) -> 45169 | L87: =EOMONTH(K87,1) -> 45199 | ... AA87: =EOMONTH(Z87,1) -> 45657
C89: Cash & Cash Equivalents | D89: =_xlfn.XLOOKUP($C89,'Cons. Financials - ''23 ''24'!$C$89:$C$149,'Cons. Financials - ''23 ''24'!P$89:P$149) -> 13173.61 | E89: =_xlfn.XLOOKUP($C89,'Cons. Financials - ''23 ''24'!$C$89:$C$149,'Cons. Financials - ''23 ''24'!Q$89:Q$149) -> 13785.012 | F89: =_xlfn.XLOOKUP($C89,'Cons. Financials - ''23 ''24'!$C$89:$C$149,'Cons. Financials - ''23 ''24'!R$89:R$149) -> 13488.748 | G89: =_xlfn.XLOOKUP($C89,'Cons. Financials - ''23 ''24'!$C$89:$C$149,'Cons. Financials - ''23 ''24'!S$89:S$149) -> 13989.07 | H89: =_xlfn.XLOOKUP($C89,'Cons. Financials - ''23 ''24'!$C$89:$C$149,'Cons. Financials - ''23 ''24'!T$89:T$149) -> 13005.638 | I89: =_xlfn.XLOOKUP($C89,'Cons. Financials - ''23 ''24'!$C$89:$C$149,'Cons. Financials - ''23 ''24'!U$89:U$149) -> 10071.56 | J89: =_xlfn.XLOOKUP($C89,'Cons. Financials - ''23 ''24'!$C$89:$C$149,'Cons. Financials - ''23 ''24'!V$89:V$149) -> 10905.635 | K89: =_xlfn.XLOOKUP($C89,'Cons. Financials - ''23 ''24'!$C$89:$C$149,'Cons. Financials - ''23 ''24'!W$89:W$149) -> 12680.159 | ... O89: =_xlfn.XLOOKUP($C89,'Cons. Financials - ''23 ''24'!$C$89:$C$149,'Cons. Financials - ''23 ''24'!AA$89:AA$149) -> 20550.831 | P89: =O89+P179 -> 23480.095 | Q89: =P89+Q179 -> 24438.573 | R89: =Q89+R179 -> 24757.917 | S89: =R89+S179 -> 25437.489 | T89: =S89+T179 -> 24022.069 | U89: =T89+U179 -> 15113.565 | V89: =U89+V179 -> 15639.879 | W89: =V89+W179 -> 17428.523 | ... AA89: =Z89+AA179 -> 22866.169
C90: Accounts receivable net | D90: =_xlfn.XLOOKUP($C90,'Cons. Financials - ''23 ''24'!$C$89:$C$149,'Cons. Financials - ''23 ''24'!P$89:P$149) -> 14066.965 | E90: =_xlfn.XLOOKUP($C90,'Cons. Financials - ''23 ''24'!$C$89:$C$149,'Cons. Financials - ''23 ''24'!Q$89:Q$149) -> 14208.021 | F90: =_xlfn.XLOOKUP($C90,'Cons. Financials - ''23 ''24'!$C$89:$C$149,'Cons. Financials - ''23 ''24'!R$89:R$149) -> 14354.796 | G90: =_xlfn.XLOOKUP($C90,'Cons. Financials - ''23 ''24'!$C$89:$C$149,'Cons. Financials - ''23 ''24'!S$89:S$149) -> 13606.018 | H90: =_xlfn.XLOOKUP($C90,'Cons. Financials - ''23 ''24'!$C$89:$C$149,'Cons. Financials - ''23 ''24'!T$89:T$149) -> 12999.925 | I90: =_xlfn.XLOOKUP($C90,'Cons. Financials - ''23 ''24'!$C$89:$C$149,'Cons. Financials - ''23 ''24'!U$89:U$149) -> 12106.236 | J90: =_xlfn.XLOOKUP($C90,'Cons. Financials - ''23 ''24'!$C$89:$C$149,'Cons. Financials - ''23 ''24'!V$89:V$149) -> 12668.991 | K90: =_xlfn.XLOOKUP($C90,'Cons. Financials - ''23 ''24'!$C$89:$C$149,'Cons. Financials - ''23 ''24'!W$89:W$149) -> 13123.033 | ... O90: =_xlfn.XLOOKUP($C90,'Cons. Financials - ''23 ''24'!$C$89:$C$149,'Cons. Financials - ''23 ''24'!AA$89:AA$149) -> 13303.136 | P90: =P121/365*P122*4 -> 13614.058 | Q90: =Q121/365*Q122*4 -> 15010.38 | R90: =R121/365*R122*4 -> 17130.037 | S90: =S121/365*S122*4 -> 18162.871 | T90: =T121/365*T122*4 -> 19883.347 | U90: =U121/365*U122*4 -> 19909.001 | V90: =V121/365*V122*4 -> 20539.641 | W90: =W121/365*W122*4 -> 18581.212 | ... AA90: =AA121/365*AA122*4 -> 15089.646
C91: Inventories | D91: =_xlfn.XLOOKUP($C91,'Cons. Financials - ''23 ''24'!$C$89:$C$149,'Cons. Financials - ''23 ''24'!P$89:P$149) -> 578.35458 | E91: =_xlfn.XLOOKUP($C91,'Cons. Financials - ''23 ''24'!$C$89:$C$149,'Cons. Financials - ''23 ''24'!Q$89:Q$149) -> 615.56505 | F91: =_xlfn.XLOOKUP($C91,'Cons. Financials - ''23 ''24'!$C$89:$C$149,'Cons. Financials - ''23 ''24'!R$89:R$149) -> 709.42225 | G91: =_xlfn.XLOOKUP($C91,'Cons. Financials - ''23 ''24'!$C$89:$C$149,'Cons. Financials - ''23 ''24'!S$89:S$149) -> 737.2791 | H91: =_xlfn.XLOOKUP($C91,'Cons. Financials - ''23 ''24'!$C$89:$C$149,'Cons. Financials - ''23 ''24'!T$89:T$149) -> 803.13031 | I91: =_xlfn.XLOOKUP($C91,'Cons. Financials - ''23 ''24'!$C$89:$C$149,'Cons. Financials - ''23 ''24'!U$89:U$149) -> 811.10528 | J91: =_xlfn.XLOOKUP($C91,'Cons. Financials - ''23 ''24'!$C$89:$C$149,'Cons. Financials - ''23 ''24'!V$89:V$149) -> 797.51991 | K91: =_xlfn.XLOOKUP($C91,'Cons. Financials - ''23 ''24'!$C$89:$C$149,'Cons. Financials - ''23 ''24'!W$89:W$149) -> 698.92814 | ... O91: =_xlfn.XLOOKUP($C91,'Cons. Financials - ''23 ''24'!$C$89:$C$149,'Cons. Financials - ''23 ''24'!AA$89:AA$149) -> 537.4508 | P91: =P124/365*P125*4 -> 614.55455 | Q91: =Q124/365*Q125*4 -> 693.75019 | R91: =R124/365*R125*4 -> 853.53778 | S91: =S124/365*S125*4 -> 1013.1722 | T91: =T124/365*T125*4 -> 1296.5381 | U91: =U124/365*U125*4 -> 1398.8772 | V91: =V124/365*V125*4 -> 1361.9106 | W91: =W124/365*W125*4 -> 1038.0174 | ... AA91: =AA124/365*AA125*4 -> 615.11238
C92: Accrued Compensation | D92: =_xlfn.XLOOKUP($C92,'Cons. Financials - ''23 ''24'!$C$89:$C$149,'Cons. Financials - ''23 ''24'!P$89:P$149) -> 88.333333 | E92: =_xlfn.XLOOKUP($C92,'Cons. Financials - ''23 ''24'!$C$89:$C$149,'Cons. Financials - ''23 ''24'!Q$89:Q$149) -> 173.60417 | F92: =_xlfn.XLOOKUP($C92,'Cons. Financials - ''23 ''24'!$C$89:$C$149,'Cons. Financials - ''23 ''24'!R$89:R$149) -> 259.22917 | G92: =_xlfn.XLOOKUP($C92,'Cons. Financials - ''23 ''24'!$C$89:$C$149,'Cons. Financials - ''23 ''24'!S$89:S$149) -> 340.85417 | H92: =_xlfn.XLOOKUP($C92,'Cons. Financials - ''23 ''24'!$C$89:$C$149,'Cons. Financials - ''23 ''24'!T$89:T$149) -> 420.47917 | I92: =_xlfn.XLOOKUP($C92,'Cons. Financials - ''23 ''24'!$C$89:$C$149,'Cons. Financials - ''23 ''24'!U$89:U$149) -> 504.10417 | J92: =_xlfn.XLOOKUP($C92,'Cons. Financials - ''23 ''24'!$C$89:$C$149,'Cons. Financials - ''23 ''24'!V$89:V$149) -> 561.47917 | K92: =_xlfn.XLOOKUP($C92,'Cons. Financials - ''23 ''24'!$C$89:$C$149,'Cons. Financials - ''23 ''24'!W$89:W$149) -> 641.35417 | ... O92: =_xlfn.XLOOKUP($C92,'Cons. Financials - ''23 ''24'!$C$89:$C$149,'Cons. Financials - ''23 ''24'!AA$89:AA$149) -> 3.7472222 | P92: =O92+('Corporate Monthly - ''25'!I294-'Corporate Monthly - ''25'!I117)/1000 -> 101.41389 | Q92: =P92+('Corporate Monthly - ''25'!J294-'Corporate Monthly - ''25'!J117)/1000 -> 210.16389 | R92: =Q92+('Corporate Monthly - ''25'!K294-'Corporate Monthly - ''25'!K117)/1000 -> 318.91389 | S92: =R92+('Corporate Monthly - ''25'!L294-'Corporate Monthly - ''25'!L117)/1000 -> 427.66389 | T92: =S92+('Corporate Monthly - ''25'!M294-'Corporate Monthly - ''25'!M117)/1000 -> 536.41389 | U92: =T92+('Corporate Monthly - ''25'!N294-'Corporate Monthly - ''25'!N117)/1000 -> 645.16389 | V92: =U92+('Corporate Monthly - ''25'!O294-'Corporate Monthly - ''25'!O117)/1000 -> 753.91389 | W92: =V92+('Corporate Monthly - ''25'!P294-'Corporate Monthly - ''25'!P117)/1000 -> 862.66389 | ... AA92: =Z92+('Corporate Monthly - ''25'!T294-'Corporate Monthly - ''25'!T117)/1000 -> 3.7472222
C93: Prepaid expenses and other current assets | D93: =_xlfn.XLOOKUP($C93,'Cons. Financials - ''23 ''24'!$C$89:$C$149,'Cons. Financials - ''23 ''24'!P$89:P$149) -> 7426.8519 | E93: =_xlfn.XLOOKUP($C93,'Cons. Financials - ''23 ''24'!$C$89:$C$149,'Cons. Financials - ''23 ''24'!Q$89:Q$149) -> 7744.8019 | F93: =_xlfn.XLOOKUP($C93,'Cons. Financials - ''23 ''24'!$C$89:$C$149,'Cons. Financials - ''23 ''24'!R$89:R$149) -> 8229.5566 | G93: =_xlfn.XLOOKUP($C93,'Cons. Financials - ''23 ''24'!$C$89:$C$149,'Cons. Financials - ''23 ''24'!S$89:S$149) -> 7501.3407 | H93: =_xlfn.XLOOKUP($C93,'Cons. Financials - ''23 ''24'!$C$89:$C$149,'Cons. Financials - ''23 ''24'!T$89:T$149) -> 7447.3253 | I93: =_xlfn.XLOOKUP($C93,'Cons. Financials - ''23 ''24'!$C$89:$C$149,'Cons. Financials - ''23 ''24'!U$89:U$149) -> 6830.6613 | J93: =_xlfn.XLOOKUP($C93,'Cons. Financials - ''23 ''24'!$C$89:$C$149,'Cons. Financials - ''23 ''24'!V$89:V$149) -> 7067.8713 | K93: =_xlfn.XLOOKUP($C93,'Cons. Financials - ''23 ''24'!$C$89:$C$149,'Cons. Financials - ''23 ''24'!W$89:W$149) -> 7611.8645 | ... O93: =_xlfn.XLOOKUP($C93,'Cons. Financials - ''23 ''24'!$C$89:$C$149,'Cons. Financials - ''23 ''24'!AA$89:AA$149) -> 8477.3958 | P93: =P130*P122 -> 7187.733 | Q93: =Q130*Q122 -> 8182.1681 | R93: =R130*R122 -> 9820.593 | S93: =S130*S122 -> 10013.649 | T93: =T130*T122 -> 11390.662 | U93: =U130*U122 -> 11233.19 | V93: =V130*V122 -> 11458.808 | W93: =W130*W122 -> 10777.819 | ... AA93: =AA130*AA122 -> 9615.8458
C94: Total Current Assets | D94: =SUM(D89:D93) -> 35334.115 | E94: =SUM(E89:E93) -> 36527.005 | F94: =SUM(F89:F93) -> 37041.752 | G94: =SUM(G89:G93) -> 36174.562 | H94: =SUM(H89:H93) -> 34676.498 | I94: =SUM(I89:I93) -> 30323.667 | J94: =SUM(J89:J93) -> 32001.496 | K94: =SUM(K89:K93) -> 34755.339 | ... AA94: =SUM(AA89:AA93) -> 48190.521
C96: Property and equipment net | D96: =_xlfn.XLOOKUP($C96,'Cons. Financials - ''23 ''24'!$C$89:$C$149,'Cons. Financials - ''23 ''24'!P$89:P$149) -> 24134.565 | E96: =_xlfn.XLOOKUP($C96,'Cons. Financials - ''23 ''24'!$C$89:$C$149,'Cons. Financials - ''23 ''24'!Q$89:Q$149) -> 24175.731 | F96: =_xlfn.XLOOKUP($C96,'Cons. Financials - ''23 ''24'!$C$89:$C$149,'Cons. Financials - ''23 ''24'!R$89:R$149) -> 24488.278 | G96: =_xlfn.XLOOKUP($C96,'Cons. Financials - ''23 ''24'!$C$89:$C$149,'Cons. Financials - ''23 ''24'!S$89:S$149) -> 24453.676 | H96: =_xlfn.XLOOKUP($C96,'Cons. Financials - ''23 ''24'!$C$89:$C$149,'Cons. Financials - ''23 ''24'!T$89:T$149) -> 24487.501 | I96: =_xlfn.XLOOKUP($C96,'Cons. Financials - ''23 ''24'!$C$89:$C$149,'Cons. Financials - ''23 ''24'!U$89:U$149) -> 24569.701 | J96: =_xlfn.XLOOKUP($C96,'Cons. Financials - ''23 ''24'!$C$89:$C$149,'Cons. Financials - ''23 ''24'!V$89:V$149) -> 24473.576 | K96: =_xlfn.XLOOKUP($C96,'Cons. Financials - ''23 ''24'!$C$89:$C$149,'Cons. Financials - ''23 ''24'!W$89:W$149) -> 24566.547 | ... O96: =_xlfn.XLOOKUP($C96,'Cons. Financials - ''23 ''24'!$C$89:$C$149,'Cons. Financials - ''23 ''24'!AA$89:AA$149) -> 24819.97 | P96: =O96-P171+P56 -> 25032.586 | Q96: =P96-Q171+Q56 -> 25241.034 | R96: =Q96-R171+R56 -> 25445.316 | S96: =R96-S171+S56 -> 25645.432 | T96: =S96-T171+T56 -> 25841.38 | U96: =T96-U171+U56 -> 26033.162 | V96: =U96-V171+V56 -> 26716.611 | W96: =V96-W171+W56 -> 27391.726 | ... AA96: =Z96-AA171+AA56 -> 30008.854
C97: Operating lease right-of-use assets | D97: =_xlfn.XLOOKUP($C97,'Cons. Financials - ''23 ''24'!$C$89:$C$149,'Cons. Financials - ''23 ''24'!P$89:P$149) -> 23842 | E97: =_xlfn.XLOOKUP($C97,'Cons. Financials - ''23 ''24'!$C$89:$C$149,'Cons. Financials - ''23 ''24'!Q$89:Q$149) -> 23842 | F97: =_xlfn.XLOOKUP($C97,'Cons. Financials - ''23 ''24'!$C$89:$C$149,'Cons. Financials - ''23 ''24'!R$89:R$149) -> 23842 | G97: =_xlfn.XLOOKUP($C97,'Cons. Financials - ''23 ''24'!$C$89:$C$149,'Cons. Financials - ''23 ''24'!S$89:S$149) -> 23842 | H97: =_xlfn.XLOOKUP($C97,'Cons. Financials - ''23 ''24'!$C$89:$C$149,'Cons. Financials - ''23 ''24'!T$89:T$149) -> 23842 | I97: =_xlfn.XLOOKUP($C97,'Cons. Financials - ''23 ''24'!$C$89:$C$149,'Cons. Financials - ''23 ''24'!U$89:U$149) -> 23842 | J97: =_xlfn.XLOOKUP($C97,'Cons. Financials - ''23 ''24'!$C$89:$C$149,'Cons. Financials - ''23 ''24'!V$89:V$149) -> 23842 | K97: =_xlfn.XLOOKUP($C97,'Cons. Financials - ''23 ''24'!$C$89:$C$149,'Cons. Financials - ''23 ''24'!W$89:W$149) -> 23842 | ... O97: =_xlfn.XLOOKUP($C97,'Cons. Financials - ''23 ''24'!$C$89:$C$149,'Cons. Financials - ''23 ''24'!AA$89:AA$149) -> 23842 | P97: =O97 -> 23842 | Q97: =P97 -> 23842 | R97: =Q97 -> 23842 | S97: =R97 -> 23842 | T97: =S97 -> 23842 | U97: =T97 -> 23842 | V97: =U97 -> 23842 | W97: =V97 -> 23842 | ... AA97: =Z97 -> 23842
C98: Intangible assets net | D98: =_xlfn.XLOOKUP($C98,'Cons. Financials - ''23 ''24'!$C$89:$C$149,'Cons. Financials - ''23 ''24'!P$89:P$149) -> 183356.81 | E98: =_xlfn.XLOOKUP($C98,'Cons. Financials - ''23 ''24'!$C$89:$C$149,'Cons. Financials - ''23 ''24'!Q$89:Q$149) -> 183344.68 | F98: =_xlfn.XLOOKUP($C98,'Cons. Financials - ''23 ''24'!$C$89:$C$149,'Cons. Financials - ''23 ''24'!R$89:R$149) -> 183332.55 | G98: =_xlfn.XLOOKUP($C98,'Cons. Financials - ''23 ''24'!$C$89:$C$149,'Cons. Financials - ''23 ''24'!S$89:S$149) -> 183320.42 | H98: =_xlfn.XLOOKUP($C98,'Cons. Financials - ''23 ''24'!$C$89:$C$149,'Cons. Financials - ''23 ''24'!T$89:T$149) -> 183308.29 | I98: =_xlfn.XLOOKUP($C98,'Cons. Financials - ''23 ''24'!$C$89:$C$149,'Cons. Financials - ''23 ''24'!U$89:U$149) -> 183296.15 | J98: =_xlfn.XLOOKUP($C98,'Cons. Financials - ''23 ''24'!$C$89:$C$149,'Cons. Financials - ''23 ''24'!V$89:V$149) -> 183284.02 | K98: =_xlfn.XLOOKUP($C98,'Cons. Financials - ''23 ''24'!$C$89:$C$149,'Cons. Financials - ''23 ''24'!W$89:W$149) -> 183271.89 | ... O98: =_xlfn.XLOOKUP($C98,'Cons. Financials - ''23 ''24'!$C$89:$C$149,'Cons. Financials - ''23 ''24'!AA$89:AA$149) -> 183223.36 | P98: =O98+P59 -> 183211.23 | Q98: =P98+Q59 -> 183199.1 | R98: =Q98+R59 -> 183186.97 | S98: =R98+S59 -> 183174.83 | T98: =S98+T59 -> 183162.7 | U98: =T98+U59 -> 183150.57 | V98: =U98+V59 -> 183138.44 | W98: =V98+W59 -> 183126.31 | ... AA98: =Z98+AA59 -> 183077.78
C99: Other assets | D99: =_xlfn.XLOOKUP($C99,'Cons. Financials - ''23 ''24'!$C$89:$C$149,'Cons. Financials - ''23 ''24'!P$89:P$149) -> 2305.067 | E99: =_xlfn.XLOOKUP($C99,'Cons. Financials - ''23 ''24'!$C$89:$C$149,'Cons. Financials - ''23 ''24'!Q$89:Q$149) -> 2302.9746 | F99: =_xlfn.XLOOKUP($C99,'Cons. Financials - ''23 ''24'!$C$89:$C$149,'Cons. Financials - ''23 ''24'!R$89:R$149) -> 2298.3279 | G99: =_xlfn.XLOOKUP($C99,'Cons. Financials - ''23 ''24'!$C$89:$C$149,'Cons. Financials - ''23 ''24'!S$89:S$149) -> 2295.7772 | H99: =_xlfn.XLOOKUP($C99,'Cons. Financials - ''23 ''24'!$C$89:$C$149,'Cons. Financials - ''23 ''24'!T$89:T$149) -> 2296.9493 | I99: =_xlfn.XLOOKUP($C99,'Cons. Financials - ''23 ''24'!$C$89:$C$149,'Cons. Financials - ''23 ''24'!U$89:U$149) -> 2294.3928 | J99: =_xlfn.XLOOKUP($C99,'Cons. Financials - ''23 ''24'!$C$89:$C$149,'Cons. Financials - ''23 ''24'!V$89:V$149) -> 2297.7077 | K99: =_xlfn.XLOOKUP($C99,'Cons. Financials - ''23 ''24'!$C$89:$C$149,'Cons. Financials - ''23 ''24'!W$89:W$149) -> 2292.7594 | ... O99: =_xlfn.XLOOKUP($C99,'Cons. Financials - ''23 ''24'!$C$89:$C$149,'Cons. Financials - ''23 ''24'!AA$89:AA$149) -> 2287.6535 | P99: =O99 -> 2287.6535 | Q99: =P99 -> 2287.6535 | R99: =Q99 -> 2287.6535 | S99: =R99 -> 2287.6535 | T99: =S99 -> 2287.6535 | U99: =T99 -> 2287.6535 | V99: =U99 -> 2287.6535 | W99: =V99 -> 2287.6535 | ... AA99: =Z99 -> 2287.6535
C100: Total Assets | D100: =SUM(D94,D96:D99) -> 268972.56 | E100: =SUM(E94,E96:E99) -> 270192.39 | F100: =SUM(F94,F96:F99) -> 271002.91 | G100: =SUM(G94,G96:G99) -> 270086.43 | H100: =SUM(H94,H96:H99) -> 268611.23 | I100: =SUM(I94,I96:I99) -> 264325.91 | J100: =SUM(J94,J96:J99) -> 265898.8 | K100: =SUM(K94,K96:K99) -> 268728.54 | ... AA100: =SUM(AA94,AA96:AA99) -> 287406.81
C102: Accounts Payable | D102: =_xlfn.XLOOKUP($C102,'Cons. Financials - ''23 ''24'!$C$89:$C$149,'Cons. Financials - ''23 ''24'!P$89:P$149) -> 271.25004 | E102: =_xlfn.XLOOKUP($C102,'Cons. Financials - ''23 ''24'!$C$89:$C$149,'Cons. Financials - ''23 ''24'!Q$89:Q$149) -> 283.25464 | F102: =_xlfn.XLOOKUP($C102,'Cons. Financials - ''23 ''24'!$C$89:$C$149,'Cons. Financials - ''23 ''24'!R$89:R$149) -> 318.62093 | G102: =_xlfn.XLOOKUP($C102,'Cons. Financials - ''23 ''24'!$C$89:$C$149,'Cons. Financials - ''23 ''24'!S$89:S$149) -> 333.70359 | H102: =_xlfn.XLOOKUP($C102,'Cons. Financials - ''23 ''24'!$C$89:$C$149,'Cons. Financials - ''23 ''24'!T$89:T$149) -> 379.51654 | I102: =_xlfn.XLOOKUP($C102,'Cons. Financials - ''23 ''24'!$C$89:$C$149,'Cons. Financials - ''23 ''24'!U$89:U$149) -> 384.51875 | J102: =_xlfn.XLOOKUP($C102,'Cons. Financials - ''23 ''24'!$C$89:$C$149,'Cons. Financials - ''23 ''24'!V$89:V$149) -> 378.42225 | K102: =_xlfn.XLOOKUP($C102,'Cons. Financials - ''23 ''24'!$C$89:$C$149,'Cons. Financials - ''23 ''24'!W$89:W$149) -> 340.33932 | ... O102: =_xlfn.XLOOKUP($C102,'Cons. Financials - ''23 ''24'!$C$89:$C$149,'Cons. Financials - ''23 ''24'!AA$89:AA$149) -> 275.18775 | P102: =P133*P132 -> 274.64298 | Q102: =Q133*Q132 -> 312.44434 | R102: =R133*R132 -> 382.1935 | S102: =S133*S132 -> 449.11309 | T102: =T133*T132 -> 590.1189 | U102: =U133*U132 -> 635.7478 | V102: =V133*V132 -> 618.76891 | W102: =W133*W132 -> 489.87045 | ... AA102: =AA133*AA132 -> 312.95928
C103: Deferred Revenue | D103: =_xlfn.XLOOKUP($C103,'Cons. Financials - ''23 ''24'!$C$89:$C$149,'Cons. Financials - ''23 ''24'!P$89:P$149) -> 12443.338 | E103: =_xlfn.XLOOKUP($C103,'Cons. Financials - ''23 ''24'!$C$89:$C$149,'Cons. Financials - ''23 ''24'!Q$89:Q$149) -> 12529.921 | F103: =_xlfn.XLOOKUP($C103,'Cons. Financials - ''23 ''24'!$C$89:$C$149,'Cons. Financials - ''23 ''24'!R$89:R$149) -> 12551.701 | G103: =_xlfn.XLOOKUP($C103,'Cons. Financials - ''23 ''24'!$C$89:$C$149,'Cons. Financials - ''23 ''24'!S$89:S$149) -> 11618.612 | H103: =_xlfn.XLOOKUP($C103,'Cons. Financials - ''23 ''24'!$C$89:$C$149,'Cons. Financials - ''23 ''24'!T$89:T$149) -> 10814.638 | I103: =_xlfn.XLOOKUP($C103,'Cons. Financials - ''23 ''24'!$C$89:$C$149,'Cons. Financials - ''23 ''24'!U$89:U$149) -> 10447.876 | J103: =_xlfn.XLOOKUP($C103,'Cons. Financials - ''23 ''24'!$C$89:$C$149,'Cons. Financials - ''23 ''24'!V$89:V$149) -> 10824.646 | K103: =_xlfn.XLOOKUP($C103,'Cons. Financials - ''23 ''24'!$C$89:$C$149,'Cons. Financials - ''23 ''24'!W$89:W$149) -> 11336.423 | ... O103: =_xlfn.XLOOKUP($C103,'Cons. Financials - ''23 ''24'!$C$89:$C$149,'Cons. Financials - ''23 ''24'!AA$89:AA$149) -> 11666.095 | P103: =P135*P122 -> 12042.706 | Q103: =Q135*Q122 -> 13237.513 | R103: =R135*R122 -> 14978.346 | S103: =S135*S122 -> 15509.855 | T103: =T135*T122 -> 16540.956 | U103: =U135*U122 -> 17181.787 | V103: =V135*V122 -> 17549.492 | W103: =W135*W122 -> 16051.509 | ... AA103: =AA135*AA122 -> 13232.763
C104: Accrued expenses and other current liabilities | D104: =_xlfn.XLOOKUP($C104,'Cons. Financials - ''23 ''24'!$C$89:$C$149,'Cons. Financials - ''23 ''24'!P$89:P$149) -> 8840.4526 | E104: =_xlfn.XLOOKUP($C104,'Cons. Financials - ''23 ''24'!$C$89:$C$149,'Cons. Financials - ''23 ''24'!Q$89:Q$149) -> 8624.0111 | F104: =_xlfn.XLOOKUP($C104,'Cons. Financials - ''23 ''24'!$C$89:$C$149,'Cons. Financials - ''23 ''24'!R$89:R$149) -> 8640.1178 | G104: =_xlfn.XLOOKUP($C104,'Cons. Financials - ''23 ''24'!$C$89:$C$149,'Cons. Financials - ''23 ''24'!S$89:S$149) -> 8511.5778 | H104: =_xlfn.XLOOKUP($C104,'Cons. Financials - ''23 ''24'!$C$89:$C$149,'Cons. Financials - ''23 ''24'!T$89:T$149) -> 8283.5071 | I104: =_xlfn.XLOOKUP($C104,'Cons. Financials - ''23 ''24'!$C$89:$C$149,'Cons. Financials - ''23 ''24'!U$89:U$149) -> 8066.1154 | J104: =_xlfn.XLOOKUP($C104,'Cons. Financials - ''23 ''24'!$C$89:$C$149,'Cons. Financials - ''23 ''24'!V$89:V$149) -> 8356.9425 | K104: =_xlfn.XLOOKUP($C104,'Cons. Financials - ''23 ''24'!$C$89:$C$149,'Cons. Financials - ''23 ''24'!W$89:W$149) -> 8649.7283 | ... O104: =_xlfn.XLOOKUP($C104,'Cons. Financials - ''23 ''24'!$C$89:$C$149,'Cons. Financials - ''23 ''24'!AA$89:AA$149) -> 8958.357 | P104: =P136*P122 -> 8555.8207 | Q104: =Q136*Q122 -> 9111.0282 | R104: =R136*R122 -> 10310.529 | S104: =S136*S122 -> 11362.229 | T104: =T136*T122 -> 12669.6 | U104: =U136*U122 -> 13264.924 | V104: =V136*V122 -> 13548.719 | W104: =W136*W122 -> 12247.355 | ... AA104: =AA136*AA122 -> 10161.396
C105: Total Current Liabilities | D105: =SUM(D102:D104) -> 21555.041 | E105: =SUM(E102:E104) -> 21437.186 | F105: =SUM(F102:F104) -> 21510.44 | G105: =SUM(G102:G104) -> 20463.894 | H105: =SUM(H102:H104) -> 19477.661 | I105: =SUM(I102:I104) -> 18898.51 | J105: =SUM(J102:J104) -> 19560.011 | K105: =SUM(K102:K104) -> 20326.491 | ... AA105: =SUM(AA102:AA104) -> 23707.119
C107: Long Term Debt - Revolver | D107: =_xlfn.XLOOKUP($C107,'Cons. Financials - ''23 ''24'!$C$89:$C$149,'Cons. Financials - ''23 ''24'!P$89:P$149) -> 3250 | E107: =_xlfn.XLOOKUP($C107,'Cons. Financials - ''23 ''24'!$C$89:$C$149,'Cons. Financials - ''23 ''24'!Q$89:Q$149) -> 3250 | F107: =_xlfn.XLOOKUP($C107,'Cons. Financials - ''23 ''24'!$C$89:$C$149,'Cons. Financials - ''23 ''24'!R$89:R$149) -> 3250 | G107: =_xlfn.XLOOKUP($C107,'Cons. Financials - ''23 ''24'!$C$89:$C$149,'Cons. Financials - ''23 ''24'!S$89:S$149) -> 3250 | H107: =_xlfn.XLOOKUP($C107,'Cons. Financials - ''23 ''24'!$C$89:$C$149,'Cons. Financials - ''23 ''24'!T$89:T$149) -> 3250 | I107: =_xlfn.XLOOKUP($C107,'Cons. Financials - ''23 ''24'!$C$89:$C$149,'Cons. Financials - ''23 ''24'!U$89:U$149) -> 0 | J107: =_xlfn.XLOOKUP($C107,'Cons. Financials - ''23 ''24'!$C$89:$C$149,'Cons. Financials - ''23 ''24'!V$89:V$149) -> 0 | K107: =_xlfn.XLOOKUP($C107,'Cons. Financials - ''23 ''24'!$C$89:$C$149,'Cons. Financials - ''23 ''24'!W$89:W$149) -> 0 | ... O107: =_xlfn.XLOOKUP($C107,'Cons. Financials - ''23 ''24'!$C$89:$C$149,'Cons. Financials - ''23 ''24'!AA$89:AA$149) -> 0 | P107: =O107+P175 -> 0 | Q107: =P107+Q175 -> 0 | R107: =Q107+R175 -> 0 | S107: =R107+S175 -> 0 | T107: =S107+T175 -> 0 | U107: =T107+U175 -> 10000 | V107: =U107+V175 -> 10000 | W107: =V107+W175 -> 10000 | ... AA107: =Z107+AA175 -> 10000
C108: Long Term Debt - Unitranche | D108: =_xlfn.XLOOKUP($C108,'Cons. Financials - ''23 ''24'!$C$89:$C$149,'Cons. Financials - ''23 ''24'!P$89:P$149) -> 95000 | E108: =_xlfn.XLOOKUP($C108,'Cons. Financials - ''23 ''24'!$C$89:$C$149,'Cons. Financials - ''23 ''24'!Q$89:Q$149) -> 95000 | F108: =_xlfn.XLOOKUP($C108,'Cons. Financials - ''23 ''24'!$C$89:$C$149,'Cons. Financials - ''23 ''24'!R$89:R$149) -> 94750 | G108: =_xlfn.XLOOKUP($C108,'Cons. Financials - ''23 ''24'!$C$89:$C$149,'Cons. Financials - ''23 ''24'!S$89:S$149) -> 94750 | H108: =_xlfn.XLOOKUP($C108,'Cons. Financials - ''23 ''24'!$C$89:$C$149,'Cons. Financials - ''23 ''24'!T$89:T$149) -> 94750 | I108: =_xlfn.XLOOKUP($C108,'Cons. Financials - ''23 ''24'!$C$89:$C$149,'Cons. Financials - ''23 ''24'!U$89:U$149) -> 94500 | J108: =_xlfn.XLOOKUP($C108,'Cons. Financials - ''23 ''24'!$C$89:$C$149,'Cons. Financials - ''23 ''24'!V$89:V$149) -> 94500 | K108: =_xlfn.XLOOKUP($C108,'Cons. Financials - ''23 ''24'!$C$89:$C$149,'Cons. Financials - ''23 ''24'!W$89:W$149) -> 94500 | ... O108: =_xlfn.XLOOKUP($C108,'Cons. Financials - ''23 ''24'!$C$89:$C$149,'Cons. Financials - ''23 ''24'!AA$89:AA$149) -> 94000 | P108: =O108+P176 -> 94000 | Q108: =P108+Q176 -> 94000 | R108: =Q108+R176 -> 93750 | S108: =R108+S176 -> 93750 | T108: =S108+T176 -> 93750 | U108: =T108+U176 -> 93500 | V108: =U108+V176 -> 93500 | W108: =V108+W176 -> 93500 | ... AA108: =Z108+AA176 -> 93000
C109: Operating lease right-of-use liabilities | D109: =_xlfn.XLOOKUP($C109,'Cons. Financials - ''23 ''24'!$C$89:$C$149,'Cons. Financials - ''23 ''24'!P$89:P$149) -> 23842 | E109: =_xlfn.XLOOKUP($C109,'Cons. Financials - ''23 ''24'!$C$89:$C$149,'Cons. Financials - ''23 ''24'!Q$89:Q$149) -> 23842 | F109: =_xlfn.XLOOKUP($C109,'Cons. Financials - ''23 ''24'!$C$89:$C$149,'Cons. Financials - ''23 ''24'!R$89:R$149) -> 23842 | G109: =_xlfn.XLOOKUP($C109,'Cons. Financials - ''23 ''24'!$C$89:$C$149,'Cons. Financials - ''23 ''24'!S$89:S$149) -> 23842 | H109: =_xlfn.XLOOKUP($C109,'Cons. Financials - ''23 ''24'!$C$89:$C$149,'Cons. Financials - ''23 ''24'!T$89:T$149) -> 23842 | I109: =_xlfn.XLOOKUP($C109,'Cons. Financials - ''23 ''24'!$C$89:$C$149,'Cons. Financials - ''23 ''24'!U$89:U$149) -> 23842 | J109: =_xlfn.XLOOKUP($C109,'Cons. Financials - ''23 ''24'!$C$89:$C$149,'Cons. Financials - ''23 ''24'!V$89:V$149) -> 23842 | K109: =_xlfn.XLOOKUP($C109,'Cons. Financials - ''23 ''24'!$C$89:$C$149,'Cons. Financials - ''23 ''24'!W$89:W$149) -> 23842 | ... O109: =_xlfn.XLOOKUP($C109,'Cons. Financials - ''23 ''24'!$C$89:$C$149,'Cons. Financials - ''23 ''24'!AA$89:AA$149) -> 23842 | P109: =O109 -> 23842 | Q109: =P109 -> 23842 | R109: =Q109 -> 23842 | S109: =R109 -> 23842 | T109: =S109 -> 23842 | U109: =T109 -> 23842 | V109: =U109 -> 23842 | W109: =V109 -> 23842 | ... AA109: =Z109 -> 23842
C110: Total Liabilities | D110: =SUM(D105,D107:D109) -> 143647.04 | E110: =SUM(E105,E107:E109) -> 143529.19 | F110: =SUM(F105,F107:F109) -> 143352.44 | G110: =SUM(G105,G107:G109) -> 142305.89 | H110: =SUM(H105,H107:H109) -> 141319.66 | I110: =SUM(I105,I107:I109) -> 137240.51 | J110: =SUM(J105,J107:J109) -> 137902.01 | K110: =SUM(K105,K107:K109) -> 138668.49 | ... AA110: =SUM(AA105,AA107:AA109) -> 150549.12
C112: Common Stock & Paid-in-capital | D112: =_xlfn.XLOOKUP($C112,'Cons. Financials - ''23 ''24'!$C$89:$C$149,'Cons. Financials - ''23 ''24'!P$89:P$149) -> 82320.123 | E112: =_xlfn.XLOOKUP($C112,'Cons. Financials - ''23 ''24'!$C$89:$C$149,'Cons. Financials - ''23 ''24'!Q$89:Q$149) -> 82320.123 | F112: =_xlfn.XLOOKUP($C112,'Cons. Financials - ''23 ''24'!$C$89:$C$149,'Cons. Financials - ''23 ''24'!R$89:R$149) -> 82320.123 | G112: =_xlfn.XLOOKUP($C112,'Cons. Financials - ''23 ''24'!$C$89:$C$149,'Cons. Financials - ''23 ''24'!S$89:S$149) -> 82320.123 | H112: =_xlfn.XLOOKUP($C112,'Cons. Financials - ''23 ''24'!$C$89:$C$149,'Cons. Financials - ''23 ''24'!T$89:T$149) -> 82320.123 | I112: =_xlfn.XLOOKUP($C112,'Cons. Financials - ''23 ''24'!$C$89:$C$149,'Cons. Financials - ''23 ''24'!U$89:U$149) -> 82320.123 | J112: =_xlfn.XLOOKUP($C112,'Cons. Financials - ''23 ''24'!$C$89:$C$149,'Cons. Financials - ''23 ''24'!V$89:V$149) -> 82320.123 | K112: =_xlfn.XLOOKUP($C112,'Cons. Financials - ''23 ''24'!$C$89:$C$149,'Cons. Financials - ''23 ''24'!W$89:W$149) -> 82320.123 | ... O112: =_xlfn.XLOOKUP($C112,'Cons. Financials - ''23 ''24'!$C$89:$C$149,'Cons. Financials - ''23 ''24'!AA$89:AA$149) -> 82320.123 | P112: =O112 -> 82320.123 | Q112: =P112 -> 82320.123 | R112: =Q112 -> 82320.123 | S112: =R112 -> 82320.123 | T112: =S112 -> 82320.123 | U112: =T112 -> 82320.123 | V112: =U112 -> 82320.123 | W112: =V112 -> 82320.123 | ... AA112: =Z112 -> 82320.123
C113: Retained Earnings | D113: =_xlfn.XLOOKUP($C113,'Cons. Financials - ''23 ''24'!$C$89:$C$149,'Cons. Financials - ''23 ''24'!P$89:P$149) -> 43005.398 | E113: =_xlfn.XLOOKUP($C113,'Cons. Financials - ''23 ''24'!$C$89:$C$149,'Cons. Financials - ''23 ''24'!Q$89:Q$149) -> 44343.084 | F113: =_xlfn.XLOOKUP($C113,'Cons. Financials - ''23 ''24'!$C$89:$C$149,'Cons. Financials - ''23 ''24'!R$89:R$149) -> 45330.345 | G113: =_xlfn.XLOOKUP($C113,'Cons. Financials - ''23 ''24'!$C$89:$C$149,'Cons. Financials - ''23 ''24'!S$89:S$149) -> 45460.417 | H113: =_xlfn.XLOOKUP($C113,'Cons. Financials - ''23 ''24'!$C$89:$C$149,'Cons. Financials - ''23 ''24'!T$89:T$149) -> 44971.45 | I113: =_xlfn.XLOOKUP($C113,'Cons. Financials - ''23 ''24'!$C$89:$C$149,'Cons. Financials - ''23 ''24'!U$89:U$149) -> 44765.282 | J113: =_xlfn.XLOOKUP($C113,'Cons. Financials - ''23 ''24'!$C$89:$C$149,'Cons. Financials - ''23 ''24'!V$89:V$149) -> 45676.669 | K113: =_xlfn.XLOOKUP($C113,'Cons. Financials - ''23 ''24'!$C$89:$C$149,'Cons. Financials - ''23 ''24'!W$89:W$149) -> 47739.922 | ... O113: =_xlfn.XLOOKUP($C113,'Cons. Financials - ''23 ''24'!$C$89:$C$149,'Cons. Financials - ''23 ''24'!AA$89:AA$149) -> 55983.784 | P113: =O113+P72+P174 -> 58336.031 | Q113: =P113+Q72+Q174 -> 60281.713 | R113: =Q113+R72+R174 -> 62059.744 | S113: =R113+S72+S174 -> 62771.444 | T113: =S113+T72+T174 -> 62549.968 | U113: =T113+U72+U174 -> 42868.6 | V113: =U113+V72+V174 -> 44359.753 | W113: =V113+W72+W174 -> 46885.064 | ... AA113: =Z113+AA72+AA174 -> 54537.566
C114: Total Shareholder's Equity | D114: =SUM(D112:D113) -> 125325.52 | E114: =SUM(E112:E113) -> 126663.21 | F114: =SUM(F112:F113) -> 127650.47 | G114: =SUM(G112:G113) -> 127780.54 | H114: =SUM(H112:H113) -> 127291.57 | I114: =SUM(I112:I113) -> 127085.4 | J114: =SUM(J112:J113) -> 127996.79 | K114: =SUM(K112:K113) -> 130060.05 | ... AA114: =SUM(AA112:AA113) -> 136857.69
...

Sheet Site Level Budget - '25
B2: Site | C2: Key | E2: Happy Pets Vets | AH2: =TODAY() -> 45999
B3: =G5 -> 1 | F3: Site Level Financials | AH3: ($ in 000s)
B5: =G5 -> 1 | F5: Site: | G5: 1
B6: =G5 -> 1 | F6: Paws & Claws Veterinary Care
B7: =G5 -> 1
B8: =G5 -> 1 | G8: 2024A | S8: 2025 Budget | AF8: Historicals | AH8: Budget
B9: =G5 -> 1 | G9: 44957 | H9: =EOMONTH(G9,1) -> 44985 | I9: =EOMONTH(H9,1) -> 45016 | J9: =EOMONTH(I9,1) -> 45046 | K9: =EOMONTH(J9,1) -> 45077 | L9: =EOMONTH(K9,1) -> 45107 | M9: =EOMONTH(L9,1) -> 45138 | N9: =EOMONTH(M9,1) -> 45169 | O9: =EOMONTH(N9,1) -> 45199 | ... AD9: =EOMONTH(AC9,1) -> 45657 | AF9: 45291 | AG9: 45657 | AH9: 46022
B10: =G5 -> 1
B11: =G5 -> 1 | C11: =B11&" - "&F11 -> 1 - Employed Vets | F11: Employed Vets | G11: =_xlfn.XLOOKUP($C11,'Site Level Financials - ''23 ''24'!$C$2:$C$1577,'Site Level Financials - ''23 ''24'!S$2:S$1577) -> 4 | H11: =_xlfn.XLOOKUP($C11,'Site Level Financials - ''23 ''24'!$C$2:$C$1577,'Site Level Financials - ''23 ''24'!T$2:T$1577) -> 4 | I11: =_xlfn.XLOOKUP($C11,'Site Level Financials - ''23 ''24'!$C$2:$C$1577,'Site Level Financials - ''23 ''24'!U$2:U$1577) -> 4 | J11: =_xlfn.XLOOKUP($C11,'Site Level Financials - ''23 ''24'!$C$2:$C$1577,'Site Level Financials - ''23 ''24'!V$2:V$1577) -> 3 | K11: =_xlfn.XLOOKUP($C11,'Site Level Financials - ''23 ''24'!$C$2:$C$1577,'Site Level Financials - ''23 ''24'!W$2:W$1577) -> 3 | L11: =_xlfn.XLOOKUP($C11,'Site Level Financials - ''23 ''24'!$C$2:$C$1577,'Site Level Financials - ''23 ''24'!X$2:X$1577) -> 4 | M11: =_xlfn.XLOOKUP($C11,'Site Level Financials - ''23 ''24'!$C$2:$C$1577,'Site Level Financials - ''23 ''24'!Y$2:Y$1577) -> 4 | N11: =_xlfn.XLOOKUP($C11,'Site Level Financials - ''23 ''24'!$C$2:$C$1577,'Site Level Financials - ''23 ''24'!Z$2:Z$1577) -> 5 | ... R11: =_xlfn.XLOOKUP($C11,'Site Level Financials - ''23 ''24'!$C$2:$C$1577,'Site Level Financials - ''23 ''24'!AD$2:AD$1577) -> 4 | S11: =R11+_xlfn.XLOOKUP($R11,'Budget Assumption Driver'!$A$7:$A$11,'Budget Assumption Driver'!E$7:E$11) -> 4 | T11: =S11+_xlfn.XLOOKUP($R11,'Budget Assumption Driver'!$A$7:$A$11,'Budget Assumption Driver'!F$7:F$11) -> 4 | U11: =T11+_xlfn.XLOOKUP($R11,'Budget Assumption Driver'!$A$7:$A$11,'Budget Assumption Driver'!G$7:G$11) -> 4 | V11: =U11+_xlfn.XLOOKUP($R11,'Budget Assumption Driver'!$A$7:$A$11,'Budget Assumption Driver'!H$7:H$11) -> 4 | W11: =V11+_xlfn.XLOOKUP($R11,'Budget Assumption Driver'!$A$7:$A$11,'Budget Assumption Driver'!I$7:I$11) -> 4 | X11: =W11+_xlfn.XLOOKUP($R11,'Budget Assumption Driver'!$A$7:$A$11,'Budget Assumption Driver'!J$7:J$11) -> 4 | Y11: =X11+_xlfn.XLOOKUP($R11,'Budget Assumption Driver'!$A$7:$A$11,'Budget Assumption Driver'!K$7:K$11) -> 4 | Z11: =Y11+_xlfn.XLOOKUP($R11,'Budget Assumption Driver'!$A$7:$A$11,'Budget Assumption Driver'!L$7:L$11) -> 4 | ... AD11: =AC11+_xlfn.XLOOKUP($R11,'Budget Assumption Driver'!$A$7:$A$11,'Budget Assumption Driver'!P$7:P$11) -> 4 | AF11: =_xlfn.XLOOKUP($C11,'Site Level Financials - ''23 ''24'!$C$2:$C$1577,'Site Level Financials - ''23 ''24'!$AF$2:$AF$1577) -> 4.5873606 | AG11: =AG13/AG12 -> 4.1635688 | AH11: =AH13/AH12 -> 4
B12: =G5 -> 1 | C12: =B12&" - "&F12 -> 1 - Workdays in Month / Year | F12: Workdays in Month / Year | G12: =_xlfn.XLOOKUP($C12,'Site Level Financials - ''23 ''24'!$C$2:$C$1577,'Site Level Financials - ''23 ''24'!S$2:S$1577) -> 23 | H12: =_xlfn.XLOOKUP($C12,'Site Level Financials - ''23 ''24'!$C$2:$C$1577,'Site Level Financials - ''23 ''24'!T$2:T$1577) -> 22 | I12: =_xlfn.XLOOKUP($C12,'Site Level Financials - ''23 ''24'!$C$2:$C$1577,'Site Level Financials - ''23 ''24'!U$2:U$1577) -> 22 | J12: =_xlfn.XLOOKUP($C12,'Site Level Financials - ''23 ''24'!$C$2:$C$1577,'Site Level Financials - ''23 ''24'!V$2:V$1577) -> 22 | K12: =_xlfn.XLOOKUP($C12,'Site Level Financials - ''23 ''24'!$C$2:$C$1577,'Site Level Financials - ''23 ''24'!W$2:W$1577) -> 24 | L12: =_xlfn.XLOOKUP($C12,'Site Level Financials - ''23 ''24'!$C$2:$C$1577,'Site Level Financials - ''23 ''24'!X$2:X$1577) -> 21 | M12: =_xlfn.XLOOKUP($C12,'Site Level Financials - ''23 ''24'!$C$2:$C$1577,'Site Level Financials - ''23 ''24'!Y$2:Y$1577) -> 23 | N12: =_xlfn.XLOOKUP($C12,'Site Level Financials - ''23 ''24'!$C$2:$C$1577,'Site Level Financials - ''23 ''24'!Z$2:Z$1577) -> 23 | ... R12: =_xlfn.XLOOKUP($C12,'Site Level Financials - ''23 ''24'!$C$2:$C$1577,'Site Level Financials - ''23 ''24'!AD$2:AD$1577) -> 22 | S12: =NETWORKDAYS(R9,S9) -> 23 | T12: =NETWORKDAYS(S9,T9) -> 22 | U12: =NETWORKDAYS(T9,U9) -> 22 | V12: =NETWORKDAYS(U9,V9) -> 22 | W12: =NETWORKDAYS(V9,W9) -> 24 | X12: =NETWORKDAYS(W9,X9) -> 21 | Y12: =NETWORKDAYS(X9,Y9) -> 23 | Z12: =NETWORKDAYS(Y9,Z9) -> 23 | ... AD12: =NETWORKDAYS(AC9,AD9) -> 22 | AF12: =_xlfn.XLOOKUP($C12,'Site Level Financials - ''23 ''24'!$C$2:$C$1577,'Site Level Financials - ''23 ''24'!$AF$2:$AF$1577) -> 269 | AG12: =SUM(G12:R12) -> 269 | AH12: =SUM(S12:AD12) -> 269
B13: =G5 -> 1 | C13: =B13&" - "&F13 -> 1 - Total Vet Days | F13: Total Vet Days | G13: =_xlfn.XLOOKUP($C13,'Site Level Financials - ''23 ''24'!$C$2:$C$1577,'Site Level Financials - ''23 ''24'!S$2:S$1577) -> 92 | H13: =_xlfn.XLOOKUP($C13,'Site Level Financials - ''23 ''24'!$C$2:$C$1577,'Site Level Financials - ''23 ''24'!T$2:T$1577) -> 88 | I13: =_xlfn.XLOOKUP($C13,'Site Level Financials - ''23 ''24'!$C$2:$C$1577,'Site Level Financials - ''23 ''24'!U$2:U$1577) -> 88 | J13: =_xlfn.XLOOKUP($C13,'Site Level Financials - ''23 ''24'!$C$2:$C$1577,'Site Level Financials - ''23 ''24'!V$2:V$1577) -> 66 | K13: =_xlfn.XLOOKUP($C13,'Site Level Financials - ''23 ''24'!$C$2:$C$1577,'Site Level Financials - ''23 ''24'!W$2:W$1577) -> 72 | L13: =_xlfn.XLOOKUP($C13,'Site Level Financials - ''23 ''24'!$C$2:$C$1577,'Site Level Financials - ''23 ''24'!X$2:X$1577) -> 84 | M13: =_xlfn.XLOOKUP($C13,'Site Level Financials - ''23 ''24'!$C$2:$C$1577,'Site Level Financials - ''23 ''24'!Y$2:Y$1577) -> 92 | N13: =_xlfn.XLOOKUP($C13,'Site Level Financials - ''23 ''24'!$C$2:$C$1577,'Site Level Financials - ''23 ''24'!Z$2:Z$1577) -> 115 | ... R13: =_xlfn.XLOOKUP($C13,'Site Level Financials - ''23 ''24'!$C$2:$C$1577,'Site Level Financials - ''23 ''24'!AD$2:AD$1577) -> 88 | S13: =S11*S12 -> 92 | T13: =T11*T12 -> 88 | U13: =U11*U12 -> 88 | V13: =V11*V12 -> 88 | W13: =W11*W12 -> 96 | X13: =X11*X12 -> 84 | Y13: =Y11*Y12 -> 92 | Z13: =Z11*Z12 -> 92 | ... AD13: =AD11*AD12 -> 88 | AF13: =_xlfn.XLOOKUP($C13,'Site Level Financials - ''23 ''24'!$C$2:$C$1577,'Site Level Financials - ''23 ''24'!$AF$2:$AF$1577) -> 1234 | AG13: =SUM(G13:R13) -> 1120 | AH13: =SUM(S13:AD13) -> 1076
B14: =G5 -> 1 | C14: =B14&" - "&F14 -> 1 - Production per Vet Workday | F14: Production per Vet Workday | G14: =_xlfn.XLOOKUP($C14,'Site Level Financials - ''23 ''24'!$C$2:$C$1577,'Site Level Financials - ''23 ''24'!S$2:S$1577) -> 4.7371343 | H14: =_xlfn.XLOOKUP($C14,'Site Level Financials - ''23 ''24'!$C$2:$C$1577,'Site Level Financials - ''23 ''24'!T$2:T$1577) -> 4.8160244 | I14: =_xlfn.XLOOKUP($C14,'Site Level Financials - ''23 ''24'!$C$2:$C$1577,'Site Level Financials - ''23 ''24'!U$2:U$1577) -> 5.1871468 | J14: =_xlfn.XLOOKUP($C14,'Site Level Financials - ''23 ''24'!$C$2:$C$1577,'Site Level Financials - ''23 ''24'!V$2:V$1577) -> 5.924964 | K14: =_xlfn.XLOOKUP($C14,'Site Level Financials - ''23 ''24'!$C$2:$C$1577,'Site Level Financials - ''23 ''24'!W$2:W$1577) -> 5.7445992 | L14: =_xlfn.XLOOKUP($C14,'Site Level Financials - ''23 ''24'!$C$2:$C$1577,'Site Level Financials - ''23 ''24'!X$2:X$1577) -> 4.9005212 | M14: =_xlfn.XLOOKUP($C14,'Site Level Financials - ''23 ''24'!$C$2:$C$1577,'Site Level Financials - ''23 ''24'!Y$2:Y$1577) -> 4.7825476 | N14: =_xlfn.XLOOKUP($C14,'Site Level Financials - ''23 ''24'!$C$2:$C$1577,'Site Level Financials - ''23 ''24'!Z$2:Z$1577) -> 4.1464776 | ... R14: =_xlfn.XLOOKUP($C14,'Site Level Financials - ''23 ''24'!$C$2:$C$1577,'Site Level Financials - ''23 ''24'!AD$2:AD$1577) -> 2.6331003 | S14: =R14*(1+_xlfn.XLOOKUP($R11,'Budget Assumption Driver'!$A$15:$A$19,'Budget Assumption Driver'!E$15:E$19)) -> 3.7253334 | T14: =S14*(1+_xlfn.XLOOKUP($R11,'Budget Assumption Driver'!$A$15:$A$19,'Budget Assumption Driver'!F$15:F$19)) -> 4.0328449 | U14: =T14*(1+_xlfn.XLOOKUP($R11,'Budget Assumption Driver'!$A$15:$A$19,'Budget Assumption Driver'!G$15:G$19)) -> 4.3304254 | V14: =U14*(1+_xlfn.XLOOKUP($R11,'Budget Assumption Driver'!$A$15:$A$19,'Budget Assumption Driver'!H$15:H$19)) -> 4.6385852 | W14: =V14*(1+_xlfn.XLOOKUP($R11,'Budget Assumption Driver'!$A$15:$A$19,'Budget Assumption Driver'!I$15:I$19)) -> 5.0535949 | X14: =W14*(1+_xlfn.XLOOKUP($R11,'Budget Assumption Driver'!$A$15:$A$19,'Budget Assumption Driver'!J$15:J$19)) -> 4.85 | Y14: =X14*(1+_xlfn.XLOOKUP($R11,'Budget Assumption Driver'!$A$15:$A$19,'Budget Assumption Driver'!K$15:K$19)) -> 4.4611945 | Z14: =Y14*(1+_xlfn.XLOOKUP($R11,'Budget Assumption Driver'!$A$15:$A$19,'Budget Assumption Driver'!L$15:L$19)) -> 3.8254334 | ... AD14: =AC14*(1+_xlfn.XLOOKUP($R11,'Budget Assumption Driver'!$A$15:$A$19,'Budget Assumption Driver'!P$15:P$19)) -> 2.7170291 | AF14: =_xlfn.XLOOKUP($C14,'Site Level Financials - ''23 ''24'!$C$2:$C$1577,'Site Level Financials - ''23 ''24'!$AF$2:$AF$1577) -> 4.4853101 | AG14: =AG15/AG13 -> 4.4622702 | AH14: =AH15/AH13 -> 4.0586445
B15: =G5 -> 1 | C15: =B15&" - "&F15 -> 1 - Total Production | F15: Total Production | G15: =_xlfn.XLOOKUP($C15,'Site Level Financials - ''23 ''24'!$C$2:$C$1577,'Site Level Financials - ''23 ''24'!S$2:S$1577) -> 435.81635 | H15: =_xlfn.XLOOKUP($C15,'Site Level Financials - ''23 ''24'!$C$2:$C$1577,'Site Level Financials - ''23 ''24'!T$2:T$1577) -> 423.81015 | I15: =_xlfn.XLOOKUP($C15,'Site Level Financials - ''23 ''24'!$C$2:$C$1577,'Site Level Financials - ''23 ''24'!U$2:U$1577) -> 456.46892 | J15: =_xlfn.XLOOKUP($C15,'Site Level Financials - ''23 ''24'!$C$2:$C$1577,'Site Level Financials - ''23 ''24'!V$2:V$1577) -> 391.04763 | K15: =_xlfn.XLOOKUP($C15,'Site Level Financials - ''23 ''24'!$C$2:$C$1577,'Site Level Financials - ''23 ''24'!W$2:W$1577) -> 413.61114 | L15: =_xlfn.XLOOKUP($C15,'Site Level Financials - ''23 ''24'!$C$2:$C$1577,'Site Level Financials - ''23 ''24'!X$2:X$1577) -> 411.64378 | M15: =_xlfn.XLOOKUP($C15,'Site Level Financials - ''23 ''24'!$C$2:$C$1577,'Site Level Financials - ''23 ''24'!Y$2:Y$1577) -> 439.99438 | N15: =_xlfn.XLOOKUP($C15,'Site Level Financials - ''23 ''24'!$C$2:$C$1577,'Site Level Financials - ''23 ''24'!Z$2:Z$1577) -> 476.84493 | ... R15: =_xlfn.XLOOKUP($C15,'Site Level Financials - ''23 ''24'!$C$2:$C$1577,'Site Level Financials - ''23 ''24'!AD$2:AD$1577) -> 231.71283 | S15: =S14*S13 -> 342.73067 | T15: =T14*T13 -> 354.89035 | U15: =U14*U13 -> 381.07744 | V15: =V14*V13 -> 408.19549 | W15: =W14*W13 -> 485.14511 | X15: =X14*X13 -> 407.4 | Y15: =Y14*Y13 -> 410.4299 | Z15: =Z14*Z13 -> 351.93987 | ... AD15: =AD14*AD13 -> 239.09856 | AF15: =_xlfn.XLOOKUP($C15,'Site Level Financials - ''23 ''24'!$C$2:$C$1577,'Site Level Financials - ''23 ''24'!$AF$2:$AF$1577) -> 5534.8727 | AG15: =SUM(G15:R15) -> 4997.7427 | AH15: =SUM(S15:AD15) -> 4367.1014
B16: =G5 -> 1 | C16: =B16&" - "&F16 -> 1 - Revenue as a % of Production | F16: Revenue as a % of Production | G16: =_xlfn.XLOOKUP($C16,'Site Level Financials - ''23 ''24'!$C$2:$C$1577,'Site Level Financials - ''23 ''24'!S$2:S$1577) -> 0.97856317 | H16: =_xlfn.XLOOKUP($C16,'Site Level Financials - ''23 ''24'!$C$2:$C$1577,'Site Level Financials - ''23 ''24'!T$2:T$1577) -> 0.97856317 | I16: =_xlfn.XLOOKUP($C16,'Site Level Financials - ''23 ''24'!$C$2:$C$1577,'Site Level Financials - ''23 ''24'!U$2:U$1577) -> 0.97856317 | J16: =_xlfn.XLOOKUP($C16,'Site Level Financials - ''23 ''24'!$C$2:$C$1577,'Site Level Financials - ''23 ''24'!V$2:V$1577) -> 0.97856317 | K16: =_xlfn.XLOOKUP($C16,'Site Level Financials - ''23 ''24'!$C$2:$C$1577,'Site Level Financials - ''23 ''24'!W$2:W$1577) -> 0.97856317 | L16: =_xlfn.XLOOKUP($C16,'Site Level Financials - ''23 ''24'!$C$2:$C$1577,'Site Level Financials - ''23 ''24'!X$2:X$1577) -> 0.97856317 | M16: =_xlfn.XLOOKUP($C16,'Site Level Financials - ''23 ''24'!$C$2:$C$1577,'Site Level Financials - ''23 ''24'!Y$2:Y$1577) -> 0.97856317 | N16: =_xlfn.XLOOKUP($C16,'Site Level Financials - ''23 ''24'!$C$2:$C$1577,'Site Level Financials - ''23 ''24'!Z$2:Z$1577) -> 0.97856317 | ... R16: =_xlfn.XLOOKUP($C16,'Site Level Financials - ''23 ''24'!$C$2:$C$1577,'Site Level Financials - ''23 ''24'!AD$2:AD$1577) -> 0.97856317 | S16: =SUM(G45:R45)/SUM(G15:R15) -> 0.98241067 | T16: =S16 -> 0.98241067 | U16: =T16 -> 0.98241067 | V16: =U16 -> 0.98241067 | W16: =V16 -> 0.98241067 | X16: =W16 -> 0.98241067 | Y16: =X16 -> 0.98241067 | Z16: =Y16 -> 0.98241067 | AA16: =Z16 -> 0.98241067 | ... AD16: =AC16 -> 0.98241067 | AF16: =_xlfn.XLOOKUP($C16,'Site Level Financials - ''23 ''24'!$C$2:$C$1577,'Site Level Financials - ''23 ''24'!$AF$2:$AF$1577) -> 0.98364296 | AG16: =AG17/AG15 -> 0.97856317 | AH16: =AH17/AH15 -> 0.98241067
B17: =G5 -> 1 | C17: =B17&" - "&F17 -> 1 - Total Revenue | F17: Total Revenue | G17: =_xlfn.XLOOKUP($C17,'Site Level Financials - ''23 ''24'!$C$2:$C$1577,'Site Level Financials - ''23 ''24'!S$2:S$1577) -> 426.47384 | H17: =_xlfn.XLOOKUP($C17,'Site Level Financials - ''23 ''24'!$C$2:$C$1577,'Site Level Financials - ''23 ''24'!T$2:T$1577) -> 414.725 | I17: =_xlfn.XLOOKUP($C17,'Site Level Financials - ''23 ''24'!$C$2:$C$1577,'Site Level Financials - ''23 ''24'!U$2:U$1577) -> 446.68367 | J17: =_xlfn.XLOOKUP($C17,'Site Level Financials - ''23 ''24'!$C$2:$C$1577,'Site Level Financials - ''23 ''24'!V$2:V$1577) -> 382.66481 | K17: =_xlfn.XLOOKUP($C17,'Site Level Financials - ''23 ''24'!$C$2:$C$1577,'Site Level Financials - ''23 ''24'!W$2:W$1577) -> 404.74463 | L17: =_xlfn.XLOOKUP($C17,'Site Level Financials - ''23 ''24'!$C$2:$C$1577,'Site Level Financials - ''23 ''24'!X$2:X$1577) -> 402.81944 | M17: =_xlfn.XLOOKUP($C17,'Site Level Financials - ''23 ''24'!$C$2:$C$1577,'Site Level Financials - ''23 ''24'!Y$2:Y$1577) -> 430.56229 | N17: =_xlfn.XLOOKUP($C17,'Site Level Financials - ''23 ''24'!$C$2:$C$1577,'Site Level Financials - ''23 ''24'!Z$2:Z$1577) -> 466.62288 | ... R17: =_xlfn.XLOOKUP($C17,'Site Level Financials - ''23 ''24'!$C$2:$C$1577,'Site Level Financials - ''23 ''24'!AD$2:AD$1577) -> 226.74564 | S17: =S16*S15 -> 336.70227 | T17: =T16*T15 -> 348.64807 | U17: =U16*U15 -> 374.37454 | V17: =V16*V15 -> 401.01561 | W17: =W16*W15 -> 476.61174 | X17: =X16*X15 -> 400.23411 | Y17: =Y16*Y15 -> 403.21071 | Z17: =Z16*Z15 -> 345.74949 | ... AD17: =AD16*AD15 -> 234.89298 | AF17: =_xlfn.XLOOKUP($C17,'Site Level Financials - ''23 ''24'!$C$2:$C$1577,'Site Level Financials - ''23 ''24'!$AF$2:$AF$1577) -> 5444.3385 | AG17: =SUM(G17:R17) -> 4890.6069 | AH17: =SUM(S17:AD17) -> 4290.2871
B18: =G5 -> 1 | C18: =B18&" - "&F18 -> 1 - % YoY Revenue Growth | F18: % YoY Revenue Growth | G18: =_xlfn.XLOOKUP($C18,'Site Level Financials - ''23 ''24'!$C$2:$C$1577,'Site Level Financials - ''23 ''24'!S$2:S$1577) -> 0.1491425 | H18: =_xlfn.XLOOKUP($C18,'Site Level Financials - ''23 ''24'!$C$2:$C$1577,'Site Level Financials - ''23 ''24'!T$2:T$1577) -> 0.10233061 | I18: =_xlfn.XLOOKUP($C18,'Site Level Financials - ''23 ''24'!$C$2:$C$1577,'Site Level Financials - ''23 ''24'!U$2:U$1577) -> -0.052123494 | J18: =_xlfn.XLOOKUP($C18,'Site Level Financials - ''23 ''24'!$C$2:$C$1577,'Site Level Financials - ''23 ''24'!V$2:V$1577) -> -0.12381794 | K18: =_xlfn.XLOOKUP($C18,'Site Level Financials - ''23 ''24'!$C$2:$C$1577,'Site Level Financials - ''23 ''24'!W$2:W$1577) -> -0.19976752 | L18: =_xlfn.XLOOKUP($C18,'Site Level Financials - ''23 ''24'!$C$2:$C$1577,'Site Level Financials - ''23 ''24'!X$2:X$1577) -> -0.26992859 | M18: =_xlfn.XLOOKUP($C18,'Site Level Financials - ''23 ''24'!$C$2:$C$1577,'Site Level Financials - ''23 ''24'!Y$2:Y$1577) -> -0.13356457 | N18: =_xlfn.XLOOKUP($C18,'Site Level Financials - ''23 ''24'!$C$2:$C$1577,'Site Level Financials - ''23 ''24'!Z$2:Z$1577) -> -0.055032549 | ... R18: =_xlfn.XLOOKUP($C18,'Site Level Financials - ''23 ''24'!$C$2:$C$1577,'Site Level Financials - ''23 ''24'!AD$2:AD$1577) -> -0.37244173 | S18: =S17/G17-1 -> -0.21049724 | T18: =T17/H17-1 -> -0.15932711 | U18: =U17/I17-1 -> -0.16187995 | V18: =V17/J17-1 -> 0.047955296 | W18: =W17/K17-1 -> 0.17756161 | X18: =X17/L17-1 -> -0.0064180983 | Y18: =Y17/M17-1 -> -0.063525261 | Z18: =Z17/N17-1 -> -0.25903872 | ... AD18: =AD17/R17-1 -> 0.035931629 | AG18: =AG17/AF17-1 -> -0.10170778 | AH18: =AH17/AG17-1 -> -0.12274956
B19: =G5 -> 1 | C19: =B19&" - "&F19 -> 1 -
B20: =G5 -> 1 | C20: =B20&" - "&F20 -> 1 - Doctor Compensation | F20: Doctor Compensation | G20: =_xlfn.XLOOKUP($C20,'Site Level Financials - ''23 ''24'!$C$2:$C$1577,'Site Level Financials - ''23 ''24'!S$2:S$1577) -> -135.6734 | H20: =_xlfn.XLOOKUP($C20,'Site Level Financials - ''23 ''24'!$C$2:$C$1577,'Site Level Financials - ''23 ''24'!T$2:T$1577) -> -136.66238 | I20: =_xlfn.XLOOKUP($C20,'Site Level Financials - ''23 ''24'!$C$2:$C$1577,'Site Level Financials - ''23 ''24'!U$2:U$1577) -> -156.48908 | J20: =_xlfn.XLOOKUP($C20,'Site Level Financials - ''23 ''24'!$C$2:$C$1577,'Site Level Financials - ''23 ''24'!V$2:V$1577) -> -166.13691 | K20: =_xlfn.XLOOKUP($C20,'Site Level Financials - ''23 ''24'!$C$2:$C$1577,'Site Level Financials - ''23 ''24'!W$2:W$1577) -> -184.63856 | L20: =_xlfn.XLOOKUP($C20,'Site Level Financials - ''23 ''24'!$C$2:$C$1577,'Site Level Financials - ''23 ''24'!X$2:X$1577) -> -143.79696 | M20: =_xlfn.XLOOKUP($C20,'Site Level Financials - ''23 ''24'!$C$2:$C$1577,'Site Level Financials - ''23 ''24'!Y$2:Y$1577) -> -155.96362 | N20: =_xlfn.XLOOKUP($C20,'Site Level Financials - ''23 ''24'!$C$2:$C$1577,'Site Level Financials - ''23 ''24'!Z$2:Z$1577) -> -129.38144 | ... R20: =_xlfn.XLOOKUP($C20,'Site Level Financials - ''23 ''24'!$C$2:$C$1577,'Site Level Financials - ''23 ''24'!AD$2:AD$1577) -> -90.458233 | S20: =S21*S17 -> -107.11453 | T20: =T21*T17 -> -114.88836 | U20: =U21*U17 -> -131.15663 | V20: =V21*V17 -> -174.10406 | W20: =W21*W17 -> -217.42328 | X20: =X21*X17 -> -142.87406 | Y20: =Y21*Y17 -> -146.05599 | Z20: =Z21*Z17 -> -95.86664 | ... AD20: =AD21*AD17 -> -93.708545 | AF20: =_xlfn.XLOOKUP($C20,'Site Level Financials - ''23 ''24'!$C$2:$C$1577,'Site Level Financials - ''23 ''24'!$AF$2:$AF$1577) -> -1670.3808 | AG20: =SUM(G20:R20) -> -1685.0007 | AH20: =SUM(S20:AD20) -> -1513.3054
B21: =G5 -> 1 | C21: =B21&" - "&F21 -> 1 - % of Revenue - Doctor Compensation | F21: ="% of Revenue - "&F20 -> % of Revenue - Doctor Compensation | G21: =G20/G17 -> -0.31812832 | H21: =H20/H17 -> -0.32952531 | I21: =I20/I17 -> -0.35033535 | J21: =J20/J17 -> -0.43415781 | K21: =K20/K17 -> -0.45618532 | L21: =L20/L17 -> -0.35697623 | M21: =M20/M17 -> -0.36223242 | N21: =N20/N17 -> -0.27727196 | ... R21: =R20/R17 -> -0.39894144 | S21: =_xlfn.XLOOKUP($F21,'Budget Assumption Driver'!$A$33:$A$39,'Budget Assumption Driver'!E$33:E$39)+G21 -> -0.31812832 | T21: =_xlfn.XLOOKUP($F21,'Budget Assumption Driver'!$A$33:$A$39,'Budget Assumption Driver'!F$33:F$39)+H21 -> -0.32952531 | U21: =_xlfn.XLOOKUP($F21,'Budget Assumption Driver'!$A$33:$A$39,'Budget Assumption Driver'!G$33:G$39)+I21 -> -0.35033535 | V21: =_xlfn.XLOOKUP($F21,'Budget Assumption Driver'!$A$33:$A$39,'Budget Assumption Driver'!H$33:H$39)+J21 -> -0.43415781 | W21: =_xlfn.XLOOKUP($F21,'Budget Assumption Driver'!$A$33:$A$39,'Budget Assumption Driver'!I$33:I$39)+K21 -> -0.45618532 | X21: =_xlfn.XLOOKUP($F21,'Budget Assumption Driver'!$A$33:$A$39,'Budget Assumption Driver'!J$33:J$39)+L21 -> -0.35697623 | Y21: =_xlfn.XLOOKUP($F21,'Budget Assumption Driver'!$A$33:$A$39,'Budget Assumption Driver'!K$33:K$39)+M21 -> -0.36223242 | Z21: =_xlfn.XLOOKUP($F21,'Budget Assumption Driver'!$A$33:$A$39,'Budget Assumption Driver'!L$33:L$39)+N21 -> -0.27727196 | ... AD21: =_xlfn.XLOOKUP($F21,'Budget Assumption Driver'!$A$33:$A$39,'Budget Assumption Driver'!P$33:P$39)+R21 -> -0.39894144 | AF21: =_xlfn.XLOOKUP($C21,'Site Level Financials - ''23 ''24'!$C$2:$C$1577,'Site Level Financials - ''23 ''24'!$AF$2:$AF$1577) -> -0.30681061 | AG21: =AG20/AG17 -> -0.34453816 | AH21: =AH20/AH17 -> -0.35272824
B22: =G5 -> 1 | C22: =B22&" - "&F22 -> 1 -
B23: =G5 -> 1 | C23: =B23&" - "&F23 -> 1 - Administrative Staff Compensation | F23: Administrative Staff Compensation | G23: =_xlfn.XLOOKUP($C23,'Site Level Financials - ''23 ''24'!$C$2:$C$1577,'Site Level Financials - ''23 ''24'!S$2:S$1577) -> -71.662216 | H23: =_xlfn.XLOOKUP($C23,'Site Level Financials - ''23 ''24'!$C$2:$C$1577,'Site Level Financials - ''23 ''24'!T$2:T$1577) -> -70.741312 | I23: =_xlfn.XLOOKUP($C23,'Site Level Financials - ''23 ''24'!$C$2:$C$1577,'Site Level Financials - ''23 ''24'!U$2:U$1577) -> -83.643635 | J23: =_xlfn.XLOOKUP($C23,'Site Level Financials - ''23 ''24'!$C$2:$C$1577,'Site Level Financials - ''23 ''24'!V$2:V$1577) -> -93.399864 | K23: =_xlfn.XLOOKUP($C23,'Site Level Financials - ''23 ''24'!$C$2:$C$1577,'Site Level Financials - ''23 ''24'!W$2:W$1577) -> -99.535279 | L23: =_xlfn.XLOOKUP($C23,'Site Level Financials - ''23 ''24'!$C$2:$C$1577,'Site Level Financials - ''23 ''24'!X$2:X$1577) -> -79.219325 | M23: =_xlfn.XLOOKUP($C23,'Site Level Financials - ''23 ''24'!$C$2:$C$1577,'Site Level Financials - ''23 ''24'!Y$2:Y$1577) -> -90.295169 | N23: =_xlfn.XLOOKUP($C23,'Site Level Financials - ''23 ''24'!$C$2:$C$1577,'Site Level Financials - ''23 ''24'!Z$2:Z$1577) -> -75.944163 | ... R23: =_xlfn.XLOOKUP($C23,'Site Level Financials - ''23 ''24'!$C$2:$C$1577,'Site Level Financials - ''23 ''24'!AD$2:AD$1577) -> -48.935851 | S23: =S24*S17 -> -56.577518 | T23: =T24*T17 -> -59.470303 | U23: =U24*U17 -> -70.103408 | V23: =V24*V17 -> -97.878882 | W23: =W24*W17 -> -117.20892 | X23: =X24*X17 -> -78.710888 | Y23: =Y24*Y17 -> -84.559144 | Z23: =Z24*Z17 -> -56.271684 | ... AD23: =AD24*AD17 -> -50.694196 | AF23: =_xlfn.XLOOKUP($C23,'Site Level Financials - ''23 ''24'!$C$2:$C$1577,'Site Level Financials - ''23 ''24'!$AF$2:$AF$1577) -> -910.83507 | AG23: =SUM(G23:R23) -> -940.97639 | AH23: =SUM(S23:AD23) -> -842.67723
B24: =G5 -> 1 | C24: =B24&" - "&F24 -> 1 - % of Revenue - Administrative Staff Compensation | F24: ="% of Revenue - "&F23 -> % of Revenue - Administrative Staff Compensation | G24: =G23/G17 -> -0.16803426 | H24: =H23/H17 -> -0.17057402 | I24: =I23/I17 -> -0.18725474 | J24: =J23/J17 -> -0.24407749 | K24: =K23/K17 -> -0.24592118 | L24: =L23/L17 -> -0.19666212 | M24: =M23/M17 -> -0.20971453 | N24: =N23/N17 -> -0.16275276 | ... R24: =R23/R17 -> -0.21581827 | S24: =_xlfn.XLOOKUP($F24,'Budget Assumption Driver'!$A$33:$A$39,'Budget Assumption Driver'!E$33:E$39)+G24 -> -0.16803426 | T24: =_xlfn.XLOOKUP($F24,'Budget Assumption Driver'!$A$33:$A$39,'Budget Assumption Driver'!F$33:F$39)+H24 -> -0.17057402 | U24: =_xlfn.XLOOKUP($F24,'Budget Assumption Driver'!$A$33:$A$39,'Budget Assumption Driver'!G$33:G$39)+I24 -> -0.18725474 | V24: =_xlfn.XLOOKUP($F24,'Budget Assumption Driver'!$A$33:$A$39,'Budget Assumption Driver'!H$33:H$39)+J24 -> -0.24407749 | W24: =_xlfn.XLOOKUP($F24,'Budget Assumption Driver'!$A$33:$A$39,'Budget Assumption Driver'!I$33:I$39)+K24 -> -0.24592118 | X24: =_xlfn.XLOOKUP($F24,'Budget Assumption Driver'!$A$33:$A$39,'Budget Assumption Driver'!J$33:J$39)+L24 -> -0.19666212 | Y24: =_xlfn.XLOOKUP($F24,'Budget Assumption Driver'!$A$33:$A$39,'Budget Assumption Driver'!K$33:K$39)+M24 -> -0.20971453 | Z24: =_xlfn.XLOOKUP($F24,'Budget Assumption Driver'!$A$33:$A$39,'Budget Assumption Driver'!L$33:L$39)+N24 -> -0.16275276 | ... AD24: =_xlfn.XLOOKUP($F24,'Budget Assumption Driver'!$A$33:$A$39,'Budget Assumption Driver'!P$33:P$39)+R24 -> -0.21581827 | AF24: =_xlfn.XLOOKUP($C24,'Site Level Financials - ''23 ''24'!$C$2:$C$1577,'Site Level Financials - ''23 ''24'!$AF$2:$AF$1577) -> -0.16729949 | AG24: =AG23/AG17 -> -0.19240483 | AH24: =AH23/AH17 -> -0.19641512
B25: =G5 -> 1 | C25: =B25&" - "&F25 -> 1 -
B26: =G5 -> 1 | C26: =B26&" - "&F26 -> 1 - Office Supplies | F26: Office Supplies | G26: =_xlfn.XLOOKUP($C26,'Site Level Financials - ''23 ''24'!$C$2:$C$1577,'Site Level Financials - ''23 ''24'!S$2:S$1577) -> -39.117157 | H26: =_xlfn.XLOOKUP($C26,'Site Level Financials - ''23 ''24'!$C$2:$C$1577,'Site Level Financials - ''23 ''24'!T$2:T$1577) -> -38.116146 | I26: =_xlfn.XLOOKUP($C26,'Site Level Financials - ''23 ''24'!$C$2:$C$1577,'Site Level Financials - ''23 ''24'!U$2:U$1577) -> -45.756335 | J26: =_xlfn.XLOOKUP($C26,'Site Level Financials - ''23 ''24'!$C$2:$C$1577,'Site Level Financials - ''23 ''24'!V$2:V$1577) -> -49.367419 | K26: =_xlfn.XLOOKUP($C26,'Site Level Financials - ''23 ''24'!$C$2:$C$1577,'Site Level Financials - ''23 ''24'!W$2:W$1577) -> -53.790408 | L26: =_xlfn.XLOOKUP($C26,'Site Level Financials - ''23 ''24'!$C$2:$C$1577,'Site Level Financials - ''23 ''24'!X$2:X$1577) -> -41.751224 | M26: =_xlfn.XLOOKUP($C26,'Site Level Financials - ''23 ''24'!$C$2:$C$1577,'Site Level Financials - ''23 ''24'!Y$2:Y$1577) -> -46.102047 | N26: =_xlfn.XLOOKUP($C26,'Site Level Financials - ''23 ''24'!$C$2:$C$1577,'Site Level Financials - ''23 ''24'!Z$2:Z$1577) -> -37.265389 | ... R26: =_xlfn.XLOOKUP($C26,'Site Level Financials - ''23 ''24'!$C$2:$C$1577,'Site Level Financials - ''23 ''24'!AD$2:AD$1577) -> -23.451874 | S26: =S27*S17 -> -30.883104 | T26: =T27*T17 -> -32.04321 | U26: =U27*U17 -> -38.349302 | V26: =V27*V17 -> -51.734848 | W26: =W27*W17 -> -63.341519 | X26: =X27*X17 -> -41.483261 | Y26: =Y27*Y17 -> -43.173403 | Z26: =Z27*Z17 -> -27.61221 | ... AD26: =AD27*AD17 -> -24.294538 | AF26: =_xlfn.XLOOKUP($C26,'Site Level Financials - ''23 ''24'!$C$2:$C$1577,'Site Level Financials - ''23 ''24'!$AF$2:$AF$1577) -> -432.22357 | AG26: =SUM(G26:R26) -> -476.06151 | AH26: =SUM(S26:AD26) -> -429.11233
B27: =G5 -> 1 | C27: =B27&" - "&F27 -> 1 - % of Revenue - Office Supplies | F27: ="% of Revenue - "&F26 -> % of Revenue - Office Supplies | G27: =G26/G17 -> -0.091722291 | H27: =H26/H17 -> -0.091907035 | I27: =I26/I17 -> -0.10243566 | J27: =J26/J17 -> -0.12900956 | K27: =K26/K17 -> -0.13289962 | L27: =L26/L17 -> -0.10364749 | M27: =M26/M17 -> -0.10707405 | N27: =N26/N17 -> -0.079861897 | ... R27: =R26/R17 -> -0.10342811 | S27: =_xlfn.XLOOKUP($F27,'Budget Assumption Driver'!$A$33:$A$39,'Budget Assumption Driver'!E$33:E$39)+G27 -> -0.091722291 | T27: =_xlfn.XLOOKUP($F27,'Budget Assumption Driver'!$A$33:$A$39,'Budget Assumption Driver'!F$33:F$39)+H27 -> -0.091907035 | U27: =_xlfn.XLOOKUP($F27,'Budget Assumption Driver'!$A$33:$A$39,'Budget Assumption Driver'!G$33:G$39)+I27 -> -0.10243566 | V27: =_xlfn.XLOOKUP($F27,'Budget Assumption Driver'!$A$33:$A$39,'Budget Assumption Driver'!H$33:H$39)+J27 -> -0.12900956 | W27: =_xlfn.XLOOKUP($F27,'Budget Assumption Driver'!$A$33:$A$39,'Budget Assumption Driver'!I$33:I$39)+K27 -> -0.13289962 | X27: =_xlfn.XLOOKUP($F27,'Budget Assumption Driver'!$A$33:$A$39,'Budget Assumption Driver'!J$33:J$39)+L27 -> -0.10364749 | Y27: =_xlfn.XLOOKUP($F27,'Budget Assumption Driver'!$A$33:$A$39,'Budget Assumption Driver'!K$33:K$39)+M27 -> -0.10707405 | Z27: =_xlfn.XLOOKUP($F27,'Budget Assumption Driver'!$A$33:$A$39,'Budget Assumption Driver'!L$33:L$39)+N27 -> -0.079861897 | ... AD27: =_xlfn.XLOOKUP($F27,'Budget Assumption Driver'!$A$33:$A$39,'Budget Assumption Driver'!P$33:P$39)+R27 -> -0.10342811 | AF27: =_xlfn.XLOOKUP($C27,'Site Level Financials - ''23 ''24'!$C$2:$C$1577,'Site Level Financials - ''23 ''24'!$AF$2:$AF$1577) -> -0.079389548 | AG27: =AG26/AG17 -> -0.09734201 | AH27: =AH26/AH17 -> -0.10001949
B28: =G5 -> 1 | C28: =B28&" - "&F28 -> 1 -
B29: =G5 -> 1 | C29: =B29&" - "&F29 -> 1 - Office Gross Profit | F29: Office Gross Profit | G29: =_xlfn.XLOOKUP($C29,'Site Level Financials - ''23 ''24'!$C$2:$C$1577,'Site Level Financials - ''23 ''24'!S$2:S$1577) -> 180.02106 | H29: =_xlfn.XLOOKUP($C29,'Site Level Financials - ''23 ''24'!$C$2:$C$1577,'Site Level Financials - ''23 ''24'!T$2:T$1577) -> 169.20516 | I29: =_xlfn.XLOOKUP($C29,'Site Level Financials - ''23 ''24'!$C$2:$C$1577,'Site Level Financials - ''23 ''24'!U$2:U$1577) -> 160.79462 | J29: =_xlfn.XLOOKUP($C29,'Site Level Financials - ''23 ''24'!$C$2:$C$1577,'Site Level Financials - ''23 ''24'!V$2:V$1577) -> 73.760609 | K29: =_xlfn.XLOOKUP($C29,'Site Level Financials - ''23 ''24'!$C$2:$C$1577,'Site Level Financials - ''23 ''24'!W$2:W$1577) -> 66.780386 | L29: =_xlfn.XLOOKUP($C29,'Site Level Financials - ''23 ''24'!$C$2:$C$1577,'Site Level Financials - ''23 ''24'!X$2:X$1577) -> 138.05193 | M29: =_xlfn.XLOOKUP($C29,'Site Level Financials - ''23 ''24'!$C$2:$C$1577,'Site Level Financials - ''23 ''24'!Y$2:Y$1577) -> 138.20146 | N29: =_xlfn.XLOOKUP($C29,'Site Level Financials - ''23 ''24'!$C$2:$C$1577,'Site Level Financials - ''23 ''24'!Z$2:Z$1577) -> 224.03189 | ... R29: =_xlfn.XLOOKUP($C29,'Site Level Financials - ''23 ''24'!$C$2:$C$1577,'Site Level Financials - ''23 ''24'!AD$2:AD$1577) -> 63.899683 | S29: =S17+S20+S23+S26 -> 142.12712 | T29: =T17+T20+T23+T26 -> 142.24619 | U29: =U17+U20+U23+U26 -> 134.7652 | V29: =V17+V20+V23+V26 -> 77.297821 | W29: =W17+W20+W23+W26 -> 78.638018 | X29: =X17+X20+X23+X26 -> 137.1659 | Y29: =Y17+Y20+Y23+Y26 -> 129.42217 | Z29: =Z17+Z20+Z23+Z26 -> 165.99895 | ... AD29: =AD17+AD20+AD23+AD26 -> 66.195703 | AF29: =_xlfn.XLOOKUP($C29,'Site Level Financials - ''23 ''24'!$C$2:$C$1577,'Site Level Financials - ''23 ''24'!$AF$2:$AF$1577) -> 2430.899 | AG29: =SUM(G29:R29) -> 1788.5683 | AH29: =SUM(S29:AD29) -> 1505.1921
B30: =G5 -> 1 | C30: =B30&" - "&F30 -> 1 - % of Revenue - Office Gross Profit | F30: ="% of Revenue - "&F29 -> % of Revenue - Office Gross Profit | G30: =G29/G17 -> 0.42211513 | H30: =H29/H17 -> 0.40799363 | I30: =I29/I17 -> 0.35997426 | J30: =J29/J17 -> 0.19275514 | K30: =K29/K17 -> 0.16499388 | L30: =L29/L17 -> 0.34271417 | M30: =M29/M17 -> 0.32097901 | N30: =N29/N17 -> 0.48011338 | ... AD30: =AD29/AD17 -> 0.28181218 | AF30: =_xlfn.XLOOKUP($C30,'Site Level Financials - ''23 ''24'!$C$2:$C$1577,'Site Level Financials - ''23 ''24'!$AF$2:$AF$1577) -> 0.44650035 | AG30: =AG29/AG17 -> 0.365715 | AH30: =AH29/AH17 -> 0.35083715
B31: =G5 -> 1 | C31: =B31&" - "&F31 -> 1 -
B32: =G5 -> 1 | C32: =B32&" - "&F32 -> 1 - General and Administrative Expense | F32: General and Administrative Expense | G32: =_xlfn.XLOOKUP($C32,'Site Level Financials - ''23 ''24'!$C$2:$C$1577,'Site Level Financials - ''23 ''24'!S$2:S$1577) -> -26.153612 | H32: =_xlfn.XLOOKUP($C32,'Site Level Financials - ''23 ''24'!$C$2:$C$1577,'Site Level Financials - ''23 ''24'!T$2:T$1577) -> -26.879657 | I32: =_xlfn.XLOOKUP($C32,'Site Level Financials - ''23 ''24'!$C$2:$C$1577,'Site Level Financials - ''23 ''24'!U$2:U$1577) -> -31.963288 | J32: =_xlfn.XLOOKUP($C32,'Site Level Financials - ''23 ''24'!$C$2:$C$1577,'Site Level Financials - ''23 ''24'!V$2:V$1577) -> -33.530066 | K32: =_xlfn.XLOOKUP($C32,'Site Level Financials - ''23 ''24'!$C$2:$C$1577,'Site Level Financials - ''23 ''24'!W$2:W$1577) -> -39.912042 | L32: =_xlfn.XLOOKUP($C32,'Site Level Financials - ''23 ''24'!$C$2:$C$1577,'Site Level Financials - ''23 ''24'!X$2:X$1577) -> -31.063624 | M32: =_xlfn.XLOOKUP($C32,'Site Level Financials - ''23 ''24'!$C$2:$C$1577,'Site Level Financials - ''23 ''24'!Y$2:Y$1577) -> -36.377022 | N32: =_xlfn.XLOOKUP($C32,'Site Level Financials - ''23 ''24'!$C$2:$C$1577,'Site Level Financials - ''23 ''24'!Z$2:Z$1577) -> -29.210481 | ... R32: =_xlfn.XLOOKUP($C32,'Site Level Financials - ''23 ''24'!$C$2:$C$1577,'Site Level Financials - ''23 ''24'!AD$2:AD$1577) -> -17.606031 | S32: =S33*S17 -> -20.648349 | T32: =T33*T17 -> -22.596999 | U32: =U33*U17 -> -26.789072 | V32: =V33*V17 -> -35.13801 | W32: =W33*W17 -> -46.998889 | X32: =X33*X17 -> -30.864255 | Y32: =Y33*Y17 -> -34.066162 | Z32: =Z33*Z17 -> -21.643835 | ... AD32: =AD33*AD17 -> -18.238645 | AF32: =_xlfn.XLOOKUP($C32,'Site Level Financials - ''23 ''24'!$C$2:$C$1577,'Site Level Financials - ''23 ''24'!$AF$2:$AF$1577) -> -334.52874 | AG32: =SUM(G32:R32) -> -356.07038 | AH32: =SUM(S32:AD32) -> -319.68133
B33: =G5 -> 1 | C33: =B33&" - "&F33 -> 1 - % of Revenue - General and Administrative Expense | F33: ="% of Revenue - "&F32 -> % of Revenue - General and Administrative Expense | G33: =G32/G17 -> -0.061325244 | H33: =H32/H17 -> -0.064813205 | I33: =I32/I17 -> -0.071556875 | J33: =J32/J17 -> -0.08762255 | K33: =K32/K17 -> -0.09861043 | L33: =L32/L17 -> -0.077115503 | M33: =M32/M17 -> -0.084487245 | N33: =N32/N17 -> -0.062599761 | ... R33: =R32/R17 -> -0.077646614 | S33: =_xlfn.XLOOKUP($F33,'Budget Assumption Driver'!$A$33:$A$39,'Budget Assumption Driver'!E$33:E$39)+G33 -> -0.061325244 | T33: =_xlfn.XLOOKUP($F33,'Budget Assumption Driver'!$A$33:$A$39,'Budget Assumption Driver'!F$33:F$39)+H33 -> -0.064813205 | U33: =_xlfn.XLOOKUP($F33,'Budget Assumption Driver'!$A$33:$A$39,'Budget Assumption Driver'!G$33:G$39)+I33 -> -0.071556875 | V33: =_xlfn.XLOOKUP($F33,'Budget Assumption Driver'!$A$33:$A$39,'Budget Assumption Driver'!H$33:H$39)+J33 -> -0.08762255 | W33: =_xlfn.XLOOKUP($F33,'Budget Assumption Driver'!$A$33:$A$39,'Budget Assumption Driver'!I$33:I$39)+K33 -> -0.09861043 | X33: =_xlfn.XLOOKUP($F33,'Budget Assumption Driver'!$A$33:$A$39,'Budget Assumption Driver'!J$33:J$39)+L33 -> -0.077115503 | Y33: =_xlfn.XLOOKUP($F33,'Budget Assumption Driver'!$A$33:$A$39,'Budget Assumption Driver'!K$33:K$39)+M33 -> -0.084487245 | Z33: =_xlfn.XLOOKUP($F33,'Budget Assumption Driver'!$A$33:$A$39,'Budget Assumption Driver'!L$33:L$39)+N33 -> -0.062599761 | ... AD33: =_xlfn.XLOOKUP($F33,'Budget Assumption Driver'!$A$33:$A$39,'Budget Assumption Driver'!P$33:P$39)+R33 -> -0.077646614 | AF33: =_xlfn.XLOOKUP($C33,'Site Level Financials - ''23 ''24'!$C$2:$C$1577,'Site Level Financials - ''23 ''24'!$AF$2:$AF$1577) -> -0.061445249 | AG33: =AG32/AG17 -> -0.072806992 | AH33: =AH32/AH17 -> -0.074512806
B34: =G5 -> 1 | C34: =B34&" - "&F34 -> 1 -
B35: =G5 -> 1 | C35: =B35&" - "&F35 -> 1 - Marketing | F35: Marketing | G35: =_xlfn.XLOOKUP($C35,'Site Level Financials - ''23 ''24'!$C$2:$C$1577,'Site Level Financials - ''23 ''24'!S$2:S$1577) -> -22.508831 | H35: =_xlfn.XLOOKUP($C35,'Site Level Financials - ''23 ''24'!$C$2:$C$1577,'Site Level Financials - ''23 ''24'!T$2:T$1577) -> -23.552364 | I35: =_xlfn.XLOOKUP($C35,'Site Level Financials - ''23 ''24'!$C$2:$C$1577,'Site Level Financials - ''23 ''24'!U$2:U$1577) -> -28.326141 | J35: =_xlfn.XLOOKUP($C35,'Site Level Financials - ''23 ''24'!$C$2:$C$1577,'Site Level Financials - ''23 ''24'!V$2:V$1577) -> -30.584046 | K35: =_xlfn.XLOOKUP($C35,'Site Level Financials - ''23 ''24'!$C$2:$C$1577,'Site Level Financials - ''23 ''24'!W$2:W$1577) -> -33.584182 | L35: =_xlfn.XLOOKUP($C35,'Site Level Financials - ''23 ''24'!$C$2:$C$1577,'Site Level Financials - ''23 ''24'!X$2:X$1577) -> -26.859614 | M35: =_xlfn.XLOOKUP($C35,'Site Level Financials - ''23 ''24'!$C$2:$C$1577,'Site Level Financials - ''23 ''24'!Y$2:Y$1577) -> -31.103692 | N35: =_xlfn.XLOOKUP($C35,'Site Level Financials - ''23 ''24'!$C$2:$C$1577,'Site Level Financials - ''23 ''24'!Z$2:Z$1577) -> -26.438497 | ... R35: =_xlfn.XLOOKUP($C35,'Site Level Financials - ''23 ''24'!$C$2:$C$1577,'Site Level Financials - ''23 ''24'!AD$2:AD$1577) -> -16.235661 | S35: =S36*S17 -> -17.770784 | T35: =T36*T17 -> -19.799833 | U35: =U36*U17 -> -23.740707 | V35: =V36*V17 -> -32.050713 | W35: =W36*W17 -> -39.547444 | X35: =X36*X17 -> -26.687226 | Y35: =Y36*Y17 -> -29.127822 | Z35: =Z36*Z17 -> -19.589903 | ... AD35: =AD36*AD17 -> -16.819035 | AF35: =_xlfn.XLOOKUP($C35,'Site Level Financials - ''23 ''24'!$C$2:$C$1577,'Site Level Financials - ''23 ''24'!$AF$2:$AF$1577) -> -282.45253 | AG35: =SUM(G35:R35) -> -311.44064 | AH35: =SUM(S35:AD35) -> -279.44984
B36: =G5 -> 1 | C36: =B36&" - "&F36 -> 1 - % of Revenue - Marketing | F36: ="% of Revenue - "&F35 -> % of Revenue - Marketing | G36: =G35/G17 -> -0.052778926 | H36: =H35/H17 -> -0.056790315 | I36: =I35/I17 -> -0.063414319 | J36: =J35/J17 -> -0.079923855 | K36: =K35/K17 -> -0.082976227 | L36: =L35/L17 -> -0.066679039 | M36: =M35/M17 -> -0.072239703 | N36: =N35/N17 -> -0.056659239 | ... R36: =R35/R17 -> -0.071602969 | S36: =_xlfn.XLOOKUP($F36,'Budget Assumption Driver'!$A$33:$A$39,'Budget Assumption Driver'!E$33:E$39)+G36 -> -0.052778926 | T36: =_xlfn.XLOOKUP($F36,'Budget Assumption Driver'!$A$33:$A$39,'Budget Assumption Driver'!F$33:F$39)+H36 -> -0.056790315 | U36: =_xlfn.XLOOKUP($F36,'Budget Assumption Driver'!$A$33:$A$39,'Budget Assumption Driver'!G$33:G$39)+I36 -> -0.063414319 | V36: =_xlfn.XLOOKUP($F36,'Budget Assumption Driver'!$A$33:$A$39,'Budget Assumption Driver'!H$33:H$39)+J36 -> -0.079923855 | W36: =_xlfn.XLOOKUP($F36,'Budget Assumption Driver'!$A$33:$A$39,'Budget Assumption Driver'!I$33:I$39)+K36 -> -0.082976227 | X36: =_xlfn.XLOOKUP($F36,'Budget Assumption Driver'!$A$33:$A$39,'Budget Assumption Driver'!J$33:J$39)+L36 -> -0.066679039 | Y36: =_xlfn.XLOOKUP($F36,'Budget Assumption Driver'!$A$33:$A$39,'Budget Assumption Driver'!K$33:K$39)+M36 -> -0.072239703 | Z36: =_xlfn.XLOOKUP($F36,'Budget Assumption Driver'!$A$33:$A$39,'Budget Assumption Driver'!L$33:L$39)+N36 -> -0.056659239 | ... AD36: =_xlfn.XLOOKUP($F36,'Budget Assumption Driver'!$A$33:$A$39,'Budget Assumption Driver'!P$33:P$39)+R36 -> -0.071602969 | AF36: =_xlfn.XLOOKUP($C36,'Site Level Financials - ''23 ''24'!$C$2:$C$1577,'Site Level Financials - ''23 ''24'!$AF$2:$AF$1577) -> -0.051880045 | AG36: =AG35/AG17 -> -0.063681388 | AH36: =AH35/AH17 -> -0.065135464
B37: =G5 -> 1 | C37: =B37&" - "&F37 -> 1 -
B38: =G5 -> 1 | C38: =B38&" - "&F38 -> 1 - Office Rent | F38: Office Rent | G38: =_xlfn.XLOOKUP($C38,'Site Level Financials - ''23 ''24'!$C$2:$C$1577,'Site Level Financials - ''23 ''24'!S$2:S$1577) -> -31.99104 | H38: =_xlfn.XLOOKUP($C38,'Site Level Financials - ''23 ''24'!$C$2:$C$1577,'Site Level Financials - ''23 ''24'!T$2:T$1577) -> -31.99104 | I38: =_xlfn.XLOOKUP($C38,'Site Level Financials - ''23 ''24'!$C$2:$C$1577,'Site Level Financials - ''23 ''24'!U$2:U$1577) -> -31.99104 | J38: =_xlfn.XLOOKUP($C38,'Site Level Financials - ''23 ''24'!$C$2:$C$1577,'Site Level Financials - ''23 ''24'!V$2:V$1577) -> -31.99104 | K38: =_xlfn.XLOOKUP($C38,'Site Level Financials - ''23 ''24'!$C$2:$C$1577,'Site Level Financials - ''23 ''24'!W$2:W$1577) -> -31.99104 | L38: =_xlfn.XLOOKUP($C38,'Site Level Financials - ''23 ''24'!$C$2:$C$1577,'Site Level Financials - ''23 ''24'!X$2:X$1577) -> -31.99104 | M38: =_xlfn.XLOOKUP($C38,'Site Level Financials - ''23 ''24'!$C$2:$C$1577,'Site Level Financials - ''23 ''24'!Y$2:Y$1577) -> -31.99104 | N38: =_xlfn.XLOOKUP($C38,'Site Level Financials - ''23 ''24'!$C$2:$C$1577,'Site Level Financials - ''23 ''24'!Z$2:Z$1577) -> -31.99104 | ... R38: =_xlfn.XLOOKUP($C38,'Site Level Financials - ''23 ''24'!$C$2:$C$1577,'Site Level Financials - ''23 ''24'!AD$2:AD$1577) -> -32.950771 | S38: =G38*(1+S39) -> -32.950771 | T38: =H38*(1+T39) -> -32.950771 | U38: =I38*(1+U39) -> -32.950771 | V38: =J38*(1+V39) -> -32.950771 | W38: =K38*(1+W39) -> -32.950771 | X38: =L38*(1+X39) -> -32.950771 | Y38: =M38*(1+Y39) -> -32.950771 | Z38: =N38*(1+Z39) -> -32.950771 | ... AD38: =R38*(1+AD39) -> -33.939294 | AF38: =_xlfn.XLOOKUP($C38,'Site Level Financials - ''23 ''24'!$C$2:$C$1577,'Site Level Financials - ''23 ''24'!$AF$2:$AF$1577) -> -375.50857 | AG38: =SUM(G38:R38) -> -386.77167 | AH38: =SUM(S38:AD38) -> -398.37482
B39: =G5 -> 1 | C39: =B39&" - "&F39 -> 1 - % YoY Growth | F39: % YoY Growth | G39: =_xlfn.XLOOKUP($C39,'Site Level Financials - ''23 ''24'!$C$2:$C$1577,'Site Level Financials - ''23 ''24'!S$2:S$1577) -> 0.029994268 | H39: =_xlfn.XLOOKUP($C39,'Site Level Financials - ''23 ''24'!$C$2:$C$1577,'Site Level Financials - ''23 ''24'!T$2:T$1577) -> 0.029994268 | I39: =_xlfn.XLOOKUP($C39,'Site Level Financials - ''23 ''24'!$C$2:$C$1577,'Site Level Financials - ''23 ''24'!U$2:U$1577) -> 0.029994268 | J39: =_xlfn.XLOOKUP($C39,'Site Level Financials - ''23 ''24'!$C$2:$C$1577,'Site Level Financials - ''23 ''24'!V$2:V$1577) -> 0.029994268 | K39: =_xlfn.XLOOKUP($C39,'Site Level Financials - ''23 ''24'!$C$2:$C$1577,'Site Level Financials - ''23 ''24'!W$2:W$1577) -> 0.029994268 | L39: =_xlfn.XLOOKUP($C39,'Site Level Financials - ''23 ''24'!$C$2:$C$1577,'Site Level Financials - ''23 ''24'!X$2:X$1577) -> 0.029994268 | M39: =_xlfn.XLOOKUP($C39,'Site Level Financials - ''23 ''24'!$C$2:$C$1577,'Site Level Financials - ''23 ''24'!Y$2:Y$1577) -> 0.029994268 | N39: =_xlfn.XLOOKUP($C39,'Site Level Financials - ''23 ''24'!$C$2:$C$1577,'Site Level Financials - ''23 ''24'!Z$2:Z$1577) -> 0.029994268 | ... R39: =_xlfn.XLOOKUP($C39,'Site Level Financials - ''23 ''24'!$C$2:$C$1577,'Site Level Financials - ''23 ''24'!AD$2:AD$1577) -> 0.029994268 | S39: =_xlfn.XLOOKUP($F39,'Budget Assumption Driver'!$A$33:$A$39,'Budget Assumption Driver'!E$33:E$39) -> 0.03 | T39: =_xlfn.XLOOKUP($F39,'Budget Assumption Driver'!$A$33:$A$39,'Budget Assumption Driver'!F$33:F$39) -> 0.03 | U39: =_xlfn.XLOOKUP($F39,'Budget Assumption Driver'!$A$33:$A$39,'Budget Assumption Driver'!G$33:G$39) -> 0.03 | V39: =_xlfn.XLOOKUP($F39,'Budget Assumption Driver'!$A$33:$A$39,'Budget Assumption Driver'!H$33:H$39) -> 0.03 | W39: =_xlfn.XLOOKUP($F39,'Budget Assumption Driver'!$A$33:$A$39,'Budget Assumption Driver'!I$33:I$39) -> 0.03 | X39: =_xlfn.XLOOKUP($F39,'Budget Assumption Driver'!$A$33:$A$39,'Budget Assumption Driver'!J$33:J$39) -> 0.03 | Y39: =_xlfn.XLOOKUP($F39,'Budget Assumption Driver'!$A$33:$A$39,'Budget Assumption Driver'!K$33:K$39) -> 0.03 | Z39: =_xlfn.XLOOKUP($F39,'Budget Assumption Driver'!$A$33:$A$39,'Budget Assumption Driver'!L$33:L$39) -> 0.03 | ... AD39: =_xlfn.XLOOKUP($F39,'Budget Assumption Driver'!$A$33:$A$39,'Budget Assumption Driver'!P$33:P$39) -> 0.03 | AG39: =AG38/AF38-1 -> 0.029994268 | AH39: =AH38/AG38-1 -> 0.03
B40: =G5 -> 1 | C40: =B40&" - "&F40 -> 1 -
B41: =G5 -> 1 | C41: =B41&" - "&F41 -> 1 - Office EBITDA | F41: Office EBITDA | G41: =_xlfn.XLOOKUP($C41,'Site Level Financials - ''23 ''24'!$C$2:$C$1577,'Site Level Financials - ''23 ''24'!S$2:S$1577) -> 99.367574 | H41: =_xlfn.XLOOKUP($C41,'Site Level Financials - ''23 ''24'!$C$2:$C$1577,'Site Level Financials - ''23 ''24'!T$2:T$1577) -> 86.782101 | I41: =_xlfn.XLOOKUP($C41,'Site Level Financials - ''23 ''24'!$C$2:$C$1577,'Site Level Financials - ''23 ''24'!U$2:U$1577) -> 68.514154 | J41: =_xlfn.XLOOKUP($C41,'Site Level Financials - ''23 ''24'!$C$2:$C$1577,'Site Level Financials - ''23 ''24'!V$2:V$1577) -> -22.344543 | K41: =_xlfn.XLOOKUP($C41,'Site Level Financials - ''23 ''24'!$C$2:$C$1577,'Site Level Financials - ''23 ''24'!W$2:W$1577) -> -38.706879 | L41: =_xlfn.XLOOKUP($C41,'Site Level Financials - ''23 ''24'!$C$2:$C$1577,'Site Level Financials - ''23 ''24'!X$2:X$1577) -> 48.137652 | M41: =_xlfn.XLOOKUP($C41,'Site Level Financials - ''23 ''24'!$C$2:$C$1577,'Site Level Financials - ''23 ''24'!Y$2:Y$1577) -> 38.729704 | N41: =_xlfn.XLOOKUP($C41,'Site Level Financials - ''23 ''24'!$C$2:$C$1577,'Site Level Financials - ''23 ''24'!Z$2:Z$1577) -> 136.39187 | ... R41: =_xlfn.XLOOKUP($C41,'Site Level Financials - ''23 ''24'!$C$2:$C$1577,'Site Level Financials - ''23 ''24'!AD$2:AD$1577) -> -2.8927806 | S41: =S29+S32+S35+S38 -> 70.757217 | T41: =T29+T32+T35+T38 -> 66.898588 | U41: =U29+U32+U35+U38 -> 51.284647 | V41: =V29+V32+V35+V38 -> -22.841673 | W41: =W29+W32+W35+W38 -> -40.859085 | X41: =X29+X32+X35+X38 -> 46.663647 | Y41: =Y29+Y32+Y35+Y38 -> 33.277419 | Z41: =Z29+Z32+Z35+Z38 -> 91.814445 | ... AD41: =AD29+AD32+AD35+AD38 -> -2.8012712 | AF41: =_xlfn.XLOOKUP($C41,'Site Level Financials - ''23 ''24'!$C$2:$C$1577,'Site Level Financials - ''23 ''24'!$AF$2:$AF$1577) -> 1438.4092 | AG41: =SUM(G41:R41) -> 734.2856 | AH41: =SUM(S41:AD41) -> 507.68611
B42: =G5 -> 1 | C42: =B42&" - "&F42 -> 1 - % of Revenue - Office EBITDA | F42: ="% of Revenue - "&F41 -> % of Revenue - Office EBITDA | G42: =G41/G17 -> 0.23299805 | H42: =H41/H17 -> 0.20925216 | I42: =I41/I17 -> 0.15338406 | J42: =J41/J17 -> -0.058391946 | K42: =K41/K17 -> -0.09563284 | L42: =L41/L17 -> 0.11950181 | M42: =M41/M17 -> 0.089951453 | N42: =N41/N17 -> 0.29229572 | ... AD42: =AD41/AD17 -> -0.011925734 | AF42: =_xlfn.XLOOKUP($C42,'Site Level Financials - ''23 ''24'!$C$2:$C$1577,'Site Level Financials - ''23 ''24'!$AF$2:$AF$1577) -> 0.26420275 | AG42: =AG41/AG17 -> 0.15014202 | AH42: =AH41/AH17 -> 0.11833383
B43: =G5 -> 1 | C43: =B43&" - "&F43 -> 1 -
B44: =G5 -> 1 | C44: =B44&" - "&F44 -> 1 - Memo: | F44: Memo:
B45: =G5 -> 1 | C45: =B45&" - "&F45 -> 1 - Collections | F45: Collections | G45: =_xlfn.XLOOKUP($C45,'Site Level Financials - ''23 ''24'!$C$2:$C$1577,'Site Level Financials - ''23 ''24'!S$2:S$1577) -> 422.94349 | H45: =_xlfn.XLOOKUP($C45,'Site Level Financials - ''23 ''24'!$C$2:$C$1577,'Site Level Financials - ''23 ''24'!T$2:T$1577) -> 407.12303 | I45: =_xlfn.XLOOKUP($C45,'Site Level Financials - ''23 ''24'!$C$2:$C$1577,'Site Level Financials - ''23 ''24'!U$2:U$1577) -> 455.89217 | J45: =_xlfn.XLOOKUP($C45,'Site Level Financials - ''23 ''24'!$C$2:$C$1577,'Site Level Financials - ''23 ''24'!V$2:V$1577) -> 380.45242 | K45: =_xlfn.XLOOKUP($C45,'Site Level Financials - ''23 ''24'!$C$2:$C$1577,'Site Level Financials - ''23 ''24'!W$2:W$1577) -> 403.4762 | L45: =_xlfn.XLOOKUP($C45,'Site Level Financials - ''23 ''24'!$C$2:$C$1577,'Site Level Financials - ''23 ''24'!X$2:X$1577) -> 407.86079 | M45: =_xlfn.XLOOKUP($C45,'Site Level Financials - ''23 ''24'!$C$2:$C$1577,'Site Level Financials - ''23 ''24'!Y$2:Y$1577) -> 437.52424 | N45: =_xlfn.XLOOKUP($C45,'Site Level Financials - ''23 ''24'!$C$2:$C$1577,'Site Level Financials - ''23 ''24'!Z$2:Z$1577) -> 476.14498 | ... R45: =_xlfn.XLOOKUP($C45,'Site Level Financials - ''23 ''24'!$C$2:$C$1577,'Site Level Financials - ''23 ''24'!AD$2:AD$1577) -> 229.09013 | S45: =S46*S15 -> 336.70227 | T45: =T46*T15 -> 348.64807 | U45: =U46*U15 -> 374.37454 | V45: =V46*V15 -> 401.01561 | W45: =W46*W15 -> 476.61174 | X45: =X46*X15 -> 400.23411 | Y45: =Y46*Y15 -> 403.21071 | Z45: =Z46*Z15 -> 345.74949 | ... AD45: =AD46*AD15 -> 234.89298 | AF45: =_xlfn.XLOOKUP($C45,'Site Level Financials - ''23 ''24'!$C$2:$C$1577,'Site Level Financials - ''23 ''24'!$AF$2:$AF$1577) -> 5426.8483 | AG45: =SUM(G45:R45) -> 4909.8357 | AH45: =SUM(S45:AD45) -> 4290.2871
B46: =G5 -> 1 | C46: =B46&" - "&F46 -> 1 - Collections as a % of Production | F46: Collections as a % of Production | G46: =_xlfn.XLOOKUP($C46,'Site Level Financials - ''23 ''24'!$C$2:$C$1577,'Site Level Financials - ''23 ''24'!S$2:S$1577) -> 0.97046263 | H46: =_xlfn.XLOOKUP($C46,'Site Level Financials - ''23 ''24'!$C$2:$C$1577,'Site Level Financials - ''23 ''24'!T$2:T$1577) -> 0.96062597 | I46: =_xlfn.XLOOKUP($C46,'Site Level Financials - ''23 ''24'!$C$2:$C$1577,'Site Level Financials - ''23 ''24'!U$2:U$1577) -> 0.9987365 | J46: =_xlfn.XLOOKUP($C46,'Site Level Financials - ''23 ''24'!$C$2:$C$1577,'Site Level Financials - ''23 ''24'!V$2:V$1577) -> 0.97290558 | K46: =_xlfn.XLOOKUP($C46,'Site Level Financials - ''23 ''24'!$C$2:$C$1577,'Site Level Financials - ''23 ''24'!W$2:W$1577) -> 0.97549644 | L46: =_xlfn.XLOOKUP($C46,'Site Level Financials - ''23 ''24'!$C$2:$C$1577,'Site Level Financials - ''23 ''24'!X$2:X$1577) -> 0.99081003 | M46: =_xlfn.XLOOKUP($C46,'Site Level Financials - ''23 ''24'!$C$2:$C$1577,'Site Level Financials - ''23 ''24'!Y$2:Y$1577) -> 0.99438597 | N46: =_xlfn.XLOOKUP($C46,'Site Level Financials - ''23 ''24'!$C$2:$C$1577,'Site Level Financials - ''23 ''24'!Z$2:Z$1577) -> 0.99853214 | ... R46: =_xlfn.XLOOKUP($C46,'Site Level Financials - ''23 ''24'!$C$2:$C$1577,'Site Level Financials - ''23 ''24'!AD$2:AD$1577) -> 0.98868126 | S46: =S16 -> 0.98241067 | T46: =T16 -> 0.98241067 | U46: =U16 -> 0.98241067 | V46: =V16 -> 0.98241067 | W46: =W16 -> 0.98241067 | X46: =X16 -> 0.98241067 | Y46: =Y16 -> 0.98241067 | Z46: =Z16 -> 0.98241067 | ... AD46: =AD16 -> 0.98241067 | AF46: =_xlfn.XLOOKUP($C46,'Site Level Financials - ''23 ''24'!$C$2:$C$1577,'Site Level Financials - ''23 ''24'!$AF$2:$AF$1577) -> 0.98048296 | AG46: =AG45/AG15 -> 0.98241067 | AH46: =AH45/AH15 -> 0.98241067
B47: =G5 -> 1 | C47: =B47&" - "&F47 -> 1 -
B48: =G5 -> 1 | C48: =B48&" - "&F48 -> 1 - Production per Vet Workday - YoY Change | F48: Production per Vet Workday - YoY Change | G48: =_xlfn.XLOOKUP($C48,'Site Level Financials - ''23 ''24'!$C$2:$C$1577,'Site Level Financials - ''23 ''24'!S$2:S$1577) -> 0.1048857 | H48: =_xlfn.XLOOKUP($C48,'Site Level Financials - ''23 ''24'!$C$2:$C$1577,'Site Level Financials - ''23 ''24'!T$2:T$1577) -> 0.057686835 | I48: =_xlfn.XLOOKUP($C48,'Site Level Financials - ''23 ''24'!$C$2:$C$1577,'Site Level Financials - ''23 ''24'!U$2:U$1577) -> 0.0394149 | J48: =_xlfn.XLOOKUP($C48,'Site Level Financials - ''23 ''24'!$C$2:$C$1577,'Site Level Financials - ''23 ''24'!V$2:V$1577) -> 0.12092957 | K48: =_xlfn.XLOOKUP($C48,'Site Level Financials - ''23 ''24'!$C$2:$C$1577,'Site Level Financials - ''23 ''24'!W$2:W$1577) -> 0.027827241 | L48: =_xlfn.XLOOKUP($C48,'Site Level Financials - ''23 ''24'!$C$2:$C$1577,'Site Level Financials - ''23 ''24'!X$2:X$1577) -> 0.0046910107 | M48: =_xlfn.XLOOKUP($C48,'Site Level Financials - ''23 ''24'!$C$2:$C$1577,'Site Level Financials - ''23 ''24'!Y$2:Y$1577) -> 0.041333111 | N48: =_xlfn.XLOOKUP($C48,'Site Level Financials - ''23 ''24'!$C$2:$C$1577,'Site Level Financials - ''23 ''24'!Z$2:Z$1577) -> -0.0088283455 | ... R48: =_xlfn.XLOOKUP($C48,'Site Level Financials - ''23 ''24'!$C$2:$C$1577,'Site Level Financials - ''23 ''24'!AD$2:AD$1577) -> -0.21148004 | S48: =S14/G14-1 -> -0.21358924 | T48: =T14/H14-1 -> -0.16261951 | U48: =U14/I14-1 -> -0.16516236 | V48: =V14/J14-1 -> -0.21711168 | W48: =W14/K14-1 -> -0.12028763 | X48: =X14/L14-1 -> -0.010309349 | Y48: =Y14/M14-1 -> -0.067192858 | Z48: =Z14/N14-1 -> -0.077425766 | ... AD48: =AD14/R14-1 -> 0.03187452 | AG48: =AG14/AF14-1 -> -0.0051367386 | AH48: =AH14/AG14-1 -> -0.09045301
B52: Site | E52: Happy Pets Vets | AH52: =TODAY() -> 45999
B53: =G55 -> 2 | F53: Site Level Financials | AH53: ($ in 000s)
B55: =G55 -> 2 | F55: Site: | G55: 2
B56: =G55 -> 2 | F56: BlueTail Animal Hospital
B57: =G55 -> 2
B58: =G55 -> 2 | G58: 2024A | S58: 2025 Budget | AF58: Historicals | AH58: Budget
B59: =G55 -> 2 | G59: 44957 | H59: =EOMONTH(G59,1) -> 44985 | I59: =EOMONTH(H59,1) -> 45016 | J59: =EOMONTH(I59,1) -> 45046 | K59: =EOMONTH(J59,1) -> 45077 | L59: =EOMONTH(K59,1) -> 45107 | M59: =EOMONTH(L59,1) -> 45138 | N59: =EOMONTH(M59,1) -> 45169 | O59: =EOMONTH(N59,1) -> 45199 | ... AD59: =EOMONTH(AC59,1) -> 45657 | AF59: 45291 | AG59: 45657 | AH59: 46022
B60: =G55 -> 2
B61: =G55 -> 2 | C61: =B61&" - "&F61 -> 2 - Employed Vets | F61: Employed Vets | G61: =_xlfn.XLOOKUP($C61,'Site Level Financials - ''23 ''24'!$C$2:$C$1577,'Site Level Financials - ''23 ''24'!S$2:S$1577) -> 4 | H61: =_xlfn.XLOOKUP($C61,'Site Level Financials - ''23 ''24'!$C$2:$C$1577,'Site Level Financials - ''23 ''24'!T$2:T$1577) -> 3 | I61: =_xlfn.XLOOKUP($C61,'Site Level Financials - ''23 ''24'!$C$2:$C$1577,'Site Level Financials - ''23 ''24'!U$2:U$1577) -> 3 | J61: =_xlfn.XLOOKUP($C61,'Site Level Financials - ''23 ''24'!$C$2:$C$1577,'Site Level Financials - ''23 ''24'!V$2:V$1577) -> 3 | K61: =_xlfn.XLOOKUP($C61,'Site Level Financials - ''23 ''24'!$C$2:$C$1577,'Site Level Financials - ''23 ''24'!W$2:W$1577) -> 2 | L61: =_xlfn.XLOOKUP($C61,'Site Level Financials - ''23 ''24'!$C$2:$C$1577,'Site Level Financials - ''23 ''24'!X$2:X$1577) -> 2 | M61: =_xlfn.XLOOKUP($C61,'Site Level Financials - ''23 ''24'!$C$2:$C$1577,'Site Level Financials - ''23 ''24'!Y$2:Y$1577) -> 3 | N61: =_xlfn.XLOOKUP($C61,'Site Level Financials - ''23 ''24'!$C$2:$C$1577,'Site Level Financials - ''23 ''24'!Z$2:Z$1577) -> 4 | ... R61: =_xlfn.XLOOKUP($C61,'Site Level Financials - ''23 ''24'!$C$2:$C$1577,'Site Level Financials - ''23 ''24'!AD$2:AD$1577) -> 3 | S61: =R61+_xlfn.XLOOKUP($R61,'Budget Assumption Driver'!$A$7:$A$11,'Budget Assumption Driver'!E$7:E$11) -> 3 | T61: =S61+_xlfn.XLOOKUP($R61,'Budget Assumption Driver'!$A$7:$A$11,'Budget Assumption Driver'!F$7:F$11) -> 3 | U61: =T61+_xlfn.XLOOKUP($R61,'Budget Assumption Driver'!$A$7:$A$11,'Budget Assumption Driver'!G$7:G$11) -> 3 | V61: =U61+_xlfn.XLOOKUP($R61,'Budget Assumption Driver'!$A$7:$A$11,'Budget Assumption Driver'!H$7:H$11) -> 3 | W61: =V61+_xlfn.XLOOKUP($R61,'Budget Assumption Driver'!$A$7:$A$11,'Budget Assumption Driver'!I$7:I$11) -> 3 | X61: =W61+_xlfn.XLOOKUP($R61,'Budget Assumption Driver'!$A$7:$A$11,'Budget Assumption Driver'!J$7:J$11) -> 3 | Y61: =X61+_xlfn.XLOOKUP($R61,'Budget Assumption Driver'!$A$7:$A$11,'Budget Assumption Driver'!K$7:K$11) -> 4 | Z61: =Y61+_xlfn.XLOOKUP($R61,'Budget Assumption Driver'!$A$7:$A$11,'Budget Assumption Driver'!L$7:L$11) -> 4 | ... AD61: =AC61+_xlfn.XLOOKUP($R61,'Budget Assumption Driver'!$A$7:$A$11,'Budget Assumption Driver'!P$7:P$11) -> 4 | AF61: =_xlfn.XLOOKUP($C61,'Site Level Financials - ''23 ''24'!$C$2:$C$1577,'Site Level Financials - ''23 ''24'!$AF$2:$AF$1577) -> 2.1666667 | AG61: =AG63/AG62 -> 3.2527881 | AH61: =AH63/AH62 -> 3.5018587
B62: =G55 -> 2 | C62: =B62&" - "&F62 -> 2 - Workdays in Month / Year | F62: Workdays in Month / Year | G62: =_xlfn.XLOOKUP($C62,'Site Level Financials - ''23 ''24'!$C$2:$C$1577,'Site Level Financials - ''23 ''24'!S$2:S$1577) -> 23 | H62: =_xlfn.XLOOKUP($C62,'Site Level Financials - ''23 ''24'!$C$2:$C$1577,'Site Level Financials - ''23 ''24'!T$2:T$1577) -> 22 | I62: =_xlfn.XLOOKUP($C62,'Site Level Financials - ''23 ''24'!$C$2:$C$1577,'Site Level Financials - ''23 ''24'!U$2:U$1577) -> 22 | J62: =_xlfn.XLOOKUP($C62,'Site Level Financials - ''23 ''24'!$C$2:$C$1577,'Site Level Financials - ''23 ''24'!V$2:V$1577) -> 22 | K62: =_xlfn.XLOOKUP($C62,'Site Level Financials - ''23 ''24'!$C$2:$C$1577,'Site Level Financials - ''23 ''24'!W$2:W$1577) -> 24 | L62: =_xlfn.XLOOKUP($C62,'Site Level Financials - ''23 ''24'!$C$2:$C$1577,'Site Level Financials - ''23 ''24'!X$2:X$1577) -> 21 | M62: =_xlfn.XLOOKUP($C62,'Site Level Financials - ''23 ''24'!$C$2:$C$1577,'Site Level Financials - ''23 ''24'!Y$2:Y$1577) -> 23 | N62: =_xlfn.XLOOKUP($C62,'Site Level Financials - ''23 ''24'!$C$2:$C$1577,'Site Level Financials - ''23 ''24'!Z$2:Z$1577) -> 23 | ... R62: =_xlfn.XLOOKUP($C62,'Site Level Financials - ''23 ''24'!$C$2:$C$1577,'Site Level Financials - ''23 ''24'!AD$2:AD$1577) -> 22 | S62: =NETWORKDAYS(R59,S59) -> 23 | T62: =NETWORKDAYS(S59,T59) -> 22 | U62: =NETWORKDAYS(T59,U59) -> 22 | V62: =NETWORKDAYS(U59,V59) -> 22 | W62: =NETWORKDAYS(V59,W59) -> 24 | X62: =NETWORKDAYS(W59,X59) -> 21 | Y62: =NETWORKDAYS(X59,Y59) -> 23 | Z62: =NETWORKDAYS(Y59,Z59) -> 23 | ... AD62: =NETWORKDAYS(AC59,AD59) -> 22 | AF62: =_xlfn.XLOOKUP($C62,'Site Level Financials - ''23 ''24'!$C$2:$C$1577,'Site Level Financials - ''23 ''24'!$AF$2:$AF$1577) -> 269 | AG62: =SUM(G62:R62) -> 269 | AH62: =SUM(S62:AD62) -> 269
B63: =G55 -> 2 | C63: =B63&" - "&F63 -> 2 - Total Vet Days | F63: Total Vet Days | G63: =_xlfn.XLOOKUP($C63,'Site Level Financials - ''23 ''24'!$C$2:$C$1577,'Site Level Financials - ''23 ''24'!S$2:S$1577) -> 92 | H63: =_xlfn.XLOOKUP($C63,'Site Level Financials - ''23 ''24'!$C$2:$C$1577,'Site Level Financials - ''23 ''24'!T$2:T$1577) -> 66 | I63: =_xlfn.XLOOKUP($C63,'Site Level Financials - ''23 ''24'!$C$2:$C$1577,'Site Level Financials - ''23 ''24'!U$2:U$1577) -> 66 | J63: =_xlfn.XLOOKUP($C63,'Site Level Financials - ''23 ''24'!$C$2:$C$1577,'Site Level Financials - ''23 ''24'!V$2:V$1577) -> 66 | K63: =_xlfn.XLOOKUP($C63,'Site Level Financials - ''23 ''24'!$C$2:$C$1577,'Site Level Financials - ''23 ''24'!W$2:W$1577) -> 48 | L63: =_xlfn.XLOOKUP($C63,'Site Level Financials - ''23 ''24'!$C$2:$C$1577,'Site Level Financials - ''23 ''24'!X$2:X$1577) -> 42 | M63: =_xlfn.XLOOKUP($C63,'Site Level Financials - ''23 ''24'!$C$2:$C$1577,'Site Level Financials - ''23 ''24'!Y$2:Y$1577) -> 69 | N63: =_xlfn.XLOOKUP($C63,'Site Level Financials - ''23 ''24'!$C$2:$C$1577,'Site Level Financials - ''23 ''24'!Z$2:Z$1577) -> 92 | ... R63: =_xlfn.XLOOKUP($C63,'Site Level Financials - ''23 ''24'!$C$2:$C$1577,'Site Level Financials - ''23 ''24'!AD$2:AD$1577) -> 66 | S63: =S61*S62 -> 69 | T63: =T61*T62 -> 66 | U63: =U61*U62 -> 66 | V63: =V61*V62 -> 66 | W63: =W61*W62 -> 72 | X63: =X61*X62 -> 63 | Y63: =Y61*Y62 -> 92 | Z63: =Z61*Z62 -> 92 | ... AD63: =AD61*AD62 -> 88 | AF63: =_xlfn.XLOOKUP($C63,'Site Level Financials - ''23 ''24'!$C$2:$C$1577,'Site Level Financials - ''23 ''24'!$AF$2:$AF$1577) -> 584 | AG63: =SUM(G63:R63) -> 875 | AH63: =SUM(S63:AD63) -> 942
B64: =G55 -> 2 | C64: =B64&" - "&F64 -> 2 - Production per Vet Workday | F64: Production per Vet Workday | G64: =_xlfn.XLOOKUP($C64,'Site Level Financials - ''23 ''24'!$C$2:$C$1577,'Site Level Financials - ''23 ''24'!S$2:S$1577) -> 6.135802 | H64: =_xlfn.XLOOKUP($C64,'Site Level Financials - ''23 ''24'!$C$2:$C$1577,'Site Level Financials - ''23 ''24'!T$2:T$1577) -> 7.0517745 | I64: =_xlfn.XLOOKUP($C64,'Site Level Financials - ''23 ''24'!$C$2:$C$1577,'Site Level Financials - ''23 ''24'!U$2:U$1577) -> 7.5467398 | J64: =_xlfn.XLOOKUP($C64,'Site Level Financials - ''23 ''24'!$C$2:$C$1577,'Site Level Financials - ''23 ''24'!V$2:V$1577) -> 7.7678369 | K64: =_xlfn.XLOOKUP($C64,'Site Level Financials - ''23 ''24'!$C$2:$C$1577,'Site Level Financials - ''23 ''24'!W$2:W$1577) -> 8.6661667 | L64: =_xlfn.XLOOKUP($C64,'Site Level Financials - ''23 ''24'!$C$2:$C$1577,'Site Level Financials - ''23 ''24'!X$2:X$1577) -> 9.4009747 | M64: =_xlfn.XLOOKUP($C64,'Site Level Financials - ''23 ''24'!$C$2:$C$1577,'Site Level Financials - ''23 ''24'!Y$2:Y$1577) -> 7.1963112 | N64: =_xlfn.XLOOKUP($C64,'Site Level Financials - ''23 ''24'!$C$2:$C$1577,'Site Level Financials - ''23 ''24'!Z$2:Z$1577) -> 6.2061327 | ... R64: =_xlfn.XLOOKUP($C64,'Site Level Financials - ''23 ''24'!$C$2:$C$1577,'Site Level Financials - ''23 ''24'!AD$2:AD$1577) -> 4.7969625 | S64: =R64*(1+_xlfn.XLOOKUP($R61,'Budget Assumption Driver'!$A$15:$A$19,'Budget Assumption Driver'!E$15:E$19)) -> 6.7867845 | T64: =S64*(1+_xlfn.XLOOKUP($R61,'Budget Assumption Driver'!$A$15:$A$19,'Budget Assumption Driver'!F$15:F$19)) -> 7.3470066 | U64: =T64*(1+_xlfn.XLOOKUP($R61,'Budget Assumption Driver'!$A$15:$A$19,'Budget Assumption Driver'!G$15:G$19)) -> 7.8891366 | V64: =U64*(1+_xlfn.XLOOKUP($R61,'Budget Assumption Driver'!$A$15:$A$19,'Budget Assumption Driver'!H$15:H$19)) -> 8.4505397 | W64: =V64*(1+_xlfn.XLOOKUP($R61,'Budget Assumption Driver'!$A$15:$A$19,'Budget Assumption Driver'!I$15:I$19)) -> 9.2066014 | X64: =W64*(1+_xlfn.XLOOKUP($R61,'Budget Assumption Driver'!$A$15:$A$19,'Budget Assumption Driver'!J$15:J$19)) -> 8.8356937 | Y64: =X64*(1+_xlfn.XLOOKUP($R61,'Budget Assumption Driver'!$A$15:$A$19,'Budget Assumption Driver'!K$15:K$19)) -> 7.2438014 | Z64: =Y64*(1+_xlfn.XLOOKUP($R61,'Budget Assumption Driver'!$A$15:$A$19,'Budget Assumption Driver'!L$15:L$19)) -> 6.2114933 | ... AD64: =AC64*(1+_xlfn.XLOOKUP($R61,'Budget Assumption Driver'!$A$15:$A$19,'Budget Assumption Driver'!P$15:P$19)) -> 4.4117376 | AF64: =_xlfn.XLOOKUP($C64,'Site Level Financials - ''23 ''24'!$C$2:$C$1577,'Site Level Financials - ''23 ''24'!$AF$2:$AF$1577) -> 7.7292135 | AG64: =AG65/AG63 -> 6.6559772 | AH64: =AH65/AH63 -> 6.8774648
B65: =G55 -> 2 | C65: =B65&" - "&F65 -> 2 - Total Production | F65: Total Production | G65: =_xlfn.XLOOKUP($C65,'Site Level Financials - ''23 ''24'!$C$2:$C$1577,'Site Level Financials - ''23 ''24'!S$2:S$1577) -> 564.49378 | H65: =_xlfn.XLOOKUP($C65,'Site Level Financials - ''23 ''24'!$C$2:$C$1577,'Site Level Financials - ''23 ''24'!T$2:T$1577) -> 465.41712 | I65: =_xlfn.XLOOKUP($C65,'Site Level Financials - ''23 ''24'!$C$2:$C$1577,'Site Level Financials - ''23 ''24'!U$2:U$1577) -> 498.08483 | J65: =_xlfn.XLOOKUP($C65,'Site Level Financials - ''23 ''24'!$C$2:$C$1577,'Site Level Financials - ''23 ''24'!V$2:V$1577) -> 512.67723 | K65: =_xlfn.XLOOKUP($C65,'Site Level Financials - ''23 ''24'!$C$2:$C$1577,'Site Level Financials - ''23 ''24'!W$2:W$1577) -> 415.976 | L65: =_xlfn.XLOOKUP($C65,'Site Level Financials - ''23 ''24'!$C$2:$C$1577,'Site Level Financials - ''23 ''24'!X$2:X$1577) -> 394.84094 | M65: =_xlfn.XLOOKUP($C65,'Site Level Financials - ''23 ''24'!$C$2:$C$1577,'Site Level Financials - ''23 ''24'!Y$2:Y$1577) -> 496.54547 | N65: =_xlfn.XLOOKUP($C65,'Site Level Financials - ''23 ''24'!$C$2:$C$1577,'Site Level Financials - ''23 ''24'!Z$2:Z$1577) -> 570.96421 | ... R65: =_xlfn.XLOOKUP($C65,'Site Level Financials - ''23 ''24'!$C$2:$C$1577,'Site Level Financials - ''23 ''24'!AD$2:AD$1577) -> 316.59952 | S65: =S64*S63 -> 468.28813 | T65: =T64*T63 -> 484.90244 | U65: =U64*U63 -> 520.68301 | V65: =V64*V63 -> 557.73562 | W65: =W64*W63 -> 662.8753 | X65: =X64*X63 -> 556.6487 | Y65: =Y64*Y63 -> 666.42973 | Z65: =Z64*Z63 -> 571.45738 | ... AD65: =AD64*AD63 -> 388.23291 | AF65: =_xlfn.XLOOKUP($C65,'Site Level Financials - ''23 ''24'!$C$2:$C$1577,'Site Level Financials - ''23 ''24'!$AF$2:$AF$1577) -> 4097.426 | AG65: =SUM(G65:R65) -> 5823.98 | AH65: =SUM(S65:AD65) -> 6478.5718
B66: =G55 -> 2 | C66: =B66&" - "&F66 -> 2 - Revenue as a % of Production | F66: Revenue as a % of Production | G66: =_xlfn.XLOOKUP($C66,'Site Level Financials - ''23 ''24'!$C$2:$C$1577,'Site Level Financials - ''23 ''24'!S$2:S$1577) -> 0.98521086 | H66: =_xlfn.XLOOKUP($C66,'Site Level Financials - ''23 ''24'!$C$2:$C$1577,'Site Level Financials - ''23 ''24'!T$2:T$1577) -> 0.98521086 | I66: =_xlfn.XLOOKUP($C66,'Site Level Financials - ''23 ''24'!$C$2:$C$1577,'Site Level Financials - ''23 ''24'!U$2:U$1577) -> 0.98521086 | J66: =_xlfn.XLOOKUP($C66,'Site Level Financials - ''23 ''24'!$C$2:$C$1577,'Site Level Financials - ''23 ''24'!V$2:V$1577) -> 0.98521086 | K66: =_xlfn.XLOOKUP($C66,'Site Level Financials - ''23 ''24'!$C$2:$C$1577,'Site Level Financials - ''23 ''24'!W$2:W$1577) -> 0.98521086 | L66: =_xlfn.XLOOKUP($C66,'Site Level Financials - ''23 ''24'!$C$2:$C$1577,'Site Level Financials - ''23 ''24'!X$2:X$1577) -> 0.98521086 | M66: =_xlfn.XLOOKUP($C66,'Site Level Financials - ''23 ''24'!$C$2:$C$1577,'Site Level Financials - ''23 ''24'!Y$2:Y$1577) -> 0.98521086 | N66: =_xlfn.XLOOKUP($C66,'Site Level Financials - ''23 ''24'!$C$2:$C$1577,'Site Level Financials - ''23 ''24'!Z$2:Z$1577) -> 0.98521086 | ... R66: =_xlfn.XLOOKUP($C66,'Site Level Financials - ''23 ''24'!$C$2:$C$1577,'Site Level Financials - ''23 ''24'!AD$2:AD$1577) -> 0.98521086 | S66: =SUM(G95:R95)/SUM(G65:R65) -> 0.97740173 | T66: =S66 -> 0.97740173 | U66: =T66 -> 0.97740173 | V66: =U66 -> 0.97740173 | W66: =V66 -> 0.97740173 | X66: =W66 -> 0.97740173 | Y66: =X66 -> 0.97740173 | Z66: =Y66 -> 0.97740173 | AA66: =Z66 -> 0.97740173 | ... AD66: =AC66 -> 0.97740173 | AF66: =_xlfn.XLOOKUP($C66,'Site Level Financials - ''23 ''24'!$C$2:$C$1577,'Site Level Financials - ''23 ''24'!$AF$2:$AF$1577) -> 0.98156386 | AG66: =AG67/AG65 -> 0.98521086 | AH66: =AH67/AH65 -> 0.97740173
B67: =G55 -> 2 | C67: =B67&" - "&F67 -> 2 - Total Revenue | F67: Total Revenue | G67: =_xlfn.XLOOKUP($C67,'Site Level Financials - ''23 ''24'!$C$2:$C$1577,'Site Level Financials - ''23 ''24'!S$2:S$1577) -> 556.14541 | H67: =_xlfn.XLOOKUP($C67,'Site Level Financials - ''23 ''24'!$C$2:$C$1577,'Site Level Financials - ''23 ''24'!T$2:T$1577) -> 458.534 | I67: =_xlfn.XLOOKUP($C67,'Site Level Financials - ''23 ''24'!$C$2:$C$1577,'Site Level Financials - ''23 ''24'!U$2:U$1577) -> 490.71858 | J67: =_xlfn.XLOOKUP($C67,'Site Level Financials - ''23 ''24'!$C$2:$C$1577,'Site Level Financials - ''23 ''24'!V$2:V$1577) -> 505.09518 | K67: =_xlfn.XLOOKUP($C67,'Site Level Financials - ''23 ''24'!$C$2:$C$1577,'Site Level Financials - ''23 ''24'!W$2:W$1577) -> 409.82408 | L67: =_xlfn.XLOOKUP($C67,'Site Level Financials - ''23 ''24'!$C$2:$C$1577,'Site Level Financials - ''23 ''24'!X$2:X$1577) -> 389.00158 | M67: =_xlfn.XLOOKUP($C67,'Site Level Financials - ''23 ''24'!$C$2:$C$1577,'Site Level Financials - ''23 ''24'!Y$2:Y$1577) -> 489.20199 | N67: =_xlfn.XLOOKUP($C67,'Site Level Financials - ''23 ''24'!$C$2:$C$1577,'Site Level Financials - ''23 ''24'!Z$2:Z$1577) -> 562.52014 | ... R67: =_xlfn.XLOOKUP($C67,'Site Level Financials - ''23 ''24'!$C$2:$C$1577,'Site Level Financials - ''23 ''24'!AD$2:AD$1577) -> 311.91729 | S67: =S66*S65 -> 457.70563 | T67: =T66*T65 -> 473.94448 | U67: =U66*U65 -> 508.91648 | V67: =V66*V65 -> 545.13176 | W67: =W66*W65 -> 647.89547 | X67: =X66*X65 -> 544.06941 | Y67: =Y66*Y65 -> 651.36957 | Z67: =Z66*Z65 -> 558.54344 | ... AD67: =AD66*AD65 -> 379.45952 | AF67: =_xlfn.XLOOKUP($C67,'Site Level Financials - ''23 ''24'!$C$2:$C$1577,'Site Level Financials - ''23 ''24'!$AF$2:$AF$1577) -> 4021.8852 | AG67: =SUM(G67:R67) -> 5737.8484 | AH67: =SUM(S67:AD67) -> 6332.1673
B68: =G55 -> 2 | C68: =B68&" - "&F68 -> 2 - % YoY Revenue Growth | F68: % YoY Revenue Growth | G68: =_xlfn.XLOOKUP($C68,'Site Level Financials - ''23 ''24'!$C$2:$C$1577,'Site Level Financials - ''23 ''24'!S$2:S$1577) -> 2.7791732 | H68: =_xlfn.XLOOKUP($C68,'Site Level Financials - ''23 ''24'!$C$2:$C$1577,'Site Level Financials - ''23 ''24'!T$2:T$1577) -> 2.02965 | I68: =_xlfn.XLOOKUP($C68,'Site Level Financials - ''23 ''24'!$C$2:$C$1577,'Site Level Financials - ''23 ''24'!U$2:U$1577) -> 1.5184773 | J68: =_xlfn.XLOOKUP($C68,'Site Level Financials - ''23 ''24'!$C$2:$C$1577,'Site Level Financials - ''23 ''24'!V$2:V$1577) -> 1.7544983 | K68: =_xlfn.XLOOKUP($C68,'Site Level Financials - ''23 ''24'!$C$2:$C$1577,'Site Level Financials - ''23 ''24'!W$2:W$1577) -> 0.7667082 | L68: =_xlfn.XLOOKUP($C68,'Site Level Financials - ''23 ''24'!$C$2:$C$1577,'Site Level Financials - ''23 ''24'!X$2:X$1577) -> 0.76699366 | M68: =_xlfn.XLOOKUP($C68,'Site Level Financials - ''23 ''24'!$C$2:$C$1577,'Site Level Financials - ''23 ''24'!Y$2:Y$1577) -> 0.36435827 | N68: =_xlfn.XLOOKUP($C68,'Site Level Financials - ''23 ''24'!$C$2:$C$1577,'Site Level Financials - ''23 ''24'!Z$2:Z$1577) -> 0.096948033 | ... R68: =_xlfn.XLOOKUP($C68,'Site Level Financials - ''23 ''24'!$C$2:$C$1577,'Site Level Financials - ''23 ''24'!AD$2:AD$1577) -> -0.37453887 | S68: =S67/G67-1 -> -0.17700367 | T68: =T67/H67-1 -> 0.033608149 | U68: =U67/I67-1 -> 0.037084182 | V68: =V67/J67-1 -> 0.079265423 | W68: =W67/K67-1 -> 0.58091119 | X68: =X67/L67-1 -> 0.39863032 | Y68: =Y67/M67-1 -> 0.33149411 | Z68: =Z67/N67-1 -> -0.0070694423 | ... AD68: =AD67/R67-1 -> 0.2165389 | AG68: =AG67/AF67-1 -> 0.42665642 | AH68: =AH67/AG67-1 -> 0.10357871
B69: =G55 -> 2 | C69: =B69&" - "&F69 -> 2 -
B70: =G55 -> 2 | C70: =B70&" - "&F70 -> 2 - Doctor Compensation | F70: Doctor Compensation | G70: =_xlfn.XLOOKUP($C70,'Site Level Financials - ''23 ''24'!$C$2:$C$1577,'Site Level Financials - ''23 ''24'!S$2:S$1577) -> -91.87896 | H70: =_xlfn.XLOOKUP($C70,'Site Level Financials - ''23 ''24'!$C$2:$C$1577,'Site Level Financials - ''23 ''24'!T$2:T$1577) -> -120.0723 | I70: =_xlfn.XLOOKUP($C70,'Site Level Financials - ''23 ''24'!$C$2:$C$1577,'Site Level Financials - ''23 ''24'!U$2:U$1577) -> -126.41341 | J70: =_xlfn.XLOOKUP($C70,'Site Level Financials - ''23 ''24'!$C$2:$C$1577,'Site Level Financials - ''23 ''24'!V$2:V$1577) -> -106.40047 | K70: =_xlfn.XLOOKUP($C70,'Site Level Financials - ''23 ''24'!$C$2:$C$1577,'Site Level Financials - ''23 ''24'!W$2:W$1577) -> -126.71038 | L70: =_xlfn.XLOOKUP($C70,'Site Level Financials - ''23 ''24'!$C$2:$C$1577,'Site Level Financials - ''23 ''24'!X$2:X$1577) -> -120.98997 | M70: =_xlfn.XLOOKUP($C70,'Site Level Financials - ''23 ''24'!$C$2:$C$1577,'Site Level Financials - ''23 ''24'!Y$2:Y$1577) -> -132.90038 | N70: =_xlfn.XLOOKUP($C70,'Site Level Financials - ''23 ''24'!$C$2:$C$1577,'Site Level Financials - ''23 ''24'!Z$2:Z$1577) -> -142.61028 | ... R70: =_xlfn.XLOOKUP($C70,'Site Level Financials - ''23 ''24'!$C$2:$C$1577,'Site Level Financials - ''23 ''24'!AD$2:AD$1577) -> -96.371518 | S70: =S71*S67 -> -75.616046 | T70: =T71*T67 -> -124.10771 | U70: =U71*U67 -> -131.10135 | V70: =V71*V67 -> -114.83434 | W70: =W71*W67 -> -200.31786 | X70: =X71*X67 -> -169.22024 | Y70: =Y71*Y67 -> -176.95607 | Z70: =Z71*Z67 -> -141.6021 | ... AD70: =AD71*AD67 -> -117.2397 | AF70: =_xlfn.XLOOKUP($C70,'Site Level Financials - ''23 ''24'!$C$2:$C$1577,'Site Level Financials - ''23 ''24'!$AF$2:$AF$1577) -> -924.91046 | AG70: =SUM(G70:R70) -> -1454.0652 | AH70: =SUM(S70:AD70) -> -1641.8871
B71: =G55 -> 2 | C71: =B71&" - "&F71 -> 2 - % of Revenue - Doctor Compensation | F71: ="% of Revenue - "&F70 -> % of Revenue - Doctor Compensation | G71: =G70/G67 -> -0.16520672 | H71: =H70/H67 -> -0.26186129 | I71: =I70/I67 -> -0.25760877 | J71: =J70/J67 -> -0.21065429 | K71: =K70/K67 -> -0.30918237 | L71: =L70/L67 -> -0.31102693 | M71: =M70/M67 -> -0.27166769 | N71: =N70/N67 -> -0.25352031 | ... R71: =R70/R67 -> -0.30896498 | S71: =_xlfn.XLOOKUP($F71,'Budget Assumption Driver'!$A$33:$A$39,'Budget Assumption Driver'!E$33:E$39)+G71 -> -0.16520672 | T71: =_xlfn.XLOOKUP($F71,'Budget Assumption Driver'!$A$33:$A$39,'Budget Assumption Driver'!F$33:F$39)+H71 -> -0.26186129 | U71: =_xlfn.XLOOKUP($F71,'Budget Assumption Driver'!$A$33:$A$39,'Budget Assumption Driver'!G$33:G$39)+I71 -> -0.25760877 | V71: =_xlfn.XLOOKUP($F71,'Budget Assumption Driver'!$A$33:$A$39,'Budget Assumption Driver'!H$33:H$39)+J71 -> -0.21065429 | W71: =_xlfn.XLOOKUP($F71,'Budget Assumption Driver'!$A$33:$A$39,'Budget Assumption Driver'!I$33:I$39)+K71 -> -0.30918237 | X71: =_xlfn.XLOOKUP($F71,'Budget Assumption Driver'!$A$33:$A$39,'Budget Assumption Driver'!J$33:J$39)+L71 -> -0.31102693 | Y71: =_xlfn.XLOOKUP($F71,'Budget Assumption Driver'!$A$33:$A$39,'Budget Assumption Driver'!K$33:K$39)+M71 -> -0.27166769 | Z71: =_xlfn.XLOOKUP($F71,'Budget Assumption Driver'!$A$33:$A$39,'Budget Assumption Driver'!L$33:L$39)+N71 -> -0.25352031 | ... AD71: =_xlfn.XLOOKUP($F71,'Budget Assumption Driver'!$A$33:$A$39,'Budget Assumption Driver'!P$33:P$39)+R71 -> -0.30896498 | AF71: =_xlfn.XLOOKUP($C71,'Site Level Financials - ''23 ''24'!$C$2:$C$1577,'Site Level Financials - ''23 ''24'!$AF$2:$AF$1577) -> -0.22996938 | AG71: =AG70/AG67 -> -0.25341645 | AH71: =AH70/AH67 -> -0.25929306
B72: =G55 -> 2 | C72: =B72&" - "&F72 -> 2 -
B73: =G55 -> 2 | C73: =B73&" - "&F73 -> 2 - Administrative Staff Compensation | F73: Administrative Staff Compensation | G73: =_xlfn.XLOOKUP($C73,'Site Level Financials - ''23 ''24'!$C$2:$C$1577,'Site Level Financials - ''23 ''24'!S$2:S$1577) -> -55.327628 | H73: =_xlfn.XLOOKUP($C73,'Site Level Financials - ''23 ''24'!$C$2:$C$1577,'Site Level Financials - ''23 ''24'!T$2:T$1577) -> -52.981192 | I73: =_xlfn.XLOOKUP($C73,'Site Level Financials - ''23 ''24'!$C$2:$C$1577,'Site Level Financials - ''23 ''24'!U$2:U$1577) -> -57.16115 | J73: =_xlfn.XLOOKUP($C73,'Site Level Financials - ''23 ''24'!$C$2:$C$1577,'Site Level Financials - ''23 ''24'!V$2:V$1577) -> -61.260981 | K73: =_xlfn.XLOOKUP($C73,'Site Level Financials - ''23 ''24'!$C$2:$C$1577,'Site Level Financials - ''23 ''24'!W$2:W$1577) -> -72.771925 | L73: =_xlfn.XLOOKUP($C73,'Site Level Financials - ''23 ''24'!$C$2:$C$1577,'Site Level Financials - ''23 ''24'!X$2:X$1577) -> -72.025329 | M73: =_xlfn.XLOOKUP($C73,'Site Level Financials - ''23 ''24'!$C$2:$C$1577,'Site Level Financials - ''23 ''24'!Y$2:Y$1577) -> -60.145439 | N73: =_xlfn.XLOOKUP($C73,'Site Level Financials - ''23 ''24'!$C$2:$C$1577,'Site Level Financials - ''23 ''24'!Z$2:Z$1577) -> -49.770814 | ... R73: =_xlfn.XLOOKUP($C73,'Site Level Financials - ''23 ''24'!$C$2:$C$1577,'Site Level Financials - ''23 ''24'!AD$2:AD$1577) -> -50.435624 | S73: =S74*S67 -> -45.534435 | T73: =T74*T67 -> -54.761792 | U73: =U74*U67 -> -59.280924 | V73: =V74*V67 -> -66.116858 | W73: =W74*W67 -> -115.04595 | X73: =X74*X67 -> -100.73681 | Y73: =Y74*Y67 -> -80.083298 | Z73: =Z74*Z67 -> -49.418962 | ... AD73: =AD74*AD67 -> -61.356898 | AF73: =_xlfn.XLOOKUP($C73,'Site Level Financials - ''23 ''24'!$C$2:$C$1577,'Site Level Financials - ''23 ''24'!$AF$2:$AF$1577) -> -430.20319 | AG73: =SUM(G73:R73) -> -712.1592 | AH73: =SUM(S73:AD73) -> -812.828
B74: =G55 -> 2 | C74: =B74&" - "&F74 -> 2 - % of Revenue - Administrative Staff Compensation | F74: ="% of Revenue - "&F73 -> % of Revenue - Administrative Staff Compensation | G74: =G73/G67 -> -0.099484104 | H74: =H73/H67 -> -0.11554474 | I74: =I73/I67 -> -0.11648458 | J74: =J73/J67 -> -0.12128601 | K74: =K73/K67 -> -0.17756869 | L74: =L73/L67 -> -0.18515433 | M74: =M73/M67 -> -0.12294602 | N74: =N73/N67 -> -0.08847828 | ... R74: =R73/R67 -> -0.1616955 | S74: =_xlfn.XLOOKUP($F74,'Budget Assumption Driver'!$A$33:$A$39,'Budget Assumption Driver'!E$33:E$39)+G74 -> -0.099484104 | T74: =_xlfn.XLOOKUP($F74,'Budget Assumption Driver'!$A$33:$A$39,'Budget Assumption Driver'!F$33:F$39)+H74 -> -0.11554474 | U74: =_xlfn.XLOOKUP($F74,'Budget Assumption Driver'!$A$33:$A$39,'Budget Assumption Driver'!G$33:G$39)+I74 -> -0.11648458 | V74: =_xlfn.XLOOKUP($F74,'Budget Assumption Driver'!$A$33:$A$39,'Budget Assumption Driver'!H$33:H$39)+J74 -> -0.12128601 | W74: =_xlfn.XLOOKUP($F74,'Budget Assumption Driver'!$A$33:$A$39,'Budget Assumption Driver'!I$33:I$39)+K74 -> -0.17756869 | X74: =_xlfn.XLOOKUP($F74,'Budget Assumption Driver'!$A$33:$A$39,'Budget Assumption Driver'!J$33:J$39)+L74 -> -0.18515433 | Y74: =_xlfn.XLOOKUP($F74,'Budget Assumption Driver'!$A$33:$A$39,'Budget Assumption Driver'!K$33:K$39)+M74 -> -0.12294602 | Z74: =_xlfn.XLOOKUP($F74,'Budget Assumption Driver'!$A$33:$A$39,'Budget Assumption Driver'!L$33:L$39)+N74 -> -0.08847828 | ... AD74: =_xlfn.XLOOKUP($F74,'Budget Assumption Driver'!$A$33:$A$39,'Budget Assumption Driver'!P$33:P$39)+R74 -> -0.1616955 | AF74: =_xlfn.XLOOKUP($C74,'Site Level Financials - ''23 ''24'!$C$2:$C$1577,'Site Level Financials - ''23 ''24'!$AF$2:$AF$1577) -> -0.10696556 | AG74: =AG73/AG67 -> -0.12411607 | AH74: =AH73/AH67 -> -0.1283649
B75: =G55 -> 2 | C75: =B75&" - "&F75 -> 2 -
B76: =G55 -> 2 | C76: =B76&" - "&F76 -> 2 - Office Supplies | F76: Office Supplies | G76: =_xlfn.XLOOKUP($C76,'Site Level Financials - ''23 ''24'!$C$2:$C$1577,'Site Level Financials - ''23 ''24'!S$2:S$1577) -> -11.896387 | H76: =_xlfn.XLOOKUP($C76,'Site Level Financials - ''23 ''24'!$C$2:$C$1577,'Site Level Financials - ''23 ''24'!T$2:T$1577) -> -12.221992 | I76: =_xlfn.XLOOKUP($C76,'Site Level Financials - ''23 ''24'!$C$2:$C$1577,'Site Level Financials - ''23 ''24'!U$2:U$1577) -> -13.432747 | J76: =_xlfn.XLOOKUP($C76,'Site Level Financials - ''23 ''24'!$C$2:$C$1577,'Site Level Financials - ''23 ''24'!V$2:V$1577) -> -13.623183 | K76: =_xlfn.XLOOKUP($C76,'Site Level Financials - ''23 ''24'!$C$2:$C$1577,'Site Level Financials - ''23 ''24'!W$2:W$1577) -> -16.700416 | L76: =_xlfn.XLOOKUP($C76,'Site Level Financials - ''23 ''24'!$C$2:$C$1577,'Site Level Financials - ''23 ''24'!X$2:X$1577) -> -17.009541 | M76: =_xlfn.XLOOKUP($C76,'Site Level Financials - ''23 ''24'!$C$2:$C$1577,'Site Level Financials - ''23 ''24'!Y$2:Y$1577) -> -14.033907 | N76: =_xlfn.XLOOKUP($C76,'Site Level Financials - ''23 ''24'!$C$2:$C$1577,'Site Level Financials - ''23 ''24'!Z$2:Z$1577) -> -11.282312 | ... R76: =_xlfn.XLOOKUP($C76,'Site Level Financials - ''23 ''24'!$C$2:$C$1577,'Site Level Financials - ''23 ''24'!AD$2:AD$1577) -> -9.0373056 | S76: =S77*S67 -> -9.7906824 | T76: =T77*T67 -> -12.632751 | U76: =U77*U67 -> -13.93089 | V76: =V77*V67 -> -14.70303 | W76: =W77*W67 -> -26.401875 | X76: =X77*X67 -> -23.79006 | Y76: =Y77*Y67 -> -18.686065 | Z76: =Z77*Z67 -> -11.202553 | ... AD76: =AD77*AD67 -> -10.994234 | AF76: =_xlfn.XLOOKUP($C76,'Site Level Financials - ''23 ''24'!$C$2:$C$1577,'Site Level Financials - ''23 ''24'!$AF$2:$AF$1577) -> -142.09966 | AG76: =SUM(G76:R76) -> -153.41885 | AH76: =SUM(S76:AD76) -> -176.37695
B77: =G55 -> 2 | C77: =B77&" - "&F77 -> 2 - % of Revenue - Office Supplies | F77: ="% of Revenue - "&F76 -> % of Revenue - Office Supplies | G77: =G76/G67 -> -0.021390784 | H77: =H76/H67 -> -0.026654495 | I77: =I76/I67 -> -0.027373627 | J77: =J76/J67 -> -0.026971516 | K77: =K76/K67 -> -0.040750208 | L77: =L76/L67 -> -0.043726149 | M77: =M76/M67 -> -0.028687347 | N77: =N76/N67 -> -0.020056726 | ... R77: =R76/R67 -> -0.028973404 | S77: =_xlfn.XLOOKUP($F77,'Budget Assumption Driver'!$A$33:$A$39,'Budget Assumption Driver'!E$33:E$39)+G77 -> -0.021390784 | T77: =_xlfn.XLOOKUP($F77,'Budget Assumption Driver'!$A$33:$A$39,'Budget Assumption Driver'!F$33:F$39)+H77 -> -0.026654495 | U77: =_xlfn.XLOOKUP($F77,'Budget Assumption Driver'!$A$33:$A$39,'Budget Assumption Driver'!G$33:G$39)+I77 -> -0.027373627 | V77: =_xlfn.XLOOKUP($F77,'Budget Assumption Driver'!$A$33:$A$39,'Budget Assumption Driver'!H$33:H$39)+J77 -> -0.026971516 | W77: =_xlfn.XLOOKUP($F77,'Budget Assumption Driver'!$A$33:$A$39,'Budget Assumption Driver'!I$33:I$39)+K77 -> -0.040750208 | X77: =_xlfn.XLOOKUP($F77,'Budget Assumption Driver'!$A$33:$A$39,'Budget Assumption Driver'!J$33:J$39)+L77 -> -0.043726149 | Y77: =_xlfn.XLOOKUP($F77,'Budget Assumption Driver'!$A$33:$A$39,'Budget Assumption Driver'!K$33:K$39)+M77 -> -0.028687347 | Z77: =_xlfn.XLOOKUP($F77,'Budget Assumption Driver'!$A$33:$A$39,'Budget Assumption Driver'!L$33:L$39)+N77 -> -0.020056726 | ... AD77: =_xlfn.XLOOKUP($F77,'Budget Assumption Driver'!$A$33:$A$39,'Budget Assumption Driver'!P$33:P$39)+R77 -> -0.028973404 | AF77: =_xlfn.XLOOKUP($C77,'Site Level Financials - ''23 ''24'!$C$2:$C$1577,'Site Level Financials - ''23 ''24'!$AF$2:$AF$1577) -> -0.035331605 | AG77: =AG76/AG67 -> -0.026738045 | AH77: =AH76/AH67 -> -0.027854121
B78: =G55 -> 2 | C78: =B78&" - "&F78 -> 2 -
B79: =G55 -> 2 | C79: =B79&" - "&F79 -> 2 - Office Gross Profit | F79: Office Gross Profit | G79: =_xlfn.XLOOKUP($C79,'Site Level Financials - ''23 ''24'!$C$2:$C$1577,'Site Level Financials - ''23 ''24'!S$2:S$1577) -> 397.04243 | H79: =_xlfn.XLOOKUP($C79,'Site Level Financials - ''23 ''24'!$C$2:$C$1577,'Site Level Financials - ''23 ''24'!T$2:T$1577) -> 273.25851 | I79: =_xlfn.XLOOKUP($C79,'Site Level Financials - ''23 ''24'!$C$2:$C$1577,'Site Level Financials - ''23 ''24'!U$2:U$1577) -> 293.71127 | J79: =_xlfn.XLOOKUP($C79,'Site Level Financials - ''23 ''24'!$C$2:$C$1577,'Site Level Financials - ''23 ''24'!V$2:V$1577) -> 323.81055 | K79: =_xlfn.XLOOKUP($C79,'Site Level Financials - ''23 ''24'!$C$2:$C$1577,'Site Level Financials - ''23 ''24'!W$2:W$1577) -> 193.64136 | L79: =_xlfn.XLOOKUP($C79,'Site Level Financials - ''23 ''24'!$C$2:$C$1577,'Site Level Financials - ''23 ''24'!X$2:X$1577) -> 178.97674 | M79: =_xlfn.XLOOKUP($C79,'Site Level Financials - ''23 ''24'!$C$2:$C$1577,'Site Level Financials - ''23 ''24'!Y$2:Y$1577) -> 282.12227 | N79: =_xlfn.XLOOKUP($C79,'Site Level Financials - ''23 ''24'!$C$2:$C$1577,'Site Level Financials - ''23 ''24'!Z$2:Z$1577) -> 358.85674 | ... R79: =_xlfn.XLOOKUP($C79,'Site Level Financials - ''23 ''24'!$C$2:$C$1577,'Site Level Financials - ''23 ''24'!AD$2:AD$1577) -> 156.07284 | S79: =S67+S70+S73+S76 -> 326.76446 | T79: =T67+T70+T73+T76 -> 282.44222 | U79: =U67+U70+U73+U76 -> 304.60332 | V79: =V67+V70+V73+V76 -> 349.47753 | W79: =W67+W70+W73+W76 -> 306.12979 | X79: =X67+X70+X73+X76 -> 250.3223 | Y79: =Y67+Y70+Y73+Y76 -> 375.64414 | Z79: =Z67+Z70+Z73+Z76 -> 356.31982 | ... AD79: =AD67+AD70+AD73+AD76 -> 189.86868 | AF79: =_xlfn.XLOOKUP($C79,'Site Level Financials - ''23 ''24'!$C$2:$C$1577,'Site Level Financials - ''23 ''24'!$AF$2:$AF$1577) -> 2524.6719 | AG79: =SUM(G79:R79) -> 3418.2052 | AH79: =SUM(S79:AD79) -> 3701.0753
B80: =G55 -> 2 | C80: =B80&" - "&F80 -> 2 - % of Revenue - Office Gross Profit | F80: ="% of Revenue - "&F79 -> % of Revenue - Office Gross Profit | G80: =G79/G67 -> 0.71391839 | H80: =H79/H67 -> 0.59593947 | I80: =I79/I67 -> 0.59853302 | J80: =J79/J67 -> 0.64108818 | K80: =K79/K67 -> 0.47249873 | L80: =L79/L67 -> 0.46009258 | M80: =M79/M67 -> 0.57669894 | N80: =N79/N67 -> 0.63794469 | ... AD80: =AD79/AD67 -> 0.50036612 | AF80: =_xlfn.XLOOKUP($C80,'Site Level Financials - ''23 ''24'!$C$2:$C$1577,'Site Level Financials - ''23 ''24'!$AF$2:$AF$1577) -> 0.62773346 | AG80: =AG79/AG67 -> 0.59572944 | AH80: =AH79/AH67 -> 0.58448792
B81: =G55 -> 2 | C81: =B81&" - "&F81 -> 2 -
B82: =G55 -> 2 | C82: =B82&" - "&F82 -> 2 - General and Administrative Expense | F82: General and Administrative Expense | G82: =_xlfn.XLOOKUP($C82,'Site Level Financials - ''23 ''24'!$C$2:$C$1577,'Site Level Financials - ''23 ''24'!S$2:S$1577) -> -3.0132316 | H82: =_xlfn.XLOOKUP($C82,'Site Level Financials - ''23 ''24'!$C$2:$C$1577,'Site Level Financials - ''23 ''24'!T$2:T$1577) -> -2.9805501 | I82: =_xlfn.XLOOKUP($C82,'Site Level Financials - ''23 ''24'!$C$2:$C$1577,'Site Level Financials - ''23 ''24'!U$2:U$1577) -> -3.3981807 | J82: =_xlfn.XLOOKUP($C82,'Site Level Financials - ''23 ''24'!$C$2:$C$1577,'Site Level Financials - ''23 ''24'!V$2:V$1577) -> -4.3278925 | K82: =_xlfn.XLOOKUP($C82,'Site Level Financials - ''23 ''24'!$C$2:$C$1577,'Site Level Financials - ''23 ''24'!W$2:W$1577) -> -5.8090935 | L82: =_xlfn.XLOOKUP($C82,'Site Level Financials - ''23 ''24'!$C$2:$C$1577,'Site Level Financials - ''23 ''24'!X$2:X$1577) -> -6.313786 | M82: =_xlfn.XLOOKUP($C82,'Site Level Financials - ''23 ''24'!$C$2:$C$1577,'Site Level Financials - ''23 ''24'!Y$2:Y$1577) -> -5.6733855 | N82: =_xlfn.XLOOKUP($C82,'Site Level Financials - ''23 ''24'!$C$2:$C$1577,'Site Level Financials - ''23 ''24'!Z$2:Z$1577) -> -5.2912867 | ... R82: =_xlfn.XLOOKUP($C82,'Site Level Financials - ''23 ''24'!$C$2:$C$1577,'Site Level Financials - ''23 ''24'!AD$2:AD$1577) -> -3.281692 | S82: =S83*S67 -> -2.4798786 | T82: =T83*T67 -> -3.0807209 | U82: =U83*U67 -> -3.5241995 | V82: =V83*V67 -> -4.6709448 | W82: =W83*W67 -> -9.1836608 | X82: =X83*X67 -> -8.8306526 | Y82: =Y83*Y67 -> -7.5540794 | Z82: =Z83*Z67 -> -5.2538802 | ... AD82: =AD83*AD67 -> -3.992306 | AF82: =_xlfn.XLOOKUP($C82,'Site Level Financials - ''23 ''24'!$C$2:$C$1577,'Site Level Financials - ''23 ''24'!$AF$2:$AF$1577) -> -43.023101 | AG82: =SUM(G82:R82) -> -56.064371 | AH82: =SUM(S82:AD82) -> -64.596559
B83: =G55 -> 2 | C83: =B83&" - "&F83 -> 2 - % of Revenue - General and Administrative Expense | F83: ="% of Revenue - "&F82 -> % of Revenue - General and Administrative Expense | G83: =G82/G67 -> -0.0054180644 | H83: =H82/H67 -> -0.0065001725 | I83: =I82/I67 -> -0.0069249074 | J83: =J82/J67 -> -0.0085684693 | K83: =K82/K67 -> -0.014174603 | L83: =L82/L67 -> -0.016230746 | M83: =M82/M67 -> -0.011597225 | N83: =N82/N67 -> -0.009406395 | ... R83: =R82/R67 -> -0.010521033 | S83: =_xlfn.XLOOKUP($F83,'Budget Assumption Driver'!$A$33:$A$39,'Budget Assumption Driver'!E$33:E$39)+G83 -> -0.0054180644 | T83: =_xlfn.XLOOKUP($F83,'Budget Assumption Driver'!$A$33:$A$39,'Budget Assumption Driver'!F$33:F$39)+H83 -> -0.0065001725 | U83: =_xlfn.XLOOKUP($F83,'Budget Assumption Driver'!$A$33:$A$39,'Budget Assumption Driver'!G$33:G$39)+I83 -> -0.0069249074 | V83: =_xlfn.XLOOKUP($F83,'Budget Assumption Driver'!$A$33:$A$39,'Budget Assumption Driver'!H$33:H$39)+J83 -> -0.0085684693 | W83: =_xlfn.XLOOKUP($F83,'Budget Assumption Driver'!$A$33:$A$39,'Budget Assumption Driver'!I$33:I$39)+K83 -> -0.014174603 | X83: =_xlfn.XLOOKUP($F83,'Budget Assumption Driver'!$A$33:$A$39,'Budget Assumption Driver'!J$33:J$39)+L83 -> -0.016230746 | Y83: =_xlfn.XLOOKUP($F83,'Budget Assumption Driver'!$A$33:$A$39,'Budget Assumption Driver'!K$33:K$39)+M83 -> -0.011597225 | Z83: =_xlfn.XLOOKUP($F83,'Budget Assumption Driver'!$A$33:$A$39,'Budget Assumption Driver'!L$33:L$39)+N83 -> -0.009406395 | ... AD83: =_xlfn.XLOOKUP($F83,'Budget Assumption Driver'!$A$33:$A$39,'Budget Assumption Driver'!P$33:P$39)+R83 -> -0.010521033 | AF83: =_xlfn.XLOOKUP($C83,'Site Level Financials - ''23 ''24'!$C$2:$C$1577,'Site Level Financials - ''23 ''24'!$AF$2:$AF$1577) -> -0.010697247 | AG83: =AG82/AG67 -> -0.0097709746 | AH83: =AH82/AH67 -> -0.010201335
B84: =G55 -> 2 | C84: =B84&" - "&F84 -> 2 -
B85: =G55 -> 2 | C85: =B85&" - "&F85 -> 2 - Marketing | F85: Marketing | G85: =_xlfn.XLOOKUP($C85,'Site Level Financials - ''23 ''24'!$C$2:$C$1577,'Site Level Financials - ''23 ''24'!S$2:S$1577) -> -3.2023968 | H85: =_xlfn.XLOOKUP($C85,'Site Level Financials - ''23 ''24'!$C$2:$C$1577,'Site Level Financials - ''23 ''24'!T$2:T$1577) -> -3.1428719 | I85: =_xlfn.XLOOKUP($C85,'Site Level Financials - ''23 ''24'!$C$2:$C$1577,'Site Level Financials - ''23 ''24'!U$2:U$1577) -> -3.5143259 | J85: =_xlfn.XLOOKUP($C85,'Site Level Financials - ''23 ''24'!$C$2:$C$1577,'Site Level Financials - ''23 ''24'!V$2:V$1577) -> -3.5343478 | K85: =_xlfn.XLOOKUP($C85,'Site Level Financials - ''23 ''24'!$C$2:$C$1577,'Site Level Financials - ''23 ''24'!W$2:W$1577) -> -3.3114646 | L85: =_xlfn.XLOOKUP($C85,'Site Level Financials - ''23 ''24'!$C$2:$C$1577,'Site Level Financials - ''23 ''24'!X$2:X$1577) -> -2.880623 | M85: =_xlfn.XLOOKUP($C85,'Site Level Financials - ''23 ''24'!$C$2:$C$1577,'Site Level Financials - ''23 ''24'!Y$2:Y$1577) -> -2.1294592 | N85: =_xlfn.XLOOKUP($C85,'Site Level Financials - ''23 ''24'!$C$2:$C$1577,'Site Level Financials - ''23 ''24'!Z$2:Z$1577) -> -1.4063004 | ... R85: =_xlfn.XLOOKUP($C85,'Site Level Financials - ''23 ''24'!$C$2:$C$1577,'Site Level Financials - ''23 ''24'!AD$2:AD$1577) -> -1.170836 | S85: =S86*S67 -> -2.6355608 | T85: =T86*T67 -> -3.248498 | U85: =U86*U67 -> -3.6446518 | V85: =V86*V67 -> -3.8144994 | W85: =W86*W67 -> -5.2351315 | X85: =X86*X67 -> -4.0289267 | Y85: =Y86*Y67 -> -2.8353624 | Z85: =Z86*Z67 -> -1.3963586 | ... AD85: =AD86*AD67 -> -1.4243675 | AF85: =_xlfn.XLOOKUP($C85,'Site Level Financials - ''23 ''24'!$C$2:$C$1577,'Site Level Financials - ''23 ''24'!$AF$2:$AF$1577) -> -45.55526 | AG85: =SUM(G85:R85) -> -30.280119 | AH85: =SUM(S85:AD85) -> -34.310313
B86: =G55 -> 2 | C86: =B86&" - "&F86 -> 2 - % of Revenue - Marketing | F86: ="% of Revenue - "&F85 -> % of Revenue - Marketing | G86: =G85/G67 -> -0.0057582005 | H86: =H85/H67 -> -0.0068541741 | I86: =I85/I67 -> -0.0071615912 | J86: =J85/J67 -> -0.0069973897 | K86: =K85/K67 -> -0.0080802101 | L86: =L85/L67 -> -0.0074051704 | M86: =M85/M67 -> -0.0043529243 | N86: =N85/N67 -> -0.0025 | ... R86: =R85/R67 -> -0.0037536746 | S86: =_xlfn.XLOOKUP($F86,'Budget Assumption Driver'!$A$33:$A$39,'Budget Assumption Driver'!E$33:E$39)+G86 -> -0.0057582005 | T86: =_xlfn.XLOOKUP($F86,'Budget Assumption Driver'!$A$33:$A$39,'Budget Assumption Driver'!F$33:F$39)+H86 -> -0.0068541741 | U86: =_xlfn.XLOOKUP($F86,'Budget Assumption Driver'!$A$33:$A$39,'Budget Assumption Driver'!G$33:G$39)+I86 -> -0.0071615912 | V86: =_xlfn.XLOOKUP($F86,'Budget Assumption Driver'!$A$33:$A$39,'Budget Assumption Driver'!H$33:H$39)+J86 -> -0.0069973897 | W86: =_xlfn.XLOOKUP($F86,'Budget Assumption Driver'!$A$33:$A$39,'Budget Assumption Driver'!I$33:I$39)+K86 -> -0.0080802101 | X86: =_xlfn.XLOOKUP($F86,'Budget Assumption Driver'!$A$33:$A$39,'Budget Assumption Driver'!J$33:J$39)+L86 -> -0.0074051704 | Y86: =_xlfn.XLOOKUP($F86,'Budget Assumption Driver'!$A$33:$A$39,'Budget Assumption Driver'!K$33:K$39)+M86 -> -0.0043529243 | Z86: =_xlfn.XLOOKUP($F86,'Budget Assumption Driver'!$A$33:$A$39,'Budget Assumption Driver'!L$33:L$39)+N86 -> -0.0025 | ... AD86: =_xlfn.XLOOKUP($F86,'Budget Assumption Driver'!$A$33:$A$39,'Budget Assumption Driver'!P$33:P$39)+R86 -> -0.0037536746 | AF86: =_xlfn.XLOOKUP($C86,'Site Level Financials - ''23 ''24'!$C$2:$C$1577,'Site Level Financials - ''23 ''24'!$AF$2:$AF$1577) -> -0.011326842 | AG86: =AG85/AG67 -> -0.0052772602 | AH86: =AH85/AH67 -> -0.0054184154
B87: =G55 -> 2 | C87: =B87&" - "&F87 -> 2 -
B88: =G55 -> 2 | C88: =B88&" - "&F88 -> 2 - Office Rent | F88: Office Rent | G88: =_xlfn.XLOOKUP($C88,'Site Level Financials - ''23 ''24'!$C$2:$C$1577,'Site Level Financials - ''23 ''24'!S$2:S$1577) -> -17.208038 | H88: =_xlfn.XLOOKUP($C88,'Site Level Financials - ''23 ''24'!$C$2:$C$1577,'Site Level Financials - ''23 ''24'!T$2:T$1577) -> -17.208038 | I88: =_xlfn.XLOOKUP($C88,'Site Level Financials - ''23 ''24'!$C$2:$C$1577,'Site Level Financials - ''23 ''24'!U$2:U$1577) -> -17.208038 | J88: =_xlfn.XLOOKUP($C88,'Site Level Financials - ''23 ''24'!$C$2:$C$1577,'Site Level Financials - ''23 ''24'!V$2:V$1577) -> -17.208038 | K88: =_xlfn.XLOOKUP($C88,'Site Level Financials - ''23 ''24'!$C$2:$C$1577,'Site Level Financials - ''23 ''24'!W$2:W$1577) -> -17.208038 | L88: =_xlfn.XLOOKUP($C88,'Site Level Financials - ''23 ''24'!$C$2:$C$1577,'Site Level Financials - ''23 ''24'!X$2:X$1577) -> -17.208038 | M88: =_xlfn.XLOOKUP($C88,'Site Level Financials - ''23 ''24'!$C$2:$C$1577,'Site Level Financials - ''23 ''24'!Y$2:Y$1577) -> -17.724279 | N88: =_xlfn.XLOOKUP($C88,'Site Level Financials - ''23 ''24'!$C$2:$C$1577,'Site Level Financials - ''23 ''24'!Z$2:Z$1577) -> -17.724279 | ... R88: =_xlfn.XLOOKUP($C88,'Site Level Financials - ''23 ''24'!$C$2:$C$1577,'Site Level Financials - ''23 ''24'!AD$2:AD$1577) -> -17.724279 | S88: =G88*(1+S89) -> -17.724279 | T88: =H88*(1+T89) -> -17.724279 | U88: =I88*(1+U89) -> -17.724279 | V88: =J88*(1+V89) -> -17.724279 | W88: =K88*(1+W89) -> -17.724279 | X88: =L88*(1+X89) -> -17.724279 | Y88: =M88*(1+Y89) -> -18.256007 | Z88: =N88*(1+Z89) -> -18.256007 | ... AD88: =R88*(1+AD89) -> -18.256007 | AF88: =_xlfn.XLOOKUP($C88,'Site Level Financials - ''23 ''24'!$C$2:$C$1577,'Site Level Financials - ''23 ''24'!$AF$2:$AF$1577) -> -203.48798 | AG88: =SUM(G88:R88) -> -209.5939 | AH88: =SUM(S88:AD88) -> -215.88172
B89: =G55 -> 2 | C89: =B89&" - "&F89 -> 2 - % YoY Growth | F89: % YoY Growth | G89: =_xlfn.XLOOKUP($C89,'Site Level Financials - ''23 ''24'!$C$2:$C$1577,'Site Level Financials - ''23 ''24'!S$2:S$1577) -> 0.030006288 | H89: =_xlfn.XLOOKUP($C89,'Site Level Financials - ''23 ''24'!$C$2:$C$1577,'Site Level Financials - ''23 ''24'!T$2:T$1577) -> 0.030006288 | I89: =_xlfn.XLOOKUP($C89,'Site Level Financials - ''23 ''24'!$C$2:$C$1577,'Site Level Financials - ''23 ''24'!U$2:U$1577) -> 0.030006288 | J89: =_xlfn.XLOOKUP($C89,'Site Level Financials - ''23 ''24'!$C$2:$C$1577,'Site Level Financials - ''23 ''24'!V$2:V$1577) -> 0.030006288 | K89: =_xlfn.XLOOKUP($C89,'Site Level Financials - ''23 ''24'!$C$2:$C$1577,'Site Level Financials - ''23 ''24'!W$2:W$1577) -> 0.030006288 | L89: =_xlfn.XLOOKUP($C89,'Site Level Financials - ''23 ''24'!$C$2:$C$1577,'Site Level Financials - ''23 ''24'!X$2:X$1577) -> 0.030006288 | M89: =_xlfn.XLOOKUP($C89,'Site Level Financials - ''23 ''24'!$C$2:$C$1577,'Site Level Financials - ''23 ''24'!Y$2:Y$1577) -> 0.030006288 | N89: =_xlfn.XLOOKUP($C89,'Site Level Financials - ''23 ''24'!$C$2:$C$1577,'Site Level Financials - ''23 ''24'!Z$2:Z$1577) -> 0.030006288 | ... R89: =_xlfn.XLOOKUP($C89,'Site Level Financials - ''23 ''24'!$C$2:$C$1577,'Site Level Financials - ''23 ''24'!AD$2:AD$1577) -> 0.030006288 | S89: =_xlfn.XLOOKUP($F89,'Budget Assumption Driver'!$A$33:$A$39,'Budget Assumption Driver'!E$33:E$39) -> 0.03 | T89: =_xlfn.XLOOKUP($F89,'Budget Assumption Driver'!$A$33:$A$39,'Budget Assumption Driver'!F$33:F$39) -> 0.03 | U89: =_xlfn.XLOOKUP($F89,'Budget Assumption Driver'!$A$33:$A$39,'Budget Assumption Driver'!G$33:G$39) -> 0.03 | V89: =_xlfn.XLOOKUP($F89,'Budget Assumption Driver'!$A$33:$A$39,'Budget Assumption Driver'!H$33:H$39) -> 0.03 | W89: =_xlfn.XLOOKUP($F89,'Budget Assumption Driver'!$A$33:$A$39,'Budget Assumption Driver'!I$33:I$39) -> 0.03 | X89: =_xlfn.XLOOKUP($F89,'Budget Assumption Driver'!$A$33:$A$39,'Budget Assumption Driver'!J$33:J$39) -> 0.03 | Y89: =_xlfn.XLOOKUP($F89,'Budget Assumption Driver'!$A$33:$A$39,'Budget Assumption Driver'!K$33:K$39) -> 0.03 | Z89: =_xlfn.XLOOKUP($F89,'Budget Assumption Driver'!$A$33:$A$39,'Budget Assumption Driver'!L$33:L$39) -> 0.03 | ... AD89: =_xlfn.XLOOKUP($F89,'Budget Assumption Driver'!$A$33:$A$39,'Budget Assumption Driver'!P$33:P$39) -> 0.03 | AG89: =AG88/AF88-1 -> 0.030006288 | AH89: =AH88/AG88-1 -> 0.03
B90: =G55 -> 2 | C90: =B90&" - "&F90 -> 2 -
B91: =G55 -> 2 | C91: =B91&" - "&F91 -> 2 - Office EBITDA | F91: Office EBITDA | G91: =_xlfn.XLOOKUP($C91,'Site Level Financials - ''23 ''24'!$C$2:$C$1577,'Site Level Financials - ''23 ''24'!S$2:S$1577) -> 373.61877 | H91: =_xlfn.XLOOKUP($C91,'Site Level Financials - ''23 ''24'!$C$2:$C$1577,'Site Level Financials - ''23 ''24'!T$2:T$1577) -> 249.92705 | I91: =_xlfn.XLOOKUP($C91,'Site Level Financials - ''23 ''24'!$C$2:$C$1577,'Site Level Financials - ''23 ''24'!U$2:U$1577) -> 269.59073 | J91: =_xlfn.XLOOKUP($C91,'Site Level Financials - ''23 ''24'!$C$2:$C$1577,'Site Level Financials - ''23 ''24'!V$2:V$1577) -> 298.74027 | K91: =_xlfn.XLOOKUP($C91,'Site Level Financials - ''23 ''24'!$C$2:$C$1577,'Site Level Financials - ''23 ''24'!W$2:W$1577) -> 167.31276 | L91: =_xlfn.XLOOKUP($C91,'Site Level Financials - ''23 ''24'!$C$2:$C$1577,'Site Level Financials - ''23 ''24'!X$2:X$1577) -> 152.5743 | M91: =_xlfn.XLOOKUP($C91,'Site Level Financials - ''23 ''24'!$C$2:$C$1577,'Site Level Financials - ''23 ''24'!Y$2:Y$1577) -> 256.59515 | N91: =_xlfn.XLOOKUP($C91,'Site Level Financials - ''23 ''24'!$C$2:$C$1577,'Site Level Financials - ''23 ''24'!Z$2:Z$1577) -> 334.43487 | ... R91: =_xlfn.XLOOKUP($C91,'Site Level Financials - ''23 ''24'!$C$2:$C$1577,'Site Level Financials - ''23 ''24'!AD$2:AD$1577) -> 133.89604 | S91: =S79+S82+S85+S88 -> 303.92475 | T91: =T79+T82+T85+T88 -> 258.38873 | U91: =U79+U82+U85+U88 -> 279.71019 | V91: =V79+V82+V85+V88 -> 323.26781 | W91: =W79+W82+W85+W88 -> 273.98671 | X91: =X79+X82+X85+X88 -> 219.73844 | Y91: =Y79+Y82+Y85+Y88 -> 346.99869 | Z91: =Z79+Z82+Z85+Z88 -> 331.41357 | ... AD91: =AD79+AD82+AD85+AD88 -> 166.196 | AF91: =_xlfn.XLOOKUP($C91,'Site Level Financials - ''23 ''24'!$C$2:$C$1577,'Site Level Financials - ''23 ''24'!$AF$2:$AF$1577) -> 2232.6056 | AG91: =SUM(G91:R91) -> 3122.2668 | AH91: =SUM(S91:AD91) -> 3386.2867
B92: =G55 -> 2 | C92: =B92&" - "&F92 -> 2 - % of Revenue - Office EBITDA | F92: ="% of Revenue - "&F91 -> % of Revenue - Office EBITDA | G92: =G91/G67 -> 0.67180051 | H92: =H91/H67 -> 0.54505675 | I92: =I91/I67 -> 0.5493795 | J92: =J91/J67 -> 0.59145342 | K92: =K91/K67 -> 0.40825508 | L92: =L91/L67 -> 0.39222025 | M92: =M91/M67 -> 0.52451779 | N92: =N91/N67 -> 0.59452959 | ... AD92: =AD91/AD67 -> 0.43798086 | AF92: =_xlfn.XLOOKUP($C92,'Site Level Financials - ''23 ''24'!$C$2:$C$1577,'Site Level Financials - ''23 ''24'!$AF$2:$AF$1577) -> 0.5551142 | AG92: =AG91/AG67 -> 0.54415289 | AH92: =AH91/AH67 -> 0.53477531
B93: =G55 -> 2 | C93: =B93&" - "&F93 -> 2 -
B94: =G55 -> 2 | C94: =B94&" - "&F94 -> 2 - Memo: | F94: Memo:
